Workbook

Sheet AXIS 3167
A1: Name :- AJAY KUMAR GUPTA
A2: Joint Holder :- -
A3: FLAT NO D-07 ISHWAR PARADISE ASHOKA MARG
A4: NASHIK BEHIND INOX THEATRE
A5: NASHIK-422011
A6: MAHARASHTRA-INDIA
A7: Customer ID :- 837058342
A8: IFSC Code :- UTIB0000115
A9: MICR Code :- 422211002
A10: Nominee Registered :- Y
A11: Registered Mobile No :- XXXXXX4014
A12: Registered Email ID :- g.XXXXay@yahoo.com
A13: PAN :- ACLPG1926E
A14: Statement of Account No - 910010047943167 for the period (From : 01-04-2023 To : 31-12-2023) | D14: =SUBTOTAL(9,D16:D186) -> 2424706.7 | E14: =SUBTOTAL(9,E16:E186) -> 2267777.9 | F14: =F16+D16 -> 188100.16
A15: SRL NO | B15: Tran Date | C15: PARTICULARS | D15: DR | E15: CR | F15: BAL | G15: Account No | I15: TX Date | J15: Particulars | K15: Ref | L15: DR | M15: CR | N15: Balance | O15: Account No
A16: 1 | B16: 45018 | C16: UPI/P2A/345797693295/SACHIN BA/Kotak Mah/Diesal | D16: 3400 | E16: 0 | F16: 184700.16 | G16: AXIS 3167 | H16: =F14-D16+E16-F16 -> 0 | I16: =B16 -> 45018 | J16: =C16 -> UPI/P2A/345797693295/SACHIN BA/Kotak Mah/Diesal | L16: =D16 -> 3400 | M16: =E16 -> 0 | N16: =F16 -> 184700.16 | O16: =G16 -> AXIS 3167
A17: 2 | B17: 45018 | C17: UPI/P2M/345789552921/MANISH HE/Yes Bank /Amle | D17: 230 | E17: 0 | F17: 184470.16 | G17: AXIS 3167 | H17: =F16-D17+E17-F17 -> 0 | I17: =B17 -> 45018 | J17: =C17 -> UPI/P2M/345789552921/MANISH HE/Yes Bank /Amle | L17: =D17 -> 230 | M17: =E17 -> 0 | N17: =F17 -> 184470.16 | O17: =G17 -> AXIS 3167
A18: 3 | B18: 45018 | C18: UPI/P2M/345726651875/SAGAR SWE/Yes Bank /sweets | D18: 416 | E18: 0 | F18: 184054.16 | G18: AXIS 3167 | H18: =F17-D18+E18-F18 -> 0 | I18: =B18 -> 45018 | J18: =C18 -> UPI/P2M/345726651875/SAGAR SWE/Yes Bank /sweets | L18: =D18 -> 416 | M18: =E18 -> 0 | N18: =F18 -> 184054.16 | O18: =G18 -> AXIS 3167
A19: 4 | B19: 45018 | C19: INB/NEFT/AXIR230915974036/Ajay Kum/STATE B/Housin | D19: 100000 | E19: 0 | F19: 84054.16 | G19: AXIS 3167 | H19: =F18-D19+E19-F19 -> 0 | I19: =B19 -> 45018 | J19: =C19 -> INB/NEFT/AXIR230915974036/Ajay Kum/STATE B/Housin | L19: =D19 -> 100000 | M19: =E19 -> 0 | N19: =F19 -> 84054.16 | O19: =G19 -> AXIS 3167
A20: 5 | B20: 45020 | C20: UPI/P2M/346037289751/SHAGUN TR/Yes Bank /Ice cre | D20: 115 | E20: 0 | F20: 83939.16 | G20: AXIS 3167 | H20: =F19-D20+E20-F20 -> 0 | I20: =B20 -> 45020 | J20: =C20 -> UPI/P2M/346037289751/SHAGUN TR/Yes Bank /Ice cre | L20: =D20 -> 115 | M20: =E20 -> 0 | N20: =F20 -> 83939.16 | O20: =G20 -> AXIS 3167
A21: 6 | B21: 45023 | C21: BRN-PYMT-CARD-4111460000883615 | D21: 10917.37 | E21: 0 | F21: 73021.79 | G21: AXIS 3167 | H21: =F20-D21+E21-F21 -> 0 | I21: =B21 -> 45023 | J21: =C21 -> BRN-PYMT-CARD-4111460000883615 | L21: =D21 -> 10917.37 | M21: =E21 -> 0 | N21: =F21 -> 73021.79 | O21: =G21 -> AXIS 3167
A22: 7 | B22: 45034 | C22: UPI/P2A/347498540738/SANGITA R/State Ban/Teeth i | D22: 15000 | E22: 0 | F22: 58021.79 | G22: AXIS 3167 | H22: =F21-D22+E22-F22 -> 0 | I22: =B22 -> 45034 | J22: =C22 -> UPI/P2A/347498540738/SANGITA R/State Ban/Teeth i | L22: =D22 -> 15000 | M22: =E22 -> 0 | N22: =F22 -> 58021.79 | O22: =G22 -> AXIS 3167
A23: 8 | B23: 45034 | C23: ATM-CASH-AXIS/BPRH265601/7630/180423/NASHIK | D23: 20000 | E23: 0 | F23: 38021.79 | G23: AXIS 3167 | H23: =F22-D23+E23-F23 -> 0 | I23: =B23 -> 45034 | J23: =C23 -> ATM-CASH-AXIS/BPRH265601/7630/180423/NASHIK | L23: =D23 -> 20000 | M23: =E23 -> 0 | N23: =F23 -> 38021.79 | O23: =G23 -> AXIS 3167
A24: 9 | B24: 45034 | C24: CASH-AXIS-RVSL/180423/21:04 | D24: 0 | E24: 20000 | F24: 58021.79 | G24: AXIS 3167 | H24: =F23-D24+E24-F24 -> 0 | I24: =B24 -> 45034 | J24: =C24 -> CASH-AXIS-RVSL/180423/21:04 | L24: =D24 -> 0 | M24: =E24 -> 20000 | N24: =F24 -> 58021.79 | O24: =G24 -> AXIS 3167
A25: 10 | B25: 45034 | C25: ATM-CASH-AXIS/BPRH265601/7631/180423/NASHIK | D25: 10000 | E25: 0 | F25: 48021.79 | G25: AXIS 3167 | H25: =F24-D25+E25-F25 -> 0 | I25: =B25 -> 45034 | J25: =C25 -> ATM-CASH-AXIS/BPRH265601/7631/180423/NASHIK | L25: =D25 -> 10000 | M25: =E25 -> 0 | N25: =F25 -> 48021.79 | O25: =G25 -> AXIS 3167
A26: 11 | B26: 45034 | C26: CASH-AXIS-RVSL/180423/21:06 | D26: 0 | E26: 10000 | F26: 58021.79 | G26: AXIS 3167 | H26: =F25-D26+E26-F26 -> 0 | I26: =B26 -> 45034 | J26: =C26 -> CASH-AXIS-RVSL/180423/21:06 | L26: =D26 -> 0 | M26: =E26 -> 10000 | N26: =F26 -> 58021.79 | O26: =G26 -> AXIS 3167
A27: 12 | B27: 45036 | C27: UPI/P2A/311016102687/AMOL DHON/Kotak Mah/Diesal | D27: 3450 | E27: 0 | F27: 54571.79 | G27: AXIS 3167 | H27: =F26-D27+E27-F27 -> 0 | I27: =B27 -> 45036 | J27: =C27 -> UPI/P2A/311016102687/AMOL DHON/Kotak Mah/Diesal | L27: =D27 -> 3450 | M27: =E27 -> 0 | N27: =F27 -> 54571.79 | O27: =G27 -> AXIS 3167
A28: 13 | B28: 45038 | C28: ATM-CASH-AXIS/SPCN11530/8513/220423/SINNAR | D28: 20000 | E28: 0 | F28: 34571.79 | G28: AXIS 3167 | H28: =F27-D28+E28-F28 -> 0 | I28: =B28 -> 45038 | J28: =C28 -> ATM-CASH-AXIS/SPCN11530/8513/220423/SINNAR | L28: =D28 -> 20000 | M28: =E28 -> 0 | N28: =F28 -> 34571.79 | O28: =G28 -> AXIS 3167
... A267: 252 | B267: 45382 | C267: SB:910010047943167:Int.Pd:01-01-2024 to 31-03-2024 | D267: 0 | E267: 1054 | F267: 90615.86 | G267: AXIS 3167 | H267: =F266-D267+E267-F267 -> 0 | I267: =B267 -> 45382 | J267: =C267 -> SB:910010047943167:Int.Pd:01-01-2024 to 31-03-2024 | L267: =D267 -> 0 | M267: =E267 -> 1054 | N267: =F267 -> 90615.86 | O267: =G267 -> AXIS 3167

Sheet BOI 6699
A1: -->
A2: Bank of India
A5: INDUSTRIAL AREA KOTA Branch
A7: Account statement
A9: Name AJAY KUMAR GUPTA
A10: Account No. 662113100016699
A11: Account Type Savings Account
A12: Customer Id 007154451
A13: Statement of Account for the period 01/04/2023 to 31/03/2024
A15: All Amounts in INR
A17: No. | B17: Txn Date | C17: Description | D17: ChequeNo. | E17: Cr/Dr | F17: Amount(INR) | G17: Balance(INR)
A19: 1 | B19: 45043.353 | C19: 662113100016699:SBInt.Pd:01-02-2023 to 26-04-2023 | E19: CR | F19: 55 | G19: 8641 | H19: =G19-F19 -> 8586
A20: 2 | B20: 45043.492 | C20: DORMANT ACCOUNT TRANSFER DEBIT | E20: DR | F20: 8641 | G20: 0
A21: 3 | B21: 45287.778 | C21: 662113100016699 DORMANT ACCOUNT REFUND | E21: CR | F21: 8814 | G21: 8814
A22: 4 | B22: 45288.574 | C22: BY CASH-6621-INDUSTRIAL AREA KOTA | E22: CR | F22: 1000 | G22: 9814
A23: 5 | B23: 45296.76 | C23: NEFT/SBIN424005475251/SBIN/Mr AJAY KUMAR GUPTA | E23: CR | F23: 1000 | G23: 10814
A24: 6 | B24: 45326.624 | C24: 662113100016699:SBInt.Pd:01-11-2023 to 31-01-2024 | E24: CR | F24: 29 | G24: 10843
A25: 7 | B25: 45337.279 | C25: Min Bal Charge+Serv.TAX December23 | E25: DR | F25: 118 | G25: 10725
A26: 8 | B26: 45352.723 | C26: NEFT/SBIN324061157023/SBIN/Mr AJAY KUMAR GUPTA | E26: CR | F26: 5000 | G26: 15725
A28: Any discrepancy in this document of accounts should be notified to the bank within a period of 30 days of receipt
A29: of this statement. It will be treated that the entries/contents of this statement are checked and found correct by
A30: you, if no such complaint is made within the period stated above.
A33: Beware of fictitious offers, messages/SMS about lottery winnings, cheap fund offers, employment offers, scholarship offers, offer of emigration visas, offer of admission to reputed universities abroad and similar such offers from fraudsters either within the country or from abroad.
A35: For any support or clarification please contact Call Centre No.1800 220 229, 1800 103 1906 , 022 40919191.

Sheet HDFC 5930
D1: Account Branch :KOTA - RAJASTHAN
A2: MR. AJAY KUMAR GUPTA | D2: Address :SHOWROOM NO. 13-14
A3: 11 NEW MARKET | D3: MAIN JHALAWAR ROAD
A4: ABHINANDAN NEW MARKET | D4: .
A5: RAWATBHATA | D5: City :KOTA
A6: RAWATBHATTA BAZAR 323307 | D6: State :RAJASTHAN
D7: Phone no. :18002026161
D8: Email :
A9: JOINT HOLDERS : | D9: OD Limit :0 Currency :INR
D10: Cust ID :2600484
A11: Nomination : Registered | D11: Account No :01671000085930 VRM POTENTIAL
A12: Statement From : 01/04/2023 To : 31/12/2023 | D12: A/C Open Date :01/06/2005
D13: Account Status :Regular
D14: RTGS/NEFT IFSC :HDFC0000167 MICR :324240002
D15: =SUM(D17:D861) -> 7665777.6 | E15: =SUM(E17:E861) -> 7690470 | F15: =F17+D17 -> 32408.51
A16: Date | B16: Narration | C16: Value Dt | D16: Withdrawal Amt. | E16: Deposit Amt. | F16: Closing Balance | G16: Account No | I16: TX Date | J16: Particulars | K16: Ref | L16: DR | M16: CR | N16: Balance | O16: Account No
A17: 45019 | B17: NET PI TO HSL SEC A/C 347707-00602340029392 | C17: 45019 | D17: 881.67 | E17: 0 | F17: 31526.84 | G17: HDFC 5930 | I17: =A17 -> 45019 | J17: =B17 -> NET PI TO HSL SEC A/C 347707-00602340029392 | L17: =D17 -> 881.67 | M17: =E17 -> 0 | N17: =F17 -> 31526.84 | O17: =G17 -> HDFC 5930
A18: 45019 | B18: NET PO FROM HSL A/C 347707-00602340029392 | C18: 45019 | D18: 0 | E18: 3799.47 | F18: 35326.31 | G18: HDFC 5930 | H18: =F17-D18+E18-F18 -> 0 | I18: =A18 -> 45019 | J18: =B18 -> NET PO FROM HSL A/C 347707-00602340029392 | L18: =D18 -> 0 | M18: =E18 -> 3799.47 | N18: =F18 -> 35326.31 | O18: =G18 -> HDFC 5930
A19: 45020 | B19: ACH D- TP ACH INVESTOCAFE-1111407380 | C19: 45020 | D19: 1500 | E19: 0 | F19: 33826.31 | G19: HDFC 5930 | H19: =F18-D19+E19-F19 -> 0 | I19: =A19 -> 45020 | J19: =B19 -> ACH D- TP ACH INVESTOCAFE-1111407380 | L19: =D19 -> 1500 | M19: =E19 -> 0 | N19: =F19 -> 33826.31 | O19: =G19 -> HDFC 5930
A20: 45020 | B20: ACH D- TP ACH INVESTOCAFE-1111407381 | C20: 45020 | D20: 2000 | E20: 0 | F20: 31826.31 | G20: HDFC 5930 | H20: =F19-D20+E20-F20 -> 0 | I20: =A20 -> 45020 | J20: =B20 -> ACH D- TP ACH INVESTOCAFE-1111407381 | L20: =D20 -> 2000 | M20: =E20 -> 0 | N20: =F20 -> 31826.31 | O20: =G20 -> HDFC 5930
A21: 45020 | B21: ACH D- TP ACH INVESTOCAFE-1111407382 | C21: 45020 | D21: 2000 | E21: 0 | F21: 29826.31 | G21: HDFC 5930 | H21: =F20-D21+E21-F21 -> 0 | I21: =A21 -> 45020 | J21: =B21 -> ACH D- TP ACH INVESTOCAFE-1111407382 | L21: =D21 -> 2000 | M21: =E21 -> 0 | N21: =F21 -> 29826.31 | O21: =G21 -> HDFC 5930
A22: 45021 | B22: NET PI TO HSL SEC A/C 347707-00602340029392 | C22: 45021 | D22: 591.52 | E22: 0 | F22: 29234.79 | G22: HDFC 5930 | H22: =F21-D22+E22-F22 -> 0 | I22: =A22 -> 45021 | J22: =B22 -> NET PI TO HSL SEC A/C 347707-00602340029392 | L22: =D22 -> 591.52 | M22: =E22 -> 0 | N22: =F22 -> 29234.79 | O22: =G22 -> HDFC 5930
A23: 45021 | B23: NET PI TO HSL SEC A/C 347707-00602340029392 | C23: 45021 | D23: 15603.7 | E23: 0 | F23: 13631.09 | G23: HDFC 5930 | H23: =F22-D23+E23-F23 -> 0 | I23: =A23 -> 45021 | J23: =B23 -> NET PI TO HSL SEC A/C 347707-00602340029392 | L23: =D23 -> 15603.7 | M23: =E23 -> 0 | N23: =F23 -> 13631.09 | O23: =G23 -> HDFC 5930
A24: 45022 | B24: NET PO FROM HSL A/C 347707-00602340029392 | C24: 45022 | D24: 0 | E24: 7926.99 | F24: 21558.08 | G24: HDFC 5930 | H24: =F23-D24+E24-F24 -> 0 | I24: =A24 -> 45022 | J24: =B24 -> NET PO FROM HSL A/C 347707-00602340029392 | L24: =D24 -> 0 | M24: =E24 -> 7926.99 | N24: =F24 -> 21558.08 | O24: =G24 -> HDFC 5930
A25: 45022 | B25: NET PI TO HSL SEC A/C 347707-00602340029392 | C25: 45022 | D25: 288.07 | E25: 0 | F25: 21270.01 | G25: HDFC 5930 | H25: =F24-D25+E25-F25 -> 0 | I25: =A25 -> 45022 | J25: =B25 -> NET PI TO HSL SEC A/C 347707-00602340029392 | L25: =D25 -> 288.07 | M25: =E25 -> 0 | N25: =F25 -> 21270.01 | O25: =G25 -> HDFC 5930
A26: 45022 | B26: NET PO FROM HSL A/C 347707-00602340029392 | C26: 45022 | D26: 0 | E26: 661.41 | F26: 21931.42 | G26: HDFC 5930 | H26: =F25-D26+E26-F26 -> 0 | I26: =A26 -> 45022 | J26: =B26 -> NET PO FROM HSL A/C 347707-00602340029392 | L26: =D26 -> 0 | M26: =E26 -> 661.41 | N26: =F26 -> 21931.42 | O26: =G26 -> HDFC 5930
A27: 45024 | B27: ACH D- TP ACH INVESTOCAFE-1116440799 | C27: 45024 | D27: 2000 | E27: 0 | F27: 19931.42 | G27: HDFC 5930 | H27: =F26-D27+E27-F27 -> 0 | I27: =A27 -> 45024 | J27: =B27 -> ACH D- TP ACH INVESTOCAFE-1116440799 | L27: =D27 -> 2000 | M27: =E27 -> 0 | N27: =F27 -> 19931.42 | O27: =G27 -> HDFC 5930
A28: 45024 | B28: ACH D- TP ACH INVESTOCAFE-1116440800 | C28: 45024 | D28: 2500 | E28: 0 | F28: 17431.42 | G28: HDFC 5930 | H28: =F27-D28+E28-F28 -> 0 | I28: =A28 -> 45024 | J28: =B28 -> ACH D- TP ACH INVESTOCAFE-1116440800 | L28: =D28 -> 2500 | M28: =E28 -> 0 | N28: =F28 -> 17431.42 | O28: =G28 -> HDFC 5930
A29: 45026 | B29: O/MF-HSBC MF -O416 -000000101236 | C29: 45026 | D29: 4000 | E29: 0 | F29: 13431.42 | G29: HDFC 5930 | H29: =F28-D29+E29-F29 -> 0 | I29: =A29 -> 45026 | J29: =B29 -> O/MF-HSBC MF -O416 -000000101236 | L29: =D29 -> 4000 | M29: =E29 -> 0 | N29: =F29 -> 13431.42 | O29: =G29 -> HDFC 5930
... A1094: 45383 | B1094: CREDIT INTEREST CAPITALISED | C1094: 45382 | D1094: 0 | E1094: 538 | F1094: 37929.61 | G1094: HDFC 5930 | H1094: =F1093-D1094+E1094-F1094 -> 0 | I1094: =A1094 -> 45383 | J1094: =B1094 -> CREDIT INTEREST CAPITALISED | L1094: =D1094 -> 0 | M1094: =E1094 -> 538 | N1094: =F1094 -> 37929.61 | O1094: =G1094 -> HDFC 5930

Sheet SBI OD 5441
A1: Account Name : | B1: Mr. AJAY KUMAR GUPTA
A2: Address : | B2: FLAT NO D-07 ISHWAR PARADISE
B3: ASHOKA MARG NASIK ROAD
B4: NASIK-422101
B5: Nashik
A6: Date : | B6: 45304
A7: Account Number : | B7: _00000032718635441
A8: Account Description: | B8: SBI SURAKSHIT HL MAXGN AUG 12
A9: Branch : | B9: SHIVAJI NAGAR, NASIK
A10: Drawing Power : | B10: 1800295
A11: Interest Rate(% p.a.): | B11: 10.5
A12: CIF No. : | B12: _85190853479
A13: IFS (Indian Financial System) Code : | B13: SBIN0011669
A14: MICR (Magnetic Ink Character Recognition) Code : | B14: _422002020
A15: Nomination Registered : | B15: No
A16: Balance on 1 Apr 2023 : | B16: -307107.37
A17: Start Date : | B17: 45017
A18: End Date : | B18: 45291 | E18: =SUM(E20:E87) -> 2665450 | F18: =SUM(F20:F87) -> 2944355 | G18: =G20+E20 -> -307107.37
A19: Txn Date | B19: Value Date | C19: Description | D19: Ref No./Cheque No. | E19: Debit | F19: Credit | G19: Balance | H19: Account No | J19: TX Date | K19: Particulars | L19: Ref | M19: DR | N19: CR | O19: Balance | P19: Account No
A20: 45017 | B20: 45017 | C20: TO TRANSFER-INB Payment towards loan repayment-- | D20: IIB6318597 TRANSFER TO 20010697703 | E20: 25000 | F20: 0 | G20: -332107.37 | H20: SBI 5441 | J20: =A20 -> 45017 | K20: =C20 -> TO TRANSFER-INB Payment towards loan repayment-- | L20: =D20 -> IIB6318597 TRANSFER TO 20010697703 | M20: =E20 -> 25000 | N20: =F20 -> 0 | O20: =G20 -> -332107.37 | P20: =H20 -> SBI 5441
A21: 45018 | B21: 45018 | C21: BY TRANSFER-NEFT*UTIB0000115*AXIR230915974036*AJAY KUMAR GUPTA-- | D21: TRANSFER FROM 3199964044308 | E21: 0 | F21: 100000 | G21: -232107.37 | H21: SBI 5441 | I21: =G20-E21+F21-G21 -> 0 | J21: =A21 -> 45018 | K21: =C21 -> BY TRANSFER-NEFT*UTIB0000115*AXIR230915974036*AJAY KUMAR GUPTA-- | L21: =D21 -> TRANSFER FROM 3199964044308 | M21: =E21 -> 0 | N21: =F21 -> 100000 | O21: =G21 -> -232107.37 | P21: =H21 -> SBI 5441
A22: 45018 | B22: 45018 | C22: DEPOSIT TRANSFER--- | D22: TRANSFER FROM 20010697703 | E22: 0 | F22: 26595 | G22: -205512.37 | H22: SBI 5441 | I22: =G21-E22+F22-G22 -> 0 | J22: =A22 -> 45018 | K22: =C22 -> DEPOSIT TRANSFER--- | L22: =D22 -> TRANSFER FROM 20010697703 | M22: =E22 -> 0 | N22: =F22 -> 26595 | O22: =G22 -> -205512.37 | P22: =H22 -> SBI 5441
A23: 45029 | B23: 45029 | C23: BY TRANSFER-SBILT13042023084220295270-Loan repayment-- | D23: TRANSFER FROM 20010697703 | E23: 0 | F23: 50000 | G23: -155512.37 | H23: SBI 5441 | I23: =G22-E23+F23-G23 -> 0 | J23: =A23 -> 45029 | K23: =C23 -> BY TRANSFER-SBILT13042023084220295270-Loan repayment-- | L23: =D23 -> TRANSFER FROM 20010697703 | M23: =E23 -> 0 | N23: =F23 -> 50000 | O23: =G23 -> -155512.37 | P23: =H23 -> SBI 5441
A24: 45031 | B24: 45031 | C24: BY TRANSFER-INB Payment towards loan repayment-- | D24: IIB6794633 TRANSFER FROM 20010697703 | E24: 0 | F24: 100000 | G24: -55512.37 | H24: SBI 5441 | I24: =G23-E24+F24-G24 -> 0 | J24: =A24 -> 45031 | K24: =C24 -> BY TRANSFER-INB Payment towards loan repayment-- | L24: =D24 -> IIB6794633 TRANSFER FROM 20010697703 | M24: =E24 -> 0 | N24: =F24 -> 100000 | O24: =G24 -> -55512.37 | P24: =H24 -> SBI 5441
A25: 45039 | B25: 45039 | C25: TO TRANSFER-INB Payment towards loan repayment-- | D25: IIB6951402 TRANSFER TO 20010697703 | E25: 35000 | F25: 0 | G25: -90512.37 | H25: SBI 5441 | I25: =G24-E25+F25-G25 -> 0 | J25: =A25 -> 45039 | K25: =C25 -> TO TRANSFER-INB Payment towards loan repayment-- | L25: =D25 -> IIB6951402 TRANSFER TO 20010697703 | M25: =E25 -> 35000 | N25: =F25 -> 0 | O25: =G25 -> -90512.37 | P25: =H25 -> SBI 5441
A26: 45039 | B26: 45039 | C26: BY TRANSFER-INB Payment towards loan repayment-- | D26: IIB6951312 TRANSFER FROM 20010697703 | E26: 0 | F26: 70000 | G26: -20512.37 | H26: SBI 5441 | I26: =G25-E26+F26-G26 -> 0 | J26: =A26 -> 45039 | K26: =C26 -> BY TRANSFER-INB Payment towards loan repayment-- | L26: =D26 -> IIB6951312 TRANSFER FROM 20010697703 | M26: =E26 -> 0 | N26: =F26 -> 70000 | O26: =G26 -> -20512.37 | P26: =H26 -> SBI 5441
A27: 45042 | B27: 45042 | C27: TO TRANSFER-INB Deposit / Investment-- | D27: IIB7031794 TRANSFER TO 20010697703 | E27: 10000 | F27: 0 | G27: -30512.37 | H27: SBI 5441 | I27: =G26-E27+F27-G27 -> 0 | J27: =A27 -> 45042 | K27: =C27 -> TO TRANSFER-INB Deposit / Investment-- | L27: =D27 -> IIB7031794 TRANSFER TO 20010697703 | M27: =E27 -> 10000 | N27: =F27 -> 0 | O27: =G27 -> -30512.37 | P27: =H27 -> SBI 5441
A28: 45046 | B28: 45046 | C28: TO TRANSFER-INB Payment towards loan repayment-- | D28: IIB7146807 TRANSFER TO 20010697703 | E28: 20000 | F28: 0 | G28: -50512.37 | H28: SBI 5441 | I28: =G27-E28+F28-G28 -> 0 | J28: =A28 -> 45046 | K28: =C28 -> TO TRANSFER-INB Payment towards loan repayment-- | L28: =D28 -> IIB7146807 TRANSFER TO 20010697703 | M28: =E28 -> 20000 | N28: =F28 -> 0 | O28: =G28 -> -50512.37 | P28: =H28 -> SBI 5441
A29: 45046 | B29: 45046 | C29: DEBIT INTEREST--- | E29: 1016 | F29: 0 | G29: -51528.37 | H29: SBI 5441 | I29: =G28-E29+F29-G29 -> 0 | J29: =A29 -> 45046 | K29: =C29 -> DEBIT INTEREST--- | L29: =D29 -> 0 | M29: =E29 -> 1016 | N29: =F29 -> 0 | O29: =G29 -> -51528.37 | P29: =H29 -> SBI 5441
A30: 45048 | B30: 45048 | C30: DEPOSIT TRANSFER--- | D30: TRANSFER FROM 20010697703 | E30: 0 | F30: 26595 | G30: -24933.37 | H30: SBI 5441 | I30: =G29-E30+F30-G30 -> 0 | J30: =A30 -> 45048 | K30: =C30 -> DEPOSIT TRANSFER--- | L30: =D30 -> TRANSFER FROM 20010697703 | M30: =E30 -> 0 | N30: =F30 -> 26595 | O30: =G30 -> -24933.37 | P30: =H30 -> SBI 5441
A31: 45077 | B31: 45077 | C31: DEBIT INTEREST--- | E31: 227 | F31: 0 | G31: -25160.37 | H31: SBI 5441 | I31: =G30-E31+F31-G31 -> 0 | J31: =A31 -> 45077 | K31: =C31 -> DEBIT INTEREST--- | L31: =D31 -> 0 | M31: =E31 -> 227 | N31: =F31 -> 0 | O31: =G31 -> -25160.37 | P31: =H31 -> SBI 5441
A32: 45078 | B32: 45078 | C32: TO TRANSFER-INB Deposit / Investment-- | D32: IIB8049885 TRANSFER TO 20010697703 | E32: 30000 | F32: 0 | G32: -55160.37 | H32: SBI 5441 | I32: =G31-E32+F32-G32 -> 0 | J32: =A32 -> 45078 | K32: =C32 -> TO TRANSFER-INB Deposit / Investment-- | L32: =D32 -> IIB8049885 TRANSFER TO 20010697703 | M32: =E32 -> 30000 | N32: =F32 -> 0 | O32: =G32 -> -55160.37 | P32: =H32 -> SBI 5441
A33: 45079 | B33: 45079 | C33: DEPOSIT TRANSFER--- | D33: TRANSFER FROM 20010697703 | E33: 0 | F33: 26595 | G33: -28565.37 | H33: SBI 5441 | I33: =G32-E33+F33-G33 -> 0 | J33: =A33 -> 45079 | K33: =C33 -> DEPOSIT TRANSFER--- | L33: =D33 -> TRANSFER FROM 20010697703 | M33: =E33 -> 0 | N33: =F33 -> 26595 | O33: =G33 -> -28565.37 | P33: =H33 -> SBI 5441
A34: 45082 | B34: 45082 | C34: TO TRANSFER-INB Deposit / Investment-- | D34: IIB8169986 TRANSFER TO 20010697703 | E34: 75000 | F34: 0 | G34: -103565.37 | H34: SBI 5441 | I34: =G33-E34+F34-G34 -> 0 | J34: =A34 -> 45082 | K34: =C34 -> TO TRANSFER-INB Deposit / Investment-- | L34: =D34 -> IIB8169986 TRANSFER TO 20010697703 | M34: =E34 -> 75000 | N34: =F34 -> 0 | O34: =G34 -> -103565.37 | P34: =H34 -> SBI 5441
A35: 45089 | B35: 45089 | C35: TO TRANSFER-INB Deposit / Investment-- | D35: IIB8402515 TRANSFER TO 20010697703 | E35: 10000 | F35: 0 | G35: -113565.37 | H35: SBI 5441 | I35: =G34-E35+F35-G35 -> 0 | J35: =A35 -> 45089 | K35: =C35 -> TO TRANSFER-INB Deposit / Investment-- | L35: =D35 -> IIB8402515 TRANSFER TO 20010697703 | M35: =E35 -> 10000 | N35: =F35 -> 0 | O35: =G35 -> -113565.37 | P35: =H35 -> SBI 5441
A36: 45092 | B36: 45092 | C36: TO TRANSFER-INB Deposit / Investment-- | D36: IIB8464838 TRANSFER TO 20010697703 | E36: 75000 | F36: 0 | G36: -188565.37 | H36: SBI 5441 | I36: =G35-E36+F36-G36 -> 0 | J36: =A36 -> 45092 | K36: =C36 -> TO TRANSFER-INB Deposit / Investment-- | L36: =D36 -> IIB8464838 TRANSFER TO 20010697703 | M36: =E36 -> 75000 | N36: =F36 -> 0 | O36: =G36 -> -188565.37 | P36: =H36 -> SBI 5441
A37: 45102 | B37: 45102 | C37: BY TRANSFER-INB Payment towards loan repayment-- | D37: IIB8695782 TRANSFER FROM 20010697703 | E37: 0 | F37: 40000 | G37: -148565.37 | H37: SBI 5441 | I37: =G36-E37+F37-G37 -> 0 | J37: =A37 -> 45102 | K37: =C37 -> BY TRANSFER-INB Payment towards loan repayment-- | L37: =D37 -> IIB8695782 TRANSFER FROM 20010697703 | M37: =E37 -> 0 | N37: =F37 -> 40000 | O37: =G37 -> -148565.37 | P37: =H37 -> SBI 5441
A38: 45107 | B38: 45107 | C38: DEBIT INTEREST--- | E38: 1130 | F38: 0 | G38: -149695.37 | H38: SBI 5441 | I38: =G37-E38+F38-G38 -> 0 | J38: =A38 -> 45107 | K38: =C38 -> DEBIT INTEREST--- | L38: =D38 -> 0 | M38: =E38 -> 1130 | N38: =F38 -> 0 | O38: =G38 -> -149695.37 | P38: =H38 -> SBI 5441
A39: 45109 | B39: 45109 | C39: DEPOSIT TRANSFER--- | D39: TRANSFER FROM 20010697703 | E39: 0 | F39: 26595 | G39: -123100.37 | H39: SBI 5441 | I39: =G38-E39+F39-G39 -> 0 | J39: =A39 -> 45109 | K39: =C39 -> DEPOSIT TRANSFER--- | L39: =D39 -> TRANSFER FROM 20010697703 | M39: =E39 -> 0 | N39: =F39 -> 26595 | O39: =G39 -> -123100.37 | P39: =H39 -> SBI 5441
A40: 45117 | B40: 45117 | C40: TO TRANSFER-INB NEFT UTR NO: SBIN123191905507--AJAY KUMAR GUPTA | D40: NEFT INB: IRW5728101 / AJAY KUMAR GUPTA | E40: 100000 | F40: 0 | G40: -223100.37 | H40: SBI 5441 | I40: =G39-E40+F40-G40 -> 0 | J40: =A40 -> 45117 | K40: =C40 -> TO TRANSFER-INB NEFT UTR NO: SBIN123191905507--AJAY KUMAR GUPTA | L40: =D40 -> NEFT INB: IRW5728101 / AJAY KUMAR GUPTA | M40: =E40 -> 100000 | N40: =F40 -> 0 | O40: =G40 -> -223100.37 | P40: =H40 -> SBI 5441
A41: 45122 | B41: 45122 | C41: TO TRANSFER-INB Credit card payment-- | D41: IIB9347211 TRANSFER TO 20010697703 | E41: 50000 | F41: 0 | G41: -273100.37 | H41: SBI 5441 | I41: =G40-E41+F41-G41 -> 0 | J41: =A41 -> 45122 | K41: =C41 -> TO TRANSFER-INB Credit card payment-- | L41: =D41 -> IIB9347211 TRANSFER TO 20010697703 | M41: =E41 -> 50000 | N41: =F41 -> 0 | O41: =G41 -> -273100.37 | P41: =H41 -> SBI 5441
A42: 45138 | B42: 45138 | C42: DEBIT INTEREST--- | E42: 1955 | F42: 0 | G42: -275055.37 | H42: SBI 5441 | I42: =G41-E42+F42-G42 -> 0 | J42: =A42 -> 45138 | K42: =C42 -> DEBIT INTEREST--- | L42: =D42 -> 0 | M42: =E42 -> 1955 | N42: =F42 -> 0 | O42: =G42 -> -275055.37 | P42: =H42 -> SBI 5441
A43: 45139 | B43: 45139 | C43: TO TRANSFER-INB Deposit / Investment-- | D43: IIB9788460 TRANSFER TO 20010697703 | E43: 200000 | F43: 0 | G43: -475055.37 | H43: SBI 5441 | I43: =G42-E43+F43-G43 -> 0 | J43: =A43 -> 45139 | K43: =C43 -> TO TRANSFER-INB Deposit / Investment-- | L43: =D43 -> IIB9788460 TRANSFER TO 20010697703 | M43: =E43 -> 200000 | N43: =F43 -> 0 | O43: =G43 -> -475055.37 | P43: =H43 -> SBI 5441
A44: 45139 | B44: 45139 | C44: TO TRANSFER-INB NEFT UTR NO: SBIN123213282053--Sunita Gupta | D44: NEFT INB: IRW7078841 / Sunita Gupta | E44: 150000 | F44: 0 | G44: -625055.37 | H44: SBI 5441 | I44: =G43-E44+F44-G44 -> 0 | J44: =A44 -> 45139 | K44: =C44 -> TO TRANSFER-INB NEFT UTR NO: SBIN123213282053--Sunita Gupta | L44: =D44 -> NEFT INB: IRW7078841 / Sunita Gupta | M44: =E44 -> 150000 | N44: =F44 -> 0 | O44: =G44 -> -625055.37 | P44: =H44 -> SBI 5441
A45: 45139 | B45: 45139 | C45: TO TRANSFER-INB NEFT UTR NO: SBIN123213306776--Ajay Kumar Gupta | D45: NEFT INB: IRW7080126 / Ajay Kumar Gupta | E45: 150000 | F45: 0 | G45: -775055.37 | H45: SBI 5441 | I45: =G44-E45+F45-G45 -> 0 | J45: =A45 -> 45139 | K45: =C45 -> TO TRANSFER-INB NEFT UTR NO: SBIN123213306776--Ajay Kumar Gupta | L45: =D45 -> NEFT INB: IRW7080126 / Ajay Kumar Gupta | M45: =E45 -> 150000 | N45: =F45 -> 0 | O45: =G45 -> -775055.37 | P45: =H45 -> SBI 5441
A46: 45140 | B46: 45140 | C46: DEPOSIT TRANSFER--- | D46: TRANSFER FROM 20010697703 | E46: 0 | F46: 26595 | G46: -748460.37 | H46: SBI 5441 | I46: =G45-E46+F46-G46 -> 0 | J46: =A46 -> 45140 | K46: =C46 -> DEPOSIT TRANSFER--- | L46: =D46 -> TRANSFER FROM 20010697703 | M46: =E46 -> 0 | N46: =F46 -> 26595 | O46: =G46 -> -748460.37 | P46: =H46 -> SBI 5441
A47: 45140 | B47: 45140 | C47: TO TRANSFER-INB NEFT UTR NO: SBIN323214823530--Ajay Kumar Gupta | D47: NEFT INB: IRW7212363 / Ajay Kumar Gupta | E47: 100000 | F47: 0 | G47: -848460.37 | H47: SBI 5441 | I47: =G46-E47+F47-G47 -> 0 | J47: =A47 -> 45140 | K47: =C47 -> TO TRANSFER-INB NEFT UTR NO: SBIN323214823530--Ajay Kumar Gupta | L47: =D47 -> NEFT INB: IRW7212363 / Ajay Kumar Gupta | M47: =E47 -> 100000 | N47: =F47 -> 0 | O47: =G47 -> -848460.37 | P47: =H47 -> SBI 5441
A48: 45141 | B48: 45141 | C48: TO TRANSFER-INB NEFT UTR NO: SBIN423215673440--Ajay Kumar Gupta | D48: NEFT INB: IRW7293534 / Ajay Kumar Gupta | E48: 100000 | F48: 0 | G48: -948460.37 | H48: SBI 5441 | I48: =G47-E48+F48-G48 -> 0 | J48: =A48 -> 45141 | K48: =C48 -> TO TRANSFER-INB NEFT UTR NO: SBIN423215673440--Ajay Kumar Gupta | L48: =D48 -> NEFT INB: IRW7293534 / Ajay Kumar Gupta | M48: =E48 -> 100000 | N48: =F48 -> 0 | O48: =G48 -> -948460.37 | P48: =H48 -> SBI 5441
A49: 45143 | B49: 45143 | C49: TO TRANSFER-INB NEFT UTR NO: SBIN223217438050--Ajay Kumar Gupta | D49: NEFT INB: IRW7472424 / Ajay Kumar Gupta | E49: 100000 | F49: 0 | G49: -1048460.4 | H49: SBI 5441 | I49: =G48-E49+F49-G49 -> 0 | J49: =A49 -> 45143 | K49: =C49 -> TO TRANSFER-INB NEFT UTR NO: SBIN223217438050--Ajay Kumar Gupta | L49: =D49 -> NEFT INB: IRW7472424 / Ajay Kumar Gupta | M49: =E49 -> 100000 | N49: =F49 -> 0 | O49: =G49 -> -1048460.4 | P49: =H49 -> SBI 5441
A50: 45145 | B50: 45145 | C50: TO TRANSFER-INB NEFT UTR NO: SBIN423219506319--Ajay Kumar Gupta | D50: NEFT INB: IRW7614691 / Ajay Kumar Gupta | E50: 100000 | F50: 0 | G50: -1148460.4 | H50: SBI 5441 | I50: =G49-E50+F50-G50 -> 0 | J50: =A50 -> 45145 | K50: =C50 -> TO TRANSFER-INB NEFT UTR NO: SBIN423219506319--Ajay Kumar Gupta | L50: =D50 -> NEFT INB: IRW7614691 / Ajay Kumar Gupta | M50: =E50 -> 100000 | N50: =F50 -> 0 | O50: =G50 -> -1148460.4 | P50: =H50 -> SBI 5441
A51: 45156 | B51: 45156 | C51: TO TRANSFER-INB NEFT UTR NO: SBIN423230587703--Ajay Kumar Gupta | D51: NEFT INB: IRW8240391 / Ajay Kumar Gupta | E51: 100000 | F51: 0 | G51: -1248460.4 | H51: SBI 5441 | I51: =G50-E51+F51-G51 -> 0 | J51: =A51 -> 45156 | K51: =C51 -> TO TRANSFER-INB NEFT UTR NO: SBIN423230587703--Ajay Kumar Gupta | L51: =D51 -> NEFT INB: IRW8240391 / Ajay Kumar Gupta | M51: =E51 -> 100000 | N51: =F51 -> 0 | O51: =G51 -> -1248460.4 | P51: =H51 -> SBI 5441
A52: 45157 | B52: 45157 | C52: TO TRANSFER-INB NEFT UTR NO: SBIN523231563697--Ajay Kumar Gupta | D52: NEFT INB: IRW8298482 / Ajay Kumar Gupta | E52: 50000 | F52: 0 | G52: -1298460.4 | H52: SBI 5441 | I52: =G51-E52+F52-G52 -> 0 | J52: =A52 -> 45157 | K52: =C52 -> TO TRANSFER-INB NEFT UTR NO: SBIN523231563697--Ajay Kumar Gupta | L52: =D52 -> NEFT INB: IRW8298482 / Ajay Kumar Gupta | M52: =E52 -> 50000 | N52: =F52 -> 0 | O52: =G52 -> -1298460.4 | P52: =H52 -> SBI 5441
A53: 45162 | B53: 45162 | C53: BY TRANSFER-NEFT*UTIB0000115*AXOIR32366073380*AJAY KUMAR GUPTA-- | D53: TRANSFER FROM 4697176044305 | E53: 0 | F53: 500000 | G53: -798460.37 | H53: SBI 5441 | I53: =G52-E53+F53-G53 -> 0 | J53: =A53 -> 45162 | K53: =C53 -> BY TRANSFER-NEFT*UTIB0000115*AXOIR32366073380*AJAY KUMAR GUPTA-- | L53: =D53 -> TRANSFER FROM 4697176044305 | M53: =E53 -> 0 | N53: =F53 -> 500000 | O53: =G53 -> -798460.37 | P53: =H53 -> SBI 5441
A54: 45163 | B54: 45163 | C54: TO TRANSFER-INB Deposit / Investment-- | D54: IIC0426902 TRANSFER TO 20010697703 | E54: 10000 | F54: 0 | G54: -808460.37 | H54: SBI 5441 | I54: =G53-E54+F54-G54 -> 0 | J54: =A54 -> 45163 | K54: =C54 -> TO TRANSFER-INB Deposit / Investment-- | L54: =D54 -> IIC0426902 TRANSFER TO 20010697703 | M54: =E54 -> 10000 | N54: =F54 -> 0 | O54: =G54 -> -808460.37 | P54: =H54 -> SBI 5441
A55: 45169 | B55: 45169 | C55: DEBIT INTEREST--- | E55: 9201 | F55: 0 | G55: -817661.37 | H55: SBI 5441 | I55: =G54-E55+F55-G55 -> 0 | J55: =A55 -> 45169 | K55: =C55 -> DEBIT INTEREST--- | L55: =D55 -> 0 | M55: =E55 -> 9201 | N55: =F55 -> 0 | O55: =G55 -> -817661.37 | P55: =H55 -> SBI 5441
A56: 45170 | B56: 45170 | C56: BY TRANSFER-INB Payment towards loan repayment-- | D56: IIC0639835 TRANSFER FROM 20010697703 | E56: 0 | F56: 200000 | G56: -617661.37 | H56: SBI 5441 | I56: =G55-E56+F56-G56 -> 0 | J56: =A56 -> 45170 | K56: =C56 -> BY TRANSFER-INB Payment towards loan repayment-- | L56: =D56 -> IIC0639835 TRANSFER FROM 20010697703 | M56: =E56 -> 0 | N56: =F56 -> 200000 | O56: =G56 -> -617661.37 | P56: =H56 -> SBI 5441
A57: 45171 | B57: 45171 | C57: DEPOSIT TRANSFER--- | D57: TRANSFER FROM 20010697703 | E57: 0 | F57: 26595 | G57: -591066.37 | H57: SBI 5441 | I57: =G56-E57+F57-G57 -> 0 | J57: =A57 -> 45171 | K57: =C57 -> DEPOSIT TRANSFER--- | L57: =D57 -> TRANSFER FROM 20010697703 | M57: =E57 -> 0 | N57: =F57 -> 26595 | O57: =G57 -> -591066.37 | P57: =H57 -> SBI 5441
A58: 45178 | B58: 45178 | C58: BY TRANSFER-INB Payment towards loan repayment-- | D58: IIC0918892 TRANSFER FROM 20010697703 | E58: 0 | F58: 150000 | G58: -441066.37 | H58: SBI 5441 | I58: =G57-E58+F58-G58 -> 0 | J58: =A58 -> 45178 | K58: =C58 -> BY TRANSFER-INB Payment towards loan repayment-- | L58: =D58 -> IIC0918892 TRANSFER FROM 20010697703 | M58: =E58 -> 0 | N58: =F58 -> 150000 | O58: =G58 -> -441066.37 | P58: =H58 -> SBI 5441
A59: 45181 | B59: 45181 | C59: TO TRANSFER-INB Deposit / Investment-- | D59: IIC0994290 TRANSFER TO 20010697703 | E59: 1000 | F59: 0 | G59: -442066.37 | H59: SBI 5441 | I59: =G58-E59+F59-G59 -> 0 | J59: =A59 -> 45181 | K59: =C59 -> TO TRANSFER-INB Deposit / Investment-- | L59: =D59 -> IIC0994290 TRANSFER TO 20010697703 | M59: =E59 -> 1000 | N59: =F59 -> 0 | O59: =G59 -> -442066.37 | P59: =H59 -> SBI 5441
A60: 45181 | B60: 45181 | C60: TO TRANSFER-INB Deposit / Investment-- | D60: IIC0994300 TRANSFER TO 20010697703 | E60: 10000 | F60: 0 | G60: -452066.37 | H60: SBI 5441 | I60: =G59-E60+F60-G60 -> 0 | J60: =A60 -> 45181 | K60: =C60 -> TO TRANSFER-INB Deposit / Investment-- | L60: =D60 -> IIC0994300 TRANSFER TO 20010697703 | M60: =E60 -> 10000 | N60: =F60 -> 0 | O60: =G60 -> -452066.37 | P60: =H60 -> SBI 5441
A61: 45181 | B61: 45181 | C61: TO TRANSFER-INB Deposit / Investment-- | D61: IIC0999297 TRANSFER TO 20010697703 | E61: 75000 | F61: 0 | G61: -527066.37 | H61: SBI 5441 | I61: =G60-E61+F61-G61 -> 0 | J61: =A61 -> 45181 | K61: =C61 -> TO TRANSFER-INB Deposit / Investment-- | L61: =D61 -> IIC0999297 TRANSFER TO 20010697703 | M61: =E61 -> 75000 | N61: =F61 -> 0 | O61: =G61 -> -527066.37 | P61: =H61 -> SBI 5441
A62: 45181 | B62: 45181 | C62: BY TRANSFER-NEFT*HDFC0000001*N255232639871634*AJAY KUMAR GUPTA-- | D62: TRANSFER FROM 4697201044308 | E62: 0 | F62: 500000 | G62: -27066.37 | H62: SBI 5441 | I62: =G61-E62+F62-G62 -> 0 | J62: =A62 -> 45181 | K62: =C62 -> BY TRANSFER-NEFT*HDFC0000001*N255232639871634*AJAY KUMAR GUPTA-- | L62: =D62 -> TRANSFER FROM 4697201044308 | M62: =E62 -> 0 | N62: =F62 -> 500000 | O62: =G62 -> -27066.37 | P62: =H62 -> SBI 5441
A63: 45199 | B63: 45199 | C63: DEBIT INTEREST--- | E63: 1869 | F63: 0 | G63: -28935.37 | H63: SBI 5441 | I63: =G62-E63+F63-G63 -> 0 | J63: =A63 -> 45199 | K63: =C63 -> DEBIT INTEREST--- | L63: =D63 -> 0 | M63: =E63 -> 1869 | N63: =F63 -> 0 | O63: =G63 -> -28935.37 | P63: =H63 -> SBI 5441
A64: 45201 | B64: 45201 | C64: DEPOSIT TRANSFER--- | D64: TRANSFER FROM 20010697703 | E64: 0 | F64: 26595 | G64: -2340.37 | H64: SBI 5441 | I64: =G63-E64+F64-G64 -> 0 | J64: =A64 -> 45201 | K64: =C64 -> DEPOSIT TRANSFER--- | L64: =D64 -> TRANSFER FROM 20010697703 | M64: =E64 -> 0 | N64: =F64 -> 26595 | O64: =G64 -> -2340.37 | P64: =H64 -> SBI 5441
A65: 45212 | B65: 45212 | C65: TO TRANSFER-INB Payment of education fee-- | D65: IIC1835052 TRANSFER TO 20010697703 | E65: 10000 | F65: 0 | G65: -12340.37 | H65: SBI 5441 | I65: =G64-E65+F65-G65 -> 0 | J65: =A65 -> 45212 | K65: =C65 -> TO TRANSFER-INB Payment of education fee-- | L65: =D65 -> IIC1835052 TRANSFER TO 20010697703 | M65: =E65 -> 10000 | N65: =F65 -> 0 | O65: =G65 -> -12340.37 | P65: =H65 -> SBI 5441
A66: 45218 | B66: 45218 | C66: TO TRANSFER-INB Deposit / Investment-- | D66: IIC1965407 TRANSFER TO 20010697703 | E66: 10000 | F66: 0 | G66: -22340.37 | H66: SBI 5441 | I66: =G65-E66+F66-G66 -> 0 | J66: =A66 -> 45218 | K66: =C66 -> TO TRANSFER-INB Deposit / Investment-- | L66: =D66 -> IIC1965407 TRANSFER TO 20010697703 | M66: =E66 -> 10000 | N66: =F66 -> 0 | O66: =G66 -> -22340.37 | P66: =H66 -> SBI 5441
A67: 45222 | B67: 45222 | C67: TO TRANSFER-INB NEFT UTR NO: SBIN223296246482--Ajay Kumar Gupta | D67: NEFT INB: IRX2448244 / Ajay Kumar Gupta | E67: 200000 | F67: 0 | G67: -222340.37 | H67: SBI 5441 | I67: =G66-E67+F67-G67 -> 0 | J67: =A67 -> 45222 | K67: =C67 -> TO TRANSFER-INB NEFT UTR NO: SBIN223296246482--Ajay Kumar Gupta | L67: =D67 -> NEFT INB: IRX2448244 / Ajay Kumar Gupta | M67: =E67 -> 200000 | N67: =F67 -> 0 | O67: =G67 -> -222340.37 | P67: =H67 -> SBI 5441
A68: 45230 | B68: 45230 | C68: TO TRANSFER-INB Payment towards loan repayment-- | D68: IIC2218026 TRANSFER TO 20010697703 | E68: 25000 | F68: 0 | G68: -247340.37 | H68: SBI 5441 | I68: =G67-E68+F68-G68 -> 0 | J68: =A68 -> 45230 | K68: =C68 -> TO TRANSFER-INB Payment towards loan repayment-- | L68: =D68 -> IIC2218026 TRANSFER TO 20010697703 | M68: =E68 -> 25000 | N68: =F68 -> 0 | O68: =G68 -> -247340.37 | P68: =H68 -> SBI 5441
A69: 45230 | B69: 45230 | C69: TO TRANSFER-INB NEFT UTR NO: SBIN423304369896--Ajay Kumar Gupta | D69: NEFT INB: IRX2847544 / Ajay Kumar Gupta | E69: 300000 | F69: 0 | G69: -547340.37 | H69: SBI 5441 | I69: =G68-E69+F69-G69 -> 0 | J69: =A69 -> 45230 | K69: =C69 -> TO TRANSFER-INB NEFT UTR NO: SBIN423304369896--Ajay Kumar Gupta | L69: =D69 -> NEFT INB: IRX2847544 / Ajay Kumar Gupta | M69: =E69 -> 300000 | N69: =F69 -> 0 | O69: =G69 -> -547340.37 | P69: =H69 -> SBI 5441
A70: 45230 | B70: 45230 | C70: BY TRANSFER-RTGS UTR NO: HDFCR52023103150344939--AJAY KUMAR GUPTA | D70: TRANSFER FROM 3199856044300 / AJAY KUMAR GUPTA | E70: 0 | F70: 350000 | G70: -197340.37 | H70: SBI 5441 | I70: =G69-E70+F70-G70 -> 0 | J70: =A70 -> 45230 | K70: =C70 -> BY TRANSFER-RTGS UTR NO: HDFCR52023103150344939--AJAY KUMAR GUPTA | L70: =D70 -> TRANSFER FROM 3199856044300 / AJAY KUMAR GUPTA | M70: =E70 -> 0 | N70: =F70 -> 350000 | O70: =G70 -> -197340.37 | P70: =H70 -> SBI 5441
A71: 45230 | B71: 45230 | C71: DEBIT INTEREST--- | E71: 622 | F71: 0 | G71: -197962.37 | H71: SBI 5441 | I71: =G70-E71+F71-G71 -> 0 | J71: =A71 -> 45230 | K71: =C71 -> DEBIT INTEREST--- | L71: =D71 -> 0 | M71: =E71 -> 622 | N71: =F71 -> 0 | O71: =G71 -> -197962.37 | P71: =H71 -> SBI 5441
A72: 45232 | B72: 45232 | C72: DEPOSIT TRANSFER--- | D72: TRANSFER FROM 20010697703 | E72: 0 | F72: 26595 | G72: -171367.37 | H72: SBI 5441 | I72: =G71-E72+F72-G72 -> 0 | J72: =A72 -> 45232 | K72: =C72 -> DEPOSIT TRANSFER--- | L72: =D72 -> TRANSFER FROM 20010697703 | M72: =E72 -> 0 | N72: =F72 -> 26595 | O72: =G72 -> -171367.37 | P72: =H72 -> SBI 5441
A73: 45232 | B73: 45232 | C73: BY TRANSFER-NEFT*HDFC0000001*N306232716343009*AJAY KUMAR GUPTA-- | D73: TRANSFER FROM 4697257044303 | E73: 0 | F73: 75000 | G73: -96367.37 | H73: SBI 5441 | I73: =G72-E73+F73-G73 -> 0 | J73: =A73 -> 45232 | K73: =C73 -> BY TRANSFER-NEFT*HDFC0000001*N306232716343009*AJAY KUMAR GUPTA-- | L73: =D73 -> TRANSFER FROM 4697257044303 | M73: =E73 -> 0 | N73: =F73 -> 75000 | O73: =G73 -> -96367.37 | P73: =H73 -> SBI 5441
A74: 45236 | B74: 45236 | C74: TO TRANSFER-INB NEFT UTR NO: SBIN123310294550--Ajay Kumar Gupta | D74: NEFT INB: IRX3339417 / Ajay Kumar Gupta | E74: 100000 | F74: 0 | G74: -196367.37 | H74: SBI 5441 | I74: =G73-E74+F74-G74 -> 0 | J74: =A74 -> 45236 | K74: =C74 -> TO TRANSFER-INB NEFT UTR NO: SBIN123310294550--Ajay Kumar Gupta | L74: =D74 -> NEFT INB: IRX3339417 / Ajay Kumar Gupta | M74: =E74 -> 100000 | N74: =F74 -> 0 | O74: =G74 -> -196367.37 | P74: =H74 -> SBI 5441
A75: 45243 | B75: 45243 | C75: BY TRANSFER-NEFT*HDFC0000001*N317232738102386*AJAY KUMAR GUPTA-- | D75: TRANSFER FROM 3199419044300 | E75: 0 | F75: 75000 | G75: -121367.37 | H75: SBI 5441 | I75: =G74-E75+F75-G75 -> 0 | J75: =A75 -> 45243 | K75: =C75 -> BY TRANSFER-NEFT*HDFC0000001*N317232738102386*AJAY KUMAR GUPTA-- | L75: =D75 -> TRANSFER FROM 3199419044300 | M75: =E75 -> 0 | N75: =F75 -> 75000 | O75: =G75 -> -121367.37 | P75: =H75 -> SBI 5441
A76: 45247 | B76: 45247 | C76: BY TRANSFER-NEFT*HDFC0000001*N321232743060950*AJAY KUMAR GUPTA-- | D76: TRANSFER FROM 4697205044304 | E76: 0 | F76: 100000 | G76: -21367.37 | H76: SBI 5441 | I76: =G75-E76+F76-G76 -> 0 | J76: =A76 -> 45247 | K76: =C76 -> BY TRANSFER-NEFT*HDFC0000001*N321232743060950*AJAY KUMAR GUPTA-- | L76: =D76 -> TRANSFER FROM 4697205044304 | M76: =E76 -> 0 | N76: =F76 -> 100000 | O76: =G76 -> -21367.37 | P76: =H76 -> SBI 5441
A77: 45253 | B77: 45253 | C77: BY TRANSFER-INB Payment towards loan repayment-- | D77: IIC2861225 TRANSFER FROM 20010697703 | E77: 0 | F77: 20000 | G77: -1367.37 | H77: SBI 5441 | I77: =G76-E77+F77-G77 -> 0 | J77: =A77 -> 45253 | K77: =C77 -> BY TRANSFER-INB Payment towards loan repayment-- | L77: =D77 -> IIC2861225 TRANSFER FROM 20010697703 | M77: =E77 -> 0 | N77: =F77 -> 20000 | O77: =G77 -> -1367.37 | P77: =H77 -> SBI 5441
A78: 45260 | B78: 45260 | C78: DEBIT INTEREST--- | E78: 732 | F78: 0 | G78: -2099.37 | H78: SBI 5441 | I78: =G77-E78+F78-G78 -> 0 | J78: =A78 -> 45260 | K78: =C78 -> DEBIT INTEREST--- | L78: =D78 -> 0 | M78: =E78 -> 732 | N78: =F78 -> 0 | O78: =G78 -> -2099.37 | P78: =H78 -> SBI 5441
A79: 45261 | B79: 45261 | C79: TO TRANSFER-INB NEFT UTR NO: SBIN323335872056--Ajay Kumar Gupta | D79: NEFT INB: IRX4838746 / Ajay Kumar Gupta | E79: 250000 | F79: 0 | G79: -252099.37 | H79: SBI 5441 | I79: =G78-E79+F79-G79 -> 0 | J79: =A79 -> 45261 | K79: =C79 -> TO TRANSFER-INB NEFT UTR NO: SBIN323335872056--Ajay Kumar Gupta | L79: =D79 -> NEFT INB: IRX4838746 / Ajay Kumar Gupta | M79: =E79 -> 250000 | N79: =F79 -> 0 | O79: =G79 -> -252099.37 | P79: =H79 -> SBI 5441
A80: 45261 | B80: 45261 | C80: BY TRANSFER-INB Payment towards loan repayment-- | D80: IIC3095625 TRANSFER FROM 20010697703 | E80: 0 | F80: 70000 | G80: -182099.37 | H80: SBI 5441 | I80: =G79-E80+F80-G80 -> 0 | J80: =A80 -> 45261 | K80: =C80 -> BY TRANSFER-INB Payment towards loan repayment-- | L80: =D80 -> IIC3095625 TRANSFER FROM 20010697703 | M80: =E80 -> 0 | N80: =F80 -> 70000 | O80: =G80 -> -182099.37 | P80: =H80 -> SBI 5441
A81: 45262 | B81: 45262 | C81: DEPOSIT TRANSFER--- | D81: TRANSFER FROM 20010697703 | E81: 0 | F81: 26595 | G81: -155504.37 | H81: SBI 5441 | I81: =G80-E81+F81-G81 -> 0 | J81: =A81 -> 45262 | K81: =C81 -> DEPOSIT TRANSFER--- | L81: =D81 -> TRANSFER FROM 20010697703 | M81: =E81 -> 0 | N81: =F81 -> 26595 | O81: =G81 -> -155504.37 | P81: =H81 -> SBI 5441
A82: 45264 | B82: 45264 | C82: TO TRANSFER-INB NEFT UTR NO: SBIN523338840590--Ajay Kumar Gupta | D82: NEFT INB: IRX5047074 / Ajay Kumar Gupta | E82: 150000 | F82: 0 | G82: -305504.37 | H82: SBI 5441 | I82: =G81-E82+F82-G82 -> 0 | J82: =A82 -> 45264 | K82: =C82 -> TO TRANSFER-INB NEFT UTR NO: SBIN523338840590--Ajay Kumar Gupta | L82: =D82 -> NEFT INB: IRX5047074 / Ajay Kumar Gupta | M82: =E82 -> 150000 | N82: =F82 -> 0 | O82: =G82 -> -305504.37 | P82: =H82 -> SBI 5441
A83: 45265 | B83: 45265 | C83: BY TRANSFER-INB Payment towards loan repayment-- | D83: IIC3256631 TRANSFER FROM 20010697703 | E83: 0 | F83: 75000 | G83: -230504.37 | H83: SBI 5441 | I83: =G82-E83+F83-G83 -> 0 | J83: =A83 -> 45265 | K83: =C83 -> BY TRANSFER-INB Payment towards loan repayment-- | L83: =D83 -> IIC3256631 TRANSFER FROM 20010697703 | M83: =E83 -> 0 | N83: =F83 -> 75000 | O83: =G83 -> -230504.37 | P83: =H83 -> SBI 5441
A84: 45272 | B84: 45272 | C84: BY TRANSFER-SBILT12122023135917188300-Loan repayment-- | D84: TRANSFER FROM 20010697703 | E84: 0 | F84: 225000 | G84: -5504.37 | H84: SBI 5441 | I84: =G83-E84+F84-G84 -> 0 | J84: =A84 -> 45272 | K84: =C84 -> BY TRANSFER-SBILT12122023135917188300-Loan repayment-- | L84: =D84 -> TRANSFER FROM 20010697703 | M84: =E84 -> 0 | N84: =F84 -> 225000 | O84: =G84 -> -5504.37 | P84: =H84 -> SBI 5441
A85: 45274 | B85: 45274 | C85: BY TRANSFER-INB Payment towards loan repayment-- | D85: IIC3482728 TRANSFER FROM 20010697703 | E85: 0 | F85: 5000 | G85: -504.37 | H85: SBI 5441 | I85: =G84-E85+F85-G85 -> 0 | J85: =A85 -> 45274 | K85: =C85 -> BY TRANSFER-INB Payment towards loan repayment-- | L85: =D85 -> IIC3482728 TRANSFER FROM 20010697703 | M85: =E85 -> 0 | N85: =F85 -> 5000 | O85: =G85 -> -504.37 | P85: =H85 -> SBI 5441
A86: 45291 | B86: 45291 | C86: TO TRANSFER-INB Payment towards loan repayment-- | D86: IIC3891043 TRANSFER TO 20010697703 | E86: 27000 | F86: 0 | G86: -27504.37 | H86: SBI 5441 | I86: =G85-E86+F86-G86 -> 0 | J86: =A86 -> 45291 | K86: =C86 -> TO TRANSFER-INB Payment towards loan repayment-- | L86: =D86 -> IIC3891043 TRANSFER TO 20010697703 | M86: =E86 -> 27000 | N86: =F86 -> 0 | O86: =G86 -> -27504.37 | P86: =H86 -> SBI 5441
A87: 45291 | B87: 45291 | C87: DEBIT INTEREST--- | E87: 698 | F87: 0 | G87: -28202.37 | H87: SBI 5441 | I87: =G86-E87+F87-G87 -> 0 | J87: =A87 -> 45291 | K87: =C87 -> DEBIT INTEREST--- | L87: =D87 -> 0 | M87: =E87 -> 698 | N87: =F87 -> 0 | O87: =G87 -> -28202.37 | P87: =H87 -> SBI 5441
A88: 45293 | B88: 45293 | C88: DEPOSIT TRANSFER--- | D88: TRANSFER FROM 20010697703 | E88: 0 | F88: 26595 | G88: -1607.37 | H88: SBI 5441 | I88: =G87-E88+F88-G88 -> 0 | J88: =A88 -> 45293 | K88: =C88 -> DEPOSIT TRANSFER--- | L88: =D88 -> TRANSFER FROM 20010697703 | M88: =E88 -> 0 | N88: =F88 -> 26595 | O88: =G88 -> -1607.37 | P88: =H88 -> SBI 5441
A89: 45300 | B89: 45300 | C89: TO TRANSFER-INB Deposit / Investment-- | D89: IIC4223827 TRANSFER TO 20010697703 | E89: 15000 | F89: 0 | G89: -16607.37 | H89: SBI 5441 | I89: =G88-E89+F89-G89 -> 0 | J89: =A89 -> 45300 | K89: =C89 -> TO TRANSFER-INB Deposit / Investment-- | L89: =D89 -> IIC4223827 TRANSFER TO 20010697703 | M89: =E89 -> 15000 | N89: =F89 -> 0 | O89: =G89 -> -16607.37 | P89: =H89 -> SBI 5441
A90: 45304 | B90: 45304 | C90: TO TRANSFER-INB NEFT UTR NO: SBIN324013860186--Ajay Kumar Gupta | D90: NEFT INB: IRX7701395 / Ajay Kumar Gupta | E90: 100000 | F90: 0 | G90: -116607.37 | H90: SBI 5441 | I90: =G89-E90+F90-G90 -> 0 | J90: =A90 -> 45304 | K90: =C90 -> TO TRANSFER-INB NEFT UTR NO: SBIN324013860186--Ajay Kumar Gupta | L90: =D90 -> NEFT INB: IRX7701395 / Ajay Kumar Gupta | M90: =E90 -> 100000 | N90: =F90 -> 0 | O90: =G90 -> -116607.37 | P90: =H90 -> SBI 5441
A91: 45309 | B91: 45309 | C91: TO TRANSFER-INB NEFT UTR NO: SBIN224018057920--Ajay Kumar Gupta | D91: NEFT INB: IRX7925240 / Ajay Kumar Gupta | E91: 100000 | F91: 0 | G91: -216607.37 | H91: SBI 5441 | I91: =G90-E91+F91-G91 -> 0 | J91: =A91 -> 45309 | K91: =C91 -> TO TRANSFER-INB NEFT UTR NO: SBIN224018057920--Ajay Kumar Gupta | L91: =D91 -> NEFT INB: IRX7925240 / Ajay Kumar Gupta | M91: =E91 -> 100000 | N91: =F91 -> 0 | O91: =G91 -> -216607.37 | P91: =H91 -> SBI 5441
A92: 45311 | B92: 45311 | C92: TO TRANSFER-INB Payment towards loan repayment-- | D92: IIC4476141 TRANSFER TO 20010697703 | E92: 75000 | F92: 0 | G92: -291607.37 | H92: SBI 5441 | I92: =G91-E92+F92-G92 -> 0 | J92: =A92 -> 45311 | K92: =C92 -> TO TRANSFER-INB Payment towards loan repayment-- | L92: =D92 -> IIC4476141 TRANSFER TO 20010697703 | M92: =E92 -> 75000 | N92: =F92 -> 0 | O92: =G92 -> -291607.37 | P92: =H92 -> SBI 5441
A93: 45311 | B93: 45311 | C93: BY TRANSFER-INB Payment towards loan repayment-- | D93: IIC4476150 TRANSFER FROM 20010697703 | E93: 0 | F93: 150000 | G93: -141607.37 | H93: SBI 5441 | I93: =G92-E93+F93-G93 -> 0 | J93: =A93 -> 45311 | K93: =C93 -> BY TRANSFER-INB Payment towards loan repayment-- | L93: =D93 -> IIC4476150 TRANSFER FROM 20010697703 | M93: =E93 -> 0 | N93: =F93 -> 150000 | O93: =G93 -> -141607.37 | P93: =H93 -> SBI 5441
A94: 45322 | B94: 45322 | C94: DEBIT INTEREST--- | E94: 812 | F94: 0 | G94: -142419.37 | H94: SBI 5441 | I94: =G93-E94+F94-G94 -> 0 | J94: =A94 -> 45322 | K94: =C94 -> DEBIT INTEREST--- | L94: =D94 -> 0 | M94: =E94 -> 812 | N94: =F94 -> 0 | O94: =G94 -> -142419.37 | P94: =H94 -> SBI 5441
A95: 45324 | B95: 45324 | C95: DEPOSIT TRANSFER--- | D95: TRANSFER FROM 20010697703 | E95: 0 | F95: 26595 | G95: -115824.37 | H95: SBI 5441 | I95: =G94-E95+F95-G95 -> 0 | J95: =A95 -> 45324 | K95: =C95 -> DEPOSIT TRANSFER--- | L95: =D95 -> TRANSFER FROM 20010697703 | M95: =E95 -> 0 | N95: =F95 -> 26595 | O95: =G95 -> -115824.37 | P95: =H95 -> SBI 5441
A96: 45329 | B96: 45329 | C96: TO TRANSFER-INB Deposit / Investment-- | D96: IIC4978875 TRANSFER TO 20010697703 | E96: 50000 | F96: 0 | G96: -165824.37 | H96: SBI 5441 | I96: =G95-E96+F96-G96 -> 0 | J96: =A96 -> 45329 | K96: =C96 -> TO TRANSFER-INB Deposit / Investment-- | L96: =D96 -> IIC4978875 TRANSFER TO 20010697703 | M96: =E96 -> 50000 | N96: =F96 -> 0 | O96: =G96 -> -165824.37 | P96: =H96 -> SBI 5441
A97: 45343 | B97: 45343 | C97: BY TRANSFER-INB Payment towards loan repayment-- | D97: IIC5298224 TRANSFER FROM 20010697703 | E97: 0 | F97: 165000 | G97: -824.37 | H97: SBI 5441 | I97: =G96-E97+F97-G97 -> 4.6611603e-12 | J97: =A97 -> 45343 | K97: =C97 -> BY TRANSFER-INB Payment towards loan repayment-- | L97: =D97 -> IIC5298224 TRANSFER FROM 20010697703 | M97: =E97 -> 0 | N97: =F97 -> 165000 | O97: =G97 -> -824.37 | P97: =H97 -> SBI 5441
A98: 45350 | B98: 45350 | C98: TO TRANSFER-INB Deposit / Investment-- | D98: IIC5445549 TRANSFER TO 20010697703 | E98: 100000 | F98: 0 | G98: -100824.37 | H98: SBI 5441 | I98: =G97-E98+F98-G98 -> 0 | J98: =A98 -> 45350 | K98: =C98 -> TO TRANSFER-INB Deposit / Investment-- | L98: =D98 -> IIC5445549 TRANSFER TO 20010697703 | M98: =E98 -> 100000 | N98: =F98 -> 0 | O98: =G98 -> -100824.37 | P98: =H98 -> SBI 5441
A99: 45351 | B99: 45351 | C99: DEBIT INTEREST--- | E99: 935 | F99: 0 | G99: -101759.37 | H99: SBI 5441 | I99: =G98-E99+F99-G99 -> 0 | J99: =A99 -> 45351 | K99: =C99 -> DEBIT INTEREST--- | L99: =D99 -> 0 | M99: =E99 -> 935 | N99: =F99 -> 0 | O99: =G99 -> -101759.37 | P99: =H99 -> SBI 5441
A100: 45353 | B100: 45353 | C100: DEPOSIT TRANSFER--- | D100: TRANSFER FROM 20010697703 | E100: 0 | F100: 26595 | G100: -75164.37 | H100: SBI 5441 | I100: =G99-E100+F100-G100 -> 0 | J100: =A100 -> 45353 | K100: =C100 -> DEPOSIT TRANSFER--- | L100: =D100 -> TRANSFER FROM 20010697703 | M100: =E100 -> 0 | N100: =F100 -> 26595 | O100: =G100 -> -75164.37 | P100: =H100 -> SBI 5441
...

Sheet SBI Bank 3479
A1: Account Name : | B1: Mr. AJAY KUMAR GUPTA
A2: Address : | B2: FLAT NO D-07 ISHWAR PARADISE
B3: ASHOKA MARG NASIK ROAD
B4: NASIK-422101
B5: Nashik
A6: Date : | B6: 45304
A7: Account Number : | B7: _00000020010697703
A8: Account Description: | B8: SBCHQ-SBP-GEN-PUB-IND-ALL-INR
A9: Branch : | B9: SHIVAJI NAGAR, NASIK
A10: Drawing Power : | B10: 0
A11: Interest Rate(% p.a.): | B11: 2.7
A12: MOD Balance : | B12: 0
A13: CIF No. : | B13: _85190853479
A14: IFS (Indian Financial System) Code : | B14: SBIN0011669
A15: MICR (Magnetic Ink Character Recognition) Code : | B15: _422002020
A16: Nomination Registered : | B16: Yes
A17: Balance on 1 Apr 2023 : | B17: 4724.4
A18: Start Date : | B18: 45017
A19: End Date : | B19: 45291 | E19: =SUBTOTAL(9,E21:E178) -> 2832081.1 | F19: =SUBTOTAL(9,F21:F178) -> 3143745.2 | G19: =G21-F21 -> 4724.4
A20: Txn Date | B20: Value Date | C20: Description | D20: Ref No./Cheque No. | E20: Debit | F20: Credit | G20: Balance | H20: Account No | J20: TX Date | K20: Particulars | L20: Ref | M20: DR | N20: CR | O20: Balance | P20: Account No
A21: 45017 | B21: 45017 | C21: BY TRANSFER-INB Payment towards loan repayment-- | D21: IIB6318597 TRANSFER FROM 32718635441 | E21: 0 | F21: 25000 | G21: 29724.4 | H21: SBI 3479 | I21: =G19+F21-E21-G21 -> 0 | J21: =A21 -> 45017 | K21: =C21 -> BY TRANSFER-INB Payment towards loan repayment-- | L21: =D21 -> IIB6318597 TRANSFER FROM 32718635441 | M21: =E21 -> 0 | N21: =F21 -> 25000 | O21: =G21 -> 29724.4 | P21: =H21 -> SBI 3479
A22: 45018 | B22: 45018 | C22: WITHDRAWAL TRANSFER--- | D22: TRANSFER TO 32718635441 | E22: 26595 | F22: 0 | G22: 3129.4 | H22: SBI 3479 | I22: =G21+F22-E22-G22 -> 0 | J22: =A22 -> 45018 | K22: =C22 -> WITHDRAWAL TRANSFER--- | L22: =D22 -> TRANSFER TO 32718635441 | M22: =E22 -> 26595 | N22: =F22 -> 0 | O22: =G22 -> 3129.4 | P22: =H22 -> SBI 3479
A23: 45022 | B23: 45022 | C23: BY TRANSFER-INB -For 19260165-- | D23: 6503260805CTW5438690 TRANSFER FROM 4 | E23: 0 | F23: 1664.77 | G23: 4794.17 | H23: SBI 3479 | I23: =G22+F23-E23-G23 -> 0 | J23: =A23 -> 45022 | K23: =C23 -> BY TRANSFER-INB -For 19260165-- | L23: =D23 -> 6503260805CTW5438690 TRANSFER FROM 4 | M23: =E23 -> 0 | N23: =F23 -> 1664.77 | O23: =G23 -> 4794.17 | P23: =H23 -> SBI 3479
A24: 45027 | B24: 45027 | C24: BY TRANSFER-INB -For 19260165-- | D24: 6503375120CTW5943163 TRANSFER FROM 4 | E24: 0 | F24: 290.28 | G24: 5084.45 | H24: SBI 3479 | I24: =G23+F24-E24-G24 -> 0 | J24: =A24 -> 45027 | K24: =C24 -> BY TRANSFER-INB -For 19260165-- | L24: =D24 -> 6503375120CTW5943163 TRANSFER FROM 4 | M24: =E24 -> 0 | N24: =F24 -> 290.28 | O24: =G24 -> 5084.45 | P24: =H24 -> SBI 3479
A25: 45027 | B25: 45027 | C25: BY TRANSFER-INB -For 19260165-- | D25: 6503407916CTW6110905 TRANSFER FROM 4 | E25: 0 | F25: 173592.01 | G25: 178676.46 | H25: SBI 3479 | I25: =G24+F25-E25-G25 -> 0 | J25: =A25 -> 45027 | K25: =C25 -> BY TRANSFER-INB -For 19260165-- | L25: =D25 -> 6503407916CTW6110905 TRANSFER FROM 4 | M25: =E25 -> 0 | N25: =F25 -> 173592.01 | O25: =G25 -> 178676.46 | P25: =H25 -> SBI 3479
A26: 45028 | B26: 45028 | C26: BULK POSTING-ACHCr HDFC01984000016202 DWARIKESH INTD-- | E26: 0 | F26: 1200 | G26: 179876.46 | H26: SBI 3479 | I26: =G25+F26-E26-G26 -> 0 | J26: =A26 -> 45028 | K26: =C26 -> BULK POSTING-ACHCr HDFC01984000016202 DWARIKESH INTD-- | L26: =D26 -> 0 | M26: =E26 -> 0 | N26: =F26 -> 1200 | O26: =G26 -> 179876.46 | P26: =H26 -> SBI 3479
A27: 45029 | B27: 45029 | C27: TO TRANSFER-SBILT13042023084220295270-Loan repayment-- | D27: TRANSFER TO 32718635441 | E27: 50000 | F27: 0 | G27: 129876.46 | H27: SBI 3479 | I27: =G26+F27-E27-G27 -> 0 | J27: =A27 -> 45029 | K27: =C27 -> TO TRANSFER-SBILT13042023084220295270-Loan repayment-- | L27: =D27 -> TRANSFER TO 32718635441 | M27: =E27 -> 50000 | N27: =F27 -> 0 | O27: =G27 -> 129876.46 | P27: =H27 -> SBI 3479
A28: 45031 | B28: 45031 | C28: TO TRANSFER-INB SBICARD FOR BILLDESK SBICARD Payments-- | D28: YSBI1843207721IGAPLILQC0 TRANSFER TO | E28: 4502 | F28: 0 | G28: 125374.46 | H28: SBI 3479 | I28: =G27+F28-E28-G28 -> 0 | J28: =A28 -> 45031 | K28: =C28 -> TO TRANSFER-INB SBICARD FOR BILLDESK SBICARD Payments-- | L28: =D28 -> YSBI1843207721IGAPLILQC0 TRANSFER TO | M28: =E28 -> 4502 | N28: =F28 -> 0 | O28: =G28 -> 125374.46 | P28: =H28 -> SBI 3479
A29: 45031 | B29: 45031 | C29: TO TRANSFER-INB Payment towards loan repayment-- | D29: IIB6794633 TRANSFER TO 32718635441 | E29: 100000 | F29: 0 | G29: 25374.46 | H29: SBI 3479 | I29: =G28+F29-E29-G29 -> 0 | J29: =A29 -> 45031 | K29: =C29 -> TO TRANSFER-INB Payment towards loan repayment-- | L29: =D29 -> IIB6794633 TRANSFER TO 32718635441 | M29: =E29 -> 100000 | N29: =F29 -> 0 | O29: =G29 -> 25374.46 | P29: =H29 -> SBI 3479
A30: 45035 | B30: 45035 | C30: BY TRANSFER-INB -For 19260165-- | D30: 6503644322CTW7125901 TRANSFER FROM 4 | E30: 0 | F30: 3231.91 | G30: 28606.37 | H30: SBI 3479 | I30: =G29+F30-E30-G30 -> 0 | J30: =A30 -> 45035 | K30: =C30 -> BY TRANSFER-INB -For 19260165-- | L30: =D30 -> 6503644322CTW7125901 TRANSFER FROM 4 | M30: =E30 -> 0 | N30: =F30 -> 3231.91 | O30: =G30 -> 28606.37 | P30: =H30 -> SBI 3479
A31: 45036 | B31: 45036 | C31: BY TRANSFER-INB -For 19260165-- | D31: 6503677670CTW7273599 TRANSFER FROM 4 | E31: 0 | F31: 15083.73 | G31: 43690.1 | H31: SBI 3479 | I31: =G30+F31-E31-G31 -> 0 | J31: =A31 -> 45036 | K31: =C31 -> BY TRANSFER-INB -For 19260165-- | L31: =D31 -> 6503677670CTW7273599 TRANSFER FROM 4 | M31: =E31 -> 0 | N31: =F31 -> 15083.73 | O31: =G31 -> 43690.1 | P31: =H31 -> SBI 3479
A32: 45039 | B32: 45039 | C32: BY TRANSFER-INB Payment towards loan repayment-- | D32: IIB6951402 TRANSFER FROM 32718635441 | E32: 0 | F32: 35000 | G32: 78690.1 | H32: SBI 3479 | I32: =G31+F32-E32-G32 -> 0 | J32: =A32 -> 45039 | K32: =C32 -> BY TRANSFER-INB Payment towards loan repayment-- | L32: =D32 -> IIB6951402 TRANSFER FROM 32718635441 | M32: =E32 -> 0 | N32: =F32 -> 35000 | O32: =G32 -> 78690.1 | P32: =H32 -> SBI 3479
A33: 45039 | B33: 45039 | C33: TO TRANSFER-INB Payment towards loan repayment-- | D33: IIB6951312 TRANSFER TO 32718635441 | E33: 70000 | F33: 0 | G33: 8690.1 | H33: SBI 3479 | I33: =G32+F33-E33-G33 -> 0 | J33: =A33 -> 45039 | K33: =C33 -> TO TRANSFER-INB Payment towards loan repayment-- | L33: =D33 -> IIB6951312 TRANSFER TO 32718635441 | M33: =E33 -> 70000 | N33: =F33 -> 0 | O33: =G33 -> 8690.1 | P33: =H33 -> SBI 3479
A34: 45041 | B34: 45041 | C34: BULK POSTING-ACHCr KKBK00188000018285 DHAMPUR SUGAR-- | E34: 0 | F34: 300 | G34: 8990.1 | H34: SBI 3479 | I34: =G33+F34-E34-G34 -> 0 | J34: =A34 -> 45041 | K34: =C34 -> BULK POSTING-ACHCr KKBK00188000018285 DHAMPUR SUGAR-- | L34: =D34 -> 0 | M34: =E34 -> 0 | N34: =F34 -> 300 | O34: =G34 -> 8990.1 | P34: =H34 -> SBI 3479
A35: 45042 | B35: 45042 | C35: BY TRANSFER-INB Deposit / Investment-- | D35: IIB7031794 TRANSFER FROM 32718635441 | E35: 0 | F35: 10000 | G35: 18990.1 | H35: SBI 3479 | I35: =G34+F35-E35-G35 -> 0 | J35: =A35 -> 45042 | K35: =C35 -> BY TRANSFER-INB Deposit / Investment-- | L35: =D35 -> IIB7031794 TRANSFER FROM 32718635441 | M35: =E35 -> 0 | N35: =F35 -> 10000 | O35: =G35 -> 18990.1 | P35: =H35 -> SBI 3479
A36: 45044 | B36: 45044 | C36: BY TRANSFER-INB -For 19260165-- | D36: 6503910734CTW8203019 TRANSFER FROM 4 | E36: 0 | F36: 5755.3 | G36: 24745.4 | H36: SBI 3479 | I36: =G35+F36-E36-G36 -> 0 | J36: =A36 -> 45044 | K36: =C36 -> BY TRANSFER-INB -For 19260165-- | L36: =D36 -> 6503910734CTW8203019 TRANSFER FROM 4 | M36: =E36 -> 0 | N36: =F36 -> 5755.3 | O36: =G36 -> 24745.4 | P36: =H36 -> SBI 3479
A37: 45046 | B37: 45046 | C37: BY TRANSFER-INB Payment towards loan repayment-- | D37: IIB7146807 TRANSFER FROM 32718635441 | E37: 0 | F37: 20000 | G37: 44745.4 | H37: SBI 3479 | I37: =G36+F37-E37-G37 -> 0 | J37: =A37 -> 45046 | K37: =C37 -> BY TRANSFER-INB Payment towards loan repayment-- | L37: =D37 -> IIB7146807 TRANSFER FROM 32718635441 | M37: =E37 -> 0 | N37: =F37 -> 20000 | O37: =G37 -> 44745.4 | P37: =H37 -> SBI 3479
A38: 45048 | B38: 45048 | C38: WITHDRAWAL TRANSFER--- | D38: TRANSFER TO 32718635441 | E38: 26595 | F38: 0 | G38: 18150.4 | H38: SBI 3479 | I38: =G37+F38-E38-G38 -> 0 | J38: =A38 -> 45048 | K38: =C38 -> WITHDRAWAL TRANSFER--- | L38: =D38 -> TRANSFER TO 32718635441 | M38: =E38 -> 26595 | N38: =F38 -> 0 | O38: =G38 -> 18150.4 | P38: =H38 -> SBI 3479
A39: 45049 | B39: 45049 | C39: BY TRANSFER-INB -For 19260165-- | D39: 6504023356CTW8820042 TRANSFER FROM 4 | E39: 0 | F39: 6485.61 | G39: 24636.01 | H39: SBI 3479 | I39: =G38+F39-E39-G39 -> 0 | J39: =A39 -> 45049 | K39: =C39 -> BY TRANSFER-INB -For 19260165-- | L39: =D39 -> 6504023356CTW8820042 TRANSFER FROM 4 | M39: =E39 -> 0 | N39: =F39 -> 6485.61 | O39: =G39 -> 24636.01 | P39: =H39 -> SBI 3479
A40: 45050 | B40: 45050 | C40: TO TRANSFER-TRFD TO MANKIND PHARMA LTD IPO ALLOTMENT-- | D40: TRANSFER TO 38660007037 | E40: 14040 | F40: 0 | G40: 10596.01 | H40: SBI 3479 | I40: =G39+F40-E40-G40 -> 0 | J40: =A40 -> 45050 | K40: =C40 -> TO TRANSFER-TRFD TO MANKIND PHARMA LTD IPO ALLOTMENT-- | L40: =D40 -> TRANSFER TO 38660007037 | M40: =E40 -> 14040 | N40: =F40 -> 0 | O40: =G40 -> 10596.01 | P40: =H40 -> SBI 3479
A41: 45055 | B41: 45055 | C41: BY TRANSFER-INB -For 19260165-- | D41: 6504141132CTW9502868 TRANSFER FROM 4 | E41: 0 | F41: 12256.46 | G41: 22852.47 | H41: SBI 3479 | I41: =G40+F41-E41-G41 -> 0 | J41: =A41 -> 45055 | K41: =C41 -> BY TRANSFER-INB -For 19260165-- | L41: =D41 -> 6504141132CTW9502868 TRANSFER FROM 4 | M41: =E41 -> 0 | N41: =F41 -> 12256.46 | O41: =G41 -> 22852.47 | P41: =H41 -> SBI 3479
A42: 45055 | B42: 45055 | C42: BY TRANSFER-INB -For 19260165-- | D42: 6504184340CTW9668902 TRANSFER FROM 4 | E42: 0 | F42: 6179.42 | G42: 29031.89 | H42: SBI 3479 | I42: =G41+F42-E42-G42 -> 0 | J42: =A42 -> 45055 | K42: =C42 -> BY TRANSFER-INB -For 19260165-- | L42: =D42 -> 6504184340CTW9668902 TRANSFER FROM 4 | M42: =E42 -> 0 | N42: =F42 -> 6179.42 | O42: =G42 -> 29031.89 | P42: =H42 -> SBI 3479
A43: 45056 | B43: 45056 | C43: BY TRANSFER-INB -For 19260165-- | D43: 6504223720CTW9833700 TRANSFER FROM 4 | E43: 0 | F43: 24788.72 | G43: 53820.61 | H43: SBI 3479 | I43: =G42+F43-E43-G43 -> 0 | J43: =A43 -> 45056 | K43: =C43 -> BY TRANSFER-INB -For 19260165-- | L43: =D43 -> 6504223720CTW9833700 TRANSFER FROM 4 | M43: =E43 -> 0 | N43: =F43 -> 24788.72 | O43: =G43 -> 53820.61 | P43: =H43 -> SBI 3479
A44: 45061 | B44: 45061 | C44: BY TRANSFER-INB -For 19260165-- | D44: 6504374486CTX0412280 TRANSFER FROM 4 | E44: 0 | F44: 7543.98 | G44: 61364.59 | H44: SBI 3479 | I44: =G43+F44-E44-G44 -> 0 | J44: =A44 -> 45061 | K44: =C44 -> BY TRANSFER-INB -For 19260165-- | L44: =D44 -> 6504374486CTX0412280 TRANSFER FROM 4 | M44: =E44 -> 0 | N44: =F44 -> 7543.98 | O44: =G44 -> 61364.59 | P44: =H44 -> SBI 3479
A45: 45062 | B45: 45062 | C45: TO TRANSFER-INB SBICARD FOR BILLDESK SBICARD Payments-- | D45: YSBI1891515209IGAPPCVJO4 TRANSFER TO | E45: 34058 | F45: 0 | G45: 27306.59 | H45: SBI 3479 | I45: =G44+F45-E45-G45 -> 0 | J45: =A45 -> 45062 | K45: =C45 -> TO TRANSFER-INB SBICARD FOR BILLDESK SBICARD Payments-- | L45: =D45 -> YSBI1891515209IGAPPCVJO4 TRANSFER TO | M45: =E45 -> 34058 | N45: =F45 -> 0 | O45: =G45 -> 27306.59 | P45: =H45 -> SBI 3479
A46: 45065 | B46: 45065 | C46: TO TRANSFER-ForTrading-- | D46: TRANSFER TO 31842374252 | E46: 15000 | F46: 0 | G46: 12306.59 | H46: SBI 3479 | I46: =G45+F46-E46-G46 -> 0 | J46: =A46 -> 45065 | K46: =C46 -> TO TRANSFER-ForTrading-- | L46: =D46 -> TRANSFER TO 31842374252 | M46: =E46 -> 15000 | N46: =F46 -> 0 | O46: =G46 -> 12306.59 | P46: =H46 -> SBI 3479
... A67: 45092 | B67: 45092 | C67: TO TRANSFER-ForTrading-- | D67: TRANSFER TO 41128839515 | E67: 9775.42 | F67: 0 | G67: 75050.01 | H67: SBI 3479 | I67: =G66+F67-E67-G67 -> 0 | J67: =A67 -> 45092 | K67: =C67 -> TO TRANSFER-ForTrading-- | L67: =D67 -> TRANSFER TO 41128839515 | M67: =E67 -> 9775.42 | N67: =F67 -> 0 | O67: =G67 -> 75050.01 | P67: =H67 -> SBI 3479
A68: 45093 | B68: 45093 | C68: BULK POSTING-ACHCr UTIB00862000018061 IIL FINAL 2022-- | E68: 0 | F68: 600 | G68: 75650.01 | H68: SBI 3479 | I68: =G67+F68-E68-G68 -> 0 | J68: =A68 -> 45093 | K68: =C68 -> BULK POSTING-ACHCr UTIB00862000018061 IIL FINAL 2022-- | L68: =D68 -> 0 | M68: =E68 -> 0 | N68: =F68 -> 600 | O68: =G68 -> 75650.01 | P68: =H68 -> SBI 3479
A69: 45097 | B69: 45097 | C69: TO TRANSFER-INB SBICARD FOR BILLDESK SBICARD Payments-- | D69: YSBI1955450045IGAPTJWVV9 TRANSFER TO | E69: 22004 | F69: 0 | G69: 53646.01 | H69: SBI 3479 | I69: =G68+F69-E69-G69 -> 0 | J69: =A69 -> 45097 | K69: =C69 -> TO TRANSFER-INB SBICARD FOR BILLDESK SBICARD Payments-- | L69: =D69 -> YSBI1955450045IGAPTJWVV9 TRANSFER TO | M69: =E69 -> 22004 | N69: =F69 -> 0 | O69: =G69 -> 53646.01 | P69: =H69 -> SBI 3479
A70: 45101 | B70: 45101 | C70: BY TRANSFER-INB -For 19260165-- | D70: 6505821497CTX5583074 TRANSFER FROM 4 | E70: 0 | F70: 15281.68 | G70: 68927.69 | H70: SBI 3479 | I70: =G69+F70-E70-G70 -> 0 | J70: =A70 -> 45101 | K70: =C70 -> BY TRANSFER-INB -For 19260165-- | L70: =D70 -> 6505821497CTX5583074 TRANSFER FROM 4 | M70: =E70 -> 0 | N70: =F70 -> 15281.68 | O70: =G70 -> 68927.69 | P70: =H70 -> SBI 3479
A71: 45102 | B71: 45102 | C71: TO TRANSFER-INB Payment towards loan repayment-- | D71: IIB8695782 TRANSFER TO 32718635441 | E71: 40000 | F71: 0 | G71: 28927.69 | H71: SBI 3479 | I71: =G70+F71-E71-G71 -> 0 | J71: =A71 -> 45102 | K71: =C71 -> TO TRANSFER-INB Payment towards loan repayment-- | L71: =D71 -> IIB8695782 TRANSFER TO 32718635441 | M71: =E71 -> 40000 | N71: =F71 -> 0 | O71: =G71 -> 28927.69 | P71: =H71 -> SBI 3479
A72: 45102 | B72: 45102 | C72: CREDIT INTEREST--- | E72: 0 | F72: 231 | G72: 29158.69 | H72: SBI 3479 | I72: =G71+F72-E72-G72 -> 0 | J72: =A72 -> 45102 | K72: =C72 -> CREDIT INTEREST--- | L72: =D72 -> 0 | M72: =E72 -> 0 | N72: =F72 -> 231 | O72: =G72 -> 29158.69 | P72: =H72 -> SBI 3479
A73: 45105 | B73: 45105 | C73: BY TRANSFER-NEFT*KKBK0000958*KKBKH23179159219*MARUTI INTERIOR-- | D73: TRANSFER FROM 3199967044305 | E73: 0 | F73: 500 | G73: 29658.69 | H73: SBI 3479 | I73: =G72+F73-E73-G73 -> 0 | J73: =A73 -> 45105 | K73: =C73 -> BY TRANSFER-NEFT*KKBK0000958*KKBKH23179159219*MARUTI INTERIOR-- | L73: =D73 -> TRANSFER FROM 3199967044305 | M73: =E73 -> 0 | N73: =F73 -> 500 | O73: =G73 -> 29658.69 | P73: =H73 -> SBI 3479
A74: 45109 | B74: 45109 | C74: WITHDRAWAL TRANSFER--- | D74: TRANSFER TO 32718635441 | E74: 26595 | F74: 0 | G74: 3063.69 | H74: SBI 3479 | I74: =G73+F74-E74-G74 -> 0 | J74: =A74 -> 45109 | K74: =C74 -> WITHDRAWAL TRANSFER--- | L74: =D74 -> TRANSFER TO 32718635441 | M74: =E74 -> 26595 | N74: =F74 -> 0 | O74: =G74 -> 3063.69 | P74: =H74 -> SBI 3479
A75: 45110 | B75: 45110 | C75: BULK POSTING-ACHCr UTIB01853000028122 TCS FINDIV 030-- | E75: 0 | F75: 600 | G75: 3663.69 | H75: SBI 3479 | I75: =G74+F75-E75-G75 -> 0 | J75: =A75 -> 45110 | K75: =C75 -> BULK POSTING-ACHCr UTIB01853000028122 TCS FINDIV 030-- | L75: =D75 -> 0 | M75: =E75 -> 0 | N75: =F75 -> 600 | O75: =G75 -> 3663.69 | P75: =H75 -> SBI 3479
A76: 45110 | B76: 45110 | C76: BULK POSTING-ACHCr ICIC02491000005006 INFOSYS LIMITE-- | E76: 0 | F76: 437.5 | G76: 4101.19 | H76: SBI 3479 | I76: =G75+F76-E76-G76 -> 0 | J76: =A76 -> 45110 | K76: =C76 -> BULK POSTING-ACHCr ICIC02491000005006 INFOSYS LIMITE-- | L76: =D76 -> 0 | M76: =E76 -> 0 | N76: =F76 -> 437.5 | O76: =G76 -> 4101.19 | P76: =H76 -> SBI 3479
A77: 45112 | B77: 45112 | C77: BY TRANSFER-INB -For 19260165-- | D77: 6506147038CTX6898368 TRANSFER FROM 4 | E77: 0 | F77: 10472.73 | G77: 14573.92 | H77: SBI 3479 | I77: =G76+F77-E77-G77 -> 0 | J77: =A77 -> 45112 | K77: =C77 -> BY TRANSFER-INB -For 19260165-- | L77: =D77 -> 6506147038CTX6898368 TRANSFER FROM 4 | M77: =E77 -> 0 | N77: =F77 -> 10472.73 | O77: =G77 -> 14573.92 | P77: =H77 -> SBI 3479
A78: 45115 | B78: 45115 | C78: TO TRANSFER-CMP SBI CAPS-- | D78: CMP00000000682469890AOJY240135 TRANS | E78: 84.96 | F78: 0 | G78: 14488.96 | H78: SBI 3479 | I78: =G77+F78-E78-G78 -> 0 | J78: =A78 -> 45115 | K78: =C78 -> TO TRANSFER-CMP SBI CAPS-- | L78: =D78 -> CMP00000000682469890AOJY240135 TRANS | M78: =E78 -> 84.96 | N78: =F78 -> 0 | O78: =G78 -> 14488.96 | P78: =H78 -> SBI 3479
A79: 45118 | B79: 45118 | C79: TO TRANSFER-ForTrading-- | D79: TRANSFER TO 31842374252 | E79: 1000 | F79: 0 | G79: 13488.96 | H79: SBI 3479 | I79: =G78+F79-E79-G79 -> 0 | J79: =A79 -> 45118 | K79: =C79 -> TO TRANSFER-ForTrading-- | L79: =D79 -> TRANSFER TO 31842374252 | M79: =E79 -> 1000 | N79: =F79 -> 0 | O79: =G79 -> 13488.96 | P79: =H79 -> SBI 3479
A80: 45120 | B80: 45120 | C80: TO TRANSFER-ForTrading-- | D80: TRANSFER TO 31842374252 | E80: 8344.24 | F80: 0 | G80: 5144.72 | H80: SBI 3479 | I80: =G79+F80-E80-G80 -> 0 | J80: =A80 -> 45120 | K80: =C80 -> TO TRANSFER-ForTrading-- | L80: =D80 -> TRANSFER TO 31842374252 | M80: =E80 -> 8344.24 | N80: =F80 -> 0 | O80: =G80 -> 5144.72 | P80: =H80 -> SBI 3479
A81: 45122 | B81: 45122 | C81: BY TRANSFER-INB Credit card payment-- | D81: IIB9347211 TRANSFER FROM 32718635441 | E81: 0 | F81: 50000 | G81: 55144.72 | H81: SBI 3479 | I81: =G80+F81-E81-G81 -> 0 | J81: =A81 -> 45122 | K81: =C81 -> BY TRANSFER-INB Credit card payment-- | L81: =D81 -> IIB9347211 TRANSFER FROM 32718635441 | M81: =E81 -> 0 | N81: =F81 -> 50000 | O81: =G81 -> 55144.72 | P81: =H81 -> SBI 3479
A82: 45122 | B82: 45122 | C82: TO TRANSFER-INB IRCTC Retiring Room Booki-- | D82: 6002554109IGAPWSDNF9 TRANSFER TO 317 | E82: 784 | F82: 0 | G82: 54360.72 | H82: SBI 3479 | I82: =G81+F82-E82-G82 -> 0 | J82: =A82 -> 45122 | K82: =C82 -> TO TRANSFER-INB IRCTC Retiring Room Booki-- | L82: =D82 -> 6002554109IGAPWSDNF9 TRANSFER TO 317 | M82: =E82 -> 784 | N82: =F82 -> 0 | O82: =G82 -> 54360.72 | P82: =H82 -> SBI 3479
A83: 45123 | B83: 45123 | C83: TO TRANSFER-INB Commission of IGAPWSDNF9--- | D83: IGAPWSDNF9ICZ8446575 TRANSFER TO 319 | E83: 11.8 | F83: 0 | G83: 54348.92 | H83: SBI 3479 | I83: =G82+F83-E83-G83 -> 0 | J83: =A83 -> 45123 | K83: =C83 -> TO TRANSFER-INB Commission of IGAPWSDNF9--- | L83: =D83 -> IGAPWSDNF9ICZ8446575 TRANSFER TO 319 | M83: =E83 -> 11.8 | N83: =F83 -> 0 | O83: =G83 -> 54348.92 | P83: =H83 -> SBI 3479
A84: 45125 | B84: 45125 | C84: BULK POSTING-ACHCr NACH00000000057636 MAWANA SUGARS-- | E84: 0 | F84: 1500 | G84: 55848.92 | H84: SBI 3479 | I84: =G83+F84-E84-G84 -> 0 | J84: =A84 -> 45125 | K84: =C84 -> BULK POSTING-ACHCr NACH00000000057636 MAWANA SUGARS-- | L84: =D84 -> 0 | M84: =E84 -> 0 | N84: =F84 -> 1500 | O84: =G84 -> 55848.92 | P84: =H84 -> SBI 3479
A85: 45129 | B85: 45129 | C85: BY TRANSFER-INB -For 19260165-- | D85: 6506899613CTX9331230 TRANSFER FROM 4 | E85: 0 | F85: 1735.8 | G85: 57584.72 | H85: SBI 3479 | I85: =G84+F85-E85-G85 -> 0 | J85: =A85 -> 45129 | K85: =C85 -> BY TRANSFER-INB -For 19260165-- | L85: =D85 -> 6506899613CTX9331230 TRANSFER FROM 4 | M85: =E85 -> 0 | N85: =F85 -> 1735.8 | O85: =G85 -> 57584.72 | P85: =H85 -> SBI 3479
A86: 45131 | B86: 45131 | C86: TO TRANSFER-INB SBICARD FOR BILLDESK SBICARD Payments-- | D86: YSBI2008918542IGAPXVZET8 TRANSFER TO | E86: 11996 | F86: 0 | G86: 45588.72 | H86: SBI 3479 | I86: =G85+F86-E86-G86 -> 0 | J86: =A86 -> 45131 | K86: =C86 -> TO TRANSFER-INB SBICARD FOR BILLDESK SBICARD Payments-- | L86: =D86 -> YSBI2008918542IGAPXVZET8 TRANSFER TO | M86: =E86 -> 11996 | N86: =F86 -> 0 | O86: =G86 -> 45588.72 | P86: =H86 -> SBI 3479
A87: 45132 | B87: 45132 | C87: TO TRANSFER-ForTrading-- | D87: TRANSFER TO 31842374252 | E87: 6660.9 | F87: 0 | G87: 38927.82 | H87: SBI 3479 | I87: =G86+F87-E87-G87 -> 0 | J87: =A87 -> 45132 | K87: =C87 -> TO TRANSFER-ForTrading-- | L87: =D87 -> TRANSFER TO 31842374252 | M87: =E87 -> 6660.9 | N87: =F87 -> 0 | O87: =G87 -> 38927.82 | P87: =H87 -> SBI 3479
A88: 45138 | B88: 45138 | C88: BY TRANSFER-INB -For 19260165-- | D88: 6507302733CTY0446779 TRANSFER FROM 4 | E88: 0 | F88: 4020.82 | G88: 42948.64 | H88: SBI 3479 | I88: =G87+F88-E88-G88 -> 0 | J88: =A88 -> 45138 | K88: =C88 -> BY TRANSFER-INB -For 19260165-- | L88: =D88 -> 6507302733CTY0446779 TRANSFER FROM 4 | M88: =E88 -> 0 | N88: =F88 -> 4020.82 | O88: =G88 -> 42948.64 | P88: =H88 -> SBI 3479
A89: 45139 | B89: 45139 | C89: BY TRANSFER-INB Deposit / Investment-- | D89: IIB9788460 TRANSFER FROM 32718635441 | E89: 0 | F89: 200000 | G89: 242948.64 | H89: SBI 3479 | I89: =G88+F89-E89-G89 -> 0 | J89: =A89 -> 45139 | K89: =C89 -> BY TRANSFER-INB Deposit / Investment-- | L89: =D89 -> IIB9788460 TRANSFER FROM 32718635441 | M89: =E89 -> 0 | N89: =F89 -> 200000 | O89: =G89 -> 242948.64 | P89: =H89 -> SBI 3479
A90: 45139 | B90: 45139 | C90: TO TRANSFER-INB NEFT UTR NO: SBIN123213509185--Ajay Kumar Gupta | D90: NEFT INB: IRW7094432 / Ajay Kumar Gupta | E90: 50000 | F90: 0 | G90: 192948.64 | H90: SBI 3479 | I90: =G89+F90-E90-G90 -> 0 | J90: =A90 -> 45139 | K90: =C90 -> TO TRANSFER-INB NEFT UTR NO: SBIN123213509185--Ajay Kumar Gupta | L90: =D90 -> NEFT INB: IRW7094432 / Ajay Kumar Gupta | M90: =E90 -> 50000 | N90: =F90 -> 0 | O90: =G90 -> 192948.64 | P90: =H90 -> SBI 3479
A91: 45139 | B91: 45139 | C91: BY TRANSFER-INB -For 19260165-- | D91: 6507355775CTY0616825 TRANSFER FROM 4 | E91: 0 | F91: 6826.36 | G91: 199775 | H91: SBI 3479 | I91: =G90+F91-E91-G91 -> 0 | J91: =A91 -> 45139 | K91: =C91 -> BY TRANSFER-INB -For 19260165-- | L91: =D91 -> 6507355775CTY0616825 TRANSFER FROM 4 | M91: =E91 -> 0 | N91: =F91 -> 6826.36 | O91: =G91 -> 199775 | P91: =H91 -> SBI 3479
A92: 45140 | B92: 45140 | C92: WITHDRAWAL TRANSFER--- | D92: TRANSFER TO 32718635441 | E92: 26595 | F92: 0 | G92: 173180 | H92: SBI 3479 | I92: =G91+F92-E92-G92 -> 0 | J92: =A92 -> 45140 | K92: =C92 -> WITHDRAWAL TRANSFER--- | L92: =D92 -> TRANSFER TO 32718635441 | M92: =E92 -> 26595 | N92: =F92 -> 0 | O92: =G92 -> 173180 | P92: =H92 -> SBI 3479
A93: 45141 | B93: 45141 | C93: BULK POSTING-ACHCr HDFC01160000010513 PaushakDiv2022-- | E93: 0 | F93: 560 | G93: 173740 | H93: SBI 3479 | I93: =G92+F93-E93-G93 -> 0 | J93: =A93 -> 45141 | K93: =C93 -> BULK POSTING-ACHCr HDFC01160000010513 PaushakDiv2022-- | L93: =D93 -> 0 | M93: =E93 -> 0 | N93: =F93 -> 560 | O93: =G93 -> 173740 | P93: =H93 -> SBI 3479
A94: 45141 | B94: 45141 | C94: TO TRANSFER-ForTrading-- | D94: TRANSFER TO 41128839515 | E94: 2783.24 | F94: 0 | G94: 170956.76 | H94: SBI 3479 | I94: =G93+F94-E94-G94 -> 0 | J94: =A94 -> 45141 | K94: =C94 -> TO TRANSFER-ForTrading-- | L94: =D94 -> TRANSFER TO 41128839515 | M94: =E94 -> 2783.24 | N94: =F94 -> 0 | O94: =G94 -> 170956.76 | P94: =H94 -> SBI 3479
A95: 45145 | B95: 45145 | C95: BULK POSTING-ACHCr UTIB01853000028122 TCS1STINTDIV07-- | E95: 0 | F95: 225 | G95: 171181.76 | H95: SBI 3479 | I95: =G94+F95-E95-G95 -> 0 | J95: =A95 -> 45145 | K95: =C95 -> BULK POSTING-ACHCr UTIB01853000028122 TCS1STINTDIV07-- | L95: =D95 -> 0 | M95: =E95 -> 0 | N95: =F95 -> 225 | O95: =G95 -> 171181.76 | P95: =H95 -> SBI 3479
A96: 45146 | B96: 45146 | C96: BY TRANSFER-INB -For 19260165-- | D96: 6507606618CTY1477227 TRANSFER FROM 4 | E96: 0 | F96: 6019.92 | G96: 177201.68 | H96: SBI 3479 | I96: =G95+F96-E96-G96 -> 0 | J96: =A96 -> 45146 | K96: =C96 -> BY TRANSFER-INB -For 19260165-- | L96: =D96 -> 6507606618CTY1477227 TRANSFER FROM 4 | M96: =E96 -> 0 | N96: =F96 -> 6019.92 | O96: =G96 -> 177201.68 | P96: =H96 -> SBI 3479
A97: 45146 | B97: 45146 | C97: BY TRANSFER-INB -For 19260165-- | D97: 6507655384CTY1639300 TRANSFER FROM 4 | E97: 0 | F97: 109.74 | G97: 177311.42 | H97: SBI 3479 | I97: =G96+F97-E97-G97 -> 0 | J97: =A97 -> 45146 | K97: =C97 -> BY TRANSFER-INB -For 19260165-- | L97: =D97 -> 6507655384CTY1639300 TRANSFER FROM 4 | M97: =E97 -> 0 | N97: =F97 -> 109.74 | O97: =G97 -> 177311.42 | P97: =H97 -> SBI 3479
A98: 45148 | B98: 45148 | C98: TO TRANSFER-INB IRCTC-RAILWAY TICKET BOOK Railway Ticket Booki-- | D98: 100004364001235IGAQACFDX7 TRANSFER T | E98: 1092.55 | F98: 0 | G98: 176218.87 | H98: SBI 3479 | I98: =G97+F98-E98-G98 -> 0 | J98: =A98 -> 45148 | K98: =C98 -> TO TRANSFER-INB IRCTC-RAILWAY TICKET BOOK Railway Ticket Booki-- | L98: =D98 -> 100004364001235IGAQACFDX7 TRANSFER T | M98: =E98 -> 1092.55 | N98: =F98 -> 0 | O98: =G98 -> 176218.87 | P98: =H98 -> SBI 3479
A99: 45148 | B99: 45148 | C99: BY TRANSFER-INB -For 19260165-- | D99: 6507697708CTY1817402 TRANSFER FROM 4 | E99: 0 | F99: 16490.51 | G99: 192709.38 | H99: SBI 3479 | I99: =G98+F99-E99-G99 -> 0 | J99: =A99 -> 45148 | K99: =C99 -> BY TRANSFER-INB -For 19260165-- | L99: =D99 -> 6507697708CTY1817402 TRANSFER FROM 4 | M99: =E99 -> 0 | N99: =F99 -> 16490.51 | O99: =G99 -> 192709.38 | P99: =H99 -> SBI 3479
A100: 45148 | B100: 45148 | C100: TO TRANSFER-ForTrading-- | D100: TRANSFER TO 31842374252 | E100: 555.86 | F100: 0 | G100: 192153.52 | H100: SBI 3479 | I100: =G99+F100-E100-G100 -> 0 | J100: =A100 -> 45148 | K100: =C100 -> TO TRANSFER-ForTrading-- | L100: =D100 -> TRANSFER TO 31842374252 | M100: =E100 -> 555.86 | N100: =F100 -> 0 | O100: =G100 -> 192153.52 | P100: =H100 -> SBI 3479
A101: 45149 | B101: 45149 | C101: TO TRANSFER-INB NEFT UTR NO: SBIN423223756583--Ajay Kumar Gupta | D101: NEFT INB: IRW7872614 / Ajay Kumar Gupta | E101: 150000 | F101: 0 | G101: 42153.52 | H101: SBI 3479 | I101: =G100+F101-E101-G101 -> 0 | J101: =A101 -> 45149 | K101: =C101 -> TO TRANSFER-INB NEFT UTR NO: SBIN423223756583--Ajay Kumar Gupta | L101: =D101 -> NEFT INB: IRW7872614 / Ajay Kumar Gupta | M101: =E101 -> 150000 | N101: =F101 -> 0 | O101: =G101 -> 42153.52 | P101: =H101 -> SBI 3479
A102: 45152 | B102: 45152 | C102: TO TRANSFER-ForTrading-- | D102: TRANSFER TO 31842374252 | E102: 19795.49 | F102: 0 | G102: 22358.03 | H102: SBI 3479 | I102: =G101+F102-E102-G102 -> 0 | J102: =A102 -> 45152 | K102: =C102 -> TO TRANSFER-ForTrading-- | L102: =D102 -> TRANSFER TO 31842374252 | M102: =E102 -> 19795.49 | N102: =F102 -> 0 | O102: =G102 -> 22358.03 | P102: =H102 -> SBI 3479
A103: 45160 | B103: 45160 | C103: TO TRANSFER-ForTrading-- | D103: TRANSFER TO 31842374252 | E103: 4.51 | F103: 0 | G103: 22353.52 | H103: SBI 3479 | I103: =G102+F103-E103-G103 -> 0 | J103: =A103 -> 45160 | K103: =C103 -> TO TRANSFER-ForTrading-- | L103: =D103 -> TRANSFER TO 31842374252 | M103: =E103 -> 4.51 | N103: =F103 -> 0 | O103: =G103 -> 22353.52 | P103: =H103 -> SBI 3479
A104: 45162 | B104: 45162 | C104: TO TRANSFER-ForTrading-- | D104: TRANSFER TO 41128839515 | E104: 327.52 | F104: 0 | G104: 22026 | H104: SBI 3479 | I104: =G103+F104-E104-G104 -> 0 | J104: =A104 -> 45162 | K104: =C104 -> TO TRANSFER-ForTrading-- | L104: =D104 -> TRANSFER TO 41128839515 | M104: =E104 -> 327.52 | N104: =F104 -> 0 | O104: =G104 -> 22026 | P104: =H104 -> SBI 3479
A105: 45163 | B105: 45163 | C105: BY TRANSFER-INB Deposit / Investment-- | D105: IIC0426902 TRANSFER FROM 32718635441 | E105: 0 | F105: 10000 | G105: 32026 | H105: SBI 3479 | I105: =G104+F105-E105-G105 -> 0 | J105: =A105 -> 45163 | K105: =C105 -> BY TRANSFER-INB Deposit / Investment-- | L105: =D105 -> IIC0426902 TRANSFER FROM 32718635441 | M105: =E105 -> 0 | N105: =F105 -> 10000 | O105: =G105 -> 32026 | P105: =H105 -> SBI 3479
A106: 45167 | B106: 45167 | C106: BY TRANSFER-INB -For 19260165-- | D106: 6508499164CTY4124307 TRANSFER FROM 4 | E106: 0 | F106: 195190.1 | G106: 227216.1 | H106: SBI 3479 | I106: =G105+F106-E106-G106 -> 0 | J106: =A106 -> 45167 | K106: =C106 -> BY TRANSFER-INB -For 19260165-- | L106: =D106 -> 6508499164CTY4124307 TRANSFER FROM 4 | M106: =E106 -> 0 | N106: =F106 -> 195190.1 | O106: =G106 -> 227216.1 | P106: =H106 -> SBI 3479
A107: 45170 | B107: 45170 | C107: BY TRANSFER-INB -For 19260165-- | D107: 6508650813CTY4556318 TRANSFER FROM 4 | E107: 0 | F107: 194689.11 | G107: 421905.21 | H107: SBI 3479 | I107: =G106+F107-E107-G107 -> 0 | J107: =A107 -> 45170 | K107: =C107 -> BY TRANSFER-INB -For 19260165-- | L107: =D107 -> 6508650813CTY4556318 TRANSFER FROM 4 | M107: =E107 -> 0 | N107: =F107 -> 194689.11 | O107: =G107 -> 421905.21 | P107: =H107 -> SBI 3479
... A121: 45183 | B121: 45183 | C121: BY TRANSFER-INB -For 19260165-- | D121: 6509369100CTY6450565 TRANSFER FROM 4 | E121: 0 | F121: 14953.38 | G121: 156892.35 | H121: SBI 3479 | I121: =G120+F121-E121-G121 -> 0 | J121: =A121 -> 45183 | K121: =C121 -> BY TRANSFER-INB -For 19260165-- | L121: =D121 -> 6509369100CTY6450565 TRANSFER FROM 4 | M121: =E121 -> 0 | N121: =F121 -> 14953.38 | O121: =G121 -> 156892.35 | P121: =H121 -> SBI 3479
A122: 45184 | B122: 45184 | C122: DEBIT-ATMCard AMC 652294*6987-- | E122: 147.5 | F122: 0 | G122: 156744.85 | H122: SBI 3479 | I122: =G121+F122-E122-G122 -> 0 | J122: =A122 -> 45184 | K122: =C122 -> DEBIT-ATMCard AMC 652294*6987-- | L122: =D122 -> 0 | M122: =E122 -> 147.5 | N122: =F122 -> 0 | O122: =G122 -> 156744.85 | P122: =H122 -> SBI 3479
A123: 45187 | B123: 45187 | C123: BY TRANSFER-INB -For 19260165-- | D123: 6509578041CTY7160595 TRANSFER FROM 4 | E123: 0 | F123: 10732.31 | G123: 167477.16 | H123: SBI 3479 | I123: =G122+F123-E123-G123 -> 0 | J123: =A123 -> 45187 | K123: =C123 -> BY TRANSFER-INB -For 19260165-- | L123: =D123 -> 6509578041CTY7160595 TRANSFER FROM 4 | M123: =E123 -> 0 | N123: =F123 -> 10732.31 | O123: =G123 -> 167477.16 | P123: =H123 -> SBI 3479
A124: 45188 | B124: 45188 | C124: TO TRANSFER-INB SBICARD FOR BILLDESK SBICARD Payments-- | D124: YSBI2082212999IGAQEWBTN6 TRANSFER TO | E124: 104832 | F124: 0 | G124: 62645.16 | H124: SBI 3479 | I124: =G123+F124-E124-G124 -> 0 | J124: =A124 -> 45188 | K124: =C124 -> TO TRANSFER-INB SBICARD FOR BILLDESK SBICARD Payments-- | L124: =D124 -> YSBI2082212999IGAQEWBTN6 TRANSFER TO | M124: =E124 -> 104832 | N124: =F124 -> 0 | O124: =G124 -> 62645.16 | P124: =H124 -> SBI 3479
A125: 45194 | B125: 45194 | C125: CREDIT INTEREST--- | E125: 0 | F125: 540 | G125: 63185.16 | H125: SBI 3479 | I125: =G124+F125-E125-G125 -> 0 | J125: =A125 -> 45194 | K125: =C125 -> CREDIT INTEREST--- | L125: =D125 -> 0 | M125: =E125 -> 0 | N125: =F125 -> 540 | O125: =G125 -> 63185.16 | P125: =H125 -> SBI 3479
A126: 45196 | B126: 45196 | C126: BULK POSTING-ACHCr NACH00000000061871 MIL Fin Div 20-- | E126: 0 | F126: 210 | G126: 63395.16 | H126: SBI 3479 | I126: =G125+F126-E126-G126 -> 0 | J126: =A126 -> 45196 | K126: =C126 -> BULK POSTING-ACHCr NACH00000000061871 MIL Fin Div 20-- | L126: =D126 -> 0 | M126: =E126 -> 0 | N126: =F126 -> 210 | O126: =G126 -> 63395.16 | P126: =H126 -> SBI 3479
A127: 45200 | B127: 45200 | C127: ATM WDL-ATM CASH 9577 SBI SHIVAJI NAGAR ATM NASHIK-- | E127: 5000 | F127: 0 | G127: 58395.16 | H127: SBI 3479 | I127: =G126+F127-E127-G127 -> 0 | J127: =A127 -> 45200 | K127: =C127 -> ATM WDL-ATM CASH 9577 SBI SHIVAJI NAGAR ATM NASHIK-- | L127: =D127 -> 0 | M127: =E127 -> 5000 | N127: =F127 -> 0 | O127: =G127 -> 58395.16 | P127: =H127 -> SBI 3479
A128: 45201 | B128: 45201 | C128: WITHDRAWAL TRANSFER--- | D128: TRANSFER TO 32718635441 | E128: 26595 | F128: 0 | G128: 31800.16 | H128: SBI 3479 | I128: =G127+F128-E128-G128 -> 0 | J128: =A128 -> 45201 | K128: =C128 -> WITHDRAWAL TRANSFER--- | L128: =D128 -> TRANSFER TO 32718635441 | M128: =E128 -> 26595 | N128: =F128 -> 0 | O128: =G128 -> 31800.16 | P128: =H128 -> SBI 3479
A129: 45203 | B129: 45203 | C129: BULK POSTING-ACHCr NACH00000000025450 JRAL Fin Div 2-- | E129: 0 | F129: 384 | G129: 32184.16 | H129: SBI 3479 | I129: =G128+F129-E129-G129 -> 0 | J129: =A129 -> 45203 | K129: =C129 -> BULK POSTING-ACHCr NACH00000000025450 JRAL Fin Div 2-- | L129: =D129 -> 0 | M129: =E129 -> 0 | N129: =F129 -> 384 | O129: =G129 -> 32184.16 | P129: =H129 -> SBI 3479
A130: 45205 | B130: 45205 | C130: BULK POSTING-ACHCr ICIC03217000005737 BRL FIN DIV 22-- | E130: 0 | F130: 13.5 | G130: 32197.66 | H130: SBI 3479 | I130: =G129+F130-E130-G130 -> 0 | J130: =A130 -> 45205 | K130: =C130 -> BULK POSTING-ACHCr ICIC03217000005737 BRL FIN DIV 22-- | L130: =D130 -> 0 | M130: =E130 -> 0 | N130: =F130 -> 13.5 | O130: =G130 -> 32197.66 | P130: =H130 -> SBI 3479
A131: 45205 | B131: 45205 | C131: BY TRANSFER-INB -For 19260165-- | D131: 6510350270CTY9505871 TRANSFER FROM 4 | E131: 0 | F131: 10636.95 | G131: 42834.61 | H131: SBI 3479 | I131: =G130+F131-E131-G131 -> 0 | J131: =A131 -> 45205 | K131: =C131 -> BY TRANSFER-INB -For 19260165-- | L131: =D131 -> 6510350270CTY9505871 TRANSFER FROM 4 | M131: =E131 -> 0 | N131: =F131 -> 10636.95 | O131: =G131 -> 42834.61 | P131: =H131 -> SBI 3479
A132: 45211 | B132: 45211 | C132: TO TRANSFER-INB SBICARD FOR BILLDESK SBICARD Payments-- | D132: YSBI2108669698IGAQHPMIQ8 TRANSFER TO | E132: 14636 | F132: 0 | G132: 28198.61 | H132: SBI 3479 | I132: =G131+F132-E132-G132 -> 0 | J132: =A132 -> 45211 | K132: =C132 -> TO TRANSFER-INB SBICARD FOR BILLDESK SBICARD Payments-- | L132: =D132 -> YSBI2108669698IGAQHPMIQ8 TRANSFER TO | M132: =E132 -> 14636 | N132: =F132 -> 0 | O132: =G132 -> 28198.61 | P132: =H132 -> SBI 3479
A133: 45211 | B133: 45211 | C133: TO TRANSFER-ForTrading-- | D133: TRANSFER TO 41128839515 | E133: 7092.45 | F133: 0 | G133: 21106.16 | H133: SBI 3479 | I133: =G132+F133-E133-G133 -> 0 | J133: =A133 -> 45211 | K133: =C133 -> TO TRANSFER-ForTrading-- | L133: =D133 -> TRANSFER TO 41128839515 | M133: =E133 -> 7092.45 | N133: =F133 -> 0 | O133: =G133 -> 21106.16 | P133: =H133 -> SBI 3479
...

Sheet Conso
A1: Ajay Kumar Gupta | D1: ='HDFC 5930'!D15 -> 7665777.6 | E1: ='HDFC 5930'!E15 -> 7690470 | L1: Earnings | N1: Amount | O1: Recoveries | P1: Amount
A2: Account of Statements from 01-04-2023 to 31-03-2024 | D2: =SUBTOTAL(9,D4:D1632) -> 80000 | E2: =SUBTOTAL(9,E4:E1632) -> 0 | F2: =D2-E2 -> 80000 | L2: Salary JUL AUG | M2: 14 Days | N2: 129902 | O2: PF | P2: 10663
A3: TX Date | B3: Particulars | C3: Ref | D3: DR | E3: CR | F3: Balance | G3: Kya hai? | H3: Account No | L3: LTA | M3: 2022-23 | N3: 10726 | O3: Prof Tax | P3: 200
A4: 45017 | B4: BY TRANSFER-INB Payment towards loan repayment-- | C4: IIB6318597 TRANSFER FROM 32718635441 | D4: 0 | E4: 25000 | F4: 29724.4 | G4: Contra | H4: SBI 3479 | L4: Leave Encashment | M4: 97 Days | N4: 822114 | O4: Income Tax (Tentative) | P4: 92321
A5: 45017 | B5: TO TRANSFER-INB Payment towards loan repayment-- | C5: IIB6318597 TRANSFER TO 20010697703 | D5: 25000 | E5: 0 | F5: -332107.37 | G5: Contra | H5: SBI 5441 | M5: 59.5 Days | N5: 210119 | O5: Extra Availed Leave | P5: 14429
A6: 45018 | B6: UPI/P2A/345797693295/SACHIN BA/Kotak Mah/Diesal | D6: 3400 | E6: 0 | F6: 184700.16 | G6: Personal | H6: AXIS 3167 | L6: Bonus | M6: 2022-23 | N6: 416051 | O6: Cash Advance | P6: 283333
A7: 45018 | B7: UPI/P2M/345789552921/MANISH HE/Yes Bank /Amle | D7: 230 | E7: 0 | F7: 184470.16 | G7: Personal | H7: AXIS 3167 | L7: CAR Reimbursement | M7: 2023-24 | N7: 134178 | O7: Uniform Charges | P7: 4299
A8: 45018 | B8: UPI/P2M/345726651875/SAGAR SWE/Yes Bank /sweets | D8: 416 | E8: 0 | F8: 184054.16 | G8: Personal | H8: AXIS 3167 | L8: Gratuity | N8: 1589138
A9: 45018 | B9: INB/NEFT/AXIR230915974036/Ajay Kum/STATE B/Housin | D9: 100000 | E9: 0 | F9: 84054.16 | G9: Contra | H9: AXIS 3167 | N9: =SUM(N2:N6) -> 1588912 | P9: =SUM(P2:P8) -> 405245
A10: 45018 | B10: WITHDRAWAL TRANSFER--- | C10: TRANSFER TO 32718635441 | D10: 26595 | E10: 0 | F10: 3129.4 | G10: Contra | H10: SBI 3479
A11: 45018 | B11: BY TRANSFER-NEFT*UTIB0000115*AXIR230915974036*AJAY KUMAR GUPTA-- | C11: TRANSFER FROM 3199964044308 | D11: 0 | E11: 100000 | F11: -232107.37 | G11: Contra | H11: SBI 5441 | O11: Holded Amount | P11: 328745
A12: 45018 | B12: DEPOSIT TRANSFER--- | C12: TRANSFER FROM 20010697703 | D12: 0 | E12: 26595 | F12: -205512.37 | G12: Contra | H12: SBI 5441 | O12: As per statement | P12: =N9-P9+P11 -> 1512412
A13: 45019 | B13: NET PI TO HSL SEC A/C 347707-00602340029392 | D13: 881.67 | E13: 0 | F13: 31526.84 | G13: HSL | H13: HDFC 5930 | N13: Full and Final | O13: Actual In bank | P13: =SUMIF($G:$G,N13,$E:$E) -> 1512412
A14: 45019 | B14: NET PO FROM HSL A/C 347707-00602340029392 | D14: 0 | E14: 3799.47 | F14: 35326.31 | G14: HSL | H14: HDFC 5930 | O14: Diff | P14: =P13-P12 -> 0
A15: 45020 | B15: UPI/P2M/346037289751/SHAGUN TR/Yes Bank /Ice cre | D15: 115 | E15: 0 | F15: 83939.16 | G15: Personal | H15: AXIS 3167
A16: 45020 | B16: ACH D- TP ACH INVESTOCAFE-1111407380 | D16: 1500 | E16: 0 | F16: 33826.31 | G16: SIP | H16: HDFC 5930
A17: 45020 | B17: ACH D- TP ACH INVESTOCAFE-1111407381 | D17: 2000 | E17: 0 | F17: 31826.31 | G17: SIP | H17: HDFC 5930
A18: 45020 | B18: ACH D- TP ACH INVESTOCAFE-1111407382 | D18: 2000 | E18: 0 | F18: 29826.31 | G18: SIP | H18: HDFC 5930
A19: 45021 | B19: NET PI TO HSL SEC A/C 347707-00602340029392 | D19: 591.52 | E19: 0 | F19: 29234.79 | G19: HSL | H19: HDFC 5930
A20: 45021 | B20: NET PI TO HSL SEC A/C 347707-00602340029392 | D20: 15603.7 | E20: 0 | F20: 13631.09 | G20: HSL | H20: HDFC 5930
A21: 45022 | B21: NET PO FROM HSL A/C 347707-00602340029392 | D21: 0 | E21: 7926.99 | F21: 21558.08 | G21: HSL | H21: HDFC 5930
A22: 45022 | B22: NET PI TO HSL SEC A/C 347707-00602340029392 | D22: 288.07 | E22: 0 | F22: 21270.01 | G22: HSL | H22: HDFC 5930
A23: 45022 | B23: NET PO FROM HSL A/C 347707-00602340029392 | D23: 0 | E23: 661.41 | F23: 21931.42 | G23: HSL | H23: HDFC 5930
A24: 45022 | B24: BY TRANSFER-INB -For 19260165-- | C24: 6503260805CTW5438690 TRANSFER FROM 4 | D24: 0 | E24: 1664.77 | F24: 4794.17 | G24: Suspense | H24: SBI 3479
A25: 45023 | B25: BRN-PYMT-CARD-4111460000883615 | D25: 10917.37 | E25: 0 | F25: 73021.79 | G25: Credit card | H25: AXIS 3167
A26: 45024 | B26: ACH D- TP ACH INVESTOCAFE-1116440799 | D26: 2000 | E26: 0 | F26: 19931.42 | G26: SIP | H26: HDFC 5930
A27: 45024 | B27: ACH D- TP ACH INVESTOCAFE-1116440800 | D27: 2500 | E27: 0 | F27: 17431.42 | G27: SIP | H27: HDFC 5930
A28: 45026 | B28: O/MF-HSBC MF -O416 -000000101236 | D28: 4000 | E28: 0 | F28: 13431.42 | G28: SIP | H28: HDFC 5930
A29: 45026 | B29: NET PAYIN TO BSE MF A/C -57500000389146- FROM A/C -01671000085930- UCC -347707-57500000389146 | D29: 3000 | E29: 0 | F29: 10431.42 | G29: SIP | H29: HDFC 5930
A30: 45026 | B30: NET PAYIN TO BSE MF A/C -57500000389146- FROM A/C -01671000085930- UCC -347707-57500000389146 | D30: 3000 | E30: 0 | F30: 7431.42 | G30: SIP | H30: HDFC 5930
A31: 45026 | B31: NET PO FROM HSL A/C 347707-00602340029392 | D31: 0 | E31: 19098.12 | F31: 26529.54 | G31: HSL | H31: HDFC 5930
A32: 45026 | B32: ACH C- STEEL AUTHORITY OF I-000000000000 | D32: 0 | E32: 100 | F32: 26629.54 | G32: Dividend Income | H32: HDFC 5930
A33: 45026 | B33: NET PI TO HSL SEC A/C 347707-00602340029392 | D33: 1153.56 | E33: 0 | F33: 25475.98 | G33: HSL | H33: HDFC 5930
A34: 45026 | B34: NET PI TO HSL SEC A/C 347707-00602340029392 | D34: 2752.88 | E34: 0 | F34: 22723.1 | G34: HSL | H34: HDFC 5930
A35: 45026 | B35: NET PO FROM HSL A/C 347707-00602340029392 | D35: 0 | E35: 4701.48 | F35: 27424.58 | G35: HSL | H35: HDFC 5930
A36: 45027 | B36: NET PI TO HSL SEC A/C 347707-00602340029392 | D36: 287.81 | E36: 0 | F36: 27136.77 | G36: HSL | H36: HDFC 5930
A37: 45027 | B37: NET PO FROM HSL A/C 347707-00602340029392 | D37: 0 | E37: 1542.96 | F37: 28679.73 | G37: HSL | H37: HDFC 5930
A38: 45027 | B38: BY TRANSFER-INB -For 19260165-- | C38: 6503375120CTW5943163 TRANSFER FROM 4 | D38: 0 | E38: 290.28 | F38: 5084.45 | G38: Suspense | H38: SBI 3479
A39: 45027 | B39: BY TRANSFER-INB -For 19260165-- | C39: 6503407916CTW6110905 TRANSFER FROM 4 | D39: 0 | E39: 173592.01 | F39: 178676.46 | G39: Suspense | H39: SBI 3479
A40: 45028 | B40: NET PI TO HSL SEC A/C 347707-00602340029392 | D40: 288.57 | E40: 0 | F40: 28391.16 | G40: HSL | H40: HDFC 5930
A41: 45028 | B41: NET PO FROM HSL A/C 347707-00602340029392 | D41: 0 | E41: 6276.96 | F41: 34668.12 | G41: HSL | H41: HDFC 5930
A42: 45028 | B42: BULK POSTING-ACHCr HDFC01984000016202 DWARIKESH INTD-- | C42: 0 | D42: 0 | E42: 1200 | F42: 179876.46 | G42: Dividend Income | H42: SBI 3479
A43: 45029 | B43: DEPOSITORY CHARGES MAR23 - 40227714 | D43: 660.8 | E43: 0 | F43: 34007.32 | G43: Bank Charges | H43: HDFC 5930
A44: 45029 | B44: NET PI TO HSL SEC A/C 347707-00602340029392 | D44: 291.66 | E44: 0 | F44: 33715.66 | G44: HSL | H44: HDFC 5930
A45: 45029 | B45: TO TRANSFER-SBILT13042023084220295270-Loan repayment-- | C45: TRANSFER TO 32718635441 | D45: 50000 | E45: 0 | F45: 129876.46 | G45: Contra | H45: SBI 3479
A46: 45029 | B46: BY TRANSFER-SBILT13042023084220295270-Loan repayment-- | C46: TRANSFER FROM 20010697703 | D46: 0 | E46: 50000 | F46: -155512.37 | G46: Contra | H46: SBI 5441
A47: 45030 | B47: NET PI TO HSL SEC A/C 347707-00602340029392 | D47: 32591.86 | E47: 0 | F47: 1123.8 | G47: HSL | H47: HDFC 5930
A48: 45030 | B48: NET PO FROM HSL A/C 347707-00602340029392 | D48: 0 | E48: 9620.14 | F48: 10743.94 | G48: HSL | H48: HDFC 5930
A49: 45031 | B49: TO TRANSFER-INB SBICARD FOR BILLDESK SBICARD Payments-- | C49: YSBI1843207721IGAPLILQC0 TRANSFER TO | D49: 4502 | E49: 0 | F49: 125374.46 | G49: Credit card | H49: SBI 3479
A50: 45031 | B50: TO TRANSFER-INB Payment towards loan repayment-- | C50: IIB6794633 TRANSFER TO 32718635441 | D50: 100000 | E50: 0 | F50: 25374.46 | G50: Contra | H50: SBI 3479
A51: 45031 | B51: BY TRANSFER-INB Payment towards loan repayment-- | C51: IIB6794633 TRANSFER FROM 20010697703 | D51: 0 | E51: 100000 | F51: -55512.37 | G51: Contra | H51: SBI 5441
A52: 45033 | B52: NET PAYIN TO BSE MF A/C -57500000389146- FROM A/C -01671000085930- UCC -347707-57500000389146 | D52: 3000 | E52: 0 | F52: 7743.94 | G52: SIP | H52: HDFC 5930
A53: 45033 | B53: ACH D- TP ACH INVESTOCAFE-1121518334 | D53: 1500 | E53: 0 | F53: 6243.94 | G53: SIP | H53: HDFC 5930
A54: 45033 | B54: ACH D- TP ACH INVESTOCAFE-1121518335 | D54: 2000 | E54: 0 | F54: 4243.94 | G54: SIP | H54: HDFC 5930
A55: 45033 | B55: ACH D- TP ACH INVESTOCAFE-1121518336 | D55: 2000 | E55: 0 | F55: 2243.94 | G55: SIP | H55: HDFC 5930
A56: 45033 | B56: NET PI TO HSL SEC A/C 347707-00602340029392 | D56: 1115 | E56: 0 | F56: 1128.94 | G56: HSL | H56: HDFC 5930
A57: 45034 | B57: UPI/P2A/347498540738/SANGITA R/State Ban/Teeth i | D57: 15000 | E57: 0 | F57: 58021.79 | G57: UPI | H57: AXIS 3167
A58: 45034 | B58: ATM-CASH-AXIS/BPRH265601/7630/180423/NASHIK | D58: 20000 | E58: 0 | F58: 38021.79 | G58: Contra | H58: AXIS 3167
A59: 45034 | B59: CASH-AXIS-RVSL/180423/21:04 | D59: 0 | E59: 20000 | F59: 58021.79 | G59: Contra | H59: AXIS 3167
A60: 45034 | B60: ATM-CASH-AXIS/BPRH265601/7631/180423/NASHIK | D60: 10000 | E60: 0 | F60: 48021.79 | G60: Contra | H60: AXIS 3167
A61: 45034 | B61: CASH-AXIS-RVSL/180423/21:06 | D61: 0 | E61: 10000 | F61: 58021.79 | G61: Contra | H61: AXIS 3167
A62: 45034 | B62: NET PI TO HSL SEC A/C 347707-00602340029392 | D62: 774.94 | E62: 0 | F62: 354 | G62: HSL | H62: HDFC 5930
A63: 45034 | B63: NET PO FROM HSL A/C 347707-00602340029392 | D63: 0 | E63: 9335.99 | F63: 9689.99 | G63: HSL | H63: HDFC 5930
... A69: 45035 | B69: NET PI TO HSL SEC A/C 347707-00602340029392 | D69: 2092.4 | E69: 0 | F69: 48402.92 | G69: HSL | H69: HDFC 5930
A70: 45035 | B70: BY TRANSFER-INB -For 19260165-- | C70: 6503644322CTW7125901 TRANSFER FROM 4 | D70: 0 | E70: 3231.91 | F70: 28606.37 | G70: Suspense | H70: SBI 3479
A71: 45036 | B71: UPI/P2A/311016102687/AMOL DHON/Kotak Mah/Diesal | D71: 3450 | E71: 0 | F71: 54571.79 | G71: UPI | H71: AXIS 3167
A72: 45036 | B72: NET PO FROM HSL A/C 347707-00602340029392 | D72: 0 | E72: 7676.51 | F72: 56079.43 | G72: HSL | H72: HDFC 5930
A73: 45036 | B73: NET PI TO HSL SEC A/C 347707-00602340029392 | D73: 316.05 | E73: 0 | F73: 55763.38 | G73: HSL | H73: HDFC 5930
A74: 45036 | B74: NET PI TO HSL SEC A/C 347707-00602340029392 | D74: 3812.7 | E74: 0 | F74: 51950.68 | G74: HSL | H74: HDFC 5930
A75: 45036 | B75: NET PO FROM HSL A/C 347707-00602340029392 | D75: 0 | E75: 65.68 | F75: 52016.36 | G75: HSL | H75: HDFC 5930
A76: 45036 | B76: BY TRANSFER-INB -For 19260165-- | C76: 6503677670CTW7273599 TRANSFER FROM 4 | D76: 0 | E76: 15083.73 | F76: 43690.1 | G76: Suspense | H76: SBI 3479
A77: 45037 | B77: NET PAYIN TO BSE MF A/C -57500000389146- FROM A/C -01671000085930- UCC -347707-57500000389146 | D77: 3000 | E77: 0 | F77: 49016.36 | G77: SIP | H77: HDFC 5930
A78: 45037 | B78: ACH D- TP ACH INVESTOCAFE-1122935617 | D78: 2000 | E78: 0 | F78: 47016.36 | G78: SIP | H78: HDFC 5930
A79: 45037 | B79: ACH D- TP ACH INVESTOCAFE-1122935618 | D79: 2500 | E79: 0 | F79: 44516.36 | G79: SIP | H79: HDFC 5930
A80: 45037 | B80: NET PI TO HSL SEC A/C 347707-00602340029392 | D80: 314.17 | E80: 0 | F80: 44202.19 | G80: HSL | H80: HDFC 5930
A81: 45037 | B81: NET PI TO HSL SEC A/C 347707-00602340029392 | D81: 11742.09 | E81: 0 | F81: 32460.1 | G81: HSL | H81: HDFC 5930
A82: 45037 | B82: NET PO FROM HSL A/C 347707-00602340029392 | D82: 0 | E82: 8132.17 | F82: 40592.27 | G82: HSL | H82: HDFC 5930
A83: 45038 | B83: ATM-CASH-AXIS/SPCN11530/8513/220423/SINNAR | D83: 20000 | E83: 0 | F83: 34571.79 | G83: ATM Withdrawal | H83: AXIS 3167
A84: 45038 | B84: UPI/P2M/347819751793/MedPlus/Yes Bank /Payment | D84: 104.5 | E84: 0 | F84: 34467.29 | G84: UPI | H84: AXIS 3167
A85: 45039 | B85: BY TRANSFER-INB Payment towards loan repayment-- | C85: IIB6951402 TRANSFER FROM 32718635441 | D85: 0 | E85: 35000 | F85: 78690.1 | G85: Contra | H85: SBI 3479
A86: 45039 | B86: TO TRANSFER-INB Payment towards loan repayment-- | C86: IIB6951312 TRANSFER TO 32718635441 | D86: 70000 | E86: 0 | F86: 8690.1 | G86: Contra | H86: SBI 3479
A87: 45039 | B87: TO TRANSFER-INB Payment towards loan repayment-- | C87: IIB6951402 TRANSFER TO 20010697703 | D87: 35000 | E87: 0 | F87: -90512.37 | G87: Contra | H87: SBI 5441
A88: 45039 | B88: BY TRANSFER-INB Payment towards loan repayment-- | C88: IIB6951312 TRANSFER FROM 20010697703 | D88: 0 | E88: 70000 | F88: -20512.37 | G88: Contra | H88: SBI 5441
A89: 45040 | B89: NBSM/9904449/Maha Electricity(BILLDESK)/ | D89: 1670 | E89: 0 | F89: 32797.29 | G89: Electricity | H89: AXIS 3167
A90: 45040 | B90: UPI-SUNITA GUPTA-AJAYGUPTANEL1@YBL-HDFC0000167-348023861893-TRANSFER FROM AKG | D90: 5000 | E90: 0 | F90: 35592.27 | G90: Transfer to Sunita Gupta | H90: HDFC 5930
A91: 45040 | B91: NET PI TO HSL SEC A/C 347707-00602340029392 | D91: 925.14 | E91: 0 | F91: 34667.13 | G91: HSL | H91: HDFC 5930
A92: 45040 | B92: NET PI TO HSL SEC A/C 347707-00602340029392 | D92: 244.28 | E92: 0 | F92: 34422.85 | G92: HSL | H92: HDFC 5930
A93: 45040 | B93: NET PO FROM HSL A/C 347707-00602340029392 | D93: 0 | E93: 6888.24 | F93: 41311.09 | G93: HSL | H93: HDFC 5930
A94: 45041 | B94: BRN-SALARY PAYMENT-BY SALARY | D94: 0 | E94: 5000 | F94: 37797.29 | G94: Salary | H94: AXIS 3167
A95: 45041 | B95: UPI/P2A/348115026783/RAVINDRA /Bank of B/Chairs | D95: 6000 | E95: 0 | F95: 31797.29 | G95: UPI | H95: AXIS 3167
A96: 45041 | B96: O/MF-ICICI PRU MF -PSIG -000000101236 | D96: 3000 | E96: 0 | F96: 38311.09 | G96: SIP | H96: HDFC 5930
A97: 45041 | B97: NET PO FROM HSL A/C 347707-00602340029392 | D97: 0 | E97: 3690.26 | F97: 42001.35 | G97: HSL | H97: HDFC 5930
A98: 45041 | B98: NET PO FROM HSL A/C 347707-00602340029392 | D98: 0 | E98: 7612.22 | F98: 49613.57 | G98: HSL | H98: HDFC 5930
A99: 45041 | B99: BULK POSTING-ACHCr KKBK00188000018285 DHAMPUR SUGAR-- | C99: 0 | D99: 0 | E99: 300 | F99: 8990.1 | G99: Dividend Income | H99: SBI 3479
A100: 45042 | B100: .ACH DEBIT RETURN CHARGES 010323 010323-MIR2411185005629 | D100: 590 | E100: 0 | F100: 49023.57 | G100: Bank Charges | H100: HDFC 5930
A101: 45042 | B101: .ACH DEBIT RETURN CHARGES 010323 010323-MIR2411184909776 | D101: 649 | E101: 0 | F101: 48374.57 | G101: Bank Charges | H101: HDFC 5930
A102: 45042 | B102: .ACH DEBIT RETURN CHARGES 010323 010323-MIR2411184961200 | D102: 531 | E102: 0 | F102: 47843.57 | G102: Bank Charges | H102: HDFC 5930
A103: 45042 | B103: NET PI TO HSL SEC A/C 347707-00602340029392 | D103: 17070.22 | E103: 0 | F103: 30773.35 | G103: HSL | H103: HDFC 5930
A104: 45042 | B104: BY TRANSFER-INB Deposit / Investment-- | C104: IIB7031794 TRANSFER FROM 32718635441 | D104: 0 | E104: 10000 | F104: 18990.1 | G104: Contra | H104: SBI 3479
A105: 45042 | B105: TO TRANSFER-INB Deposit / Investment-- | C105: IIB7031794 TRANSFER TO 20010697703 | D105: 10000 | E105: 0 | F105: -30512.37 | G105: Contra | H105: SBI 5441
...

Sheet Bank Summary
B1: All Banks
B2: Ajay Gupta Bank Summary
B3: 01-04-2023 to 31-03-2024
B4: Particulars | C4: ₹ | D4: Particulars | E4: ₹
D5: Opening Balances | E5: =-I45 -> 73288.3
B7: Contra | C7: =SUMIFS(Conso!$E:$E,Conso!$G:$G,B7) -> 9230781 | D7: Contra | E7: =SUMIFS(Conso!$D:$D,Conso!$G:$G,D7) -> 9230781
B8: Personal | C8: =SUMIFS(Conso!$E:$E,Conso!$G:$G,B8) -> 17250 | D8: Personal | E8: =SUMIFS(Conso!$D:$D,Conso!$G:$G,D8) -> 37987.55
B9: HSL | C9: =SUMIFS(Conso!$E:$E,Conso!$G:$G,B9) -> 2756189 | D9: HSL | E9: =SUMIFS(Conso!$D:$D,Conso!$G:$G,D9) -> 4213437.4
B10: Suspense | C10: =SUMIFS(Conso!$E:$E,Conso!$G:$G,B10) -> 3244957.2 | D10: Suspense | E10: =SUMIFS(Conso!$D:$D,Conso!$G:$G,D10) -> 2091653.4
B11: Credit card | C11: =SUMIFS(Conso!$E:$E,Conso!$G:$G,B11) -> 0 | D11: Credit card | E11: =SUMIFS(Conso!$D:$D,Conso!$G:$G,D11) -> 421522.67
B12: Dividend Income | C12: =SUMIFS(Conso!$E:$E,Conso!$G:$G,B12) -> 43886.25 | D12: Dividend Income | E12: =SUMIFS(Conso!$D:$D,Conso!$G:$G,D12) -> 0
B13: Bank Charges | C13: =SUMIFS(Conso!$E:$E,Conso!$G:$G,B13) -> 0 | D13: Bank Charges | E13: =SUMIFS(Conso!$D:$D,Conso!$G:$G,D13) -> 23439.45
B14: UPI | C14: =SUMIFS(Conso!$E:$E,Conso!$G:$G,B14) -> 123680 | D14: UPI | E14: =SUMIFS(Conso!$D:$D,Conso!$G:$G,D14) -> 228355.95
B15: Payment from Aayush | C15: =SUMIFS(Conso!$E:$E,Conso!$G:$G,B15) -> 325000 | D15: Payment from Aayush | E15: =SUMIFS(Conso!$D:$D,Conso!$G:$G,D15) -> 20000
B16: ATM Withdrawal | C16: =SUMIFS(Conso!$E:$E,Conso!$G:$G,B16) -> 0 | D16: ATM Withdrawal | E16: =SUMIFS(Conso!$D:$D,Conso!$G:$G,D16) -> 225500
B17: Electricity | C17: =SUMIFS(Conso!$E:$E,Conso!$G:$G,B17) -> 0 | D17: Electricity | E17: =SUMIFS(Conso!$D:$D,Conso!$G:$G,D17) -> 19560
B18: Transfer to Sunita Gupta | C18: =SUMIFS(Conso!$E:$E,Conso!$G:$G,B18) -> 0 | D18: Transfer to Sunita Gupta | E18: =SUMIFS(Conso!$D:$D,Conso!$G:$G,D18) -> 1095000
... B38: Maintenance | C38: =SUMIFS(Conso!$E:$E,Conso!$G:$G,B38) -> 0 | D38: Maintenance | E38: =SUMIFS(Conso!$D:$D,Conso!$G:$G,D38) -> 15000
B39: Payment to sunita | C39: =SUMIFS(Conso!$E:$E,Conso!$G:$G,B39) -> 0 | D39: Payment to sunita | E39: =SUMIFS(Conso!$D:$D,Conso!$G:$G,D39) -> 100000 | I39: Opening Balance | J39: Closing Balance
B40: Payment from sunita | C40: =SUMIFS(Conso!$E:$E,Conso!$G:$G,B40) -> 100000 | D40: Payment from sunita | E40: =SUMIFS(Conso!$D:$D,Conso!$G:$G,D40) -> 0 | H40: AXIS | I40: ='AXIS 3167'!F14 -> 188100.16 | J40: ='AXIS 3167'!F267 -> 90615.86
C41: =SUMIFS(Conso!$E:$E,Conso!$G:$G,B41) -> 0 | D41: Advance Tax Payment | E41: =SUMIFS(Conso!$D:$D,Conso!$G:$G,D41) -> 18000 | H41: BOI | I41: ='BOI 6699'!H19 -> 8586 | J41: ='BOI 6699'!G26 -> 15725
D42: Closing Balances | E42: =C44-SUM(E5:E41) -> 232605.38 | F42: =J45 -> 212778.38 | G42: =E42-F42 -> 19827 | H42: HDFC | I42: ='HDFC 5930'!F15 -> 32408.51 | J42: ='HDFC 5930'!F1094 -> 37929.61
H43: SBI OD | I43: ='SBI OD 5441'!G18 -> -307107.37 | J43: ='SBI OD 5441'!G102 -> -195.37
C44: =SUM(C7:C43) -> 20585695 | E44: =SUM(E5:E43) -> 20585695 | G44: =C44-E44 -> 0 | H44: SBI BANK | I44: ='SBI Bank 3479'!G19 -> 4724.4 | J44: ='SBI Bank 3479'!G227 -> 68703.28
I45: =SUM(I40:I44) -> -73288.3 | J45: =SUM(J40:J44) -> 212778.38
I46: =E5+I45 -> 0
C50: =SUM(C7:C41) -> 20585695 | E50: =SUM(E7:E41) -> 20279801
C51: =Conso!E2 -> 0 | E51: =Conso!D2 -> 80000
C52: =C51-C50 -> -20585695 | E52: =E51-E50 -> -20199801
I55: =I45+C50-E50 -> 232605.38
I56: =I55-J45 -> 19827

Sheet Salary
C1: Taxable | D1: Taxable | E1: Taxable | F1: Taxable | G1: Taxable | H1: Taxable | I1: Taxable | J1: Taxable | L1: Taxable | U1: =SUM(U4:U8) -> 359852
C2: =SUBTOTAL(9,C4:C8) -> 892369.99 | D2: =SUBTOTAL(9,D4:D8) -> 356948 | E2: =SUBTOTAL(9,E4:E8) -> 50102.16 | F2: =SUBTOTAL(9,F4:F8) -> 858.19 | G2: =SUBTOTAL(9,G4:G8) -> 16685 | H2: =SUBTOTAL(9,H4:H8) -> 6674 | I2: =SUBTOTAL(9,I4:I8) -> 5362.71 | J2: =SUBTOTAL(9,J4:J8) -> 10726 | ... N2: =SUBTOTAL(9,N4:N8) -> 1589138 | P2: =SUBTOTAL(9,P4:P8) -> 1755777.1 | AB2: =SUBTOTAL(9,AB4:AB8) -> 915015.26
C3: Basic | D3: HRA | E3: Special Allowance | F3: Child Education Allow | G3: BF Basic Arrear | H3: BF HRA Arrear | I3: Other Allowance | J3: LTA | K3: Leave Encashment | L3: Bonus | M3: Car Reimb | N3: Gratuity | P3: Total Earnings | Q3: Total Earnings as per 26AS | S3: Ee PF contribution | T3: Prof Tax - split period | U3: TDS | V3: Round off | W3: Cf PF Monthly | X3: Reg. repayment (Advance) | Y3: Mess Deductions | Z3: Extra Availed leave | AA3: Uniform Charges | AB3: Total Deductions | AC3: Net Pay
B4: 45017 | C4: 195200 | D4: 78080 | E4: 11678 | F4: 200 | G4: 0 | H4: 0 | I4: 1250 | J4: 0 | K4: 0 | L4: 0 | M4: 0 | N4: 0 | O4: 6340 | P4: =SUM(C4:N4) -> 286408 | Q4: 292748 | R4: =Q4-P4 -> 6340 | S4: 23424 | T4: 200 | U4: 64038 | V4: -0.36 | W4: 0 | X4: 35416.67 | Y4: 440 | Z4: 0 | AA4: 0 | AB4: =SUM(S4:AA4) -> 123518.31 | AC4: =P4-AB4 -> 162889.69
B5: 45047 | C5: 211885 | D5: 84754 | E5: 11678 | F5: 200 | G5: =C5-C4 -> 16685 | H5: =D5-D4 -> 6674 | I5: 1250 | J5: 0 | K5: 0 | L5: 0 | M5: 0 | N5: 0 | O5: 6340 | P5: =SUM(C5:N5) -> 333126 | Q5: 339466 | R5: =Q5-P5 -> 6340 | S5: 25426 | T5: 200 | U5: 71988 | V5: 0.31 | W5: 2002 | X5: 35416.67 | Y5: 400 | Z5: 0 | AA5: 0 | AB5: =SUM(S5:AA5) -> 135432.98 | AC5: =P5-AB5 -> 197693.02
B6: 45078 | C6: 211885 | D6: 84754 | E6: 11678 | F6: 200 | G6: 0 | H6: 0 | I6: 1250 | J6: 0 | K6: 0 | L6: 0 | M6: 0 | N6: 0 | O6: 6340 | P6: =SUM(C6:N6) -> 309767 | Q6: 316107 | R6: =Q6-P6 -> 6340 | S6: 25426 | T6: 200 | U6: 71988 | V6: -0.02 | W6: 0 | X6: 35416.67 | Y6: 350 | Z6: 0 | AA6: 0 | AB6: =SUM(S6:AA6) -> 133380.65 | AC6: 0
B7: 45108 | C7: 184544.99 | D7: 73818 | E7: 10171.16 | F7: 174.19 | G7: 0 | H7: 0 | I7: 1088.71 | J7: 0 | K7: 0 | L7: 0 | M7: 0 | N7: 0 | O7: 6340 | P7: =SUM(C7:N7) -> 269797.05 | Q7: 276137 | R7: =Q7-P7 -> 6339.95 | S7: 22145 | T7: 200 | U7: 59517 | V7: -0.35 | W7: 0 | X7: 35416.67 | Y7: 160 | Z7: 0 | AA7: 0 | AB7: =SUM(S7:AA7) -> 117438.32 | AC7: 0
B8: 45139 | C8: 88855 | D8: 35542 | E8: 4897 | F8: 84 | G8: 0 | H8: 0 | I8: 524 | J8: 10726 | K8: =822114+210119 -> 1032233 | L8: 416051 | M8: 134178 | N8: 1589138 | P8: =SUM(C8:N8)-M8-N8-K8 -> 556679 | R8: =Q8-P8 -> -556679 | S8: =N16 -> 10663 | T8: =N17 -> 200 | U8: 92321 | V8: 0 | W8: 0 | X8: 283333 | Y8: 0 | Z8: 14429 | AA8: 4299 | AB8: =SUM(S8:AA8) -> 405245 | AC8: =P8-AB8+P6-AB6+P7-AB7+K8 -> 1512412.1
C9: =SUM(C4:C8) -> 892369.99 | D9: =SUM(D4:D8) -> 356948 | E9: =SUM(E4:E8) -> 50102.16 | F9: =SUM(F4:F8) -> 858.19 | G9: =SUM(G4:G8) -> 16685 | H9: =SUM(H4:H8) -> 6674 | I9: =SUM(I4:I8) -> 5362.71 | J9: =SUM(J4:J8) -> 10726 | ... O9: =SUM(O4:O8) -> 25360
C10: 909055 | D10: 363622 | E10: 60465.29 | F10: 858.06 | J10: 10726 | K10: 1032233.3 | L10: 416051
C11: =C9-C10+G9 -> -0.01 | D11: =D9-D10+H9 -> 0 | E11: =E9-E10+I9 -> -5000.42 | F11: =F9-F10 -> 0.13 | G11: =G9-G10 -> 16685 | H11: =H9-H10 -> 6674 | I11: =I9-I10 -> 5362.71 | J11: =J9-J10 -> 0 | K11: =K9-K10 -> -0.29 | L11: =L9-L10 -> 0 | M11: =M9-M10 -> 134178 | ... O11: =O9-O10 -> 25360
J15: Earnings | L15: Amount | M15: Recoveries | N15: Amount
J16: Salary JUL AUG | K16: 14 Days | L16: 129902 | M16: PF | N16: 10663
J17: LTA | K17: 2022-23 | L17: 10726 | M17: Prof Tax | N17: 200
J18: Leave Encashment | K18: 97 Days | L18: 822114 | M18: Income Tax (Tentative) | N18: 92321
K19: 59.5 Days | L19: 210119 | M19: Extra Availed Leave | N19: 14429
J20: Bonus | K20: 2022-23 | L20: 416051 | M20: Cash Advance | N20: 283333
J21: CAR Reimbursement | K21: 2023-24 | L21: 134178 | M21: Uniform Charges | N21: 4299
J22: Gratuity | L22: 1589138
L23: =SUM(L16:L20) -> 1588912 | N23: =SUM(N16:N22) -> 405245
M25: Holded Amount | N25: 328745
M26: As per statement | N26: =L23-N23+N25 -> 1512412

Sheet Leave Encashment
B2: Leave Encashment
B3: Particulars | C3: Amount (Rs)
B4: Leave encashment received (A) | C4: =SUM(Salary!L18:L19) -> 1032233
B5: Less: Exemption under Section 10(10AA) – (B) Least of the following: | C5: =MIN(C6:C9) -> 0
B6: i) Amount notified by the Government** Rs 25,00,000 (C) | C6: 2500000
B7: ii) Actual leave encashment amount (D) | C7: =C4 -> 1032233 | H7: =[1]Salary!C4 -> 0
B8: iii) Average salary* of last 10 months (E) | C8: =I8 -> 0 | E8: Salary per day | F8: No. Of days | H8: =[1]Salary!C6 -> 0 | I8: =H8*4+H7*6 -> 0 | P8: =M16 -> 0 | Q8: =M17 -> 0
B9: iv) Salary per day *unutilised leave (considering maximum 30 days leave per year) for every year of completed service (F) | C9: =G9 -> 0 | E9: =[1]Salary!C6/30 -> 0 | F9: =(97+59.5)+(0*30/42) -> 156.5 | G9: =E9*F9 -> 0
B10: Leave encashment taxable – (A) – (B) | C10: =C4-C5 -> 1032233
B13: Gratuity
B14: Particulars | C14: Amount (Rs) | AT14: =AI17-SUM(AT9:AT13) -> 0
B15: Gratuity received (A) | C15: =Salary!L22 -> 1589138
B16: Less: Exemption – (B) Least of the following: | C16: =MIN(C17:C19) -> 1589137.5 | E16: Last Drawn Salary | F16: No of Years of Service | K16: 129902 | N16: =SUM(K16:K17,K20) -> 556679
B17: Last salary (basic + DA)* number of years of employment* 15/26; | C17: =H17 -> 1589137.5 | E17: =Salary!C6 -> 211885 | F17: 13 | G17: =15/26 -> 0.57692308 | H17: =E17*F17*G17 -> 1589137.5 | K17: 10726 | AI17: =SUM(AH3:AH17) -> 0
B18: Rs. 20 lakhs (which has been hiked from Rs. 10 Lakh as per the amendment); | C18: 2000000 | K18: 822114
B19: Gratuity Actually received | C19: =C15 -> 1589138 | K19: 210119 | AI19: -150000
B20: Leave encashment taxable – (A) – (B) | C20: =ROUNDDOWN(C15-C16,0) -> 0 | K20: 416051 | AI20: -50000
K21: 134178
K22: 1589138 | AI22: =SUM(AI17:AI21) -> -200000
M26: =K23-M23+M25 -> 0

Sheet Ajay SBI Flat Insurance account
A1: Account Name : | B1: Mr. AJAY KUMAR GUPTA
A2: Address : | B2: FLAT NO D-07 ISHWAR PARADISE
B3: ASHOKA MARG NASIK ROAD
B4: NASIK-422101
B5: Nashik
A6: Date : | B6: 45426
A7: Account Number : | B7: _00000032718709979
A8: Account Description: | B8: MAXGAIN SURAKSHA
A9: Branch : | B9: SHIVAJI NAGAR, NASIK
A10: Balance on 1 Apr 2023 : | B10: -363
A11: Start Date : | B11: 45017
A12: End Date : | B12: 45382
A13: Txn Date | B13: Value Date | C13: Description | D13: Ref No./Cheque No. | E13: Debit | F13: Credit | G13: Balance
A14: 45382 | B14: 45382 | C14: INTEREST--- | D14: - | E14: 4 | G14: -404
A15: 45351 | B15: 45351 | C15: INTEREST--- | D15: - | E15: 3 | G15: -400
A16: 45322 | B16: 45322 | C16: INTEREST--- | D16: - | E16: 4 | G16: -397
A17: 45291 | B17: 45291 | C17: INTEREST--- | D17: - | E17: 4 | G17: -393
A18: 45260 | B18: 45260 | C18: INTEREST--- | D18: - | E18: 4 | G18: -389
A19: 45230 | B19: 45230 | C19: INTEREST--- | D19: - | E19: 4 | G19: -385
A20: 45199 | B20: 45199 | C20: INTEREST--- | D20: - | E20: 3 | G20: -381
A21: 45169 | B21: 45169 | C21: INTEREST--- | D21: - | E21: 3 | G21: -378
A22: 45138 | B22: 45138 | C22: INTEREST--- | D22: - | E22: 3 | G22: -375
A23: 45107 | B23: 45107 | C23: INTEREST--- | D23: - | E23: 3 | G23: -372
A24: 45077 | B24: 45077 | C24: INTEREST--- | D24: - | E24: 3 | G24: -369
A25: 45046 | B25: 45046 | C25: INTEREST--- | D25: - | E25: 3 | G25: -366
A27: **This is a computer generated statement and does not require a signature
