Workbook

Sheet AXIS
B1: Axis Bank Narration Sheet
B2: Colour Legend of Categories:
B3: UPI - Fresh Produce | C3: UPI Payment | D3: NEFT Transfer | E3: Cash Withdrawal | F3: Received - Sunita Gupta
B4: Zerodha Broking | C4: Transfer - Ajay Gupta | D4: Bank Charges | E4: Bank Interest | F4: Dividend Income
B5: UPI - Pharmacy | C5: Received - Rakhi Vin | D5: Received - Deepika U | E5: Received - Bhutada S | F5: Received - Aditya Dh
B6: Received - Priti Muk | C6: Received - Deepali A | D6: UPI - IRCTC | E6: UPI - Flipkart | F6: Misc Income
B7: UPI - Meesho | C7: Received - Sharda Ar | D7: Received - Manjoosha | E7: Transfer - Sunita Gupta | F7: Transfer - Archit Gupta
B8: Received - Google In | C8: Received - Archit Gupta | D8: Shopping - Jewellery | E8: Health Insurance
A10: Date | B10: Particulars | C10: Ref | D10: Value_Date | E10: DR | F10: CR | G10: Balance | H10: Beneficiary | I10: Human_Narration | J10: Auto_Narration | K10: Account_Head | L10: Confidence | M10: Match
A11: 45388 | B11: UPI/P2M/409717050341/SHIVBHOLA VEGETABLE E/veg/Yes Bank Ltd | C11: - | D11: 45388 | E11: 30 | F11: 0 | G11: 9444.62 | I11: Household Expenses | J11: UPI - Fresh Produce | K11: Groceries | L11: 0.82 | M11: [DIFF]
A12: 45395 | B12: UPI/P2A/447025620282/DEEPIKA UMESH MUNDADA/kitty/State Bank Of India | C12: - | D12: 45395 | E12: 1000 | F12: 0 | G12: 8444.62 | H12: Deepika Umesh Mundada | I12: Kitty | J12: UPI Payment | K12: Personal | L12: 0.55 | M12: [DIFF]
A13: 45405 | B13: UPI/P2A/448073432191/BHARTI RATAN DEVNANI /tiffin/Union Bank of India | C13: - | D13: 45405 | E13: 390 | F13: 0 | G13: 8054.62 | H13: Bharti Ratan Devnani | I13: Household Expenses | J13: UPI Payment | K13: Personal | L13: 0.55 | M13: [DIFF]
A14: 45406 | B14: UPI/P2M/448166340115/KUNAL EAKNATH MAKUNE /milk/Yes Bank Ltd | C14: - | D14: 45406 | E14: 150 | F14: 0 | G14: 7904.62 | H14: Kunal Eaknath Makune | I14: Household Expenses | J14: UPI Payment | K14: Personal | L14: 0.55 | M14: [DIFF]
A15: 45408 | B15: NEFT/YESB41177892573/ZERODHA BROKING LTD-DSCNB A//YES BANK/YESB0000001 | C15: - | D15: 45408 | E15: 0 | F15: 4251.5 | G15: 12156.12 | I15: Zerodha | J15: NEFT Transfer | K15: Transfer | L15: 0.7 | M15: [DIFF]
A16: 45415 | B16: ATM-CASH-AXIS/BPRH265601/1296/030524/NASHIK | C16: - | D16: 45415 | E16: 2000 | F16: 0 | G16: 10156.12 | I16: ATM Withdrawal | J16: Cash Withdrawal | K16: Cash | L16: 0.92 | M16: [MATCH]
A17: 45420 | B17: NEFT/N129243028299413/SUNITA GUPTA/HDFC BANK/Transfer from HDFC | C17: - | D17: 45420 | E17: 0 | F17: 50000 | G17: 60156.12 | I17: Contra | J17: Received - Sunita Gupta | K17: Sunita Gupta | L17: 0.88 | M17: [DIFF]
A18: 45420 | B18: UPI/P2M/412955259759/Zerodha Broking Ltd /001847/HDFC BANK LTD | C18: - | D18: 45420 | E18: 50000 | F18: 0 | G18: 10156.12 | I18: Zerodha | J18: Zerodha Broking | K18: Zerodha Broking Limited | L18: 0.88 | M18: [DIFF]
A19: 45422 | B19: UPI/P2M/413124576623/PREMJI TRADERS /UPI/Yes Bank Ltd | C19: - | D19: 45422 | E19: 1320 | F19: 0 | G19: 8836.12 | H19: Premji Traders | I19: Household Expenses | J19: UPI Payment | K19: Personal | L19: 0.55 | M19: [DIFF]
A20: 45427 | B20: NEFT/N136243040620640/SUNITA GUPTA/HDFC BANK/frm HDFC to Axis | C20: - | D20: 45427 | E20: 0 | F20: 100000 | G20: 108836.12 | I20: Contra | J20: Received - Sunita Gupta | K20: Sunita Gupta | L20: 0.88 | M20: [DIFF]
A21: 45427 | B21: INB/IFT/Ajay Kumar Gupta/TPARTY TRANSFER | C21: - | D21: 45427 | E21: 40000 | F21: 0 | G21: 68836.12 | I21: Transfer from Ajay | J21: Transfer - Ajay Gupta | K21: Ajay Gupta | L21: 0.88 | M21: [MATCH]
A22: 45436 | B22: INB/IFT/Ajay Kumar Gupta/TPARTY TRANSFER | C22: - | D22: 45436 | E22: 30000 | F22: 0 | G22: 38836.12 | I22: Transfer from Ajay | J22: Transfer - Ajay Gupta | K22: Ajay Gupta | L22: 0.88 | M22: [MATCH]
A23: 45451 | B23: NEFT/YESEB41601792243/ZERODHA BROKING LTD- FOR ZER/YES BANK/12067726cc9f47dca08914 Zerodh | C23: - | D23: 45451 | E23: 0 | F23: 7726.63 | G23: 46562.75 | I23: Zerodha | J23: NEFT Transfer | K23: Transfer | L23: 0.7 | M23: [DIFF]
A24: 45453 | B24: GST @18% on MAB Charge | C24: - | D24: 45453 | E24: 108 | F24: 0 | G24: 46454.75 | I24: Bank Charges | J24: Bank Charges | K24: Bank Charges | L24: 0.88 | M24: [MATCH]
A25: 45453 | B25: Non-Maint Avg bal chgs Apr2024 | C25: - | D25: 45453 | E25: 600 | F25: 0 | G25: 45854.75 | I25: Bank Charges | J25: Bank Charges | K25: Bank Charges | L25: 0.88 | M25: [MATCH]
A26: 45464 | B26: UPI/P2M/417362340012/ZERODHA BROKING LIMIT/244473/ICICI Bank | C26: - | D26: 45464 | E26: 25000 | F26: 0 | G26: 20854.75 | I26: Zerodha | J26: Zerodha Broking | K26: Zerodha Broking Limited | L26: 0.88 | M26: [DIFF]
A27: 45465 | B27: UPI/P2A/454025238186/PRERANA MANOJ CHANDAK/kitty/Axis Bank Ltd. | C27: - | D27: 45465 | E27: 1000 | F27: 0 | G27: 19854.75 | H27: Prerana Manoj Chandak | I27: Kitty | J27: UPI Payment | K27: Personal | L27: 0.55 | M27: [DIFF]
A28: 45467 | B28: NEFT/N176243108305610/SUNITA GUPTA/HDFC BANK/Trf frm Sunita HDF | C28: - | D28: 45467 | E28: 0 | F28: 50000 | G28: 69854.75 | I28: Contra | J28: Received - Sunita Gupta | K28: Sunita Gupta | L28: 0.88 | M28: [DIFF]
A29: 45467 | B29: UPI/P2M/417673461227/ZERODHA BROKING LIMIT/922743/ICICI Bank | C29: - | D29: 45467 | E29: 30000 | F29: 0 | G29: 39854.75 | I29: Zerodha | J29: Zerodha Broking | K29: Zerodha Broking Limited | L29: 0.88 | M29: [DIFF]
A30: 45467 | B30: UPI/P2M/417673480863/ZERODHA BROKING LIMIT/102002/ICICI Bank | C30: - | D30: 45467 | E30: 30000 | F30: 0 | G30: 9854.75 | I30: Zerodha | J30: Zerodha Broking | K30: Zerodha Broking Limited | L30: 0.88 | M30: [DIFF]
A31: 45467 | B31: NEFT/N176243109164220/SUNITA GUPTA/HDFC BANK/tfr frm Axis 2 hfc | C31: - | D31: 45467 | E31: 0 | F31: 25000 | G31: 34854.75 | I31: Contra | J31: Received - Sunita Gupta | K31: Sunita Gupta | L31: 0.88 | M31: [DIFF]
A32: 45472 | B32: UPI/P2A/418192452596/BHARTI RATAN DEVNANI /tiffin/Union Bank of India | C32: - | D32: 45472 | E32: 770 | F32: 0 | G32: 34084.75 | H32: Bharti Ratan Devnani | I32: Household Expenses | J32: UPI Payment | K32: Personal | L32: 0.55 | M32: [DIFF]
A33: 45474 | B33: SB:919010088767042:Int.Pd:01-04-2024 to 30-06-2024 | C33: - | D33: 45474 | E33: 0 | F33: 208 | G33: 34292.75 | I33: Bank Interest | J33: Bank Interest | K33: Bank Interest | L33: 0.93 | M33: [MATCH]
A34: 45474 | B34: ACH-CR-CANBANK DIV 2023-24-NACH-6544153-6544153 | C34: - | D34: 45474 | E34: 0 | F34: 805 | G34: 35097.75 | I34: Dividend Income | J34: Dividend Income | K34: Dividend Income | L34: 0.85 | M34: [MATCH]
A35: 45474 | B35: ATM-CASH-AXIS/BPRH265601/1591/010724/NASHIK | C35: - | D35: 45474 | E35: 2000 | F35: 0 | G35: 33097.75 | I35: ATM Withdrawal | J35: Cash Withdrawal | K35: Cash | L35: 0.92 | M35: [MATCH]
A36: 45476 | B36: NEFT/YESEB41852036982/ZERODHA BROKING LTD- FOR ZER/YES BANK/4565c0180515af30213b5d Zerodh | C36: - | D36: 45476 | E36: 0 | F36: 3688.79 | G36: 36786.54 | I36: Zerodha | J36: NEFT Transfer | K36: Transfer | L36: 0.7 | M36: [DIFF]
A37: 45478 | B37: UPI/P2M/455345663321/JEET PHARMACY AND MIN/medici/Axis Bank Ltd. | C37: - | D37: 45478 | E37: 22 | F37: 0 | G37: 36764.54 | I37: UPI | J37: UPI - Pharmacy | K37: Healthcare | L37: 0.85 | M37: [MATCH]
A38: 45478 | B38: UPI/P2A/455392699359/RAKHI VIN/ICICI Ban/UPI/ | C38: - | D38: 45478 | E38: 0 | F38: 1000 | G38: 37764.54 | I38: UPI | J38: Received - Rakhi Vin | K38: Personal | L38: 0.55 | M38: [DIFF]
A39: 45479 | B39: UPI/P2A/418872101808/DEEPIKA U/State Ban/UPI/ | C39: - | D39: 45479 | E39: 0 | F39: 1000 | G39: 38764.54 | I39: UPI | J39: Received - Deepika U | K39: Personal | L39: 0.55 | M39: [DIFF]
A40: 45481 | B40: UPI/P2A/419032821898/KAMINI MIHANI 95279/cream/State Bank Of India | C40: - | D40: 45481 | E40: 650 | F40: 0 | G40: 38114.54 | H40: Kamini Mihani 95279 | I40: UPI | J40: UPI Payment | K40: Personal | L40: 0.55 | M40: [MATCH]
A41: 45484 | B41: UPI/P2A/419395681329/BHUTADA S/Bank of B/Payment/ | C41: - | D41: 45484 | E41: 0 | F41: 1000 | G41: 39114.54 | I41: UPI | J41: Received - Bhutada S | K41: Personal | L41: 0.55 | M41: [DIFF]
A42: 45484 | B42: UPI/P2M/419362096628/SHIVBHOLA VEGETABLE E/vegeta/Yes Bank Ltd | C42: - | D42: 45484 | E42: 25 | F42: 0 | G42: 39089.54 | I42: UPI | J42: UPI - Fresh Produce | K42: Groceries | L42: 0.82 | M42: [MATCH]
A43: 45484 | B43: UPI/P2A/419342818267/ADITYA DH/Axis Bank/Payment/ | C43: - | D43: 45484 | E43: 0 | F43: 1000 | G43: 40089.54 | I43: UPI | J43: Received - Aditya Dh | K43: Personal | L43: 0.55 | M43: [DIFF]
A44: 45489 | B44: UPI/P2A/419895360581/BHARTI RATAN DEVNANI /UPI/Union Bank of India | C44: - | D44: 45489 | E44: 320 | F44: 0 | G44: 39769.54 | H44: Bharti Ratan Devnani | I44: UPI | J44: UPI Payment | K44: Personal | L44: 0.55 | M44: [MATCH]
A45: 45490 | B45: GST @18% on MAB Charge | C45: - | D45: 45490 | E45: 108 | F45: 0 | G45: 39661.54 | I45: Bank Charges | J45: Bank Charges | K45: Bank Charges | L45: 0.88 | M45: [MATCH]
A46: 45490 | B46: Non-Maint Avg bal chgs May2024 | C46: - | D46: 45490 | E46: 600 | F46: 0 | G46: 39061.54 | I46: Bank Charges | J46: Bank Charges | K46: Bank Charges | L46: 0.88 | M46: [MATCH]
A47: 45491 | B47: ACH-CR-HDFC LIFE INSURANCE-NACH-00000000000005531 | C47: - | D47: 45491 | E47: 0 | F47: 50 | G47: 39111.54 | I47: Dividend Income | J47: Dividend Income | K47: Dividend Income | L47: 0.85 | M47: [MATCH]
A48: 45492 | B48: UPI/P2M/420154995267/MADHURI SEN /parlou/Axis Bank Ltd. | C48: - | D48: 45492 | E48: 1000 | F48: 0 | G48: 38111.54 | H48: Madhuri Sen | I48: UPI | J48: UPI Payment | K48: Personal | L48: 0.55 | M48: [MATCH]
A49: 45494 | B49: UPI/P2A/420322676433/PRITI MUK/HDFC BANK/Payment/ | C49: - | D49: 45494 | E49: 0 | F49: 150 | G49: 38261.54 | I49: UPI | J49: Received - Priti Muk | K49: Personal | L49: 0.55 | M49: [DIFF]
A50: 45494 | B50: UPI/P2A/420369431939/KAMINI MIHANI 95279/parlou/State Bank Of India | C50: - | D50: 45494 | E50: 600 | F50: 0 | G50: 37661.54 | H50: Kamini Mihani 95279 | I50: UPI | J50: UPI Payment | K50: Personal | L50: 0.55 | M50: [MATCH]
A51: 45494 | B51: UPI/P2A/456924153221/ADITI GUPTA /rumal/State Bank Of India | C51: - | D51: 45494 | E51: 420 | F51: 0 | G51: 37241.54 | H51: Aditi Gupta | I51: UPI | J51: UPI Payment | K51: Personal | L51: 0.55 | M51: [MATCH]
A52: 45498 | B52: UPI/P2A/420791199151/DEEPALI A/HDFC BANK/Payment/ | C52: - | D52: 45498 | E52: 0 | F52: 1000 | G52: 38241.54 | I52: UPI | J52: Received - Deepali A | K52: Personal | L52: 0.55 | M52: [DIFF]
A53: 45498 | B53: UPI/P2M/420734844951/IRCTC CF /IRCTC/HDFC BANK LTD | C53: - | D53: 45498 | E53: 407.25 | F53: 0 | G53: 37834.29 | I53: UPI | J53: UPI - IRCTC | K53: Travel | L53: 0.68 | M53: [MATCH]
A54: 45504 | B54: ACH-CR-SHRDCCLFnl202324-NACH-00000000000000067267 | C54: - | D54: 45504 | E54: 0 | F54: 900 | G54: 38734.29 | I54: Dividend Income | J54: Dividend Income | K54: Dividend Income | L54: 0.85 | M54: [MATCH]
A55: 45507 | B55: NEFT/YESF342160112723/ZERODHA BROKING LTD-DSCNB A//YES BANK/ae4b1fbf69 Zerodha payout | C55: - | D55: 45507 | E55: 0 | F55: 25000 | G55: 63734.29 | I55: Zerodha | J55: NEFT Transfer | K55: Transfer | L55: 0.7 | M55: [DIFF]
A56: 45510 | B56: UPI/P2M/458538155643/Flipkart Payments /UPI/Yes Bank Ltd | C56: - | D56: 45510 | E56: 1519 | F56: 0 | G56: 62215.29 | I56: UPI | J56: UPI - Flipkart | K56: Shopping | L56: 0.68 | M56: [MATCH]
A57: 45516 | B57: UPI/P2A/422527945475/BHARTI RATAN DEVNANI /tiffin/Union Bank of India | C57: - | D57: 45516 | E57: 400 | F57: 0 | G57: 61815.29 | H57: Bharti Ratan Devnani | I57: UPI | J57: UPI Payment | K57: Personal | L57: 0.55 | M57: [MATCH]
A58: 45518 | B58: GST @18% on MAB Charge | C58: - | D58: 45518 | E58: 108 | F58: 0 | G58: 61707.29 | I58: Bank Charges | J58: Bank Charges | K58: Bank Charges | L58: 0.88 | M58: [MATCH]
A59: 45518 | B59: Non-Maint Avg bal chgs Jun2024 | C59: - | D59: 45518 | E59: 600 | F59: 0 | G59: 61107.29 | I59: Bank Charges | J59: Bank Charges | K59: Bank Charges | L59: 0.88 | M59: [MATCH]
A60: 45520 | B60: UPI/P2A/459516048244/Kriti Gupta /rakhi/State Bank Of India | C60: - | D60: 45520 | E60: 1300 | F60: 0 | G60: 59807.29 | H60: Kriti Gupta | I60: UPI | J60: UPI Payment | K60: Personal | L60: 0.55 | M60: [MATCH]
A61: 45525 | B61: Charge Refund: MABPR | C61: - | D61: 45525 | E61: 0 | F61: 600 | G61: 60407.29 | I61: Bank Charges | J61: Misc Income | K61: Misc Income | L61: 0.7 | M61: [DIFF]
A62: 45529 | B62: UPI/P2M/423838369708/Meesho /UPI In/Yes Bank Ltd | C62: - | D62: 45529 | E62: 127 | F62: 0 | G62: 60280.29 | I62: UPI | J62: UPI - Meesho | K62: Shopping | L62: 0.68 | M62: [MATCH]
A63: 45529 | B63: NEFT/N238243225110515/SUNITA GUPTA/HDFC BANK/Trf frm HDFC Sunit | C63: - | D63: 45529 | E63: 0 | F63: 150000 | G63: 210280.29 | I63: Contra | J63: Received - Sunita Gupta | K63: Sunita Gupta | L63: 0.88 | M63: [DIFF]
A64: 45530 | B64: NEFT/YESF342390240804/ZERODHA BROKING LTD-DSCNB A//YES BANK/f940673c85 Zerodha payout | C64: - | D64: 45530 | E64: 0 | F64: 11206.33 | G64: 221486.62 | I64: Zerodha | J64: NEFT Transfer | K64: Transfer | L64: 0.7 | M64: [DIFF]
A65: 45538 | B65: UPI/P2M/424703060377/064101250/Kotak Mah/CHANNEL/TEZ | C65: - | D65: 45538 | E65: 14696 | F65: 0 | G65: 206790.62 | H65: P2M | I65: UPI | J65: UPI Payment | K65: Personal | L65: 0.55 | M65: [MATCH]
A66: 45538 | B66: UPI/P2A/424719830314/SHARDA AR/Federal B/UPI/ | C66: - | D66: 45538 | E66: 0 | F66: 230 | G66: 207020.62 | I66: UPI | J66: Received - Sharda Ar | K66: Personal | L66: 0.55 | M66: [DIFF]
A67: 45540 | B67: UPI/P2A/424911534092/MANJOOSHA/HDFC BANK/UPI/ | C67: - | D67: 45540 | E67: 0 | F67: 40 | G67: 207060.62 | I67: UPI | J67: Received - Manjoosha | K67: Personal | L67: 0.55 | M67: [DIFF]
A68: 45541 | B68: NEFT/YESF342500035924/ZERODHA BROKING LTD-DSCNB A//YES BANK/845c06dd7a Zerodha payout | C68: - | D68: 45541 | E68: 0 | F68: 19000 | G68: 226060.62 | I68: Zerodha | J68: NEFT Transfer | K68: Transfer | L68: 0.7 | M68: [DIFF]
A69: 45546 | B69: MIL DIVIDEND AC/ | C69: - | D69: 45546 | E69: 0 | F69: 10 | G69: 226070.62 | I69: Dividend Income | J69: Dividend Income | K69: Dividend Income | L69: 0.85 | M69: [MATCH]
A70: 45556 | B70: UPI/P2A/463116904245/BHARTI RATAN DEVNANI /tiffin/Union Bank of India | C70: - | D70: 45556 | E70: 310 | F70: 0 | G70: 225760.62 | H70: Bharti Ratan Devnani | I70: UPI | J70: UPI Payment | K70: Personal | L70: 0.55 | M70: [MATCH]
A71: 45557 | B71: UPI/P2M/463260761650/SHAS /Paymen/Yes Bank Ltd | C71: - | D71: 45557 | E71: 422 | F71: 0 | G71: 225338.62 | H71: Shas | I71: UPI | J71: UPI Payment | K71: Personal | L71: 0.55 | M71: [MATCH]
A72: 45559 | B72: UPI/P2M/463437357157/SANGITA RAJENDRA MUTH/dentis/Yes Bank Ltd | C72: - | D72: 45559 | E72: 500 | F72: 0 | G72: 224838.62 | H72: Sangita Rajendra Muth | I72: UPI | J72: UPI Payment | K72: Personal | L72: 0.55 | M72: [MATCH]
A73: 45562 | B73: ACH-CR-USL FIN DIV 23 24-NACH-23827-23827 | C73: - | D73: 45562 | E73: 0 | F73: 250 | G73: 225088.62 | I73: Dividend Income | J73: Dividend Income | K73: Dividend Income | L73: 0.85 | M73: [MATCH]
A74: 45563 | B74: UPI/P2M/463877794818/SANGITA RAJENDRA MUTH/dentis/Yes Bank Ltd | C74: - | D74: 45563 | E74: 1700 | F74: 0 | G74: 223388.62 | H74: Sangita Rajendra Muth | I74: UPI | J74: UPI Payment | K74: Personal | L74: 0.55 | M74: [MATCH]
A75: 45563 | B75: ATM-CASH/SBI SHIVAJI NAGAR/NASHIK/280924 | C75: - | D75: 45563 | E75: 10000 | F75: 0 | G75: 213388.62 | I75: ATM Withdrawal | J75: Cash Withdrawal | K75: Cash | L75: 0.92 | M75: [MATCH]
A76: 45565 | B76: NEFT/IR/AXOIR27490761713/Sunita Gupta/HDFC BANK/Transfer from Sunita Axis Ban | C76: - | D76: 45565 | E76: 100000 | F76: 0 | G76: 113388.62 | I76: Contra | J76: Transfer - Sunita Gupta | K76: Sunita Gupta | L76: 0.88 | M76: [DIFF]
A77: 45566 | B77: SB:919010088767042:Int.Pd:01-07-2024 to 30-09-2024 | C77: - | D77: 45566 | E77: 0 | F77: 881 | G77: 114269.62 | I77: Bank Interest | J77: Bank Interest | K77: Bank Interest | L77: 0.93 | M77: [MATCH]
A78: 45568 | B78: NEFT/YESF342771615268/ZERODHA BROKING LTD-DSCNB A//YES BANK/9e2d83f3e8 Zerodha payout | C78: - | D78: 45568 | E78: 0 | F78: 39310.75 | G78: 153580.37 | I78: Zerodha | J78: NEFT Transfer | K78: Transfer | L78: 0.7 | M78: [DIFF]
A79: 45581 | B79: UPI/P2A/465679437892/ASHWINI HEMANT PATIL /kitty/State Bank Of India | C79: - | D79: 45581 | E79: 5000 | F79: 0 | G79: 148580.37 | H79: Ashwini Hemant Patil | I79: UPI | J79: UPI Payment | K79: Personal | L79: 0.55 | M79: [MATCH]
A80: 45586 | B80: UPI/P2A/429536466098/BHAGAWATI PRASAD MAND/UPI/ICICI Bank | C80: - | D80: 45586 | E80: 15 | F80: 0 | G80: 148565.37 | H80: Bhagawati Prasad Mand | I80: UPI | J80: UPI Payment | K80: Personal | L80: 0.55 | M80: [MATCH]
A81: 45589 | B81: UPI/P2M/466409647719/REET FASHION /UPI/Yes Bank Ltd | C81: - | D81: 45589 | E81: 7000 | F81: 0 | G81: 141565.37 | H81: Reet Fashion | I81: UPI | J81: UPI Payment | K81: Personal | L81: 0.55 | M81: [MATCH]
A82: 45592 | B82: INB/IFT/Ajay Kumar Gupta/TPARTY TRANSFER | C82: - | D82: 45592 | E82: 100000 | F82: 0 | G82: 41565.37 | I82: Transfer to Aayush | J82: Transfer - Ajay Gupta | K82: Ajay Gupta | L82: 0.88 | M82: [DIFF]
A83: 45594 | B83: UPI/P2M/430390809811/Zerodha Broking Ltd /505142/HDFC BANK LTD | C83: - | D83: 45594 | E83: 25000 | F83: 0 | G83: 16565.37 | I83: UPI | J83: Zerodha Broking | K83: Zerodha Broking Limited | L83: 0.88 | M83: [MATCH]
A84: 45596 | B84: Dr Card Charges GST ANNUAL 4153XXXXXXXX5568 | C84: - | D84: 45596 | E84: 590 | F84: 0 | G84: 15975.37 | I84: Bank Charges | J84: Bank Charges | K84: Bank Charges | L84: 0.88 | M84: [MATCH]
A85: 45597 | B85: NEFT/YESF343062522862/ZERODHA BROKING LTD-DSCNB A//YES BANK/ad64ca2b52d2cc19a41251 Zerodh | C85: - | D85: 45597 | E85: 0 | F85: 25000 | G85: 40975.37 | I85: Zerodha | J85: NEFT Transfer | K85: Transfer | L85: 0.7 | M85: [DIFF]
A86: 45608 | B86: UPI/P2A/431766739628/BHARTI RATAN DEVNANI /UPI/Union Bank of India | C86: - | D86: 45608 | E86: 3420 | F86: 0 | G86: 37555.37 | H86: Bharti Ratan Devnani | I86: UPI | J86: UPI Payment | K86: Personal | L86: 0.55 | M86: [MATCH]
A87: 45609 | B87: UPI/P2A/431861950461/ARCHIT GUPTA /UPI/AXIS BANK | C87: - | D87: 45609 | E87: 10000 | F87: 0 | G87: 27555.37 | I87: UPI | J87: Transfer - Archit Gupta | K87: Archit Gupta | L87: 0.85 | M87: [MATCH]
A88: 45609 | B88: UPI/P2A/975907133184/GOOGLE IN/AXIS BANK/Rewarded/ | C88: - | D88: 45609 | E88: 0 | F88: 5 | G88: 27560.37 | I88: UPI | J88: Received - Google In | K88: Personal | L88: 0.55 | M88: [DIFF]
A89: 45609 | B89: UPI/P2A/431836159142/ARCHIT GU/Axis Bank/UPI/ | C89: - | D89: 45609 | E89: 0 | F89: 10000 | G89: 37560.37 | I89: UPI | J89: Received - Archit Gupta | K89: Archit Gupta | L89: 0.85 | M89: [DIFF]
A90: 45623 | B90: UPI/P2M/469858954034/Shiv Shakti Saundarya/jewell/Yes Bank Ltd | C90: - | D90: 45623 | E90: 2280 | F90: 0 | G90: 35280.37 | H90: Shiv Shakti Saundarya | I90: UPI | J90: UPI Payment | K90: Personal | L90: 0.55 | M90: [MATCH]
A91: 45635 | B91: UPI/P2M/471025503720/GHANSHYAM ABHUSHAN BH/jewell/Yes Bank Ltd | C91: - | D91: 45635 | E91: 2700 | F91: 0 | G91: 32580.37 | I91: UPI | J91: Shopping - Jewellery | K91: Shopping | L91: 0.85 | M91: [DIFF]
A92: 45642 | B92: UPI/P2M/435186763971/SHIVANJALI /UPI/Yes Bank Ltd | C92: - | D92: 45642 | E92: 500 | F92: 0 | G92: 32080.37 | H92: Shivanjali | I92: UPI | J92: UPI Payment | K92: Personal | L92: 0.55 | M92: [MATCH]
A93: 45658 | B93: SB:919010088767042:Int.Pd:01-10-2024 to 31-12-2024 | C93: - | D93: 45658 | E93: 0 | F93: 505 | G93: 32585.37 | I93: Bank Interest | J93: Bank Interest | K93: Bank Interest | L93: 0.93 | M93: [MATCH]
A94: 45661 | B94: NEFT/YESF350044351321/ZERODHA BROKING LTD-DSCNB A//YES BANK/5c107df8698e45fda08666:Zerodh | C94: - | D94: 45661 | E94: 0 | F94: 24454.02 | G94: 57039.39 | I94: Zerodha | J94: NEFT Transfer | K94: Transfer | L94: 0.7 | M94: [DIFF]
A95: 45684 | B95: UPI/P2A/539337800613/MADHURI SEN /UPI/BANK OF INDIA | C95: - | D95: 45684 | E95: 20000 | F95: 0 | G95: 37039.39 | H95: Madhuri Sen | I95: UPI | J95: UPI Payment | K95: Personal | L95: 0.55 | M95: [MATCH]
A96: 45698 | B96: UPI/P2A/540741534158/ASHLESHA RAMDAS WAGH/UPI/State Bank Of India | C96: - | D96: 45698 | E96: 1200 | F96: 0 | G96: 35839.39 | H96: Ashlesha Ramdas Wagh | I96: UPI | J96: UPI Payment | K96: Personal | L96: 0.55 | M96: [MATCH]
A97: 45702 | B97: UPI/P2A/504523848997/BHARTI RATAN DEVNANI /UPI/UNION BANK OF INDIA | C97: - | D97: 45702 | E97: 320 | F97: 0 | G97: 35519.39 | H97: Bharti Ratan Devnani | I97: UPI | J97: UPI Payment | K97: Personal | L97: 0.55 | M97: [MATCH]
A98: 45719 | B98: UPI/P2M/542808073747/K V GAYATHRI /milk/YES BANK LIMITED YBS | C98: - | D98: 45719 | E98: 50 | F98: 0 | G98: 35469.39 | H98: K V Gayathri | I98: UPI | J98: UPI Payment | K98: Personal | L98: 0.55 | M98: [MATCH]
A99: 45719 | B99: UPI/P2M/542879469211/Flipkart Payments /UPI/YES BANK LIMITED YBS | C99: - | D99: 45719 | E99: 1270 | F99: 0 | G99: 34199.39 | I99: UPI | J99: UPI - Flipkart | K99: Shopping | L99: 0.68 | M99: [MATCH]
A100: 45719 | B100: UPI/P2A/506209457462/Flipkart /YES BANK /express/ | C100: - | D100: 45719 | E100: 0 | F100: 965 | G100: 35164.39 | I100: UPI | J100: UPI - Flipkart | K100: Shopping | L100: 0.68 | M100: [MATCH]
A101: 45719 | B101: UPI/P2A/506209459641/Flipkart /YES BANK /express/ | C101: - | D101: 45719 | E101: 0 | F101: 305 | G101: 35469.39 | I101: UPI | J101: UPI - Flipkart | K101: Shopping | L101: 0.68 | M101: [MATCH]
...

Sheet HDFC
B1: HDFC Bank Narration Sheet
B2: Colour Legend of Categories:
B3: HDFC Securities - Buy | C3: HDFC Securities - Sell | D3: Internal Transfer | E3: Depository Charges | F3: Received - Sunita Gupta
B4: MF Investment | C4: SIP | D4: Transfer - Sunita Gupta | E4: Dividend Income | F4: Bank Charges
B5: Transfer - Archit Gupta | C5: Received - Ajay Gupta | D5: Bank Interest | E5: Cash Withdrawal | F5: Income Tax Refund
B6: UPI Payment | C6: UPI - Paytm | D6: UPI - Fresh Produce | E6: Transfer - Ajay Gupta | F6: HDFC Securities - Settlement
B7: Received - Archit Gupta | C7: MF Redemption | D7: Cash Deposit | E7: Transfer - Megha Gupta | F7: Misc Income
A9: Date | B9: Particulars | C9: Ref | D9: Value_Date | E9: DR | F9: CR | G9: Balance | H9: Beneficiary | I9: Human_Narration | J9: Auto_Narration | K9: Account_Head | L9: Confidence | M9: Match
A10: 45383 | B10: NET PI TO HSL SEC A/C 523686-00602340029434 | C10: 0000000508932363 | D10: 45383 | E10: 1672 | F10: 0 | G10: 31564 | I10: HSL | J10: HDFC Securities - Buy | K10: HDFC Securities | L10: 0.97 | M10: [MATCH]
A11: 45384 | B11: NET PO FROM HSL A/C 523686-50200085415108 | C11: 0000000509188445 | D11: 45384 | E11: 0 | F11: 16753.39 | G11: 48317.39 | I11: HSL | J11: HDFC Securities - Sell | K11: HDFC Securities | L11: 0.97 | M11: [MATCH]
A12: 45384 | B12: NET PO FROM HSL A/C 523686-50200085415108 | C12: 0000000509246217 | D12: 45384 | E12: 0 | F12: 97641.5 | G12: 145958.89 | I12: HSL | J12: HDFC Securities - Sell | K12: HDFC Securities | L12: 0.97 | M12: [MATCH]
A13: 45384 | B13: NET PI TO HSL SEC A/C 523686-00602340029434 | C13: 0000000509399140 | D13: 45384 | E13: 418 | F13: 0 | G13: 145540.89 | I13: HSL | J13: HDFC Securities - Buy | K13: HDFC Securities | L13: 0.97 | M13: [MATCH]
A14: 45384 | B14: NET PI TO HSL SEC A/C 523686-00602340029434 | C14: 0000000509532005 | D14: 45384 | E14: 103098.99 | F14: 0 | G14: 42441.9 | I14: HSL | J14: HDFC Securities - Buy | K14: HDFC Securities | L14: 0.97 | M14: [MATCH]
A15: 45385 | B15: NET PO FROM HSL A/C 523686-50200085415108 | C15: 0000000509650601 | D15: 45385 | E15: 0 | F15: 1514.95 | G15: 43956.85 | I15: HSL | J15: HDFC Securities - Sell | K15: HDFC Securities | L15: 0.97 | M15: [MATCH]
A16: 45385 | B16: NET PI TO HSL SEC A/C 523686-00602340029434 | C16: 0000000509793906 | D16: 45385 | E16: 379.22 | F16: 0 | G16: 43577.63 | I16: HSL | J16: HDFC Securities - Buy | K16: HDFC Securities | L16: 0.97 | M16: [MATCH]
A17: 45386 | B17: NET PO FROM HSL A/C 523686-50200085415108 | C17: 0000000510056916 | D17: 45386 | E17: 0 | F17: 6701.42 | G17: 50279.05 | I17: HSL | J17: HDFC Securities - Sell | K17: HDFC Securities | L17: 0.97 | M17: [MATCH]
A18: 45386 | B18: 50100128155413-TPT-TO MUMMY-AAYUSH KUMAR GUPTA | C18: 0000000526007002 | D18: 45386 | E18: 0 | F18: 30000 | G18: 80279.05 | I18: Transfer from Aayush | J18: Internal Transfer | K18: Transfer | L18: 0.8 | M18: [DIFF]
A19: 45386 | B19: NET PI TO HSL SEC A/C 523686-00602340029434 | C19: 0000000510198174 | D19: 45386 | E19: 425.81 | F19: 0 | G19: 79853.24 | I19: HSL | J19: HDFC Securities - Buy | K19: HDFC Securities | L19: 0.97 | M19: [MATCH]
A20: 45386 | B20: NET PI TO HSL SEC A/C 523686-00602340029434 | C20: 0000000510339907 | D20: 45386 | E20: 72828.22 | F20: 0 | G20: 7025.02 | I20: HSL | J20: HDFC Securities - Buy | K20: HDFC Securities | L20: 0.97 | M20: [MATCH]
A21: 45387 | B21: NET PI TO HSL SEC A/C 523686-00602340029434 | C21: 0000000510610766 | D21: 45387 | E21: 402.46 | F21: 0 | G21: 6622.56 | I21: HSL | J21: HDFC Securities - Buy | K21: HDFC Securities | L21: 0.97 | M21: [MATCH]
... A336: 45523 | B336: NET PI TO HSL SEC A/C 523686-00602340029434 | C336: 0000000553401436 | D336: 45523 | E336: 891.84 | F336: 0 | G336: 82313.36 | I336: HSL | J336: HDFC Securities - Buy | K336: HDFC Securities | L336: 0.97 | M336: [MATCH]
A337: 45523 | B337: UPI-BHARAT SHIVAJI SALVE-Q693795930@YBL-YESB0YBLUPI-459804001805-VEGITABLE | C337: 0000459804001805 | D337: 45523 | E337: 290 | F337: 0 | G337: 82023.36 | H337: Bharat Shivaji Salve | I337: UPI | J337: UPI Payment | K337: Personal | L337: 0.55 | M337: [MATCH]
A338: 45523 | B338: YHDF2417946248/BILLDKTHECALCUTTAELE | C338: 0002423259470626 | D338: 45523 | E338: 17805 | F338: 0 | G338: 64218.36 | I338: Electricity Bill | J338: SIP | K338: SIP | L338: 0.9 | M338: [DIFF]
A339: 45523 | B339: NET PI TO HSL SEC A/C 523686-00602340029434 | C339: 0000000553549010 | D339: 45523 | E339: 1362.77 | F339: 0 | G339: 62855.59 | I339: HSL | J339: HDFC Securities - Buy | K339: HDFC Securities | L339: 0.97 | M339: [MATCH]
A340: 45524 | B340: NET PO FROM HSL A/C 523686-50200085415108 | C340: 0000000553719337 | D340: 45524 | E340: 0 | F340: 87679.6 | G340: 150535.19 | I340: HSL | J340: HDFC Securities - Sell | K340: HDFC Securities | L340: 0.97 | M340: [MATCH]
A341: 45524 | B341: UPI-OM SUPAR SHOPI-PAYTMQR1BM2V0ZITY@PAYTM-YESB0PTMUPI-423376646504-CHACH | C341: 0000423376646504 | D341: 45524 | E341: 18 | F341: 0 | G341: 150517.19 | I341: UPI | J341: UPI - Paytm | K341: Personal | L341: 0.65 | M341: [MATCH]
A342: 45524 | B342: UPI-BHARAT SHIVAJI SALVE-Q275219389@YBL-YESB0YBLUPI-459917741143-FRUIT | C342: 0000459917741143 | D342: 45524 | E342: 300 | F342: 0 | G342: 150217.19 | I342: UPI | J342: UPI - Fresh Produce | K342: Groceries | L342: 0.82 | M342: [MATCH]
A343: 45524 | B343: NET PI TO HSL SEC A/C 523686-00602340029434 | C343: 0000000553854506 | D343: 45524 | E343: 279.69 | F343: 0 | G343: 149937.5 | I343: HSL | J343: HDFC Securities - Buy | K343: HDFC Securities | L343: 0.97 | M343: [MATCH]
A344: 45524 | B344: UPI-KUNAL RAMESH JADHAV-Q579080630@YBL-YESB0YBLUPI-459947687018-BUKE | C344: 0000459947687018 | D344: 45524 | E344: 130 | F344: 0 | G344: 149807.5 | H344: Kunal Ramesh Jadhav | I344: UPI | J344: UPI Payment | K344: Personal | L344: 0.55 | M344: [MATCH]
A345: 45525 | B345: NET PO FROM HSL A/C 523686-50200085415108 | C345: 0000000554118937 | D345: 45525 | E345: 0 | F345: 87035.28 | G345: 236842.78 | I345: HSL | J345: HDFC Securities - Sell | K345: HDFC Securities | L345: 0.97 | M345: [MATCH]
A346: 45525 | B346: UPI-KRUSHNASAGAR MITHAI-PAYTMQR596DKQ@PAYTM-YESB0PTMUPI-423452847251-NAMKIN | C346: 0000423452847251 | D346: 45525 | E346: 55 | F346: 0 | G346: 236787.78 | I346: UPI | J346: UPI - Paytm | K346: Personal | L346: 0.65 | M346: [MATCH]
A347: 45525 | B347: 01671000085930-TPT-BORROW FROM SUNITA-AJAY KUMAR GUPTA | C347: 0000000311404451 | D347: 45525 | E347: 200000 | F347: 0 | G347: 36787.78 | I347: Transfer to Ajay | J347: Transfer - Sunita Gupta | K347: Sunita Gupta | L347: 0.88 | M347: [DIFF]
A348: 45525 | B348: ACH C- CDSL FNLDIV 2023 24-345199 | C348: 0000007667792344 | D348: 45525 | E348: 0 | F348: 1980 | G348: 38767.78 | I348: Dividend Income | J348: Dividend Income | K348: Dividend Income | L348: 0.88 | M348: [MATCH]
A349: 45525 | B349: NET PI TO HSL SEC A/C 523686-00602340029434 | C349: 0000000554261223 | D349: 45525 | E349: 280.7 | F349: 0 | G349: 38487.08 | I349: HSL | J349: HDFC Securities - Buy | K349: HDFC Securities | L349: 0.97 | M349: [MATCH]
A350: 45526 | B350: NET PO FROM HSL A/C 523686-50200085415108 | C350: 0000000554540381 | D350: 45526 | E350: 0 | F350: 13652.52 | G350: 52139.6 | I350: HSL | J350: HDFC Securities - Sell | K350: HDFC Securities | L350: 0.97 | M350: [MATCH]
A351: 45526 | B351: NET PI TO HSL SEC A/C 523686-00602340029434 | C351: 0000000554671236 | D351: 45526 | E351: 254.07 | F351: 0 | G351: 51885.53 | I351: HSL | J351: HDFC Securities - Buy | K351: HDFC Securities | L351: 0.97 | M351: [MATCH]
A352: 45526 | B352: 01671000085930-TPT-MONEY RETURNED-AJAY KUMAR GUPTA | C352: 0000000317317050 | D352: 45526 | E352: 0 | F352: 200000 | G352: 251885.53 | I352: Transfer by Ajay | J352: Received - Ajay Gupta | K352: Ajay Gupta | L352: 0.88 | M352: [DIFF]
A353: 45527 | B353: NET PO FROM HSL A/C 523686-50200085415108 | C353: 0000000554967819 | D353: 45527 | E353: 0 | F353: 1025.02 | G353: 252910.55 | I353: HSL | J353: HDFC Securities - Sell | K353: HDFC Securities | L353: 0.97 | M353: [MATCH]
A354: 45527 | B354: NET PO FROM HSL A/C 523686-50200085415108 | C354: 0000000555007760 | D354: 45527 | E354: 0 | F354: 41057.08 | G354: 293967.63 | I354: HSL | J354: HDFC Securities - Sell | K354: HDFC Securities | L354: 0.97 | M354: [MATCH]
A355: 45527 | B355: NET PI TO HSL SEC A/C 523686-00602340029434 | C355: 0000000555104327 | D355: 45527 | E355: 258.93 | F355: 0 | G355: 293708.7 | I355: HSL | J355: HDFC Securities - Buy | K355: HDFC Securities | L355: 0.97 | M355: [MATCH]
A356: 45527 | B356: ACH C- CAMS INT DIV 2024 25-154890 | C356: 0000007750640328 | D356: 45527 | E356: 0 | F356: 220 | G356: 293928.7 | I356: Dividend Income | J356: Dividend Income | K356: Dividend Income | L356: 0.88 | M356: [MATCH]
... A679: 45681 | B679: NET PI TO HSL SEC A/C 523686-00602340029434 | C679: 0000000603897648 | D679: 45681 | E679: 391.02 | F679: 0 | G679: 54154.59 | I679: HSL | J679: HDFC Securities - Buy | K679: HDFC Securities | L679: 0.97 | M679: [MATCH]
A680: 45681 | B680: UPI-BIDYUT HALDAR-7014298146@AXL-SBIN0031251-220367711683-LEMON TEA | C680: 0000220367711683 | D680: 45681 | E680: 20000 | F680: 0 | G680: 34154.59 | H680: Bidyut Haldar | I680: Shaadi Kharcha | J680: UPI Payment | K680: Personal | L680: 0.55 | M680: [DIFF]
A681: 45681 | B681: NET PI TO HSL SEC A/C 523686-00602340029434 | C681: 0000000604083144 | D681: 45681 | E681: 7692.58 | F681: 0 | G681: 26462.01 | I681: HSL | J681: HDFC Securities - Buy | K681: HDFC Securities | L681: 0.97 | M681: [MATCH]
A682: 45681 | B682: YHDF2518408318/BILLDKTHECALCUTTAELE | C682: 0000252474286240 | D682: 45681 | E682: 10164 | F682: 0 | G682: 16298.01 | I682: Electricity Bill | J682: SIP | K682: SIP | L682: 0.9 | M682: [DIFF]
A683: 45684 | B683: ACH D- TP ACH INDIANESIGN-1692517311 | C683: 0000003797480267 | D683: 45684 | E683: 10000 | F683: 0 | G683: 6298.01 | I683: SIP - 10000 | J683: SIP | K683: SIP | L683: 0.95 | M683: [DIFF]
A684: 45684 | B684: NET PI TO HSL SEC A/C 523686-00602340029434 | C684: 0000000604402522 | D684: 45684 | E684: 1183.08 | F684: 0 | G684: 5114.93 | I684: HSL | J684: HDFC Securities - Buy | K684: HDFC Securities | L684: 0.97 | M684: [MATCH]
A685: 45684 | B685: NET PI TO HSL SEC A/C 523686-00602340029434 | C685: 0000000604613595 | D685: 45684 | E685: 5114.93 | F685: 0 | G685: 0 | I685: HSL | J685: HDFC Securities - Buy | K685: HDFC Securities | L685: 0.97 | M685: [MATCH]
A686: 45686 | B686: NEFT CR-UTIB0000004-AXIS MUTUAL FUND DIVIDEND A/C-SUNITA GUPTA-UTIBN62025012940337499 | C686: UTIBN62025012940337499 | D686: 45686 | E686: 0 | F686: 84.57 | G686: 84.57 | I686: Dividend Income | J686: Dividend Income | K686: Dividend Income | L686: 0.85 | M686: [MATCH]
A687: 45686 | B687: NET PI TO HSL SEC A/C 523686-00602340029434 | C687: 0000000605469737 | D687: 45686 | E687: 84.57 | F687: 0 | G687: 0 | I687: HSL | J687: HDFC Securities - Buy | K687: HDFC Securities | L687: 0.97 | M687: [MATCH]
A688: 45687 | B688: FT- 605558165-50200085415108 - HDFC SECURITIES LTD-CLIENT DSCNB A/C - | C688: 0000000927235357 | D688: 45687 | E688: 0 | F688: 28044.51 | G688: 28044.51 | I688: HDFC Sec | J688: HDFC Securities - Settlement | K688: HDFC Securities | L688: 0.93 | M688: [DIFF]
A689: 45687 | B689: UPI-AJAY KUMAR GUPTA-AJAYGUPTANEL@IBL-HDFC0000167-810561957614-PAYMENT FROM PHONE | C689: 0000810561957614 | D689: 45687 | E689: 0 | F689: 20000 | G689: 48044.51 | I689: UPI | J689: Received - Ajay Gupta | K689: Ajay Gupta | L689: 0.88 | M689: [DIFF]
A690: 45687 | B690: NET PI TO HSL SEC A/C 523686-00602340029434 | C690: 0000000605686935 | D690: 45687 | E690: 392.82 | F690: 0 | G690: 47651.69 | I690: HSL | J690: HDFC Securities - Buy | K690: HDFC Securities | L690: 0.97 | M690: [MATCH]
A691: 45687 | B691: NET PI TO HSL SEC A/C 523686-00602340029434 | C691: 0000000605831271 | D691: 45687 | E691: 19819.29 | F691: 0 | G691: 27832.4 | I691: HSL | J691: HDFC Securities - Buy | K691: HDFC Securities | L691: 0.97 | M691: [MATCH]
A692: 45687 | B692: NEFT CR-SBIN0004266-SBI GENERAL INSURANCE CO LTDSBI GEN-SUNITA GUPTA 0000000002717756-SBINN52025013077176630 | C692: SBINN52025013077176630 | D692: 45687 | E692: 0 | F692: 2738 | G692: 30570.4 | I692: Rental Income | J692: Received - Sunita Gupta | K692: Sunita Gupta | L692: 0.88 | M692: [DIFF]
... A824: 45745 | B824: ISAQMC-JUL-SEP24-323600 070325-MIR2508872188526 | C824: MIR2508872188526 | D824: 45745 | E824: 295 | F824: 0 | G824: 63142.65 | I824: Bank Charges | J824: Bank Charges | K824: Bank Charges | L824: 0.9 | M824: [MATCH]

Sheet SBI
B1: State Bank of India Narration Sheet
B2: Colour Legend of Categories:
B3: Cash Withdrawal | C3: Bank Interest | D3: What is this? | E3: Received - Sunita Gupta | F3: Rent
A5: Date | B5: Particulars | C5: Ref | D5: Value_Date | E5: DR | F5: CR | G5: Balance | H5: Beneficiary | I5: Human_Narration | J5: Auto_Narration | K5: Account_Head | L5: Confidence | M5: Match
A6: 45415 | B6: ATM WDL-ATM CASH 3233 SBI SHIVAJI NAGAR ATM NASHIK-- | D6: 45415 | E6: 2000 | F6: 0 | G6: 24120.7 | I6: ATM Withdrawal | J6: Cash Withdrawal | K6: Cash | L6: 0.92 | M6: [MATCH]
A7: 45468 | B7: CREDIT INTEREST--- | D7: 45468 | E7: 0 | F7: 169 | G7: 24289.7 | I7: Bank Interest | J7: Bank Interest | K7: Bank Interest | L7: 0.9 | M7: [MATCH]
A8: 45474 | B8: ATM WDL-ATM CASH 2734 SBI SHIVAJI NAGAR ATM NASHIK-- | D8: 45474 | E8: 2000 | F8: 0 | G8: 22289.7 | I8: ATM Withdrawal | J8: Cash Withdrawal | K8: Cash | L8: 0.92 | M8: [MATCH]
A9: 45554 | B9: DEBIT-ATMCard AMC 652294*8079-- | D9: 45554 | E9: 236 | F9: 0 | G9: 22053.7 | I9: Bank Charges | J9: What is this? | K9: Suspense | L9: 0 | M9: [DIFF]
A10: 45560 | B10: CREDIT INTEREST--- | D10: 45560 | E10: 0 | F10: 152 | G10: 22205.7 | I10: Bank Interest | J10: Bank Interest | K10: Bank Interest | L10: 0.9 | M10: [MATCH]
A11: 45651 | B11: CREDIT INTEREST--- | D11: 45651 | E11: 0 | F11: 149 | G11: 22354.7 | I11: Bank Interest | J11: Bank Interest | K11: Bank Interest | L11: 0.9 | M11: [MATCH]
A12: 45708 | B12: BY TRANSFER-INB borrow-- | C12: IID4853269 TRANSFER FROM 32718635441 | D12: 45708 | E12: 0 | F12: 100000 | G12: 122354.7 | I12: Transfer from Ajay | J12: What is this? | K12: Suspense | L12: 0 | M12: [DIFF]
A13: 45709 | B13: TO TRANSFER-INB Security deposit return-- | C13: IT00YWYOL0 TRANSFER TO 35730790076 | D13: 45709 | E13: 100000 | F13: 0 | G13: 22354.7 | I13: Security Deposit Returned | J13: What is this? | K13: Suspense | L13: 0 | M13: [DIFF]
A14: 45724 | B14: BY TRANSFER-INB borrow from Sunita-- | C14: IID5359354 TRANSFER FROM 32718635441 | D14: 45724 | E14: 0 | F14: 32000 | G14: 54354.7 | I14: Transfer from Ajay | J14: Received - Sunita Gupta | K14: Sunita Gupta | L14: 0.88 | M14: [DIFF]
A15: 45724 | B15: TO TRANSFER-INB Pymt twrds scrap material-- | C15: IT00ZBZYC9 TRANSFER TO 35730790076 | D15: 45724 | E15: 43000 | F15: 0 | G15: 11354.7 | I15: Asset Purchase | J15: What is this? | K15: Suspense | L15: 0 | M15: [DIFF]
A16: 45726 | B16: BY TRANSFER-NEFT*HDFC0000001*HDFCH00113163511*SUNITA GUPTA*BAT-- | C16: TRANSFER FROM 3199970044309 | D16: 45726 | E16: 0 | F16: 30000 | G16: 41354.7 | I16: Rent Income | J16: Received - Sunita Gupta | K16: Sunita Gupta | L16: 0.88 | M16: [DIFF]
A17: 45726 | B17: TO TRANSFER-INB Rent-- | C17: IT00ZCPZM4 TRANSFER TO 35730790076 | D17: 45726 | E17: 21955 | F17: 0 | G17: 19399.7 | J17: Rent | K17: Rent | L17: 0.9 | M17: N/A
A18: 45741 | B18: CREDIT INTEREST--- | D18: 45741 | E18: 0 | F18: 151 | G18: 19550.7 | I18: Bank Interest | J18: Bank Interest | K18: Bank Interest | L18: 0.9 | M18: [MATCH]

Sheet For Tally
B1: Tally Export Narration Sheet
B2: Colour Legend of Categories:
B3: HDFC Securities - Buy | C3: HDFC Securities - Sell | D3: Internal Transfer | E3: Depository Charges | F3: UPI - Fresh Produce
B4: Received - Sunita Gupta | C4: UPI Payment | D4: MF Investment | E4: SIP | F4: Transfer - Sunita Gupta
B5: Dividend Income | C5: NEFT Transfer | D5: Bank Charges | E5: Cash Withdrawal | F5: Zerodha Broking
B6: Transfer - Archit Gupta | C6: Transfer - Ajay Gupta | D6: Received - Ajay Gupta | E6: Bank Interest | F6: Received - Rakhi Vin
B7: UPI - Pharmacy | C7: Received - Deepika U | D7: Received - Bhutada S | E7: Received - Aditya Dh | F7: Received - Priti Muk
B8: Received - Deepali A | C8: UPI - IRCTC | D8: Income Tax Refund | E8: UPI - Flipkart | F8: UPI - Paytm
B9: Misc Income | C9: UPI - Meesho | D9: Received - Sharda Ar | E9: Received - Manjoosha | F9: HDFC Securities - Settlement
B10: What is this? | C10: Received - Archit Gupta | D10: MF Redemption | E10: Received - Google In | F10: Shopping - Jewellery
B11: Cash Deposit | C11: Transfer - Megha Gupta | D11: Rent | E11: Health Insurance
A13: TX Date | B13: Date | C13: DR | D13: CR | E13: Beneficiary | F13: Narration | G13: Confidence | H13: Account Head | I13: Account No | J13: Kya Hai? | K13: Particulars | L13: Bank | M13: Duplicate
A14: 45383 | B14: 45383 | C14: 1672 | D14: 0 | F14: HDFC Securities - Buy | G14: 0.97 | H14: HDFC Securities | I14: HDFC 0094 | J14: HSL | K14: NET PI TO HSL SEC A/C 523686-00602340029434 | L14: HDFC Bank
A15: 45384 | B15: 45384 | C15: 0 | D15: 16753.39 | F15: HDFC Securities - Sell | G15: 0.97 | H15: HDFC Securities | I15: HDFC 0094 | J15: HSL | K15: NET PO FROM HSL A/C 523686-50200085415108 | L15: HDFC Bank
A16: 45384 | B16: 45384 | C16: 0 | D16: 97641.5 | F16: HDFC Securities - Sell | G16: 0.97 | H16: HDFC Securities | I16: HDFC 0094 | J16: HSL | K16: NET PO FROM HSL A/C 523686-50200085415108 | L16: HDFC Bank
A17: 45384 | B17: 45384 | C17: 418 | D17: 0 | F17: HDFC Securities - Buy | G17: 0.97 | H17: HDFC Securities | I17: HDFC 0094 | J17: HSL | K17: NET PI TO HSL SEC A/C 523686-00602340029434 | L17: HDFC Bank
A18: 45384 | B18: 45384 | C18: 103098.99 | D18: 0 | F18: HDFC Securities - Buy | G18: 0.97 | H18: HDFC Securities | I18: HDFC 0094 | J18: HSL | K18: NET PI TO HSL SEC A/C 523686-00602340029434 | L18: HDFC Bank
A19: 45385 | B19: 45385 | C19: 0 | D19: 1514.95 | F19: HDFC Securities - Sell | G19: 0.97 | H19: HDFC Securities | I19: HDFC 0094 | J19: HSL | K19: NET PO FROM HSL A/C 523686-50200085415108 | L19: HDFC Bank
A20: 45385 | B20: 45385 | C20: 379.22 | D20: 0 | F20: HDFC Securities - Buy | G20: 0.97 | H20: HDFC Securities | I20: HDFC 0094 | J20: HSL | K20: NET PI TO HSL SEC A/C 523686-00602340029434 | L20: HDFC Bank
A21: 45386 | B21: 45386 | C21: 0 | D21: 6701.42 | F21: HDFC Securities - Sell | G21: 0.97 | H21: HDFC Securities | I21: HDFC 0094 | J21: HSL | K21: NET PO FROM HSL A/C 523686-50200085415108 | L21: HDFC Bank
A22: 45386 | B22: 45386 | C22: 0 | D22: 30000 | F22: Internal Transfer | G22: 0.8 | H22: Transfer | I22: HDFC 0094 | J22: Transfer from Aayush | K22: 50100128155413-TPT-TO MUMMY-AAYUSH KUMAR GUPTA | L22: HDFC Bank
A23: 45386 | B23: 45386 | C23: 425.81 | D23: 0 | F23: HDFC Securities - Buy | G23: 0.97 | H23: HDFC Securities | I23: HDFC 0094 | J23: HSL | K23: NET PI TO HSL SEC A/C 523686-00602340029434 | L23: HDFC Bank
A24: 45386 | B24: 45386 | C24: 72828.22 | D24: 0 | F24: HDFC Securities - Buy | G24: 0.97 | H24: HDFC Securities | I24: HDFC 0094 | J24: HSL | K24: NET PI TO HSL SEC A/C 523686-00602340029434 | L24: HDFC Bank
A25: 45387 | B25: 45387 | C25: 402.46 | D25: 0 | F25: HDFC Securities - Buy | G25: 0.97 | H25: HDFC Securities | I25: HDFC 0094 | J25: HSL | K25: NET PI TO HSL SEC A/C 523686-00602340029434 | L25: HDFC Bank
... A41: 45394 | B41: 45394 | C41: 0 | D41: 30503.75 | F41: HDFC Securities - Sell | G41: 0.97 | H41: HDFC Securities | I41: HDFC 0094 | J41: HSL | K41: NET PO FROM HSL A/C 523686-50200085415108 | L41: HDFC Bank
A42: 45395 | B42: 45395 | C42: 1000 | D42: 0 | E42: Deepika Umesh Mundada | F42: UPI Payment | G42: 0.55 | H42: Personal | I42: AXIS 7042 | J42: Kitty | K42: UPI/P2A/447025620282/DEEPIKA UMESH MUNDADA/kitty/State Bank Of India | L42: Axis Bank
A43: 45397 | B43: 45397 | C43: 0 | D43: 29255.99 | F43: HDFC Securities - Sell | G43: 0.97 | H43: HDFC Securities | I43: HDFC 0094 | J43: HSL | K43: NET PO FROM HSL A/C 523686-50200085415108 | L43: HDFC Bank
A44: 45397 | B44: 45397 | C44: 5000 | D44: 0 | F44: MF Investment | G44: 0.92 | H44: Mutual_Fund_Investments | I44: HDFC 0094 | J44: SIP - 5000 | K44: ACH D- INDIAN CLEARING CORP-P25847643X05 | L44: HDFC Bank
A45: 45397 | B45: 45397 | C45: 1254.81 | D45: 0 | F45: HDFC Securities - Buy | G45: 0.97 | H45: HDFC Securities | I45: HDFC 0094 | J45: HSL | K45: NET PI TO HSL SEC A/C 523686-00602340029434 | L45: HDFC Bank
A46: 45398 | B46: 45398 | C46: 32991.42 | D46: 0 | F46: HDFC Securities - Buy | G46: 0.97 | H46: HDFC Securities | I46: HDFC 0094 | J46: HSL | K46: NET PI TO HSL SEC A/C 523686-00602340029434 | L46: HDFC Bank
A47: 45398 | B47: 45398 | C47: 10000 | D47: 0 | F47: SIP | G47: 0.9 | H47: SIP | I47: HDFC 0094 | J47: Electricity Bill | K47: YHDF2301816719/BILLDKINDIANCLEARING | L47: HDFC Bank
A48: 45398 | B48: 45398 | C48: 0 | D48: 29141.48 | F48: HDFC Securities - Sell | G48: 0.97 | H48: HDFC Securities | I48: HDFC 0094 | J48: HSL | K48: NET PO FROM HSL A/C 523686-50200085415108 | L48: HDFC Bank
A49: 45398 | B49: 45398 | C49: 400.81 | D49: 0 | F49: HDFC Securities - Buy | G49: 0.97 | H49: HDFC Securities | I49: HDFC 0094 | J49: HSL | K49: NET PI TO HSL SEC A/C 523686-00602340029434 | L49: HDFC Bank
A50: 45400 | B50: 45400 | C50: 0 | D50: 10255.18 | F50: HDFC Securities - Sell | G50: 0.97 | H50: HDFC Securities | I50: HDFC 0094 | J50: HSL | K50: NET PO FROM HSL A/C 523686-50200085415108 | L50: HDFC Bank
A51: 45400 | B51: 45400 | C51: 731.06 | D51: 0 | F51: HDFC Securities - Buy | G51: 0.97 | H51: HDFC Securities | I51: HDFC 0094 | J51: HSL | K51: NET PI TO HSL SEC A/C 523686-00602340029434 | L51: HDFC Bank
A52: 45400 | B52: 45400 | C52: 20472.73 | D52: 0 | F52: HDFC Securities - Buy | G52: 0.97 | H52: HDFC Securities | I52: HDFC 0094 | J52: HSL | K52: NET PI TO HSL SEC A/C 523686-00602340029434 | L52: HDFC Bank
A53: 45401 | B53: 45401 | C53: 26524.15 | D53: 0 | F53: HDFC Securities - Buy | G53: 0.97 | H53: HDFC Securities | I53: HDFC 0094 | J53: HSL | K53: NET PI TO HSL SEC A/C 523686-00602340029434 | L53: HDFC Bank
A54: 45401 | B54: 45401 | C54: 401.53 | D54: 0 | F54: HDFC Securities - Buy | G54: 0.97 | H54: HDFC Securities | I54: HDFC 0094 | J54: HSL | K54: NET PI TO HSL SEC A/C 523686-00602340029434 | L54: HDFC Bank
A55: 45404 | B55: 45404 | C55: 1243.71 | D55: 0 | F55: HDFC Securities - Buy | G55: 0.97 | H55: HDFC Securities | I55: HDFC 0094 | J55: HSL | K55: NET PI TO HSL SEC A/C 523686-00602340029434 | L55: HDFC Bank
A56: 45405 | B56: 45405 | C56: 390 | D56: 0 | E56: Bharti Ratan Devnani | F56: UPI Payment | G56: 0.55 | H56: Personal | I56: AXIS 7042 | J56: Household Expenses | K56: UPI/P2A/448073432191/BHARTI RATAN DEVNANI /tiffin/Union Bank of India | L56: Axis Bank
A57: 45405 | B57: 45405 | C57: 100000 | D57: 0 | F57: Transfer - Sunita Gupta | G57: 0.88 | H57: Sunita Gupta | I57: HDFC 0094 | J57: Transfer from Ajay | K57: 01671000085930-TPT-MONEY RETURNED FROM SUNITA TO AKG-AJAY KUMAR GUPTA | L57: HDFC Bank
A58: 45405 | B58: 45405 | C58: 0 | D58: 89361.65 | F58: HDFC Securities - Sell | G58: 0.97 | H58: HDFC Securities | I58: HDFC 0094 | J58: HSL | K58: NET PO FROM HSL A/C 523686-50200085415108 | L58: HDFC Bank
A59: 45405 | B59: 45405 | C59: 0 | D59: 19918.93 | F59: HDFC Securities - Sell | G59: 0.97 | H59: HDFC Securities | I59: HDFC 0094 | J59: HSL | K59: NET PO FROM HSL A/C 523686-50200085415108 | L59: HDFC Bank
A60: 45405 | B60: 45405 | C60: 425.91 | D60: 0 | F60: HDFC Securities - Buy | G60: 0.97 | H60: HDFC Securities | I60: HDFC 0094 | J60: HSL | K60: NET PI TO HSL SEC A/C 523686-00602340029434 | L60: HDFC Bank
A61: 45406 | B61: 45406 | C61: 376.18 | D61: 0 | F61: HDFC Securities - Buy | G61: 0.97 | H61: HDFC Securities | I61: HDFC 0094 | J61: HSL | K61: NET PI TO HSL SEC A/C 523686-00602340029434 | L61: HDFC Bank
A62: 45406 | B62: 45406 | C62: 0 | D62: 15099.63 | F62: HDFC Securities - Sell | G62: 0.97 | H62: HDFC Securities | I62: HDFC 0094 | J62: HSL | K62: NET PO FROM HSL A/C 523686-50200085415108 | L62: HDFC Bank
A63: 45406 | B63: 45406 | C63: 18664 | D63: 0 | F63: SIP | G63: 0.9 | H63: SIP | I63: HDFC 0094 | J63: Electricity Bill | K63: YHDF2309213912/BILLDKTHECALCUTTAELE | L63: HDFC Bank
A64: 45406 | B64: 45406 | C64: 150 | D64: 0 | E64: Kunal Eaknath Makune | F64: UPI Payment | G64: 0.55 | H64: Personal | I64: AXIS 7042 | J64: Household Expenses | K64: UPI/P2M/448166340115/KUNAL EAKNATH MAKUNE /milk/Yes Bank Ltd | L64: Axis Bank
A65: 45407 | B65: 45407 | C65: 83979.75 | D65: 0 | F65: HDFC Securities - Buy | G65: 0.97 | H65: HDFC Securities | I65: HDFC 0094 | J65: HSL | K65: NET PI TO HSL SEC A/C 523686-00602340029434 | L65: HDFC Bank
A66: 45407 | B66: 45407 | C66: 0 | D66: 84.57 | F66: Dividend Income | G66: 0.85 | H66: Dividend Income | I66: HDFC 0094 | J66: MF - Dividend | K66: NEFT CR-UTIB0000004-AXIS MUTUAL FUND DIVIDEND A/C-SUNITA GUPTA-AXISCN0597839178 | L66: HDFC Bank
A67: 45407 | B67: 45407 | C67: 374.11 | D67: 0 | F67: HDFC Securities - Buy | G67: 0.97 | H67: HDFC Securities | I67: HDFC 0094 | J67: HSL | K67: NET PI TO HSL SEC A/C 523686-00602340029434 | L67: HDFC Bank
A68: 45407 | B68: 45407 | C68: 0 | D68: 42290.74 | F68: HDFC Securities - Sell | G68: 0.97 | H68: HDFC Securities | I68: HDFC 0094 | J68: HSL | K68: NET PO FROM HSL A/C 523686-50200085415108 | L68: HDFC Bank
A69: 45407 | B69: 45407 | C69: 0 | D69: 74786.99 | F69: HDFC Securities - Sell | G69: 0.97 | H69: HDFC Securities | I69: HDFC 0094 | J69: HSL | K69: NET PO FROM HSL A/C 523686-50200085415108 | L69: HDFC Bank
A70: 45407 | B70: 45407 | C70: 10000 | D70: 0 | F70: MF Investment | G70: 0.92 | H70: Mutual_Fund_Investments | I70: HDFC 0094 | J70: SIP - 10000 | K70: ACH D- INDIAN CLEARING CORP-P25847643X05 | L70: HDFC Bank
A71: 45408 | B71: 45408 | C71: 0 | D71: 4251.5 | F71: NEFT Transfer | G71: 0.7 | H71: Transfer | I71: AXIS 7042 | J71: Zerodha | K71: NEFT/YESB41177892573/ZERODHA BROKING LTD-DSCNB A//YES BANK/YESB0000001 | L71: Axis Bank
A72: 45408 | B72: 45408 | C72: 0 | D72: 1478.14 | F72: HDFC Securities - Sell | G72: 0.97 | H72: HDFC Securities | I72: HDFC 0094 | J72: HSL | K72: NET PO FROM HSL A/C 523686-50200085415108 | L72: HDFC Bank
A73: 45408 | B73: 45408 | C73: 0 | D73: 19816.62 | F73: HDFC Securities - Sell | G73: 0.97 | H73: HDFC Securities | I73: HDFC 0094 | J73: HSL | K73: NET PO FROM HSL A/C 523686-50200085415108 | L73: HDFC Bank
A74: 45408 | B74: 45408 | C74: 308.18 | D74: 0 | F74: HDFC Securities - Buy | G74: 0.97 | H74: HDFC Securities | I74: HDFC 0094 | J74: HSL | K74: NET PI TO HSL SEC A/C 523686-00602340029434 | L74: HDFC Bank
A75: 45408 | B75: 45408 | C75: 41835.78 | D75: 0 | F75: HDFC Securities - Buy | G75: 0.97 | H75: HDFC Securities | I75: HDFC 0094 | J75: HSL | K75: NET PI TO HSL SEC A/C 523686-00602340029434 | L75: HDFC Bank
A76: 45411 | B76: 45411 | C76: 0 | D76: 1181.14 | F76: HDFC Securities - Sell | G76: 0.97 | H76: HDFC Securities | I76: HDFC 0094 | J76: HSL | K76: NET PO FROM HSL A/C 523686-50200085415108 | L76: HDFC Bank
... A113: 45422 | B113: 45422 | C113: 0 | D113: 349.85 | F113: HDFC Securities - Sell | G113: 0.97 | H113: HDFC Securities | I113: HDFC 0094 | J113: HSL | K113: NET PO FROM HSL A/C 523686-50200085415108 | L113: HDFC Bank
A114: 45422 | B114: 45422 | C114: 1320 | D114: 0 | E114: Premji Traders | F114: UPI Payment | G114: 0.55 | H114: Personal | I114: AXIS 7042 | J114: Household Expenses | K114: UPI/P2M/413124576623/PREMJI TRADERS /UPI/Yes Bank Ltd | L114: Axis Bank
A115: 45422 | B115: 45422 | C115: 0 | D115: 18664 | F115: Received - Sunita Gupta | G115: 0.88 | H115: Sunita Gupta | I115: HDFC 0094 | J115: Rental Income | K115: NEFT CR-SBIN0004266-SBI GENERAL INSURANCE CO LTDSBI GEN-SUNITA GUPTA 0000000002717756-SBIN324131864994 | L115: HDFC Bank
A116: 45422 | B116: 45422 | C116: 230.71 | D116: 0 | F116: HDFC Securities - Buy | G116: 0.97 | H116: HDFC Securities | I116: HDFC 0094 | J116: HSL | K116: NET PI TO HSL SEC A/C 523686-00602340029434 | L116: HDFC Bank
A117: 45422 | B117: 45422 | C117: 12572.1 | D117: 0 | F117: HDFC Securities - Buy | G117: 0.97 | H117: HDFC Securities | I117: HDFC 0094 | J117: HSL | K117: NET PI TO HSL SEC A/C 523686-00602340029434 | L117: HDFC Bank
A118: 45422 | B118: 45422 | C118: 6380.74 | D118: 0 | F118: HDFC Securities - Buy | G118: 0.97 | H118: HDFC Securities | I118: HDFC 0094 | J118: HSL | K118: NET PI TO HSL SEC A/C 523686-00602340029434 | L118: HDFC Bank
A119: 45425 | B119: 45425 | C119: 759.6 | D119: 0 | F119: HDFC Securities - Buy | G119: 0.97 | H119: HDFC Securities | I119: HDFC 0094 | J119: HSL | K119: NET PI TO HSL SEC A/C 523686-00602340029434 | L119: HDFC Bank
A120: 45425 | B120: 45425 | C120: 920.99 | D120: 0 | F120: HDFC Securities - Buy | G120: 0.97 | H120: HDFC Securities | I120: HDFC 0094 | J120: HSL | K120: NET PI TO HSL SEC A/C 523686-00602340029434 | L120: HDFC Bank
A121: 45426 | B121: 45426 | C121: 272.35 | D121: 0 | F121: HDFC Securities - Buy | G121: 0.97 | H121: HDFC Securities | I121: HDFC 0094 | J121: HSL | K121: NET PI TO HSL SEC A/C 523686-00602340029434 | L121: HDFC Bank
A122: 45426 | B122: 45426 | C122: 0 | D122: 2084.4 | F122: HDFC Securities - Sell | G122: 0.97 | H122: HDFC Securities | I122: HDFC 0094 | J122: HSL | K122: NET PO FROM HSL A/C 523686-50200085415108 | L122: HDFC Bank
A123: 45427 | B123: 45427 | C123: 0 | D123: 10981.68 | F123: HDFC Securities - Sell | G123: 0.97 | H123: HDFC Securities | I123: HDFC 0094 | J123: HSL | K123: NET PO FROM HSL A/C 523686-50200085415108 | L123: HDFC Bank
A124: 45427 | B124: 45427 | C124: 0 | D124: 100000 | F124: Received - Sunita Gupta | G124: 0.88 | H124: Sunita Gupta | I124: AXIS 7042 | J124: Contra | K124: NEFT/N136243040620640/SUNITA GUPTA/HDFC BANK/frm HDFC to Axis | L124: Axis Bank
A125: 45427 | B125: 45427 | C125: 40000 | D125: 0 | F125: Transfer - Ajay Gupta | G125: 0.88 | H125: Ajay Gupta | I125: AXIS 7042 | J125: Transfer from Ajay | K125: INB/IFT/Ajay Kumar Gupta/TPARTY TRANSFER | L125: Axis Bank
A126: 45427 | B126: 45427 | C126: 0 | D126: 134185.19 | F126: HDFC Securities - Sell | G126: 0.97 | H126: HDFC Securities | I126: HDFC 0094 | J126: HSL | K126: NET PO FROM HSL A/C 523686-50200085415108 | L126: HDFC Bank
... A221: 45464 | B221: 45464 | C221: 31329 | D221: 0 | F221: SIP | G221: 0.9 | H221: SIP | I221: HDFC 0094 | J221: Electricity Bill | K221: YHDF2359276422/BILLDKTHECALCUTTAELE | L221: HDFC Bank
A222: 45465 | B222: 45465 | C222: 1000 | D222: 0 | E222: Prerana Manoj Chandak | F222: UPI Payment | G222: 0.55 | H222: Personal | I222: AXIS 7042 | J222: Kitty | K222: UPI/P2A/454025238186/PRERANA MANOJ CHANDAK/kitty/Axis Bank Ltd. | L222: Axis Bank
A223: 45467 | B223: 45467 | C223: 0 | D223: 50000 | F223: Received - Sunita Gupta | G223: 0.88 | H223: Sunita Gupta | I223: AXIS 7042 | J223: Contra | K223: NEFT/N176243108305610/SUNITA GUPTA/HDFC BANK/Trf frm Sunita HDF | L223: Axis Bank
A224: 45467 | B224: 45467 | C224: 25000 | D224: 0 | F224: Transfer - Sunita Gupta | G224: 0.88 | H224: Sunita Gupta | I224: HDFC 0094 | J224: Contra | K224: NEFT DR-UTIB0002656-SUNITA GUPTA-NETBANK, MUM-N176243109164220-TFR FRM AXIS 2 HFC | L224: HDFC Bank
A225: 45467 | B225: 45467 | C225: 1135.23 | D225: 0 | F225: HDFC Securities - Buy | G225: 0.97 | H225: HDFC Securities | I225: HDFC 0094 | J225: HSL | K225: NET PI TO HSL SEC A/C 523686-00602340029434 | L225: HDFC Bank
A226: 45467 | B226: 45467 | C226: 50000 | D226: 0 | F226: Transfer - Sunita Gupta | G226: 0.88 | H226: Sunita Gupta | I226: HDFC 0094 | J226: Contra | K226: NEFT DR-UTIB0002656-SUNITA GUPTA-NETBANK, MUM-N176243108305610-TRF FRM SUNITA HDF | L226: HDFC Bank
A227: 45467 | B227: 45467 | C227: 30000 | D227: 0 | F227: Zerodha Broking | G227: 0.88 | H227: Zerodha Broking Limited | I227: AXIS 7042 | J227: Zerodha | K227: UPI/P2M/417673480863/ZERODHA BROKING LIMIT/102002/ICICI Bank | L227: Axis Bank | M227: ⚠ Possible Duplicate
A228: 45467 | B228: 45467 | C228: 0 | D228: 19521.12 | F228: HDFC Securities - Sell | G228: 0.97 | H228: HDFC Securities | I228: HDFC 0094 | J228: HSL | K228: NET PO FROM HSL A/C 523686-50200085415108 | L228: HDFC Bank
A229: 45467 | B229: 45467 | C229: 0 | D229: 25000 | F229: Received - Sunita Gupta | G229: 0.88 | H229: Sunita Gupta | I229: AXIS 7042 | J229: Contra | K229: NEFT/N176243109164220/SUNITA GUPTA/HDFC BANK/tfr frm Axis 2 hfc | L229: Axis Bank
A230: 45467 | B230: 45467 | C230: 30000 | D230: 0 | F230: Zerodha Broking | G230: 0.88 | H230: Zerodha Broking Limited | I230: AXIS 7042 | J230: Zerodha | K230: UPI/P2M/417673461227/ZERODHA BROKING LIMIT/922743/ICICI Bank | L230: Axis Bank | M230: ⚠ Possible Duplicate
A231: 45467 | B231: 45467 | C231: 0 | D231: 25173.36 | F231: HDFC Securities - Sell | G231: 0.97 | H231: HDFC Securities | I231: HDFC 0094 | J231: HSL | K231: NET PO FROM HSL A/C 523686-50200085415108 | L231: HDFC Bank
A232: 45468 | B232: 45468 | C232: 0 | D232: 34583.15 | F232: HDFC Securities - Sell | G232: 0.97 | H232: HDFC Securities | I232: HDFC 0094 | J232: HSL | K232: NET PO FROM HSL A/C 523686-50200085415108 | L232: HDFC Bank
A233: 45468 | B233: 45468 | C233: 0 | D233: 86730.8 | F233: HDFC Securities - Sell | G233: 0.97 | H233: HDFC Securities | I233: HDFC 0094 | J233: HSL | K233: NET PO FROM HSL A/C 523686-50200085415108 | L233: HDFC Bank
A234: 45468 | B234: 45468 | C234: 150000 | D234: 0 | F234: Transfer - Sunita Gupta | G234: 0.88 | H234: Sunita Gupta | I234: HDFC 0094 | J234: Transfer from Ajay | K234: 01671000085930-TPT-MARRIAGE EXPENSES FROM SUNITA-AJAY KUMAR GUPTA | L234: HDFC Bank
A235: 45468 | B235: 45468 | C235: 370.62 | D235: 0 | F235: HDFC Securities - Buy | G235: 0.97 | H235: HDFC Securities | I235: HDFC 0094 | J235: HSL | K235: NET PI TO HSL SEC A/C 523686-00602340029434 | L235: HDFC Bank
A236: 45468 | B236: 45468 | C236: 0 | D236: 720 | F236: Dividend Income | G236: 0.88 | H236: Dividend Income | I236: HDFC 0094 | J236: Dividend Income | K236: ACH C- HINDUSTANUNILEVERL-00000000000030 | L236: HDFC Bank
A237: 45468 | B237: 45468 | C237: 0 | D237: 50 | F237: Dividend Income | G237: 0.88 | H237: Dividend Income | I237: HDFC 0094 | J237: Dividend Income | K237: ACH C- HIMADRI SPECIALITY C-NIN300476410 | L237: HDFC Bank
A238: 45468 | B238: 45468 | C238: 31517.3 | D238: 0 | F238: HDFC Securities - Buy | G238: 0.97 | H238: HDFC Securities | I238: HDFC 0094 | J238: HSL | K238: NET PI TO HSL SEC A/C 523686-00602340029434 | L238: HDFC Bank
A239: 45468 | B239: 45468 | C239: 0 | D239: 169 | F239: Bank Interest | G239: 0.9 | H239: Bank Interest | I239: SBI 7685 | J239: Bank Interest | K239: CREDIT INTEREST--- | L239: State Bank of India
A240: 45468 | B240: 45468 | C240: 10000 | D240: 0 | F240: MF Investment | G240: 0.92 | H240: Mutual_Fund_Investments | I240: HDFC 0094 | J240: SIP - 10000 | K240: ACH D- INDIAN CLEARING CORP-P25847643X05 | L240: HDFC Bank
A241: 45469 | B241: 45469 | C241: 5260.5 | D241: 0 | F241: HDFC Securities - Buy | G241: 0.97 | H241: HDFC Securities | I241: HDFC 0094 | J241: HSL | K241: NET PI TO HSL SEC A/C 523686-00602340029434 | L241: HDFC Bank
A242: 45469 | B242: 45469 | C242: 0 | D242: 7425.28 | F242: HDFC Securities - Sell | G242: 0.97 | H242: HDFC Securities | I242: HDFC 0094 | J242: HSL | K242: NET PO FROM HSL A/C 523686-50200085415108 | L242: HDFC Bank
... A249: 45471 | B249: 45471 | C249: 315.89 | D249: 0 | F249: HDFC Securities - Buy | G249: 0.97 | H249: HDFC Securities | I249: HDFC 0094 | J249: HSL | K249: NET PI TO HSL SEC A/C 523686-00602340029434 | L249: HDFC Bank
A250: 45472 | B250: 45472 | C250: 770 | D250: 0 | E250: Bharti Ratan Devnani | F250: UPI Payment | G250: 0.55 | H250: Personal | I250: AXIS 7042 | J250: Household Expenses | K250: UPI/P2A/418192452596/BHARTI RATAN DEVNANI /tiffin/Union Bank of India | L250: Axis Bank
A251: 45473 | B251: 45473 | C251: 0 | D251: 567 | F251: Bank Interest | G251: 0.95 | H251: Bank Interest | I251: HDFC 0094 | J251: Bank Interest | K251: INTEREST PAID TILL 30-JUN-2024 | L251: HDFC Bank
A252: 45474 | B252: 45474 | C252: 0 | D252: 805 | F252: Dividend Income | G252: 0.85 | H252: Dividend Income | I252: AXIS 7042 | J252: Dividend Income | K252: ACH-CR-CANBANK DIV 2023-24-NACH-6544153-6544153 | L252: Axis Bank
...

Sheet Conso
A1: Aayush Kumar Gupta
A2: Account of Statements from 01-Apr-2024 to 29-Mar-2025 | D2: =SUM(D5:D929) | E2: =SUM(E5:E929) | F2: =E2-D2
A4: TX Date | B4: Particulars | C4: Ref | D4: DR | E4: CR | F4: Balance | G4: Account Head | H4: Account No
A5: 45383 | B5: NET PI TO HSL SEC A/C 523686-00602340029434 | C5: 0000000508932363 | D5: 1672 | E5: 0 | F5: 31564 | G5: HDFC Securities | H5: HDFC 0094
A6: 45384 | B6: NET PO FROM HSL A/C 523686-50200085415108 | C6: 0000000509188445 | D6: 0 | E6: 16753.39 | F6: 48317.39 | G6: HDFC Securities | H6: HDFC 0094
A7: 45384 | B7: NET PO FROM HSL A/C 523686-50200085415108 | C7: 0000000509246217 | D7: 0 | E7: 97641.5 | F7: 145958.89 | G7: HDFC Securities | H7: HDFC 0094
A8: 45384 | B8: NET PI TO HSL SEC A/C 523686-00602340029434 | C8: 0000000509399140 | D8: 418 | E8: 0 | F8: 145540.89 | G8: HDFC Securities | H8: HDFC 0094
A9: 45384 | B9: NET PI TO HSL SEC A/C 523686-00602340029434 | C9: 0000000509532005 | D9: 103098.99 | E9: 0 | F9: 42441.9 | G9: HDFC Securities | H9: HDFC 0094
A10: 45385 | B10: NET PO FROM HSL A/C 523686-50200085415108 | C10: 0000000509650601 | D10: 0 | E10: 1514.95 | F10: 43956.85 | G10: HDFC Securities | H10: HDFC 0094
A11: 45385 | B11: NET PI TO HSL SEC A/C 523686-00602340029434 | C11: 0000000509793906 | D11: 379.22 | E11: 0 | F11: 43577.63 | G11: HDFC Securities | H11: HDFC 0094
A12: 45386 | B12: NET PO FROM HSL A/C 523686-50200085415108 | C12: 0000000510056916 | D12: 0 | E12: 6701.42 | F12: 50279.05 | G12: HDFC Securities | H12: HDFC 0094
A13: 45386 | B13: 50100128155413-TPT-TO MUMMY-AAYUSH KUMAR GUPTA | C13: 0000000526007002 | D13: 0 | E13: 30000 | F13: 80279.05 | G13: Transfer | H13: HDFC 0094
A14: 45386 | B14: NET PI TO HSL SEC A/C 523686-00602340029434 | C14: 0000000510198174 | D14: 425.81 | E14: 0 | F14: 79853.24 | G14: HDFC Securities | H14: HDFC 0094
A15: 45386 | B15: NET PI TO HSL SEC A/C 523686-00602340029434 | C15: 0000000510339907 | D15: 72828.22 | E15: 0 | F15: 7025.02 | G15: HDFC Securities | H15: HDFC 0094
A16: 45387 | B16: NET PI TO HSL SEC A/C 523686-00602340029434 | C16: 0000000510610766 | D16: 402.46 | E16: 0 | F16: 6622.56 | G16: HDFC Securities | H16: HDFC 0094
... A81: 45415 | B81: NET PI TO HSL SEC A/C 523686-00602340029434 | C81: 0000000518339597 | D81: 10104.28 | E81: 0 | F81: 129461.15 | G81: HDFC Securities | H81: HDFC 0094
A82: 45415 | B82: ATM WDL-ATM CASH 3233 SBI SHIVAJI NAGAR ATM NASHIK-- | D82: 2000 | E82: 0 | F82: 24120.7 | G82: Cash | H82: SBI 7685
A83: 45415 | B83: NET PI TO HSL SEC A/C 523686-00602340029434 | C83: 0000000518405610 | D83: 56293.41 | E83: 0 | F83: 73167.74 | G83: HDFC Securities | H83: HDFC 0094
A84: 45415 | B84: ATM-CASH-AXIS/BPRH265601/1296/030524/NASHIK | C84: - | D84: 2000 | E84: 0 | F84: 10156.12 | G84: Cash | H84: AXIS 7042
A85: 45418 | B85: NET PO FROM HSL A/C 523686-50200085415108 | C85: 0000000518591456 | D85: 0 | E85: 4235.46 | F85: 77403.2 | G85: HDFC Securities | H85: HDFC 0094
A86: 45418 | B86: NET PI TO HSL SEC A/C 523686-00602340029434 | C86: 0000000518796402 | D86: 572.91 | E86: 0 | F86: 76830.29 | G86: HDFC Securities | H86: HDFC 0094
A87: 45419 | B87: NET PI TO HSL SEC A/C 523686-00602340029434 | C87: 0000000519455052 | D87: 25590.3 | E87: 0 | F87: 79699.58 | G87: HDFC Securities | H87: HDFC 0094
A88: 45419 | B88: NET PI TO HSL SEC A/C 523686-00602340029434 | C88: 0000000519502107 | D88: 414.01 | E88: 0 | F88: 79285.57 | G88: HDFC Securities | H88: HDFC 0094
A89: 45419 | B89: NET PI TO HSL SEC A/C 523686-00602340029434 | C89: 0000000519276521 | D89: 244.98 | E89: 0 | F89: 105289.88 | G89: HDFC Securities | H89: HDFC 0094
A90: 45419 | B90: NET PO FROM HSL A/C 523686-50200085415108 | C90: 0000000519124423 | D90: 0 | E90: 28704.57 | F90: 105534.86 | G90: HDFC Securities | H90: HDFC 0094
A91: 45420 | B91: UPI/P2M/412955259759/Zerodha Broking Ltd /001847/HDFC BANK LTD | C91: - | D91: 50000 | E91: 0 | F91: 10156.12 | G91: Zerodha Broking Limited | H91: AXIS 7042
A92: 45420 | B92: NET PO FROM HSL A/C 523686-50200085415108 | C92: 0000000519626421 | D92: 0 | E92: 100255.34 | F92: 179540.91 | G92: HDFC Securities | H92: HDFC 0094
A93: 45420 | B93: NET PI TO HSL SEC A/C 523686-00602340029434 | C93: 0000000519739579 | D93: 217.06 | E93: 0 | F93: 179323.85 | G93: HDFC Securities | H93: HDFC 0094
A94: 45420 | B94: NEFT DR-UTIB0002656-SUNITA GUPTA-NETBANK, MUM-N129243028299413-TRANSFER FROM HDFC | C94: N129243028299413 | D94: 50000 | E94: 0 | F94: 129323.85 | G94: Sunita Gupta | H94: HDFC 0094
... A229: 45468 | B229: NET PI TO HSL SEC A/C 523686-00602340029434 | C229: 0000000535062991 | D229: 31517.3 | E229: 0 | F229: 81011.44 | G229: HDFC Securities | H229: HDFC 0094
A230: 45468 | B230: CREDIT INTEREST--- | D230: 0 | E230: 169 | F230: 24289.7 | G230: Bank Interest | H230: SBI 7685
A231: 45468 | B231: ACH D- INDIAN CLEARING CORP-P25847643X05 | C231: 0000005424732775 | D231: 10000 | E231: 0 | F231: 262129.36 | G231: Mutual_Fund_Investments | H231: HDFC 0094
A232: 45469 | B232: NET PI TO HSL SEC A/C 523686-00602340029434 | C232: 0000000535488603 | D232: 5260.5 | E232: 0 | F232: 133225.42 | G232: HDFC Securities | H232: HDFC 0094
A233: 45469 | B233: NET PO FROM HSL A/C 523686-50200085415108 | C233: 0000000535184207 | D233: 0 | E233: 7425.28 | F233: 88436.72 | G233: HDFC Securities | H233: HDFC 0094
A234: 45469 | B234: NET PO FROM HSL A/C 523686-50200085415108 | C234: 0000000535222691 | D234: 0 | E234: 50389.77 | F234: 138826.49 | G234: HDFC Securities | H234: HDFC 0094
A235: 45469 | B235: NET PI TO HSL SEC A/C 523686-00602340029434 | C235: 0000000535337288 | D235: 340.57 | E235: 0 | F235: 138485.92 | G235: HDFC Securities | H235: HDFC 0094
A236: 45470 | B236: NEFT CR-UTIB0000004-AXIS MUTUAL FUND DIVIDEND A/C-SUNITA GUPTA-AXISCN0662480411 | C236: AXISCN0662480411 | D236: 0 | E236: 84.57 | F236: 132993.15 | G236: Dividend Income | H236: HDFC 0094
A237: 45470 | B237: NET PI TO HSL SEC A/C 523686-00602340029434 | C237: 0000000535761235 | D237: 316.84 | E237: 0 | F237: 132908.58 | G237: HDFC Securities | H237: HDFC 0094
A238: 45470 | B238: NET PI TO HSL SEC A/C 523686-00602340029434 | C238: 0000000535933355 | D238: 2666.08 | E238: 0 | F238: 130327.07 | G238: HDFC Securities | H238: HDFC 0094
A239: 45471 | B239: ACH C- LTIMIN FINAL 2023 24-213986 | C239: 0000005527258486 | D239: 0 | E239: 1800 | F239: 132127.07 | G239: Dividend Income | H239: HDFC 0094
A240: 45471 | B240: NET PI TO HSL SEC A/C 523686-00602340029434 | C240: 0000000536193081 | D240: 315.89 | E240: 0 | F240: 131811.18 | G240: HDFC Securities | H240: HDFC 0094
A241: 45472 | B241: UPI/P2A/418192452596/BHARTI RATAN DEVNANI /tiffin/Union Bank of India | C241: - | D241: 770 | E241: 0 | F241: 34084.75 | G241: Personal | H241: AXIS 7042
A242: 45473 | B242: INTEREST PAID TILL 30-JUN-2024 | C242: 000000000000000 | D242: 0 | E242: 567 | F242: 132378.18 | G242: Bank Interest | H242: HDFC 0094
... A249: 45474 | B249: ACH C- CANBANK DIV 2023-24-6273195 | C249: 0000005519468069 | D249: 0 | E249: 1610 | F249: 162070.88 | G249: Dividend Income | H249: HDFC 0094
A250: 45474 | B250: ATM WDL-ATM CASH 2734 SBI SHIVAJI NAGAR ATM NASHIK-- | D250: 2000 | E250: 0 | F250: 22289.7 | G250: Cash | H250: SBI 7685
A251: 45474 | B251: NET PI TO HSL SEC A/C 523686-00602340029434 | C251: 0000000536692596 | D251: 947.67 | E251: 0 | F251: 160460.88 | G251: HDFC Securities | H251: HDFC 0094
A252: 45475 | B252: NET PI TO HSL SEC A/C 523686-00602340029434 | C252: 0000000537161174 | D252: 306 | E252: 0 | F252: 170833.53 | G252: HDFC Securities | H252: HDFC 0094
A253: 45475 | B253: NET PO FROM HSL A/C 523686-50200085415108 | C253: 0000000537004329 | D253: 0 | E253: 11268.65 | F253: 171139.53 | G253: HDFC Securities | H253: HDFC 0094
A254: 45475 | B254: NET PI TO HSL SEC A/C 523686-00602340029434 | C254: 0000000537348821 | D254: 49494.48 | E254: 0 | F254: 121339.05 | G254: HDFC Securities | H254: HDFC 0094
A255: 45476 | B255: NET PI TO HSL SEC A/C 523686-00602340029434 | C255: 0000000537624361 | D255: 283.44 | E255: 0 | F255: 121055.61 | G255: HDFC Securities | H255: HDFC 0094
A256: 45476 | B256: NEFT/YESEB41852036982/ZERODHA BROKING LTD- FOR ZER/YES BANK/4565c0180515af30213b5d Zerodh | C256: - | D256: 0 | E256: 3688.79 | F256: 36786.54 | G256: Transfer | H256: AXIS 7042
A257: 45477 | B257: NET PI TO HSL SEC A/C 523686-00602340029434 | C257: 0000000538072401 | D257: 322.26 | E257: 0 | F257: 125037.77 | G257: HDFC Securities | H257: HDFC 0094
A258: 45477 | B258: NET PI TO HSL SEC A/C 523686-00602340029434 | C258: 0000000538242270 | D258: 3478.18 | E258: 0 | F258: 121559.59 | G258: HDFC Securities | H258: HDFC 0094
A259: 45477 | B259: DR LAL PATH DIV23 2400000000000000009172 | C259: 0000241853654755 | D259: 0 | E259: 210 | F259: 125360.03 | G259: Dividend Income | H259: HDFC 0094
A260: 45477 | B260: NET PO FROM HSL A/C 523686-50200085415108 | C260: 0000000537925180 | D260: 0 | E260: 4094.42 | F260: 125150.03 | G260: HDFC Securities | H260: HDFC 0094
A261: 45478 | B261: NET PI TO HSL SEC A/C 523686-00602340029434 | C261: 0000000538741295 | D261: 77779.54 | E261: 0 | F261: 104543.57 | G261: HDFC Securities | H261: HDFC 0094
A262: 45478 | B262: NEFT CR-SBIN0004266-SBI GENERAL INSURANCE CO LTDSBI GEN-SUNITA GUPTA 0000000002717756-SBIN224187636782 | C262: SBIN224187636782 | D262: 0 | E262: 31329 | F262: 182323.11 | G262: Sunita Gupta | H262: HDFC 0094
... A478: 45553 | B478: NET PI TO HSL SEC A/C 523686-00602340029434 | C478: 0000000563713390 | D478: 36560.41 | E478: 0 | F478: 0 | G478: HDFC Securities | H478: HDFC 0094
A479: 45554 | B479: DEBIT-ATMCard AMC 652294*8079-- | D479: 236 | E479: 0 | F479: 22053.7 | G479: Suspense | H479: SBI 7685
A480: 45554 | B480: NET PO FROM HSL A/C 523686-50200085415108 | C480: 0000000563894192 | D480: 0 | E480: 19217.6 | F480: 19217.6 | G480: HDFC Securities | H480: HDFC 0094
A481: 45554 | B481: NET PI TO HSL SEC A/C 523686-00602340029434 | C481: 0000000564000369 | D481: 329.62 | E481: 0 | F481: 18887.98 | G481: HDFC Securities | H481: HDFC 0094
A482: 45554 | B482: NET PI TO HSL SEC A/C 523686-00602340029434 | C482: 0000000564228802 | D482: 7169.87 | E482: 0 | F482: 11718.11 | G482: HDFC Securities | H482: HDFC 0094
A483: 45555 | B483: NET PI TO HSL SEC A/C 523686-00602340029434 | C483: 0000000564557579 | D483: 366.63 | E483: 0 | F483: 11351.48 | G483: HDFC Securities | H483: HDFC 0094
A484: 45556 | B484: UPI/P2A/463116904245/BHARTI RATAN DEVNANI /tiffin/Union Bank of India | C484: - | D484: 310 | E484: 0 | F484: 225760.62 | G484: Personal | H484: AXIS 7042
A485: 45557 | B485: UPI/P2M/463260761650/SHAS /Paymen/Yes Bank Ltd | C485: - | D485: 422 | E485: 0 | F485: 225338.62 | G485: Personal | H485: AXIS 7042
A486: 45558 | B486: NET PI TO HSL SEC A/C 523686-00602340029434 | C486: 0000000565055253 | D486: 1099.89 | E486: 0 | F486: 98999.37 | G486: HDFC Securities | H486: HDFC 0094
A487: 45558 | B487: YHDF2442937528/BILLDKTHECALCUTTAELE | C487: 0002426762566375 | D487: 16728 | E487: 0 | F487: 82271.37 | G487: SIP | H487: HDFC 0094
A488: 45558 | B488: NET PI TO HSL SEC A/C 523686-00602340029434 | C488: 0000000565232384 | D488: 181.39 | E488: 0 | F488: 82089.98 | G488: HDFC Securities | H488: HDFC 0094
A489: 45558 | B489: FT- 564856018-50200085415108 - HDFC SECURITIES LTD-CLIENT DSCNB A/C - | C489: 0000000779555955 | D489: 0 | E489: 88747.78 | F489: 100099.26 | G489: HDFC Securities | H489: HDFC 0094
A490: 45559 | B490: UPI/P2M/463437357157/SANGITA RAJENDRA MUTH/dentis/Yes Bank Ltd | C490: - | D490: 500 | E490: 0 | F490: 224838.62 | G490: Personal | H490: AXIS 7042
A491: 45559 | B491: NET PI TO HSL SEC A/C 523686-00602340029434 | C491: 0000000565543352 | D491: 339.23 | E491: 0 | F491: 81750.75 | G491: HDFC Securities | H491: HDFC 0094
... A496: 45560 | B496: ATW-498792XXXXXX0500-S1ANMN04-NASHIK | C496: 0000000000005540 | D496: 10000 | E496: 0 | F496: 50445.02 | G496: Cash | H496: HDFC 0094
A497: 45560 | B497: CREDIT INTEREST--- | D497: 0 | E497: 152 | F497: 22205.7 | G497: Bank Interest | H497: SBI 7685
A498: 45561 | B498: NET PI TO HSL SEC A/C 523686-00602340029434 | C498: 0000000566467505 | D498: 313.62 | E498: 0 | F498: 182823.04 | G498: HDFC Securities | H498: HDFC 0094
A499: 45561 | B499: NEFT CR-SBIN0004266-SBI GENERAL INSURANCE CO LTDSBI GEN-SUNITA GUPTA 0000000002717756-SBIN324270219069 | C499: SBIN324270219069 | D499: 0 | E499: 2380 | F499: 185203.04 | G499: Sunita Gupta | H499: HDFC 0094
A500: 45561 | B500: NET PO FROM HSL A/C 523686-50200085415108 | C500: 0000000566338714 | D500: 0 | E500: 132691.64 | F500: 183136.66 | G500: HDFC Securities | H500: HDFC 0094
A501: 45562 | B501: NEFT CR-SBIN0004266-SBI GENERAL INSURANCE CO LTDSBI GEN-SUNITA GUPTA 0000000002717756-SBIN424271842614 | C501: SBIN424271842614 | D501: 0 | E501: 16728 | F501: 154599.16 | G501: Sunita Gupta | H501: HDFC 0094
A502: 45562 | B502: 50100542230922-TPT-FOR EXPENSES TRN TO ARCHIT-ARCHIT GUPTA | C502: 0000000503500292 | D502: 50000 | E502: 0 | F502: 137871.16 | G502: Archit Gupta | H502: HDFC 0094
A503: 45562 | B503: NET PI TO HSL SEC A/C 523686-00602340029434 | C503: 0000000566936909 | D503: 316.1 | E503: 0 | F503: 187871.16 | G503: HDFC Securities | H503: HDFC 0094
A504: 45562 | B504: FT- 566781852-50200085415108 - HDFC SECURITIES LTD-CLIENT DSCNB A/C - | C504: 0000000784623671 | D504: 0 | E504: 2984.22 | F504: 188187.26 | G504: HDFC Securities | H504: HDFC 0094
A505: 45562 | B505: ACH-CR-USL FIN DIV 23 24-NACH-23827-23827 | C505: - | D505: 0 | E505: 250 | F505: 225088.62 | G505: Dividend Income | H505: AXIS 7042
A506: 45563 | B506: UPI/P2M/463877794818/SANGITA RAJENDRA MUTH/dentis/Yes Bank Ltd | C506: - | D506: 1700 | E506: 0 | F506: 223388.62 | G506: Personal | H506: AXIS 7042
A507: 45563 | B507: ATM-CASH/SBI SHIVAJI NAGAR/NASHIK/280924 | C507: - | D507: 10000 | E507: 0 | F507: 213388.62 | G507: Cash | H507: AXIS 7042
A508: 45565 | B508: NET PI TO HSL SEC A/C 523686-00602340029434 | C508: 0000000567395837 | D508: 951.48 | E508: 0 | F508: 159596.45 | G508: HDFC Securities | H508: HDFC 0094
A509: 45565 | B509: FT- 567225434-50200085415108 - HDFC SECURITIES LTD-CLIENT DSCNB A/C - | C509: 0000000786722540 | D509: 0 | E509: 5948.77 | F509: 160547.93 | G509: HDFC Securities | H509: HDFC 0094
... A709: 45651 | B709: YHDF2500679849/BILLDKTHECALCUTTAELE | C709: 0002436071393645 | D709: 11832 | E709: 0 | F709: 9772.68 | G709: SIP | H709: HDFC 0094
A710: 45651 | B710: CREDIT INTEREST--- | D710: 0 | E710: 149 | F710: 22354.7 | G710: Bank Interest | H710: SBI 7685
A711: 45652 | B711: FT- 594273619-50200085415108 - HDFC SECURITIES LTD-CLIENT DSCNB A/C - | C711: 0000000886172799 | D711: 0 | E711: 1057.24 | F711: 10829.92 | G711: HDFC Securities | H711: HDFC 0094
A712: 45652 | B712: ACH D- TP ACH INDIANESIGN-1660009188 | C712: 0000002662972044 | D712: 10000 | E712: 0 | F712: 829.92 | G712: SIP | H712: HDFC 0094
A713: 45652 | B713: NET PI TO HSL SEC A/C 523686-00602340029434 | C713: 0000000594440742 | D713: 829.92 | E713: 0 | F713: 0 | G713: HDFC Securities | H713: HDFC 0094
A714: 45656 | B714: NET PI TO HSL SEC A/C 523686-00602340029434 | C714: 0000000595531923 | D714: 84.57 | E714: 0 | F714: 0 | G714: HDFC Securities | H714: HDFC 0094
A715: 45656 | B715: NEFT CR-UTIB0000004-AXIS MUTUAL FUND DIVIDEND A/C-SUNITA GUPTA-AXISCN0872204867 | C715: AXISCN0872204867 | D715: 0 | E715: 84.57 | F715: 84.57 | G715: Dividend Income | H715: HDFC 0094
A716: 45657 | B716: NET PI TO HSL SEC A/C 523686-00602340029434 | C716: 0000000595927394 | D716: 6300.62 | E716: 0 | F716: 18222.9 | G716: HDFC Securities | H716: HDFC 0094
A717: 45657 | B717: NET PI TO HSL SEC A/C 523686-00602340029434 | C717: 0000000595770114 | D717: 426.63 | E717: 0 | F717: 24523.52 | G717: HDFC Securities | H717: HDFC 0094
A718: 45657 | B718: FT- 595680118-50200085415108 - HDFC SECURITIES LTD-CLIENT DSCNB A/C - | C718: 0000000891478194 | D718: 0 | E718: 24950.15 | F718: 24950.15 | G718: HDFC Securities | H718: HDFC 0094
A719: 45658 | B719: SB:919010088767042:Int.Pd:01-10-2024 to 31-12-2024 | C719: - | D719: 0 | E719: 505 | F719: 32585.37 | G719: Bank Interest | H719: AXIS 7042
A720: 45658 | B720: NET PI TO HSL SEC A/C 523686-00602340029434 | C720: 0000000596236855 | D720: 419.42 | E720: 0 | F720: 18337.48 | G720: HDFC Securities | H720: HDFC 0094
A721: 45658 | B721: INTEREST PAID TILL 31-DEC-2024 | C721: 000000000000000 | D721: 0 | E721: 534 | F721: 18756.9 | G721: Bank Interest | H721: HDFC 0094
A722: 45659 | B722: NET PI TO HSL SEC A/C 523686-00602340029434 | C722: 0000000596618890 | D722: 419.42 | E722: 0 | F722: 19910.73 | G722: HDFC Securities | H722: HDFC 0094
... A911: 45740 | B911: NET PI TO HSL SEC A/C 523686-00602340029434 | C911: 0000000621091728 | D911: 1278.96 | E911: 0 | F911: 14726.68 | G911: HDFC Securities | H911: HDFC 0094
...

Sheet Bank Summary
A1: All Banks
A2: Aayush Gupta Bank Summary
A3: 01-Apr-2024 to 29-Mar-2025
A5: Narration | B5: Total Credit (₹) | C5: Narration | D5: Total Debit (₹)
A6: Bank Charges | B6: =SUMIFS('For Tally'!D:D, 'For Tally'!F:F, A6) | C6: Bank Charges | D6: =SUMIFS('For Tally'!C:C, 'For Tally'!F:F, C6)
A7: Bank Interest | B7: =SUMIFS('For Tally'!D:D, 'For Tally'!F:F, A7) | C7: Bank Interest | D7: =SUMIFS('For Tally'!C:C, 'For Tally'!F:F, C7)
A8: Cash Deposit | B8: =SUMIFS('For Tally'!D:D, 'For Tally'!F:F, A8) | C8: Cash Deposit | D8: =SUMIFS('For Tally'!C:C, 'For Tally'!F:F, C8)
A9: Cash Withdrawal | B9: =SUMIFS('For Tally'!D:D, 'For Tally'!F:F, A9) | C9: Cash Withdrawal | D9: =SUMIFS('For Tally'!C:C, 'For Tally'!F:F, C9)
A10: Depository Charges | B10: =SUMIFS('For Tally'!D:D, 'For Tally'!F:F, A10) | C10: Depository Charges | D10: =SUMIFS('For Tally'!C:C, 'For Tally'!F:F, C10)
A11: Dividend Income | B11: =SUMIFS('For Tally'!D:D, 'For Tally'!F:F, A11) | C11: Dividend Income | D11: =SUMIFS('For Tally'!C:C, 'For Tally'!F:F, C11)
A12: HDFC Securities - Buy | B12: =SUMIFS('For Tally'!D:D, 'For Tally'!F:F, A12) | C12: HDFC Securities - Buy | D12: =SUMIFS('For Tally'!C:C, 'For Tally'!F:F, C12)
A13: HDFC Securities - Sell | B13: =SUMIFS('For Tally'!D:D, 'For Tally'!F:F, A13) | C13: HDFC Securities - Sell | D13: =SUMIFS('For Tally'!C:C, 'For Tally'!F:F, C13)
A14: HDFC Securities - Settlement | B14: =SUMIFS('For Tally'!D:D, 'For Tally'!F:F, A14) | C14: HDFC Securities - Settlement | D14: =SUMIFS('For Tally'!C:C, 'For Tally'!F:F, C14)
A15: Health Insurance | B15: =SUMIFS('For Tally'!D:D, 'For Tally'!F:F, A15) | C15: Health Insurance | D15: =SUMIFS('For Tally'!C:C, 'For Tally'!F:F, C15)
A16: Income Tax Refund | B16: =SUMIFS('For Tally'!D:D, 'For Tally'!F:F, A16) | C16: Income Tax Refund | D16: =SUMIFS('For Tally'!C:C, 'For Tally'!F:F, C16)
A17: Internal Transfer | B17: =SUMIFS('For Tally'!D:D, 'For Tally'!F:F, A17) | C17: Internal Transfer | D17: =SUMIFS('For Tally'!C:C, 'For Tally'!F:F, C17)
... A50: Zerodha Broking | B50: =SUMIFS('For Tally'!D:D, 'For Tally'!F:F, A50) | C50: Zerodha Broking | D50: =SUMIFS('For Tally'!C:C, 'For Tally'!F:F, C50)
A51: TOTAL | B51: =SUM(B5:B50) | C51: TOTAL | D51: =SUM(D5:D50) | E51: Net | F51: =B51-D51
A53: Opening & Closing Balances
A54: Account | B54: Opening Balance (₹) | C54: Closing Balance (₹)
A55: AXIS 7042 | B55: 9474.62 | C55: =B55 + SUMIFS('For Tally'!D:D, 'For Tally'!I:I, A55) - SUMIFS('For Tally'!C:C, 'For Tally'!I:I, A55)
A56: HDFC 0094 | B56: 33236 | C56: =B56 + SUMIFS('For Tally'!D:D, 'For Tally'!I:I, A56) - SUMIFS('For Tally'!C:C, 'For Tally'!I:I, A56)
A57: SBI 7685 | B57: 26120.7 | C57: =B57 + SUMIFS('For Tally'!D:D, 'For Tally'!I:I, A57) - SUMIFS('For Tally'!C:C, 'For Tally'!I:I, A57)
A59: Confidence Distribution
A60: Band | B60: Count | C60: % of Total
A61: High (≥ 0.85) — Confident | B61: =COUNTIF('For Tally'!G:G, ">=0.85") | C61: =B61/SUM(B61:B63)
A62: Medium (0.60–0.84) — Review | B62: =COUNTIFS('For Tally'!G:G, ">=0.60", 'For Tally'!G:G, "<0.85") | C62: =B62/SUM(B61:B63)
A63: Low (< 0.60) — Needs attention | B63: =COUNTIF('For Tally'!G:G, "<0.60") | C63: =B63/SUM(B61:B63)

Sheet Monthly Pivot
A1: Monthly Spend & Income Pivot
A3: Bank Filter Toggles: | B3: Axis Bank | C3: HDFC Bank | D3: State Bank of India
B4: TRUE | C4: TRUE | D4: TRUE
B5: =IF(B4, B3, "") | C5: =IF(C4, C3, "") | D5: =IF(D4, D3, "")
A7: PAYMENTS / DEBITS (Bank) | B7: Apr-2024 | C7: May-2024 | D7: Jun-2024 | E7: Jul-2024 | F7: Aug-2024 | G7: Sep-2024 | H7: Oct-2024 | I7: Nov-2024 | J7: Dec-2024 | K7: Jan-2025 | L7: Feb-2025 | M7: Mar-2025 | N7: TOTAL
A8: Ajay Gupta | B8: =SUMPRODUCT(SUMIFS('For Tally'!C:C, 'For Tally'!H:H, $A8, 'For Tally'!A:A, ">=2024-04-01", 'For Tally'!A:A, "<=2024-04-30", 'For Tally'!L:L, $B$5:$D$5)) | C8: =SUMPRODUCT(SUMIFS('For Tally'!C:C, 'For Tally'!H:H, $A8, 'For Tally'!A:A, ">=2024-05-01", 'For Tally'!A:A, "<=2024-05-31", 'For Tally'!L:L, $B$5:$D$5)) | D8: =SUMPRODUCT(SUMIFS('For Tally'!C:C, 'For Tally'!H:H, $A8, 'For Tally'!A:A, ">=2024-06-01", 'For Tally'!A:A, "<=2024-06-30", 'For Tally'!L:L, $B$5:$D$5)) | E8: =SUMPRODUCT(SUMIFS('For Tally'!C:C, 'For Tally'!H:H, $A8, 'For Tally'!A:A, ">=2024-07-01", 'For Tally'!A:A, "<=2024-07-31", 'For Tally'!L:L, $B$5:$D$5)) | F8: =SUMPRODUCT(SUMIFS('For Tally'!C:C, 'For Tally'!H:H, $A8, 'For Tally'!A:A, ">=2024-08-01", 'For Tally'!A:A, "<=2024-08-31", 'For Tally'!L:L, $B$5:$D$5)) | G8: =SUMPRODUCT(SUMIFS('For Tally'!C:C, 'For Tally'!H:H, $A8, 'For Tally'!A:A, ">=2024-09-01", 'For Tally'!A:A, "<=2024-09-30", 'For Tally'!L:L, $B$5:$D$5)) | H8: =SUMPRODUCT(SUMIFS('For Tally'!C:C, 'For Tally'!H:H, $A8, 'For Tally'!A:A, ">=2024-10-01", 'For Tally'!A:A, "<=2024-10-31", 'For Tally'!L:L, $B$5:$D$5)) | I8: =SUMPRODUCT(SUMIFS('For Tally'!C:C, 'For Tally'!H:H, $A8, 'For Tally'!A:A, ">=2024-11-01", 'For Tally'!A:A, "<=2024-11-30", 'For Tally'!L:L, $B$5:$D$5)) | J8: =SUMPRODUCT(SUMIFS('For Tally'!C:C, 'For Tally'!H:H, $A8, 'For Tally'!A:A, ">=2024-12-01", 'For Tally'!A:A, "<=2024-12-31", 'For Tally'!L:L, $B$5:$D$5)) | K8: =SUMPRODUCT(SUMIFS('For Tally'!C:C, 'For Tally'!H:H, $A8, 'For Tally'!A:A, ">=2025-01-01", 'For Tally'!A:A, "<=2025-01-31", 'For Tally'!L:L, $B$5:$D$5)) | L8: =SUMPRODUCT(SUMIFS('For Tally'!C:C, 'For Tally'!H:H, $A8, 'For Tally'!A:A, ">=2025-02-01", 'For Tally'!A:A, "<=2025-02-28", 'For Tally'!L:L, $B$5:$D$5)) | M8: =SUMPRODUCT(SUMIFS('For Tally'!C:C, 'For Tally'!H:H, $A8, 'For Tally'!A:A, ">=2025-03-01", 'For Tally'!A:A, "<=2025-03-31", 'For Tally'!L:L, $B$5:$D$5)) | N8: =SUM(B8:M8)
A9: Archit Gupta | B9: =SUMPRODUCT(SUMIFS('For Tally'!C:C, 'For Tally'!H:H, $A9, 'For Tally'!A:A, ">=2024-04-01", 'For Tally'!A:A, "<=2024-04-30", 'For Tally'!L:L, $B$5:$D$5)) | C9: =SUMPRODUCT(SUMIFS('For Tally'!C:C, 'For Tally'!H:H, $A9, 'For Tally'!A:A, ">=2024-05-01", 'For Tally'!A:A, "<=2024-05-31", 'For Tally'!L:L, $B$5:$D$5)) | D9: =SUMPRODUCT(SUMIFS('For Tally'!C:C, 'For Tally'!H:H, $A9, 'For Tally'!A:A, ">=2024-06-01", 'For Tally'!A:A, "<=2024-06-30", 'For Tally'!L:L, $B$5:$D$5)) | E9: =SUMPRODUCT(SUMIFS('For Tally'!C:C, 'For Tally'!H:H, $A9, 'For Tally'!A:A, ">=2024-07-01", 'For Tally'!A:A, "<=2024-07-31", 'For Tally'!L:L, $B$5:$D$5)) | F9: =SUMPRODUCT(SUMIFS('For Tally'!C:C, 'For Tally'!H:H, $A9, 'For Tally'!A:A, ">=2024-08-01", 'For Tally'!A:A, "<=2024-08-31", 'For Tally'!L:L, $B$5:$D$5)) | G9: =SUMPRODUCT(SUMIFS('For Tally'!C:C, 'For Tally'!H:H, $A9, 'For Tally'!A:A, ">=2024-09-01", 'For Tally'!A:A, "<=2024-09-30", 'For Tally'!L:L, $B$5:$D$5)) | H9: =SUMPRODUCT(SUMIFS('For Tally'!C:C, 'For Tally'!H:H, $A9, 'For Tally'!A:A, ">=2024-10-01", 'For Tally'!A:A, "<=2024-10-31", 'For Tally'!L:L, $B$5:$D$5)) | I9: =SUMPRODUCT(SUMIFS('For Tally'!C:C, 'For Tally'!H:H, $A9, 'For Tally'!A:A, ">=2024-11-01", 'For Tally'!A:A, "<=2024-11-30", 'For Tally'!L:L, $B$5:$D$5)) | J9: =SUMPRODUCT(SUMIFS('For Tally'!C:C, 'For Tally'!H:H, $A9, 'For Tally'!A:A, ">=2024-12-01", 'For Tally'!A:A, "<=2024-12-31", 'For Tally'!L:L, $B$5:$D$5)) | K9: =SUMPRODUCT(SUMIFS('For Tally'!C:C, 'For Tally'!H:H, $A9, 'For Tally'!A:A, ">=2025-01-01", 'For Tally'!A:A, "<=2025-01-31", 'For Tally'!L:L, $B$5:$D$5)) | L9: =SUMPRODUCT(SUMIFS('For Tally'!C:C, 'For Tally'!H:H, $A9, 'For Tally'!A:A, ">=2025-02-01", 'For Tally'!A:A, "<=2025-02-28", 'For Tally'!L:L, $B$5:$D$5)) | M9: =SUMPRODUCT(SUMIFS('For Tally'!C:C, 'For Tally'!H:H, $A9, 'For Tally'!A:A, ">=2025-03-01", 'For Tally'!A:A, "<=2025-03-31", 'For Tally'!L:L, $B$5:$D$5)) | N9: =SUM(B9:M9)
A10: Bank Charges | B10: =SUMPRODUCT(SUMIFS('For Tally'!C:C, 'For Tally'!H:H, $A10, 'For Tally'!A:A, ">=2024-04-01", 'For Tally'!A:A, "<=2024-04-30", 'For Tally'!L:L, $B$5:$D$5)) | C10: =SUMPRODUCT(SUMIFS('For Tally'!C:C, 'For Tally'!H:H, $A10, 'For Tally'!A:A, ">=2024-05-01", 'For Tally'!A:A, "<=2024-05-31", 'For Tally'!L:L, $B$5:$D$5)) | D10: =SUMPRODUCT(SUMIFS('For Tally'!C:C, 'For Tally'!H:H, $A10, 'For Tally'!A:A, ">=2024-06-01", 'For Tally'!A:A, "<=2024-06-30", 'For Tally'!L:L, $B$5:$D$5)) | E10: =SUMPRODUCT(SUMIFS('For Tally'!C:C, 'For Tally'!H:H, $A10, 'For Tally'!A:A, ">=2024-07-01", 'For Tally'!A:A, "<=2024-07-31", 'For Tally'!L:L, $B$5:$D$5)) | F10: =SUMPRODUCT(SUMIFS('For Tally'!C:C, 'For Tally'!H:H, $A10, 'For Tally'!A:A, ">=2024-08-01", 'For Tally'!A:A, "<=2024-08-31", 'For Tally'!L:L, $B$5:$D$5)) | G10: =SUMPRODUCT(SUMIFS('For Tally'!C:C, 'For Tally'!H:H, $A10, 'For Tally'!A:A, ">=2024-09-01", 'For Tally'!A:A, "<=2024-09-30", 'For Tally'!L:L, $B$5:$D$5)) | H10: =SUMPRODUCT(SUMIFS('For Tally'!C:C, 'For Tally'!H:H, $A10, 'For Tally'!A:A, ">=2024-10-01", 'For Tally'!A:A, "<=2024-10-31", 'For Tally'!L:L, $B$5:$D$5)) | I10: =SUMPRODUCT(SUMIFS('For Tally'!C:C, 'For Tally'!H:H, $A10, 'For Tally'!A:A, ">=2024-11-01", 'For Tally'!A:A, "<=2024-11-30", 'For Tally'!L:L, $B$5:$D$5)) | J10: =SUMPRODUCT(SUMIFS('For Tally'!C:C, 'For Tally'!H:H, $A10, 'For Tally'!A:A, ">=2024-12-01", 'For Tally'!A:A, "<=2024-12-31", 'For Tally'!L:L, $B$5:$D$5)) | K10: =SUMPRODUCT(SUMIFS('For Tally'!C:C, 'For Tally'!H:H, $A10, 'For Tally'!A:A, ">=2025-01-01", 'For Tally'!A:A, "<=2025-01-31", 'For Tally'!L:L, $B$5:$D$5)) | L10: =SUMPRODUCT(SUMIFS('For Tally'!C:C, 'For Tally'!H:H, $A10, 'For Tally'!A:A, ">=2025-02-01", 'For Tally'!A:A, "<=2025-02-28", 'For Tally'!L:L, $B$5:$D$5)) | M10: =SUMPRODUCT(SUMIFS('For Tally'!C:C, 'For Tally'!H:H, $A10, 'For Tally'!A:A, ">=2025-03-01", 'For Tally'!A:A, "<=2025-03-31", 'For Tally'!L:L, $B$5:$D$5)) | N10: =SUM(B10:M10)
A11: Cash | B11: =SUMPRODUCT(SUMIFS('For Tally'!C:C, 'For Tally'!H:H, $A11, 'For Tally'!A:A, ">=2024-04-01", 'For Tally'!A:A, "<=2024-04-30", 'For Tally'!L:L, $B$5:$D$5)) | C11: =SUMPRODUCT(SUMIFS('For Tally'!C:C, 'For Tally'!H:H, $A11, 'For Tally'!A:A, ">=2024-05-01", 'For Tally'!A:A, "<=2024-05-31", 'For Tally'!L:L, $B$5:$D$5)) | D11: =SUMPRODUCT(SUMIFS('For Tally'!C:C, 'For Tally'!H:H, $A11, 'For Tally'!A:A, ">=2024-06-01", 'For Tally'!A:A, "<=2024-06-30", 'For Tally'!L:L, $B$5:$D$5)) | E11: =SUMPRODUCT(SUMIFS('For Tally'!C:C, 'For Tally'!H:H, $A11, 'For Tally'!A:A, ">=2024-07-01", 'For Tally'!A:A, "<=2024-07-31", 'For Tally'!L:L, $B$5:$D$5)) | F11: =SUMPRODUCT(SUMIFS('For Tally'!C:C, 'For Tally'!H:H, $A11, 'For Tally'!A:A, ">=2024-08-01", 'For Tally'!A:A, "<=2024-08-31", 'For Tally'!L:L, $B$5:$D$5)) | G11: =SUMPRODUCT(SUMIFS('For Tally'!C:C, 'For Tally'!H:H, $A11, 'For Tally'!A:A, ">=2024-09-01", 'For Tally'!A:A, "<=2024-09-30", 'For Tally'!L:L, $B$5:$D$5)) | H11: =SUMPRODUCT(SUMIFS('For Tally'!C:C, 'For Tally'!H:H, $A11, 'For Tally'!A:A, ">=2024-10-01", 'For Tally'!A:A, "<=2024-10-31", 'For Tally'!L:L, $B$5:$D$5)) | I11: =SUMPRODUCT(SUMIFS('For Tally'!C:C, 'For Tally'!H:H, $A11, 'For Tally'!A:A, ">=2024-11-01", 'For Tally'!A:A, "<=2024-11-30", 'For Tally'!L:L, $B$5:$D$5)) | J11: =SUMPRODUCT(SUMIFS('For Tally'!C:C, 'For Tally'!H:H, $A11, 'For Tally'!A:A, ">=2024-12-01", 'For Tally'!A:A, "<=2024-12-31", 'For Tally'!L:L, $B$5:$D$5)) | K11: =SUMPRODUCT(SUMIFS('For Tally'!C:C, 'For Tally'!H:H, $A11, 'For Tally'!A:A, ">=2025-01-01", 'For Tally'!A:A, "<=2025-01-31", 'For Tally'!L:L, $B$5:$D$5)) | L11: =SUMPRODUCT(SUMIFS('For Tally'!C:C, 'For Tally'!H:H, $A11, 'For Tally'!A:A, ">=2025-02-01", 'For Tally'!A:A, "<=2025-02-28", 'For Tally'!L:L, $B$5:$D$5)) | M11: =SUMPRODUCT(SUMIFS('For Tally'!C:C, 'For Tally'!H:H, $A11, 'For Tally'!A:A, ">=2025-03-01", 'For Tally'!A:A, "<=2025-03-31", 'For Tally'!L:L, $B$5:$D$5)) | N11: =SUM(B11:M11)
A12: Depository Charges | B12: =SUMPRODUCT(SUMIFS('For Tally'!C:C, 'For Tally'!H:H, $A12, 'For Tally'!A:A, ">=2024-04-01", 'For Tally'!A:A, "<=2024-04-30", 'For Tally'!L:L, $B$5:$D$5)) | C12: =SUMPRODUCT(SUMIFS('For Tally'!C:C, 'For Tally'!H:H, $A12, 'For Tally'!A:A, ">=2024-05-01", 'For Tally'!A:A, "<=2024-05-31", 'For Tally'!L:L, $B$5:$D$5)) | D12: =SUMPRODUCT(SUMIFS('For Tally'!C:C, 'For Tally'!H:H, $A12, 'For Tally'!A:A, ">=2024-06-01", 'For Tally'!A:A, "<=2024-06-30", 'For Tally'!L:L, $B$5:$D$5)) | E12: =SUMPRODUCT(SUMIFS('For Tally'!C:C, 'For Tally'!H:H, $A12, 'For Tally'!A:A, ">=2024-07-01", 'For Tally'!A:A, "<=2024-07-31", 'For Tally'!L:L, $B$5:$D$5)) | F12: =SUMPRODUCT(SUMIFS('For Tally'!C:C, 'For Tally'!H:H, $A12, 'For Tally'!A:A, ">=2024-08-01", 'For Tally'!A:A, "<=2024-08-31", 'For Tally'!L:L, $B$5:$D$5)) | G12: =SUMPRODUCT(SUMIFS('For Tally'!C:C, 'For Tally'!H:H, $A12, 'For Tally'!A:A, ">=2024-09-01", 'For Tally'!A:A, "<=2024-09-30", 'For Tally'!L:L, $B$5:$D$5)) | H12: =SUMPRODUCT(SUMIFS('For Tally'!C:C, 'For Tally'!H:H, $A12, 'For Tally'!A:A, ">=2024-10-01", 'For Tally'!A:A, "<=2024-10-31", 'For Tally'!L:L, $B$5:$D$5)) | I12: =SUMPRODUCT(SUMIFS('For Tally'!C:C, 'For Tally'!H:H, $A12, 'For Tally'!A:A, ">=2024-11-01", 'For Tally'!A:A, "<=2024-11-30", 'For Tally'!L:L, $B$5:$D$5)) | J12: =SUMPRODUCT(SUMIFS('For Tally'!C:C, 'For Tally'!H:H, $A12, 'For Tally'!A:A, ">=2024-12-01", 'For Tally'!A:A, "<=2024-12-31", 'For Tally'!L:L, $B$5:$D$5)) | K12: =SUMPRODUCT(SUMIFS('For Tally'!C:C, 'For Tally'!H:H, $A12, 'For Tally'!A:A, ">=2025-01-01", 'For Tally'!A:A, "<=2025-01-31", 'For Tally'!L:L, $B$5:$D$5)) | L12: =SUMPRODUCT(SUMIFS('For Tally'!C:C, 'For Tally'!H:H, $A12, 'For Tally'!A:A, ">=2025-02-01", 'For Tally'!A:A, "<=2025-02-28", 'For Tally'!L:L, $B$5:$D$5)) | M12: =SUMPRODUCT(SUMIFS('For Tally'!C:C, 'For Tally'!H:H, $A12, 'For Tally'!A:A, ">=2025-03-01", 'For Tally'!A:A, "<=2025-03-31", 'For Tally'!L:L, $B$5:$D$5)) | N12: =SUM(B12:M12)
A13: Groceries | B13: =SUMPRODUCT(SUMIFS('For Tally'!C:C, 'For Tally'!H:H, $A13, 'For Tally'!A:A, ">=2024-04-01", 'For Tally'!A:A, "<=2024-04-30", 'For Tally'!L:L, $B$5:$D$5)) | C13: =SUMPRODUCT(SUMIFS('For Tally'!C:C, 'For Tally'!H:H, $A13, 'For Tally'!A:A, ">=2024-05-01", 'For Tally'!A:A, "<=2024-05-31", 'For Tally'!L:L, $B$5:$D$5)) | D13: =SUMPRODUCT(SUMIFS('For Tally'!C:C, 'For Tally'!H:H, $A13, 'For Tally'!A:A, ">=2024-06-01", 'For Tally'!A:A, "<=2024-06-30", 'For Tally'!L:L, $B$5:$D$5)) | E13: =SUMPRODUCT(SUMIFS('For Tally'!C:C, 'For Tally'!H:H, $A13, 'For Tally'!A:A, ">=2024-07-01", 'For Tally'!A:A, "<=2024-07-31", 'For Tally'!L:L, $B$5:$D$5)) | F13: =SUMPRODUCT(SUMIFS('For Tally'!C:C, 'For Tally'!H:H, $A13, 'For Tally'!A:A, ">=2024-08-01", 'For Tally'!A:A, "<=2024-08-31", 'For Tally'!L:L, $B$5:$D$5)) | G13: =SUMPRODUCT(SUMIFS('For Tally'!C:C, 'For Tally'!H:H, $A13, 'For Tally'!A:A, ">=2024-09-01", 'For Tally'!A:A, "<=2024-09-30", 'For Tally'!L:L, $B$5:$D$5)) | H13: =SUMPRODUCT(SUMIFS('For Tally'!C:C, 'For Tally'!H:H, $A13, 'For Tally'!A:A, ">=2024-10-01", 'For Tally'!A:A, "<=2024-10-31", 'For Tally'!L:L, $B$5:$D$5)) | I13: =SUMPRODUCT(SUMIFS('For Tally'!C:C, 'For Tally'!H:H, $A13, 'For Tally'!A:A, ">=2024-11-01", 'For Tally'!A:A, "<=2024-11-30", 'For Tally'!L:L, $B$5:$D$5)) | J13: =SUMPRODUCT(SUMIFS('For Tally'!C:C, 'For Tally'!H:H, $A13, 'For Tally'!A:A, ">=2024-12-01", 'For Tally'!A:A, "<=2024-12-31", 'For Tally'!L:L, $B$5:$D$5)) | K13: =SUMPRODUCT(SUMIFS('For Tally'!C:C, 'For Tally'!H:H, $A13, 'For Tally'!A:A, ">=2025-01-01", 'For Tally'!A:A, "<=2025-01-31", 'For Tally'!L:L, $B$5:$D$5)) | L13: =SUMPRODUCT(SUMIFS('For Tally'!C:C, 'For Tally'!H:H, $A13, 'For Tally'!A:A, ">=2025-02-01", 'For Tally'!A:A, "<=2025-02-28", 'For Tally'!L:L, $B$5:$D$5)) | M13: =SUMPRODUCT(SUMIFS('For Tally'!C:C, 'For Tally'!H:H, $A13, 'For Tally'!A:A, ">=2025-03-01", 'For Tally'!A:A, "<=2025-03-31", 'For Tally'!L:L, $B$5:$D$5)) | N13: =SUM(B13:M13)
A14: HDFC Securities | B14: =SUMPRODUCT(SUMIFS('For Tally'!C:C, 'For Tally'!H:H, $A14, 'For Tally'!A:A, ">=2024-04-01", 'For Tally'!A:A, "<=2024-04-30", 'For Tally'!L:L, $B$5:$D$5)) | C14: =SUMPRODUCT(SUMIFS('For Tally'!C:C, 'For Tally'!H:H, $A14, 'For Tally'!A:A, ">=2024-05-01", 'For Tally'!A:A, "<=2024-05-31", 'For Tally'!L:L, $B$5:$D$5)) | D14: =SUMPRODUCT(SUMIFS('For Tally'!C:C, 'For Tally'!H:H, $A14, 'For Tally'!A:A, ">=2024-06-01", 'For Tally'!A:A, "<=2024-06-30", 'For Tally'!L:L, $B$5:$D$5)) | E14: =SUMPRODUCT(SUMIFS('For Tally'!C:C, 'For Tally'!H:H, $A14, 'For Tally'!A:A, ">=2024-07-01", 'For Tally'!A:A, "<=2024-07-31", 'For Tally'!L:L, $B$5:$D$5)) | F14: =SUMPRODUCT(SUMIFS('For Tally'!C:C, 'For Tally'!H:H, $A14, 'For Tally'!A:A, ">=2024-08-01", 'For Tally'!A:A, "<=2024-08-31", 'For Tally'!L:L, $B$5:$D$5)) | G14: =SUMPRODUCT(SUMIFS('For Tally'!C:C, 'For Tally'!H:H, $A14, 'For Tally'!A:A, ">=2024-09-01", 'For Tally'!A:A, "<=2024-09-30", 'For Tally'!L:L, $B$5:$D$5)) | H14: =SUMPRODUCT(SUMIFS('For Tally'!C:C, 'For Tally'!H:H, $A14, 'For Tally'!A:A, ">=2024-10-01", 'For Tally'!A:A, "<=2024-10-31", 'For Tally'!L:L, $B$5:$D$5)) | I14: =SUMPRODUCT(SUMIFS('For Tally'!C:C, 'For Tally'!H:H, $A14, 'For Tally'!A:A, ">=2024-11-01", 'For Tally'!A:A, "<=2024-11-30", 'For Tally'!L:L, $B$5:$D$5)) | J14: =SUMPRODUCT(SUMIFS('For Tally'!C:C, 'For Tally'!H:H, $A14, 'For Tally'!A:A, ">=2024-12-01", 'For Tally'!A:A, "<=2024-12-31", 'For Tally'!L:L, $B$5:$D$5)) | K14: =SUMPRODUCT(SUMIFS('For Tally'!C:C, 'For Tally'!H:H, $A14, 'For Tally'!A:A, ">=2025-01-01", 'For Tally'!A:A, "<=2025-01-31", 'For Tally'!L:L, $B$5:$D$5)) | L14: =SUMPRODUCT(SUMIFS('For Tally'!C:C, 'For Tally'!H:H, $A14, 'For Tally'!A:A, ">=2025-02-01", 'For Tally'!A:A, "<=2025-02-28", 'For Tally'!L:L, $B$5:$D$5)) | M14: =SUMPRODUCT(SUMIFS('For Tally'!C:C, 'For Tally'!H:H, $A14, 'For Tally'!A:A, ">=2025-03-01", 'For Tally'!A:A, "<=2025-03-31", 'For Tally'!L:L, $B$5:$D$5)) | N14: =SUM(B14:M14)
A15: Health Insurance | B15: =SUMPRODUCT(SUMIFS('For Tally'!C:C, 'For Tally'!H:H, $A15, 'For Tally'!A:A, ">=2024-04-01", 'For Tally'!A:A, "<=2024-04-30", 'For Tally'!L:L, $B$5:$D$5)) | C15: =SUMPRODUCT(SUMIFS('For Tally'!C:C, 'For Tally'!H:H, $A15, 'For Tally'!A:A, ">=2024-05-01", 'For Tally'!A:A, "<=2024-05-31", 'For Tally'!L:L, $B$5:$D$5)) | D15: =SUMPRODUCT(SUMIFS('For Tally'!C:C, 'For Tally'!H:H, $A15, 'For Tally'!A:A, ">=2024-06-01", 'For Tally'!A:A, "<=2024-06-30", 'For Tally'!L:L, $B$5:$D$5)) | E15: =SUMPRODUCT(SUMIFS('For Tally'!C:C, 'For Tally'!H:H, $A15, 'For Tally'!A:A, ">=2024-07-01", 'For Tally'!A:A, "<=2024-07-31", 'For Tally'!L:L, $B$5:$D$5)) | F15: =SUMPRODUCT(SUMIFS('For Tally'!C:C, 'For Tally'!H:H, $A15, 'For Tally'!A:A, ">=2024-08-01", 'For Tally'!A:A, "<=2024-08-31", 'For Tally'!L:L, $B$5:$D$5)) | G15: =SUMPRODUCT(SUMIFS('For Tally'!C:C, 'For Tally'!H:H, $A15, 'For Tally'!A:A, ">=2024-09-01", 'For Tally'!A:A, "<=2024-09-30", 'For Tally'!L:L, $B$5:$D$5)) | H15: =SUMPRODUCT(SUMIFS('For Tally'!C:C, 'For Tally'!H:H, $A15, 'For Tally'!A:A, ">=2024-10-01", 'For Tally'!A:A, "<=2024-10-31", 'For Tally'!L:L, $B$5:$D$5)) | I15: =SUMPRODUCT(SUMIFS('For Tally'!C:C, 'For Tally'!H:H, $A15, 'For Tally'!A:A, ">=2024-11-01", 'For Tally'!A:A, "<=2024-11-30", 'For Tally'!L:L, $B$5:$D$5)) | J15: =SUMPRODUCT(SUMIFS('For Tally'!C:C, 'For Tally'!H:H, $A15, 'For Tally'!A:A, ">=2024-12-01", 'For Tally'!A:A, "<=2024-12-31", 'For Tally'!L:L, $B$5:$D$5)) | K15: =SUMPRODUCT(SUMIFS('For Tally'!C:C, 'For Tally'!H:H, $A15, 'For Tally'!A:A, ">=2025-01-01", 'For Tally'!A:A, "<=2025-01-31", 'For Tally'!L:L, $B$5:$D$5)) | L15: =SUMPRODUCT(SUMIFS('For Tally'!C:C, 'For Tally'!H:H, $A15, 'For Tally'!A:A, ">=2025-02-01", 'For Tally'!A:A, "<=2025-02-28", 'For Tally'!L:L, $B$5:$D$5)) | M15: =SUMPRODUCT(SUMIFS('For Tally'!C:C, 'For Tally'!H:H, $A15, 'For Tally'!A:A, ">=2025-03-01", 'For Tally'!A:A, "<=2025-03-31", 'For Tally'!L:L, $B$5:$D$5)) | N15: =SUM(B15:M15)
A16: Healthcare | B16: =SUMPRODUCT(SUMIFS('For Tally'!C:C, 'For Tally'!H:H, $A16, 'For Tally'!A:A, ">=2024-04-01", 'For Tally'!A:A, "<=2024-04-30", 'For Tally'!L:L, $B$5:$D$5)) | C16: =SUMPRODUCT(SUMIFS('For Tally'!C:C, 'For Tally'!H:H, $A16, 'For Tally'!A:A, ">=2024-05-01", 'For Tally'!A:A, "<=2024-05-31", 'For Tally'!L:L, $B$5:$D$5)) | D16: =SUMPRODUCT(SUMIFS('For Tally'!C:C, 'For Tally'!H:H, $A16, 'For Tally'!A:A, ">=2024-06-01", 'For Tally'!A:A, "<=2024-06-30", 'For Tally'!L:L, $B$5:$D$5)) | E16: =SUMPRODUCT(SUMIFS('For Tally'!C:C, 'For Tally'!H:H, $A16, 'For Tally'!A:A, ">=2024-07-01", 'For Tally'!A:A, "<=2024-07-31", 'For Tally'!L:L, $B$5:$D$5)) | F16: =SUMPRODUCT(SUMIFS('For Tally'!C:C, 'For Tally'!H:H, $A16, 'For Tally'!A:A, ">=2024-08-01", 'For Tally'!A:A, "<=2024-08-31", 'For Tally'!L:L, $B$5:$D$5)) | G16: =SUMPRODUCT(SUMIFS('For Tally'!C:C, 'For Tally'!H:H, $A16, 'For Tally'!A:A, ">=2024-09-01", 'For Tally'!A:A, "<=2024-09-30", 'For Tally'!L:L, $B$5:$D$5)) | H16: =SUMPRODUCT(SUMIFS('For Tally'!C:C, 'For Tally'!H:H, $A16, 'For Tally'!A:A, ">=2024-10-01", 'For Tally'!A:A, "<=2024-10-31", 'For Tally'!L:L, $B$5:$D$5)) | I16: =SUMPRODUCT(SUMIFS('For Tally'!C:C, 'For Tally'!H:H, $A16, 'For Tally'!A:A, ">=2024-11-01", 'For Tally'!A:A, "<=2024-11-30", 'For Tally'!L:L, $B$5:$D$5)) | J16: =SUMPRODUCT(SUMIFS('For Tally'!C:C, 'For Tally'!H:H, $A16, 'For Tally'!A:A, ">=2024-12-01", 'For Tally'!A:A, "<=2024-12-31", 'For Tally'!L:L, $B$5:$D$5)) | K16: =SUMPRODUCT(SUMIFS('For Tally'!C:C, 'For Tally'!H:H, $A16, 'For Tally'!A:A, ">=2025-01-01", 'For Tally'!A:A, "<=2025-01-31", 'For Tally'!L:L, $B$5:$D$5)) | L16: =SUMPRODUCT(SUMIFS('For Tally'!C:C, 'For Tally'!H:H, $A16, 'For Tally'!A:A, ">=2025-02-01", 'For Tally'!A:A, "<=2025-02-28", 'For Tally'!L:L, $B$5:$D$5)) | M16: =SUMPRODUCT(SUMIFS('For Tally'!C:C, 'For Tally'!H:H, $A16, 'For Tally'!A:A, ">=2025-03-01", 'For Tally'!A:A, "<=2025-03-31", 'For Tally'!L:L, $B$5:$D$5)) | N16: =SUM(B16:M16)
A17: Megha Gupta | B17: =SUMPRODUCT(SUMIFS('For Tally'!C:C, 'For Tally'!H:H, $A17, 'For Tally'!A:A, ">=2024-04-01", 'For Tally'!A:A, "<=2024-04-30", 'For Tally'!L:L, $B$5:$D$5)) | C17: =SUMPRODUCT(SUMIFS('For Tally'!C:C, 'For Tally'!H:H, $A17, 'For Tally'!A:A, ">=2024-05-01", 'For Tally'!A:A, "<=2024-05-31", 'For Tally'!L:L, $B$5:$D$5)) | D17: =SUMPRODUCT(SUMIFS('For Tally'!C:C, 'For Tally'!H:H, $A17, 'For Tally'!A:A, ">=2024-06-01", 'For Tally'!A:A, "<=2024-06-30", 'For Tally'!L:L, $B$5:$D$5)) | E17: =SUMPRODUCT(SUMIFS('For Tally'!C:C, 'For Tally'!H:H, $A17, 'For Tally'!A:A, ">=2024-07-01", 'For Tally'!A:A, "<=2024-07-31", 'For Tally'!L:L, $B$5:$D$5)) | F17: =SUMPRODUCT(SUMIFS('For Tally'!C:C, 'For Tally'!H:H, $A17, 'For Tally'!A:A, ">=2024-08-01", 'For Tally'!A:A, "<=2024-08-31", 'For Tally'!L:L, $B$5:$D$5)) | G17: =SUMPRODUCT(SUMIFS('For Tally'!C:C, 'For Tally'!H:H, $A17, 'For Tally'!A:A, ">=2024-09-01", 'For Tally'!A:A, "<=2024-09-30", 'For Tally'!L:L, $B$5:$D$5)) | H17: =SUMPRODUCT(SUMIFS('For Tally'!C:C, 'For Tally'!H:H, $A17, 'For Tally'!A:A, ">=2024-10-01", 'For Tally'!A:A, "<=2024-10-31", 'For Tally'!L:L, $B$5:$D$5)) | I17: =SUMPRODUCT(SUMIFS('For Tally'!C:C, 'For Tally'!H:H, $A17, 'For Tally'!A:A, ">=2024-11-01", 'For Tally'!A:A, "<=2024-11-30", 'For Tally'!L:L, $B$5:$D$5)) | J17: =SUMPRODUCT(SUMIFS('For Tally'!C:C, 'For Tally'!H:H, $A17, 'For Tally'!A:A, ">=2024-12-01", 'For Tally'!A:A, "<=2024-12-31", 'For Tally'!L:L, $B$5:$D$5)) | K17: =SUMPRODUCT(SUMIFS('For Tally'!C:C, 'For Tally'!H:H, $A17, 'For Tally'!A:A, ">=2025-01-01", 'For Tally'!A:A, "<=2025-01-31", 'For Tally'!L:L, $B$5:$D$5)) | L17: =SUMPRODUCT(SUMIFS('For Tally'!C:C, 'For Tally'!H:H, $A17, 'For Tally'!A:A, ">=2025-02-01", 'For Tally'!A:A, "<=2025-02-28", 'For Tally'!L:L, $B$5:$D$5)) | M17: =SUMPRODUCT(SUMIFS('For Tally'!C:C, 'For Tally'!H:H, $A17, 'For Tally'!A:A, ">=2025-03-01", 'For Tally'!A:A, "<=2025-03-31", 'For Tally'!L:L, $B$5:$D$5)) | N17: =SUM(B17:M17)
A18: Mutual_Fund_Investments | B18: =SUMPRODUCT(SUMIFS('For Tally'!C:C, 'For Tally'!H:H, $A18, 'For Tally'!A:A, ">=2024-04-01", 'For Tally'!A:A, "<=2024-04-30", 'For Tally'!L:L, $B$5:$D$5)) | C18: =SUMPRODUCT(SUMIFS('For Tally'!C:C, 'For Tally'!H:H, $A18, 'For Tally'!A:A, ">=2024-05-01", 'For Tally'!A:A, "<=2024-05-31", 'For Tally'!L:L, $B$5:$D$5)) | D18: =SUMPRODUCT(SUMIFS('For Tally'!C:C, 'For Tally'!H:H, $A18, 'For Tally'!A:A, ">=2024-06-01", 'For Tally'!A:A, "<=2024-06-30", 'For Tally'!L:L, $B$5:$D$5)) | E18: =SUMPRODUCT(SUMIFS('For Tally'!C:C, 'For Tally'!H:H, $A18, 'For Tally'!A:A, ">=2024-07-01", 'For Tally'!A:A, "<=2024-07-31", 'For Tally'!L:L, $B$5:$D$5)) | F18: =SUMPRODUCT(SUMIFS('For Tally'!C:C, 'For Tally'!H:H, $A18, 'For Tally'!A:A, ">=2024-08-01", 'For Tally'!A:A, "<=2024-08-31", 'For Tally'!L:L, $B$5:$D$5)) | G18: =SUMPRODUCT(SUMIFS('For Tally'!C:C, 'For Tally'!H:H, $A18, 'For Tally'!A:A, ">=2024-09-01", 'For Tally'!A:A, "<=2024-09-30", 'For Tally'!L:L, $B$5:$D$5)) | H18: =SUMPRODUCT(SUMIFS('For Tally'!C:C, 'For Tally'!H:H, $A18, 'For Tally'!A:A, ">=2024-10-01", 'For Tally'!A:A, "<=2024-10-31", 'For Tally'!L:L, $B$5:$D$5)) | I18: =SUMPRODUCT(SUMIFS('For Tally'!C:C, 'For Tally'!H:H, $A18, 'For Tally'!A:A, ">=2024-11-01", 'For Tally'!A:A, "<=2024-11-30", 'For Tally'!L:L, $B$5:$D$5)) | J18: =SUMPRODUCT(SUMIFS('For Tally'!C:C, 'For Tally'!H:H, $A18, 'For Tally'!A:A, ">=2024-12-01", 'For Tally'!A:A, "<=2024-12-31", 'For Tally'!L:L, $B$5:$D$5)) | K18: =SUMPRODUCT(SUMIFS('For Tally'!C:C, 'For Tally'!H:H, $A18, 'For Tally'!A:A, ">=2025-01-01", 'For Tally'!A:A, "<=2025-01-31", 'For Tally'!L:L, $B$5:$D$5)) | L18: =SUMPRODUCT(SUMIFS('For Tally'!C:C, 'For Tally'!H:H, $A18, 'For Tally'!A:A, ">=2025-02-01", 'For Tally'!A:A, "<=2025-02-28", 'For Tally'!L:L, $B$5:$D$5)) | M18: =SUMPRODUCT(SUMIFS('For Tally'!C:C, 'For Tally'!H:H, $A18, 'For Tally'!A:A, ">=2025-03-01", 'For Tally'!A:A, "<=2025-03-31", 'For Tally'!L:L, $B$5:$D$5)) | N18: =SUM(B18:M18)
A19: Personal | B19: =SUMPRODUCT(SUMIFS('For Tally'!C:C, 'For Tally'!H:H, $A19, 'For Tally'!A:A, ">=2024-04-01", 'For Tally'!A:A, "<=2024-04-30", 'For Tally'!L:L, $B$5:$D$5)) | C19: =SUMPRODUCT(SUMIFS('For Tally'!C:C, 'For Tally'!H:H, $A19, 'For Tally'!A:A, ">=2024-05-01", 'For Tally'!A:A, "<=2024-05-31", 'For Tally'!L:L, $B$5:$D$5)) | D19: =SUMPRODUCT(SUMIFS('For Tally'!C:C, 'For Tally'!H:H, $A19, 'For Tally'!A:A, ">=2024-06-01", 'For Tally'!A:A, "<=2024-06-30", 'For Tally'!L:L, $B$5:$D$5)) | E19: =SUMPRODUCT(SUMIFS('For Tally'!C:C, 'For Tally'!H:H, $A19, 'For Tally'!A:A, ">=2024-07-01", 'For Tally'!A:A, "<=2024-07-31", 'For Tally'!L:L, $B$5:$D$5)) | F19: =SUMPRODUCT(SUMIFS('For Tally'!C:C, 'For Tally'!H:H, $A19, 'For Tally'!A:A, ">=2024-08-01", 'For Tally'!A:A, "<=2024-08-31", 'For Tally'!L:L, $B$5:$D$5)) | G19: =SUMPRODUCT(SUMIFS('For Tally'!C:C, 'For Tally'!H:H, $A19, 'For Tally'!A:A, ">=2024-09-01", 'For Tally'!A:A, "<=2024-09-30", 'For Tally'!L:L, $B$5:$D$5)) | H19: =SUMPRODUCT(SUMIFS('For Tally'!C:C, 'For Tally'!H:H, $A19, 'For Tally'!A:A, ">=2024-10-01", 'For Tally'!A:A, "<=2024-10-31", 'For Tally'!L:L, $B$5:$D$5)) | I19: =SUMPRODUCT(SUMIFS('For Tally'!C:C, 'For Tally'!H:H, $A19, 'For Tally'!A:A, ">=2024-11-01", 'For Tally'!A:A, "<=2024-11-30", 'For Tally'!L:L, $B$5:$D$5)) | J19: =SUMPRODUCT(SUMIFS('For Tally'!C:C, 'For Tally'!H:H, $A19, 'For Tally'!A:A, ">=2024-12-01", 'For Tally'!A:A, "<=2024-12-31", 'For Tally'!L:L, $B$5:$D$5)) | K19: =SUMPRODUCT(SUMIFS('For Tally'!C:C, 'For Tally'!H:H, $A19, 'For Tally'!A:A, ">=2025-01-01", 'For Tally'!A:A, "<=2025-01-31", 'For Tally'!L:L, $B$5:$D$5)) | L19: =SUMPRODUCT(SUMIFS('For Tally'!C:C, 'For Tally'!H:H, $A19, 'For Tally'!A:A, ">=2025-02-01", 'For Tally'!A:A, "<=2025-02-28", 'For Tally'!L:L, $B$5:$D$5)) | M19: =SUMPRODUCT(SUMIFS('For Tally'!C:C, 'For Tally'!H:H, $A19, 'For Tally'!A:A, ">=2025-03-01", 'For Tally'!A:A, "<=2025-03-31", 'For Tally'!L:L, $B$5:$D$5)) | N19: =SUM(B19:M19)
... A27: Zerodha Broking Limited | B27: =SUMPRODUCT(SUMIFS('For Tally'!C:C, 'For Tally'!H:H, $A27, 'For Tally'!A:A, ">=2024-04-01", 'For Tally'!A:A, "<=2024-04-30", 'For Tally'!L:L, $B$5:$D$5)) | C27: =SUMPRODUCT(SUMIFS('For Tally'!C:C, 'For Tally'!H:H, $A27, 'For Tally'!A:A, ">=2024-05-01", 'For Tally'!A:A, "<=2024-05-31", 'For Tally'!L:L, $B$5:$D$5)) | D27: =SUMPRODUCT(SUMIFS('For Tally'!C:C, 'For Tally'!H:H, $A27, 'For Tally'!A:A, ">=2024-06-01", 'For Tally'!A:A, "<=2024-06-30", 'For Tally'!L:L, $B$5:$D$5)) | E27: =SUMPRODUCT(SUMIFS('For Tally'!C:C, 'For Tally'!H:H, $A27, 'For Tally'!A:A, ">=2024-07-01", 'For Tally'!A:A, "<=2024-07-31", 'For Tally'!L:L, $B$5:$D$5)) | F27: =SUMPRODUCT(SUMIFS('For Tally'!C:C, 'For Tally'!H:H, $A27, 'For Tally'!A:A, ">=2024-08-01", 'For Tally'!A:A, "<=2024-08-31", 'For Tally'!L:L, $B$5:$D$5)) | G27: =SUMPRODUCT(SUMIFS('For Tally'!C:C, 'For Tally'!H:H, $A27, 'For Tally'!A:A, ">=2024-09-01", 'For Tally'!A:A, "<=2024-09-30", 'For Tally'!L:L, $B$5:$D$5)) | H27: =SUMPRODUCT(SUMIFS('For Tally'!C:C, 'For Tally'!H:H, $A27, 'For Tally'!A:A, ">=2024-10-01", 'For Tally'!A:A, "<=2024-10-31", 'For Tally'!L:L, $B$5:$D$5)) | I27: =SUMPRODUCT(SUMIFS('For Tally'!C:C, 'For Tally'!H:H, $A27, 'For Tally'!A:A, ">=2024-11-01", 'For Tally'!A:A, "<=2024-11-30", 'For Tally'!L:L, $B$5:$D$5)) | J27: =SUMPRODUCT(SUMIFS('For Tally'!C:C, 'For Tally'!H:H, $A27, 'For Tally'!A:A, ">=2024-12-01", 'For Tally'!A:A, "<=2024-12-31", 'For Tally'!L:L, $B$5:$D$5)) | K27: =SUMPRODUCT(SUMIFS('For Tally'!C:C, 'For Tally'!H:H, $A27, 'For Tally'!A:A, ">=2025-01-01", 'For Tally'!A:A, "<=2025-01-31", 'For Tally'!L:L, $B$5:$D$5)) | L27: =SUMPRODUCT(SUMIFS('For Tally'!C:C, 'For Tally'!H:H, $A27, 'For Tally'!A:A, ">=2025-02-01", 'For Tally'!A:A, "<=2025-02-28", 'For Tally'!L:L, $B$5:$D$5)) | M27: =SUMPRODUCT(SUMIFS('For Tally'!C:C, 'For Tally'!H:H, $A27, 'For Tally'!A:A, ">=2025-03-01", 'For Tally'!A:A, "<=2025-03-31", 'For Tally'!L:L, $B$5:$D$5)) | N27: =SUM(B27:M27)
A28: MONTHLY TOTAL | B28: =SUM(B8:B27) | C28: =SUM(C8:C27) | D28: =SUM(D8:D27) | E28: =SUM(E8:E27) | F28: =SUM(F8:F27) | G28: =SUM(G8:G27) | H28: =SUM(H8:H27) | I28: =SUM(I8:I27) | ... N28: =SUM(N8:N27)
A30: RECEIPTS / CREDITS | B30: Apr-2024 | C30: May-2024 | D30: Jun-2024 | E30: Jul-2024 | F30: Aug-2024 | G30: Sep-2024 | H30: Oct-2024 | I30: Nov-2024 | J30: Dec-2024 | K30: Jan-2025 | L30: Feb-2025 | M30: Mar-2025 | N30: TOTAL
A31: Ajay Gupta | B31: =SUMPRODUCT(SUMIFS('For Tally'!D:D, 'For Tally'!H:H, $A31, 'For Tally'!A:A, ">=2024-04-01", 'For Tally'!A:A, "<=2024-04-30", 'For Tally'!L:L, $B$5:$D$5)) | C31: =SUMPRODUCT(SUMIFS('For Tally'!D:D, 'For Tally'!H:H, $A31, 'For Tally'!A:A, ">=2024-05-01", 'For Tally'!A:A, "<=2024-05-31", 'For Tally'!L:L, $B$5:$D$5)) | D31: =SUMPRODUCT(SUMIFS('For Tally'!D:D, 'For Tally'!H:H, $A31, 'For Tally'!A:A, ">=2024-06-01", 'For Tally'!A:A, "<=2024-06-30", 'For Tally'!L:L, $B$5:$D$5)) | E31: =SUMPRODUCT(SUMIFS('For Tally'!D:D, 'For Tally'!H:H, $A31, 'For Tally'!A:A, ">=2024-07-01", 'For Tally'!A:A, "<=2024-07-31", 'For Tally'!L:L, $B$5:$D$5)) | F31: =SUMPRODUCT(SUMIFS('For Tally'!D:D, 'For Tally'!H:H, $A31, 'For Tally'!A:A, ">=2024-08-01", 'For Tally'!A:A, "<=2024-08-31", 'For Tally'!L:L, $B$5:$D$5)) | G31: =SUMPRODUCT(SUMIFS('For Tally'!D:D, 'For Tally'!H:H, $A31, 'For Tally'!A:A, ">=2024-09-01", 'For Tally'!A:A, "<=2024-09-30", 'For Tally'!L:L, $B$5:$D$5)) | H31: =SUMPRODUCT(SUMIFS('For Tally'!D:D, 'For Tally'!H:H, $A31, 'For Tally'!A:A, ">=2024-10-01", 'For Tally'!A:A, "<=2024-10-31", 'For Tally'!L:L, $B$5:$D$5)) | I31: =SUMPRODUCT(SUMIFS('For Tally'!D:D, 'For Tally'!H:H, $A31, 'For Tally'!A:A, ">=2024-11-01", 'For Tally'!A:A, "<=2024-11-30", 'For Tally'!L:L, $B$5:$D$5)) | J31: =SUMPRODUCT(SUMIFS('For Tally'!D:D, 'For Tally'!H:H, $A31, 'For Tally'!A:A, ">=2024-12-01", 'For Tally'!A:A, "<=2024-12-31", 'For Tally'!L:L, $B$5:$D$5)) | K31: =SUMPRODUCT(SUMIFS('For Tally'!D:D, 'For Tally'!H:H, $A31, 'For Tally'!A:A, ">=2025-01-01", 'For Tally'!A:A, "<=2025-01-31", 'For Tally'!L:L, $B$5:$D$5)) | L31: =SUMPRODUCT(SUMIFS('For Tally'!D:D, 'For Tally'!H:H, $A31, 'For Tally'!A:A, ">=2025-02-01", 'For Tally'!A:A, "<=2025-02-28", 'For Tally'!L:L, $B$5:$D$5)) | M31: =SUMPRODUCT(SUMIFS('For Tally'!D:D, 'For Tally'!H:H, $A31, 'For Tally'!A:A, ">=2025-03-01", 'For Tally'!A:A, "<=2025-03-31", 'For Tally'!L:L, $B$5:$D$5)) | N31: =SUM(B31:M31)
A32: Archit Gupta | B32: =SUMPRODUCT(SUMIFS('For Tally'!D:D, 'For Tally'!H:H, $A32, 'For Tally'!A:A, ">=2024-04-01", 'For Tally'!A:A, "<=2024-04-30", 'For Tally'!L:L, $B$5:$D$5)) | C32: =SUMPRODUCT(SUMIFS('For Tally'!D:D, 'For Tally'!H:H, $A32, 'For Tally'!A:A, ">=2024-05-01", 'For Tally'!A:A, "<=2024-05-31", 'For Tally'!L:L, $B$5:$D$5)) | D32: =SUMPRODUCT(SUMIFS('For Tally'!D:D, 'For Tally'!H:H, $A32, 'For Tally'!A:A, ">=2024-06-01", 'For Tally'!A:A, "<=2024-06-30", 'For Tally'!L:L, $B$5:$D$5)) | E32: =SUMPRODUCT(SUMIFS('For Tally'!D:D, 'For Tally'!H:H, $A32, 'For Tally'!A:A, ">=2024-07-01", 'For Tally'!A:A, "<=2024-07-31", 'For Tally'!L:L, $B$5:$D$5)) | F32: =SUMPRODUCT(SUMIFS('For Tally'!D:D, 'For Tally'!H:H, $A32, 'For Tally'!A:A, ">=2024-08-01", 'For Tally'!A:A, "<=2024-08-31", 'For Tally'!L:L, $B$5:$D$5)) | G32: =SUMPRODUCT(SUMIFS('For Tally'!D:D, 'For Tally'!H:H, $A32, 'For Tally'!A:A, ">=2024-09-01", 'For Tally'!A:A, "<=2024-09-30", 'For Tally'!L:L, $B$5:$D$5)) | H32: =SUMPRODUCT(SUMIFS('For Tally'!D:D, 'For Tally'!H:H, $A32, 'For Tally'!A:A, ">=2024-10-01", 'For Tally'!A:A, "<=2024-10-31", 'For Tally'!L:L, $B$5:$D$5)) | I32: =SUMPRODUCT(SUMIFS('For Tally'!D:D, 'For Tally'!H:H, $A32, 'For Tally'!A:A, ">=2024-11-01", 'For Tally'!A:A, "<=2024-11-30", 'For Tally'!L:L, $B$5:$D$5)) | J32: =SUMPRODUCT(SUMIFS('For Tally'!D:D, 'For Tally'!H:H, $A32, 'For Tally'!A:A, ">=2024-12-01", 'For Tally'!A:A, "<=2024-12-31", 'For Tally'!L:L, $B$5:$D$5)) | K32: =SUMPRODUCT(SUMIFS('For Tally'!D:D, 'For Tally'!H:H, $A32, 'For Tally'!A:A, ">=2025-01-01", 'For Tally'!A:A, "<=2025-01-31", 'For Tally'!L:L, $B$5:$D$5)) | L32: =SUMPRODUCT(SUMIFS('For Tally'!D:D, 'For Tally'!H:H, $A32, 'For Tally'!A:A, ">=2025-02-01", 'For Tally'!A:A, "<=2025-02-28", 'For Tally'!L:L, $B$5:$D$5)) | M32: =SUMPRODUCT(SUMIFS('For Tally'!D:D, 'For Tally'!H:H, $A32, 'For Tally'!A:A, ">=2025-03-01", 'For Tally'!A:A, "<=2025-03-31", 'For Tally'!L:L, $B$5:$D$5)) | N32: =SUM(B32:M32)
A33: Bank Interest | B33: =SUMPRODUCT(SUMIFS('For Tally'!D:D, 'For Tally'!H:H, $A33, 'For Tally'!A:A, ">=2024-04-01", 'For Tally'!A:A, "<=2024-04-30", 'For Tally'!L:L, $B$5:$D$5)) | C33: =SUMPRODUCT(SUMIFS('For Tally'!D:D, 'For Tally'!H:H, $A33, 'For Tally'!A:A, ">=2024-05-01", 'For Tally'!A:A, "<=2024-05-31", 'For Tally'!L:L, $B$5:$D$5)) | D33: =SUMPRODUCT(SUMIFS('For Tally'!D:D, 'For Tally'!H:H, $A33, 'For Tally'!A:A, ">=2024-06-01", 'For Tally'!A:A, "<=2024-06-30", 'For Tally'!L:L, $B$5:$D$5)) | E33: =SUMPRODUCT(SUMIFS('For Tally'!D:D, 'For Tally'!H:H, $A33, 'For Tally'!A:A, ">=2024-07-01", 'For Tally'!A:A, "<=2024-07-31", 'For Tally'!L:L, $B$5:$D$5)) | F33: =SUMPRODUCT(SUMIFS('For Tally'!D:D, 'For Tally'!H:H, $A33, 'For Tally'!A:A, ">=2024-08-01", 'For Tally'!A:A, "<=2024-08-31", 'For Tally'!L:L, $B$5:$D$5)) | G33: =SUMPRODUCT(SUMIFS('For Tally'!D:D, 'For Tally'!H:H, $A33, 'For Tally'!A:A, ">=2024-09-01", 'For Tally'!A:A, "<=2024-09-30", 'For Tally'!L:L, $B$5:$D$5)) | H33: =SUMPRODUCT(SUMIFS('For Tally'!D:D, 'For Tally'!H:H, $A33, 'For Tally'!A:A, ">=2024-10-01", 'For Tally'!A:A, "<=2024-10-31", 'For Tally'!L:L, $B$5:$D$5)) | I33: =SUMPRODUCT(SUMIFS('For Tally'!D:D, 'For Tally'!H:H, $A33, 'For Tally'!A:A, ">=2024-11-01", 'For Tally'!A:A, "<=2024-11-30", 'For Tally'!L:L, $B$5:$D$5)) | J33: =SUMPRODUCT(SUMIFS('For Tally'!D:D, 'For Tally'!H:H, $A33, 'For Tally'!A:A, ">=2024-12-01", 'For Tally'!A:A, "<=2024-12-31", 'For Tally'!L:L, $B$5:$D$5)) | K33: =SUMPRODUCT(SUMIFS('For Tally'!D:D, 'For Tally'!H:H, $A33, 'For Tally'!A:A, ">=2025-01-01", 'For Tally'!A:A, "<=2025-01-31", 'For Tally'!L:L, $B$5:$D$5)) | L33: =SUMPRODUCT(SUMIFS('For Tally'!D:D, 'For Tally'!H:H, $A33, 'For Tally'!A:A, ">=2025-02-01", 'For Tally'!A:A, "<=2025-02-28", 'For Tally'!L:L, $B$5:$D$5)) | M33: =SUMPRODUCT(SUMIFS('For Tally'!D:D, 'For Tally'!H:H, $A33, 'For Tally'!A:A, ">=2025-03-01", 'For Tally'!A:A, "<=2025-03-31", 'For Tally'!L:L, $B$5:$D$5)) | N33: =SUM(B33:M33)
A34: Cash | B34: =SUMPRODUCT(SUMIFS('For Tally'!D:D, 'For Tally'!H:H, $A34, 'For Tally'!A:A, ">=2024-04-01", 'For Tally'!A:A, "<=2024-04-30", 'For Tally'!L:L, $B$5:$D$5)) | C34: =SUMPRODUCT(SUMIFS('For Tally'!D:D, 'For Tally'!H:H, $A34, 'For Tally'!A:A, ">=2024-05-01", 'For Tally'!A:A, "<=2024-05-31", 'For Tally'!L:L, $B$5:$D$5)) | D34: =SUMPRODUCT(SUMIFS('For Tally'!D:D, 'For Tally'!H:H, $A34, 'For Tally'!A:A, ">=2024-06-01", 'For Tally'!A:A, "<=2024-06-30", 'For Tally'!L:L, $B$5:$D$5)) | E34: =SUMPRODUCT(SUMIFS('For Tally'!D:D, 'For Tally'!H:H, $A34, 'For Tally'!A:A, ">=2024-07-01", 'For Tally'!A:A, "<=2024-07-31", 'For Tally'!L:L, $B$5:$D$5)) | F34: =SUMPRODUCT(SUMIFS('For Tally'!D:D, 'For Tally'!H:H, $A34, 'For Tally'!A:A, ">=2024-08-01", 'For Tally'!A:A, "<=2024-08-31", 'For Tally'!L:L, $B$5:$D$5)) | G34: =SUMPRODUCT(SUMIFS('For Tally'!D:D, 'For Tally'!H:H, $A34, 'For Tally'!A:A, ">=2024-09-01", 'For Tally'!A:A, "<=2024-09-30", 'For Tally'!L:L, $B$5:$D$5)) | H34: =SUMPRODUCT(SUMIFS('For Tally'!D:D, 'For Tally'!H:H, $A34, 'For Tally'!A:A, ">=2024-10-01", 'For Tally'!A:A, "<=2024-10-31", 'For Tally'!L:L, $B$5:$D$5)) | I34: =SUMPRODUCT(SUMIFS('For Tally'!D:D, 'For Tally'!H:H, $A34, 'For Tally'!A:A, ">=2024-11-01", 'For Tally'!A:A, "<=2024-11-30", 'For Tally'!L:L, $B$5:$D$5)) | J34: =SUMPRODUCT(SUMIFS('For Tally'!D:D, 'For Tally'!H:H, $A34, 'For Tally'!A:A, ">=2024-12-01", 'For Tally'!A:A, "<=2024-12-31", 'For Tally'!L:L, $B$5:$D$5)) | K34: =SUMPRODUCT(SUMIFS('For Tally'!D:D, 'For Tally'!H:H, $A34, 'For Tally'!A:A, ">=2025-01-01", 'For Tally'!A:A, "<=2025-01-31", 'For Tally'!L:L, $B$5:$D$5)) | L34: =SUMPRODUCT(SUMIFS('For Tally'!D:D, 'For Tally'!H:H, $A34, 'For Tally'!A:A, ">=2025-02-01", 'For Tally'!A:A, "<=2025-02-28", 'For Tally'!L:L, $B$5:$D$5)) | M34: =SUMPRODUCT(SUMIFS('For Tally'!D:D, 'For Tally'!H:H, $A34, 'For Tally'!A:A, ">=2025-03-01", 'For Tally'!A:A, "<=2025-03-31", 'For Tally'!L:L, $B$5:$D$5)) | N34: =SUM(B34:M34)
A35: Dividend Income | B35: =SUMPRODUCT(SUMIFS('For Tally'!D:D, 'For Tally'!H:H, $A35, 'For Tally'!A:A, ">=2024-04-01", 'For Tally'!A:A, "<=2024-04-30", 'For Tally'!L:L, $B$5:$D$5)) | C35: =SUMPRODUCT(SUMIFS('For Tally'!D:D, 'For Tally'!H:H, $A35, 'For Tally'!A:A, ">=2024-05-01", 'For Tally'!A:A, "<=2024-05-31", 'For Tally'!L:L, $B$5:$D$5)) | D35: =SUMPRODUCT(SUMIFS('For Tally'!D:D, 'For Tally'!H:H, $A35, 'For Tally'!A:A, ">=2024-06-01", 'For Tally'!A:A, "<=2024-06-30", 'For Tally'!L:L, $B$5:$D$5)) | E35: =SUMPRODUCT(SUMIFS('For Tally'!D:D, 'For Tally'!H:H, $A35, 'For Tally'!A:A, ">=2024-07-01", 'For Tally'!A:A, "<=2024-07-31", 'For Tally'!L:L, $B$5:$D$5)) | F35: =SUMPRODUCT(SUMIFS('For Tally'!D:D, 'For Tally'!H:H, $A35, 'For Tally'!A:A, ">=2024-08-01", 'For Tally'!A:A, "<=2024-08-31", 'For Tally'!L:L, $B$5:$D$5)) | G35: =SUMPRODUCT(SUMIFS('For Tally'!D:D, 'For Tally'!H:H, $A35, 'For Tally'!A:A, ">=2024-09-01", 'For Tally'!A:A, "<=2024-09-30", 'For Tally'!L:L, $B$5:$D$5)) | H35: =SUMPRODUCT(SUMIFS('For Tally'!D:D, 'For Tally'!H:H, $A35, 'For Tally'!A:A, ">=2024-10-01", 'For Tally'!A:A, "<=2024-10-31", 'For Tally'!L:L, $B$5:$D$5)) | I35: =SUMPRODUCT(SUMIFS('For Tally'!D:D, 'For Tally'!H:H, $A35, 'For Tally'!A:A, ">=2024-11-01", 'For Tally'!A:A, "<=2024-11-30", 'For Tally'!L:L, $B$5:$D$5)) | J35: =SUMPRODUCT(SUMIFS('For Tally'!D:D, 'For Tally'!H:H, $A35, 'For Tally'!A:A, ">=2024-12-01", 'For Tally'!A:A, "<=2024-12-31", 'For Tally'!L:L, $B$5:$D$5)) | K35: =SUMPRODUCT(SUMIFS('For Tally'!D:D, 'For Tally'!H:H, $A35, 'For Tally'!A:A, ">=2025-01-01", 'For Tally'!A:A, "<=2025-01-31", 'For Tally'!L:L, $B$5:$D$5)) | L35: =SUMPRODUCT(SUMIFS('For Tally'!D:D, 'For Tally'!H:H, $A35, 'For Tally'!A:A, ">=2025-02-01", 'For Tally'!A:A, "<=2025-02-28", 'For Tally'!L:L, $B$5:$D$5)) | M35: =SUMPRODUCT(SUMIFS('For Tally'!D:D, 'For Tally'!H:H, $A35, 'For Tally'!A:A, ">=2025-03-01", 'For Tally'!A:A, "<=2025-03-31", 'For Tally'!L:L, $B$5:$D$5)) | N35: =SUM(B35:M35)
A36: HDFC Securities | B36: =SUMPRODUCT(SUMIFS('For Tally'!D:D, 'For Tally'!H:H, $A36, 'For Tally'!A:A, ">=2024-04-01", 'For Tally'!A:A, "<=2024-04-30", 'For Tally'!L:L, $B$5:$D$5)) | C36: =SUMPRODUCT(SUMIFS('For Tally'!D:D, 'For Tally'!H:H, $A36, 'For Tally'!A:A, ">=2024-05-01", 'For Tally'!A:A, "<=2024-05-31", 'For Tally'!L:L, $B$5:$D$5)) | D36: =SUMPRODUCT(SUMIFS('For Tally'!D:D, 'For Tally'!H:H, $A36, 'For Tally'!A:A, ">=2024-06-01", 'For Tally'!A:A, "<=2024-06-30", 'For Tally'!L:L, $B$5:$D$5)) | E36: =SUMPRODUCT(SUMIFS('For Tally'!D:D, 'For Tally'!H:H, $A36, 'For Tally'!A:A, ">=2024-07-01", 'For Tally'!A:A, "<=2024-07-31", 'For Tally'!L:L, $B$5:$D$5)) | F36: =SUMPRODUCT(SUMIFS('For Tally'!D:D, 'For Tally'!H:H, $A36, 'For Tally'!A:A, ">=2024-08-01", 'For Tally'!A:A, "<=2024-08-31", 'For Tally'!L:L, $B$5:$D$5)) | G36: =SUMPRODUCT(SUMIFS('For Tally'!D:D, 'For Tally'!H:H, $A36, 'For Tally'!A:A, ">=2024-09-01", 'For Tally'!A:A, "<=2024-09-30", 'For Tally'!L:L, $B$5:$D$5)) | H36: =SUMPRODUCT(SUMIFS('For Tally'!D:D, 'For Tally'!H:H, $A36, 'For Tally'!A:A, ">=2024-10-01", 'For Tally'!A:A, "<=2024-10-31", 'For Tally'!L:L, $B$5:$D$5)) | I36: =SUMPRODUCT(SUMIFS('For Tally'!D:D, 'For Tally'!H:H, $A36, 'For Tally'!A:A, ">=2024-11-01", 'For Tally'!A:A, "<=2024-11-30", 'For Tally'!L:L, $B$5:$D$5)) | J36: =SUMPRODUCT(SUMIFS('For Tally'!D:D, 'For Tally'!H:H, $A36, 'For Tally'!A:A, ">=2024-12-01", 'For Tally'!A:A, "<=2024-12-31", 'For Tally'!L:L, $B$5:$D$5)) | K36: =SUMPRODUCT(SUMIFS('For Tally'!D:D, 'For Tally'!H:H, $A36, 'For Tally'!A:A, ">=2025-01-01", 'For Tally'!A:A, "<=2025-01-31", 'For Tally'!L:L, $B$5:$D$5)) | L36: =SUMPRODUCT(SUMIFS('For Tally'!D:D, 'For Tally'!H:H, $A36, 'For Tally'!A:A, ">=2025-02-01", 'For Tally'!A:A, "<=2025-02-28", 'For Tally'!L:L, $B$5:$D$5)) | M36: =SUMPRODUCT(SUMIFS('For Tally'!D:D, 'For Tally'!H:H, $A36, 'For Tally'!A:A, ">=2025-03-01", 'For Tally'!A:A, "<=2025-03-31", 'For Tally'!L:L, $B$5:$D$5)) | N36: =SUM(B36:M36)
A37: Income Tax | B37: =SUMPRODUCT(SUMIFS('For Tally'!D:D, 'For Tally'!H:H, $A37, 'For Tally'!A:A, ">=2024-04-01", 'For Tally'!A:A, "<=2024-04-30", 'For Tally'!L:L, $B$5:$D$5)) | C37: =SUMPRODUCT(SUMIFS('For Tally'!D:D, 'For Tally'!H:H, $A37, 'For Tally'!A:A, ">=2024-05-01", 'For Tally'!A:A, "<=2024-05-31", 'For Tally'!L:L, $B$5:$D$5)) | D37: =SUMPRODUCT(SUMIFS('For Tally'!D:D, 'For Tally'!H:H, $A37, 'For Tally'!A:A, ">=2024-06-01", 'For Tally'!A:A, "<=2024-06-30", 'For Tally'!L:L, $B$5:$D$5)) | E37: =SUMPRODUCT(SUMIFS('For Tally'!D:D, 'For Tally'!H:H, $A37, 'For Tally'!A:A, ">=2024-07-01", 'For Tally'!A:A, "<=2024-07-31", 'For Tally'!L:L, $B$5:$D$5)) | F37: =SUMPRODUCT(SUMIFS('For Tally'!D:D, 'For Tally'!H:H, $A37, 'For Tally'!A:A, ">=2024-08-01", 'For Tally'!A:A, "<=2024-08-31", 'For Tally'!L:L, $B$5:$D$5)) | G37: =SUMPRODUCT(SUMIFS('For Tally'!D:D, 'For Tally'!H:H, $A37, 'For Tally'!A:A, ">=2024-09-01", 'For Tally'!A:A, "<=2024-09-30", 'For Tally'!L:L, $B$5:$D$5)) | H37: =SUMPRODUCT(SUMIFS('For Tally'!D:D, 'For Tally'!H:H, $A37, 'For Tally'!A:A, ">=2024-10-01", 'For Tally'!A:A, "<=2024-10-31", 'For Tally'!L:L, $B$5:$D$5)) | I37: =SUMPRODUCT(SUMIFS('For Tally'!D:D, 'For Tally'!H:H, $A37, 'For Tally'!A:A, ">=2024-11-01", 'For Tally'!A:A, "<=2024-11-30", 'For Tally'!L:L, $B$5:$D$5)) | J37: =SUMPRODUCT(SUMIFS('For Tally'!D:D, 'For Tally'!H:H, $A37, 'For Tally'!A:A, ">=2024-12-01", 'For Tally'!A:A, "<=2024-12-31", 'For Tally'!L:L, $B$5:$D$5)) | K37: =SUMPRODUCT(SUMIFS('For Tally'!D:D, 'For Tally'!H:H, $A37, 'For Tally'!A:A, ">=2025-01-01", 'For Tally'!A:A, "<=2025-01-31", 'For Tally'!L:L, $B$5:$D$5)) | L37: =SUMPRODUCT(SUMIFS('For Tally'!D:D, 'For Tally'!H:H, $A37, 'For Tally'!A:A, ">=2025-02-01", 'For Tally'!A:A, "<=2025-02-28", 'For Tally'!L:L, $B$5:$D$5)) | M37: =SUMPRODUCT(SUMIFS('For Tally'!D:D, 'For Tally'!H:H, $A37, 'For Tally'!A:A, ">=2025-03-01", 'For Tally'!A:A, "<=2025-03-31", 'For Tally'!L:L, $B$5:$D$5)) | N37: =SUM(B37:M37)
A38: Misc Income | B38: =SUMPRODUCT(SUMIFS('For Tally'!D:D, 'For Tally'!H:H, $A38, 'For Tally'!A:A, ">=2024-04-01", 'For Tally'!A:A, "<=2024-04-30", 'For Tally'!L:L, $B$5:$D$5)) | C38: =SUMPRODUCT(SUMIFS('For Tally'!D:D, 'For Tally'!H:H, $A38, 'For Tally'!A:A, ">=2024-05-01", 'For Tally'!A:A, "<=2024-05-31", 'For Tally'!L:L, $B$5:$D$5)) | D38: =SUMPRODUCT(SUMIFS('For Tally'!D:D, 'For Tally'!H:H, $A38, 'For Tally'!A:A, ">=2024-06-01", 'For Tally'!A:A, "<=2024-06-30", 'For Tally'!L:L, $B$5:$D$5)) | E38: =SUMPRODUCT(SUMIFS('For Tally'!D:D, 'For Tally'!H:H, $A38, 'For Tally'!A:A, ">=2024-07-01", 'For Tally'!A:A, "<=2024-07-31", 'For Tally'!L:L, $B$5:$D$5)) | F38: =SUMPRODUCT(SUMIFS('For Tally'!D:D, 'For Tally'!H:H, $A38, 'For Tally'!A:A, ">=2024-08-01", 'For Tally'!A:A, "<=2024-08-31", 'For Tally'!L:L, $B$5:$D$5)) | G38: =SUMPRODUCT(SUMIFS('For Tally'!D:D, 'For Tally'!H:H, $A38, 'For Tally'!A:A, ">=2024-09-01", 'For Tally'!A:A, "<=2024-09-30", 'For Tally'!L:L, $B$5:$D$5)) | H38: =SUMPRODUCT(SUMIFS('For Tally'!D:D, 'For Tally'!H:H, $A38, 'For Tally'!A:A, ">=2024-10-01", 'For Tally'!A:A, "<=2024-10-31", 'For Tally'!L:L, $B$5:$D$5)) | I38: =SUMPRODUCT(SUMIFS('For Tally'!D:D, 'For Tally'!H:H, $A38, 'For Tally'!A:A, ">=2024-11-01", 'For Tally'!A:A, "<=2024-11-30", 'For Tally'!L:L, $B$5:$D$5)) | J38: =SUMPRODUCT(SUMIFS('For Tally'!D:D, 'For Tally'!H:H, $A38, 'For Tally'!A:A, ">=2024-12-01", 'For Tally'!A:A, "<=2024-12-31", 'For Tally'!L:L, $B$5:$D$5)) | K38: =SUMPRODUCT(SUMIFS('For Tally'!D:D, 'For Tally'!H:H, $A38, 'For Tally'!A:A, ">=2025-01-01", 'For Tally'!A:A, "<=2025-01-31", 'For Tally'!L:L, $B$5:$D$5)) | L38: =SUMPRODUCT(SUMIFS('For Tally'!D:D, 'For Tally'!H:H, $A38, 'For Tally'!A:A, ">=2025-02-01", 'For Tally'!A:A, "<=2025-02-28", 'For Tally'!L:L, $B$5:$D$5)) | M38: =SUMPRODUCT(SUMIFS('For Tally'!D:D, 'For Tally'!H:H, $A38, 'For Tally'!A:A, ">=2025-03-01", 'For Tally'!A:A, "<=2025-03-31", 'For Tally'!L:L, $B$5:$D$5)) | N38: =SUM(B38:M38)
A39: Mutual Funds | B39: =SUMPRODUCT(SUMIFS('For Tally'!D:D, 'For Tally'!H:H, $A39, 'For Tally'!A:A, ">=2024-04-01", 'For Tally'!A:A, "<=2024-04-30", 'For Tally'!L:L, $B$5:$D$5)) | C39: =SUMPRODUCT(SUMIFS('For Tally'!D:D, 'For Tally'!H:H, $A39, 'For Tally'!A:A, ">=2024-05-01", 'For Tally'!A:A, "<=2024-05-31", 'For Tally'!L:L, $B$5:$D$5)) | D39: =SUMPRODUCT(SUMIFS('For Tally'!D:D, 'For Tally'!H:H, $A39, 'For Tally'!A:A, ">=2024-06-01", 'For Tally'!A:A, "<=2024-06-30", 'For Tally'!L:L, $B$5:$D$5)) | E39: =SUMPRODUCT(SUMIFS('For Tally'!D:D, 'For Tally'!H:H, $A39, 'For Tally'!A:A, ">=2024-07-01", 'For Tally'!A:A, "<=2024-07-31", 'For Tally'!L:L, $B$5:$D$5)) | F39: =SUMPRODUCT(SUMIFS('For Tally'!D:D, 'For Tally'!H:H, $A39, 'For Tally'!A:A, ">=2024-08-01", 'For Tally'!A:A, "<=2024-08-31", 'For Tally'!L:L, $B$5:$D$5)) | G39: =SUMPRODUCT(SUMIFS('For Tally'!D:D, 'For Tally'!H:H, $A39, 'For Tally'!A:A, ">=2024-09-01", 'For Tally'!A:A, "<=2024-09-30", 'For Tally'!L:L, $B$5:$D$5)) | H39: =SUMPRODUCT(SUMIFS('For Tally'!D:D, 'For Tally'!H:H, $A39, 'For Tally'!A:A, ">=2024-10-01", 'For Tally'!A:A, "<=2024-10-31", 'For Tally'!L:L, $B$5:$D$5)) | I39: =SUMPRODUCT(SUMIFS('For Tally'!D:D, 'For Tally'!H:H, $A39, 'For Tally'!A:A, ">=2024-11-01", 'For Tally'!A:A, "<=2024-11-30", 'For Tally'!L:L, $B$5:$D$5)) | J39: =SUMPRODUCT(SUMIFS('For Tally'!D:D, 'For Tally'!H:H, $A39, 'For Tally'!A:A, ">=2024-12-01", 'For Tally'!A:A, "<=2024-12-31", 'For Tally'!L:L, $B$5:$D$5)) | K39: =SUMPRODUCT(SUMIFS('For Tally'!D:D, 'For Tally'!H:H, $A39, 'For Tally'!A:A, ">=2025-01-01", 'For Tally'!A:A, "<=2025-01-31", 'For Tally'!L:L, $B$5:$D$5)) | L39: =SUMPRODUCT(SUMIFS('For Tally'!D:D, 'For Tally'!H:H, $A39, 'For Tally'!A:A, ">=2025-02-01", 'For Tally'!A:A, "<=2025-02-28", 'For Tally'!L:L, $B$5:$D$5)) | M39: =SUMPRODUCT(SUMIFS('For Tally'!D:D, 'For Tally'!H:H, $A39, 'For Tally'!A:A, ">=2025-03-01", 'For Tally'!A:A, "<=2025-03-31", 'For Tally'!L:L, $B$5:$D$5)) | N39: =SUM(B39:M39)
A40: Personal | B40: =SUMPRODUCT(SUMIFS('For Tally'!D:D, 'For Tally'!H:H, $A40, 'For Tally'!A:A, ">=2024-04-01", 'For Tally'!A:A, "<=2024-04-30", 'For Tally'!L:L, $B$5:$D$5)) | C40: =SUMPRODUCT(SUMIFS('For Tally'!D:D, 'For Tally'!H:H, $A40, 'For Tally'!A:A, ">=2024-05-01", 'For Tally'!A:A, "<=2024-05-31", 'For Tally'!L:L, $B$5:$D$5)) | D40: =SUMPRODUCT(SUMIFS('For Tally'!D:D, 'For Tally'!H:H, $A40, 'For Tally'!A:A, ">=2024-06-01", 'For Tally'!A:A, "<=2024-06-30", 'For Tally'!L:L, $B$5:$D$5)) | E40: =SUMPRODUCT(SUMIFS('For Tally'!D:D, 'For Tally'!H:H, $A40, 'For Tally'!A:A, ">=2024-07-01", 'For Tally'!A:A, "<=2024-07-31", 'For Tally'!L:L, $B$5:$D$5)) | F40: =SUMPRODUCT(SUMIFS('For Tally'!D:D, 'For Tally'!H:H, $A40, 'For Tally'!A:A, ">=2024-08-01", 'For Tally'!A:A, "<=2024-08-31", 'For Tally'!L:L, $B$5:$D$5)) | G40: =SUMPRODUCT(SUMIFS('For Tally'!D:D, 'For Tally'!H:H, $A40, 'For Tally'!A:A, ">=2024-09-01", 'For Tally'!A:A, "<=2024-09-30", 'For Tally'!L:L, $B$5:$D$5)) | H40: =SUMPRODUCT(SUMIFS('For Tally'!D:D, 'For Tally'!H:H, $A40, 'For Tally'!A:A, ">=2024-10-01", 'For Tally'!A:A, "<=2024-10-31", 'For Tally'!L:L, $B$5:$D$5)) | I40: =SUMPRODUCT(SUMIFS('For Tally'!D:D, 'For Tally'!H:H, $A40, 'For Tally'!A:A, ">=2024-11-01", 'For Tally'!A:A, "<=2024-11-30", 'For Tally'!L:L, $B$5:$D$5)) | J40: =SUMPRODUCT(SUMIFS('For Tally'!D:D, 'For Tally'!H:H, $A40, 'For Tally'!A:A, ">=2024-12-01", 'For Tally'!A:A, "<=2024-12-31", 'For Tally'!L:L, $B$5:$D$5)) | K40: =SUMPRODUCT(SUMIFS('For Tally'!D:D, 'For Tally'!H:H, $A40, 'For Tally'!A:A, ">=2025-01-01", 'For Tally'!A:A, "<=2025-01-31", 'For Tally'!L:L, $B$5:$D$5)) | L40: =SUMPRODUCT(SUMIFS('For Tally'!D:D, 'For Tally'!H:H, $A40, 'For Tally'!A:A, ">=2025-02-01", 'For Tally'!A:A, "<=2025-02-28", 'For Tally'!L:L, $B$5:$D$5)) | M40: =SUMPRODUCT(SUMIFS('For Tally'!D:D, 'For Tally'!H:H, $A40, 'For Tally'!A:A, ">=2025-03-01", 'For Tally'!A:A, "<=2025-03-31", 'For Tally'!L:L, $B$5:$D$5)) | N40: =SUM(B40:M40)
A41: Shopping | B41: =SUMPRODUCT(SUMIFS('For Tally'!D:D, 'For Tally'!H:H, $A41, 'For Tally'!A:A, ">=2024-04-01", 'For Tally'!A:A, "<=2024-04-30", 'For Tally'!L:L, $B$5:$D$5)) | C41: =SUMPRODUCT(SUMIFS('For Tally'!D:D, 'For Tally'!H:H, $A41, 'For Tally'!A:A, ">=2024-05-01", 'For Tally'!A:A, "<=2024-05-31", 'For Tally'!L:L, $B$5:$D$5)) | D41: =SUMPRODUCT(SUMIFS('For Tally'!D:D, 'For Tally'!H:H, $A41, 'For Tally'!A:A, ">=2024-06-01", 'For Tally'!A:A, "<=2024-06-30", 'For Tally'!L:L, $B$5:$D$5)) | E41: =SUMPRODUCT(SUMIFS('For Tally'!D:D, 'For Tally'!H:H, $A41, 'For Tally'!A:A, ">=2024-07-01", 'For Tally'!A:A, "<=2024-07-31", 'For Tally'!L:L, $B$5:$D$5)) | F41: =SUMPRODUCT(SUMIFS('For Tally'!D:D, 'For Tally'!H:H, $A41, 'For Tally'!A:A, ">=2024-08-01", 'For Tally'!A:A, "<=2024-08-31", 'For Tally'!L:L, $B$5:$D$5)) | G41: =SUMPRODUCT(SUMIFS('For Tally'!D:D, 'For Tally'!H:H, $A41, 'For Tally'!A:A, ">=2024-09-01", 'For Tally'!A:A, "<=2024-09-30", 'For Tally'!L:L, $B$5:$D$5)) | H41: =SUMPRODUCT(SUMIFS('For Tally'!D:D, 'For Tally'!H:H, $A41, 'For Tally'!A:A, ">=2024-10-01", 'For Tally'!A:A, "<=2024-10-31", 'For Tally'!L:L, $B$5:$D$5)) | I41: =SUMPRODUCT(SUMIFS('For Tally'!D:D, 'For Tally'!H:H, $A41, 'For Tally'!A:A, ">=2024-11-01", 'For Tally'!A:A, "<=2024-11-30", 'For Tally'!L:L, $B$5:$D$5)) | J41: =SUMPRODUCT(SUMIFS('For Tally'!D:D, 'For Tally'!H:H, $A41, 'For Tally'!A:A, ">=2024-12-01", 'For Tally'!A:A, "<=2024-12-31", 'For Tally'!L:L, $B$5:$D$5)) | K41: =SUMPRODUCT(SUMIFS('For Tally'!D:D, 'For Tally'!H:H, $A41, 'For Tally'!A:A, ">=2025-01-01", 'For Tally'!A:A, "<=2025-01-31", 'For Tally'!L:L, $B$5:$D$5)) | L41: =SUMPRODUCT(SUMIFS('For Tally'!D:D, 'For Tally'!H:H, $A41, 'For Tally'!A:A, ">=2025-02-01", 'For Tally'!A:A, "<=2025-02-28", 'For Tally'!L:L, $B$5:$D$5)) | M41: =SUMPRODUCT(SUMIFS('For Tally'!D:D, 'For Tally'!H:H, $A41, 'For Tally'!A:A, ">=2025-03-01", 'For Tally'!A:A, "<=2025-03-31", 'For Tally'!L:L, $B$5:$D$5)) | N41: =SUM(B41:M41)
A42: Sunita Gupta | B42: =SUMPRODUCT(SUMIFS('For Tally'!D:D, 'For Tally'!H:H, $A42, 'For Tally'!A:A, ">=2024-04-01", 'For Tally'!A:A, "<=2024-04-30", 'For Tally'!L:L, $B$5:$D$5)) | C42: =SUMPRODUCT(SUMIFS('For Tally'!D:D, 'For Tally'!H:H, $A42, 'For Tally'!A:A, ">=2024-05-01", 'For Tally'!A:A, "<=2024-05-31", 'For Tally'!L:L, $B$5:$D$5)) | D42: =SUMPRODUCT(SUMIFS('For Tally'!D:D, 'For Tally'!H:H, $A42, 'For Tally'!A:A, ">=2024-06-01", 'For Tally'!A:A, "<=2024-06-30", 'For Tally'!L:L, $B$5:$D$5)) | E42: =SUMPRODUCT(SUMIFS('For Tally'!D:D, 'For Tally'!H:H, $A42, 'For Tally'!A:A, ">=2024-07-01", 'For Tally'!A:A, "<=2024-07-31", 'For Tally'!L:L, $B$5:$D$5)) | F42: =SUMPRODUCT(SUMIFS('For Tally'!D:D, 'For Tally'!H:H, $A42, 'For Tally'!A:A, ">=2024-08-01", 'For Tally'!A:A, "<=2024-08-31", 'For Tally'!L:L, $B$5:$D$5)) | G42: =SUMPRODUCT(SUMIFS('For Tally'!D:D, 'For Tally'!H:H, $A42, 'For Tally'!A:A, ">=2024-09-01", 'For Tally'!A:A, "<=2024-09-30", 'For Tally'!L:L, $B$5:$D$5)) | H42: =SUMPRODUCT(SUMIFS('For Tally'!D:D, 'For Tally'!H:H, $A42, 'For Tally'!A:A, ">=2024-10-01", 'For Tally'!A:A, "<=2024-10-31", 'For Tally'!L:L, $B$5:$D$5)) | I42: =SUMPRODUCT(SUMIFS('For Tally'!D:D, 'For Tally'!H:H, $A42, 'For Tally'!A:A, ">=2024-11-01", 'For Tally'!A:A, "<=2024-11-30", 'For Tally'!L:L, $B$5:$D$5)) | J42: =SUMPRODUCT(SUMIFS('For Tally'!D:D, 'For Tally'!H:H, $A42, 'For Tally'!A:A, ">=2024-12-01", 'For Tally'!A:A, "<=2024-12-31", 'For Tally'!L:L, $B$5:$D$5)) | K42: =SUMPRODUCT(SUMIFS('For Tally'!D:D, 'For Tally'!H:H, $A42, 'For Tally'!A:A, ">=2025-01-01", 'For Tally'!A:A, "<=2025-01-31", 'For Tally'!L:L, $B$5:$D$5)) | L42: =SUMPRODUCT(SUMIFS('For Tally'!D:D, 'For Tally'!H:H, $A42, 'For Tally'!A:A, ">=2025-02-01", 'For Tally'!A:A, "<=2025-02-28", 'For Tally'!L:L, $B$5:$D$5)) | M42: =SUMPRODUCT(SUMIFS('For Tally'!D:D, 'For Tally'!H:H, $A42, 'For Tally'!A:A, ">=2025-03-01", 'For Tally'!A:A, "<=2025-03-31", 'For Tally'!L:L, $B$5:$D$5)) | N42: =SUM(B42:M42)
... A44: Transfer | B44: =SUMPRODUCT(SUMIFS('For Tally'!D:D, 'For Tally'!H:H, $A44, 'For Tally'!A:A, ">=2024-04-01", 'For Tally'!A:A, "<=2024-04-30", 'For Tally'!L:L, $B$5:$D$5)) | C44: =SUMPRODUCT(SUMIFS('For Tally'!D:D, 'For Tally'!H:H, $A44, 'For Tally'!A:A, ">=2024-05-01", 'For Tally'!A:A, "<=2024-05-31", 'For Tally'!L:L, $B$5:$D$5)) | D44: =SUMPRODUCT(SUMIFS('For Tally'!D:D, 'For Tally'!H:H, $A44, 'For Tally'!A:A, ">=2024-06-01", 'For Tally'!A:A, "<=2024-06-30", 'For Tally'!L:L, $B$5:$D$5)) | E44: =SUMPRODUCT(SUMIFS('For Tally'!D:D, 'For Tally'!H:H, $A44, 'For Tally'!A:A, ">=2024-07-01", 'For Tally'!A:A, "<=2024-07-31", 'For Tally'!L:L, $B$5:$D$5)) | F44: =SUMPRODUCT(SUMIFS('For Tally'!D:D, 'For Tally'!H:H, $A44, 'For Tally'!A:A, ">=2024-08-01", 'For Tally'!A:A, "<=2024-08-31", 'For Tally'!L:L, $B$5:$D$5)) | G44: =SUMPRODUCT(SUMIFS('For Tally'!D:D, 'For Tally'!H:H, $A44, 'For Tally'!A:A, ">=2024-09-01", 'For Tally'!A:A, "<=2024-09-30", 'For Tally'!L:L, $B$5:$D$5)) | H44: =SUMPRODUCT(SUMIFS('For Tally'!D:D, 'For Tally'!H:H, $A44, 'For Tally'!A:A, ">=2024-10-01", 'For Tally'!A:A, "<=2024-10-31", 'For Tally'!L:L, $B$5:$D$5)) | I44: =SUMPRODUCT(SUMIFS('For Tally'!D:D, 'For Tally'!H:H, $A44, 'For Tally'!A:A, ">=2024-11-01", 'For Tally'!A:A, "<=2024-11-30", 'For Tally'!L:L, $B$5:$D$5)) | J44: =SUMPRODUCT(SUMIFS('For Tally'!D:D, 'For Tally'!H:H, $A44, 'For Tally'!A:A, ">=2024-12-01", 'For Tally'!A:A, "<=2024-12-31", 'For Tally'!L:L, $B$5:$D$5)) | K44: =SUMPRODUCT(SUMIFS('For Tally'!D:D, 'For Tally'!H:H, $A44, 'For Tally'!A:A, ">=2025-01-01", 'For Tally'!A:A, "<=2025-01-31", 'For Tally'!L:L, $B$5:$D$5)) | L44: =SUMPRODUCT(SUMIFS('For Tally'!D:D, 'For Tally'!H:H, $A44, 'For Tally'!A:A, ">=2025-02-01", 'For Tally'!A:A, "<=2025-02-28", 'For Tally'!L:L, $B$5:$D$5)) | M44: =SUMPRODUCT(SUMIFS('For Tally'!D:D, 'For Tally'!H:H, $A44, 'For Tally'!A:A, ">=2025-03-01", 'For Tally'!A:A, "<=2025-03-31", 'For Tally'!L:L, $B$5:$D$5)) | N44: =SUM(B44:M44)
A45: MONTHLY TOTAL | B45: =SUM(B31:B44) | C45: =SUM(C31:C44) | D45: =SUM(D31:D44) | E45: =SUM(E31:E44) | F45: =SUM(F31:F44) | G45: =SUM(G31:G44) | H45: =SUM(H31:H44) | I45: =SUM(I31:I44) | ... N45: =SUM(N31:N44)

Sheet Colour Legend
B2: Workbook Colour Legend
B5: INCOME & INFLOWS | C5: Colour Code | D5: Description
B7: Salary | C7: Sample Fill | D7: Salary Credit (Mphasis)
B8: Bank Interest | C8: Sample Fill | D8: Interest earned on Savings accounts
B9: Dividend Income | C9: Sample Fill | D9: Dividend payout from shares
B10: Annuity Income | C10: Sample Fill | D10: Annuity credits (HDFC Life)
B11: Income Tax Refund | C11: Sample Fill | D11: Income Tax Refund from Department
B12: MF Redemption | C12: Sample Fill | D12: Inflows from selling Mutual Funds
B13: Upwork Income | C13: Sample Fill | D13: Inward remittances from Upwork freelancing
B14: Cash Deposit | C14: Sample Fill | D14: Cash deposits made at CDM / Branch
B15: Freelance Income | C15: Sample Fill | D15: Freelance work escrow payouts
B16: Cashback - BHIM | C16: Sample Fill | D16: Cashback rewards earned on BHIM app
B17: Cashback - Kiwi | C17: Sample Fill | D17: Cashback rewards earned on Kiwi app
... B65: What is this? | C65: Sample Fill | D65: Suspense items requiring review (Suspense)
