Workbook

Sheet CG
B3: 347707 - Capital Gain Loss Details for Equity Derivatives as on: 2025/03/30 16:28:53
A5: CONTRACT | B5: BUY TRANSACTION DATE | C5: BUY TRANSACTION QTY | D5: BUY TRANSACTION VALUE | E5: SELL TRANSACTION DATE | F5: SELL TRANSACTION QTY | G5: SELL TRANSACTION VALUE | H5: PROFIT/LOSS | J5: Turnover | K5: =SUM(I6:I7) -> 3327.58
A6: OPTSTK-ABB-27-MAR-2025-5600-CE | B6: 26-MAR-2025 | C6: 125 | D6: 2964.79 | E6: 27-MAR-2025 | F6: 125 | G6: 0 | H6: -2964.79 | I6: =ABS(H6) -> 2964.79 | J6: Purchases | K6: =K5-K7 -> 6655.1575
A7: OPTIDX-NIFTY-09-MAY-2024-22500-CE | B7: 07-MAY-2024 | C7: 25 | D7: 1267.7 | E7: 07-MAY-2024 | F7: 25 | G7: 904.91 | H7: -362.79 | I7: =ABS(H7) -> 362.79 | J7: Loss | K7: =H8 -> -3327.5775
A8: DERIVATIVE FUND GAIN/LOSS | H8: -3327.5775
A10: * The Report includes Buy Back transactions

Sheet Interest Charged Report
A1: Interest Charged in ALL segment for period 01/04/24 to 31/03/25
A2: Entity Id : 347707 | E2: Amount is in Rs. | J2: Interest Charged | K2: =SUMIFS('HDFC HSL Ledger'!$J:$J,'HDFC HSL Ledger'!$M:$M,J2) -> 108443.43
A3: Sr No | B3: Date | C3: Segment | D3: Interest % | E3: Interest | F3: Debit Amount | G3: Interest Amount (Rs.) | H3: Interest Recovered (Rs.) | K3: =H371-K2 -> 0
E4: Charged for
E5: Day
A6: 0 | B6: 45744 | C6: MTF | D6: 13 | E6: 45743 | F6: 1161591.6 | G6: 413.72 | H6: 413.72
A7: 0 | B7: 45743 | C7: MTF | D7: 13 | E7: 45742 | F7: 1075559.7 | G7: 383.08 | H7: 383.08
A8: 0 | B8: 45742 | C8: MTF | D8: 13 | E8: 45741 | F8: 1081946.4 | G8: 385.35 | H8: 385.35
A9: 0 | B9: 45741 | C9: MTF | D9: 13 | E9: 45740 | F9: 1081140.5 | G9: 385.06 | H9: 385.06
A10: 0 | B10: 45740 | C10: MTF | D10: 13 | E10: 45739 | F10: 1035629.3 | G10: 368.85 | H10: 368.85
A11: 0 | B11: 45740 | C11: MTF | D11: 13 | E11: 45738 | F11: 1035629.3 | G11: 368.85 | H11: 368.85
A12: 0 | B12: 45740 | C12: MTF | D12: 13 | E12: 45737 | F12: 1035629.3 | G12: 368.85 | H12: 368.85
A13: 0 | B13: 45737 | C13: MTF | D13: 13 | E13: 45736 | F13: 969442.25 | G13: 345.28 | H13: 345.28
A14: 0 | B14: 45736 | C14: MTF | D14: 13 | E14: 45735 | F14: 996346.07 | G14: 354.86 | H14: 354.86
A15: 0 | B15: 45735 | C15: MTF | D15: 13 | E15: 45734 | F15: 754544.74 | G15: 268.74 | H15: 268.74
A16: 0 | B16: 45734 | C16: MTF | D16: 13 | E16: 45733 | F16: 739481.79 | G16: 263.38 | H16: 263.38
A17: 0 | B17: 45733 | C17: MTF | D17: 13 | E17: 45732 | F17: 792923.66 | G17: 282.41 | H17: 282.41
... A370: 0 | B370: 45383 | C370: MTF | D370: 13 | E370: 45379 | F370: 1272122.1 | G370: 453.08 | H370: 453.08
A371: 0 | B371: null | C371: TOTAL | D371: null | E371: null | F371: 3.0447589e+08 | G371: 108443.43 | H371: 108443.43
A372: No data found for specified parameters.

Sheet HDFC HSL Ledger
A2: Financial Ledger for the period 01/04/24 and 31/03/25
A3: Entity Id : 347707 | J3: Amount is in Rs. | L3: 1837434
J4: =J5-J6 -> -1.7291341e+08 | K4: =K5-K6 -> -1.7265918e+08
J6: =SUBTOTAL(9,J8:J2235) -> 1.7291341e+08 | K6: =SUBTOTAL(9,K8:K2235) -> 1.7265918e+08
A7: Sr No | B7: Trd Date | C7: Due Date | D7: Exchange | E7: Seg | F7: Narration | G7: Voucher Type | H7: Voucher No | I7: Bill No | J7: Dr Amount | K7: Cr Amount | L7: Running Balance | M7: 0
A8: 1 | B8: 45383 | C8: 45383 | D8: NSE | E8: E | F8: Online Trf for Net Payin from Bank A/c 01671000085930-/-MTF | G8: BANK RECEIPT | H8: ="20240401/34608" -> 20240401/34608 | I8: =" " | J8: 0 | K8: 1812.32 | L8: 1835621.7 | M8: Contra - HDFC
A9: 2 | B9: 45383 | C9: 45383 | D9: NSE | E9: E | F9: Online Trf for Net Payin from Bank A/c 01671000085930-/-MTF | G9: BANK RECEIPT | H9: ="20240401/92165" -> 20240401/92165 | I9: =" " | J9: 0 | K9: 19318.18 | L9: 1816303.5 | M9: Contra - HDFC
A10: 3 | B10: 45383 | C10: 45383 | D10: NSE | E10: E | F10: M/2024062/Margin Reversal-/-MTF | G10: BILLS | H10: ="20240401/157760" -> 20240401/157760 | I10: =" " | J10: 0 | K10: 595832.92 | L10: 1220470.6
A11: 4 | B11: 45383 | C11: 45383 | D11: NSE | E11: E | F11: M/2024062/Emargin MTM Loss Reversal-/-MTF | G11: BILLS | H11: ="20240401/157761" -> 20240401/157761 | I11: =" " | J11: 0 | K11: 51302.19 | L11: 1169168.4
A12: 5 | B12: 45383 | C12: 45383 | D12: NSE | E12: E | F12: Bg interest on MTF from 28-mar-2024 to 31-mar-2024-/-MTF | G12: BILLS | H12: ="20240401/17095" -> 20240401/17095 | I12: =" " | J12: 1812.32 | K12: 0 | L12: 1170980.7 | M12: Interest Charged
A13: 6 | B13: 45383 | C13: 45383 | D13: NSE | E13: E | F13: M/2024062/Emargin MTM Loss Bills.-/-MTF | G13: BILLS | H13: ="20240401/59807" -> 20240401/59807 | I13: =" " | J13: 32159.25 | K13: 0 | L13: 1203140
A14: 7 | B14: 45383 | C14: 45383 | D14: NSE | E14: E | F14: M/2024062/Margin Pay In-/-MTF | G14: BILLS | H14: ="20240401/59808" -> 20240401/59808 | I14: =" " | J14: 585074.73 | K14: 0 | L14: 1788214.7
A15: 8 | B15: 45384 | C15: 45384 | D15: NSE | E15: E | F15: Online Trf for Net Payout to Bank A/c 01671000085930-/-MTF | G15: BANK PAYMENT | H15: ="20240402/5441" -> 20240402/5441 | I15: =" " | J15: 5099.51 | K15: 0 | L15: 1793314.2 | M15: Contra - HDFC
A16: 9 | B16: 45384 | C16: 45384 | D16: NSE | E16: E | F16: Online Trf for Net Payout to Bank A/c 01671000085930 | G16: BANK PAYMENT | H16: ="20240402/60049" -> 20240402/60049 | I16: =" " | J16: 20780.76 | K16: 0 | L16: 1814095 | M16: Contra - HDFC
A17: 10 | B17: 45384 | C17: 45384 | D17: NSE | E17: E | F17: Online Trf for Net Payin from Bank A/c 01671000085930-/-MTF | G17: BANK RECEIPT | H17: ="20240402/36639" -> 20240402/36639 | I17: =" " | J17: 0 | K17: 446.2 | L17: 1813648.8 | M17: Contra - HDFC
A18: 11 | B18: 45384 | C18: 45384 | D18: NSE | E18: E | F18: Online Trf for Net Payin from Bank A/c 01671000085930-/-MTF | G18: BANK RECEIPT | H18: ="20240402/85908" -> 20240402/85908 | I18: =" " | J18: 0 | K18: 14690.62 | L18: 1798958.2 | M18: Contra - HDFC
A19: 12 | B19: 45384 | C19: 45384 | D19: NSE | E19: E | F19: Bg interest on MTF for 01-apr-2024-/-MTF | G19: BILLS | H19: ="20240402/269790" -> 20240402/269790 | I19: =" " | J19: 446.2 | K19: 0 | L19: 1799404.4 | M19: Interest Charged
A20: 13 | B20: 45384 | C20: 45384 | D20: NSE | E20: E | F20: M/2024063/Emargin MTM Loss Bills.-/-MTF | G20: BILLS | H20: ="20240402/305405" -> 20240402/305405 | I20: =" " | J20: 30696.45 | K20: 0 | L20: 1830100.8
A21: 14 | B21: 45384 | C21: 45384 | D21: NSE | E21: E | F21: M/2024063/Margin Pay In-/-MTF | G21: BILLS | H21: ="20240402/307831" -> 20240402/307831 | I21: =" " | J21: 601228.15 | K21: 0 | L21: 2431329
A22: 15 | B22: 45384 | C22: 45384 | D22: NSE | E22: E | F22: M/2024063/Emargin MTM Loss Reversal-/-MTF | G22: BILLS | H22: ="20240402/402125" -> 20240402/402125 | I22: =" " | J22: 0 | K22: 32159.25 | L22: 2399169.7
A23: 16 | B23: 45384 | C23: 45384 | D23: NSE | E23: E | F23: M/2024063/Margin Reversal-/-MTF | G23: BILLS | H23: ="20240402/402126" -> 20240402/402126 | I23: =" " | J23: 0 | K23: 585074.73 | L23: 1814095
A24: 17 | B24: 45384 | C24: 45385 | D24: NSE | E24: E | F24: M/2024063/02-APR-2024-/-MTF | G24: BILLS | H24: ="20240402/464157" -> 20240402/464157 | I24: ="2404000652344" -> 2404000652344 | J24: 45341.55 | K24: 0 | L24: 1859436.5
A25: 18 | B25: 45385 | C25: 45385 | D25: NSE | E25: E | F25: Online Trf for Net Payin from Bank A/c 01671000085930-/-MTF | G25: BANK RECEIPT | H25: ="20240403/36950" -> 20240403/36950 | I25: =" " | J25: 0 | K25: 421.05 | L25: 1859015.5 | M25: Contra - HDFC
A26: 19 | B26: 45385 | C26: 45385 | D26: NSE | E26: E | F26: Bg interest on MTF for 02-apr-2024-/-MTF | G26: BILLS | H26: ="20240403/109642" -> 20240403/109642 | I26: =" " | J26: 421.05 | K26: 0 | L26: 1859436.5 | M26: Interest Charged
A27: 20 | B27: 45385 | C27: 45385 | D27: NSE | E27: E | F27: M/2024064/Margin Pay In-/-MTF | G27: BILLS | H27: ="20240403/166706" -> 20240403/166706 | I27: =" " | J27: 597155.41 | K27: 0 | L27: 2456591.9
A28: 21 | B28: 45385 | C28: 45385 | D28: NSE | E28: E | F28: M/2024064/Emargin MTM Loss Bills.-/-MTF | G28: BILLS | H28: ="20240403/166707" -> 20240403/166707 | I28: =" " | J28: 28384.4 | K28: 0 | L28: 2484976.3
A29: 22 | B29: 45385 | C29: 45385 | D29: NSE | E29: E | F29: M/2024064/Emargin MTM Loss Reversal-/-MTF | G29: BILLS | H29: ="20240403/257319" -> 20240403/257319 | I29: =" " | J29: 0 | K29: 30696.45 | L29: 2454279.9
A30: 23 | B30: 45385 | C30: 45385 | D30: NSE | E30: E | F30: M/2024064/Margin Reversal-/-MTF | G30: BILLS | H30: ="20240403/257320" -> 20240403/257320 | I30: =" " | J30: 0 | K30: 601228.15 | L30: 1853051.7
A31: 24 | B31: 45385 | C31: 45386 | D31: NSE | E31: E | F31: M/2024064/03-APR-2024-/-MTF | G31: BILLS | H31: ="20240403/340295" -> 20240403/340295 | I31: ="2404001080296" -> 2404001080296 | J31: 0 | K31: 13035.58 | L31: 1840016.2
A32: 25 | B32: 45386 | C32: 45386 | D32: NSE | E32: E | F32: Online Trf for Net Payout to Bank A/c 01671000085930-/-MTF | G32: BANK PAYMENT | H32: ="20240404/12287" -> 20240404/12287 | I32: =" " | J32: 10225.46 | K32: 0 | L32: 1850241.6 | M32: Contra - HDFC
A33: 26 | B33: 45386 | C33: 45386 | D33: NSE | E33: E | F33: Online Trf for Net Payin from Bank A/c 01671000085930-/-MTF | G33: BANK RECEIPT | H33: ="20240404/37512" -> 20240404/37512 | I33: =" " | J33: 0 | K33: 437.2 | L33: 1849804.4 | M33: Contra - HDFC
A34: 27 | B34: 45386 | C34: 45386 | D34: NSE | E34: E | F34: Online Trf for Net Payin from Bank A/c 01671000085930-/-MTF | G34: BANK RECEIPT | H34: ="20240404/91644" -> 20240404/91644 | I34: =" " | J34: 0 | K34: 1425.24 | L34: 1848379.2 | M34: Contra - HDFC
A35: 28 | B35: 45386 | C35: 45386 | D35: NSE | E35: E | F35: Bg interest on MTF for 03-apr-2024-/-MTF | G35: BILLS | H35: ="20240404/139989" -> 20240404/139989 | I35: =" " | J35: 437.2 | K35: 0 | L35: 1848816.4 | M35: Interest Charged
A36: 29 | B36: 45386 | C36: 45386 | D36: NSE | E36: E | F36: M/2024065/Margin Pay In-/-MTF | G36: BILLS | H36: ="20240404/188788" -> 20240404/188788 | I36: =" " | J36: 600868 | K36: 0 | L36: 2449684.4
A37: 30 | B37: 45386 | C37: 45386 | D37: NSE | E37: E | F37: M/2024065/Emargin MTM Loss Bills.-/-MTF | G37: BILLS | H37: ="20240404/188789" -> 20240404/188789 | I37: =" " | J37: 26097.05 | K37: 0 | L37: 2475781.4
A38: 31 | B38: 45386 | C38: 45386 | D38: NSE | E38: E | F38: M/2024065/Margin Reversal-/-MTF | G38: BILLS | H38: ="20240404/279848" -> 20240404/279848 | I38: =" " | J38: 0 | K38: 597155.41 | L38: 1878626
A39: 32 | B39: 45386 | C39: 45386 | D39: NSE | E39: E | F39: M/2024065/Emargin MTM Loss Reversal-/-MTF | G39: BILLS | H39: ="20240404/279849" -> 20240404/279849 | I39: =" " | J39: 0 | K39: 28384.4 | L39: 1850241.6
A40: 33 | B40: 45386 | C40: 45387 | D40: NSE | E40: E | F40: M/2024065/04-APR-2024-/-Cash | G40: BILLS | H40: ="20240404/343542" -> 20240404/343542 | I40: ="2404001471480" -> 2404001471480 | J40: 0 | K40: 25672.95 | L40: 1824568.7
A41: 34 | B41: 45386 | C41: 45387 | D41: NSE | E41: E | F41: M/2024065/04-APR-2024-/-MTF | G41: BILLS | H41: ="20240404/343543" -> 20240404/343543 | I41: ="2404001513522" -> 2404001513522 | J41: 10621.29 | K41: 0 | L41: 1835190
A42: 35 | B42: 45387 | C42: 45387 | D42: NSE | E42: E | F42: Online Trf for Net Payout to Bank A/c 01671000085930 | G42: BANK PAYMENT | H42: ="20240405/16760" -> 20240405/16760 | I42: =" " | J42: 25672.95 | K42: 0 | L42: 1860862.9 | M42: Contra - HDFC
A43: 36 | B43: 45387 | C43: 45387 | D43: NSE | E43: E | F43: Online Trf for Net Payin from Bank A/c 01671000085930-/-MTF | G43: BANK RECEIPT | H43: ="20240405/31444" -> 20240405/31444 | I43: =" " | J43: 0 | K43: 435.69 | L43: 1860427.2 | M43: Contra - HDFC
A44: 37 | B44: 45387 | C44: 45387 | D44: NSE | E44: E | F44: Online Trf for Net Payin from Bank A/c 01671000085930-/-MTF | G44: BANK RECEIPT | H44: ="20240405/94199" -> 20240405/94199 | I44: =" " | J44: 0 | K44: 1443.03 | L44: 1858984.2 | M44: Contra - HDFC
A45: 38 | B45: 45387 | C45: 45387 | D45: NSE | E45: E | F45: Bg interest on MTF for 04-apr-2024-/-MTF | G45: BILLS | H45: ="20240405/140869" -> 20240405/140869 | I45: =" " | J45: 435.69 | K45: 0 | L45: 1859419.9 | M45: Interest Charged
A46: 39 | B46: 45387 | C46: 45387 | D46: NSE | E46: E | F46: M/2024066/Emargin MTM Loss Bills.-/-MTF | G46: BILLS | H46: ="20240405/203113" -> 20240405/203113 | I46: =" " | J46: 27633.75 | K46: 0 | L46: 1887053.6
A47: 40 | B47: 45387 | C47: 45387 | D47: NSE | E47: E | F47: M/2024066/Margin Pay In-/-MTF | G47: BILLS | H47: ="20240405/203114" -> 20240405/203114 | I47: =" " | J47: 600774.33 | K47: 0 | L47: 2487828
A48: 41 | B48: 45387 | C48: 45387 | D48: NSE | E48: E | F48: M/2024066/Margin Reversal-/-MTF | G48: BILLS | H48: ="20240405/284084" -> 20240405/284084 | I48: =" " | J48: 0 | K48: 600868 | L48: 1886960
A49: 42 | B49: 45387 | C49: 45387 | D49: NSE | E49: E | F49: M/2024066/Emargin MTM Loss Reversal-/-MTF | G49: BILLS | H49: ="20240405/284085" -> 20240405/284085 | I49: =" " | J49: 0 | K49: 26097.05 | L49: 1860862.9
A50: 43 | B50: 45387 | C50: 45390 | D50: NSE | E50: E | F50: M/2024066/05-APR-2024-/-Cash | G50: BILLS | H50: ="20240405/345083" -> 20240405/345083 | I50: ="2404001947705" -> 2404001947705 | J50: 0 | K50: 17621.38 | L50: 1843241.5
A51: 44 | B51: 45390 | C51: 45390 | D51: NSE | E51: E | F51: Online Trf for Net Payout to Bank A/c 01671000085930 | G51: BANK PAYMENT | H51: ="20240408/22723" -> 20240408/22723 | I51: =" " | J51: 17621.38 | K51: 0 | L51: 1860862.9 | M51: Contra - HDFC
A52: 45 | B52: 45390 | C52: 45390 | D52: NSE | E52: E | F52: Online Trf for Net Payin from Bank A/c 01671000085930-/-MTF | G52: BANK RECEIPT | H52: ="20240408/109932" -> 20240408/109932 | I52: =" " | J52: 0 | K52: 7512.35 | L52: 1853350.6 | M52: Contra - HDFC
A53: 46 | B53: 45390 | C53: 45390 | D53: NSE | E53: E | F53: Online Trf for Net Payin from Bank A/c 01671000085930-/-MTF | G53: BANK RECEIPT | H53: ="20240408/36179" -> 20240408/36179 | I53: =" " | J53: 0 | K53: 1316.88 | L53: 1852033.7 | M53: Contra - HDFC
A54: 47 | B54: 45390 | C54: 45390 | D54: NSE | E54: E | F54: Bg interest on MTF from 05-apr-2024 to 07-apr-2024-/-MTF | G54: BILLS | H54: ="20240408/168210" -> 20240408/168210 | I54: =" " | J54: 1316.88 | K54: 0 | L54: 1853350.6 | M54: Interest Charged
A55: 48 | B55: 45390 | C55: 45390 | D55: NSE | E55: E | F55: M/2024067/Emargin MTM Loss Bills.-/-MTF | G55: BILLS | H55: ="20240408/246445" -> 20240408/246445 | I55: =" " | J55: 29160.09 | K55: 0 | L55: 1882510.6
A56: 49 | B56: 45390 | C56: 45390 | D56: NSE | E56: E | F56: M/2024067/Margin Pay In-/-MTF | G56: BILLS | H56: ="20240408/246446" -> 20240408/246446 | I56: =" " | J56: 606760.34 | K56: 0 | L56: 2489271
A57: 50 | B57: 45390 | C57: 45390 | D57: NSE | E57: E | F57: M/2024067/Emargin MTM Loss Reversal-/-MTF | G57: BILLS | H57: ="20240408/322377" -> 20240408/322377 | I57: =" " | J57: 0 | K57: 27633.75 | L57: 2461637.2
A58: 51 | B58: 45390 | C58: 45390 | D58: NSE | E58: E | F58: M/2024067/Margin Reversal-/-MTF | G58: BILLS | H58: ="20240408/322378" -> 20240408/322378 | I58: =" " | J58: 0 | K58: 600774.33 | L58: 1860862.9
A59: 52 | B59: 45391 | C59: 45391 | D59: NSE | E59: E | F59: Online Trf for Net Payin from Bank A/c 01671000085930-/-MTF | G59: BANK RECEIPT | H59: ="20240409/70483" -> 20240409/70483 | I59: =" " | J59: 0 | K59: 6794.95 | L59: 1854068 | M59: Contra - HDFC
A60: 53 | B60: 45391 | C60: 45391 | D60: NSE | E60: E | F60: M/2024068/Emargin MTM Loss Reversal-/-MTF | G60: BILLS | H60: ="20240409/124125" -> 20240409/124125 | I60: =" " | J60: 0 | K60: 29160.09 | L60: 1824907.9
A61: 54 | B61: 45391 | C61: 45391 | D61: NSE | E61: E | F61: M/2024068/Margin Reversal-/-MTF | G61: BILLS | H61: ="20240409/124126" -> 20240409/124126 | I61: =" " | J61: 0 | K61: 606760.34 | L61: 1218147.5
A62: 55 | B62: 45391 | C62: 45391 | D62: NSE | E62: E | F62: Bg interest on MTF for 08-apr-2024-/-MTF | G62: BILLS | H62: ="20240409/37094" -> 20240409/37094 | I62: =" " | J62: 436.28 | K62: 0 | L62: 1218583.8 | M62: Interest Charged
A63: 56 | B63: 45391 | C63: 45391 | D63: NSE | E63: E | F63: M/2024068/Emargin MTM Loss Bills.-/-MTF | G63: BILLS | H63: ="20240409/65998" -> 20240409/65998 | I63: =" " | J63: 31484.95 | K63: 0 | L63: 1250068.8
A64: 57 | B64: 45391 | C64: 45391 | D64: NSE | E64: E | F64: M/2024068/Margin Pay In-/-MTF | G64: BILLS | H64: ="20240409/65999" -> 20240409/65999 | I64: =" " | J64: 610794.15 | K64: 0 | L64: 1860862.9
A65: 58 | B65: 45391 | C65: 45392 | D65: NSE | E65: E | F65: M/2024068/09-APR-2024-/-MTF | G65: BILLS | H65: ="20240409/230125" -> 20240409/230125 | I65: ="2404002756391" -> 2404002756391 | J65: 17494.02 | K65: 0 | L65: 1878356.9
A66: 59 | B66: 45392 | C66: 45392 | D66: NSE | E66: E | F66: Online Trf for Net Payin from Bank A/c 01671000085930-/-MTF | G66: BANK RECEIPT | H66: ="20240410/29172" -> 20240410/29172 | I66: =" " | J66: 0 | K66: 434.02 | L66: 1877922.9 | M66: Contra - HDFC
A67: 60 | B67: 45392 | C67: 45392 | D67: NSE | E67: E | F67: Online Trf for Net Payin from Bank A/c 01671000085930-/-MTF | G67: BANK RECEIPT | H67: ="20240410/82912" -> 20240410/82912 | I67: =" " | J67: 0 | K67: 2033.3 | L67: 1875889.6 | M67: Contra - HDFC
A68: 61 | B68: 45392 | C68: 45392 | D68: NSE | E68: E | F68: Bg interest on MTF for 09-apr-2024-/-MTF | G68: BILLS | H68: ="20240410/261570" -> 20240410/261570 | I68: =" " | J68: 434.02 | K68: 0 | L68: 1876323.6 | M68: Interest Charged
A69: 62 | B69: 45392 | C69: 45392 | D69: NSE | E69: E | F69: M/2024069/Emargin MTM Loss Bills.-/-MTF | G69: BILLS | H69: ="20240410/286070" -> 20240410/286070 | I69: =" " | J69: 27116.9 | K69: 0 | L69: 1903440.5
A70: 63 | B70: 45392 | C70: 45392 | D70: NSE | E70: E | F70: M/2024069/Margin Pay In-/-MTF | G70: BILLS | H70: ="20240410/286071" -> 20240410/286071 | I70: =" " | J70: 582617.78 | K70: 0 | L70: 2486058.3
A71: 64 | B71: 45392 | C71: 45392 | D71: NSE | E71: E | F71: M/2024069/Emargin MTM Loss Reversal-/-MTF | G71: BILLS | H71: ="20240410/369925" -> 20240410/369925 | I71: =" " | J71: 0 | K71: 31484.95 | L71: 2454573.4
A72: 65 | B72: 45392 | C72: 45392 | D72: NSE | E72: E | F72: M/2024069/Margin Reversal-/-MTF | G72: BILLS | H72: ="20240410/369926" -> 20240410/369926 | I72: =" " | J72: 0 | K72: 610794.15 | L72: 1843779.2
A73: 66 | B73: 45392 | C73: 45394 | D73: NSE | E73: E | F73: M/2024069/10-APR-2024-/-Cash | G73: BILLS | H73: ="20240410/457646" -> 20240410/457646 | I73: ="2404003299659" -> 2404003299659 | J73: 0 | K73: 22935.47 | L73: 1820843.7
A74: 67 | B74: 45392 | C74: 45394 | D74: NSE | E74: E | F74: M/2024069/10-APR-2024-/-MTF | G74: BILLS | H74: ="20240410/457647" -> 20240410/457647 | I74: ="2404003299659" -> 2404003299659 | J74: 0 | K74: 45434.18 | L74: 1775409.6
A75: 68 | B75: 45394 | C75: 45394 | D75: BSE | E75: E | F75: Online Trf for Net Payin from Bank A/c 01671000085930 | G75: BANK RECEIPT | H75: ="20240412/123068" -> 20240412/123068 | I75: =" " | J75: 0 | K75: 42.91 | L75: 1775366.6 | M75: Contra - HDFC
A76: 69 | B76: 45394 | C76: 45394 | D76: NSE | E76: E | F76: Online Trf for Net Payout to Bank A/c 01671000085930-/-MTF | G76: BANK PAYMENT | H76: ="20240412/18840" -> 20240412/18840 | I76: =" " | J76: 6052.98 | K76: 0 | L76: 1781419.6 | M76: Contra - HDFC
A77: 70 | B77: 45394 | C77: 45394 | D77: NSE | E77: E | F77: Online Trf for Net Payout to Bank A/c 01671000085930 | G77: BANK PAYMENT | H77: ="20240412/20153" -> 20240412/20153 | I77: =" " | J77: 22935.47 | K77: 0 | L77: 1804355.1 | M77: Contra - HDFC
A78: 71 | B78: 45394 | C78: 45394 | D78: NSE | E78: E | F78: Online Trf for Net Payin from Bank A/c 01671000085930-/-MTF | G78: BANK RECEIPT | H78: ="20240412/30991" -> 20240412/30991 | I78: =" " | J78: 0 | K78: 879.04 | L78: 1803476.1 | M78: Contra - HDFC
A79: 72 | B79: 45394 | C79: 45394 | D79: NSE | E79: E | F79: Online Trf for Net Payin from Bank A/c 01671000085930-/-MTF | G79: BANK RECEIPT | H79: ="20240412/95277" -> 20240412/95277 | I79: =" " | J79: 0 | K79: 23319.29 | L79: 1780156.8 | M79: Contra - HDFC
A80: 73 | B80: 45394 | C80: 45394 | D80: NSE | E80: E | F80: Bg interest on MTF from 10-apr-2024 to 11-apr-2024-/-MTF | G80: BILLS | H80: ="20240412/145159" -> 20240412/145159 | I80: =" " | J80: 879.04 | K80: 0 | L80: 1781035.8 | M80: Interest Charged
A81: 74 | B81: 45394 | C81: 45394 | D81: NSE | E81: E | F81: M/2024070/Emargin MTM Loss Bills.-/-MTF | G81: BILLS | H81: ="20240412/196999" -> 20240412/196999 | I81: =" " | J81: 28117.95 | K81: 0 | L81: 1809153.8
A82: 75 | B82: 45394 | C82: 45394 | D82: NSE | E82: E | F82: M/2024070/Margin Pay In-/-MTF | G82: BILLS | H82: ="20240412/199420" -> 20240412/199420 | I82: =" " | J82: 574205.17 | K82: 0 | L82: 2383358.9
A83: 76 | B83: 45394 | C83: 45394 | D83: NSE | E83: E | F83: M/2024070/Emargin MTM Loss Reversal-/-MTF | G83: BILLS | H83: ="20240412/281335" -> 20240412/281335 | I83: =" " | J83: 0 | K83: 27116.9 | L83: 2356242
A84: 77 | B84: 45394 | C84: 45394 | D84: NSE | E84: E | F84: M/2024070/Margin Reversal-/-MTF | G84: BILLS | H84: ="20240412/281336" -> 20240412/281336 | I84: =" " | J84: 0 | K84: 582617.78 | L84: 1773624.2
A85: 78 | B85: 45394 | C85: 45397 | D85: BSE | E85: E | F85: OFB/2024035/12-APR-2024-/-Cash | G85: BILLS | H85: ="20240412/291340" -> 20240412/291340 | I85: ="2404003811545" -> 2404003811545 | J85: 42.91 | K85: 0 | L85: 1773667.2
A86: 79 | B86: 45397 | C86: 45397 | D86: NSE | E86: E | F86: Online Trf for Net Payin from Bank A/c 01671000085930-/-MTF | G86: BANK RECEIPT | H86: ="20240415/35265" -> 20240415/35265 | I86: =" " | J86: 0 | K86: 1251.57 | L86: 1772415.6 | M86: Contra - HDFC
A87: 80 | B87: 45397 | C87: 45397 | D87: NSE | E87: E | F87: Bg interest on MTF from 12-apr-2024 to 14-apr-2024-/-MTF | G87: BILLS | H87: ="20240415/144912" -> 20240415/144912 | I87: =" " | J87: 1251.57 | K87: 0 | L87: 1773667.2 | M87: Interest Charged
A88: 81 | B88: 45397 | C88: 45397 | D88: NSE | E88: E | F88: M/2024071/Emargin MTM Loss Bills.-/-MTF | G88: BILLS | H88: ="20240415/177876" -> 20240415/177876 | I88: =" " | J88: 38346.79 | K88: 0 | L88: 1812013.9
A89: 82 | B89: 45397 | C89: 45397 | D89: NSE | E89: E | F89: M/2024071/Margin Pay In-/-MTF | G89: BILLS | H89: ="20240415/177877" -> 20240415/177877 | I89: =" " | J89: 548441.83 | K89: 0 | L89: 2360455.8
A90: 83 | B90: 45397 | C90: 45397 | D90: NSE | E90: E | F90: M/2024071/Emargin MTM Loss Reversal-/-MTF | G90: BILLS | H90: ="20240415/280982" -> 20240415/280982 | I90: =" " | J90: 0 | K90: 28117.95 | L90: 2332337.8
A91: 84 | B91: 45397 | C91: 45397 | D91: NSE | E91: E | F91: M/2024071/Margin Reversal-/-MTF | G91: BILLS | H91: ="20240415/280983" -> 20240415/280983 | I91: =" " | J91: 0 | K91: 574205.17 | L91: 1758132.7
A92: 85 | B92: 45397 | C92: 45398 | D92: NSE | E92: E | F92: M/2024071/15-APR-2024-/-Cash | G92: BILLS | H92: ="20240415/356603" -> 20240415/356603 | I92: ="2404004191510" -> 2404004191510 | J92: 0 | K92: 29908.32 | L92: 1728224.3
A93: 86 | B93: 45397 | C93: 45398 | D93: NSE | E93: E | F93: M/2024071/15-APR-2024-/-MTF | G93: BILLS | H93: ="20240415/356604" -> 20240415/356604 | I93: ="2404004191510" -> 2404004191510 | J93: 0 | K93: 55832.86 | L93: 1672391.5
A94: 87 | B94: 45398 | C94: 45398 | D94: NSE | E94: E | F94: Online Trf for Net Payout to Bank A/c 01671000085930 | G94: BANK PAYMENT | H94: ="20240416/36693" -> 20240416/36693 | I94: =" " | J94: 29908.32 | K94: 0 | L94: 1702299.8 | M94: Contra - HDFC
A95: 88 | B95: 45398 | C95: 45398 | D95: NSE | E95: E | F95: Online Trf for Net Payout to Bank A/c 01671000085930-/-MTF | G95: BANK PAYMENT | H95: ="20240416/6962" -> 20240416/6962 | I95: =" " | J95: 16741.9 | K95: 0 | L95: 1719041.7 | M95: Contra - HDFC
A96: 89 | B96: 45398 | C96: 45398 | D96: NSE | E96: E | F96: Online Trf for Net Payin from Bank A/c 01671000085930-/-MTF | G96: BANK RECEIPT | H96: ="20240416/33682" -> 20240416/33682 | I96: =" " | J96: 0 | K96: 417.19 | L96: 1718624.5 | M96: Contra - HDFC
A97: 90 | B97: 45398 | C97: 45398 | D97: NSE | E97: E | F97: Online Trf for Net Payin from Bank A/c 01671000085930-/-MTF | G97: BANK RECEIPT | H97: ="20240416/89931" -> 20240416/89931 | I97: =" " | J97: 0 | K97: 20617.33 | L97: 1698007.2 | M97: Contra - HDFC
A98: 91 | B98: 45398 | C98: 45398 | D98: NSE | E98: E | F98: Bg interest on MTF for 15-apr-2024-/-MTF | G98: BILLS | H98: ="20240416/114143" -> 20240416/114143 | I98: =" " | J98: 417.19 | K98: 0 | L98: 1698424.4 | M98: Interest Charged
A99: 92 | B99: 45398 | C99: 45398 | D99: NSE | E99: E | F99: M/2024072/Margin Pay In-/-MTF | G99: BILLS | H99: ="20240416/207364" -> 20240416/207364 | I99: =" " | J99: 562328.23 | K99: 0 | L99: 2260752.6
A100: 93 | B100: 45398 | C100: 45398 | D100: NSE | E100: E | F100: M/2024072/Emargin MTM Loss Bills.-/-MTF | G100: BILLS | H100: ="20240416/207365" -> 20240416/207365 | I100: =" " | J100: 45077.72 | K100: 0 | L100: 2305830.3
A101: 94 | B101: 45398 | C101: 45398 | D101: NSE | E101: E | F101: M/2024072/Emargin MTM Loss Reversal-/-MTF | G101: BILLS | H101: ="20240416/242893" -> 20240416/242893 | I101: =" " | J101: 0 | K101: 38346.79 | L101: 2267483.5
A102: 95 | B102: 45398 | C102: 45398 | D102: NSE | E102: E | F102: M/2024072/Margin Reversal-/-MTF | G102: BILLS | H102: ="20240416/242894" -> 20240416/242894 | I102: =" " | J102: 0 | K102: 548441.83 | L102: 1719041.7
...

Sheet BSPL
C2: Ajay Kumar Gupta
C3: Balance Sheet As on 31.03.2025
C4: Assets | D4: Amount Rs. | E4: Liabilities | F4: Amount Rs.
C5: Bank | D5: ='HDFC Bank Statement'!F867 -> 17092.59 | E5: Capital Account | F5: =D9-SUM(F6:F8) -> 2128751
C6: HDFC Security (Debtor) | D6: ='HDFC HSL Ledger'!L2235 -> 2091658.4
C7: Cash | D7: =F24 -> 20000
C9: Total | D9: =SUM(D5:D8) -> 2128751 | E9: Total | F9: =SUM(F5:F8) -> 2128751
C11: Ajay Kumar Gupta
C12: P&L For the year ended 31.03.2025
C13: Particulars | D13: Amount Rs. | E13: Particulars | F13: Amount Rs.
C14: Purchases | D14: =CG!K6 -> 6655.1575 | E14: Sales | F14: =CG!K5 -> 3327.58
E15: By Gross Loss | F15: =D14-F14 -> 3327.5775
C17: Total | D17: =SUM(D14:D16) -> 6655.1575 | E17: Total | F17: =SUM(F14:F16) -> 6655.1575
C19: Ajay Kumar Gupta
C20: Cash Account For the FY 2024-25
C21: Particulars | D21: Amount Rs. | E21: Particulars | F21: Amount Rs.
C22: To Opening Balance | D22: 60000 | E22: By Cash Withdrawal | F22: =SUMIFS('HDFC Bank Statement'!$D:$D,'HDFC Bank Statement'!$G:$G,I24) -> 240000 | I22: Cash Deposit
C23: To Household Expenses | D23: 180000
C24: To Cash Deposit | D24: =SUMIFS('HDFC Bank Statement'!$E:$E,'HDFC Bank Statement'!$G:$G,I22) -> 20000 | E24: To Closing Balance | F24: =D26-F22 -> 20000 | I24: ATM Withdrawal
C26: Total | D26: =SUM(D22:D25) -> 260000 | E26: Total | F26: =SUM(F22:F25) -> 260000

Sheet HDFC Bank Statement
D2: =D3-D4 -> 1.7241918e+08 | E2: =E3-E4 -> 1.7289341e+08
A3: Ajay Kumar Gupta | D3: ='HDFC HSL Ledger'!K6 -> 1.7265918e+08 | E3: ='HDFC HSL Ledger'!J6 -> 1.7291341e+08
A4: Account of Statements from 01-04-2024 to 31-03-2025 | D4: =SUBTOTAL(9,D6:D1446) -> 240000 | E4: =SUBTOTAL(9,E6:E1446) -> 20000 | F4: 205 | G4: =E4-F4 -> 19795
A5: TX Date | B5: Particulars | C5: Ref | D5: DR | E5: CR | F5: Balance | G5: Kya hai?
A6: 45383 | B6: NET PI TO HSL SEC A/C 347707-00602340029392 | C6: 0000000508947795 | D6: 1812.32 | E6: 0 | F6: 36117.29 | G6: Contra - HSL
A7: 45384 | B7: NET PI TO HSL SEC A/C 347707-00602340029392 | C7: 0000000509074379 | D7: 19318.18 | E7: 0 | F7: 16799.11 | G7: Contra - HSL
A8: 45384 | B8: NET PO FROM HSL A/C 347707-50200085415108 | C8: 0000000509179804 | D8: 0 | E8: 5099.51 | F8: 21898.62 | G8: Contra - HSL
A9: 45384 | B9: NET PO FROM HSL A/C 347707-50200085415108 | C9: 0000000509225366 | D9: 0 | E9: 20780.76 | F9: 42679.38 | G9: Contra - HSL
A10: 45384 | B10: NET PI TO HSL SEC A/C 347707-00602340029392 | C10: 0000000509405924 | D10: 446.2 | E10: 0 | F10: 42233.18 | G10: Contra - HSL
A11: 45384 | B11: NET PI TO HSL SEC A/C 347707-00602340029392 | C11: 0000000509532842 | D11: 14690.62 | E11: 0 | F11: 27542.56 | G11: Contra - HSL
A12: 45385 | B12: NET PI TO HSL SEC A/C 347707-00602340029392 | C12: 0000000509799278 | D12: 421.05 | E12: 0 | F12: 27121.51 | G12: Contra - HSL
A13: 45386 | B13: NET PO FROM HSL A/C 347707-50200085415108 | C13: 0000000510051241 | D13: 0 | E13: 10225.46 | F13: 37346.97 | G13: Contra - HSL
A14: 45386 | B14: NET PI TO HSL SEC A/C 347707-00602340029392 | C14: 0000000510203032 | D14: 437.2 | E14: 0 | F14: 36909.77 | G14: Contra - HSL
A15: 45386 | B15: NET PI TO HSL SEC A/C 347707-00602340029392 | C15: 0000000510341877 | D15: 1425.24 | E15: 0 | F15: 35484.53 | G15: Contra - HSL
A16: 45387 | B16: NET PO FROM HSL A/C 347707-50200085415108 | C16: 0000000510485360 | D16: 0 | E16: 25672.95 | F16: 61157.48 | G16: Contra - HSL
A17: 45387 | B17: NET PI TO HSL SEC A/C 347707-00602340029392 | C17: 0000000510621583 | D17: 435.69 | E17: 0 | F17: 60721.79 | G17: Contra - HSL
... A867: 45747 | B867: INTEREST PAID TILL 31-MAR-2025 | C867: 000000000000000 | D867: 0 | E867: 2742 | F867: 17092.59 | G867: Bank Interest
