Workbook

Sheet AXIS Aayush Axis Statement 1
A1: Name :- AAYUSH KUMAR GUPTA
A2: Joint Holder :- -
A3: AJAY KUMAR GUPTA
A4: FLAT NO - D-07 ISHWAR PARADISE
A5: NASHIK-422011
A6: MAHARASHTRA-INDIA
A7: Currency :- INR
A8: Customer ID :- 857324165
A9: IFSC Code :- UTIB0002656
A10: MICR Code :- 422211010
A11: Nominee Registered :- Y
A12: Registered Mobile No :- XXXXXX5259
... A17: Statement of Account No - 915010020334307 for the period (From : 01-04-2023 To : 31-03-2024)
F18: =F20-E20 -> 25508.68
A19: Tran Date | B19: CHQNO | C19: PARTICULARS | D19: DR | E19: CR | F19: BAL | G19: SOL
A20: 45018 | B20: - | C20: NEFT/N091232397833081/AAYUSH KU/HDFC BANK/Transfe | D20: 0 | E20: 50000 | F20: 75508.68 | G20: 248
A21: 45061 | B21: - | C21: Dr Card Charges ISSUE 4616XXXXXXXX8177 | D21: 590 | E21: 0 | F21: 74918.68 | G21: 2656 | I21: =F20-D21+E21-F21 -> 0
A22: 45061 | B22: - | C22: NBSM/12858585/IRCTC(RAZORPAY)/ | D22: 134.85 | E22: 0 | F22: 74783.83 | G22: 2656 | I22: =F21-D22+E22-F22 -> 0
A23: 45071 | B23: - | C23: ICONN REF/12858585/RAZORPAY/DT.25-05-2023 | D23: 0 | E23: 45.28 | F23: 74829.11 | G23: 100 | I23: =F22-D23+E23-F23 -> 0
A24: 45082 | B24: - | C24: INB/NEFT/AXIR231562638106/Aayush K/HDFC BA/Borrow | D24: 20000 | E24: 0 | F24: 54829.11 | G24: 2656 | I24: =F23-D24+E24-F24 -> 0
A25: 45082 | B25: - | C25: INB/IFT/Ajay Kumar Gupta/TPARTY TRANSFER | D25: 20000 | E25: 0 | F25: 34829.11 | G25: 2656 | I25: =F24-D25+E25-F25 -> 0
A26: 45086 | B26: - | C26: INB/IFT/AJAY KUMAR GUPTA/TPARTY TRANSFER | D26: 0 | E26: 20000 | F26: 54829.11 | G26: 115 | I26: =F25-D26+E26-F26 -> 0
A27: 45091 | B27: - | C27: ECOM PUR/MAKEMYTRIP IN/01126521471/140623/09:39 | D27: 6434 | E27: 0 | F27: 48395.11 | G27: 2656 | I27: =F26-D27+E27-F27 -> 0
A28: 45108 | B28: - | C28: 915010020334307:Int.Pd:01-04-2023 to 30-06-2023 | D28: 0 | E28: 504 | F28: 48899.11 | G28: 2656 | I28: =F27-D28+E28-F28 -> 0
A29: 45130 | B29: - | C29: GST @18% on Charge | D29: 0.54 | E29: 0 | F29: 48898.57 | G29: 2656 | I29: =F28-D29+E29-F29 -> 0
A30: 45130 | B30: - | C30: Consolidated Charges for A/c | D30: 3 | E30: 0 | F30: 48895.57 | G30: 2656 | I30: =F29-D30+E30-F30 -> 0
A31: 45144 | B31: - | C31: UPI/P2M/321834491026/BharatPe /YesBank_Y/Pay to | D31: 136 | E31: 0 | F31: 48759.57 | G31: 2656 | I31: =F30-D31+E31-F31 -> 0
A32: 45144 | B32: - | C32: UPI/P2M/321834593338/ATUL GARG/Paytm Pay/UPI | D32: 2285 | E32: 0 | F32: 46474.57 | G32: 2656 | I32: =F31-D32+E32-F32 -> 0
... A44: 45382 | B44: - | C44: SB:915010020334307:Int.Pd:01-01-2024 to 31-03-2024 | D44: 0 | E44: 125 | F44: 16847.21 | G44: 2656 | I44: =F43-D44+E44-F44 -> 0
A46: Charge breakup of Axis Account No :915010020334307 for the period (From : 01-04-2023 To : 31-03-2024)
A48: Period | B48: Recover Date | C48: Charge Type | D48: Total(RS). | E48: Charges(RS).
A49: 45078 | B49: 45130 | C49: SMS Alert Fee | D49: 3 | E49: 3
A50: 45170 | B50: 45221 | C50: SMS Alert Fee | D50: 1 | E50: 1
A51: 45261 | B51: 45312 | C51: SMS Alert Fee | D51: 1 | E51: 1
A53: 1. The 'charges' in the above statement indicate the net chargeable amount for the month. However the actual charge debited to the account might have elements of past unrecoverd charge also.
A54: 2. The chargeable amount is exclusive of Goods and Serivce Tax.
A56: Unless the constituent notifies the bank immediately of any discrepancy found by him/her in this statement of Account, it will be taken that he/she has found the account correct.
A58: The closing balance as shown/displayed includes not only the credit balance and / or overdraft limit, but also funds which are under clearing.
A59: It excludes the amount marked as lien, if any. Hence the closing balance displayed may not be the effective available balance. For any further clarifications, please contact the Branch.
A61: We would like to reiterate that, as a policy, Axis Bank does not ask you to part with/disclose/revalidate of your iConnect passord,login id and debit card number through emails OR phone call
A62: Further, we would like to reiterate that Axis Bank shall not be liable for any losses arising from you sharing/disclosing of your login id, password and debit card number to anyone. Please co-operate by forwarding all such suspicious/spam emails, if received by you, to customer.service@axisbank.com
A64: With effect from 1st August 2016, the replacement charges for Debit card and ATM card applicable on Current accounts have been revised. To know more about the applicable charges,please visit www.axisbank.com
A66: Deposit Insurance and Credit Guarantee Corporation (DICGC) insurance cover is applicable in all Bank's deposits, such as savings, current, fixed, recurring etc.* up to maximum amount of Rs 5 Lakh including principal &interest both* (*for exceptions and details please refer http://www.dicgc.org.in/ )
A68: In compliance with regulatory guidelines, the non-CTS cheque books attached to the accounts would be destroyed in banks core banking System. Thus, Non CTS cheques will not be valid for CASH, Clearing and Transfer transactions
A70: REGISTERED OFFICE - AXIS BANK LTD,TRISHUL,Opp. Samartheswar Temple, Near Law Garden, Ellisbridge, Ahmedabad . 380006.
A72: BRANCH ADDRESS - AXIS BANK LTD, BODHALE NAGAR NAS MH, GROUND FLOOR, SHOP NO 8, SUYOJIT ARCADE,NASHIK, PUNE ROAD, BODHALE NAGAR, 422011, NASHIK, MAHARASHTRA, INDIA, TEL:0253-2414245 FAX:_x000D_ This is a system generated output and requires no signature."
A74: Legend :
A75: ICONN | B75: Transaction trough Internet Banking
A76: VMT-ICON | B76: Visa Money Transfer through Internet Banking
A77: AUTOSWEEP | B77: Transfer to linked fixed deposit
A78: REV SWEEP | B78: Interest on Linked fixed Deposit
A79: SWEEP TRF | B79: Transfer from Linked Fixed Deposit / Account
A80: VMT | B80: Visa Money Transfer through ATM
A81: CWDR | B81: Cash Withdrawal through ATM
A82: PUR | B82: POS purchase
A83: TIP/ SCG | B83: Surcharge on usage of debit card at pumps/railway ticket purchase or hotel tips
A84: RATE.DIFF | B84: Difference in rates on usage of card internationally
A85: CLG | B85: Cheque Clearing Transaction
A86: EDC | B86: Credit transaction through EDC Machine
... A89: Int.Coll | B89: Interest collected from the customer

Sheet HDFC
A1: HDFC BANK Ltd. Page No .: 1 Statement of accounts
E5: Account Branch :NASHIK ROAD
A6: MR. AAYUSH KUMAR GUPTA | E6: Address :SHOP NO 3,
A7: FLAT NO-D-07 ISHWAR PARADISE | E7: MITHILA APARTMENTS,
A8: ASHOKA MARG BEHIND FAME | E8: BYTCO POINT,NASHIK ROAD
A9: THEATRE ASHOKA MARG,NASHIK | E9: City :NASHIK
A10: NASHIK 422011 | E10: State :MAHARASHTRA
E11: Phone no. :18002026161
E12: Email :
A13: JOINT HOLDERS : | E13: OD Limit :0 Currency :INR
E14: Cust ID :65298402
A15: Nomination : Registered | E15: Account No :50100128155413 VRM POTENTIAL
A16: Statement From : 01/04/2023 To : 31/03/2024 | E16: A/C Open Date :08/10/2015
E17: Account Status :Regular
E18: RTGS/NEFT IFSC :HDFC0000456 MICR :422240003
A20: ********************************************************************************************************************************************************************************************
A21: Date | B21: Narration | C21: Chq./Ref.No. | D21: Value Dt | E21: Withdrawal Amt. | F21: Deposit Amt. | G21: Closing Balance
A22: 45017 | B22: NEFT DR-UTIB0002656-AAYUSH KUMAR GUPTA-NETBANK, MUM-N091232397833081-TRANSFER FROM HDFC | C22: N091232397833081 | D22: 45017 | E22: 50000 | F22: 0 | G22: 33618.17
A23: 45019 | B23: NEFT CR-UTIB0000115-JINDAL SAW LIMITED-AAYUSH KUMAR GUPTA-AXISCN0231261220 | C23: AXISCN0231261220 | D23: 45019 | E23: 0 | F23: 57999 | G23: 91617.17 | I23: =G22-E23+F23-G23 -> 0
A24: 45019 | B24: NET PI TO HSL SEC A/C 2554606-00602340029427 | C24: 0000000399867464 | D24: 45019 | E24: 387.51 | F24: 0 | G24: 91229.66 | I24: =G23-E24+F24-G24 -> 0
A25: 45019 | B25: NET PO FROM HSL A/C 2554606-00602340029427 | C25: 0000000399979610 | D25: 45019 | E25: 0 | F25: 4287.59 | G25: 95517.25 | I25: =G24-E25+F25-G25 -> 0
A26: 45021 | B26: NET PI TO HSL SEC A/C 2554606-00602340029427 | C26: 0000000400386064 | D26: 45021 | E26: 21810.69 | F26: 0 | G26: 73706.56 | I26: =G25-E26+F26-G26 -> 0
A27: 45022 | B27: NET PI TO HSL SEC A/C 2554606-00602340029427 | C27: 0000000400620092 | D27: 45022 | E27: 115.7 | F27: 0 | G27: 73590.86 | I27: =G26-E27+F27-G27 -> 0
A28: 45022 | B28: NET PO FROM HSL A/C 2554606-00602340029427 | C28: 0000000400730659 | D28: 45022 | E28: 0 | F28: 1699.23 | G28: 75290.09 | I28: =G27-E28+F28-G28 -> 0
A29: 45023 | B29: 00602300000434-021333684 | C29: 0000304077582285 | D29: 45023 | E29: 0 | F29: 1880 | G29: 77170.09 | I29: =G28-E29+F29-G29 -> 0
A30: 45026 | B30: NET PI TO HSL SEC A/C 2554606-00602340029427 | C30: 0000000401078570 | D30: 45026 | E30: 466.16 | F30: 0 | G30: 76703.93 | I30: =G29-E30+F30-G30 -> 0
A31: 45026 | B31: NET PO FROM HSL A/C 2554606-00602340029427 | C31: 0000000401189359 | D31: 45026 | E31: 0 | F31: 662.12 | G31: 77366.05 | I31: =G30-E31+F31-G31 -> 0
A32: 45027 | B32: NET PI TO HSL SEC A/C 2554606-00602340029427 | C32: 0000000401415591 | D32: 45027 | E32: 116.86 | F32: 0 | G32: 77249.19 | I32: =G31-E32+F32-G32 -> 0
A33: 45027 | B33: NET PO FROM HSL A/C 2554606-00602340029427 | C33: 0000000401522488 | D33: 45027 | E33: 0 | F33: 334.27 | G33: 77583.46 | I33: =G32-E33+F33-G33 -> 0
A34: 45028 | B34: NET PI TO HSL SEC A/C 2554606-00602340029427 | C34: 0000000401746881 | D34: 45028 | E34: 117.03 | F34: 0 | G34: 77466.43 | I34: =G33-E34+F34-G34 -> 0
... A807: 45383 | B807: CREDIT INTEREST CAPITALISED | C807: 000000000000000 | D807: 45382 | E807: 0 | F807: 394 | G807: 43050.89 | I807: =G806-E807+F807-G807 -> 0
A810: STATEMENT SUMMARY :-
A811: Opening Balance | E811: Debits | F811: Credits | G811: Closing Bal
A812: 83618.17 | E812: 4097807.4 | F812: 4057240.1 | G812: 43050.89
E814: Dr Count | F814: Cr Count
E815: 510 | F815: 276

Sheet Jupiter
A1: Name: | B1: AAYUSH KUMAR GUPTA | E1: Branch Name: | F1: Fintech Partnerships (Jupiter)
A2: Communication Address: | B2: D-07, Ishwar Paradise Ashoka Marg Nashik, Behind Fame Theatre, Nashik, Maharashtra, 422006 | E2: Branch Address: | F2: Federal Bank Ltd, Fintech Partnerships Department Integrated Startup Complex, KSUM, HMT Colony, Kalamassery, Ernakulam Kerala 683503
A3: Address Last Update On: | B3: 28/10/2021 | E3: Brach Sol Id: | F3: 7777
A4: Regd. Mobile Number: | B4: 919594435259 | E4: Account Number: | F4: 77770101840847
A5: Email ID: | B5: aayushp4396@gmail.com | E5: Customer ID: | F5: 135342130
A6: Scheme: | B6: SALARY-7777 | E6: Account Open Date: | F6: 28/10/2021
A7: Type Of Account: | B7: Savings | E7: Account Status: | F7: Active
A8: IFSC: | B8: FDRL0007777 | E8: Mode Of Operation: | F8: Single
A9: MICR Code: | B9: 682049069 | E9: Joint Holders: | F9: NIL
A10: SWIFT Code: | B10: FDRLINBBIBD | E10: Nomination: | F10: Registered
A11: Effective Available Balance: | B11: 1950.19 | E11: Date of Issue: | F11: 22/04/2024
A12: Currency: | B12: INR
A14: Statement of Account for the period of 01-APR-2023 to 31-MAR-2024
A16: Date | B16: Value Date | C16: Particulars | D16: Tran Type | E16: Cheque Details | F16: Withdrawals | G16: Deposits | H16: Balance | I16: Dr/Cr
C17: Opening Balance | H17: 29.86
A18: 45024 | B18: 45024 | C18: UPIOUT/309826882296/Q143041833@ybl/Sent via /5311 | D18: TFR | F18: 10 | G18: 0 | H18: 19.86 | I18: Dr | J18: =H17-F18+G18-H18 -> 0
A19: 45038 | B19: 45038 | C19: UPIOUT/311268164406/paytm-61240897@paytm/S en/5411 | D19: TFR | F19: 9 | G19: 0 | H19: 10.86 | I19: Dr | J19: =H18-F19+G19-H19 -> 0
A20: 45099 | B20: 45099 | C20: UPI IN/317381933693/9594435259@jupiteraxis /A/0000 | D20: TFR | F20: 0 | G20: 190 | H20: 200.86 | I20: Cr | J20: =H19-F20+G20-H20 -> 0
A21: 45099 | B21: 45099 | C21: UPIOUT/317381938077/playstore@axisbank/Man da/5817 | D21: TFR | F21: 199 | G21: 0 | H21: 1.86 | I21: Dr | J21: =H20-F21+G21-H21 -> 1.3544721e-14
A22: 45130 | B22: 45130 | C22: UPI IN/320471883328/9594435259@jupiteraxis /A/0000 | D22: TFR | F22: 0 | G22: 199 | H22: 200.86 | I22: Cr | J22: =H21-F22+G22-H22 -> 0
A23: 45138 | B23: 45138 | C23: UPI IN/321287516546/9594435259@jupiteraxis /A/0000 | D23: TFR | F23: 0 | G23: 1000 | H23: 1200.86 | I23: Cr | J23: =H22-F23+G23-H23 -> 0
A24: 45138 | B24: 45138 | C24: UPIOUT/321287534320/paytm-69746593@paytm/S en/5813 | D24: TFR | F24: 400 | G24: 0 | H24: 800.86 | I24: Dr | J24: =H23-F24+G24-H24 -> 0
A25: 45138 | B25: 45138 | C25: UPIOUT/321289065233/paytm-69746593@paytm/S en/5813 | D25: TFR | F25: 200 | G25: 0 | H25: 600.86 | I25: Dr | J25: =H24-F25+G25-H25 -> 0
A26: 45138 | B26: 45138 | C26: UPIOUT/321290570632/0008288006214@ibl/Sent v/0000 | D26: TFR | F26: 600 | G26: 0 | H26: 0.86 | I26: Dr | J26: =H25-F26+G26-H26 -> 1.3655743e-14
A27: 45185 | B27: 45185 | C27: UPI IN/325983918366/9594435259@jupiteraxis /A/0000 | D27: TFR | F27: 0 | G27: 100 | H27: 100.86 | I27: Cr | J27: =H26-F27+G27-H27 -> 0
A28: 45185 | B28: 45185 | C28: UPIOUT/325983946204/aayush20gupta@oksbi/Se nt/0000 | D28: TFR | F28: 50 | G28: 0 | H28: 50.86 | I28: Dr | J28: =H27-F28+G28-H28 -> 0
A29: 45185 | B29: 45185 | C29: UPIOUT/325983968688/aayush20gupta@oksbi/Se nt/0000 | D29: TFR | F29: 50 | G29: 0 | H29: 0.86 | I29: Dr | J29: =H28-F29+G29-H29 -> 0
... A857: 45382 | B857: 45383 | C857: UPIOUT/409295559930/paytmqr110em392r1@payt m//5462 | D857: TFR | F857: 60 | G857: 0 | H857: 771.09 | I857: Dr | J857: =H856-F857+G857-H857 -> 0
C858: GRAND TOTAL | F858: 179753.05 | G858: 180494.28
A860: Abbreviations Used
A861: CASH: | B861: Cash Transaction | D861: TFR: | E861: Transfer Transaction
A862: FT: | B862: Fund Transfer | D862: CLG: | E862: Clearing Transaction
A863: SBINT: | B863: Interest on SB Account | D863: MB: | E863: Mobile Banking
A865: Disclaimer: This computer generated statement contains the particulars of the transaction(s) in the account that have been updated till the time of day end operations of the CBS system of the Bank on the previous working day and the same will not reflect the transaction(s) that have occurred in the account, if any, subsequent thereto. The Federal Bank Ltd. shall not be liable/responsible for want of full particulars of the transaction(s) at the time of the generation of this statement. This is a computer generated statement which need not normally be signed. Contents of this statement will be considered correct if no error is reported within 21 days of the statement date.
A867: ****END OF STATEMENT****
A869: The Federal Bank Ltd. Corporate Office: Federal Towers, Market Rd, Periyar Nagar, Aluva, Kerala 683101 Ph:0484 2630996 Website: www.federalbank.co.in

Sheet Kotak_Salary
C1: Account Statement
A2: AAYUSH KUMAR GUPTA
A3: 2 nd floor survey no 20 7 | E3: Cust. Reln. No. | F3: 836844778
A4: Swamy legato | E4: Account No. | F4: 3649610333
A5: Kadubisanahalli | E5: Period | F5: From 05/03/2024 To 31/03/2024
A6: Bengaluru | E6: Currency | F6: INR
A7: Karnataka | E7: Branch | F7: M G ROAD BRANCH
A8: India | E8: Nomination Regd | F8: N
A9: 560103 | E9: Nominee Name
E10: Joint Holder(S)
E11: IFSC | F11: KKBK0008066
E12: MICR | F12: 560485072
A14: Sl. No. | B14: Transaction Date | C14: Value Date | D14: Description | E14: Chq / Ref No. | F14: Amount | G14: Dr / Cr | H14: DR | I14: CR | J14: Balance | K14: Dr / Cr
A15: 1 | B15: 45366 | C15: 45366 | D15: TRANS | E15: FCM-24031594KVJN | F15: 9109 | G15: CR | H15: =IF(G15=$H$14,F15,0) -> 0 | I15: =IF(G15=$I$14,F15,0) -> 9109 | J15: 9109 | K15: CR
A16: 2 | B16: 45369 | C16: 45369 | D16: UPI/AAYUSH KUMAR GU/407811693463/MB UPI | E16: UPI-407898263279 | F16: 1 | G16: DR | H16: =IF(G16=$H$14,F16,0) -> 1 | I16: =IF(G16=$I$14,F16,0) -> 0 | J16: 9108 | K16: CR | L16: =J15-H16+I16-J16 -> 0
A17: 3 | B17: 45369 | C17: 45369 | D17: UPI/AAYUSH KUMAR GU/407811695179/MB UPI | E17: UPI-407898305881 | F17: 4999 | G17: DR | H17: =IF(G17=$H$14,F17,0) -> 4999 | I17: =IF(G17=$I$14,F17,0) -> 0 | J17: 4109 | K17: CR | L17: =J16-H17+I17-J17 -> 0
A18: 4 | B18: 45370 | C18: 45370 | D18: UPI/AAYUSH KUMAR GU/407908004025/MB UPI | E18: UPI-407933197636 | F18: 4109 | G18: DR | H18: =IF(G18=$H$14,F18,0) -> 4109 | I18: =IF(G18=$I$14,F18,0) -> 0 | J18: 0 | K18: CR | L18: =J17-H18+I18-J18 -> 0
A19: 5 | B19: 45374 | C19: 45374 | D19: Recd:IMPS/408307273704/CASHFREE P/KKBK/X0008/BAV | E19: IMPS-408307596920 | F19: 1.01 | G19: CR | H19: =IF(G19=$H$14,F19,0) -> 0 | I19: =IF(G19=$I$14,F19,0) -> 1.01 | J19: 1.01 | K19: CR | L19: =J18-H19+I19-J19 -> 0
A20: 6 | B20: 45380 | C20: 45380 | D20: SALARYTRANS | E20: FCM-2403299ES9MP | F20: 63942 | G20: CR | H20: =IF(G20=$H$14,F20,0) -> 0 | I20: =IF(G20=$I$14,F20,0) -> 63942 | J20: 63943.01 | K20: CR | L20: =J19-H20+I20-J20 -> 0
A21: 7 | B21: 45381 | C21: 45381 | D21: UPI/AAYUSH KUMAR GU/409021378087/MB UPI | E21: UPI-409009155467 | F21: 1 | G21: DR | H21: =IF(G21=$H$14,F21,0) -> 1 | I21: =IF(G21=$I$14,F21,0) -> 0 | J21: 63942.01 | K21: CR | L21: =J20-H21+I21-J21 -> 0
A22: 8 | B22: 45381 | C22: 45381 | D22: UPI/AAYUSH KUMAR GU/409021379488/MB UPI | E22: UPI-409009192485 | F22: 1998 | G22: DR | H22: =IF(G22=$H$14,F22,0) -> 1998 | I22: =IF(G22=$I$14,F22,0) -> 0 | J22: 61944.01 | K22: CR | L22: =J21-H22+I22-J22 -> 0
A23: 9 | B23: 45381 | C23: 45381 | D23: UPI/AAYUSH KUMAR GU/409021381201/MB UPI | E23: UPI-409009233431 | F23: 1998 | G23: DR | H23: =IF(G23=$H$14,F23,0) -> 1998 | I23: =IF(G23=$I$14,F23,0) -> 0 | J23: 59946.01 | K23: CR | L23: =J22-H23+I23-J23 -> 0
A24: 10 | B24: 45382 | C24: 45382 | D24: PCD/4395/GYFTR COM/7840089543310324/20:49 | E24: 409115178316 | F24: 245 | G24: DR | H24: =IF(G24=$H$14,F24,0) -> 245 | I24: =IF(G24=$I$14,F24,0) -> 0 | J24: 59701.01 | K24: CR | L24: =J23-H24+I24-J24 -> 0
A25: 11 | B25: 45383 | C25: 45382 | D25: Int.Pd:3649610333:01-01-2024 to 31-03-2024 | F25: 21 | G25: CR | H25: =IF(G25=$H$14,F25,0) -> 0 | I25: =IF(G25=$I$14,F25,0) -> 21 | J25: 59722.01 | K25: CR | L25: =J24-H25+I25-J25 -> 0

Sheet SBI_PPF
A1: Account Name : | B1: Mr. AAYUSH KUMAR GUPTA
A2: Address : | B2: FLAT NO D 07 ISHWAR PARADISE ASHOKA
B3: MARG BEHIND FAME THEATRE ASHOKA MARG
B4: NASHIK-422011
B5: Nashik
A6: Date : | B6: 45404
A7: Account Number : | B7: _00000039706255133
A8: Account Description: | B8: PPF Account
A9: Branch : | B9: SHIVAJI NAGAR, NASIK
A10: Drawing Power : | B10: 0
A11: Interest Rate(% p.a.): | B11: 7.1
A12: Nomination Registered : | B12: Yes
A13: Balance on 1 Apr 2023 : | B13: 17941
A14: Start Date : | B14: 45017
A15: End Date : | B15: 45382
A16: open date : | B16: 44107
A17: Accumulated Interest : | B17: 0
A18: Maturity Date : | B18: 49766
A19: Txn Date | B19: Value Date | C19: Description | D19: Ref No./Cheque No. | E19: Debit | F19: Credit | G19: Balance
A20: 45211 | B20: 45211 | C20: BY TRANSFER-INB Deposit / Investment-- | D20: IF38973887 TRANSFER FROM 20276981227 | E20: 0 | F20: 5000 | G20: 22941
A21: 45382 | B21: 45382 | C21: CREDIT INTEREST--- | E21: 0 | F21: 1422 | G21: 24363
A23: **This is a computer generated statement and does not require a signature

Sheet SBI_Savings
A1: Account Name : | B1: Mr. AAYUSH KUMAR GUPTA
A2: Address : | B2: FLAT NO D 07 ISHWAR PARADISE ASHOKA
B3: MARG BEHIND FAME THEATRE ASHOKA MARG
B4: NASHIK-422011
B5: Nashik
A6: Date : | B6: 45404
A7: Account Number : | B7: _00000020276981227
A8: Account Description: | B8: REGULAR SB CHQ-INDIVIDUALS
A9: Branch : | B9: SHIVAJI NAGAR, NASIK
A10: Drawing Power : | B10: 0
A11: Interest Rate(% p.a.): | B11: 2.7
A12: MOD Balance : | B12: 0
A13: CIF No. : | B13: _88071759834
A14: IFS (Indian Financial System) Code : | B14: SBIN0011669
A15: MICR (Magnetic Ink Character Recognition) Code : | B15: _422002020
A16: Nomination Registered : | B16: Yes
A17: Balance on 1 Apr 2023 : | B17: 124395.27
A18: Start Date : | B18: 45017
A19: End Date : | B19: 45382
A20: Txn Date | B20: Value Date | C20: Description | D20: Ref No./Cheque No. | E20: Debit | F20: Credit | G20: Balance
A21: 45017 | B21: 45017 | C21: BY TRANSFER-UPI/CR/309169418415/AYUSHI M/PUNB/nainamitta/UPI-- | D21: TRANSFER FROM 4693130162091 | E21: 0 | F21: 95 | G21: 124490.27
A22: 45017 | B22: 45017 | C22: TO TRANSFER-UPI/DR/309140926569/BANANA L/HDFC/bananaleaf/UPI-- | D22: TRANSFER TO 4692478162093 | E22: 70 | F22: 0 | G22: 124420.27 | I22: =G21-E22+F22-G22 -> 0
A23: 45018 | B23: 45018 | C23: TO TRANSFER-UPI/DR/309276354517/LUCKY DH/YESB/q57871899@/UPI-- | D23: TRANSFER TO 5098091162092 | E23: 90 | F23: 0 | G23: 124330.27 | I23: =G22-E23+F23-G23 -> 0
A24: 45018 | B24: 45018 | C24: BY TRANSFER-UPI/CR/309286549772/PRASHANT/HDFC/pkaps1997@/UPI-- | D24: TRANSFER FROM 4695271162095 | E24: 0 | F24: 30 | G24: 124360.27 | I24: =G23-E24+F24-G24 -> 0
A25: 45018 | B25: 45018 | C25: TO TRANSFER-UPI/DR/309274214572/PRATYAY /SBIN/7073096110/NA-- | D25: TRANSFER TO 5098127162096 | E25: 210 | F25: 0 | G25: 124150.27 | I25: =G24-E25+F25-G25 -> 0
A26: 45018 | B26: 45018 | C26: TO TRANSFER-UPI/DR/345885628443/WWW VODA/HDFC/vodafone1./UPI-- | D26: TRANSFER TO 5098093162090 | E26: 459 | F26: 0 | G26: 123691.27 | I26: =G25-E26+F26-G26 -> 0
A27: 45018 | B27: 45018 | C27: TO TRANSFER-UPI/DR/309277368845/KUNAL BH/HDFC/kunalbhard/UPI-- | D27: TRANSFER TO 5099812162090 | E27: 71 | F27: 0 | G27: 123620.27 | I27: =G26-E27+F27-G27 -> 0
A28: 45019 | B28: 45019 | C28: TO TRANSFER-UPI/DR/345945568018/Zerodha /HDFC/zerodhabro/08956-- | D28: TRANSFER TO 4695788162098 | E28: 5000 | F28: 0 | G28: 118620.27 | I28: =G27-E28+F28-G28 -> 0
A29: 45020 | B29: 45020 | C29: TO TRANSFER-UPI/DR/309414339465/SEVEN SP/PYTM/paytmqr281/UPI-- | D29: TRANSFER TO 5097637162094 | E29: 250 | F29: 0 | G29: 118370.27 | I29: =G28-E29+F29-G29 -> 0
A30: 45020 | B30: 45020 | C30: TO TRANSFER-UPI/DR/346087812550/SEVEN SP/PYTM/paytmqr281/UPI-- | D30: TRANSFER TO 5097617162098 | E30: 30 | F30: 0 | G30: 118340.27 | I30: =G29-E30+F30-G30 -> 0
A31: 45021 | B31: 45021 | C31: TO TRANSFER-UPI/DR/309564429050/BANANA L/HDFC/bananaleaf/UPI-- | D31: TRANSFER TO 4692551162099 | E31: 70 | F31: 0 | G31: 118270.27 | I31: =G30-E31+F31-G31 -> 0
A32: 45022 | B32: 45022 | C32: TO TRANSFER-UPI/DR/309682616023/Mr AADA/YESB/q423863729/UPI-- | D32: TRANSFER TO 5097803162095 | E32: 104 | F32: 0 | G32: 118166.27 | I32: =G31-E32+F32-G32 -> 0
A33: 45022 | B33: 45022 | C33: TO TRANSFER-UPI/DR/309673159840/Swiggy/UTIB/swiggyupi@/Swiggy-- | D33: TRANSFER TO 5097808162090 | E33: 306 | F33: 0 | G33: 117860.27 | I33: =G32-E33+F33-G33 -> 0
... A44: 45025 | B44: 45025 | C44: TO TRANSFER-UPI/DR/309994513204/UBER IND/HDFC/uberrides@/charg-- | D44: TRANSFER TO 4897696162090 | E44: 48.52 | F44: 0 | G44: 114271.5 | I44: =G43-E44+F44-G44 -> 0
A45: 45027 | B45: 45027 | C45: BULK POSTING-C23854246658 41774260032INTERIM DIVIDEND ACCOU-- | E45: 0 | F45: 10 | G45: 114281.5 | I45: =G44-E45+F45-G45 -> 0
A46: 45027 | B46: 45027 | C46: BY TRANSFER-UPI/CR/310198604104/IRCTC CF/HDFC/irctc.cf@h/UPI R-- | D46: TRANSFER FROM 4897733162090 | E46: 0 | F46: 830 | G46: 115111.5 | I46: =G45-E46+F46-G46 -> 0
A47: 45028 | B47: 45028 | C47: TO TRANSFER-UPI/DR/310294768781/S SARGUNAM/YESB/q200088506/UPI-- | D47: TRANSFER TO 4897692162094 | E47: 100 | F47: 0 | G47: 115011.5 | I47: =G46-E47+F47-G47 -> 0
A48: 45028 | B48: 45028 | C48: TO TRANSFER-UPI/DR/310298964851/Bharti A/HDFC/airtel.pay/UPITr-- | D48: TRANSFER TO 4897692162094 | E48: 155 | F48: 0 | G48: 114856.5 | I48: =G47-E48+F48-G48 -> 0
A49: 45028 | B49: 45028 | C49: TO TRANSFER-UPI/DR/310299085532/billdesk/ICIC/billdesk.p/UPI-- | D49: TRANSFER TO 4897692162094 | E49: 148 | F49: 0 | G49: 114708.5 | I49: =G48-E49+F49-G49 -> 0
A50: 45029 | B50: 45029 | C50: TO TRANSFER-UPI/DR/346932073976/Shankar /PYTM/paytmqr281/UPI-- | D50: TRANSFER TO 4897693162093 | E50: 80 | F50: 0 | G50: 114628.5 | I50: =G49-E50+F50-G50 -> 0
A51: 45031 | B51: 45031 | C51: TO TRANSFER-UPI/DR/310511348614/IRCTC Ap/PYTM/paytm-irct/Oid10-- | D51: TRANSFER TO 4897695162091 | E51: 1398.95 | F51: 0 | G51: 113229.55 | I51: =G50-E51+F51-G51 -> 0
A52: 45031 | B52: 45031 | C52: TO TRANSFER-UPI/DR/347115434891/PATISSER/PYTM/paytmqr281/UPI-- | D52: TRANSFER TO 4897695162091 | E52: 110 | F52: 0 | G52: 113119.55 | I52: =G51-E52+F52-G52 -> 0
A53: 45031 | B53: 45031 | C53: TO TRANSFER-UPI/DR/347130328853/BHAWANI /YESB/q385374207/UPI-- | D53: TRANSFER TO 4897695162091 | E53: 50 | F53: 0 | G53: 113069.55 | I53: =G52-E53+F53-G53 -> 0
A54: 45031 | B54: 45031 | C54: TO TRANSFER-UPI/DR/310500511889/Fudr/ICIC/fudr.cf@ic/3187 Bli-- | D54: TRANSFER TO 4897695162091 | E54: 220 | F54: 0 | G54: 112849.55 | I54: =G53-E54+F54-G54 -> 0
A55: 45032 | B55: 45032 | C55: ATM WDL-ATM CASH 7132 CP JHALAWAR JHALRAPATAN-- | E55: 2000 | F55: 0 | G55: 110849.55 | I55: =G54-E55+F55-G55 -> 0
A56: 45033 | B56: 45033 | C56: BULK POSTING-ACHCr HDFC01032000010237 VEDANTA LIMITE-- | E56: 0 | F56: 348.5 | G56: 111198.05 | I56: =G55-E56+F56-G56 -> 0
A57: 45034 | B57: 45034 | C57: TO TRANSFER-UPI/DR/310875568731/gaurav v/UTIB/fcbizcxqia/UPI-- | D57: TRANSFER TO 4897691162095 | E57: 20 | F57: 0 | G57: 111178.05 | I57: =G56-E57+F57-G57 -> 0
A58: 45034 | B58: 45034 | C58: BY TRANSFER-UPI/CR/310863283715/GOOGLEPAY/UTIB/goog-payme/UPI-- | D58: TRANSFER FROM 4897733162090 | E58: 0 | F58: 11 | G58: 111189.05 | I58: =G57-E58+F58-G58 -> 0
A59: 45034 | B59: 45034 | C59: BY TRANSFER-UPI/CR/310863285848/GOOGLEPAY/UTIB/goog-payme/UPI-- | D59: TRANSFER FROM 4897733162090 | E59: 0 | F59: 6 | G59: 111195.05 | I59: =G58-E59+F59-G59 -> 0
A60: 45034 | B60: 45034 | C60: TO TRANSFER-UPI/DR/310863414173/Plaksha /utib/plakshauni/Onlin-- | D60: TRANSFER TO 4897691162095 | E60: 7500 | F60: 0 | G60: 103695.05 | I60: =G59-E60+F60-G60 -> 0
A61: 45034 | B61: 45034 | C61: TO TRANSFER-UPI/DR/310897017239/KUNAL EA/YESB/q811125368/UPI-- | D61: TRANSFER TO 4897691162095 | E61: 105 | F61: 0 | G61: 103590.05 | I61: =G60-E61+F61-G61 -> 0
A62: 45035 | B62: 45035 | C62: TO TRANSFER-UPI/DR/310930088166/Shubham /SBIN/9920780107/UPI-- | D62: TRANSFER TO 4897692162094 | E62: 830 | F62: 0 | G62: 102760.05 | I62: =G61-E62+F62-G62 -> 0
A63: 45035 | B63: 45035 | C63: TO TRANSFER-UPI/DR/310932343001/Praful B/SBIN/q508793729/UPI-- | D63: TRANSFER TO 4897692162094 | E63: 30 | F63: 0 | G63: 102730.05 | I63: =G62-E63+F63-G63 -> 0
A64: 45035 | B64: 45035 | C64: TO TRANSFER-UPI/DR/310932978826/KUNAL EA/YESB/q811125368/UPI-- | D64: TRANSFER TO 4897692162094 | E64: 70 | F64: 0 | G64: 102660.05 | I64: =G63-E64+F64-G64 -> 0
A65: 45036 | B65: 45036 | C65: TO TRANSFER-COMM - OTHER MISC. SERVICES-- | D65: TRANSFER TO 98353116696 | E65: 177 | F65: 0 | G65: 102483.05 | I65: =G64-E65+F65-G65 -> 0
A66: 45037 | B66: 45037 | C66: TO TRANSFER-UPI/DR/347733861273/Zomato Ltd/PYTM/zomato-ord/Oid-- | D66: TRANSFER TO 4897694162092 | E66: 370.25 | F66: 0 | G66: 102112.8 | I66: =G65-E66+F66-G66 -> 0
A67: 45038 | B67: 45038 | C67: TO TRANSFER-UPI/DR/311214897545/khatabook/ICIC/ktb.ru6532/UPI-- | D67: TRANSFER TO 4897695162091 | E67: 20 | F67: 0 | G67: 102092.8 | I67: =G66-E67+F67-G67 -> 0
A68: 45038 | B68: 45038 | C68: TO TRANSFER-UPI/DR/311215008854/Om Super/PYTM/paytmqr281/UPI-- | D68: TRANSFER TO 4897695162091 | E68: 31 | F68: 0 | G68: 102061.8 | I68: =G67-E68+F68-G68 -> 0
... A103: 45064 | B103: 45064 | C103: TO TRANSFER-UPI/DR/313829232261/KUNAL EA/YESB/q811125368/milk-- | D103: TRANSFER TO 4897693162093 | E103: 35 | F103: 0 | G103: 88427.55 | I103: =G102-E103+F103-G103 -> 0
A104: 45064 | B104: 45064 | C104: BULK POSTING-ACHCr NACH00000000006422 LAURUS LABS LI-- | E104: 0 | F104: 30 | G104: 88457.55 | I104: =G103-E104+F104-G104 -> 0
A105: 45064 | B105: 45064 | C105: TO TRANSFER-UPI/DR/313851087707/The Man /YESB/themancomp/UPI-- | D105: TRANSFER TO 4897693162093 | E105: 325 | F105: 0 | G105: 88132.55 | I105: =G104-E105+F105-G105 -> 0
A106: 45065 | B106: 45065 | C106: TO TRANSFER-UPI/DR/313915167003/Bharatpe/ICIC/bharatpe.9/Pay T-- | D106: TRANSFER TO 4897694162092 | E106: 549 | F106: 0 | G106: 87583.55 | I106: =G105-E106+F106-G106 -> 0
A107: 45066 | B107: 45066 | C107: TO TRANSFER-UPI/DR/314003100568/Add Mone/PYTM/add-money@/UPI-- | D107: TRANSFER TO 4897695162091 | E107: 129 | F107: 0 | G107: 87454.55 | I107: =G106-E107+F107-G107 -> 0
A108: 45066 | B108: 45066 | C108: TO TRANSFER-UPI/DR/314083727068/IRCTC CF/HDFC/irctc.cf@h/IRCTC-- | D108: TRANSFER TO 4897695162091 | E108: 142.15 | F108: 0 | G108: 87312.4 | I108: =G107-E108+F108-G108 -> 0
A109: 45066 | B109: 45066 | C109: TO TRANSFER-UPI/DR/350602864629/MedPlus/YESB/MEDPLUSMAH/Paymen-- | D109: TRANSFER TO 4897695162091 | E109: 832.67 | F109: 0 | G109: 86479.73 | I109: =G108-E109+F109-G109 -> 0
A110: 45066 | B110: 45066 | C110: BY TRANSFER-UPI/CR/314003323481/SANGAM P/PYTM/sangamprav/UPI-- | D110: TRANSFER FROM 4897737162096 | E110: 0 | F110: 287 | G110: 86766.73 | I110: =G109-E110+F110-G110 -> 0
A111: 45067 | B111: 45067 | C111: TO TRANSFER-UPI/DR/314186708272/UBER IND/HDFC/uberrides@/charg-- | D111: TRANSFER TO 4897696162090 | E111: 209.47 | F111: 0 | G111: 86557.26 | I111: =G110-E111+F111-G111 -> 0
A112: 45068 | B112: 45068 | C112: TO TRANSFER-UPI/DR/314244285451/OLA Post/HDFC/olamoney1./UPI-- | D112: TRANSFER TO 4897690162095 | E112: 91 | F112: 0 | G112: 86466.26 | I112: =G111-E112+F112-G112 -> 0
A113: 45071 | B113: 45071 | C113: TO TRANSFER-UPI/DR/314585312544/Mr AADA/YESB/q964606339/UPI-- | D113: TRANSFER TO 4897693162093 | E113: 105 | F113: 0 | G113: 86361.26 | I113: =G112-E113+F113-G113 -> 0
A114: 45074 | B114: 45074 | C114: TO TRANSFER-UPI/DR/314881967653/SEVEN SP/PYTM/paytmqr281/UPI-- | D114: TRANSFER TO 4897696162090 | E114: 70 | F114: 0 | G114: 86291.26 | I114: =G113-E114+F114-G114 -> 0
A115: 45075 | B115: 45075 | C115: BY TRANSFER-INB IMPS314909556711/7352813446/XX1167/opentxn994-- | D115: MAD000312162118 MAD000312162118 | E115: 0 | F115: 36042.33 | G115: 122333.59 | I115: =G114-E115+F115-G115 -> 0
A116: 45075 | B116: 45075 | C116: TO TRANSFER-UPI/DR/314929747278/Mr AADA/YESB/q739730170/UPI-- | D116: TRANSFER TO 4897690162095 | E116: 40 | F116: 0 | G116: 122293.59 | I116: =G115-E116+F116-G116 -> 0
... A142: 45088 | B142: 45088 | C142: TO TRANSFER-UPI/DR/316202758430/Mr AADA/YESB/q964606339/UPI-- | D142: TRANSFER TO 4897696162090 | E142: 110 | F142: 0 | G142: 104421.86 | I142: =G141-E142+F142-G142 -> 0
A143: 45089 | B143: 45089 | C143: BULK POSTING-ACHCr ICIC04933000011905 VEDANTA LIMITE-- | E143: 0 | F143: 573.5 | G143: 104995.36 | I143: =G142-E143+F143-G143 -> 0
A144: 45089 | B144: 45089 | C144: TO TRANSFER-UPI/DR/316351822248/Vendekin/ICIC/vendekin@i/UPI-- | D144: TRANSFER TO 4897691162095 | E144: 40 | F144: 0 | G144: 104955.36 | I144: =G143-E144+F144-G144 -> 0
A145: 45089 | B145: 45089 | C145: BY TRANSFER-UPI/CR/316374839586/Vendekin/ICIC/vendekin@i/vende-- | D145: TRANSFER FROM 4897733162090 | E145: 0 | F145: 40 | G145: 104995.36 | I145: =G144-E145+F145-G145 -> 0
A146: 45089 | B146: 45089 | C146: TO TRANSFER-UPI/DR/316351881817/Mr AADA/YESB/q964606339/UPI-- | D146: TRANSFER TO 4897691162095 | E146: 30 | F146: 0 | G146: 104965.36 | I146: =G145-E146+F146-G146 -> 0
A147: 45090 | B147: 45090 | C147: TO TRANSFER-UPI/DR/316463813881/Vendekin/ICIC/vendekin@i/UPI-- | D147: TRANSFER TO 4897691162095 | E147: 20 | F147: 0 | G147: 104945.36 | I147: =G146-E147+F147-G147 -> 0
A148: 45090 | B148: 45090 | C148: TO TRANSFER-UPI/DR/316486673464/Mr AADA/YESB/q964606339/groce-- | D148: TRANSFER TO 4897691162095 | E148: 70 | F148: 0 | G148: 104875.36 | I148: =G147-E148+F148-G148 -> 0
A149: 45091 | B149: 45091 | C149: BY TRANSFER-UPI/CR/316567060362/MONISH K/ICIC/8296488092/Payme-- | D149: TRANSFER FROM 4897734162099 | E149: 0 | F149: 6434 | G149: 111309.36 | I149: =G148-E149+F149-G149 -> 0
A150: 45091 | B150: 45091 | C150: TO TRANSFER-UPI/DR/316521968604/MLML WINES/PYTM/paytmqr1tb/UPI-- | D150: TRANSFER TO 4897692162094 | E150: 200 | F150: 0 | G150: 111109.36 | I150: =G149-E150+F150-G150 -> 0
A151: 45091 | B151: 45091 | C151: BY TRANSFER-UPI/CR/316541102451/ADARSH N/HDFC/adusma02-1/UPI-- | D151: TRANSFER FROM 4897734162099 | E151: 0 | F151: 100 | G151: 111209.36 | I151: =G150-E151+F151-G151 -> 0
A152: 45091 | B152: 45091 | C152: TO TRANSFER-UPI/DR/316524431336/TAJASVI /SBIN/tejasvisin/UPI-- | D152: TRANSFER TO 4897692162094 | E152: 75 | F152: 0 | G152: 111134.36 | I152: =G151-E152+F152-G152 -> 0
A153: 45093 | B153: 45093 | C153: TO TRANSFER-UPI/DR/316703476731/Vendekin/ICIC/vendekin@i/UPI-- | D153: TRANSFER TO 4897695162091 | E153: 40 | F153: 0 | G153: 111094.36 | I153: =G152-E153+F153-G153 -> 0
A154: 45094 | B154: 45094 | C154: TO TRANSFER-UPI/DR/316823119553/Mr AADA/YESB/q964606339/UPI-- | D154: TRANSFER TO 4897695162091 | E154: 10 | F154: 0 | G154: 111084.36 | I154: =G153-E154+F154-G154 -> 0
A155: 45094 | B155: 45094 | C155: TO TRANSFER-UPI/DR/316882168944/SWIGGY/YESB/swiggy@yes/Debit M-- | D155: TRANSFER TO 4897695162091 | E155: 180 | F155: 0 | G155: 110904.36 | I155: =G154-E155+F155-G155 -> 0
... A169: 45102 | B169: 45102 | C169: TO TRANSFER-UPI/DR/354217681522/Vi/PYTM/vilpremum@/UPI-- | D169: TRANSFER TO 4897696162090 | E169: 459 | F169: 0 | G169: 107568.24 | I169: =G168-E169+F169-G169 -> 0
A170: 45102 | B170: 45102 | C170: CREDIT INTEREST--- | E170: 0 | F170: 704 | G170: 108272.24 | I170: =G169-E170+F170-G170 -> 0
A171: 45103 | B171: 45103 | C171: TO TRANSFER-UPI/DR/317765827066/Vendekin/ICIC/vendekin@i/UPI-- | D171: TRANSFER TO 4897691162095 | E171: 20 | F171: 0 | G171: 108252.24 | I171: =G170-E171+F171-G171 -> 0
A172: 45104 | B172: 45104 | C172: TO TRANSFER-UPI/DR/317878909672/Mr AADA/YESB/q739730170/UPI-- | D172: TRANSFER TO 4897691162095 | E172: 10 | F172: 0 | G172: 108242.24 | I172: =G171-E172+F172-G172 -> 0
A173: 45104 | B173: 45104 | C173: TO TRANSFER-UPI/DR/317895169831/Mr AADA/YESB/q739730170/UPI-- | D173: TRANSFER TO 4897691162095 | E173: 20 | F173: 0 | G173: 108222.24 | I173: =G172-E173+F173-G173 -> 0
A174: 45105 | B174: 45105 | C174: TO TRANSFER-UPI/DR/317916606073/SEVEN SP/PYTM/paytmqr281/UPI-- | D174: TRANSFER TO 4897692162094 | E174: 160 | F174: 0 | G174: 108062.24 | I174: =G173-E174+F174-G174 -> 0
A175: 45105 | B175: 45105 | C175: BY TRANSFER-UPI/CR/317968678553/GAURAV S/KKBK/gauravsing/UPI-- | D175: TRANSFER FROM 4897734162099 | E175: 0 | F175: 60 | G175: 108122.24 | I175: =G174-E175+F175-G175 -> 0
A176: 45105 | B176: 45105 | C176: TO TRANSFER-UPI/DR/317932368474/Vendekin/ICIC/vendekin@i/UPI-- | D176: TRANSFER TO 4897692162094 | E176: 20 | F176: 0 | G176: 108102.24 | I176: =G175-E176+F176-G176 -> 0
A177: 45106 | B177: 45106 | C177: TO TRANSFER-UPI/DR/318041657131/SEVEN SP/PYTM/paytmqr281/UPI-- | D177: TRANSFER TO 4897693162093 | E177: 30 | F177: 0 | G177: 108072.24 | I177: =G176-E177+F177-G177 -> 0
A178: 45106 | B178: 45106 | C178: TO TRANSFER-UPI/DR/318048750928/Mr AADA/YESB/q739730170/UPI-- | D178: TRANSFER TO 4897693162093 | E178: 10 | F178: 0 | G178: 108062.24 | I178: =G177-E178+F178-G178 -> 0
A179: 45108 | B179: 45108 | C179: TO TRANSFER-UPI/DR/318210431133/Mr AADA/YESB/q964606339/UPI-- | D179: TRANSFER TO 4897695162091 | E179: 20 | F179: 0 | G179: 108042.24 | I179: =G178-E179+F179-G179 -> 0
A180: 45108 | B180: 45108 | C180: TO TRANSFER-UPI/DR/318215794065/Vendekin/ICIC/vendekin@i/UPI-- | D180: TRANSFER TO 4897695162091 | E180: 40 | F180: 0 | G180: 108002.24 | I180: =G179-E180+F180-G180 -> 0
A181: 45108 | B181: 45108 | C181: BY TRANSFER-UPI/CR/318221579807/Vendekin/ICIC/vendekin@i/vende-- | D181: TRANSFER FROM 4897737162096 | E181: 0 | F181: 40 | G181: 108042.24 | I181: =G180-E181+F181-G181 -> 0
A182: 45108 | B182: 45108 | C182: TO TRANSFER-UPI/DR/318215841765/Vendekin/ICIC/vendekin@i/UPI-- | D182: TRANSFER TO 4897695162091 | E182: 40 | F182: 0 | G182: 108002.24 | I182: =G181-E182+F182-G182 -> 0
...

Sheet Conso
A1: Aayush Kumar Gupta | D1: =SUBTOTAL(9,D4:D1048576) -> 24000 | E1: =SUBTOTAL(9,E4:E1048576) -> 0
A2: Account of Statements from 01-04-2023 to 31-03-2024 | D2: =SUM(D4:D1048576) -> 4659241.2 | E2: =SUM(E4:E1048576) -> 4598826.2 | F2: =E2-D2 -> -60415 | J2: =SUBTOTAL(9,J3:J2146) -> 0
A3: TX Date | B3: Particulars | C3: Ref | D3: DR | E3: CR | F3: Balance | G3: Kya hai? | I3: Account No
A4: 45017 | B4: NEFT DR-UTIB0002656-AAYUSH KUMAR GUPTA-NETBANK, MUM-N091232397833081-TRANSFER FROM HDFC | D4: 50000 | E4: 0 | F4: 33618.17 | G4: Contra | H4: 1 | I4: HDFC | J4: =F4-E4+D4 -> 83618.17 | O4: Jupiter
A5: 45017 | B5: BY TRANSFER-UPI/CR/309169418415/AYUSHI M/PUNB/nainamitta/UPI-- | C5: TRANSFER FROM 4693130162091 | D5: 0 | E5: 95 | F5: 124490.27 | G5: UPI | H5: 1 | I5: SBI | J5: =F5-E5+D5 -> 124395.27 | K5: =F4-D5+E5-F5 -> -90777.1 | O5: SBI
A6: 45017 | B6: TO TRANSFER-UPI/DR/309140926569/BANANA L/HDFC/bananaleaf/UPI-- | C6: TRANSFER TO 4692478162093 | D6: 70 | E6: 0 | F6: 124420.27 | G6: UPI | I6: SBI | K6: =F5-D6+E6-F6 -> 0 | O6: HDFC
A7: 45018 | B7: NEFT/N091232397833081/AAYUSH KU/HDFC BANK/Transfe | D7: 0 | E7: 50000 | F7: 75508.68 | G7: Contra | H7: 1 | I7: AXIS | J7: =F7-E7+D7 -> 25508.68 | K7: =F6-D7+E7-F7 -> 98911.59 | O7: AXIS
A8: 45018 | B8: TO TRANSFER-UPI/DR/309276354517/LUCKY DH/YESB/q57871899@/UPI-- | C8: TRANSFER TO 5098091162092 | D8: 90 | E8: 0 | F8: 124330.27 | G8: UPI | I8: SBI | K8: =F7-D8+E8-F8 -> -48911.59
A9: 45018 | B9: BY TRANSFER-UPI/CR/309286549772/PRASHANT/HDFC/pkaps1997@/UPI-- | C9: TRANSFER FROM 4695271162095 | D9: 0 | E9: 30 | F9: 124360.27 | G9: UPI | I9: SBI | K9: =F8-D9+E9-F9 -> 0
A10: 45018 | B10: TO TRANSFER-UPI/DR/309274214572/PRATYAY /SBIN/7073096110/NA-- | C10: TRANSFER TO 5098127162096 | D10: 210 | E10: 0 | F10: 124150.27 | G10: UPI | I10: SBI | K10: =F9-D10+E10-F10 -> 0
A11: 45018 | B11: TO TRANSFER-UPI/DR/345885628443/WWW VODA/HDFC/vodafone1./UPI-- | C11: TRANSFER TO 5098093162090 | D11: 459 | E11: 0 | F11: 123691.27 | G11: UPI | I11: SBI | K11: =F10-D11+E11-F11 -> 0
A12: 45018 | B12: TO TRANSFER-UPI/DR/309277368845/KUNAL BH/HDFC/kunalbhard/UPI-- | C12: TRANSFER TO 5099812162090 | D12: 71 | E12: 0 | F12: 123620.27 | G12: UPI | I12: SBI | K12: =F11-D12+E12-F12 -> 0
A13: 45019 | B13: NEFT CR-UTIB0000115-JINDAL SAW LIMITED-AAYUSH KUMAR GUPTA-AXISCN0231261220 | D13: 0 | E13: 57999 | F13: 91617.17 | G13: From JSL, income PY | I13: HDFC | K13: =F12-D13+E13-F13 -> 90002.1
A14: 45019 | B14: NET PI TO HSL SEC A/C 2554606-00602340029427 | D14: 387.51 | E14: 0 | F14: 91229.66 | G14: HSL | I14: HDFC | K14: =F13-D14+E14-F14 -> 0
A15: 45019 | B15: NET PO FROM HSL A/C 2554606-00602340029427 | D15: 0 | E15: 4287.59 | F15: 95517.25 | G15: HSL | I15: HDFC | K15: =F14-D15+E15-F15 -> 0
A16: 45019 | B16: TO TRANSFER-UPI/DR/345945568018/Zerodha /HDFC/zerodhabro/08956-- | C16: TRANSFER TO 4695788162098 | D16: 5000 | E16: 0 | F16: 118620.27 | G16: UPI | I16: SBI | K16: =F15-D16+E16-F16 -> -28103.02
A17: 45020 | B17: TO TRANSFER-UPI/DR/309414339465/SEVEN SP/PYTM/paytmqr281/UPI-- | C17: TRANSFER TO 5097637162094 | D17: 250 | E17: 0 | F17: 118370.27 | G17: UPI | I17: SBI | K17: =F16-D17+E17-F17 -> 0
A18: 45020 | B18: TO TRANSFER-UPI/DR/346087812550/SEVEN SP/PYTM/paytmqr281/UPI-- | C18: TRANSFER TO 5097617162098 | D18: 30 | E18: 0 | F18: 118340.27 | G18: UPI | I18: SBI | K18: =F17-D18+E18-F18 -> 0
A19: 45021 | B19: NET PI TO HSL SEC A/C 2554606-00602340029427 | D19: 21810.69 | E19: 0 | F19: 73706.56 | G19: HSL | I19: HDFC | K19: =F18-D19+E19-F19 -> 22823.02
A20: 45021 | B20: TO TRANSFER-UPI/DR/309564429050/BANANA L/HDFC/bananaleaf/UPI-- | C20: TRANSFER TO 4692551162099 | D20: 70 | E20: 0 | F20: 118270.27 | G20: UPI | I20: SBI | K20: =F19-D20+E20-F20 -> -44633.71
A21: 45022 | B21: NET PI TO HSL SEC A/C 2554606-00602340029427 | D21: 115.7 | E21: 0 | F21: 73590.86 | G21: HSL | I21: HDFC | K21: =F20-D21+E21-F21 -> 44563.71
A22: 45022 | B22: NET PO FROM HSL A/C 2554606-00602340029427 | D22: 0 | E22: 1699.23 | F22: 75290.09 | G22: HSL | I22: HDFC | K22: =F21-D22+E22-F22 -> 0
A23: 45022 | B23: TO TRANSFER-UPI/DR/309682616023/Mr AADA/YESB/q423863729/UPI-- | C23: TRANSFER TO 5097803162095 | D23: 104 | E23: 0 | F23: 118166.27 | G23: UPI | I23: SBI | K23: =F22-D23+E23-F23 -> -42980.18
A24: 45022 | B24: TO TRANSFER-UPI/DR/309673159840/Swiggy/UTIB/swiggyupi@/Swiggy-- | C24: TRANSFER TO 5097808162090 | D24: 306 | E24: 0 | F24: 117860.27 | G24: UPI | I24: SBI | K24: =F23-D24+E24-F24 -> 0
A25: 45023 | B25: 00602300000434-021333684 | D25: 0 | E25: 1880 | F25: 77170.09 | G25: Jeevan Sanchay Return | I25: HDFC | K25: =F24-D25+E25-F25 -> 42570.18
A26: 45023 | B26: TO TRANSFER-UPI/DR/309789529764/IRCTC CF/HDFC/irctc.cf@h/IRCTC-- | C26: TRANSFER TO 4692595162098 | D26: 1448.95 | E26: 0 | F26: 116411.32 | G26: UPI | I26: SBI | K26: =F25-D26+E26-F26 -> -40690.18
A27: 45023 | B27: TO TRANSFER-UPI/DR/309789705434/IRCTC CF/HDFC/irctc.cf@h/IRCTC-- | C27: TRANSFER TO 4696934162097 | D27: 902.15 | E27: 0 | F27: 115509.17 | G27: UPI | I27: SBI | K27: =F26-D27+E27-F27 -> 0
A28: 45023 | B28: TO TRANSFER-UPI/DR/309720030395/Mr AADA/YESB/q143041833/UPI-- | C28: TRANSFER TO 4696933162098 | D28: 20 | E28: 0 | F28: 115489.17 | G28: UPI | I28: SBI | K28: =F27-D28+E28-F28 -> 0
A29: 45023 | B29: TO TRANSFER-UPI/DR/309790935099/IRCTC CF/HDFC/irctc.cf@h/IRCTC-- | C29: TRANSFER TO 4696185162096 | D29: 602.15 | E29: 0 | F29: 114887.02 | G29: UPI | I29: SBI
A30: 45023 | B30: TO TRANSFER-UPI/DR/309732235881/BANANA L/HDFC/bananaleaf/UPI-- | C30: TRANSFER TO 4692597162096 | D30: 110 | E30: 0 | F30: 114777.02 | G30: UPI | I30: SBI | K30: =F29-D30+E30-F30 -> 0
A31: 45024 | B31: UPIOUT/309826882296/Q143041833@ybl/Sent via /5311 | C31: TFR | D31: 10 | E31: 0 | F31: 19.86 | G31: UPI < 100 | H31: 1 | I31: Jupiter | J31: =F31-E31+D31 -> 29.86 | K31: =F30-D31+E31-F31 -> 114747.16
A32: 45024 | B32: TO TRANSFER-UPI/DR/309845925383/Mr AADA/YESB/q143041833/UPI-- | C32: TRANSFER TO 4696969162097 | D32: 40 | E32: 0 | F32: 114737.02 | G32: UPI | I32: SBI | K32: =F31-D32+E32-F32 -> -114757.16
A33: 45024 | B33: TO TRANSFER-UPI/DR/309870836173/SEVEN SP/PYTM/paytmqr281/UPI-- | C33: TRANSFER TO 5098011162097 | D33: 60 | E33: 0 | F33: 114677.02 | G33: UPI | I33: SBI | K33: =F32-D33+E33-F33 -> 0
A34: 45024 | B34: TO TRANSFER-UPI/DR/309861185569/Raj Rani/SBIN/lalsinghla/UPI-- | C34: TRANSFER TO 4694361162091 | D34: 132 | E34: 0 | F34: 114545.02 | G34: UPI | I34: SBI | K34: =F33-D34+E34-F34 -> 0
A35: 45024 | B35: TO TRANSFER-UPI/DR/309864621113/AJAY GUPTA/HDFC/slietajayg/UPI-- | C35: TRANSFER TO 4694315162096 | D35: 100 | E35: 0 | F35: 114445.02 | G35: UPI | I35: SBI | K35: =F34-D35+E35-F35 -> 0
A36: 45025 | B36: TO TRANSFER-UPI/DR/309973408594/JAGDISH/PYTM/7742506388/UPI-- | C36: TRANSFER TO 5098150162096 | D36: 125 | E36: 0 | F36: 114320.02 | G36: UPI | I36: SBI | K36: =F35-D36+E36-F36 -> 0
A37: 45025 | B37: TO TRANSFER-UPI/DR/309994513204/UBER IND/HDFC/uberrides@/charg-- | C37: TRANSFER TO 4897696162090 | D37: 48.52 | E37: 0 | F37: 114271.5 | G37: UPI | I37: SBI | K37: =F36-D37+E37-F37 -> 0
A38: 45026 | B38: NET PI TO HSL SEC A/C 2554606-00602340029427 | D38: 466.16 | E38: 0 | F38: 76703.93 | G38: HSL | I38: HDFC | K38: =F37-D38+E38-F38 -> 37101.41
A39: 45026 | B39: NET PO FROM HSL A/C 2554606-00602340029427 | D39: 0 | E39: 662.12 | F39: 77366.05 | G39: HSL | I39: HDFC | K39: =F38-D39+E39-F39 -> 0
A40: 45027 | B40: NET PI TO HSL SEC A/C 2554606-00602340029427 | D40: 116.86 | E40: 0 | F40: 77249.19 | G40: HSL | I40: HDFC | K40: =F39-D40+E40-F40 -> 0
A41: 45027 | B41: NET PO FROM HSL A/C 2554606-00602340029427 | D41: 0 | E41: 334.27 | F41: 77583.46 | G41: HSL | I41: HDFC | K41: =F40-D41+E41-F41 -> 0
A42: 45027 | B42: BULK POSTING-C23854246658 41774260032INTERIM DIVIDEND ACCOU-- | D42: 0 | E42: 10 | F42: 114281.5 | G42: Dividend Income | I42: SBI | K42: =F41-D42+E42-F42 -> -36688.04
A43: 45027 | B43: BY TRANSFER-UPI/CR/310198604104/IRCTC CF/HDFC/irctc.cf@h/UPI R-- | C43: TRANSFER FROM 4897733162090 | D43: 0 | E43: 830 | F43: 115111.5 | G43: UPI | I43: SBI | K43: =F42-D43+E43-F43 -> 0
A44: 45028 | B44: NET PI TO HSL SEC A/C 2554606-00602340029427 | D44: 117.03 | E44: 0 | F44: 77466.43 | G44: HSL | I44: HDFC | K44: =F43-D44+E44-F44 -> 37528.04
A45: 45028 | B45: NET PO FROM HSL A/C 2554606-00602340029427 | D45: 0 | E45: 1340.99 | F45: 78807.42 | G45: HSL | I45: HDFC | K45: =F44-D45+E45-F45 -> 0
A46: 45028 | B46: TO TRANSFER-UPI/DR/310294768781/S SARGUNAM/YESB/q200088506/UPI-- | C46: TRANSFER TO 4897692162094 | D46: 100 | E46: 0 | F46: 115011.5 | G46: UPI | I46: SBI | K46: =F45-D46+E46-F46 -> -36304.08
A47: 45028 | B47: TO TRANSFER-UPI/DR/310298964851/Bharti A/HDFC/airtel.pay/UPITr-- | C47: TRANSFER TO 4897692162094 | D47: 155 | E47: 0 | F47: 114856.5 | G47: UPI | I47: SBI | K47: =F46-D47+E47-F47 -> 0
A48: 45028 | B48: TO TRANSFER-UPI/DR/310299085532/billdesk/ICIC/billdesk.p/UPI-- | C48: TRANSFER TO 4897692162094 | D48: 148 | E48: 0 | F48: 114708.5 | G48: UPI | I48: SBI | K48: =F47-D48+E48-F48 -> 0
A49: 45029 | B49: DEPOSITORY CHARGES MAR23 - 52812428 | D49: 590 | E49: 0 | F49: 78217.42 | G49: Depos Charges | I49: HDFC | K49: =F48-D49+E49-F49 -> 35901.08
A50: 45029 | B50: NET PI TO HSL SEC A/C 2554606-00602340029427 | D50: 117.69 | E50: 0 | F50: 78099.73 | G50: HSL | I50: HDFC | K50: =F49-D50+E50-F50 -> 0
A51: 45029 | B51: NET PO FROM HSL A/C 2554606-00602340029427 | D51: 0 | E51: 134.43 | F51: 78234.16 | G51: HSL | I51: HDFC | K51: =F50-D51+E51-F51 -> 0
A52: 45029 | B52: TO TRANSFER-UPI/DR/346932073976/Shankar /PYTM/paytmqr281/UPI-- | C52: TRANSFER TO 4897693162093 | D52: 80 | E52: 0 | F52: 114628.5 | G52: UPI | I52: SBI | K52: =F51-D52+E52-F52 -> -36474.34
A53: 45031 | B53: 50100542230922-TPT-BORROW FROM AAYUSH-ARCHIT GUPTA | D53: 25000 | E53: 0 | F53: 53234.16 | G53: Transfer to Archit Gupta | I53: HDFC | K53: =F52-D53+E53-F53 -> 36394.34
A54: 45031 | B54: TO TRANSFER-UPI/DR/310511348614/IRCTC Ap/PYTM/paytm-irct/Oid10-- | C54: TRANSFER TO 4897695162091 | D54: 1398.95 | E54: 0 | F54: 113229.55 | G54: UPI | I54: SBI | K54: =F53-D54+E54-F54 -> -61394.34
A55: 45031 | B55: TO TRANSFER-UPI/DR/347115434891/PATISSER/PYTM/paytmqr281/UPI-- | C55: TRANSFER TO 4897695162091 | D55: 110 | E55: 0 | F55: 113119.55 | G55: UPI | I55: SBI | K55: =F54-D55+E55-F55 -> 0
A56: 45031 | B56: TO TRANSFER-UPI/DR/347130328853/BHAWANI /YESB/q385374207/UPI-- | C56: TRANSFER TO 4897695162091 | D56: 50 | E56: 0 | F56: 113069.55 | G56: UPI | I56: SBI | K56: =F55-D56+E56-F56 -> 0
A57: 45031 | B57: TO TRANSFER-UPI/DR/310500511889/Fudr/ICIC/fudr.cf@ic/3187 Bli-- | C57: TRANSFER TO 4897695162091 | D57: 220 | E57: 0 | F57: 112849.55 | G57: UPI | I57: SBI | K57: =F56-D57+E57-F57 -> 0
A58: 45032 | B58: ATM WDL-ATM CASH 7132 CP JHALAWAR JHALRAPATAN-- | D58: 2000 | E58: 0 | F58: 110849.55 | G58: Cash Withdrawal | I58: SBI | K58: =F57-D58+E58-F58 -> 0
A59: 45033 | B59: NET PAYIN TO BSE MF A/C -57500000389146- FROM A/C -50100128155413- UCC -2554606-57500000389146 | D59: 2500 | E59: 0 | F59: 50734.16 | G59: SIP - 2500 | I59: HDFC | K59: =F58-D59+E59-F59 -> 57615.39
A60: 45033 | B60: NET PI TO HSL SEC A/C 2554606-00602340029427 | D60: 471.04 | E60: 0 | F60: 50263.12 | G60: HSL | I60: HDFC | K60: =F59-D60+E60-F60 -> 0
A61: 45033 | B61: NET PO FROM HSL A/C 2554606-00602340029427 | D61: 0 | E61: 2222.79 | F61: 52485.91 | G61: HSL | I61: HDFC | K61: =F60-D61+E61-F61 -> 0
A62: 45033 | B62: BULK POSTING-ACHCr HDFC01032000010237 VEDANTA LIMITE-- | D62: 0 | E62: 348.5 | F62: 111198.05 | G62: Dividend Income | I62: SBI | K62: =F61-D62+E62-F62 -> -58363.64
A63: 45034 | B63: 01671000085930-TPT-MONEY RETURNED TO AAYUSH-AJAY KUMAR GUPTA | D63: 25000 | E63: 0 | F63: 27485.91 | G63: Transfer to Ajay Gupta | I63: HDFC | K63: =F62-D63+E63-F63 -> 58712.14
A64: 45034 | B64: NET PI TO HSL SEC A/C 2554606-00602340029427 | D64: 118.85 | E64: 0 | F64: 27367.06 | G64: HSL | I64: HDFC | K64: =F63-D64+E64-F64 -> 0
A65: 45034 | B65: NET PI TO HSL SEC A/C 2554606-00602340029427 | D65: 2188.95 | E65: 0 | F65: 25178.11 | G65: HSL | I65: HDFC | K65: =F64-D65+E65-F65 -> 0
A66: 45034 | B66: TO TRANSFER-UPI/DR/310875568731/gaurav v/UTIB/fcbizcxqia/UPI-- | C66: TRANSFER TO 4897691162095 | D66: 20 | E66: 0 | F66: 111178.05 | G66: UPI | I66: SBI | K66: =F65-D66+E66-F66 -> -86019.94
A67: 45034 | B67: BY TRANSFER-UPI/CR/310863283715/GOOGLEPAY/UTIB/goog-payme/UPI-- | C67: TRANSFER FROM 4897733162090 | D67: 0 | E67: 11 | F67: 111189.05 | G67: UPI | I67: SBI | K67: =F66-D67+E67-F67 -> 0
A68: 45034 | B68: BY TRANSFER-UPI/CR/310863285848/GOOGLEPAY/UTIB/goog-payme/UPI-- | C68: TRANSFER FROM 4897733162090 | D68: 0 | E68: 6 | F68: 111195.05 | G68: UPI | I68: SBI | K68: =F67-D68+E68-F68 -> 0
A69: 45034 | B69: TO TRANSFER-UPI/DR/310863414173/Plaksha /utib/plakshauni/Onlin-- | C69: TRANSFER TO 4897691162095 | D69: 7500 | E69: 0 | F69: 103695.05 | G69: UPI | I69: SBI | K69: =F68-D69+E69-F69 -> 0
A70: 45034 | B70: TO TRANSFER-UPI/DR/310897017239/KUNAL EA/YESB/q811125368/UPI-- | C70: TRANSFER TO 4897691162095 | D70: 105 | E70: 0 | F70: 103590.05 | G70: UPI | I70: SBI | K70: =F69-D70+E70-F70 -> 0
A71: 45035 | B71: NET PI TO HSL SEC A/C 2554606-00602340029427 | D71: 117.77 | E71: 0 | F71: 25060.34 | G71: HSL | I71: HDFC | K71: =F70-D71+E71-F71 -> 78411.94
A72: 45035 | B72: NET PO FROM HSL A/C 2554606-00602340029427 | D72: 0 | E72: 1395.14 | F72: 26455.48 | G72: HSL | I72: HDFC | K72: =F71-D72+E72-F72 -> 0
A73: 45035 | B73: TO TRANSFER-UPI/DR/310930088166/Shubham /SBIN/9920780107/UPI-- | C73: TRANSFER TO 4897692162094 | D73: 830 | E73: 0 | F73: 102760.05 | G73: UPI | I73: SBI | K73: =F72-D73+E73-F73 -> -77134.57
A74: 45035 | B74: TO TRANSFER-UPI/DR/310932343001/Praful B/SBIN/q508793729/UPI-- | C74: TRANSFER TO 4897692162094 | D74: 30 | E74: 0 | F74: 102730.05 | G74: UPI | I74: SBI | K74: =F73-D74+E74-F74 -> 0
A75: 45035 | B75: TO TRANSFER-UPI/DR/310932978826/KUNAL EA/YESB/q811125368/UPI-- | C75: TRANSFER TO 4897692162094 | D75: 70 | E75: 0 | F75: 102660.05 | G75: UPI | I75: SBI | K75: =F74-D75+E75-F75 -> 0
A76: 45036 | B76: NET PO FROM HSL A/C 2554606-00602340029427 | D76: 0 | E76: 6098.61 | F76: 32554.09 | G76: HSL | I76: HDFC | K76: =F75-D76+E76-F76 -> 76204.57
A77: 45036 | B77: TO TRANSFER-COMM - OTHER MISC. SERVICES-- | C77: TRANSFER TO 98353116696 | D77: 177 | E77: 0 | F77: 102483.05 | G77: Bank Charges | I77: SBI | K77: =F76-D77+E77-F77 -> -70105.96
A78: 45037 | B78: ATW-652166XXXXXX8920-CHBDL001-NASHIK | D78: 10000 | E78: 0 | F78: 22554.09 | G78: Cash Withdrawal | I78: HDFC | K78: =F77-D78+E78-F78 -> 69928.96
A79: 45037 | B79: NET PO FROM HSL A/C 2554606-00602340029427 | D79: 0 | E79: 2364.46 | F79: 24918.55 | G79: HSL | I79: HDFC | K79: =F78-D79+E79-F79 -> 0
A80: 45037 | B80: TO TRANSFER-UPI/DR/347733861273/Zomato Ltd/PYTM/zomato-ord/Oid-- | C80: TRANSFER TO 4897694162092 | D80: 370.25 | E80: 0 | F80: 102112.8 | G80: UPI | I80: SBI | K80: =F79-D80+E80-F80 -> -77564.5
A81: 45038 | B81: UPIOUT/311268164406/paytm-61240897@paytm/S en/5411 | C81: TFR | D81: 9 | E81: 0 | F81: 10.86 | G81: UPI < 100 | I81: Jupiter | K81: =F80-D81+E81-F81 -> 102092.94
A82: 45038 | B82: TO TRANSFER-UPI/DR/311214897545/khatabook/ICIC/ktb.ru6532/UPI-- | C82: TRANSFER TO 4897695162091 | D82: 20 | E82: 0 | F82: 102092.8 | G82: UPI | I82: SBI | K82: =F81-D82+E82-F82 -> -102101.94
A83: 45038 | B83: TO TRANSFER-UPI/DR/311215008854/Om Super/PYTM/paytmqr281/UPI-- | C83: TRANSFER TO 4897695162091 | D83: 31 | E83: 0 | F83: 102061.8 | G83: UPI | I83: SBI | K83: =F82-D83+E83-F83 -> 0
A84: 45040 | B84: NET PI TO HSL SEC A/C 2554606-00602340029427 | D84: 333.9 | E84: 0 | F84: 24584.65 | G84: HSL | I84: HDFC | K84: =F83-D84+E84-F84 -> 77143.25
A85: 45040 | B85: NET PO FROM HSL A/C 2554606-00602340029427 | D85: 0 | E85: 1160.53 | F85: 25745.18 | G85: HSL | I85: HDFC | K85: =F84-D85+E85-F85 -> 0
A86: 45041 | B86: NET PAYIN TO BSE MF A/C -57500000389146- FROM A/C -50100128155413- UCC -2554606-57500000389146 | D86: 2500 | E86: 0 | F86: 23245.18 | G86: SIP - 2500 | I86: HDFC | K86: =F85-D86+E86-F86 -> 0
A87: 45041 | B87: NET PO FROM HSL A/C 2554606-00602340029427 | D87: 0 | E87: 3975.3 | F87: 27220.48 | G87: HSL | I87: HDFC | K87: =F86-D87+E87-F87 -> 0
A88: 45041 | B88: NET PI TO HSL SEC A/C 2554606-00602340029427 | D88: 111.87 | E88: 0 | F88: 27108.61 | G88: HSL | I88: HDFC | K88: =F87-D88+E88-F88 -> 0
A89: 45041 | B89: NET PO FROM HSL A/C 2554606-00602340029427 | D89: 0 | E89: 4133.83 | F89: 31242.44 | G89: HSL | I89: HDFC | K89: =F88-D89+E89-F89 -> 0
A90: 45041 | B90: NET PO FROM HSL A/C 2554606-00602340029427 | D90: 0 | E90: 9183.04 | F90: 40425.48 | G90: HSL | I90: HDFC | K90: =F89-D90+E90-F90 -> 0
A91: 45041 | B91: TO TRANSFER-UPI/DR/348124957377/Mr HAROO/YESB/q840523701/UPI-- | C91: TRANSFER TO 4897691162095 | D91: 30 | E91: 0 | F91: 102031.8 | G91: UPI | I91: SBI | K91: =F90-D91+E91-F91 -> -61636.32
A92: 45042 | B92: NET PI TO HSL SEC A/C 2554606-00602340029427 | D92: 5928.58 | E92: 0 | F92: 34496.9 | G92: HSL | I92: HDFC | K92: =F91-D92+E92-F92 -> 61606.32
A93: 45042 | B93: TO TRANSFER-UPI/DR/311647973323/olamoney1/HDFC/olamoney1./UPI-- | C93: TRANSFER TO 4897692162094 | D93: 69 | E93: 0 | F93: 101962.8 | G93: UPI | I93: SBI | K93: =F92-D93+E93-F93 -> -67534.9
A94: 45042 | B94: TO TRANSFER-UPI/DR/311605861496/Vodafone/PYTM/vilpremum@/UPI-- | C94: TRANSFER TO 4897692162094 | D94: 50 | E94: 0 | F94: 101912.8 | G94: UPI | I94: SBI | K94: =F93-D94+E94-F94 -> 0
A95: 45042 | B95: TO TRANSFER-UPI/DR/311672052419/MEDPLUS /PYTM/paytm-7097/UPI-- | C95: TRANSFER TO 4897692162094 | D95: 991.82 | E95: 0 | F95: 100920.98 | G95: UPI | I95: SBI | K95: =F94-D95+E95-F95 -> 0
A96: 45043 | B96: NET PI TO HSL SEC A/C 2554606-00602340029427 | D96: 100.39 | E96: 0 | F96: 34396.51 | G96: HSL | I96: HDFC | K96: =F95-D96+E96-F96 -> 66424.08
A97: 45043 | B97: NET PO FROM HSL A/C 2554606-00602340029427 | D97: 0 | E97: 1200.79 | F97: 35597.3 | G97: HSL | I97: HDFC | K97: =F96-D97+E97-F97 -> 0
A98: 45043 | B98: TO TRANSFER-UPI/DR/311707651627/VIDYA AS/YESB/q580300757/UPI-- | C98: TRANSFER TO 4897693162093 | D98: 278 | E98: 0 | F98: 100642.98 | G98: UPI | I98: SBI | K98: =F97-D98+E98-F98 -> -65323.68
A99: 45043 | B99: BY TRANSFER-UPI/CR/311760370847/ARCHIT G/UTIB/archit4801/UPI-- | C99: TRANSFER FROM 4897735162098 | D99: 0 | E99: 100 | F99: 100742.98 | G99: UPI | I99: SBI | K99: =F98-D99+E99-F99 -> 0
A100: 45043 | B100: TO TRANSFER-UPI/DR/311713120224/ARCHIT G/UTIB/archit4801/UPI-- | C100: TRANSFER TO 4897693162093 | D100: 100 | E100: 0 | F100: 100642.98 | G100: UPI | I100: SBI | K100: =F99-D100+E100-F100 -> 0
...

Sheet Bank Summary
B3: All Banks
B4: Aayush Gupta Bank Summary
B5: 01-04-2023 to 31-03-2024
B6: Particulars | C6: ₹ | D6: Particulars | E6: ₹
B7: Opening Balances | C7: =J13 -> 233551.98 | J7: Opening | K7: Closing
I8: AXIS | J8: 25508.68 | K8: 16847.21
B9: Contra | C9: =SUMIFS(Conso!$E:$E,Conso!$G:$G,B9) -> 122214 | D9: Contra | E9: =SUMIFS(Conso!$D:$D,Conso!$G:$G,D9) -> 113106 | F9: =C9-E9 -> 9108 | I9: HDFC | J9: 83618.17 | K9: 43050.89
B10: UPI | C10: =SUMIFS(Conso!$E:$E,Conso!$G:$G,B10) -> 71195.14 | D10: UPI | E10: =SUMIFS(Conso!$D:$D,Conso!$G:$G,D10) -> 315109.26 | I10: Jupiter | J10: 29.86 | K10: 911.09
B11: From JSL, income PY | C11: =SUMIFS(Conso!$E:$E,Conso!$G:$G,B11) -> 57999 | D11: From JSL, income PY | E11: =SUMIFS(Conso!$D:$D,Conso!$G:$G,D11) -> 0 | I11: KOTAK | J11: 0 | K11: 59722.01
B12: HSL | C12: =SUMIFS(Conso!$E:$E,Conso!$G:$G,B12) -> 2186206.9 | D12: HSL | E12: =SUMIFS(Conso!$D:$D,Conso!$G:$G,D12) -> 2581041.4 | I12: SBI | J12: 124395.27 | K12: 52605.78
B13: Jeevan Sanchay Return | C13: =SUMIFS(Conso!$E:$E,Conso!$G:$G,B13) -> 20680 | D13: Jeevan Sanchay Return | E13: =SUMIFS(Conso!$D:$D,Conso!$G:$G,D13) -> 0 | J13: =SUM(J8:J12) -> 233551.98 | K13: =SUM(K8:K12) -> 173136.98
B14: UPI < 100 | C14: =SUMIFS(Conso!$E:$E,Conso!$G:$G,B14) -> 9575 | D14: UPI < 100 | E14: =SUMIFS(Conso!$D:$D,Conso!$G:$G,D14) -> 19319.29 | J14: =Conso!E2-Conso!D2 -> -60415
B15: Dividend Income | C15: =SUMIFS(Conso!$E:$E,Conso!$G:$G,B15) -> 17179.05 | D15: Dividend Income | E15: =SUMIFS(Conso!$D:$D,Conso!$G:$G,D15) -> 0
B16: Depos Charges | C16: =SUMIFS(Conso!$E:$E,Conso!$G:$G,B16) -> 0 | D16: Depos Charges | E16: =SUMIFS(Conso!$D:$D,Conso!$G:$G,D16) -> 12419.17
B17: Transfer to Archit Gupta | C17: =SUMIFS(Conso!$E:$E,Conso!$G:$G,B17) -> 0 | D17: Transfer to Archit Gupta | E17: =SUMIFS(Conso!$D:$D,Conso!$G:$G,D17) -> 75000
B18: Cash Withdrawal | C18: =SUMIFS(Conso!$E:$E,Conso!$G:$G,B18) -> 0 | D18: Cash Withdrawal | E18: =SUMIFS(Conso!$D:$D,Conso!$G:$G,D18) -> 21500
B19: SIP - 2500 | C19: =SUMIFS(Conso!$E:$E,Conso!$G:$G,B19) -> 0 | D19: SIP - 2500 | E19: =SUMIFS(Conso!$D:$D,Conso!$G:$G,D19) -> 30000
B20: Transfer to Ajay Gupta | C20: =SUMIFS(Conso!$E:$E,Conso!$G:$G,B20) -> 0 | D20: Transfer to Ajay Gupta | E20: =SUMIFS(Conso!$D:$D,Conso!$G:$G,D20) -> 325000
B21: Bank Charges | C21: =SUMIFS(Conso!$E:$E,Conso!$G:$G,B21) -> 0 | D21: Bank Charges | E21: =SUMIFS(Conso!$D:$D,Conso!$G:$G,D21) -> 2369.22
B22: Transfer From Archit Gupta | C22: =SUMIFS(Conso!$E:$E,Conso!$G:$G,B22) -> 25000 | D22: Transfer From Archit Gupta | E22: =SUMIFS(Conso!$D:$D,Conso!$G:$G,D22) -> 0
B23: Transfer From Sunita Gupta | C23: =SUMIFS(Conso!$E:$E,Conso!$G:$G,B23) -> 120000 | D23: Transfer From Sunita Gupta | E23: =SUMIFS(Conso!$D:$D,Conso!$G:$G,D23) -> 0
B24: ?? | C24: 424157.82 | D24: ?? | E24: 267495
B25: SIP - 3000 | C25: =SUMIFS(Conso!$E:$E,Conso!$G:$G,B25) -> 0 | D25: SIP - 3000 | E25: =SUMIFS(Conso!$D:$D,Conso!$G:$G,D25) -> 33000
B26: Personal | C26: =SUMIFS(Conso!$E:$E,Conso!$G:$G,B26) -> 6194.93 | D26: Personal | E26: =SUMIFS(Conso!$D:$D,Conso!$G:$G,D26) -> 22983.89
B27: Misc Income | C27: =SUMIFS(Conso!$E:$E,Conso!$G:$G,B27) -> 247.3 | D27: Misc Income | E27: =SUMIFS(Conso!$D:$D,Conso!$G:$G,D27) -> 0
B28: Plaksha Refund | C28: =SUMIFS(Conso!$E:$E,Conso!$G:$G,B28) -> 36042.33 | D28: Plaksha Refund | E28: =SUMIFS(Conso!$D:$D,Conso!$G:$G,D28) -> 0
B29: Transfer from Ajay Gupta | C29: =SUMIFS(Conso!$E:$E,Conso!$G:$G,B29) -> 996880 | D29: Transfer from Ajay Gupta | E29: =SUMIFS(Conso!$D:$D,Conso!$G:$G,D29) -> 20000
B30: Bank Interest | C30: =SUMIFS(Conso!$E:$E,Conso!$G:$G,B30) -> 5420 | D30: Bank Interest | E30: =SUMIFS(Conso!$D:$D,Conso!$G:$G,D30) -> 0
B31: Professional Fees from JSW | C31: =SUMIFS(Conso!$E:$E,Conso!$G:$G,B31) -> 10000 | D31: Professional Fees from JSW | E31: =SUMIFS(Conso!$D:$D,Conso!$G:$G,D31) -> 0
B32: Zerodha | C32: =SUMIFS(Conso!$E:$E,Conso!$G:$G,B32) -> 5644.08 | D32: Zerodha | E32: =SUMIFS(Conso!$D:$D,Conso!$G:$G,D32) -> 0
B33: HDFC Life Insurance Premium | C33: =SUMIFS(Conso!$E:$E,Conso!$G:$G,B33) -> 0 | D33: HDFC Life Insurance Premium | E33: =SUMIFS(Conso!$D:$D,Conso!$G:$G,D33) -> 306000
B34: SIP - 5000 | C34: =SUMIFS(Conso!$E:$E,Conso!$G:$G,B34) -> 0 | D34: SIP - 5000 | E34: =SUMIFS(Conso!$D:$D,Conso!$G:$G,D34) -> 65000
B35: SIP - 10000 | C35: =SUMIFS(Conso!$E:$E,Conso!$G:$G,B35) -> 0 | D35: SIP - 10000 | E35: =SUMIFS(Conso!$D:$D,Conso!$G:$G,D35) -> 20000
B36: IT Refund | C36: =SUMIFS(Conso!$E:$E,Conso!$G:$G,B36) -> 7590 | D36: IT Refund | E36: =SUMIFS(Conso!$D:$D,Conso!$G:$G,D36) -> 0
... B59: Hostel Charges + Deposit | C59: =SUMIFS(Conso!$E:$E,Conso!$G:$G,B59) -> 0 | D59: Hostel Charges + Deposit | E59: =SUMIFS(Conso!$D:$D,Conso!$G:$G,D59) -> 21000
D62: By Closing Balances | E62: =C64-SUM(E7:E60) -> 173136.98 | G62: =K13 -> 173136.98
G63: =E62-G62 -> 4.6566129e-10
C64: =SUM(C7:C63) -> 4832378.2 | E64: =SUM(E7:E63) -> 4832378.2
C68: =SUM(C9:C61) -> 4598826.2 | E68: =SUM(E9:E61) -> 4659241.2
C69: =Conso!E2 -> 4598826.2 | E69: =Conso!D2 -> 4659241.2
C70: =C68-C69 -> 0 | E70: =E68-E69 -> 0
B76: Aayush Gupta Cash Account
B77: 01-04-2023 to 31-03-2024
B78: Particulars | C78: ₹ | D78: Particulars | E78: ₹
B79: Opening Balances | C79: 38700
D80: Household Expenses | E80: 23500
B81: Cash Withdrawal | C81: =E18+E38 -> 24000
D83: By Closing Balances | E83: =C85-SUM(E79:E82) -> 39200
C85: =SUM(C79:C83) -> 62700 | E85: =SUM(E79:E83) -> 62700
C89: =SUM(C29:C81) -> 15594865 | E89: =SUM(E29:E81) -> 15188396
