Workbook

Sheet Sheet2
B3: MPHASIS LIMITED
B4: WTMC 3 BLOCK B 1ST FLOOR, BAGMANE WORLD
B5: TECHNOLOGY, MARTHAHALLI OUTER RING RD,
B6: DODDENEKUNDI, BENGALURU, KARNATAKA - 560048
B7: Month | C7: Total Days | D7: Present Days | E7: Basic | F7: HRA | G7: LTA | H7: Special Allowance | I7: Variable Pay | J7: Other Earnings | K7: Gross Salary | L7: PF Employee | M7: Medical Insurance Premium | N7: PT | O7: TDS | P7: Deductions | Q7: Net Salary
B8: 45748 | C8: =EOMONTH(B8,0)-B8+1 -> 30 | D8: =C8 -> 30 | E8: =ROUND(E$22*$D8/$C8,0) -> 46667 | F8: =ROUND(F$22*$D8/$C8,0) -> 23333 | G8: =ROUND(G$22*$D8/$C8,0) -> 3000 | H8: =ROUND(H$22*$D8/$C8,0) -> 31650 | I8: 0 | J8: 0 | K8: =SUM(E8:J8) -> 104650 | L8: 5600 | M8: 0 | N8: 200 | O8: 0 | P8: =SUM(L8:O8) -> 5800 | Q8: =K8-P8 -> 98850
B9: =EOMONTH(B8,0)+1 -> 45778 | C9: =EOMONTH(B9,0)-B9+1 -> 31 | D9: =C9 -> 31 | E9: =ROUND(E$22*$D9/$C9,0) -> 46667 | F9: =ROUND(F$22*$D9/$C9,0) -> 23333 | G9: =ROUND(G$22*$D9/$C9,0) -> 3000 | H9: =ROUND(H$22*$D9/$C9,0) -> 31650 | I9: 3698 | J9: 0 | K9: =SUM(E9:J9) -> 108348 | L9: 5600 | M9: 0 | N9: 200 | O9: 0 | P9: =SUM(L9:O9) -> 5800 | Q9: =K9-P9 -> 102548
B10: =EOMONTH(B9,0)+1 -> 45809 | C10: =EOMONTH(B10,0)-B10+1 -> 30 | D10: =C10 -> 30 | E10: =ROUND(E$22*$D10/$C10,0) -> 46667 | F10: =ROUND(F$22*$D10/$C10,0) -> 23333 | G10: =ROUND(G$22*$D10/$C10,0) -> 3000 | H10: =ROUND(H$22*$D10/$C10,0) -> 31650 | I10: 0 | J10: 1000 | K10: =SUM(E10:J10) -> 105650 | L10: 5600 | M10: 0 | N10: 200 | O10: 0 | P10: =SUM(L10:O10) -> 5800 | Q10: =K10-P10 -> 99850
B11: =EOMONTH(B10,0)+1 -> 45839 | C11: =EOMONTH(B11,0)-B11+1 -> 31 | D11: =C11 -> 31 | E11: =ROUND(E$22*$D11/$C11,0) -> 46667 | F11: =ROUND(F$22*$D11/$C11,0) -> 23333 | G11: =ROUND(G$22*$D11/$C11,0) -> 3000 | H11: =ROUND(H$22*$D11/$C11,0) -> 31650 | I11: 0 | J11: 1000 | K11: =SUM(E11:J11) -> 105650 | L11: 5600 | M11: 0 | N11: 200 | O11: 0 | P11: =SUM(L11:O11) -> 5800 | Q11: =K11-P11 -> 99850
B12: =EOMONTH(B11,0)+1 -> 45870 | C12: =EOMONTH(B12,0)-B12+1 -> 31 | D12: =C12 -> 31 | E12: =ROUND(E$22*$D12/$C12,0) -> 46667 | F12: =ROUND(F$22*$D12/$C12,0) -> 23333 | G12: =ROUND(G$22*$D12/$C12,0) -> 3000 | H12: =ROUND(H$22*$D12/$C12,0) -> 31650 | I12: 16511 | J12: 0 | K12: =SUM(E12:J12) -> 121161 | L12: 5600 | M12: 0 | N12: 200 | O12: 2121 | P12: =SUM(L12:O12) -> 7921 | Q12: =K12-P12 -> 113240
B13: =EOMONTH(B12,0)+1 -> 45901 | C13: =EOMONTH(B13,0)-B13+1 -> 30 | D13: =C13 -> 30 | E13: =ROUND(E$22*$D13/$C13,0) -> 46667 | F13: =ROUND(F$22*$D13/$C13,0) -> 23333 | G13: =ROUND(G$22*$D13/$C13,0) -> 3000 | H13: =ROUND(H$22*$D13/$C13,0) -> 31650 | I13: 0 | J13: 0 | K13: =SUM(E13:J13) -> 104650 | L13: 5600 | M13: 0 | N13: 200 | O13: 145 | P13: =SUM(L13:O13) -> 5945 | Q13: =K13-P13 -> 98705
B14: =EOMONTH(B13,0)+1 -> 45931 | C14: =EOMONTH(B14,0)-B14+1 -> 31 | D14: =C14 -> 31 | E14: =ROUND(E$22*$D14/$C14,0) -> 46667 | F14: =ROUND(F$22*$D14/$C14,0) -> 23333 | G14: =ROUND(G$22*$D14/$C14,0) -> 3000 | H14: =ROUND(H$22*$D14/$C14,0) -> 31650 | I14: 0 | J14: 0 | K14: =SUM(E14:J14) -> 104650 | L14: 5600 | M14: 0 | N14: 200 | O14: 145 | P14: =SUM(L14:O14) -> 5945 | Q14: =K14-P14 -> 98705
B15: =EOMONTH(B14,0)+1 -> 45962 | C15: =EOMONTH(B15,0)-B15+1 -> 30 | D15: =C15 -> 30 | E15: =ROUND(E$22*$D15/$C15,0) -> 46667 | F15: =ROUND(F$22*$D15/$C15,0) -> 23333 | G15: =ROUND(G$22*$D15/$C15,0) -> 3000 | H15: =ROUND(H$22*$D15/$C15,0) -> 31650 | I15: 14000 | J15: 0 | K15: =SUM(E15:J15) -> 118650 | L15: 5600 | M15: 0 | N15: 200 | O15: 4802 | P15: =SUM(L15:O15) -> 10602 | Q15: =K15-P15 -> 108048
B16: =EOMONTH(B15,0)+1 -> 45992 | C16: =EOMONTH(B16,0)-B16+1 -> 31 | D16: =C16 -> 31 | E16: =ROUND(E$22*$D16/$C16,0) -> 46667 | F16: =ROUND(F$22*$D16/$C16,0) -> 23333 | G16: =ROUND(G$22*$D16/$C16,0) -> 3000 | H16: =ROUND(H$22*$D16/$C16,0) -> 31650 | I16: 0 | J16: 0 | K16: =SUM(E16:J16) -> 104650 | L16: 5600 | M16: 0 | N16: 200 | O16: 2620 | P16: =SUM(L16:O16) -> 8420 | Q16: =K16-P16 -> 96230
B17: =EOMONTH(B16,0)+1 -> 46023 | C17: =EOMONTH(B17,0)-B17+1 -> 31 | D17: =C17 -> 31 | E17: =ROUND(E$22*$D17/$C17,0) -> 46667 | F17: =ROUND(F$22*$D17/$C17,0) -> 23333 | G17: =ROUND(G$22*$D17/$C17,0) -> 3000 | H17: =ROUND(H$22*$D17/$C17,0) -> 31650 | I17: 0 | J17: 0 | K17: =SUM(E17:J17) -> 104650 | L17: 5600 | M17: 0 | N17: 200 | O17: 2619 | P17: =SUM(L17:O17) -> 8419 | Q17: =K17-P17 -> 96231
B18: =EOMONTH(B17,0)+1 -> 46054 | C18: =EOMONTH(B18,0)-B18+1 -> 28 | D18: =C18 -> 28 | E18: =ROUND(E$22*$D18/$C18,0) -> 46667 | F18: =ROUND(F$22*$D18/$C18,0) -> 23333 | G18: =ROUND(G$22*$D18/$C18,0) -> 3000 | H18: =ROUND(H$22*$D18/$C18,0) -> 31650 | I18: 13563 | J18: 0 | K18: =SUM(E18:J18) -> 118213 | L18: 5600 | M18: 0 | N18: 300 | O18: 10733 | P18: =SUM(L18:O18) -> 16633 | Q18: =K18-P18 -> 101580
B19: =EOMONTH(B18,0)+1 -> 46082 | C19: =EOMONTH(B19,0)-B19+1 -> 31 | D19: =C19 -> 31 | E19: =ROUND(E$22*$D19/$C19,0) -> 46667 | F19: =ROUND(F$22*$D19/$C19,0) -> 23333 | G19: =ROUND(G$22*$D19/$C19,0) -> 3000 | H19: =ROUND(H$22*$D19/$C19,0) -> 31650 | I19: 0 | J19: 0 | K19: =SUM(E19:J19) -> 104650 | L19: 5600 | M19: 0 | N19: 200 | O19: 8618 | P19: =SUM(L19:O19) -> 14418 | Q19: =K19-P19 -> 90232
E20: =SUM(E8:E19) -> 560004 | F20: =SUM(F8:F19) -> 279996 | G20: =SUM(G8:G19) -> 36000 | H20: =SUM(H8:H19) -> 379800 | I20: =SUM(I8:I19) -> 47772 | J20: =SUM(J8:J19) -> 2000 | K20: =SUM(K8:K19) -> 1305572 | L20: =SUM(L8:L19) -> 67200 | ... Q20: =SUM(Q8:Q19) -> 1204069
O21: 31803
E22: 46667 | F22: 23333 | G22: 3000 | H22: 31650 | O22: =O20-O21 -> 0

Sheet Sheet1
B1: Salary structure
B2: FY 2025-26
B4: A) Taxable Income
B5: (i) Monthly Income
B6: Pay Items | C6: 45748 | D6: =EOMONTH(C6,0)+1 -> 45778 | E6: =EOMONTH(D6,0)+1 -> 45809 | F6: =EOMONTH(E6,0)+1 -> 45839 | G6: =EOMONTH(F6,0)+1 -> 45870 | H6: =EOMONTH(G6,0)+1 -> 45901 | I6: =EOMONTH(H6,0)+1 -> 45931 | J6: =EOMONTH(I6,0)+1 -> 45962 | K6: =EOMONTH(J6,0)+1 -> 45992 | ... N6: =EOMONTH(M6,0)+1 -> 46082 | O6: Total
B7: Basic Pay | C7: {=TRANSPOSE(Sheet2!E8:H8)} -> 46667 | D7: {=TRANSPOSE(Sheet2!E9:H9)} -> 46667 | E7: {=TRANSPOSE(Sheet2!E10:H10)} -> 46667 | F7: {=TRANSPOSE(Sheet2!E11:H11)} -> 46667 | G7: {=TRANSPOSE(Sheet2!E12:H12)} -> 46667 | H7: {=TRANSPOSE(Sheet2!E13:H13)} -> 46667 | I7: {=TRANSPOSE(Sheet2!E14:H14)} -> 46667 | J7: {=TRANSPOSE(Sheet2!E15:H15)} -> 46667 | K7: {=TRANSPOSE(Sheet2!E16:H16)} -> 46667 | L7: {=TRANSPOSE(Sheet2!E17:H17)} -> 46667 | M7: {=TRANSPOSE(Sheet2!E18:H18)} -> 46667 | N7: {=TRANSPOSE(Sheet2!E19:H19)} -> 46667 | O7: =SUM(C7:N7) -> 560004
B8: HRA | C8: 23333 | D8: 23333 | E8: 23333 | F8: 23333 | G8: 23333 | H8: 23333 | I8: 23333 | J8: 23333 | K8: 23333 | L8: 23333 | M8: 23333 | N8: 23333 | O8: =SUM(C8:N8) -> 279996
B9: Special Allowance | C9: 3000 | D9: 3000 | E9: 3000 | F9: 3000 | G9: 3000 | H9: 3000 | I9: 3000 | J9: 3000 | K9: 3000 | L9: 3000 | M9: 3000 | N9: 3000 | O9: =SUM(C9:N9) -> 36000
B10: LTA | C10: 31650 | D10: 31650 | E10: 31650 | F10: 31650 | G10: 31650 | H10: 31650 | I10: 31650 | J10: 31650 | K10: 31650 | L10: 31650 | M10: 31650 | N10: 31650 | O10: =SUM(C10:N10) -> 379800
B11: Other Earnings | C11: {=TRANSPOSE(Sheet2!J8:J19)} -> 0 | D11: 0 | E11: 1000 | F11: 1000 | G11: 0 | H11: 0 | I11: 0 | J11: 0 | K11: 0 | L11: 0 | M11: 0 | N11: 0 | O11: =SUM(C11:N11) -> 2000
B12: Total | C12: =SUM(C7:C11) -> 104650 | D12: =SUM(D7:D11) -> 104650 | E12: =SUM(E7:E11) -> 105650 | F12: =SUM(F7:F11) -> 105650 | G12: =SUM(G7:G11) -> 104650 | H12: =SUM(H7:H11) -> 104650 | I12: =SUM(I7:I11) -> 104650 | J12: =SUM(J7:J11) -> 104650 | ... O12: =SUM(O7:O11) -> 1257800
B14: (ii) Adhoc Income
B15: =B6 -> Pay Items | C15: =C6 -> 45748 | D15: =D6 -> 45778 | E15: =E6 -> 45809 | F15: =F6 -> 45839 | G15: =G6 -> 45870 | H15: =H6 -> 45901 | I15: =I6 -> 45931 | ... O15: =O6 -> Total
B16: Variable Pay | C16: {=TRANSPOSE(Sheet2!I8:I19)} -> 0 | D16: 3698 | E16: 0 | F16: 0 | G16: 16511 | H16: 0 | I16: 0 | J16: 14000 | K16: 0 | L16: 0 | M16: 13563 | N16: 0 | O16: =SUM(C16:N16) -> 47772
B17: Total | C17: =SUM(C16:C16) -> 0 | D17: =SUM(D16:D16) -> 3698 | E17: =SUM(E16:E16) -> 0 | F17: =SUM(F16:F16) -> 0 | G17: =SUM(G16:G16) -> 16511 | H17: =SUM(H16:H16) -> 0 | I17: =SUM(I16:I16) -> 0 | J17: =SUM(J16:J16) -> 14000 | ... O17: =SUM(O16:O16) -> 47772
B19: B) Deduction
B20: =B15 -> Pay Items | C20: =C15 -> 45748 | D20: =D15 -> 45778 | E20: =E15 -> 45809 | F20: =F15 -> 45839 | G20: =G15 -> 45870 | H20: =H15 -> 45901 | I20: =I15 -> 45931 | ... O20: =O15 -> Total
B21: Provident Fund | C21: {=TRANSPOSE(Sheet2!L8:L19)} -> 5600 | D21: 5600 | E21: 5600 | F21: 5600 | G21: 5600 | H21: 5600 | I21: 5600 | J21: 5600 | K21: 5600 | L21: 5600 | M21: 5600 | N21: 5600 | O21: =SUM(C21:N21) -> 67200
B22: Prof Tax | C22: {=TRANSPOSE(Sheet2!N8:N19)} -> 200 | D22: 200 | E22: 200 | F22: 200 | G22: 200 | H22: 200 | I22: 200 | J22: 200 | K22: 200 | L22: 200 | M22: 300 | N22: 200 | O22: =SUM(C22:N22) -> 2500
B23: TDS | C23: {=TRANSPOSE(Sheet2!O8:O19)} -> 0 | D23: 0 | E23: 0 | F23: 0 | G23: 2121 | H23: 145 | I23: 145 | J23: 4802 | K23: 2620 | L23: 2619 | M23: 10733 | N23: 8618 | O23: =SUM(C23:N23) -> 31803
B24: Total | C24: =SUM(C21:C23) -> 5800 | D24: =SUM(D21:D23) -> 5800 | E24: =SUM(E21:E23) -> 5800 | F24: =SUM(F21:F23) -> 5800 | G24: =SUM(G21:G23) -> 7921 | H24: =SUM(H21:H23) -> 5945 | I24: =SUM(I21:I23) -> 5945 | J24: =SUM(J21:J23) -> 10602 | ... O24: =SUM(O21:O23) -> 101503
B26: C) Perquisites
B27: PFM | C27: 0 | D27: 0 | E27: 0 | F27: 0 | G27: 0 | H27: 0 | I27: 0 | J27: 0 | K27: 0 | L27: 0 | M27: 0 | N27: 0 | O27: =SUM(C27:N27) -> 0 | S27: 0-4 | T27: 400000 | U27: 0 | V27: =T27*U27 -> 0
B28: Total | C28: =SUM(C27) -> 0 | D28: =SUM(D27) -> 0 | E28: =SUM(E27) -> 0 | F28: =SUM(F27) -> 0 | G28: =SUM(G27) -> 0 | H28: =SUM(H27) -> 0 | I28: =SUM(I27) -> 0 | J28: =SUM(J27) -> 0 | ... O28: =SUM(O27) -> 0 | S28: 4-8 | T28: 400000 | U28: 0.05 | V28: =T28*U28 -> 20000
S29: 8-12 | T29: 400000 | U29: 0.1 | V29: =T29*U29 -> 40000
B30: D) Gross Salary (A+B+C) | C30: =C12+C17 -> 104650 | D30: =D12+D17 -> 108348 | E30: =E12+E17 -> 105650 | F30: =F12+F17 -> 105650 | G30: =G12+G17 -> 121161 | H30: =H12+H17 -> 104650 | I30: =I12+I17 -> 104650 | J30: =J12+J17 -> 118650 | ... O30: =O12+O17 -> 1305572 | S30: 12-16 | T30: 400000 | U30: 0.15 | V30: =T30*U30 -> 60000
B31: Standard Deduction | O31: -75000 | S31: 16-20 | T31: 400000 | U31: 0.2 | V31: =T31*U31 -> 80000
B32: Net Income | O32: =SUM(O30:O31) -> 1230572 | S32: 20-24 | T32: 400000 | U32: 0.25 | V32: =T32*U32 -> 100000
B33: Tax | O33: =ROUNDUP(IF(O32>2400000,(300000+(O32-2400000)*30%),IF(O32>2000000,200000+(O32-2000000)*25%,IF(O32>1600000,120000+(O32-1600000)*20%,IF(O32>1200000,60000+(O32-1200000)*15%,IF(O32>800000,20000+(O32-800000)*10%,IF(O32>400000,(O32-400000)*5%,0)))))),0) -> 64586 | Q33: 70589 | S33: >24 | U33: 0.3 | V33: =T33*U33 -> 0
B34: Rebate | O34: =-IF(O32<1200000,MIN(O33,60000),0) -> 0 | Q34: 1200000
B35: Net Tax | O35: =SUM(O33:O34) -> 64586 | Q35: =SUM(Q33:Q34) -> 1270589
B36: Marginal Relief | O36: =-IF(O33>(O32-1200000),O33-(O32-1200000),0) -> -34014 | Q36: =Q35-O32 -> 40017
B37: Net Tax | O37: =SUM(O35:O36) -> 30572
B38: HEC | N38: 0.04 | O38: =O37*N38 -> 1222.88
B39: Total TDS Payable | O39: =SUM(O37:O38) -> 31794.88
