Workbook

Sheet HDFC Bank
B1: HDFC Bank Narration Sheet
B2: Colour Legend of Categories:
B3: No specific category colours used in this sheet.
A5: Date | B5: Particulars | C5: Ref | D5: Value_Date | E5: DR | F5: CR | G5: Balance | H5: Auto_Narration | I5: Account_Head | J5: Confidence
B6: Salary | E6: 50000 | F6: 0 | H6: What is this? | I6: Suspense | J6: 0

Sheet For Tally
A1: TX Date | B1: Date | C1: DR | D1: CR | E1: Narration | F1: Confidence | G1: Account Head | H1: Account No | I1: Particulars | J1: Bank | K1: Duplicate | L1: Pivot Category
C2: 50000 | D2: 0 | E2: What is this? | F2: 0 | G2: Suspense | H2: 123456789 | I2: Salary | J2: HDFC Bank | L2: General/Other Spends

Sheet Conso
A1: Test Entity
A2: Account of Statements from FY26 | D2: =SUBTOTAL(9, D5:D5) | E2: =SUBTOTAL(9, E5:E5) | F2: =E2-D2
A4: TX Date | B4: Particulars | C4: Ref | D4: DR | E4: CR | F4: Balance | G4: Account Head | H4: Account No
B5: Salary | D5: 50000 | E5: 0 | G5: Suspense | H5: 123456789

Sheet Bank Summary
A1: All Banks
A2: Test Entity Bank Summary
A3: FY26
A5: Narration | B5: Total Credit (₹) | C5: Narration | D5: Total Debit (₹)
A6: What is this? | B6: =SUMIFS('For Tally'!D:D, 'For Tally'!E:E, A6) | C6: What is this? | D6: =SUMIFS('For Tally'!C:C, 'For Tally'!E:E, C6)
A7: TOTAL | B7: =SUM(B5:B6) | C7: TOTAL | D7: =SUM(D5:D6) | E7: Net | F7: =B7-D7
A9: Opening & Closing Balances
A10: Account | B10: Opening Balance (₹) | C10: Closing Balance (₹)
A11: 123456789 | B11: 0 | C11: =B11 + SUMIFS('For Tally'!D:D, 'For Tally'!H:H, A11) - SUMIFS('For Tally'!C:C, 'For Tally'!H:H, A11)
A13: Confidence Distribution
A14: Band | B14: Count | C14: % of Total
A15: High (≥ 0.85) — Confident | B15: =COUNTIF('For Tally'!F:F, ">=0.85") | C15: =B15/SUM(B15:B17)
A16: Medium (0.60–0.84) — Review | B16: =COUNTIFS('For Tally'!F:F, ">=0.60", 'For Tally'!F:F, "<0.85") | C16: =B16/SUM(B15:B17)
A17: Low (< 0.60) — Needs attention | B17: =COUNTIF('For Tally'!F:F, "<0.60") | C17: =B17/SUM(B15:B17)

Sheet Monthly Pivot
A1: Unified Monthly Spend & Income Pivot
A3: Bank Filter Toggles: | B3: HDFC Bank
B4: TRUE
B5: =IF(B4, B3, "")
A7: PAYMENTS / EXPENSES (Bank + CC) | B7: TOTAL
A8: Broadband & WiFi | B8: =SUM(B8:A8)
A9: Groceries & Household | B9: =SUM(B9:A9)
A10: Food & Dining | B10: =SUM(B10:A10)
A11: Rent | B11: =SUM(B11:A11)
A12: Travel & Commute | B12: =SUM(B12:A12)
A13: Fuel | B13: =SUM(B13:A13)
A14: Transport & Automotive | B14: =SUM(B14:A14)
A15: Healthcare & Medical | B15: =SUM(B15:A15)
A16: Life Insurance | B16: =SUM(B16:A16)
A17: Health Insurance | B17: =SUM(B17:A17)
A18: Subscriptions & Services | B18: =SUM(B18:A18)
A19: Utilities & Mobile | B19: =SUM(B19:A19)
... A24: General/Other Spends | B24: =SUM(B24:A24)
A25: EXPENSE TOTAL | B25: =SUM(B8:B24)
A27: RECEIPTS / INCOME (Bank) | B27: TOTAL
A28: Salary | B28: =SUM(B28:A28)
A29: Freelance & Business Income | B29: =SUM(B29:A29)
A30: Dividend Income | B30: =SUM(B30:A30)
A31: Bank Interest | B31: =SUM(B31:A31)
A32: Investment Inflows (MF/Stocks) | B32: =SUM(B32:A32)
A33: Refunds & Reversals | B33: =SUM(B33:A33)
A34: Personal Inflows / Transfers | B34: =SUM(B34:A34)
A35: INFLOW TOTAL | B35: =SUM(B28:B34)
A37: SELF-TRANSFERS (Contra) | B37: TOTAL
A38: Self-Transfer (Contra) | B38: =SUM(B38:A38)
A39: CONTRA TOTAL | B39: =SUM(B38:B38)

Sheet Colour Legend
B2: Workbook Colour Legend
B5: INCOME & INFLOWS | C5: Colour Code | D5: Description
B7: Salary | C7: Sample Fill | D7: Salary Credit (Mphasis)
B8: Bank Interest | C8: Sample Fill | D8: Interest earned on Savings accounts
B9: Dividend Income | C9: Sample Fill | D9: Dividend payout from shares
B10: Annuity Income | C10: Sample Fill | D10: Annuity credits (HDFC Life)
B11: Income Tax Refund | C11: Sample Fill | D11: Income Tax Refund from Department
B12: MF Redemption | C12: Sample Fill | D12: Inflows from selling Mutual Funds
B13: Upwork Income | C13: Sample Fill | D13: Inward remittances from Upwork freelancing
B14: Cash Deposit | C14: Sample Fill | D14: Cash deposits made at CDM / Branch
B15: Freelance Income | C15: Sample Fill | D15: Freelance work escrow payouts
B16: Cashback - BHIM | C16: Sample Fill | D16: Cashback rewards earned on BHIM app
B17: Cashback - Kiwi | C17: Sample Fill | D17: Cashback rewards earned on Kiwi app
... B65: What is this? | C65: Sample Fill | D65: Suspense items requiring review (Suspense)
