Workbook

Sheet AXIS
B1: Axis Bank Narration Sheet
B2: Colour Legend of Categories:
B3: Salary | C3: Contra - SBI | D3: UPI - IRCTC | E3: Contra - Kotak | F3: UPI Payment
B4: Credit Card Bill Payment (CRED) | C4: Received - Megha Gupta | D4: Transfer - Megha Gupta | E4: Rent Payment (via CRED) | F4: Bank Interest
B5: NEFT Transfer | C5: UPI - Fuel (HPCL) | D5: UPI - Star Bazaar | E5: UPI - Nandini Dairy | F5: UPI - Fresh Produce
B6: UPI - Pharmacy | C6: Transfer - Ajay Gupta | D6: Transfer - Archit Gupta | E6: Received - Ajay Gupta | F6: UPI - CRED
B7: Vehicle Service | C7: Food & Dining / Hotel | D7: Entertainment | E7: UPI - Fuel | F7: Rent
B8: Health Insurance | C8: UPI - CRED Wallet | D8: Toll / FASTag | E8: UPI - Amazon | F8: Shopping - Jewellery
B9: Income Tax Payment | C9: Security Deposit | D9: UPI - Zepto | E9: Security Deposit Return | F9: UPI - BharatPe
B10: UPI - DMart | C10: Received - Ret | D10: Received - Archit Gupta | E10: UPI - Flipkart | F10: UPI - Navi
A12: Date | B12: Particulars | C12: Ref | D12: Value_Date | E12: DR | F12: CR | G12: Balance | H12: Beneficiary | I12: Human_Narration | J12: Auto_Narration | K12: Account_Head | L12: Confidence | M12: Match
A13: 45749 | B13: Salary For the Month of Mar 2025 | C13: - | D13: 45749 | E13: 0 | F13: 66897 | G13: 84253.03 | I13: Salary | J13: Salary | K13: Salary | L13: 0.95 | M13: [MATCH]
A14: 45749 | B14: NEFT/MB/AXOMB09202414101/AAYUSH KUMAR GUPTA/STATE BANK OF INDIA/ | C14: - | D14: 45749 | E14: 1 | F14: 0 | G14: 84252.03 | I14: UPI | J14: Contra - SBI | K14: SBI 1227 | L14: 0.9 | M14: [MATCH]
A15: 45749 | B15: UPI/P2A/765226990925/AAYUSH KUMAR GUPTA /UPI/State Bank Of India | C15: - | D15: 45749 | E15: 1 | F15: 0 | G15: 84251.03 | I15: UPI | J15: Contra - SBI | K15: SBI 1227 | L15: 0.9 | M15: [MATCH]
A16: 45749 | B16: UPI/P2A/765382250925/AAYUSH KUMAR GUPTA /UPI/State Bank Of India | C16: - | D16: 45749 | E16: 40000 | F16: 0 | G16: 44251.03 | I16: Transfer to SBI self | J16: Contra - SBI | K16: SBI 1227 | L16: 0.9 | M16: [DIFF]
A17: 45757 | B17: UPI/P2M/100335047021/Autope Payment Soluti/Paymen/HDFC BANK LTD | C17: - | D17: 45757 | E17: 5704.5 | F17: 0 | G17: 38546.53 | I17: UPI | J17: UPI - IRCTC | K17: Travel | L17: 0.88 | M17: [MATCH]
A18: 45763 | B18: NEFT/MB/AXOMB10626155334/AAYUSH KUMAR GUPTA/STATE BANK OF INDIA/FAMILY | C18: - | D18: 45763 | E18: 25000 | F18: 0 | G18: 13546.53 | I18: Transfer to SBI self | J18: Contra - SBI | K18: SBI 1227 | L18: 0.9 | M18: [DIFF]
A19: 45779 | B19: NEFT/HDFCH00213942923/MPHASIS LIMITED/HDFC BANK/0001SALARYAPR2025 | C19: - | D19: 45779 | E19: 0 | F19: 98850 | G19: 112396.53 | I19: Salary | J19: Salary | K19: Salary | L19: 0.97 | M19: [MATCH]
A20: 45779 | B20: UPI/P2A/294187471225/AAYUSH KUMAR GUPTA /UPI/State Bank Of India | C20: - | D20: 45779 | E20: 1 | F20: 0 | G20: 112395.53 | I20: UPI | J20: Contra - SBI | K20: SBI 1227 | L20: 0.9 | M20: [MATCH]
A21: 45779 | B21: UPI/P2A/294427061225/AAYUSH KUMAR GUPTA /UPI/Kotak Mahindra Bank | C21: - | D21: 45779 | E21: 1 | F21: 0 | G21: 112394.53 | I21: UPI | J21: Contra - Kotak | K21: KOTAK 0333 | L21: 0.9 | M21: [MATCH]
A22: 45779 | B22: UPI/P2A/294526291225/AAYUSH KUMAR GUPTA /UPI/Kotak Mahindra Bank | C22: - | D22: 45779 | E22: 65000 | F22: 0 | G22: 47394.53 | I22: Transfer to Kotak self | J22: Contra - Kotak | K22: KOTAK 0333 | L22: 0.9 | M22: [DIFF]
A23: 45780 | B23: UPI/P2A/415981531235/AAYUSH KUMAR GUPTA /UPI/Kotak Mahindra Bank | C23: - | D23: 45780 | E23: 7000 | F23: 0 | G23: 40394.53 | I23: Transfer to Kotak self | J23: Contra - Kotak | K23: KOTAK 0333 | L23: 0.9 | M23: [DIFF]
A24: 45789 | B24: UPI/P2M/477823321325/Krishna Sagar /UPI/YES BANK LIMITED YBS | C24: - | D24: 45789 | E24: 60 | F24: 0 | G24: 40334.53 | H24: Krishna Sagar | I24: UPI | J24: UPI Payment | K24: Personal | L24: 0.55 | M24: [MATCH]
A25: 45789 | B25: UPI/P2A/478925241325/KETAN YADAV SO KRISHN/UPI/UNION BANK OF INDIA | C25: - | D25: 45789 | E25: 125 | F25: 0 | G25: 40209.53 | H25: Ketan Yadav So Krishn | I25: UPI | J25: UPI Payment | K25: Personal | L25: 0.55 | M25: [MATCH]
A26: 45798 | B26: UPI/P2M/439678151415/CRED Club /paymen/AXIS BANK | C26: - | D26: 45798 | E26: 1000 | F26: 0 | G26: 39209.53 | I26: UPI | J26: Credit Card Bill Payment (CRED) | K26: Credit Card | L26: 0.85 | M26: [DIFF]
A27: 45799 | B27: UPI/P2M/544150001425/CRED Club /paymen/AXIS BANK | C27: - | D27: 45799 | E27: 1240.66 | F27: 0 | G27: 37968.87 | I27: UPI | J27: Credit Card Bill Payment (CRED) | K27: Credit Card | L27: 0.85 | M27: [DIFF]
A28: 45806 | B28: UPI/P2A/514924201264/MEGHA GUP/HDFC BANK/Paid via/ | C28: - | D28: 45806 | E28: 0 | F28: 1001 | G28: 38969.87 | I28: UPI | J28: Received - Megha Gupta | K28: Megha Gupta | L28: 0.85 | M28: [DIFF]
A29: 45806 | B29: UPI/P2A/445834401495/MEGHA GUPTA /UPI/HDFC BANK LTD | C29: - | D29: 45806 | E29: 1001 | F29: 0 | G29: 37968.87 | I29: UPI | J29: Transfer - Megha Gupta | K29: Megha Gupta | L29: 0.85 | M29: [DIFF]
A30: 45810 | B30: NEFT/HDFCH00273980424/MPHASIS LIMITED/HDFC BANK/0001SALARYMAY2025 | C30: - | D30: 45810 | E30: 0 | F30: 102548 | G30: 140516.87 | I30: Salary | J30: Salary | K30: Salary | L30: 0.97 | M30: [MATCH]
A31: 45810 | B31: UPI/P2M/858334901535/CRED RENT /paymen/AXIS BANK | C31: - | D31: 45810 | E31: 23000 | F31: 0 | G31: 117516.87 | J31: Rent Payment (via CRED) | K31: Rent | L31: 0.88 | M31: N/A
A32: 45810 | B32: UPI/P2A/868844991535/AAYUSH KUMAR GUPTA /UPI/Kotak Mahindra Bank | C32: - | D32: 45810 | E32: 5000 | F32: 0 | G32: 112516.87 | J32: Contra - Kotak | K32: KOTAK 0333 | L32: 0.9 | M32: N/A
A33: 45810 | B33: UPI/P2A/869103531535/AAYUSH KUMAR GUPTA /UPI/Kotak Mahindra Bank | C33: - | D33: 45810 | E33: 40000 | F33: 0 | G33: 72516.87 | J33: Contra - Kotak | K33: KOTAK 0333 | L33: 0.9 | M33: N/A
A34: 45821 | B34: UPI/P2A/264644071645/AAYUSH KUMAR GUPTA /UPI/Kotak Mahindra Bank | C34: - | D34: 45821 | E34: 15000 | F34: 0 | G34: 57516.87 | J34: Contra - Kotak | K34: KOTAK 0333 | L34: 0.9 | M34: N/A
A35: 45835 | B35: UPI/P2A/118805941785/Miss. MEGHA GUPTA /15k hb/CENTRAL BANK OF INDI | C35: - | D35: 45835 | E35: 15000 | F35: 0 | G35: 42516.87 | J35: Transfer - Megha Gupta | K35: Megha Gupta | L35: 0.85 | M35: N/A
A36: 45839 | B36: SB:915010020334307:Int.Pd:01-04-2025 to 30-06-2025 | C36: - | D36: 45839 | E36: 0 | F36: 291 | G36: 42807.87 | J36: Bank Interest | K36: Bank Interest | L36: 0.93 | M36: N/A
A37: 45839 | B37: NEFT/HDFCH00331835485/MPHASIS LIMITED/HDFC BANK/0001SALARYJUN2025 | C37: - | D37: 45839 | E37: 0 | F37: 98850 | G37: 141657.87 | J37: Salary | K37: Salary | L37: 0.97 | M37: N/A
A38: 45840 | B38: UPI/P2A/107436117872/Miss MEGH/CENTRAL B/UPI/ | C38: - | D38: 45840 | E38: 0 | F38: 30000 | G38: 171657.87 | J38: Received - Megha Gupta | K38: Megha Gupta | L38: 0.85 | M38: N/A
A39: 45840 | B39: UPI/P2A/774946241835/Miss. MEGHA GUPTA /UPI/CENTRAL BANK OF INDI | C39: - | D39: 45840 | E39: 40000 | F39: 0 | G39: 131657.87 | J39: Transfer - Megha Gupta | K39: Megha Gupta | L39: 0.85 | M39: N/A
A40: 45840 | B40: UPI/P2A/107437679484/Miss MEGH/CENTRAL B/UPI/ | C40: - | D40: 45840 | E40: 0 | F40: 40000 | G40: 171657.87 | J40: Received - Megha Gupta | K40: Megha Gupta | L40: 0.85 | M40: N/A
A41: 45841 | B41: UPI/P2M/820086391845/CRED RENT /paymen/AXIS BANK | C41: - | D41: 45841 | E41: 23000 | F41: 0 | G41: 148657.87 | J41: Rent Payment (via CRED) | K41: Rent | L41: 0.88 | M41: N/A
A42: 45842 | B42: NEFT/CITIN25589422876/PAYPAL PAYMENTS PL INR FBO C/CITI BANK/PPR-MISC-BRGPG8066GPPR-MISC-B | C42: - | D42: 45842 | E42: 0 | F42: 1.04 | G42: 148658.91 | J42: NEFT Transfer | K42: Transfer | L42: 0.7 | M42: N/A
... A52: 45857 | B52: UPI/P2M/556672044636/Nandini /Paid v/YES BANK LIMITED YBS | C52: - | D52: 45857 | E52: 108 | F52: 0 | G52: 103328.95 | J52: UPI - Nandini Dairy | K52: Groceries | L52: 0.82 | M52: N/A
A53: 45858 | B53: UPI/P2A/520188482857/ROHITH K N /Paid v/INDIAN OVERSEAS BANK | C53: - | D53: 45858 | E53: 148 | F53: 0 | G53: 103180.95 | H53: Rohith K N | J53: UPI Payment | K53: Personal | L53: 0.55 | M53: N/A
A54: 45858 | B54: UPI/P2A/520188629552/CHHOTELAL MAHATO /Paid v/KARNATAKA BANK LTD | C54: - | D54: 45858 | E54: 133 | F54: 0 | G54: 103047.95 | H54: Chhotelal Mahato | J54: UPI Payment | K54: Personal | L54: 0.55 | M54: N/A
A55: 45858 | B55: UPI/P2M/556709719525/FAMILY FRUITS AND VE /Paid v/IDFC FIRST BANK LTD | C55: - | D55: 45858 | E55: 145 | F55: 0 | G55: 102902.95 | J55: UPI - Fresh Produce | K55: Groceries | L55: 0.82 | M55: N/A
A56: 45860 | B56: UPI/P2M/520391364094/CRED Club /paymen/AXIS BANK | C56: - | D56: 45860 | E56: 1000 | F56: 0 | G56: 101902.95 | J56: Credit Card Bill Payment (CRED) | K56: Credit Card | L56: 0.85 | M56: N/A
A57: 45861 | B57: UPI/P2M/520491571499/CRED Club /paymen/AXIS BANK | C57: - | D57: 45861 | E57: 1032.43 | F57: 0 | G57: 100870.52 | J57: Credit Card Bill Payment (CRED) | K57: Credit Card | L57: 0.85 | M57: N/A
A58: 45861 | B58: UPI/P2A/520491680942/Miss. MEGHA GUPTA /Paid v/CENTRAL BANK OF INDI | C58: - | D58: 45861 | E58: 5000 | F58: 0 | G58: 95870.52 | J58: Transfer - Megha Gupta | K58: Megha Gupta | L58: 0.85 | M58: N/A
A59: 45862 | B59: UPI/P2A/520592762601/Miss. MEGHA GUPTA /Paid v/CENTRAL BANK OF INDI | C59: - | D59: 45862 | E59: 15000 | F59: 0 | G59: 80870.52 | J59: Transfer - Megha Gupta | K59: Megha Gupta | L59: 0.85 | M59: N/A
A60: 45862 | B60: UPI/P2A/551107842055/AAYUSH KUMAR GUPTA /UPI/Kotak Mahindra Bank | C60: - | D60: 45862 | E60: 15000 | F60: 0 | G60: 65870.52 | J60: Contra - Kotak | K60: KOTAK 0333 | L60: 0.9 | M60: N/A
A61: 45863 | B61: UPI/P2A/520694490982/Mrs G PAVITHRA /Paid v/INDIAN BANK | C61: - | D61: 45863 | E61: 100 | F61: 0 | G61: 65770.52 | H61: Mrs G Pavithra | J61: UPI Payment | K61: Personal | L61: 0.55 | M61: N/A
A62: 45864 | B62: UPI/P2A/810935882075/AAYUSH KUMAR GUPTA /UPI/Kotak Mahindra Bank | C62: - | D62: 45864 | E62: 7000 | F62: 0 | G62: 58770.52 | J62: Contra - Kotak | K62: KOTAK 0333 | L62: 0.9 | M62: N/A
A63: 45864 | B63: UPI/P2M/520780932788/MANIBHADRA CREATIONS /Paid v/AXIS BANK | C63: - | D63: 45864 | E63: 220 | F63: 0 | G63: 58550.52 | H63: Manibhadra Creations | J63: UPI Payment | K63: Personal | L63: 0.55 | M63: N/A
A64: 45867 | B64: UPI/P2M/521099427787/CENTRO Bengaluru TE0Q/Paid v/JIO PAYMENTS BANK LT | C64: - | D64: 45867 | E64: 471.75 | F64: 0 | G64: 58078.77 | H64: Centro Bengaluru Te0Q | J64: UPI Payment | K64: Personal | L64: 0.55 | M64: N/A
A65: 45870 | B65: NEFT/HDFCH00395391317/MPHASIS LIMITED/HDFC BANK/0001SALARYJUL2025 | C65: - | D65: 45870 | E65: 0 | F65: 99850 | G65: 157928.77 | J65: Salary | K65: Salary | L65: 0.97 | M65: N/A
A66: 45870 | B66: UPI/P2M/557903285414/IRCTC CF /IRCTC/HDFC BANK LTD | C66: - | D66: 45870 | E66: 442.25 | F66: 0 | G66: 157486.52 | J66: UPI - IRCTC | K66: Travel | L66: 0.68 | M66: N/A
A67: 45870 | B67: UPI/P2A/728499832135/AAYUSH KUMAR GUPTA /UPI/Kotak Mahindra Bank | C67: - | D67: 45870 | E67: 37000 | F67: 0 | G67: 120486.52 | J67: Contra - Kotak | K67: KOTAK 0333 | L67: 0.9 | M67: N/A
A68: 45870 | B68: UPI/P2M/557903541890/CRED RENT /paymen/AXIS BANK | C68: - | D68: 45870 | E68: 23000 | F68: 0 | G68: 97486.52 | J68: Rent Payment (via CRED) | K68: Rent | L68: 0.88 | M68: N/A
A69: 45876 | B69: UPI/P2A/558513441987/MEGHA GUPTA /Paid v/HDFC BANK LTD | C69: - | D69: 45876 | E69: 10000 | F69: 0 | G69: 87486.52 | J69: Transfer - Megha Gupta | K69: Megha Gupta | L69: 0.85 | M69: N/A
A70: 45877 | B70: UPI/P2A/802551602205/AAYUSH KUMAR GUPTA /UPI/Kotak Mahindra Bank | C70: - | D70: 45877 | E70: 10000 | F70: 0 | G70: 77486.52 | J70: Contra - Kotak | K70: KOTAK 0333 | L70: 0.9 | M70: N/A
A71: 45878 | B71: UPI/P2A/892339792215/AAYUSH KUMAR GUPTA /UPI/Kotak Mahindra Bank | C71: - | D71: 45878 | E71: 7000 | F71: 0 | G71: 70486.52 | J71: Contra - Kotak | K71: KOTAK 0333 | L71: 0.9 | M71: N/A
A72: 45878 | B72: UPI/P2M/558715667637/CRED Club /paymen/AXIS BANK | C72: - | D72: 45878 | E72: 1001 | F72: 0 | G72: 69485.52 | J72: Credit Card Bill Payment (CRED) | K72: Credit Card | L72: 0.85 | M72: N/A
A73: 45878 | B73: UPI/P2M/558715693325/IRCTC CF /IRCTC/HDFC BANK LTD | C73: - | D73: 45878 | E73: 2613.6 | F73: 0 | G73: 66871.92 | J73: UPI - IRCTC | K73: Travel | L73: 0.68 | M73: N/A
A74: 45878 | B74: UPI/P2M/558707343066/PUNJABI CHAAP CORNER /Paid v/HDFC BANK LTD | C74: - | D74: 45878 | E74: 198 | F74: 0 | G74: 66673.92 | H74: Punjabi Chaap Corner | J74: UPI Payment | K74: Personal | L74: 0.55 | M74: N/A
A75: 45878 | B75: UPI/P2M/558716291025/IRCTC CF /IRCTC/HDFC BANK LTD | C75: - | D75: 45878 | E75: 2813.6 | F75: 0 | G75: 63860.32 | J75: UPI - IRCTC | K75: Travel | L75: 0.68 | M75: N/A
A76: 45878 | B76: UPI/P2M/558716304669/IRCTC CF /IRCTC/HDFC BANK LTD | C76: - | D76: 45878 | E76: 202.7 | F76: 0 | G76: 63657.62 | J76: UPI - IRCTC | K76: Travel | L76: 0.68 | M76: N/A
A77: 45878 | B77: UPI/P2A/101172961110/IRCTC CF/HDFC BANK/UPI Refu/ | C77: - | D77: 45878 | E77: 0 | F77: 2460 | G77: 66117.62 | J77: UPI - IRCTC | K77: Travel | L77: 0.92 | M77: N/A
A78: 45880 | B78: UPI/P2M/558942261136/IRCTC CF /IRCTC/HDFC BANK LTD | C78: - | D78: 45880 | E78: 1164.5 | F78: 0 | G78: 64953.12 | J78: UPI - IRCTC | K78: Travel | L78: 0.68 | M78: N/A
A79: 45881 | B79: UPI/P2M/559051297013/MATS FUEL PARK HPCL /Paid v/YES BANK LIMITED YBS | C79: - | D79: 45881 | E79: 310 | F79: 0 | G79: 64643.12 | J79: UPI - Fuel (HPCL) | K79: Fuel & Petrol | L79: 0.8 | M79: N/A
A80: 45881 | B80: UPI/P2M/559054091734/ANANYA CATERERS /Paid v/Punjab National Bank | C80: - | D80: 45881 | E80: 140 | F80: 0 | G80: 64503.12 | H80: Ananya Caterers | J80: UPI Payment | K80: Personal | L80: 0.55 | M80: N/A
A81: 45884 | B81: UPI/P2M/522704883967/Mrs. G Pavithra /Paid v/State Bank Of India | C81: - | D81: 45884 | E81: 100 | F81: 0 | G81: 64403.12 | H81: Mrs. G Pavithra | J81: UPI Payment | K81: Personal | L81: 0.55 | M81: N/A
A82: 45886 | B82: UPI/P2M/522935613998/Arjun Prasad /Paid v/YES BANK LIMITED YBS | C82: - | D82: 45886 | E82: 80 | F82: 0 | G82: 64323.12 | H82: Arjun Prasad | J82: UPI Payment | K82: Personal | L82: 0.55 | M82: N/A
A83: 45888 | B83: UPI/P2M/559728319835/CRED Club /paymen/AXIS BANK | C83: - | D83: 45888 | E83: 1000 | F83: 0 | G83: 63323.12 | J83: Credit Card Bill Payment (CRED) | K83: Credit Card | L83: 0.85 | M83: N/A
A84: 45889 | B84: UPI/P2A/523273141209/NAGALINGEGOWDA B /Paid v/UCO BANK | C84: - | D84: 45889 | E84: 870 | F84: 0 | G84: 62453.12 | H84: Nagalingegowda B | J84: UPI Payment | K84: Personal | L84: 0.55 | M84: N/A
A85: 45889 | B85: UPI/P2M/559830025838/CRED Club /paymen/AXIS BANK | C85: - | D85: 45889 | E85: 1000 | F85: 0 | G85: 61453.12 | J85: Credit Card Bill Payment (CRED) | K85: Credit Card | L85: 0.85 | M85: N/A
A86: 45890 | B86: UPI/P2A/523385810581/R AMRIT /Paid v/HDFC BANK LTD | C86: - | D86: 45890 | E86: 1500 | F86: 0 | G86: 59953.12 | H86: R Amrit | J86: UPI Payment | K86: Personal | L86: 0.55 | M86: N/A
A87: 45890 | B87: UPI/P2M/559931180666/CRED Club /paymen/AXIS BANK | C87: - | D87: 45890 | E87: 1000 | F87: 0 | G87: 58953.12 | J87: Credit Card Bill Payment (CRED) | K87: Credit Card | L87: 0.85 | M87: N/A
A88: 45891 | B88: UPI/P2M/560032217371/CRED Club /paymen/AXIS BANK | C88: - | D88: 45891 | E88: 1000 | F88: 0 | G88: 57953.12 | J88: Credit Card Bill Payment (CRED) | K88: Credit Card | L88: 0.85 | M88: N/A
A89: 45892 | B89: UPI/P2M/560133308526/CRED Club /paymen/AXIS BANK | C89: - | D89: 45892 | E89: 1000 | F89: 0 | G89: 56953.12 | J89: Credit Card Bill Payment (CRED) | K89: Credit Card | L89: 0.85 | M89: N/A
A90: 45892 | B90: UPI/P2A/560123557687/UTTAM BEHERA /Paid v/State Bank Of India | C90: - | D90: 45892 | E90: 200 | F90: 0 | G90: 56753.12 | H90: Uttam Behera | J90: UPI Payment | K90: Personal | L90: 0.55 | M90: N/A
A91: 45892 | B91: UPI/P2M/560123676924/Iyengars Bread Basket/Paid v/YES BANK LIMITED YBS | C91: - | D91: 45892 | E91: 30 | F91: 0 | G91: 56723.12 | H91: Iyengars Bread Basket | J91: UPI Payment | K91: Personal | L91: 0.55 | M91: N/A
A92: 45892 | B92: UPI/P2M/560234524186/CRED Club /paymen/AXIS BANK | C92: - | D92: 45892 | E92: 1000 | F92: 0 | G92: 55723.12 | J92: Credit Card Bill Payment (CRED) | K92: Credit Card | L92: 0.85 | M92: N/A
A93: 45894 | B93: UPI/P2M/560335939173/CRED Club /paymen/AXIS BANK | C93: - | D93: 45894 | E93: 1875.87 | F93: 0 | G93: 53847.25 | J93: Credit Card Bill Payment (CRED) | K93: Credit Card | L93: 0.85 | M93: N/A
A94: 45895 | B94: UPI/P2A/560463378253/S MUKIHTAYAR /Paid v/Kotak Mahindra Bank | C94: - | D94: 45895 | E94: 87 | F94: 0 | G94: 53760.25 | H94: S Mukihtayar | J94: UPI Payment | K94: Personal | L94: 0.55 | M94: N/A
A95: 45895 | B95: UPI/P2A/560465626624/Maddula Giribabu /Paid v/AIRTEL PAYMENTS BANK | C95: - | D95: 45895 | E95: 80 | F95: 0 | G95: 53680.25 | H95: Maddula Giribabu | J95: UPI Payment | K95: Personal | L95: 0.55 | M95: N/A
A96: 45896 | B96: UPI/P2A/560575060135/G RAVEENDRA /Paid v/ICICI Bank | C96: - | D96: 45896 | E96: 150 | F96: 0 | G96: 53530.25 | H96: G Raveendra | J96: UPI Payment | K96: Personal | L96: 0.55 | M96: N/A
A97: 45896 | B97: UPI/P2A/560580037532/V KAVITHA /Paid v/UNION BANK OF INDIA | C97: - | D97: 45896 | E97: 100 | F97: 0 | G97: 53430.25 | H97: V Kavitha | J97: UPI Payment | K97: Personal | L97: 0.55 | M97: N/A
A98: 45896 | B98: UPI/P2A/560580437243/SOMARAPU NAGARAJU /Paid v/CANARA BANK | C98: - | D98: 45896 | E98: 67 | F98: 0 | G98: 53363.25 | H98: Somarapu Nagaraju | J98: UPI Payment | K98: Personal | L98: 0.55 | M98: N/A
A99: 45896 | B99: UPI/P2A/560587858515/B PRABHAVATHI /Paid v/State Bank Of India | C99: - | D99: 45896 | E99: 210 | F99: 0 | G99: 53153.25 | H99: B Prabhavathi | J99: UPI Payment | K99: Personal | L99: 0.55 | M99: N/A
A100: 45896 | B100: UPI/P2A/560587981201/Mr. S Chinni Prasad /Paid v/INDIAN BANK | C100: - | D100: 45896 | E100: 150 | F100: 0 | G100: 53003.25 | H100: Mr. S Chinni Prasad | J100: UPI Payment | K100: Personal | L100: 0.55 | M100: N/A
A101: 45896 | B101: UPI/P2A/560588548027/SWARNA KUMAR BHAMA /Paid v/State Bank Of India | C101: - | D101: 45896 | E101: 87 | F101: 0 | G101: 52916.25 | H101: Swarna Kumar Bhama | J101: UPI Payment | K101: Personal | L101: 0.55 | M101: N/A
A102: 45897 | B102: UPI/P2M/560639789726/Airtel /Prepai/YES BANK LIMITED YBS | C102: - | D102: 45897 | E102: 181 | F102: 0 | G102: 52735.25 | H102: Airtel | J102: UPI Payment | K102: Personal | L102: 0.55 | M102: N/A
A103: 45897 | B103: UPI/P2M/560696704038/MAGULURI SUBBA RAO /Paid v/State Bank Of India | C103: - | D103: 45897 | E103: 25 | F103: 0 | G103: 52710.25 | H103: Maguluri Subba Rao | J103: UPI Payment | K103: Personal | L103: 0.55 | M103: N/A
A104: 45897 | B104: UPI/P2M/560697572688/Govindas /Paid v/YES BANK LIMITED YBS | C104: - | D104: 45897 | E104: 95 | F104: 0 | G104: 52615.25 | H104: Govindas | J104: UPI Payment | K104: Personal | L104: 0.55 | M104: N/A
A105: 45897 | B105: UPI/P2A/524000980690/T VIJAYAKUMAR /Paid v/INDIAN OVERSEAS BANK | C105: - | D105: 45897 | E105: 100 | F105: 0 | G105: 52515.25 | H105: T Vijayakumar | J105: UPI Payment | K105: Personal | L105: 0.55 | M105: N/A
A106: 45898 | B106: UPI/P2A/524109286229/GET WELL SOON PHARMAC/Paid v/State Bank Of India | C106: - | D106: 45898 | E106: 800 | F106: 0 | G106: 51715.25 | J106: UPI - Pharmacy | K106: Healthcare | L106: 0.85 | M106: N/A
A107: 45898 | B107: UPI/P2A/524110281401/TELUGU DHANALAKSHMI /Paid v/UNION BANK OF INDIA | C107: - | D107: 45898 | E107: 80 | F107: 0 | G107: 51635.25 | H107: Telugu Dhanalakshmi | J107: UPI Payment | K107: Personal | L107: 0.55 | M107: N/A
A108: 45898 | B108: UPI/P2A/524111739019/K RANGAIAH /Paid v/CANARA BANK | C108: - | D108: 45898 | E108: 15 | F108: 0 | G108: 51620.25 | H108: K Rangaiah | J108: UPI Payment | K108: Personal | L108: 0.55 | M108: N/A
A109: 45899 | B109: UPI/P2M/524223688490/KANAGARAJ RAMAMOORTHY/Paid v/YES BANK LIMITED YBS | C109: - | D109: 45899 | E109: 27 | F109: 0 | G109: 51593.25 | H109: Kanagaraj Ramamoorthy | J109: UPI Payment | K109: Personal | L109: 0.55 | M109: N/A
A110: 45899 | B110: UPI/P2M/560842785807/CRED Club /paymen/AXIS BANK | C110: - | D110: 45899 | E110: 1000 | F110: 0 | G110: 50593.25 | J110: Credit Card Bill Payment (CRED) | K110: Credit Card | L110: 0.85 | M110: N/A
...

Sheet HDFC
B1: HDFC Bank Narration Sheet
B2: Colour Legend of Categories:
B3: SIP | C3: HDFC Securities - Settlement | D3: HDFC Securities - Buy | E3: HDFC Securities - Sell | F3: Annuity Income
B4: Bank Charges | C4: Cash Withdrawal | D4: Depository Charges | E4: Received - Dnyaneshwar Kuyate | F4: UPI - Amazon
B5: Received - Ashok Divedi | C5: UPI - Fresh Produce | D5: UPI - MedPlus | E5: Transfer - Sunita Gupta | F5: Received - Ajay Gupta
B6: Dividend Income | C6: Transfer - Archit Gupta | D6: Received - Sunita Gupta | E6: Received - Archit Gupta | F6: Lounge Access Charge
B7: Bank Interest | C7: Securities Settlement | D7: Transfer - Ajay Gupta | E7: Insurance Premium | F7: Equity Buy (JSW Cement)
B8: Received - Sunil Kumar Pathak | C8: Received - Alok Kumar Gupta | D8: MF Redemption | E8: Contra - SBI
A10: Date | B10: Particulars | C10: Ref | D10: Value_Date | E10: DR | F10: CR | G10: Balance | H10: Beneficiary | I10: Human_Narration | J10: Auto_Narration | K10: Account_Head | L10: Confidence | M10: Match
A11: 45748 | B11: ACH D- TP ACH INDIANESIGN-1758642535 | C11: 0000006650023609 | D11: 45748 | E11: 5000 | F11: 0 | G11: 24321.48 | J11: SIP | K11: SIP | L11: 0.95 | M11: N/A
A12: 45749 | B12: FT- 623432246-50200085415108 - HDFC SECURITIES LTD-CLIENT DSCNB A/C - | C12: 0000001009359686 | D12: 45749 | E12: 0 | F12: 5239.85 | G12: 29561.33 | J12: HDFC Securities - Settlement | K12: HDFC Securities | L12: 0.93 | M12: N/A
A13: 45749 | B13: NET PI TO HSL SEC A/C 2554606-00602340029427 | C13: 0000000623593417 | D13: 45749 | E13: 150.26 | F13: 0 | G13: 29411.07 | J13: HDFC Securities - Buy | K13: HDFC Securities | L13: 0.97 | M13: N/A
A14: 45749 | B14: NET PI TO HSL SEC A/C 2554606-00602340029427 | C14: 0000000623760831 | D14: 45749 | E14: 9081.73 | F14: 0 | G14: 20329.34 | J14: HDFC Securities - Buy | K14: HDFC Securities | L14: 0.97 | M14: N/A
A15: 45750 | B15: FT- 623852638-50200085415108 - HDFC SECURITIES LTD-CLIENT DSCNB A/C - | C15: 0000001010969056 | D15: 45750 | E15: 0 | F15: 656.71 | G15: 20986.05 | J15: HDFC Securities - Settlement | K15: HDFC Securities | L15: 0.93 | M15: N/A
A16: 45750 | B16: NET PI TO HSL SEC A/C 2554606-00602340029427 | C16: 0000000624008014 | D16: 45750 | E16: 134.41 | F16: 0 | G16: 20851.64 | J16: HDFC Securities - Buy | K16: HDFC Securities | L16: 0.97 | M16: N/A
A17: 45751 | B17: FT- 624254248-50200085415108 - HDFC SECURITIES LTD-CLIENT DSCNB A/C - | C17: 0000001012795998 | D17: 45751 | E17: 0 | F17: 10041.41 | G17: 30893.05 | J17: HDFC Securities - Settlement | K17: HDFC Securities | L17: 0.93 | M17: N/A
A18: 45751 | B18: NET PI TO HSL SEC A/C 2554606-00602340029427 | C18: 0000000624385290 | D18: 45751 | E18: 115.2 | F18: 0 | G18: 30777.85 | J18: HDFC Securities - Buy | K18: HDFC Securities | L18: 0.97 | M18: N/A
A19: 45751 | B19: NET PO FROM HSL A/C 2554606-50200085415108 | C19: 0000000624619061 | D19: 45751 | E19: 0 | F19: 6146.26 | G19: 36924.11 | J19: HDFC Securities - Sell | K19: HDFC Securities | L19: 0.97 | M19: N/A
A20: 45754 | B20: HDFCLIFE CENTR-038144668 | C20: 0000504070711353 | D20: 45754 | E20: 0 | F20: 1880 | G20: 38804.11 | J20: Annuity Income | K20: Annuity | L20: 0.95 | M20: N/A
A21: 45754 | B21: NET PI TO HSL SEC A/C 2554606-00602340029427 | C21: 0000000624943357 | D21: 45754 | E21: 323.04 | F21: 0 | G21: 38481.07 | J21: HDFC Securities - Buy | K21: HDFC Securities | L21: 0.97 | M21: N/A
A22: 45754 | B22: NET PI TO HSL SEC A/C 2554606-00602340029427 | C22: 0000000625232784 | D22: 45754 | E22: 6242.17 | F22: 0 | G22: 32238.9 | J22: HDFC Securities - Buy | K22: HDFC Securities | L22: 0.97 | M22: N/A
... A669: 46113 | B669: INTEREST PAID TILL 31-MAR-2026 | C669: 000000000000000 | D669: 46112 | E669: 0 | F669: 162 | G669: 162 | J669: Bank Interest | K669: Bank Interest | L669: 0.95 | M669: N/A

Sheet KOTAK
B1: Kotak Mahindra Bank Narration Sheet
B2: Colour Legend of Categories:
B3: UPI Payment | C3: SuperMoney (Rewards) | D3: Zerodha Broking | E3: MF Redemption | F3: UPI - CRED
B4: UPI Reversal | C4: Credit Card Bill Payment (CRED) | D4: Govt / Utility Payment | E4: Salary | F4: Transfer - Megha Gupta
B5: UPI - IRCTC | C5: Received - Megha Gupta | D5: Contra - SBI | E5: SIP | F5: Rent Payment (via CRED)
B6: Contra - Axis | C6: UPI - Amazon | D6: IMPS Receipt | E6: UPI - BharatPe | F6: Refund - Wakefit
B7: UPI - Nandini Dairy | C7: Dividend Income | D7: Received - Archit Gupta | E7: Transfer - Archit Gupta | F7: UPI - Fuel
B8: Cashback - Kiwi | C8: INDmoney Investment | D8: Depository Credit | E8: Card Purchase | F8: Bank Interest
B9: UPI - Google Play | C9: Contra - SBM | D9: UPI - Navi | E9: UPI - District (Dining) | F9: Received - Tejas P
B10: Received - Utkarsh Bhandar | C10: Received - Kriti Gupta | D10: Received - Google Pay | E10: Misc Income | F10: UPI - Hotstar
B11: UPI - OpenAI | C11: IPO Application (UPI) | D11: Received - Google India Di | E11: UPI - Zomato | F11: MF Investment
B12: Bank Charges
A14: Date | B14: Particulars | C14: Ref | D14: Value_Date | E14: DR | F14: CR | G14: Balance | H14: Beneficiary | I14: Human_Narration | J14: Auto_Narration | K14: Account_Head | L14: Confidence | M14: Match
A15: 45748.457 | B15: UPI/BARATHI ANBAZHA/509137039846/Paid via SuperM | C15: UPI-509197194351 | D15: 45748 | E15: 121 | F15: 0 | G15: 1612.19 | H15: Barathi Anbazha | J15: UPI Payment | K15: Personal | L15: 0.55 | M15: N/A
A16: 45748.709 | B16: UPI/SAMOSA PARTY Ba/509141156489/Paid via SuperM | C16: UPI-509118876248 | D16: 45748 | E16: 30 | F16: 0 | G16: 1582.19 | H16: Samosa Party Ba | J16: UPI Payment | K16: Personal | L16: 0.55 | M16: N/A
A17: 45750.765 | B17: UPI/Mrs. G Pavithr/509367683617/Paid via SuperM | C17: UPI-509356331060 | D17: 45750 | E17: 50 | F17: 0 | G17: 1532.19 | H17: Mrs. G Pavithr | J17: UPI Payment | K17: Personal | L17: 0.55 | M17: N/A
A18: 45750.949 | B18: UPI/supermoney/509381273041/Supermoney Rewa | C18: UPI-509376992939 | D18: 45750 | E18: 0 | F18: 66.74 | G18: 1598.93 | J18: SuperMoney (Rewards) | K18: Misc Income | L18: 0.88 | M18: N/A
A19: 45751.957 | B19: UPI/WALKO FOOD COMP/509484810231/Paid via SuperM | C19: UPI-509442182659 | D19: 45751 | E19: 285 | F19: 0 | G19: 1313.93 | H19: Walko Food Comp | J19: UPI Payment | K19: Personal | L19: 0.55 | M19: N/A
A20: 45752.341 | B20: NEFT YESF350953824281 ZERODHA BROKING LTD DSCNB A | C20: NEFTINW-1174470955 | D20: 45752 | E20: 0 | F20: 4213.71 | G20: 5527.64 | J20: Zerodha Broking | K20: Zerodha Broking Limited | L20: 0.92 | M20: N/A
A21: 45752.781 | B21: UPI/Counter 4/509593584977/Paid via SuperM | C21: UPI-509588244702 | D21: 45752 | E21: 210 | F21: 0 | G21: 5317.64 | H21: Counter 4 | J21: UPI Payment | K21: Personal | L21: 0.55 | M21: N/A
A22: 45753.756 | B22: UPI/DINESH KUMAR GU/546205310184/Paid via SuperM | C22: UPI-509648113097 | D22: 45753 | E22: 30 | F22: 0 | G22: 5287.64 | H22: Dinesh Kumar Gu | J22: UPI Payment | K22: Personal | L22: 0.55 | M22: N/A
A23: 45758.422 | B23: NEFT AXISCN0958713705 NIPPON INDIA SMALL CAP FUND | C23: NEFTINW-1180794199 | D23: 45758 | E23: 0 | F23: 501 | G23: 5788.64 | J23: MF Redemption | K23: Mutual Funds | L23: 0.85 | M23: N/A
A24: 45758.846 | B24: UPI/Ferdus Alom/546773545667/Paid via CRED a | C24: UPI-510184999331 | D24: 45758 | E24: 279 | F24: 0 | G24: 5509.64 | J24: UPI - CRED | K24: Personal | L24: 0.68 | M24: N/A
A25: 45758.846 | B25: REV-UPI/Ferdus Alom/546773545667/ | C25: UPI-510184999331 | D25: 45758 | E25: 0 | F25: 279 | G25: 5788.64 | J25: UPI Reversal | K25: Personal | L25: 0.88 | M25: N/A
A26: 45758.846 | B26: UPI/Ferdus Alom/546773546667/Paid via CRED a | C26: UPI-510185051060 | D26: 45758 | E26: 279 | F26: 0 | G26: 5509.64 | J26: UPI - CRED | K26: Personal | L26: 0.68 | M26: N/A
A27: 45758.846 | B27: REV-UPI/Ferdus Alom/546773546667/ | C27: UPI-510185051060 | D27: 45758 | E27: 0 | F27: 279 | G27: 5788.64 | J27: UPI Reversal | K27: Personal | L27: 0.88 | M27: N/A
A28: 45758.949 | B28: UPI/CRED/546773735558/payment on CRED | C28: UPI-510195642472 | D28: 45758 | E28: 1500 | F28: 0 | G28: 4288.64 | J28: Credit Card Bill Payment (CRED) | K28: Credit Card | L28: 0.85 | M28: N/A
A29: 45762.399 | B29: UPI/SBIMOPS/547177174910/MOPSUPITxn | C29: UPI-510591765767 | D29: 45762 | E29: 1500 | F29: 0 | G29: 2788.64 | J29: Govt / Utility Payment | K29: Utilities | L29: 0.82 | M29: N/A
A30: 45763.345 | B30: UPI/CRED/547278151800/payment on CRED | C30: UPI-510652750321 | D30: 45763 | E30: 1000 | F30: 0 | G30: 1788.64 | J30: Credit Card Bill Payment (CRED) | K30: Credit Card | L30: 0.85 | M30: N/A
A31: 45763.46 | B31: TRANS | C31: FCM-250416G7VEUG | D31: 45763 | E31: 0 | F31: 91056 | G31: 92844.64 | J31: Salary | K31: Salary | L31: 0.85 | M31: N/A
A32: 45763.472 | B32: UPI/Miss. MEGHA GU/547278323187/Happy 3 month A | C32: UPI-510661882848 | D32: 45763 | E32: 10000 | F32: 0 | G32: 82844.64 | J32: Transfer - Megha Gupta | K32: Megha Gupta | L32: 0.85 | M32: N/A
A33: 45764.28 | B33: UPI/IRCTC CF/100375704017/IRCTC TICKET BO | C33: UPI-510713871404 | D33: 45764 | E33: 427.25 | F33: 0 | G33: 82417.39 | J33: UPI - IRCTC | K33: Travel | L33: 0.68 | M33: N/A
A34: 45764.567 | B34: UPI/CredClub/547379551441/payment on CRED | C34: UPI-510733285335 | D34: 45764 | E34: 1000 | F34: 0 | G34: 81417.39 | J34: Credit Card Bill Payment (CRED) | K34: Credit Card | L34: 0.85 | M34: N/A
... A37: 45766.693 | B37: UPI/CRED/547581914199/payment on CRED | C37: UPI-510965727111 | D37: 45766 | E37: 1000 | F37: 0 | G37: 78417.39 | J37: Credit Card Bill Payment (CRED) | K37: Credit Card | L37: 0.85 | M37: N/A
A38: 45766.887 | B38: UPI/ASHIK KHAN/510976601574/Paid via SuperM | C38: UPI-510987188278 | D38: 45766 | E38: 85 | F38: 0 | G38: 78332.39 | H38: Ashik Khan | J38: UPI Payment | K38: Personal | L38: 0.55 | M38: N/A
A39: 45766.909 | B39: UPI/MAHENDRA SINGH/510977058907/Paid via SuperM | C39: UPI-510989447720 | D39: 45766 | E39: 25 | F39: 0 | G39: 78307.39 | H39: Mahendra Singh | J39: UPI Payment | K39: Personal | L39: 0.55 | M39: N/A
A40: 45767.809 | B40: UPI/MEGHA GUPTA/547683296341/Paid via CRED | C40: UPI-511039130892 | D40: 45767 | E40: 0 | F40: 10 | G40: 78317.39 | J40: Received - Megha Gupta | K40: Megha Gupta | L40: 0.85 | M40: N/A
A41: 45767.832 | B41: UPI/CRED/547683353682/payment on CRED | C41: UPI-511041990132 | D41: 45767 | E41: 1000 | F41: 0 | G41: 77317.39 | J41: Credit Card Bill Payment (CRED) | K41: Credit Card | L41: 0.85 | M41: N/A
A42: 45768.346 | B42: UPI/CRED/547783701613/payment on CRED | C42: UPI-511161263012 | D42: 45768 | E42: 1012.11 | F42: 0 | G42: 76305.28 | J42: Credit Card Bill Payment (CRED) | K42: Credit Card | L42: 0.85 | M42: N/A
A43: 45770.337 | B43: NEFT HDFCH00196714813 MIRAE ASSET MF REDEMPTION A | C43: NEFTINW-1191507783 | D43: 45770 | E43: 0 | F43: 6904.51 | G43: 83209.79 | J43: MF Redemption | K43: Mutual Funds | L43: 0.85 | M43: N/A
A44: 45770.339 | B44: UPI/IRCTC CF/547985899437/IRCTC TICKET BO | C44: UPI-511382097756 | D44: 45770 | E44: 2763.6 | F44: 0 | G44: 80446.19 | J44: UPI - IRCTC | K44: Travel | L44: 0.68 | M44: N/A
A45: 45770.344 | B45: UPI/IRCTC CF/547917547710/IRCTC TICKET BO | C45: UPI-511382338732 | D45: 45770 | E45: 162.7 | F45: 0 | G45: 80283.49 | J45: UPI - IRCTC | K45: Travel | L45: 0.68 | M45: N/A
A46: 45771.313 | B46: UPI/Om Supar Shopi/548030374691/Paid via SuperM | C46: UPI-511441566118 | D46: 45771 | E46: 40 | F46: 0 | G46: 80243.49 | H46: Om Supar Shopi | J46: UPI Payment | K46: Personal | L46: 0.55 | M46: N/A
A47: 45773.392 | B47: UPI/9594435259@supe/548257957091/Paid via SuperM | C47: UPI-511665616235 | D47: 45773 | E47: 5000 | F47: 0 | G47: 75243.49 | J47: Contra - SBI | K47: SBI 1227 | L47: 0.95 | M47: N/A
A48: 45773.777 | B48: UPI/SACHIN SHIVAJI /548264628441/Paid via SuperM | C48: UPI-511696435579 | D48: 45773 | E48: 20 | F48: 0 | G48: 75223.49 | H48: Sachin Shivaji | J48: UPI Payment | K48: Personal | L48: 0.55 | M48: N/A
A49: 45775.309 | B49: NACH-MUT-DR-INDIAN CLEARING CORP-000000PFDXIMY7ND | C49: NACHDR28042506263900 | D49: 45775 | E49: 7000 | F49: 0 | G49: 68223.49 | J49: SIP | K49: SIP | L49: 0.96 | M49: N/A
A50: 45778.823 | B50: UPI/Miss. MEGHA GU/548796376019/Paid via CRED a | C50: UPI-512110893337 | D50: 45778 | E50: 5000 | F50: 0 | G50: 63223.49 | J50: Transfer - Megha Gupta | K50: Megha Gupta | L50: 0.85 | M50: N/A
A51: 45778.824 | B51: UPI/Miss. MEGHA GU/548796379699/Paid via CRED a | C51: UPI-512111066095 | D51: 45778 | E51: 5000 | F51: 0 | G51: 58223.49 | J51: Transfer - Megha Gupta | K51: Megha Gupta | L51: 0.85 | M51: N/A
A52: 45779.472 | B52: UPI/CRED/548897087231/payment on CRED | C52: UPI-512244268011 | D52: 45779 | E52: 23000 | F52: 0 | G52: 35223.49 | J52: Rent Payment (via CRED) | K52: Rent | L52: 0.88 | M52: N/A
A53: 45779.478 | B53: UPI/AAYUSH KUMAR GU/294427061225/UPI | C53: UPI-512244855995 | D53: 45779 | E53: 0 | F53: 1 | G53: 35224.49 | J53: Contra - Axis | K53: AXIS | L53: 0.95 | M53: N/A
A54: 45779.479 | B54: UPI/AAYUSH KUMAR GU/294526291225/UPI | C54: UPI-512244915205 | D54: 45779 | E54: 0 | F54: 65000 | G54: 100224.49 | J54: Contra - Axis | K54: AXIS | L54: 0.95 | M54: N/A
A55: 45779.805 | B55: UPI/SACHIN SHIVAJI /512244955899/Paid via SuperM | C55: UPI-512275461489 | D55: 45779 | E55: 20 | F55: 0 | G55: 100204.49 | H55: Sachin Shivaji | J55: UPI Payment | K55: Personal | L55: 0.55 | M55: N/A
A56: 45780.569 | B56: UPI/AAYUSH KUMAR GU/415981531235/UPI | C56: UPI-512319612218 | D56: 45780 | E56: 0 | F56: 7000 | G56: 107204.49 | J56: Contra - Axis | K56: AXIS | L56: 0.95 | M56: N/A
A57: 45781.431 | B57: UPI/BHAGWAT BHIMRAO/512465473377/Paid via SuperM | C57: UPI-512472603018 | D57: 45781 | E57: 850 | F57: 0 | G57: 106354.49 | H57: Bhagwat Bhimrao | J57: UPI Payment | K57: Personal | L57: 0.55 | M57: N/A
A58: 45781.538 | B58: UPI/Amazon Pay Bala/512400051395/You are paying | C58: UPI-512482255509 | D58: 45781 | E58: 700 | F58: 0 | G58: 105654.49 | J58: UPI - Amazon | K58: Shopping | L58: 0.68 | M58: N/A
A59: 45782.089 | B59: Recd:IMPS/512502012718/NAVI MUTUA/KKBK/X7316/Fund | C59: IMPS-512502485720 | D59: 45782 | E59: 0 | F59: 13.38 | G59: 105667.87 | J59: IMPS Receipt | K59: Personal | L59: 0.72 | M59: N/A
A60: 45782.11 | B60: Recd:IMPS/512502023239/NAVI MUTUA/KKBK/X7316/Fund | C60: IMPS-512502494271 | D60: 45782 | E60: 0 | F60: 10679.9 | G60: 116347.77 | J60: IMPS Receipt | K60: Personal | L60: 0.72 | M60: N/A
A61: 45783.509 | B61: UPI/Zerodha Broking/512602521749/353646016145310 | C61: UPI-512607324677 | D61: 45783 | E61: 20000 | F61: 0 | G61: 96347.77 | J61: Zerodha Broking | K61: Zerodha Broking Limited | L61: 0.92 | M61: N/A
A62: 45785.357 | B62: UPI/SANJAYKUMAR HAR/512804499361/Paid via CRED | C62: UPI-512820689415 | D62: 45785 | E62: 232 | F62: 0 | G62: 96115.77 | J62: UPI - CRED | K62: Personal | L62: 0.68 | M62: N/A
A63: 45785.543 | B63: UPI/MEGHA GUPTA/512804762076/Paid via CRED | C63: UPI-512835473551 | D63: 45785 | E63: 10 | F63: 0 | G63: 96105.77 | J63: Transfer - Megha Gupta | K63: Megha Gupta | L63: 0.85 | M63: N/A
A64: 45786.863 | B64: UPI/ARTI SANDIP BHA/549538116062/Paid via SuperM | C64: UPI-512929489200 | D64: 45786 | E64: 45 | F64: 0 | G64: 96060.77 | H64: Arti Sandip Bha | J64: UPI Payment | K64: Personal | L64: 0.55 | M64: N/A
A65: 45787.556 | B65: UPI/Mr SHUBHAM RAVI/549643110338/Paid via SuperM | C65: UPI-513062663161 | D65: 45787 | E65: 20 | F65: 0 | G65: 96040.77 | H65: Mr Shubham Ravi | J65: UPI Payment | K65: Personal | L65: 0.55 | M65: N/A
A66: 45787.573 | B66: UPI/CHOPDA AUTO WHE/513006856454/Pay to BharatPe | C66: UPI-513064188493 | D66: 45787 | E66: 1960 | F66: 0 | G66: 94080.77 | J66: UPI - BharatPe | K66: Personal | L66: 0.65 | M66: N/A
A67: 45788.385 | B67: UPI/IRCTCETICKETING/100532089954/Pine Labs Payme | C67: UPI-513111733398 | D67: 45788 | E67: 688.15 | F67: 0 | G67: 93392.62 | J67: UPI - IRCTC | K67: Travel | L67: 0.68 | M67: N/A
A68: 45788.388 | B68: UPI/IRCTC CF/100532100746/IRCTC TICKET BO | C68: UPI-513111931159 | D68: 45788 | E68: 462.7 | F68: 0 | G68: 92929.92 | J68: UPI - IRCTC | K68: Travel | L68: 0.68 | M68: N/A
A69: 45789.8 | B69: UPI/GWEN SUMEET KHE/513213613192/UPI | C69: UPI-513207161827 | D69: 45789 | E69: 50 | F69: 0 | G69: 92879.92 | H69: Gwen Sumeet Khe | J69: UPI Payment | K69: Personal | L69: 0.55 | M69: N/A
A70: 45790.35 | B70: UPI/Zerodha Broking/513309616859/007060421252654 | C70: UPI-513330872694 | D70: 45790 | E70: 20000 | F70: 0 | G70: 72879.92 | J70: Zerodha Broking | K70: Zerodha Broking Limited | L70: 0.92 | M70: N/A
A71: 45790.357 | B71: NEFT AXISCN0974957690 NIPPON INDIA SMALL CAP FUND | C71: NEFTINW-1210937207 | D71: 45790 | E71: 0 | F71: 501 | G71: 73380.92 | J71: MF Redemption | K71: Mutual Funds | L71: 0.85 | M71: N/A
A72: 45792.294 | B72: UPI/CRED WALLET/513511457076/payment on CRED | C72: UPI-513553012943 | D72: 45792 | E72: 109 | F72: 0 | G72: 73271.92 | J72: UPI - CRED | K72: Personal | L72: 0.85 | M72: N/A
A73: 45792.314 | B73: UPI/CRED/513511467013/payment on CRED | C73: UPI-513553583633 | D73: 45792 | E73: 1000 | F73: 0 | G73: 72271.92 | J73: Credit Card Bill Payment (CRED) | K73: Credit Card | L73: 0.85 | M73: N/A
A74: 45794.417 | B74: UPI/IRCTC CF/513713292919/IRCTC TICKET BO | C74: UPI-513782417790 | D74: 45794 | E74: 5014.5 | F74: 0 | G74: 67257.42 | J74: UPI - IRCTC | K74: Travel | L74: 0.68 | M74: N/A
A75: 45794.694 | B75: UPI/IRCTC CF/100570866260/UPI Refund | C75: UPI-513705020960 | D75: 45794 | E75: 0 | F75: 2610 | G75: 69867.42 | J75: UPI - IRCTC | K75: Travel | L75: 0.92 | M75: N/A
A76: 45795.356 | B76: UPI/MOHMMAD SHOABE /513814119480/Paid via CRED | C76: UPI-513840166521 | D76: 45795 | E76: 430 | F76: 0 | G76: 69437.42 | J76: UPI - CRED | K76: Personal | L76: 0.68 | M76: N/A
A77: 45795.376 | B77: UPI/AKIRANI SONS/513815094999/Paid via SuperM | C77: UPI-513841152464 | D77: 45795 | E77: 20 | F77: 0 | G77: 69417.42 | H77: Akirani Sons | J77: UPI Payment | K77: Personal | L77: 0.55 | M77: N/A
A78: 45796.321 | B78: UPI/SREERAG M A/513914988417/Paid via CRED a | C78: UPI-513998678778 | D78: 45796 | E78: 250 | F78: 0 | G78: 69167.42 | J78: UPI - CRED | K78: Personal | L78: 0.68 | M78: N/A
A79: 45796.782 | B79: UPI/SHAMSHUDDIN/513929282094/Paid via SuperM | C79: UPI-513934633606 | D79: 45796 | E79: 45 | F79: 0 | G79: 69122.42 | H79: Shamshuddin | J79: UPI Payment | K79: Personal | L79: 0.55 | M79: N/A
A80: 45797.512 | B80: UPI/RK FARM FRESH V/514035234323/Paid via SuperM | C80: UPI-514072324239 | D80: 45797 | E80: 100 | F80: 0 | G80: 69022.42 | H80: Rk Farm Fresh V | J80: UPI Payment | K80: Personal | L80: 0.55 | M80: N/A
A81: 45798.811 | B81: UPI/Ali Haidar/550715908597/Pay to BharatPe | C81: UPI-514159635812 | D81: 45798 | E81: 74 | F81: 0 | G81: 68948.42 | J81: UPI - BharatPe | K81: Personal | L81: 0.65 | M81: N/A
A82: 45799.676 | B82: UPI/ARCHITA GUPTA/550877800149/wakefit Refund | C82: UPI-514206168963 | D82: 45799 | E82: 0 | F82: 9220 | G82: 78168.42 | J82: Refund - Wakefit | K82: Shopping | L82: 0.9 | M82: N/A
A83: 45799.877 | B83: UPI/Miss. MEGHA GU/514271567496/UPI | C83: UPI-514227672654 | D83: 45799 | E83: 10000 | F83: 0 | G83: 68168.42 | J83: Transfer - Megha Gupta | K83: Megha Gupta | L83: 0.85 | M83: N/A
A84: 45800.719 | B84: UPI/SHIVANNA H S/550904157384/Paid via CRED | C84: UPI-514369645960 | D84: 45800 | E84: 88 | F84: 0 | G84: 68080.42 | J84: UPI - CRED | K84: Personal | L84: 0.68 | M84: N/A
A85: 45803.36 | B85: UPI/Nandini/551219523177/Paid via CRED | C85: UPI-514621004386 | D85: 45803 | E85: 90 | F85: 0 | G85: 67990.42 | J85: UPI - Nandini Dairy | K85: Groceries | L85: 0.82 | M85: N/A
A86: 45803.369 | B86: UPI/Ali Haidar/551218525742/Pay to BharatPe | C86: UPI-514621460438 | D86: 45803 | E86: 405 | F86: 0 | G86: 67585.42 | J86: UPI - BharatPe | K86: Personal | L86: 0.65 | M86: N/A
A87: 45803.371 | B87: UPI/T S ASHOKA/551227517704/Paid via CRED | C87: UPI-514621594839 | D87: 45803 | E87: 20 | F87: 0 | G87: 67565.42 | J87: UPI - CRED | K87: Personal | L87: 0.68 | M87: N/A
A88: 45803.712 | B88: NACH-ECS-CR-BAJAJ FINANCE LIMITE-7005624 | C88: NACHDB26052516390400 | D88: 45803 | E88: 0 | F88: 24 | G88: 67589.42 | J88: Dividend Income | K88: Dividend Income | L88: 0.93 | M88: N/A
A89: 45804.433 | B89: UPI/LAKSHMAMMA/551315669791/Paid via CRED | C89: UPI-514785513617 | D89: 45804 | E89: 127 | F89: 0 | G89: 67462.42 | J89: UPI - CRED | K89: Personal | L89: 0.68 | M89: N/A
A90: 45805.284 | B90: NACH-MUT-DR-ZERODHA BROKING LTD-WOA35OYUNSED | C90: NACHDR28052506262700 | D90: 45805 | E90: 7000 | F90: 0 | G90: 60462.42 | J90: SIP | K90: SIP | L90: 0.96 | M90: N/A
A91: 45807.439 | B91: UPI/IRCTC CF/515086317592/IRCTC TICKET BO | C91: UPI-515065553633 | D91: 45807 | E91: 272.25 | F91: 0 | G91: 60190.17 | J91: UPI - IRCTC | K91: Travel | L91: 0.68 | M91: N/A
A92: 45807.745 | B92: UPI/MANJUNATHA S N/515092051166/Send Money | C92: UPI-515090972020 | D92: 45807 | E92: 70 | F92: 0 | G92: 60120.17 | H92: Manjunatha S N | J92: UPI Payment | K92: Personal | L92: 0.55 | M92: N/A
A93: 45807.762 | B93: UPI/Nandini/515092492254/Send Money | C93: UPI-515092704404 | D93: 45807 | E93: 84 | F93: 0 | G93: 60036.17 | J93: UPI - Nandini Dairy | K93: Groceries | L93: 0.82 | M93: N/A
A94: 45807.969 | B94: UPI/IRCTC CF/100650342690/IRCTC TICKET BO | C94: UPI-515014824202 | D94: 45807 | E94: 192.7 | F94: 0 | G94: 59843.47 | J94: UPI - IRCTC | K94: Travel | L94: 0.68 | M94: N/A
A95: 45808.817 | B95: UPI/ARCHIT GUPTA/551750116468/BT ear buds | C95: UPI-515162656608 | D95: 45808 | E95: 0 | F95: 799 | G95: 60642.47 | J95: Received - Archit Gupta | K95: Archit Gupta | L95: 0.85 | M95: N/A
A96: 45808.846 | B96: UPI/ARCHIT GUPTA/551785507126/UPI | C96: UPI-515166541351 | D96: 45808 | E96: 0 | F96: 1000 | G96: 61642.47 | J96: Received - Archit Gupta | K96: Archit Gupta | L96: 0.85 | M96: N/A
A97: 45808.926 | B97: UPI/ARCHIT GUPTA/515103326461/UPI | C97: UPI-515176106490 | D97: 45808 | E97: 1800 | F97: 0 | G97: 59842.47 | J97: Transfer - Archit Gupta | K97: Archit Gupta | L97: 0.85 | M97: N/A
A98: 45809.756 | B98: UPI/RAJA N/551804522587/Paid via CRED | C98: UPI-515221365505 | D98: 45809 | E98: 66 | F98: 0 | G98: 59776.47 | J98: UPI - CRED | K98: Personal | L98: 0.68 | M98: N/A
A99: 45809.757 | B99: UPI/Nandini/551802523167/Paid via CRED | C99: UPI-515221447268 | D99: 45809 | E99: 24 | F99: 0 | G99: 59752.47 | J99: UPI - Nandini Dairy | K99: Groceries | L99: 0.82 | M99: N/A
A100: 45810.544 | B100: UPI/AAYUSH KUMAR GU/868844991535/UPI | C100: UPI-515370939314 | D100: 45810 | E100: 0 | F100: 5000 | G100: 64752.47 | J100: Contra - Axis | K100: AXIS | L100: 0.95 | M100: N/A
A101: 45810.546 | B101: UPI/AAYUSH KUMAR GU/869103531535/UPI | C101: UPI-515371140519 | D101: 45810 | E101: 0 | F101: 40000 | G101: 104752.47 | J101: Contra - Axis | K101: AXIS | L101: 0.95 | M101: N/A
A102: 45811.019 | B102: UPI/supermoney/515451742169/Supermoney Rewa | C102: UPI-515416965085 | D102: 45811 | E102: 0 | F102: 49.36 | G102: 104801.83 | J102: SuperMoney (Rewards) | K102: Misc Income | L102: 0.88 | M102: N/A
A103: 45811.438 | B103: UPI/GOVINDAPPAN/552069447126/Paid via SuperM | C103: UPI-515429211702 | D103: 45811 | E103: 72 | F103: 0 | G103: 104729.83 | H103: Govindappan | J103: UPI Payment | K103: Personal | L103: 0.55 | M103: N/A
...

Sheet SBI
B1: State Bank of India Narration Sheet
B2: Colour Legend of Categories:
B3: Contra - Axis | C3: Rent | D3: Credit Card Bill Payment (CRED) | E3: Transfer - Megha Gupta | F3: UPI - Paytm
B4: UPI - Nandini Dairy | C4: UPI Payment | D4: Misc Income | E4: MF Investment | F4: Contra - Kotak
B5: Received - Megha Gupta | C5: UPI - IRCTC | D5: NEFT Transfer | E5: Received - Razorpay | F5: Bank Interest
B6: UPI - Google Pay | C6: UPI - Swiggy | D6: Received - Laxmidha | E6: Received - Jaikisha | F6: Transfer - Ajay Gupta
B7: Transfer - Sunita Gupta | C7: Received - Ajay Gupta | D7: Received - Premier | E7: Income Tax Refund | F7: Zerodha Broking
B8: Received - Archit Gupta | C8: Transfer - Archit Gupta | D8: Received - Tn99 | E8: Freelance Income | F8: Received - Chirag P
B9: Contra - HDFC | C9: Contra - Self | D9: Received - Shetaans | E9: Received - Yash Gupta | F9: Cashback - BHIM
B10: UPI Receipt | C10: UPI - Hotstar | D10: SuperMoney (Rewards)
A12: Date | B12: Particulars | C12: Ref | D12: Value_Date | E12: DR | F12: CR | G12: Balance | H12: Beneficiary | I12: Human_Narration | J12: Auto_Narration | K12: Account_Head | L12: Confidence | M12: Match
A13: 45749 | B13: DEP TFR UPI/CR/765226990925/AAYUSH K/UTIB/9594435 259/UPI 0097735162098 AT 11669 SHIVAJI NAGAR NASIK | D13: 45749 | E13: 0 | F13: 1 | G13: 10987.03 | J13: Contra - Axis | K13: AXIS | L13: 0.9 | M13: N/A
A14: 45749 | B14: DEP TFR UPI/CR/765382250925/AAYUSH K/UTIB/9594435 259/UPI 0097735162098 AT 11669 SHIVAJI NAGAR NASIK | D14: 45749 | E14: 0 | F14: 40000 | G14: 50987.03 | J14: Contra - Axis | K14: AXIS | L14: 0.9 | M14: N/A
A15: 45749 | B15: WDL TFR UPI/DR/545893374949/CRED RENT/UTIB/cred.re nt@/pay 0097693162093 AT 11669 SHIVAJI NAGAR NASIK | D15: 45749 | E15: 23000 | F15: 0 | G15: 27987.03 | J15: Rent | K15: Rent | L15: 0.9 | M15: N/A
A16: 45749 | B16: DEP TFR NEFT*UTIB0002656*AXOMB09202414101*AAYUSH K UMAR GU 0099509044300 AT 11669 SHIVAJI NAGAR NASIK | D16: 45749 | E16: 0 | F16: 1 | G16: 27988.03 | J16: Contra - Axis | K16: AXIS | L16: 0.9 | M16: N/A
A17: 45749 | B17: WDL TFR UPI/DR/509208961213/CRED Club/UTIB/cred.cl ub@/pay 0097693162093 AT 11669 SHIVAJI NAGAR NASIK | D17: 45749 | E17: 3000 | F17: 0 | G17: 24988.03 | J17: Credit Card Bill Payment (CRED) | K17: Credit Card | L17: 0.85 | M17: N/A
A18: 45749 | B18: WDL TFR UPI/DR/545868712527/Miss. ME/CBIN/meghagha ti/Paid 0097693162093 AT 11669 SHIVAJI NAGAR NASIK | D18: 45749 | E18: 2000 | F18: 0 | G18: 22988.03 | J18: Transfer - Megha Gupta | K18: Megha Gupta | L18: 0.85 | M18: N/A
A19: 45749 | B19: WDL TFR UPI/DR/545878868808/CRED Club/UTIB/cred.cl ub@/pay 0097693162093 AT 11669 SHIVAJI NAGAR NASIK | D19: 45749 | E19: 2000 | F19: 0 | G19: 20988.03 | J19: Credit Card Bill Payment (CRED) | K19: Credit Card | L19: 0.85 | M19: N/A
A20: 45749 | B20: WDL TFR UPI/DR/545887987358/CRED Club/UTIB/cred.cl ub@/pay 0097693162093 AT 11669 SHIVAJI NAGAR NASIK | D20: 45749 | E20: 2000 | F20: 0 | G20: 18988.03 | J20: Credit Card Bill Payment (CRED) | K20: Credit Card | L20: 0.85 | M20: N/A
A21: 45750 | B21: WDL TFR UPI/DR/545972230401/CRED Club/UTIB/cred.cl ub@/pay 0097694162092 AT 11669 SHIVAJI NAGAR NASIK | D21: 45750 | E21: 2000 | F21: 0 | G21: 16988.03 | J21: Credit Card Bill Payment (CRED) | K21: Credit Card | L21: 0.85 | M21: N/A
A22: 45750 | B22: WDL TFR UPI/DR/509378949775/CRED Club/UTIB/cred.cl ub@/pay 0097694162092 AT 11669 SHIVAJI NAGAR NASIK | D22: 45750 | E22: 2000 | F22: 0 | G22: 14988.03 | J22: Credit Card Bill Payment (CRED) | K22: Credit Card | L22: 0.85 | M22: N/A
A23: 45750 | B23: WDL TFR UPI/DR/509336037048/CRED Club/UTIB/cred.cl ub@/pay 0097694162092 AT 11669 SHIVAJI NAGAR NASIK | D23: 45750 | E23: 2360.82 | F23: 0 | G23: 12627.21 | J23: Credit Card Bill Payment (CRED) | K23: Credit Card | L23: 0.85 | M23: N/A
A24: 45751 | B24: WDL TFR UPI/DR/509438120147/MATS FUE/YESB/paytm-31 10/Paid 0097695162091 AT 11669 SHIVAJI NAGAR NASIK | D24: 45751 | E24: 210 | F24: 0 | G24: 12417.21 | J24: UPI - Paytm | K24: Personal | L24: 0.65 | M24: N/A
A25: 45752 | B25: WDL TFR UPI/DR/546194213465/Nandini/YESB/paytm.s1 c3/Paid 0097696162090 AT 11669 SHIVAJI NAGAR NASIK | D25: 45752 | E25: 60 | F25: 0 | G25: 12357.21 | J25: UPI - Nandini Dairy | K25: Groceries | L25: 0.82 | M25: N/A
A26: 45758 | B26: WDL TFR UPI/DR/510189443769/Ferdus /FINO/fardusal om/Paid 0097695162091 AT 11669 SHIVAJI NAGAR NASIK | D26: 45758 | E26: 279 | F26: 0 | G26: 12078.21 | H26: Ferdus | J26: UPI Payment | K26: Personal | L26: 0.55 | M26: N/A
A27: 45758 | B27: DEP TFR UPI/REV/510189443769 0097 695162091 AT 11669 SHIVAJI NAGAR NASIK | D27: 45758 | E27: 0 | F27: 279 | G27: 12357.21 | J27: Misc Income | K27: Misc Income | L27: 0.7 | M27: N/A
A28: 45758 | B28: WDL TFR UPI/DR/510127516128/Miss. ME/CBIN/meghagha ti/Paid 0097695162091 AT 11669 SHIVAJI NAGAR NASIK | D28: 45758 | E28: 10 | F28: 0 | G28: 12347.21 | J28: Transfer - Megha Gupta | K28: Megha Gupta | L28: 0.85 | M28: N/A
A29: 45762 | B29: WDL TFR UPI/DR/510522647751/BHARAT S/IOBA/84248520 34/Paid 0097692162094 AT 11669 SHIVAJI NAGAR NASIK | D29: 45762 | E29: 40 | F29: 0 | G29: 12307.21 | H29: Bharat S | J29: UPI Payment | K29: Personal | L29: 0.55 | M29: N/A
A30: 45763 | B30: DEP TFR NEFT*UTIB0002656*AXOMB10626155334*AAYUSH K UMAR GU 0099509044300 AT 11669 SHIVAJI NAGAR NASIK | D30: 45763 | E30: 0 | F30: 25000 | G30: 37307.21 | J30: Contra - Axis | K30: AXIS | L30: 0.9 | M30: N/A
A31: 45763 | B31: WDL TFR UPI/DR/510629877598/Indian C/HDFC/icclzero dh/Merc 0097693162093 AT 11669 SHIVAJI NAGAR NASIK | D31: 45763 | E31: 25000 | F31: 0 | G31: 12307.21 | J31: MF Investment | K31: Investments | L31: 0.9 | M31: N/A
A32: 45773 | B32: DEP TFR UPI/CR/548257957091/AAYUSH K/KKBK/95944352 59/Paid 0097738162095 AT 11669 SHIVAJI NAGAR NASIK | D32: 45773 | E32: 0 | F32: 5000 | G32: 17307.21 | J32: Contra - Kotak | K32: KOTAK 0333 | L32: 0.9 | M32: N/A
A33: 45773 | B33: WDL TFR SBIYA25116092502872203439-Deposit or Inv 0039706 255133 OF Mr. AAYUSH KUMAR GUPTA AT 11669 SHIVAJI NAGAR NASIK | D33: 45773 | E33: 5100 | F33: 0 | G33: 12207.21 | J33: SBI PPF | K33: PPF Deposit | L33: 0.9 | M33: N/A
A34: 45779 | B34: DEP TFR UPI/CR/294187471225/AAYUSH K/UTIB/9594435 259/UPI 0097737162096 AT 11669 SHIVAJI NAGAR NASIK | D34: 45779 | E34: 0 | F34: 1 | G34: 12208.21 | J34: Contra - Axis | K34: AXIS | L34: 0.9 | M34: N/A
A35: 45781 | B35: WDL TFR UPI/DR/512468818878/SURUSHE /YESB/Q770971 173/UPI 0097690162095 AT 11669 SHIVAJI NAGAR NASIK | D35: 45781 | E35: 60 | F35: 0 | G35: 12148.21 | H35: Surushe | J35: UPI Payment | K35: Personal | L35: 0.55 | M35: N/A
A36: 45781 | B36: WDL TFR UPI/DR/512468929763/BHIMA RAM/YESB/Q280789 230/UPI 0097690162095 AT 11669 SHIVAJI NAGAR NASIK | D36: 45781 | E36: 114 | F36: 0 | G36: 12034.21 | H36: Bhima Ram | J36: UPI Payment | K36: Personal | L36: 0.55 | M36: N/A
A37: 45785 | B37: DEP TFR UPI/CR/512804757639/MEGHA GU/HDFC/80056043 28/Paid 0097736162097 AT 11669 SHIVAJI NAGAR NASIK | D37: 45785 | E37: 0 | F37: 10 | G37: 12044.21 | J37: Received - Megha Gupta | K37: Megha Gupta | L37: 0.85 | M37: N/A
A38: 45806 | B38: DEP TFR UPI/CR/514924194600/MEGHA GU/HDFC/80056043 28/Paid 0097736162097 AT 11669 SHIVAJI NAGAR NASIK | D38: 45806 | E38: 0 | F38: 1001 | G38: 13045.21 | J38: Received - Megha Gupta | K38: Megha Gupta | L38: 0.85 | M38: N/A
A39: 45806 | B39: WDL TFR UPI/DR/551503965355/MEGHA GU/HDFC/80056043 28/Paid 0097694162092 AT 11669 SHIVAJI NAGAR NASIK | D39: 45806 | E39: 1001 | F39: 0 | G39: 12044.21 | J39: Transfer - Megha Gupta | K39: Megha Gupta | L39: 0.85 | M39: N/A
A40: 45807 | B40: WDL TFR UPI/DR/551616084739/IRCTC CF/HDFC/irctc.cf @h/IRCT 0097695162091 AT 11669 SHIVAJI NAGAR NASIK | D40: 45807 | E40: 437.25 | F40: 0 | G40: 11606.96 | J40: UPI - IRCTC | K40: Travel | L40: 0.68 | M40: N/A
A41: 45810 | B41: DEP TFR IMPS/515322719699/IDF-XX432-PERFIOS /hdf cLifeD 0098302162091 AT 11669 SHIVAJI NAGAR NASIK | D41: 45810 | E41: 0 | F41: 1 | G41: 11607.96 | J41: NEFT Transfer | K41: Transfer | L41: 0.7 | M41: N/A
A42: 45810 | B42: DEP TFR IMPS/515322728710/IDF-XX432-PERFIOS /hdf cLifeD 0098302162091 AT 11669 SHIVAJI NAGAR NASIK | D42: 45810 | E42: 0 | F42: 1 | G42: 11608.96 | J42: NEFT Transfer | K42: Transfer | L42: 0.7 | M42: N/A
A43: 45812 | B43: DEP TFR UPI/CR/515523018585/Razorpay/RATN/Payouts. ra/1745 0097735162098 AT 11669 SHIVAJI NAGAR NASIK | D43: 45812 | E43: 0 | F43: 28 | G43: 11636.96 | J43: Received - Razorpay | K43: Personal | L43: 0.55 | M43: N/A
A44: 45833 | B44: INTERES T CREDIT | D44: 45833 | E44: 0 | F44: 81 | G44: 11717.96 | J44: Bank Interest | K44: Bank Interest | L44: 0.9 | M44: N/A
A45: 45854 | B45: DEP TFR UPI/CR/498006251975/Google Pay/UTIB/google pay@/UP 0097735162098 AT 11669 SHIVAJI NAGAR NASIK | D45: 45854 | E45: 0 | F45: 2 | G45: 11719.96 | J45: UPI - Google Pay | K45: Personal | L45: 0.65 | M45: N/A
A46: 45855 | B46: DEP TFR UPI/CR/682542661985/Google Pay/UTIB/google pay@/UP 0097736162097 AT 11669 SHIVAJI NAGAR NASIK | D46: 45855 | E46: 0 | F46: 2 | G46: 11721.96 | J46: UPI - Google Pay | K46: Personal | L46: 0.65 | M46: N/A
A47: 45880 | B47: WDL TFR UPI/DR/522307669786/SWIGGY/ICIC/upiswiggy@ /Paymen 0097691162095 AT 11669 SHIVAJI NAGAR NASIK | D47: 45880 | E47: 283 | F47: 0 | G47: 11438.96 | J47: UPI - Swiggy | K47: Food & Dining | L47: 0.68 | M47: N/A
A48: 45883 | B48: DEP TFR UPI/CR/897204994636/LAXMIDHA/UCBA/94370586 84/Paym 0097736162097 AT 11669 SHIVAJI NAGAR NASIK | D48: 45883 | E48: 0 | F48: 100 | G48: 11538.96 | J48: Received - Laxmidha | K48: Personal | L48: 0.55 | M48: N/A
... A63: 45944 | B63: DEP TFR UPI/CR/565328839390/MEGHA GU/HDFC/80056043 28/Paid 0097734162099 AT 11669 SHIVAJI NAGAR NASIK | D63: 45944 | E63: 0 | F63: 2500 | G63: 9549.96 | J63: Received - Megha Gupta | K63: Megha Gupta | L63: 0.85 | M63: N/A
A64: 45966 | B64: WDL TFR UPI/DR/567599014620/HARSH DI/HDFC/harsh.k oka/UPI 0097693162093 AT 11669 SHIVAJI NAGAR NASIK | D64: 45966 | E64: 1501 | F64: 0 | G64: 8048.96 | H64: Harsh Di | J64: UPI Payment | K64: Personal | L64: 0.55 | M64: N/A
A65: 45975 | B65: DEP TFR UPI/CR/568428703730/MEGHA GU/HDFC/80056043 28/Paid 0097737162096 AT 11669 SHIVAJI NAGAR NASIK | D65: 45975 | E65: 0 | F65: 700 | G65: 8748.96 | J65: Received - Megha Gupta | K65: Megha Gupta | L65: 0.85 | M65: N/A
A66: 46001 | B66: DEP TFR UPI/CR/571063600506/Miss MEG/CBIN/meghagh ati/UPI 0097735162098 AT 11669 SHIVAJI NAGAR NASIK | D66: 46001 | E66: 0 | F66: 50 | G66: 8798.96 | J66: Received - Megha Gupta | K66: Megha Gupta | L66: 0.85 | M66: N/A
A67: 46001 | B67: DEP TFR UPI/CR/571025401558/Miss MEG/CBIN/meghagh ati/UPI 0097735162098 AT 11669 SHIVAJI NAGAR NASIK | D67: 46001 | E67: 0 | F67: 5000 | G67: 13798.96 | J67: Received - Megha Gupta | K67: Megha Gupta | L67: 0.85 | M67: N/A
A68: 46001 | B68: WDL TFR UPI/DR/534423871983/AAYUSH K/KKBK/aayush2 0gu/UPI 0097693162093 AT 11669 SHIVAJI NAGAR NASIK | D68: 46001 | E68: 5000 | F68: 0 | G68: 8798.96 | J68: Contra - Kotak | K68: KOTAK 0333 | L68: 0.9 | M68: N/A
A69: 46013 | B69: DEP TFR UPI/CR/535623790031/Miss MEG/CBIN/meghagh ati/UPI 0097733162090 AT 11669 SHIVAJI NAGAR NASIK | D69: 46013 | E69: 0 | F69: 150 | G69: 8948.96 | J69: Received - Megha Gupta | K69: Megha Gupta | L69: 0.85 | M69: N/A
A70: 46014 | B70: DEP TFR UPI/CR/572327731584/ARCHIT G/UTIB/archit4 801/UPI 0097734162099 AT 11669 SHIVAJI NAGAR NASIK | D70: 46014 | E70: 0 | F70: 5000 | G70: 13948.96 | J70: Received - Archit Gupta | K70: Archit Gupta | L70: 0.85 | M70: N/A
A71: 46014 | B71: DEP TFR UPI/CR/572336816675/ARCHIT G/UTIB/archit4 801/UPI 0097734162099 AT 11669 SHIVAJI NAGAR NASIK | D71: 46014 | E71: 0 | F71: 5000 | G71: 18948.96 | J71: Received - Archit Gupta | K71: Archit Gupta | L71: 0.85 | M71: N/A
A72: 46014 | B72: WDL TFR UPI/DR/572305853332/ARCHIT G/UTIB/archit48 01/Paid 0097692162094 AT 11669 SHIVAJI NAGAR NASIK | D72: 46014 | E72: 10000 | F72: 0 | G72: 8948.96 | J72: Transfer - Archit Gupta | K72: Archit Gupta | L72: 0.85 | M72: N/A
A73: 46015 | B73: DEP TFR UPI/CR/535879515241/Miss MEG/CBIN/meghagh ati/UPI 0097735162098 AT 11669 SHIVAJI NAGAR NASIK | D73: 46015 | E73: 0 | F73: 100 | G73: 9048.96 | J73: Received - Megha Gupta | K73: Megha Gupta | L73: 0.85 | M73: N/A
A74: 46016 | B74: DEP TFR UPI/CR/696221419888/TN99/HDFC/gonnadrv@p/S ent usi 0097736162097 AT 11669 SHIVAJI NAGAR NASIK | D74: 46016 | E74: 0 | F74: 1000 | G74: 10048.96 | J74: Received - Tn99 | K74: Personal | L74: 0.55 | M74: N/A
A75: 46016 | B75: INTERES T CREDIT | D75: 46016 | E75: 0 | F75: 60 | G75: 10108.96 | J75: Bank Interest | K75: Bank Interest | L75: 0.9 | M75: N/A
A76: 46020 | B76: DEP TFR NEFT*INDB0000006*INDBH29125478318*PAYMENT ESCROW 0099509044300 AT 11669 SHIVAJI NAGAR NASIK | D76: 46020 | E76: 0 | F76: 17320.33 | G76: 27429.29 | J76: Freelance Income | K76: Misc Income | L76: 0.92 | M76: N/A
A77: 46021 | B77: WDL TFR UPI/DR/536465560825/CRED Club/UTIB/cred.cl ub@/pay 0097692162094 AT 11669 SHIVAJI NAGAR NASIK | D77: 46021 | E77: 1450 | F77: 0 | G77: 25979.29 | J77: Credit Card Bill Payment (CRED) | K77: Credit Card | L77: 0.85 | M77: N/A
A78: 46021 | B78: WDL TFR UPI/DR/536470546712/VIJEESH B/CNRB/vijeesh 289/Pai 0097692162094 AT 11669 SHIVAJI NAGAR NASIK | D78: 46021 | E78: 3158 | F78: 0 | G78: 22821.29 | H78: Vijeesh B | J78: UPI Payment | K78: Personal | L78: 0.55 | M78: N/A
A79: 46021 | B79: WDL TFR UPI/DR/536479469562/95944352/KKBK/95944352 59/Paid 0097692162094 AT 11669 SHIVAJI NAGAR NASIK | D79: 46021 | E79: 4000 | F79: 0 | G79: 18821.29 | J79: Contra - Kotak | K79: KOTAK 0333 | L79: 0.88 | M79: N/A
A80: 46022 | B80: WDL TFR UPI/DR/536581481598/CRED Club/UTIB/cred.cl ub@/pay 0097693162093 AT 11669 SHIVAJI NAGAR NASIK | D80: 46022 | E80: 1500 | F80: 0 | G80: 17321.29 | J80: Credit Card Bill Payment (CRED) | K80: Credit Card | L80: 0.85 | M80: N/A
A81: 46022 | B81: WDL TFR UPI/DR/536589002936/ABDUL HA/BARB/ponaniha se/Paid 0097693162093 AT 11669 SHIVAJI NAGAR NASIK | D81: 46022 | E81: 140 | F81: 0 | G81: 17181.29 | H81: Abdul Ha | J81: UPI Payment | K81: Personal | L81: 0.55 | M81: N/A
A82: 46022 | B82: WDL TFR UPI/DR/536589750332/FAMILY F/IDFB/88098256 @i/Paid 0097693162093 AT 11669 SHIVAJI NAGAR NASIK | D82: 46022 | E82: 35 | F82: 0 | G82: 17146.29 | H82: Family F | J82: UPI Payment | K82: Personal | L82: 0.55 | M82: N/A
A83: 46022 | B83: WDL TFR UPI/DR/536589825371/Nandini/YESB/paytm.s1 au/Paid 0097693162093 AT 11669 SHIVAJI NAGAR NASIK | D83: 46022 | E83: 52 | F83: 0 | G83: 17094.29 | J83: UPI - Nandini Dairy | K83: Groceries | L83: 0.82 | M83: N/A
A84: 46023 | B84: WDL TFR UPI/DR/636725025260/FOTO FIELD/YESB/paytmq r647/Pa 0097694162092 AT 11669 SHIVAJI NAGAR NASIK | D84: 46023 | E84: 320 | F84: 0 | G84: 16774.29 | J84: UPI - Paytm | K84: Personal | L84: 0.65 | M84: N/A
A85: 46023 | B85: WDL TFR UPI/DR/636730425595/YASH PA/YESB/q6432024 45/Paid 0097694162092 AT 11669 SHIVAJI NAGAR NASIK | D85: 46023 | E85: 119 | F85: 0 | G85: 16655.29 | H85: Yash Pa | J85: UPI Payment | K85: Personal | L85: 0.55 | M85: N/A
A86: 46024 | B86: WDL TFR UPI/DR/636844899292/Pavithra Y/YESB/paytm. s18x/Pa 0097695162091 AT 11669 SHIVAJI NAGAR NASIK | D86: 46024 | E86: 30 | F86: 0 | G86: 16625.29 | J86: UPI - Paytm | K86: Personal | L86: 0.65 | M86: N/A
A87: 46024 | B87: WDL TFR UPI/DR/636844984756/MRP FRUI/UTIB/gpay-112 53/Paid 0097695162091 AT 11669 SHIVAJI NAGAR NASIK | D87: 46024 | E87: 160 | F87: 0 | G87: 16465.29 | J87: UPI - Google Pay | K87: Personal | L87: 0.65 | M87: N/A
A88: 46024 | B88: WDL TFR UPI/DR/636845452513/Nagamani/YESB/paytmqr6 j4/Paid 0097695162091 AT 11669 SHIVAJI NAGAR NASIK | D88: 46024 | E88: 100 | F88: 0 | G88: 16365.29 | J88: UPI - Paytm | K88: Personal | L88: 0.65 | M88: N/A
A89: 46024 | B89: WDL TFR UPI/DR/636845545897/NALABHIM/YESB/paytmqr6 uv/Paid 0097695162091 AT 11669 SHIVAJI NAGAR NASIK | D89: 46024 | E89: 63 | F89: 0 | G89: 16302.29 | J89: UPI - Paytm | K89: Personal | L89: 0.65 | M89: N/A
A90: 46035 | B90: WDL TFR UPI/DR/637914326838/VODAFONE/HSBC/viprevf@ hs/Paid 0097691162095 AT 11669 SHIVAJI NAGAR NASIK | D90: 46035 | E90: 470 | F90: 0 | G90: 15832.29 | H90: Vodafone | J90: UPI Payment | K90: Personal | L90: 0.55 | M90: N/A
A91: 46037 | B91: WDL TFR UPI/DR/638125719461/DISTRICT/AIRP/district di/UPII 0097693162093 AT 11669 SHIVAJI NAGAR NASIK | D91: 46037 | E91: 50 | F91: 0 | G91: 15782.29 | H91: District | J91: UPI Payment | K91: Personal | L91: 0.55 | M91: N/A
A92: 46037 | B92: DEP TFR UPI/CR/601569478286/AAYUSH K/KKBK/95944352 59/Paid 0097735162098 AT 11669 SHIVAJI NAGAR NASIK | D92: 46037 | E92: 0 | F92: 4217.71 | G92: 20000 | J92: Contra - Kotak | K92: KOTAK 0333 | L92: 0.9 | M92: N/A
A93: 46037 | B93: DEP TFR UPI/CR/601569529799/AAYUSH K/KKBK/95944352 59/Paid 0097735162098 AT 11669 SHIVAJI NAGAR NASIK | D93: 46037 | E93: 0 | F93: 8000 | G93: 28000 | J93: Contra - Kotak | K93: KOTAK 0333 | L93: 0.9 | M93: N/A
A94: 46043 | B94: DEP TFR UPI/CR/476311256183/CHIRAG P/HDFC/chiragtu ba/Paym 0097734162099 AT 11669 SHIVAJI NAGAR NASIK | D94: 46043 | E94: 0 | F94: 318 | G94: 28318 | J94: Received - Chirag P | K94: Personal | L94: 0.55 | M94: N/A
A95: 46050 | B95: WDL TFR UPI/DR/929509588404/IRCTC ET/NSPB/cf.irctc @c/IRCT 0097692162094 AT 11669 SHIVAJI NAGAR NASIK | D95: 46050 | E95: 4413.6 | F95: 0 | G95: 23904.4 | J95: UPI - IRCTC | K95: Travel | L95: 0.68 | M95: N/A
A96: 46051 | B96: WDL TFR UPI/DR/639588556111/95944352/KKBK/95944352 59/Paid 0097693162093 AT 11669 SHIVAJI NAGAR NASIK | D96: 46051 | E96: 4000 | F96: 0 | G96: 19904.4 | J96: Contra - Kotak | K96: KOTAK 0333 | L96: 0.88 | M96: N/A
A97: 46052 | B97: DEP TFR NEFT*HDFC0000001*HDFCH00768841281*AAYUSH K UMAR GU 0099509044300 AT 11669 SHIVAJI NAGAR NASIK | D97: 46052 | E97: 0 | F97: 50000 | G97: 69904.4 | J97: Contra - HDFC | K97: HDFC 5413 | L97: 0.9 | M97: N/A
A98: 46052 | B98: WDL TFR UPI/DR/603041682315/ABHINDAN/YESB/q144456 834/UPI 0097694162092 AT 11669 SHIVAJI NAGAR NASIK | D98: 46052 | E98: 39674 | F98: 0 | G98: 30230.4 | J98: Contra - Self | K98: Transfer | L98: 0.8 | M98: N/A
A99: 46054 | B99: DEP TFR UPI/CR/639848674109/SHETAANS/KKBK/20shait ank/UPI 0097738162095 AT 11669 SHIVAJI NAGAR NASIK | D99: 46054 | E99: 0 | F99: 1000 | G99: 31230.4 | J99: Received - Shetaans | K99: Personal | L99: 0.55 | M99: N/A
A100: 46054 | B100: WDL TFR UPI/DR/639829452747/YASH GUPTA/ICIC/yashgu pta1/kr 0097696162090 AT 11669 SHIVAJI NAGAR NASIK | D100: 46054 | E100: 700 | F100: 0 | G100: 30530.4 | H100: Yash Gupta | J100: UPI Payment | K100: Personal | L100: 0.75 | M100: N/A
A101: 46054 | B101: WDL TFR UPI/DR/639800450547/SHETAANS/KKBK/20shaita nk/arey 0097696162090 AT 11669 SHIVAJI NAGAR NASIK | D101: 46054 | E101: 1000 | F101: 0 | G101: 29530.4 | H101: Shetaans | J101: UPI Payment | K101: Personal | L101: 0.55 | M101: N/A
A102: 46054 | B102: DEP TFR UPI/CR/603222539038/YASH GUPTA/HDFC/yashgu pta1/pa 0097738162095 AT 11669 SHIVAJI NAGAR NASIK | D102: 46054 | E102: 0 | F102: 700 | G102: 30230.4 | J102: Received - Yash Gupta | K102: Personal | L102: 0.55 | M102: N/A
A103: 46054 | B103: WDL TFR UPI/DR/639931458810/YASH GUPTA/HDFC/yashgu pta1/kr 0097690162095 AT 11669 SHIVAJI NAGAR NASIK | D103: 46054 | E103: 700 | F103: 0 | G103: 29530.4 | H103: Yash Gupta | J103: UPI Payment | K103: Personal | L103: 0.75 | M103: N/A
A104: 46055 | B104: DEP TFR UPI/CR/603391938344/AAYUSH K/UTIB/95944352 59/Paid 0097732162091 AT 11669 SHIVAJI NAGAR NASIK | D104: 46055 | E104: 0 | F104: 6469.6 | G104: 36000 | J104: Contra - Axis | K104: AXIS | L104: 0.9 | M104: N/A
A105: 46056 | B105: DEP TFR UPI/CR/603463766641/SHETAANS/KKBK/20shait ank/UPI 0097733162090 AT 11669 SHIVAJI NAGAR NASIK | D105: 46056 | E105: 0 | F105: 1000 | G105: 37000 | J105: Received - Shetaans | K105: Personal | L105: 0.55 | M105: N/A
A106: 46079 | B106: WDL TFR UPI/DR/520699040576/AAYUSH K/KKBK/9594435 259/UPI 0097693162093 AT 11669 SHIVAJI NAGAR NASIK | D106: 46079 | E106: 1000 | F106: 0 | G106: 36000 | J106: Contra - Kotak | K106: KOTAK 0333 | L106: 0.9 | M106: N/A
A107: 46084 | B107: WDL TFR UPI/DR/109300057514/Zerodha /ICIC/zerodha. rz/gJgY 0097691162095 AT 11669 SHIVAJI NAGAR NASIK | D107: 46084 | E107: 26000 | F107: 0 | G107: 10000 | J107: Zerodha Broking | K107: Zerodha Broking Limited | L107: 0.88 | M107: N/A
A108: 46088 | B108: DEP TFR UPI/CR/102865244357/NPCI BHIM/HDFC/bhimcas hba/BHI 0097737162096 AT 11669 SHIVAJI NAGAR NASIK | D108: 46088 | E108: 0 | F108: 20 | G108: 10020 | J108: Cashback - BHIM | K108: Misc Income | L108: 0.88 | M108: N/A
A109: 46090 | B109: CEMTEX DEP UPI/ONRF/92 9509588404/280126/070326 | D109: 46090 | E109: 0 | F109: 2130 | G109: 12150 | J109: UPI Receipt | K109: Personal | L109: 0.55 | M109: N/A
A110: 46096 | B110: WDL TFR UPI/DR/644021649518/IRCTC ET/NSPB/cf.irctc @c/IRCT 0097696162090 AT 11669 SHIVAJI NAGAR NASIK | D110: 46096 | E110: 4513.6 | F110: 0 | G110: 7636.4 | J110: UPI - IRCTC | K110: Travel | L110: 0.68 | M110: N/A
A111: 46100 | B111: WDL TFR UPI/DR/607831805822/JioHotstar/YESB/hotsta ronl/Co 0097693162093 AT 11669 SHIVAJI NAGAR NASIK | D111: 46100 | E111: 20 | F111: 0 | G111: 7616.4 | J111: UPI - Hotstar | K111: Subscriptions | L111: 0.68 | M111: N/A
A112: 46101 | B112: DEP TFR UPI/CR/102949205929/NPCI BHIM/HDFC/bhimcas hba/BHI 0097736162097 AT 11669 SHIVAJI NAGAR NASIK | D112: 46101 | E112: 0 | F112: 8 | G112: 7624.4 | J112: Cashback - BHIM | K112: Misc Income | L112: 0.88 | M112: N/A
A113: 46104 | B113: DEP TFR UPI/CR/102962359041/NPCI BHIM/HDFC/bhimcas hba/BHI 0097732162091 AT 11669 SHIVAJI NAGAR NASIK | D113: 46104 | E113: 0 | F113: 50 | G113: 7674.4 | J113: Cashback - BHIM | K113: Misc Income | L113: 0.88 | M113: N/A
A114: 46105 | B114: DEP TFR UPI/CR/102969232051/NPCI BHIM/HDFC/bhimcas hba/BHI 0097733162090 AT 11669 SHIVAJI NAGAR NASIK | D114: 46105 | E114: 0 | F114: 2 | G114: 7676.4 | J114: Cashback - BHIM | K114: Misc Income | L114: 0.88 | M114: N/A
A115: 46106 | B115: DEP TFR UPI/CR/102974706292/NPCI BHIM/HDFC/bhimcas hba/BHI 0097734162099 AT 11669 SHIVAJI NAGAR NASIK | D115: 46106 | E115: 0 | F115: 10 | G115: 7686.4 | J115: Cashback - BHIM | K115: Misc Income | L115: 0.88 | M115: N/A
...

Sheet SBM Bank
B1: SBM Bank Narration Sheet
B2: Colour Legend of Categories:
B3: Bank Interest | C3: Contra - Kotak
A5: Date | B5: Particulars | C5: Ref | D5: Value_Date | E5: DR | F5: CR | G5: Balance | H5: Beneficiary | I5: Human_Narration | J5: Auto_Narration | K5: Account_Head | L5: Confidence | M5: Match
A6: 45778 | B6: 20052205306441:Int.Pd:31-03-2025 to 30-04-2025 | D6: 45778 | E6: 0 | F6: 1 | G6: 238 | I6: Bank Interest | J6: Bank Interest | K6: Bank Interest | L6: 0.97 | M6: [MATCH]
A7: 45809 | B7: 20052205306441:Int.Pd:01-05-2025 to 31-05-2025 | D7: 45809 | E7: 0 | F7: 1 | G7: 239 | I7: Bank Interest | J7: Bank Interest | K7: Bank Interest | L7: 0.97 | M7: [MATCH]
A8: 45839 | B8: 20052205306441:Int.Pd:01-06-2025 to 30-06-2025 | D8: 45839 | E8: 0 | F8: 1 | G8: 240 | I8: Bank Interest | J8: Bank Interest | K8: Bank Interest | L8: 0.97 | M8: [MATCH]
A9: 45870 | B9: 20052205306441:Int.Pd:01-07-2025 to 31-07-2025 | D9: 45870 | E9: 0 | F9: 1 | G9: 241 | I9: Bank Interest | J9: Bank Interest | K9: Bank Interest | L9: 0.97 | M9: [MATCH]
A10: 45870 | B10: NEFT/STCB010825236957/Aayush Kumar Gupta | C10: STCB010825236957 | D10: 45870 | E10: 241 | F10: 0 | G10: 0 | I10: Contra - Kotak | J10: Contra - Kotak | K10: KOTAK 0333 | L10: 0.9 | M10: [MATCH]

Sheet For Tally
B1: Tally Export Narration Sheet
B2: Colour Legend of Categories:
B3: SIP | C3: UPI Payment | D3: Contra - SBI | E3: Contra - Axis | F3: Rent
B4: Credit Card Bill Payment (CRED) | C4: Transfer - Megha Gupta | D4: Salary | E4: HDFC Securities - Settlement | F4: HDFC Securities - Buy
B5: SuperMoney (Rewards) | C5: HDFC Securities - Sell | D5: UPI - Paytm | E5: UPI - Nandini Dairy | F5: Zerodha Broking
B6: Annuity Income | C6: Bank Charges | D6: UPI - IRCTC | E6: Misc Income | F6: MF Redemption
B7: UPI - CRED | C7: UPI Reversal | D7: Cash Withdrawal | E7: Govt / Utility Payment | F7: MF Investment
B8: Depository Charges | C8: Received - Dnyaneshwar Kuyate | D8: Received - Megha Gupta | E8: Contra - Kotak | F8: UPI - Amazon
B9: Received - Ashok Divedi | C9: Bank Interest | D9: UPI - Fresh Produce | E9: Rent Payment (via CRED) | F9: UPI - MedPlus
B10: IMPS Receipt | C10: Transfer - Sunita Gupta | D10: Received - Ajay Gupta | E10: UPI - BharatPe | F10: Dividend Income
B11: Transfer - Archit Gupta | C11: Received - Sunita Gupta | D11: Refund - Wakefit | E11: Received - Archit Gupta | F11: NEFT Transfer
B12: UPI - Fuel | C12: Received - Razorpay | D12: Cashback - Kiwi | E12: INDmoney Investment | F12: Depository Credit
B13: Card Purchase | C13: Lounge Access Charge | D13: Securities Settlement | E13: Transfer - Ajay Gupta | F13: UPI - Fuel (HPCL)
B14: UPI - Google Pay | C14: UPI - Google Play | D14: UPI - Star Bazaar | E14: Insurance Premium | F14: Contra - SBM
... B22: Received - Ret | C22: Contra - Self | D22: Contra - HDFC | E22: Received - Shetaans | F22: Received - Yash Gupta
B23: Cashback - BHIM | C23: UPI Receipt | D23: UPI - Flipkart
A25: TX Date | B25: Date | C25: DR | D25: CR | E25: Beneficiary | F25: Narration | G25: Confidence | H25: Account Head | I25: Account No | J25: Kya Hai? | K25: Particulars | L25: Bank | M25: Duplicate
A26: 45748 | B26: 45748 | C26: 5000 | D26: 0 | F26: SIP | G26: 0.95 | H26: SIP | I26: HDFC 5413 | K26: ACH D- TP ACH INDIANESIGN-1758642535 | L26: HDFC Bank
A27: 45748.457 | B27: 45748 | C27: 121 | D27: 0 | E27: Barathi Anbazha | F27: UPI Payment | G27: 0.55 | H27: Personal | I27: KOTAK 0333 | K27: UPI/BARATHI ANBAZHA/509137039846/Paid via SuperM | L27: Kotak Mahindra Bank
A28: 45748.709 | B28: 45748 | C28: 30 | D28: 0 | E28: Samosa Party Ba | F28: UPI Payment | G28: 0.55 | H28: Personal | I28: KOTAK 0333 | K28: UPI/SAMOSA PARTY Ba/509141156489/Paid via SuperM | L28: Kotak Mahindra Bank
A29: 45749 | B29: 45749 | C29: 1 | D29: 0 | F29: Contra - SBI | G29: 0.9 | H29: SBI 1227 | I29: AXIS | J29: UPI | K29: UPI/P2A/765226990925/AAYUSH KUMAR GUPTA /UPI/State Bank Of India | L29: Axis Bank | M29: ⚠ Possible Duplicate
A30: 45749 | B30: 45749 | C30: 40000 | D30: 0 | F30: Contra - SBI | G30: 0.9 | H30: SBI 1227 | I30: AXIS | J30: Transfer to SBI self | K30: UPI/P2A/765382250925/AAYUSH KUMAR GUPTA /UPI/State Bank Of India | L30: Axis Bank
A31: 45749 | B31: 45749 | C31: 0 | D31: 1 | F31: Contra - Axis | G31: 0.9 | H31: AXIS | I31: SBI 1227 | K31: DEP TFR UPI/CR/765226990925/AAYUSH K/UTIB/9594435 259/UPI 0097735162098 AT 11669 SHIVAJI NAGAR NASIK | L31: State Bank of India | M31: ⚠ Possible Duplicate
A32: 45749 | B32: 45749 | C32: 0 | D32: 40000 | F32: Contra - Axis | G32: 0.9 | H32: AXIS | I32: SBI 1227 | K32: DEP TFR UPI/CR/765382250925/AAYUSH K/UTIB/9594435 259/UPI 0097735162098 AT 11669 SHIVAJI NAGAR NASIK | L32: State Bank of India
A33: 45749 | B33: 45749 | C33: 23000 | D33: 0 | F33: Rent | G33: 0.9 | H33: Rent | I33: SBI 1227 | K33: WDL TFR UPI/DR/545893374949/CRED RENT/UTIB/cred.re nt@/pay 0097693162093 AT 11669 SHIVAJI NAGAR NASIK | L33: State Bank of India
A34: 45749 | B34: 45749 | C34: 0 | D34: 1 | F34: Contra - Axis | G34: 0.9 | H34: AXIS | I34: SBI 1227 | K34: DEP TFR NEFT*UTIB0002656*AXOMB09202414101*AAYUSH K UMAR GU 0099509044300 AT 11669 SHIVAJI NAGAR NASIK | L34: State Bank of India | M34: ⚠ Possible Duplicate
A35: 45749 | B35: 45749 | C35: 3000 | D35: 0 | F35: Credit Card Bill Payment (CRED) | G35: 0.85 | H35: Credit Card | I35: SBI 1227 | K35: WDL TFR UPI/DR/509208961213/CRED Club/UTIB/cred.cl ub@/pay 0097693162093 AT 11669 SHIVAJI NAGAR NASIK | L35: State Bank of India
A36: 45749 | B36: 45749 | C36: 2000 | D36: 0 | F36: Transfer - Megha Gupta | G36: 0.85 | H36: Megha Gupta | I36: SBI 1227 | K36: WDL TFR UPI/DR/545868712527/Miss. ME/CBIN/meghagha ti/Paid 0097693162093 AT 11669 SHIVAJI NAGAR NASIK | L36: State Bank of India
A37: 45749 | B37: 45749 | C37: 2000 | D37: 0 | F37: Credit Card Bill Payment (CRED) | G37: 0.85 | H37: Credit Card | I37: SBI 1227 | K37: WDL TFR UPI/DR/545878868808/CRED Club/UTIB/cred.cl ub@/pay 0097693162093 AT 11669 SHIVAJI NAGAR NASIK | L37: State Bank of India | M37: ⚠ Possible Duplicate
A38: 45749 | B38: 45749 | C38: 2000 | D38: 0 | F38: Credit Card Bill Payment (CRED) | G38: 0.85 | H38: Credit Card | I38: SBI 1227 | K38: WDL TFR UPI/DR/545887987358/CRED Club/UTIB/cred.cl ub@/pay 0097693162093 AT 11669 SHIVAJI NAGAR NASIK | L38: State Bank of India | M38: ⚠ Possible Duplicate
A39: 45749 | B39: 45749 | C39: 1 | D39: 0 | F39: Contra - SBI | G39: 0.9 | H39: SBI 1227 | I39: AXIS | J39: UPI | K39: NEFT/MB/AXOMB09202414101/AAYUSH KUMAR GUPTA/STATE BANK OF INDIA/ | L39: Axis Bank | M39: ⚠ Possible Duplicate
A40: 45749 | B40: 45749 | C40: 0 | D40: 66897 | F40: Salary | G40: 0.95 | H40: Salary | I40: AXIS | J40: Salary | K40: Salary For the Month of Mar 2025 | L40: Axis Bank
A41: 45749 | B41: 45749 | C41: 0 | D41: 5239.85 | F41: HDFC Securities - Settlement | G41: 0.93 | H41: HDFC Securities | I41: HDFC 5413 | K41: FT- 623432246-50200085415108 - HDFC SECURITIES LTD-CLIENT DSCNB A/C - | L41: HDFC Bank
A42: 45749 | B42: 45749 | C42: 9081.73 | D42: 0 | F42: HDFC Securities - Buy | G42: 0.97 | H42: HDFC Securities | I42: HDFC 5413 | K42: NET PI TO HSL SEC A/C 2554606-00602340029427 | L42: HDFC Bank
A43: 45749 | B43: 45749 | C43: 150.26 | D43: 0 | F43: HDFC Securities - Buy | G43: 0.97 | H43: HDFC Securities | I43: HDFC 5413 | K43: NET PI TO HSL SEC A/C 2554606-00602340029427 | L43: HDFC Bank
A44: 45750 | B44: 45750 | C44: 0 | D44: 656.71 | F44: HDFC Securities - Settlement | G44: 0.93 | H44: HDFC Securities | I44: HDFC 5413 | K44: FT- 623852638-50200085415108 - HDFC SECURITIES LTD-CLIENT DSCNB A/C - | L44: HDFC Bank
A45: 45750 | B45: 45750 | C45: 134.41 | D45: 0 | F45: HDFC Securities - Buy | G45: 0.97 | H45: HDFC Securities | I45: HDFC 5413 | K45: NET PI TO HSL SEC A/C 2554606-00602340029427 | L45: HDFC Bank
A46: 45750 | B46: 45750 | C46: 2000 | D46: 0 | F46: Credit Card Bill Payment (CRED) | G46: 0.85 | H46: Credit Card | I46: SBI 1227 | K46: WDL TFR UPI/DR/545972230401/CRED Club/UTIB/cred.cl ub@/pay 0097694162092 AT 11669 SHIVAJI NAGAR NASIK | L46: State Bank of India | M46: ⚠ Possible Duplicate
A47: 45750 | B47: 45750 | C47: 2360.82 | D47: 0 | F47: Credit Card Bill Payment (CRED) | G47: 0.85 | H47: Credit Card | I47: SBI 1227 | K47: WDL TFR UPI/DR/509336037048/CRED Club/UTIB/cred.cl ub@/pay 0097694162092 AT 11669 SHIVAJI NAGAR NASIK | L47: State Bank of India
A48: 45750 | B48: 45750 | C48: 2000 | D48: 0 | F48: Credit Card Bill Payment (CRED) | G48: 0.85 | H48: Credit Card | I48: SBI 1227 | K48: WDL TFR UPI/DR/509378949775/CRED Club/UTIB/cred.cl ub@/pay 0097694162092 AT 11669 SHIVAJI NAGAR NASIK | L48: State Bank of India | M48: ⚠ Possible Duplicate
A49: 45750.765 | B49: 45750 | C49: 50 | D49: 0 | E49: Mrs. G Pavithr | F49: UPI Payment | G49: 0.55 | H49: Personal | I49: KOTAK 0333 | K49: UPI/Mrs. G Pavithr/509367683617/Paid via SuperM | L49: Kotak Mahindra Bank
A50: 45750.949 | B50: 45750 | C50: 0 | D50: 66.74 | F50: SuperMoney (Rewards) | G50: 0.88 | H50: Misc Income | I50: KOTAK 0333 | K50: UPI/supermoney/509381273041/Supermoney Rewa | L50: Kotak Mahindra Bank
A51: 45751 | B51: 45751 | C51: 0 | D51: 10041.41 | F51: HDFC Securities - Settlement | G51: 0.93 | H51: HDFC Securities | I51: HDFC 5413 | K51: FT- 624254248-50200085415108 - HDFC SECURITIES LTD-CLIENT DSCNB A/C - | L51: HDFC Bank
A52: 45751 | B52: 45751 | C52: 115.2 | D52: 0 | F52: HDFC Securities - Buy | G52: 0.97 | H52: HDFC Securities | I52: HDFC 5413 | K52: NET PI TO HSL SEC A/C 2554606-00602340029427 | L52: HDFC Bank
A53: 45751 | B53: 45751 | C53: 0 | D53: 6146.26 | F53: HDFC Securities - Sell | G53: 0.97 | H53: HDFC Securities | I53: HDFC 5413 | K53: NET PO FROM HSL A/C 2554606-50200085415108 | L53: HDFC Bank
A54: 45751 | B54: 45751 | C54: 210 | D54: 0 | F54: UPI - Paytm | G54: 0.65 | H54: Personal | I54: SBI 1227 | K54: WDL TFR UPI/DR/509438120147/MATS FUE/YESB/paytm-31 10/Paid 0097695162091 AT 11669 SHIVAJI NAGAR NASIK | L54: State Bank of India
A55: 45751.957 | B55: 45751 | C55: 285 | D55: 0 | E55: Walko Food Comp | F55: UPI Payment | G55: 0.55 | H55: Personal | I55: KOTAK 0333 | K55: UPI/WALKO FOOD COMP/509484810231/Paid via SuperM | L55: Kotak Mahindra Bank
A56: 45752 | B56: 45752 | C56: 60 | D56: 0 | F56: UPI - Nandini Dairy | G56: 0.82 | H56: Groceries | I56: SBI 1227 | K56: WDL TFR UPI/DR/546194213465/Nandini/YESB/paytm.s1 c3/Paid 0097696162090 AT 11669 SHIVAJI NAGAR NASIK | L56: State Bank of India
A57: 45752.341 | B57: 45752 | C57: 0 | D57: 4213.71 | F57: Zerodha Broking | G57: 0.92 | H57: Zerodha Broking Limited | I57: KOTAK 0333 | K57: NEFT YESF350953824281 ZERODHA BROKING LTD DSCNB A | L57: Kotak Mahindra Bank
A58: 45752.781 | B58: 45752 | C58: 210 | D58: 0 | E58: Counter 4 | F58: UPI Payment | G58: 0.55 | H58: Personal | I58: KOTAK 0333 | K58: UPI/Counter 4/509593584977/Paid via SuperM | L58: Kotak Mahindra Bank
A59: 45753.756 | B59: 45753 | C59: 30 | D59: 0 | E59: Dinesh Kumar Gu | F59: UPI Payment | G59: 0.55 | H59: Personal | I59: KOTAK 0333 | K59: UPI/DINESH KUMAR GU/546205310184/Paid via SuperM | L59: Kotak Mahindra Bank
A60: 45754 | B60: 45754 | C60: 323.04 | D60: 0 | F60: HDFC Securities - Buy | G60: 0.97 | H60: HDFC Securities | I60: HDFC 5413 | K60: NET PI TO HSL SEC A/C 2554606-00602340029427 | L60: HDFC Bank
A61: 45754 | B61: 45754 | C61: 0 | D61: 1880 | F61: Annuity Income | G61: 0.95 | H61: Annuity | I61: HDFC 5413 | K61: HDFCLIFE CENTR-038144668 | L61: HDFC Bank
A62: 45754 | B62: 45754 | C62: 6242.17 | D62: 0 | F62: HDFC Securities - Buy | G62: 0.97 | H62: HDFC Securities | I62: HDFC 5413 | K62: NET PI TO HSL SEC A/C 2554606-00602340029427 | L62: HDFC Bank
A63: 45755 | B63: 45755 | C63: 8913.03 | D63: 0 | F63: HDFC Securities - Buy | G63: 0.97 | H63: HDFC Securities | I63: HDFC 5413 | K63: NET PI TO HSL SEC A/C 2554606-00602340029427 | L63: HDFC Bank
A64: 45755 | B64: 45755 | C64: 295 | D64: 0 | F64: Bank Charges | G64: 0.9 | H64: Bank Charges | I64: HDFC 5413 | K64: ISAQMC-OCT-DEC24-417944 130325-MIR2609890209148 | L64: HDFC Bank
A65: 45755 | B65: 45755 | C65: 92.57 | D65: 0 | F65: HDFC Securities - Buy | G65: 0.97 | H65: HDFC Securities | I65: HDFC 5413 | K65: NET PI TO HSL SEC A/C 2554606-00602340029427 | L65: HDFC Bank
A66: 45755 | B66: 45755 | C66: 1241.91 | D66: 0 | F66: HDFC Securities - Buy | G66: 0.97 | H66: HDFC Securities | I66: HDFC 5413 | K66: NET PI TO HSL SEC A/C 2554606-00602340029427 | L66: HDFC Bank
A67: 45756 | B67: 45756 | C67: 88.96 | D67: 0 | F67: HDFC Securities - Buy | G67: 0.97 | H67: HDFC Securities | I67: HDFC 5413 | K67: NET PI TO HSL SEC A/C 2554606-00602340029427 | L67: HDFC Bank
A68: 45756 | B68: 45756 | C68: 1969.84 | D68: 0 | F68: HDFC Securities - Buy | G68: 0.97 | H68: HDFC Securities | I68: HDFC 5413 | K68: NET PI TO HSL SEC A/C 2554606-00602340029427 | L68: HDFC Bank
A69: 45757 | B69: 45757 | C69: 5704.5 | D69: 0 | F69: UPI - IRCTC | G69: 0.88 | H69: Travel | I69: AXIS | J69: UPI | K69: UPI/P2M/100335047021/Autope Payment Soluti/Paymen/HDFC BANK LTD | L69: Axis Bank
A70: 45758 | B70: 45758 | C70: 279 | D70: 0 | E70: Ferdus | F70: UPI Payment | G70: 0.55 | H70: Personal | I70: SBI 1227 | K70: WDL TFR UPI/DR/510189443769/Ferdus /FINO/fardusal om/Paid 0097695162091 AT 11669 SHIVAJI NAGAR NASIK | L70: State Bank of India
A71: 45758 | B71: 45758 | C71: 192.16 | D71: 0 | F71: HDFC Securities - Buy | G71: 0.97 | H71: HDFC Securities | I71: HDFC 5413 | K71: NET PI TO HSL SEC A/C 2554606-00602340029427 | L71: HDFC Bank
A72: 45758 | B72: 45758 | C72: 10 | D72: 0 | F72: Transfer - Megha Gupta | G72: 0.85 | H72: Megha Gupta | I72: SBI 1227 | K72: WDL TFR UPI/DR/510127516128/Miss. ME/CBIN/meghagha ti/Paid 0097695162091 AT 11669 SHIVAJI NAGAR NASIK | L72: State Bank of India
A73: 45758 | B73: 45758 | C73: 0 | D73: 279 | F73: Misc Income | G73: 0.7 | H73: Misc Income | I73: SBI 1227 | K73: DEP TFR UPI/REV/510189443769 0097 695162091 AT 11669 SHIVAJI NAGAR NASIK | L73: State Bank of India
A74: 45758.422 | B74: 45758 | C74: 0 | D74: 501 | F74: MF Redemption | G74: 0.85 | H74: Mutual Funds | I74: KOTAK 0333 | K74: NEFT AXISCN0958713705 NIPPON INDIA SMALL CAP FUND | L74: Kotak Mahindra Bank
A75: 45758.846 | B75: 45758 | C75: 279 | D75: 0 | F75: UPI - CRED | G75: 0.68 | H75: Personal | I75: KOTAK 0333 | K75: UPI/Ferdus Alom/546773545667/Paid via CRED a | L75: Kotak Mahindra Bank | M75: ⚠ Possible Duplicate
A76: 45758.846 | B76: 45758 | C76: 0 | D76: 279 | F76: UPI Reversal | G76: 0.88 | H76: Personal | I76: KOTAK 0333 | K76: REV-UPI/Ferdus Alom/546773545667/ | L76: Kotak Mahindra Bank | M76: ⚠ Possible Duplicate
A77: 45758.846 | B77: 45758 | C77: 279 | D77: 0 | F77: UPI - CRED | G77: 0.68 | H77: Personal | I77: KOTAK 0333 | K77: UPI/Ferdus Alom/546773546667/Paid via CRED a | L77: Kotak Mahindra Bank | M77: ⚠ Possible Duplicate
A78: 45758.846 | B78: 45758 | C78: 0 | D78: 279 | F78: UPI Reversal | G78: 0.88 | H78: Personal | I78: KOTAK 0333 | K78: REV-UPI/Ferdus Alom/546773546667/ | L78: Kotak Mahindra Bank | M78: ⚠ Possible Duplicate
A79: 45758.949 | B79: 45758 | C79: 1500 | D79: 0 | F79: Credit Card Bill Payment (CRED) | G79: 0.85 | H79: Credit Card | I79: KOTAK 0333 | K79: UPI/CRED/546773735558/payment on CRED | L79: Kotak Mahindra Bank
A80: 45762 | B80: 45762 | C80: 5463.17 | D80: 0 | F80: HDFC Securities - Buy | G80: 0.97 | H80: HDFC Securities | I80: HDFC 5413 | K80: NET PI TO HSL SEC A/C 2554606-00602340029427 | L80: HDFC Bank
A81: 45762 | B81: 45762 | C81: 40 | D81: 0 | E81: Bharat S | F81: UPI Payment | G81: 0.55 | H81: Personal | I81: SBI 1227 | K81: WDL TFR UPI/DR/510522647751/BHARAT S/IOBA/84248520 34/Paid 0097692162094 AT 11669 SHIVAJI NAGAR NASIK | L81: State Bank of India
A82: 45762 | B82: 45762 | C82: 0 | D82: 2697.48 | F82: HDFC Securities - Settlement | G82: 0.93 | H82: HDFC Securities | I82: HDFC 5413 | K82: FT- 626617006-50200085415108 - HDFC SECURITIES LTD-CLIENT DSCNB A/C - | L82: HDFC Bank
A83: 45762 | B83: 45762 | C83: 500 | D83: 0 | F83: Cash Withdrawal | G83: 0.92 | H83: Cash | I83: HDFC 5413 | K83: ATW-652166XXXXXX7402-S1ANMN04-NASHIK | L83: HDFC Bank
A84: 45762 | B84: 45762 | C84: 384.32 | D84: 0 | F84: HDFC Securities - Buy | G84: 0.97 | H84: HDFC Securities | I84: HDFC 5413 | K84: NET PI TO HSL SEC A/C 2554606-00602340029427 | L84: HDFC Bank
A85: 45762.399 | B85: 45762 | C85: 1500 | D85: 0 | F85: Govt / Utility Payment | G85: 0.82 | H85: Utilities | I85: KOTAK 0333 | K85: UPI/SBIMOPS/547177174910/MOPSUPITxn | L85: Kotak Mahindra Bank
A86: 45763 | B86: 45763 | C86: 0 | D86: 25000 | F86: Contra - Axis | G86: 0.9 | H86: AXIS | I86: SBI 1227 | K86: DEP TFR NEFT*UTIB0002656*AXOMB10626155334*AAYUSH K UMAR GU 0099509044300 AT 11669 SHIVAJI NAGAR NASIK | L86: State Bank of India
A87: 45763 | B87: 45763 | C87: 25000 | D87: 0 | F87: MF Investment | G87: 0.9 | H87: Investments | I87: SBI 1227 | K87: WDL TFR UPI/DR/510629877598/Indian C/HDFC/icclzero dh/Merc 0097693162093 AT 11669 SHIVAJI NAGAR NASIK | L87: State Bank of India
A88: 45763 | B88: 45763 | C88: 531 | D88: 0 | F88: Depository Charges | G88: 0.93 | H88: Depository Charges | I88: HDFC 5413 | K88: DEPOSITORY CHARGES MAR25 - 52812428 | L88: HDFC Bank
A89: 45763 | B89: 45763 | C89: 95.09 | D89: 0 | F89: HDFC Securities - Buy | G89: 0.97 | H89: HDFC Securities | I89: HDFC 5413 | K89: NET PI TO HSL SEC A/C 2554606-00602340029427 | L89: HDFC Bank
A90: 45763 | B90: 45763 | C90: 25000 | D90: 0 | F90: Contra - SBI | G90: 0.9 | H90: SBI 1227 | I90: AXIS | J90: Transfer to SBI self | K90: NEFT/MB/AXOMB10626155334/AAYUSH KUMAR GUPTA/STATE BANK OF INDIA/FAMILY | L90: Axis Bank
A91: 45763.345 | B91: 45763 | C91: 1000 | D91: 0 | F91: Credit Card Bill Payment (CRED) | G91: 0.85 | H91: Credit Card | I91: KOTAK 0333 | K91: UPI/CRED/547278151800/payment on CRED | L91: Kotak Mahindra Bank
A92: 45763.46 | B92: 45763 | C92: 0 | D92: 91056 | F92: Salary | G92: 0.85 | H92: Salary | I92: KOTAK 0333 | K92: TRANS | L92: Kotak Mahindra Bank
A93: 45763.472 | B93: 45763 | C93: 10000 | D93: 0 | F93: Transfer - Megha Gupta | G93: 0.85 | H93: Megha Gupta | I93: KOTAK 0333 | K93: UPI/Miss. MEGHA GU/547278323187/Happy 3 month A | L93: Kotak Mahindra Bank
A94: 45764 | B94: 45764 | C94: 0 | D94: 1686.98 | F94: HDFC Securities - Settlement | G94: 0.93 | H94: HDFC Securities | I94: HDFC 5413 | K94: FT- 627438941-50200085415108 - HDFC SECURITIES LTD-CLIENT DSCNB A/C - | L94: HDFC Bank
A95: 45764 | B95: 45764 | C95: 103.29 | D95: 0 | F95: HDFC Securities - Buy | G95: 0.97 | H95: HDFC Securities | I95: HDFC 5413 | K95: NET PI TO HSL SEC A/C 2554606-00602340029427 | L95: HDFC Bank
A96: 45764 | B96: 45764 | C96: 0 | D96: 21246.96 | F96: HDFC Securities - Settlement | G96: 0.93 | H96: HDFC Securities | I96: HDFC 5413 | K96: FT- 627466758-50200085415108 - HDFC SECURITIES LTD-CLIENT DSCNB A/C - | L96: HDFC Bank
A97: 45764.28 | B97: 45764 | C97: 427.25 | D97: 0 | F97: UPI - IRCTC | G97: 0.68 | H97: Travel | I97: KOTAK 0333 | K97: UPI/IRCTC CF/100375704017/IRCTC TICKET BO | L97: Kotak Mahindra Bank
A98: 45764.567 | B98: 45764 | C98: 1000 | D98: 0 | F98: Credit Card Bill Payment (CRED) | G98: 0.85 | H98: Credit Card | I98: KOTAK 0333 | K98: UPI/CredClub/547379551441/payment on CRED | L98: Kotak Mahindra Bank
A99: 45766 | B99: 45766 | C99: 0 | D99: 100 | F99: Received - Dnyaneshwar Kuyate | G99: 0.55 | H99: Personal | I99: HDFC 5413 | K99: UPI-DNYANESHWAR KUYATE-9974953233@AXL-HDFC0000305-386224665882-PAYMENT FROM PHONE | L99: HDFC Bank
A100: 45766.079 | B100: 45766 | C100: 1000 | D100: 0 | F100: Credit Card Bill Payment (CRED) | G100: 0.85 | H100: Credit Card | I100: KOTAK 0333 | K100: UPI/CRED/547581338377/payment on CRED | L100: Kotak Mahindra Bank | M100: ⚠ Possible Duplicate
A101: 45766.527 | B101: 45766 | C101: 1000 | D101: 0 | F101: Credit Card Bill Payment (CRED) | G101: 0.85 | H101: Credit Card | I101: KOTAK 0333 | K101: UPI/CRED/547581662583/payment on CRED | L101: Kotak Mahindra Bank | M101: ⚠ Possible Duplicate
A102: 45766.693 | B102: 45766 | C102: 1000 | D102: 0 | F102: Credit Card Bill Payment (CRED) | G102: 0.85 | H102: Credit Card | I102: KOTAK 0333 | K102: UPI/CRED/547581914199/payment on CRED | L102: Kotak Mahindra Bank | M102: ⚠ Possible Duplicate
A103: 45766.887 | B103: 45766 | C103: 85 | D103: 0 | E103: Ashik Khan | F103: UPI Payment | G103: 0.55 | H103: Personal | I103: KOTAK 0333 | K103: UPI/ASHIK KHAN/510976601574/Paid via SuperM | L103: Kotak Mahindra Bank
A104: 45766.909 | B104: 45766 | C104: 25 | D104: 0 | E104: Mahendra Singh | F104: UPI Payment | G104: 0.55 | H104: Personal | I104: KOTAK 0333 | K104: UPI/MAHENDRA SINGH/510977058907/Paid via SuperM | L104: Kotak Mahindra Bank
A105: 45767.809 | B105: 45767 | C105: 0 | D105: 10 | F105: Received - Megha Gupta | G105: 0.85 | H105: Megha Gupta | I105: KOTAK 0333 | K105: UPI/MEGHA GUPTA/547683296341/Paid via CRED | L105: Kotak Mahindra Bank
A106: 45767.832 | B106: 45767 | C106: 1000 | D106: 0 | F106: Credit Card Bill Payment (CRED) | G106: 0.85 | H106: Credit Card | I106: KOTAK 0333 | K106: UPI/CRED/547683353682/payment on CRED | L106: Kotak Mahindra Bank
A107: 45768 | B107: 45768 | C107: 415.56 | D107: 0 | F107: HDFC Securities - Buy | G107: 0.97 | H107: HDFC Securities | I107: HDFC 5413 | K107: NET PI TO HSL SEC A/C 2554606-00602340029427 | L107: HDFC Bank
A108: 45768 | B108: 45768 | C108: 0 | D108: 175.35 | F108: HDFC Securities - Settlement | G108: 0.93 | H108: HDFC Securities | I108: HDFC 5413 | K108: FT- 627809473-50200085415108 - HDFC SECURITIES LTD-CLIENT DSCNB A/C - | L108: HDFC Bank
...

Sheet Conso
A1: Aayush Kumar Gupta
A2: Account of Statements from 01-Apr-2025 to 01-Apr-2026 | D2: =SUM(D5:D1565) -> 4127912.7 | E2: =SUM(E5:E1565) -> 4094424.7 | F2: =E2-D2 -> -33487.95
A4: TX Date | B4: Particulars | C4: Ref | D4: DR | E4: CR | F4: Balance | G4: Account Head | H4: Account No
A5: 45748 | B5: ACH D- TP ACH INDIANESIGN-1758642535 | C5: 0000006650023609 | D5: 5000 | E5: 0 | F5: 24321.48 | G5: SIP | H5: HDFC 5413
A6: 45748.457 | B6: UPI/BARATHI ANBAZHA/509137039846/Paid via SuperM | C6: UPI-509197194351 | D6: 121 | E6: 0 | F6: 1612.19 | G6: Personal | H6: KOTAK 0333
A7: 45748.709 | B7: UPI/SAMOSA PARTY Ba/509141156489/Paid via SuperM | C7: UPI-509118876248 | D7: 30 | E7: 0 | F7: 1582.19 | G7: Personal | H7: KOTAK 0333
A8: 45749 | B8: UPI/P2A/765226990925/AAYUSH KUMAR GUPTA /UPI/State Bank Of India | C8: - | D8: 1 | E8: 0 | F8: 84251.03 | G8: SBI 1227 | H8: AXIS
A9: 45749 | B9: UPI/P2A/765382250925/AAYUSH KUMAR GUPTA /UPI/State Bank Of India | C9: - | D9: 40000 | E9: 0 | F9: 44251.03 | G9: SBI 1227 | H9: AXIS
A10: 45749 | B10: DEP TFR UPI/CR/765226990925/AAYUSH K/UTIB/9594435 259/UPI 0097735162098 AT 11669 SHIVAJI NAGAR NASIK | D10: 0 | E10: 1 | F10: 10987.03 | G10: AXIS | H10: SBI 1227
A11: 45749 | B11: DEP TFR UPI/CR/765382250925/AAYUSH K/UTIB/9594435 259/UPI 0097735162098 AT 11669 SHIVAJI NAGAR NASIK | D11: 0 | E11: 40000 | F11: 50987.03 | G11: AXIS | H11: SBI 1227
A12: 45749 | B12: WDL TFR UPI/DR/545893374949/CRED RENT/UTIB/cred.re nt@/pay 0097693162093 AT 11669 SHIVAJI NAGAR NASIK | D12: 23000 | E12: 0 | F12: 27987.03 | G12: Rent | H12: SBI 1227
A13: 45749 | B13: DEP TFR NEFT*UTIB0002656*AXOMB09202414101*AAYUSH K UMAR GU 0099509044300 AT 11669 SHIVAJI NAGAR NASIK | D13: 0 | E13: 1 | F13: 27988.03 | G13: AXIS | H13: SBI 1227
A14: 45749 | B14: WDL TFR UPI/DR/509208961213/CRED Club/UTIB/cred.cl ub@/pay 0097693162093 AT 11669 SHIVAJI NAGAR NASIK | D14: 3000 | E14: 0 | F14: 24988.03 | G14: Credit Card | H14: SBI 1227
A15: 45749 | B15: WDL TFR UPI/DR/545868712527/Miss. ME/CBIN/meghagha ti/Paid 0097693162093 AT 11669 SHIVAJI NAGAR NASIK | D15: 2000 | E15: 0 | F15: 22988.03 | G15: Megha Gupta | H15: SBI 1227
A16: 45749 | B16: WDL TFR UPI/DR/545878868808/CRED Club/UTIB/cred.cl ub@/pay 0097693162093 AT 11669 SHIVAJI NAGAR NASIK | D16: 2000 | E16: 0 | F16: 20988.03 | G16: Credit Card | H16: SBI 1227
A17: 45749 | B17: WDL TFR UPI/DR/545887987358/CRED Club/UTIB/cred.cl ub@/pay 0097693162093 AT 11669 SHIVAJI NAGAR NASIK | D17: 2000 | E17: 0 | F17: 18988.03 | G17: Credit Card | H17: SBI 1227
A18: 45749 | B18: NEFT/MB/AXOMB09202414101/AAYUSH KUMAR GUPTA/STATE BANK OF INDIA/ | C18: - | D18: 1 | E18: 0 | F18: 84252.03 | G18: SBI 1227 | H18: AXIS
A19: 45749 | B19: Salary For the Month of Mar 2025 | C19: - | D19: 0 | E19: 66897 | F19: 84253.03 | G19: Salary | H19: AXIS
A20: 45749 | B20: FT- 623432246-50200085415108 - HDFC SECURITIES LTD-CLIENT DSCNB A/C - | C20: 0000001009359686 | D20: 0 | E20: 5239.85 | F20: 29561.33 | G20: HDFC Securities | H20: HDFC 5413
A21: 45749 | B21: NET PI TO HSL SEC A/C 2554606-00602340029427 | C21: 0000000623760831 | D21: 9081.73 | E21: 0 | F21: 20329.34 | G21: HDFC Securities | H21: HDFC 5413
A22: 45749 | B22: NET PI TO HSL SEC A/C 2554606-00602340029427 | C22: 0000000623593417 | D22: 150.26 | E22: 0 | F22: 29411.07 | G22: HDFC Securities | H22: HDFC 5413
A23: 45750 | B23: FT- 623852638-50200085415108 - HDFC SECURITIES LTD-CLIENT DSCNB A/C - | C23: 0000001010969056 | D23: 0 | E23: 656.71 | F23: 20986.05 | G23: HDFC Securities | H23: HDFC 5413
A24: 45750 | B24: NET PI TO HSL SEC A/C 2554606-00602340029427 | C24: 0000000624008014 | D24: 134.41 | E24: 0 | F24: 20851.64 | G24: HDFC Securities | H24: HDFC 5413
A25: 45750 | B25: WDL TFR UPI/DR/545972230401/CRED Club/UTIB/cred.cl ub@/pay 0097694162092 AT 11669 SHIVAJI NAGAR NASIK | D25: 2000 | E25: 0 | F25: 16988.03 | G25: Credit Card | H25: SBI 1227
A26: 45750 | B26: WDL TFR UPI/DR/509336037048/CRED Club/UTIB/cred.cl ub@/pay 0097694162092 AT 11669 SHIVAJI NAGAR NASIK | D26: 2360.82 | E26: 0 | F26: 12627.21 | G26: Credit Card | H26: SBI 1227
A27: 45750 | B27: WDL TFR UPI/DR/509378949775/CRED Club/UTIB/cred.cl ub@/pay 0097694162092 AT 11669 SHIVAJI NAGAR NASIK | D27: 2000 | E27: 0 | F27: 14988.03 | G27: Credit Card | H27: SBI 1227
A28: 45750.765 | B28: UPI/Mrs. G Pavithr/509367683617/Paid via SuperM | C28: UPI-509356331060 | D28: 50 | E28: 0 | F28: 1532.19 | G28: Personal | H28: KOTAK 0333
A29: 45750.949 | B29: UPI/supermoney/509381273041/Supermoney Rewa | C29: UPI-509376992939 | D29: 0 | E29: 66.74 | F29: 1598.93 | G29: Misc Income | H29: KOTAK 0333
A30: 45751 | B30: FT- 624254248-50200085415108 - HDFC SECURITIES LTD-CLIENT DSCNB A/C - | C30: 0000001012795998 | D30: 0 | E30: 10041.41 | F30: 30893.05 | G30: HDFC Securities | H30: HDFC 5413
A31: 45751 | B31: NET PI TO HSL SEC A/C 2554606-00602340029427 | C31: 0000000624385290 | D31: 115.2 | E31: 0 | F31: 30777.85 | G31: HDFC Securities | H31: HDFC 5413
A32: 45751 | B32: NET PO FROM HSL A/C 2554606-50200085415108 | C32: 0000000624619061 | D32: 0 | E32: 6146.26 | F32: 36924.11 | G32: HDFC Securities | H32: HDFC 5413
A33: 45751 | B33: WDL TFR UPI/DR/509438120147/MATS FUE/YESB/paytm-31 10/Paid 0097695162091 AT 11669 SHIVAJI NAGAR NASIK | D33: 210 | E33: 0 | F33: 12417.21 | G33: Personal | H33: SBI 1227
A34: 45751.957 | B34: UPI/WALKO FOOD COMP/509484810231/Paid via SuperM | C34: UPI-509442182659 | D34: 285 | E34: 0 | F34: 1313.93 | G34: Personal | H34: KOTAK 0333
A35: 45752 | B35: WDL TFR UPI/DR/546194213465/Nandini/YESB/paytm.s1 c3/Paid 0097696162090 AT 11669 SHIVAJI NAGAR NASIK | D35: 60 | E35: 0 | F35: 12357.21 | G35: Groceries | H35: SBI 1227
A36: 45752.341 | B36: NEFT YESF350953824281 ZERODHA BROKING LTD DSCNB A | C36: NEFTINW-1174470955 | D36: 0 | E36: 4213.71 | F36: 5527.64 | G36: Zerodha Broking Limited | H36: KOTAK 0333
A37: 45752.781 | B37: UPI/Counter 4/509593584977/Paid via SuperM | C37: UPI-509588244702 | D37: 210 | E37: 0 | F37: 5317.64 | G37: Personal | H37: KOTAK 0333
A38: 45753.756 | B38: UPI/DINESH KUMAR GU/546205310184/Paid via SuperM | C38: UPI-509648113097 | D38: 30 | E38: 0 | F38: 5287.64 | G38: Personal | H38: KOTAK 0333
A39: 45754 | B39: NET PI TO HSL SEC A/C 2554606-00602340029427 | C39: 0000000624943357 | D39: 323.04 | E39: 0 | F39: 38481.07 | G39: HDFC Securities | H39: HDFC 5413
A40: 45754 | B40: HDFCLIFE CENTR-038144668 | C40: 0000504070711353 | D40: 0 | E40: 1880 | F40: 38804.11 | G40: Annuity | H40: HDFC 5413
A41: 45754 | B41: NET PI TO HSL SEC A/C 2554606-00602340029427 | C41: 0000000625232784 | D41: 6242.17 | E41: 0 | F41: 32238.9 | G41: HDFC Securities | H41: HDFC 5413
A42: 45755 | B42: NET PI TO HSL SEC A/C 2554606-00602340029427 | C42: 0000000625624965 | D42: 8913.03 | E42: 0 | F42: 22938.3 | G42: HDFC Securities | H42: HDFC 5413
A43: 45755 | B43: ISAQMC-OCT-DEC24-417944 130325-MIR2609890209148 | C43: MIR2609890209148 | D43: 295 | E43: 0 | F43: 31943.9 | G43: Bank Charges | H43: HDFC 5413
A44: 45755 | B44: NET PI TO HSL SEC A/C 2554606-00602340029427 | C44: 0000000625532003 | D44: 92.57 | E44: 0 | F44: 31851.33 | G44: HDFC Securities | H44: HDFC 5413
A45: 45755 | B45: NET PI TO HSL SEC A/C 2554606-00602340029427 | C45: 0000000625666983 | D45: 1241.91 | E45: 0 | F45: 21696.39 | G45: HDFC Securities | H45: HDFC 5413
A46: 45756 | B46: NET PI TO HSL SEC A/C 2554606-00602340029427 | C46: 0000000625935884 | D46: 88.96 | E46: 0 | F46: 21607.43 | G46: HDFC Securities | H46: HDFC 5413
A47: 45756 | B47: NET PI TO HSL SEC A/C 2554606-00602340029427 | C47: 0000000626082949 | D47: 1969.84 | E47: 0 | F47: 19637.59 | G47: HDFC Securities | H47: HDFC 5413
A48: 45757 | B48: UPI/P2M/100335047021/Autope Payment Soluti/Paymen/HDFC BANK LTD | C48: - | D48: 5704.5 | E48: 0 | F48: 38546.53 | G48: Travel | H48: AXIS
A49: 45758 | B49: WDL TFR UPI/DR/510189443769/Ferdus /FINO/fardusal om/Paid 0097695162091 AT 11669 SHIVAJI NAGAR NASIK | D49: 279 | E49: 0 | F49: 12078.21 | G49: Personal | H49: SBI 1227
A50: 45758 | B50: NET PI TO HSL SEC A/C 2554606-00602340029427 | C50: 0000000626391621 | D50: 192.16 | E50: 0 | F50: 19445.43 | G50: HDFC Securities | H50: HDFC 5413
A51: 45758 | B51: WDL TFR UPI/DR/510127516128/Miss. ME/CBIN/meghagha ti/Paid 0097695162091 AT 11669 SHIVAJI NAGAR NASIK | D51: 10 | E51: 0 | F51: 12347.21 | G51: Megha Gupta | H51: SBI 1227
A52: 45758 | B52: DEP TFR UPI/REV/510189443769 0097 695162091 AT 11669 SHIVAJI NAGAR NASIK | D52: 0 | E52: 279 | F52: 12357.21 | G52: Misc Income | H52: SBI 1227
A53: 45758.422 | B53: NEFT AXISCN0958713705 NIPPON INDIA SMALL CAP FUND | C53: NEFTINW-1180794199 | D53: 0 | E53: 501 | F53: 5788.64 | G53: Mutual Funds | H53: KOTAK 0333
A54: 45758.846 | B54: UPI/Ferdus Alom/546773545667/Paid via CRED a | C54: UPI-510184999331 | D54: 279 | E54: 0 | F54: 5509.64 | G54: Personal | H54: KOTAK 0333
A55: 45758.846 | B55: REV-UPI/Ferdus Alom/546773545667/ | C55: UPI-510184999331 | D55: 0 | E55: 279 | F55: 5788.64 | G55: Personal | H55: KOTAK 0333
A56: 45758.846 | B56: UPI/Ferdus Alom/546773546667/Paid via CRED a | C56: UPI-510185051060 | D56: 279 | E56: 0 | F56: 5509.64 | G56: Personal | H56: KOTAK 0333
A57: 45758.846 | B57: REV-UPI/Ferdus Alom/546773546667/ | C57: UPI-510185051060 | D57: 0 | E57: 279 | F57: 5788.64 | G57: Personal | H57: KOTAK 0333
A58: 45758.949 | B58: UPI/CRED/546773735558/payment on CRED | C58: UPI-510195642472 | D58: 1500 | E58: 0 | F58: 4288.64 | G58: Credit Card | H58: KOTAK 0333
A59: 45762 | B59: NET PI TO HSL SEC A/C 2554606-00602340029427 | C59: 0000000626975193 | D59: 5463.17 | E59: 0 | F59: 15795.42 | G59: HDFC Securities | H59: HDFC 5413
A60: 45762 | B60: WDL TFR UPI/DR/510522647751/BHARAT S/IOBA/84248520 34/Paid 0097692162094 AT 11669 SHIVAJI NAGAR NASIK | D60: 40 | E60: 0 | F60: 12307.21 | G60: Personal | H60: SBI 1227
A61: 45762 | B61: FT- 626617006-50200085415108 - HDFC SECURITIES LTD-CLIENT DSCNB A/C - | C61: 0000001027351610 | D61: 0 | E61: 2697.48 | F61: 22142.91 | G61: HDFC Securities | H61: HDFC 5413
A62: 45762 | B62: ATW-652166XXXXXX7402-S1ANMN04-NASHIK | C62: 0000000000005703 | D62: 500 | E62: 0 | F62: 21258.59 | G62: Cash | H62: HDFC 5413
A63: 45762 | B63: NET PI TO HSL SEC A/C 2554606-00602340029427 | C63: 0000000626859119 | D63: 384.32 | E63: 0 | F63: 21758.59 | G63: HDFC Securities | H63: HDFC 5413
A64: 45762.399 | B64: UPI/SBIMOPS/547177174910/MOPSUPITxn | C64: UPI-510591765767 | D64: 1500 | E64: 0 | F64: 2788.64 | G64: Utilities | H64: KOTAK 0333
A65: 45763 | B65: DEP TFR NEFT*UTIB0002656*AXOMB10626155334*AAYUSH K UMAR GU 0099509044300 AT 11669 SHIVAJI NAGAR NASIK | D65: 0 | E65: 25000 | F65: 37307.21 | G65: AXIS | H65: SBI 1227
A66: 45763 | B66: WDL TFR UPI/DR/510629877598/Indian C/HDFC/icclzero dh/Merc 0097693162093 AT 11669 SHIVAJI NAGAR NASIK | D66: 25000 | E66: 0 | F66: 12307.21 | G66: Investments | H66: SBI 1227
A67: 45763 | B67: DEPOSITORY CHARGES MAR25 - 52812428 | C67: 000000000000000 | D67: 531 | E67: 0 | F67: 15169.33 | G67: Depository Charges | H67: HDFC 5413
A68: 45763 | B68: NET PI TO HSL SEC A/C 2554606-00602340029427 | C68: 0000000627217106 | D68: 95.09 | E68: 0 | F68: 15700.33 | G68: HDFC Securities | H68: HDFC 5413
A69: 45763 | B69: NEFT/MB/AXOMB10626155334/AAYUSH KUMAR GUPTA/STATE BANK OF INDIA/FAMILY | C69: - | D69: 25000 | E69: 0 | F69: 13546.53 | G69: SBI 1227 | H69: AXIS
A70: 45763.345 | B70: UPI/CRED/547278151800/payment on CRED | C70: UPI-510652750321 | D70: 1000 | E70: 0 | F70: 1788.64 | G70: Credit Card | H70: KOTAK 0333
A71: 45763.46 | B71: TRANS | C71: FCM-250416G7VEUG | D71: 0 | E71: 91056 | F71: 92844.64 | G71: Salary | H71: KOTAK 0333
A72: 45763.472 | B72: UPI/Miss. MEGHA GU/547278323187/Happy 3 month A | C72: UPI-510661882848 | D72: 10000 | E72: 0 | F72: 82844.64 | G72: Megha Gupta | H72: KOTAK 0333
A73: 45764 | B73: FT- 627438941-50200085415108 - HDFC SECURITIES LTD-CLIENT DSCNB A/C - | C73: 0000001030124904 | D73: 0 | E73: 1686.98 | F73: 38103.27 | G73: HDFC Securities | H73: HDFC 5413
A74: 45764 | B74: NET PI TO HSL SEC A/C 2554606-00602340029427 | C74: 0000000627574414 | D74: 103.29 | E74: 0 | F74: 37999.98 | G74: HDFC Securities | H74: HDFC 5413
A75: 45764 | B75: FT- 627466758-50200085415108 - HDFC SECURITIES LTD-CLIENT DSCNB A/C - | C75: 0000001030182122 | D75: 0 | E75: 21246.96 | F75: 36416.29 | G75: HDFC Securities | H75: HDFC 5413
A76: 45764.28 | B76: UPI/IRCTC CF/100375704017/IRCTC TICKET BO | C76: UPI-510713871404 | D76: 427.25 | E76: 0 | F76: 82417.39 | G76: Travel | H76: KOTAK 0333
A77: 45764.567 | B77: UPI/CredClub/547379551441/payment on CRED | C77: UPI-510733285335 | D77: 1000 | E77: 0 | F77: 81417.39 | G77: Credit Card | H77: KOTAK 0333
A78: 45766 | B78: UPI-DNYANESHWAR KUYATE-9974953233@AXL-HDFC0000305-386224665882-PAYMENT FROM PHONE | C78: 0000386224665882 | D78: 0 | E78: 100 | F78: 38099.98 | G78: Personal | H78: HDFC 5413
... A102: 45772 | B102: NET PI TO HSL SEC A/C 2554606-00602340029427 | C102: 0000000629584719 | D102: 100.48 | E102: 0 | F102: 38154.82 | G102: HDFC Securities | H102: HDFC 5413
A103: 45773 | B103: WDL TFR SBIYA25116092502872203439-Deposit or Inv 0039706 255133 OF Mr. AAYUSH KUMAR GUPTA AT 11669 SHIVAJI NAGAR NASIK | D103: 5100 | E103: 0 | F103: 12207.21 | G103: PPF Deposit | H103: SBI 1227
A104: 45773 | B104: DEP TFR UPI/CR/548257957091/AAYUSH K/KKBK/95944352 59/Paid 0097738162095 AT 11669 SHIVAJI NAGAR NASIK | D104: 0 | E104: 5000 | F104: 17307.21 | G104: KOTAK 0333 | H104: SBI 1227
A105: 45773.392 | B105: UPI/9594435259@supe/548257957091/Paid via SuperM | C105: UPI-511665616235 | D105: 5000 | E105: 0 | F105: 75243.49 | G105: SBI 1227 | H105: KOTAK 0333
A106: 45773.777 | B106: UPI/SACHIN SHIVAJI /548264628441/Paid via SuperM | C106: UPI-511696435579 | D106: 20 | E106: 0 | F106: 75223.49 | G106: Personal | H106: KOTAK 0333
A107: 45775 | B107: ACH D- TP ACH INDIANESIGN-1788634149 | C107: 0000007607192044 | D107: 5000 | E107: 0 | F107: 30562.62 | G107: SIP | H107: HDFC 5413
A108: 45775 | B108: NET PI TO HSL SEC A/C 2554606-00602340029427 | C108: 0000000630058183 | D108: 298.68 | E108: 0 | F108: 30263.94 | G108: HDFC Securities | H108: HDFC 5413
A109: 45775 | B109: UPI-AMAZON PAY-AMAZONPAYHFC@APL-UTIB0000100-511855542450-YOU ARE PAYING FOR | C109: 0000511855542450 | D109: 856.5 | E109: 0 | F109: 29407.44 | G109: Shopping | H109: HDFC 5413
A110: 45775 | B110: NET PI TO HSL SEC A/C 2554606-00602340029427 | C110: 0000000630166745 | D110: 6370.07 | E110: 0 | F110: 23037.37 | G110: HDFC Securities | H110: HDFC 5413
A111: 45775.309 | B111: NACH-MUT-DR-INDIAN CLEARING CORP-000000PFDXIMY7ND | C111: NACHDR28042506263900 | D111: 7000 | E111: 0 | F111: 68223.49 | G111: SIP | H111: KOTAK 0333
A112: 45776 | B112: FT- 630281837-50200085415108 - HDFC SECURITIES LTD-CLIENT DSCNB A/C - | C112: 0000001042506406 | D112: 0 | E112: 22473.44 | F112: 45510.81 | G112: HDFC Securities | H112: HDFC 5413
A113: 45776 | B113: FT- 630254071-50200085415108 - HDFC SECURITIES LTD-CLIENT DSCNB A/C - | C113: 0000001042528896 | D113: 0 | E113: 2398.19 | F113: 47909 | G113: HDFC Securities | H113: HDFC 5413
A114: 45776 | B114: NET PI TO HSL SEC A/C 2554606-00602340029427 | C114: 0000000630404015 | D114: 97.29 | E114: 0 | F114: 47811.71 | G114: HDFC Securities | H114: HDFC 5413
A115: 45776 | B115: NET PI TO HSL SEC A/C 2554606-00602340029427 | C115: 0000000630528132 | D115: 15507.42 | E115: 0 | F115: 32304.29 | G115: HDFC Securities | H115: HDFC 5413
A116: 45776 | B116: UPI-ASHOK DIVEDI-9694131651@YBL-SBIN0031436-076528809621-PAYMENT FROM PHONE | C116: 0000076528809621 | D116: 0 | E116: 2100 | F116: 34404.29 | G116: Personal | H116: HDFC 5413
... A120: 45777 | B120: NET PI TO HSL SEC A/C 2554606-00602340029427 | C120: 0000000630752531 | D120: 78.21 | E120: 0 | F120: 31086.24 | G120: HDFC Securities | H120: HDFC 5413
A121: 45778 | B121: 20052205306441:Int.Pd:31-03-2025 to 30-04-2025 | D121: 0 | E121: 1 | F121: 238 | G121: Bank Interest | H121: SBM
A122: 45778.823 | B122: UPI/Miss. MEGHA GU/548796376019/Paid via CRED a | C122: UPI-512110893337 | D122: 5000 | E122: 0 | F122: 63223.49 | G122: Megha Gupta | H122: KOTAK 0333
A123: 45778.824 | B123: UPI/Miss. MEGHA GU/548796379699/Paid via CRED a | C123: UPI-512111066095 | D123: 5000 | E123: 0 | F123: 58223.49 | G123: Megha Gupta | H123: KOTAK 0333
A124: 45779 | B124: UPI-PANKAJ VERMA-PV187027@OKHDFCBANK-IPOS0000001-515908483499-FRUIT | C124: 0000515908483499 | D124: 60 | E124: 0 | F124: 30581.5 | G124: Groceries | H124: HDFC 5413
A125: 45779 | B125: UPI-JALINDAR SUKDEV SALV-PAYTM.S1CTUSY@PTY-YESB0MCHUPI-812060104821-FRUIT | C125: 0000812060104821 | D125: 50 | E125: 0 | F125: 30531.5 | G125: Groceries | H125: HDFC 5413
A126: 45779 | B126: NET PI TO HSL SEC A/C 2554606-00602340029427 | C126: 0000000631386145 | D126: 10292.04 | E126: 0 | F126: 20239.46 | G126: HDFC Securities | H126: HDFC 5413
A127: 45779 | B127: NEFT/HDFCH00213942923/MPHASIS LIMITED/HDFC BANK/0001SALARYAPR2025 | C127: - | D127: 0 | E127: 98850 | F127: 112396.53 | G127: Salary | H127: AXIS
...

Sheet Bank Summary
A1: All Banks
A2: Aayush Gupta Bank Summary
A3: 01-Apr-2025 to 01-Apr-2026
A5: Narration | B5: Total Credit (₹) | C5: Narration | D5: Total Debit (₹)
A6: Annuity Income | B6: =SUMIFS('For Tally'!D:D, 'For Tally'!F:F, A6) -> 22560 | C6: Annuity Income | D6: =SUMIFS('For Tally'!C:C, 'For Tally'!F:F, C6) -> 0
A7: Bank Charges | B7: =SUMIFS('For Tally'!D:D, 'For Tally'!F:F, A7) -> 0 | C7: Bank Charges | D7: =SUMIFS('For Tally'!C:C, 'For Tally'!F:F, C7) -> 2368.96
A8: Bank Interest | B8: =SUMIFS('For Tally'!D:D, 'For Tally'!F:F, A8) -> 3390 | C8: Bank Interest | D8: =SUMIFS('For Tally'!C:C, 'For Tally'!F:F, C8) -> 0
A9: Card Purchase | B9: =SUMIFS('For Tally'!D:D, 'For Tally'!F:F, A9) -> 0 | C9: Card Purchase | D9: =SUMIFS('For Tally'!C:C, 'For Tally'!F:F, C9) -> 4
A10: Cash Withdrawal | B10: =SUMIFS('For Tally'!D:D, 'For Tally'!F:F, A10) -> 0 | C10: Cash Withdrawal | D10: =SUMIFS('For Tally'!C:C, 'For Tally'!F:F, C10) -> 500
A11: Cashback - BHIM | B11: =SUMIFS('For Tally'!D:D, 'For Tally'!F:F, A11) -> 93 | C11: Cashback - BHIM | D11: =SUMIFS('For Tally'!C:C, 'For Tally'!F:F, C11) -> 0
A12: Cashback - Kiwi | B12: =SUMIFS('For Tally'!D:D, 'For Tally'!F:F, A12) -> 8 | C12: Cashback - Kiwi | D12: =SUMIFS('For Tally'!C:C, 'For Tally'!F:F, C12) -> 0
A13: Contra - Axis | B13: =SUMIFS('For Tally'!D:D, 'For Tally'!F:F, A13) -> 448836.97 | C13: Contra - Axis | D13: =SUMIFS('For Tally'!C:C, 'For Tally'!F:F, C13) -> 0
A14: Contra - HDFC | B14: =SUMIFS('For Tally'!D:D, 'For Tally'!F:F, A14) -> 50000 | C14: Contra - HDFC | D14: =SUMIFS('For Tally'!C:C, 'For Tally'!F:F, C14) -> 0
A15: Contra - Kotak | B15: =SUMIFS('For Tally'!D:D, 'For Tally'!F:F, A15) -> 17217.71 | C15: Contra - Kotak | D15: =SUMIFS('For Tally'!C:C, 'For Tally'!F:F, C15) -> 368605.37
A16: Contra - SBI | B16: =SUMIFS('For Tally'!D:D, 'For Tally'!F:F, A16) -> 56000 | C16: Contra - SBI | D16: =SUMIFS('For Tally'!C:C, 'For Tally'!F:F, C16) -> 203690.31
A17: Contra - SBM | B17: =SUMIFS('For Tally'!D:D, 'For Tally'!F:F, A17) -> 241 | C17: Contra - SBM | D17: =SUMIFS('For Tally'!C:C, 'For Tally'!F:F, C17) -> 0
... A109: Zerodha Broking | B109: =SUMIFS('For Tally'!D:D, 'For Tally'!F:F, A109) -> 35971 | C109: Zerodha Broking | D109: =SUMIFS('For Tally'!C:C, 'For Tally'!F:F, C109) -> 208000
A110: TOTAL | B110: =SUM(B5:B109) -> 4094424.8 | C110: TOTAL | D110: =SUM(D5:D109) -> 4127912.7 | E110: Net | F110: =B110-D110 -> -33487.95
A112: Opening & Closing Balances
A113: Account | B113: Opening Balance (₹) | C113: Closing Balance (₹)
A114: AXIS | B114: 17356.03 | C114: =B114 + SUMIFS('For Tally'!D:D, 'For Tally'!I:I, A114) - SUMIFS('For Tally'!C:C, 'For Tally'!I:I, A114) -> 5572.57
A115: HDFC 5413 | B115: 29321.48 | C115: =B115 + SUMIFS('For Tally'!D:D, 'For Tally'!I:I, A115) - SUMIFS('For Tally'!C:C, 'For Tally'!I:I, A115) -> 162
A116: KOTAK 0333 | B116: 1733.19 | C116: =B116 + SUMIFS('For Tally'!D:D, 'For Tally'!I:I, A116) - SUMIFS('For Tally'!C:C, 'For Tally'!I:I, A116) -> 8538.08
A117: SBI 1227 | B117: 10986.03 | C117: =B117 + SUMIFS('For Tally'!D:D, 'For Tally'!I:I, A117) - SUMIFS('For Tally'!C:C, 'For Tally'!I:I, A117) -> 11873.13
A118: SBM | B118: 237 | C118: =B118 + SUMIFS('For Tally'!D:D, 'For Tally'!I:I, A118) - SUMIFS('For Tally'!C:C, 'For Tally'!I:I, A118) -> 0
A120: Confidence Distribution
A121: Band | B121: Count | C121: % of Total
A122: High (≥ 0.85) — Confident | B122: =COUNTIF('For Tally'!G:G, ">=0.85") -> 1124 | C122: =B122/SUM(B122:B124) -> 0.72005125
A123: Medium (0.60–0.84) — Review | B123: =COUNTIFS('For Tally'!G:G, ">=0.60", 'For Tally'!G:G, "<0.85") -> 171 | C123: =B123/SUM(B122:B124) -> 0.10954516
A124: Low (< 0.60) — Needs attention | B124: =COUNTIF('For Tally'!G:G, "<0.60") -> 266 | C124: =B124/SUM(B122:B124) -> 0.17040359

Sheet Monthly Pivot
A1: Monthly Spend & Income Pivot
A3: Bank Filter Toggles: | B3: Axis Bank | C3: HDFC Bank | D3: Kotak Mahindra Bank | E3: SBM Bank | F3: State Bank of India
B4: TRUE | C4: TRUE | D4: TRUE | E4: TRUE | F4: TRUE
B5: =IF(B4, B3, "") -> Axis Bank | C5: =IF(C4, C3, "") -> HDFC Bank | D5: =IF(D4, D3, "") -> Kotak Mahindra Bank | E5: =IF(E4, E3, "") -> SBM Bank | F5: =IF(F4, F3, "") -> State Bank of India
A7: PAYMENTS / DEBITS (Bank) | B7: Apr-2025 | C7: May-2025 | D7: Jun-2025 | E7: Jul-2025 | F7: Aug-2025 | G7: Sep-2025 | H7: Oct-2025 | I7: Nov-2025 | J7: Dec-2025 | K7: Jan-2026 | L7: Feb-2026 | M7: Mar-2026 | N7: Apr-2026 | O7: TOTAL
A8: Ajay Gupta | B8: =SUMPRODUCT(SUMIFS('For Tally'!C:C, 'For Tally'!H:H, $A8, 'For Tally'!A:A, ">=2025-04-01", 'For Tally'!A:A, "<=2025-04-30", 'For Tally'!L:L, $B$5:$F$5)) -> 0 | C8: =SUMPRODUCT(SUMIFS('For Tally'!C:C, 'For Tally'!H:H, $A8, 'For Tally'!A:A, ">=2025-05-01", 'For Tally'!A:A, "<=2025-05-31", 'For Tally'!L:L, $B$5:$F$5)) -> 0 | D8: =SUMPRODUCT(SUMIFS('For Tally'!C:C, 'For Tally'!H:H, $A8, 'For Tally'!A:A, ">=2025-06-01", 'For Tally'!A:A, "<=2025-06-30", 'For Tally'!L:L, $B$5:$F$5)) -> 0 | E8: =SUMPRODUCT(SUMIFS('For Tally'!C:C, 'For Tally'!H:H, $A8, 'For Tally'!A:A, ">=2025-07-01", 'For Tally'!A:A, "<=2025-07-31", 'For Tally'!L:L, $B$5:$F$5)) -> 10000 | F8: =SUMPRODUCT(SUMIFS('For Tally'!C:C, 'For Tally'!H:H, $A8, 'For Tally'!A:A, ">=2025-08-01", 'For Tally'!A:A, "<=2025-08-31", 'For Tally'!L:L, $B$5:$F$5)) -> 65001 | G8: =SUMPRODUCT(SUMIFS('For Tally'!C:C, 'For Tally'!H:H, $A8, 'For Tally'!A:A, ">=2025-09-01", 'For Tally'!A:A, "<=2025-09-30", 'For Tally'!L:L, $B$5:$F$5)) -> 50000 | H8: =SUMPRODUCT(SUMIFS('For Tally'!C:C, 'For Tally'!H:H, $A8, 'For Tally'!A:A, ">=2025-10-01", 'For Tally'!A:A, "<=2025-10-31", 'For Tally'!L:L, $B$5:$F$5)) -> 340000 | I8: =SUMPRODUCT(SUMIFS('For Tally'!C:C, 'For Tally'!H:H, $A8, 'For Tally'!A:A, ">=2025-11-01", 'For Tally'!A:A, "<=2025-11-30", 'For Tally'!L:L, $B$5:$F$5)) -> 30000 | J8: =SUMPRODUCT(SUMIFS('For Tally'!C:C, 'For Tally'!H:H, $A8, 'For Tally'!A:A, ">=2025-12-01", 'For Tally'!A:A, "<=2025-12-31", 'For Tally'!L:L, $B$5:$F$5)) -> 0 | K8: =SUMPRODUCT(SUMIFS('For Tally'!C:C, 'For Tally'!H:H, $A8, 'For Tally'!A:A, ">=2026-01-01", 'For Tally'!A:A, "<=2026-01-31", 'For Tally'!L:L, $B$5:$F$5)) -> 0 | L8: =SUMPRODUCT(SUMIFS('For Tally'!C:C, 'For Tally'!H:H, $A8, 'For Tally'!A:A, ">=2026-02-01", 'For Tally'!A:A, "<=2026-02-28", 'For Tally'!L:L, $B$5:$F$5)) -> 0 | M8: =SUMPRODUCT(SUMIFS('For Tally'!C:C, 'For Tally'!H:H, $A8, 'For Tally'!A:A, ">=2026-03-01", 'For Tally'!A:A, "<=2026-03-31", 'For Tally'!L:L, $B$5:$F$5)) -> 0 | N8: =SUMPRODUCT(SUMIFS('For Tally'!C:C, 'For Tally'!H:H, $A8, 'For Tally'!A:A, ">=2026-04-01", 'For Tally'!A:A, "<=2026-04-30", 'For Tally'!L:L, $B$5:$F$5)) -> 0 | O8: =SUM(B8:N8) -> 495001
A9: Archit Gupta | B9: =SUMPRODUCT(SUMIFS('For Tally'!C:C, 'For Tally'!H:H, $A9, 'For Tally'!A:A, ">=2025-04-01", 'For Tally'!A:A, "<=2025-04-30", 'For Tally'!L:L, $B$5:$F$5)) -> 0 | C9: =SUMPRODUCT(SUMIFS('For Tally'!C:C, 'For Tally'!H:H, $A9, 'For Tally'!A:A, ">=2025-05-01", 'For Tally'!A:A, "<=2025-05-31", 'For Tally'!L:L, $B$5:$F$5)) -> 100000 | D9: =SUMPRODUCT(SUMIFS('For Tally'!C:C, 'For Tally'!H:H, $A9, 'For Tally'!A:A, ">=2025-06-01", 'For Tally'!A:A, "<=2025-06-30", 'For Tally'!L:L, $B$5:$F$5)) -> 0 | E9: =SUMPRODUCT(SUMIFS('For Tally'!C:C, 'For Tally'!H:H, $A9, 'For Tally'!A:A, ">=2025-07-01", 'For Tally'!A:A, "<=2025-07-31", 'For Tally'!L:L, $B$5:$F$5)) -> 0 | F9: =SUMPRODUCT(SUMIFS('For Tally'!C:C, 'For Tally'!H:H, $A9, 'For Tally'!A:A, ">=2025-08-01", 'For Tally'!A:A, "<=2025-08-31", 'For Tally'!L:L, $B$5:$F$5)) -> 0 | G9: =SUMPRODUCT(SUMIFS('For Tally'!C:C, 'For Tally'!H:H, $A9, 'For Tally'!A:A, ">=2025-09-01", 'For Tally'!A:A, "<=2025-09-30", 'For Tally'!L:L, $B$5:$F$5)) -> 43200 | H9: =SUMPRODUCT(SUMIFS('For Tally'!C:C, 'For Tally'!H:H, $A9, 'For Tally'!A:A, ">=2025-10-01", 'For Tally'!A:A, "<=2025-10-31", 'For Tally'!L:L, $B$5:$F$5)) -> 0 | I9: =SUMPRODUCT(SUMIFS('For Tally'!C:C, 'For Tally'!H:H, $A9, 'For Tally'!A:A, ">=2025-11-01", 'For Tally'!A:A, "<=2025-11-30", 'For Tally'!L:L, $B$5:$F$5)) -> 0 | J9: =SUMPRODUCT(SUMIFS('For Tally'!C:C, 'For Tally'!H:H, $A9, 'For Tally'!A:A, ">=2025-12-01", 'For Tally'!A:A, "<=2025-12-31", 'For Tally'!L:L, $B$5:$F$5)) -> 10000 | K9: =SUMPRODUCT(SUMIFS('For Tally'!C:C, 'For Tally'!H:H, $A9, 'For Tally'!A:A, ">=2026-01-01", 'For Tally'!A:A, "<=2026-01-31", 'For Tally'!L:L, $B$5:$F$5)) -> 0 | L9: =SUMPRODUCT(SUMIFS('For Tally'!C:C, 'For Tally'!H:H, $A9, 'For Tally'!A:A, ">=2026-02-01", 'For Tally'!A:A, "<=2026-02-28", 'For Tally'!L:L, $B$5:$F$5)) -> 0 | M9: =SUMPRODUCT(SUMIFS('For Tally'!C:C, 'For Tally'!H:H, $A9, 'For Tally'!A:A, ">=2026-03-01", 'For Tally'!A:A, "<=2026-03-31", 'For Tally'!L:L, $B$5:$F$5)) -> 0 | N9: =SUMPRODUCT(SUMIFS('For Tally'!C:C, 'For Tally'!H:H, $A9, 'For Tally'!A:A, ">=2026-04-01", 'For Tally'!A:A, "<=2026-04-30", 'For Tally'!L:L, $B$5:$F$5)) -> 0 | O9: =SUM(B9:N9) -> 153200
A10: Bank Charges | B10: =SUMPRODUCT(SUMIFS('For Tally'!C:C, 'For Tally'!H:H, $A10, 'For Tally'!A:A, ">=2025-04-01", 'For Tally'!A:A, "<=2025-04-30", 'For Tally'!L:L, $B$5:$F$5)) -> 295 | C10: =SUMPRODUCT(SUMIFS('For Tally'!C:C, 'For Tally'!H:H, $A10, 'For Tally'!A:A, ">=2025-05-01", 'For Tally'!A:A, "<=2025-05-31", 'For Tally'!L:L, $B$5:$F$5)) -> 0 | D10: =SUMPRODUCT(SUMIFS('For Tally'!C:C, 'For Tally'!H:H, $A10, 'For Tally'!A:A, ">=2025-06-01", 'For Tally'!A:A, "<=2025-06-30", 'For Tally'!L:L, $B$5:$F$5)) -> 305.96 | E10: =SUMPRODUCT(SUMIFS('For Tally'!C:C, 'For Tally'!H:H, $A10, 'For Tally'!A:A, ">=2025-07-01", 'For Tally'!A:A, "<=2025-07-31", 'For Tally'!L:L, $B$5:$F$5)) -> 0 | F10: =SUMPRODUCT(SUMIFS('For Tally'!C:C, 'For Tally'!H:H, $A10, 'For Tally'!A:A, ">=2025-08-01", 'For Tally'!A:A, "<=2025-08-31", 'For Tally'!L:L, $B$5:$F$5)) -> 0 | G10: =SUMPRODUCT(SUMIFS('For Tally'!C:C, 'For Tally'!H:H, $A10, 'For Tally'!A:A, ">=2025-09-01", 'For Tally'!A:A, "<=2025-09-30", 'For Tally'!L:L, $B$5:$F$5)) -> 295 | H10: =SUMPRODUCT(SUMIFS('For Tally'!C:C, 'For Tally'!H:H, $A10, 'For Tally'!A:A, ">=2025-10-01", 'For Tally'!A:A, "<=2025-10-31", 'For Tally'!L:L, $B$5:$F$5)) -> 0 | I10: =SUMPRODUCT(SUMIFS('For Tally'!C:C, 'For Tally'!H:H, $A10, 'For Tally'!A:A, ">=2025-11-01", 'For Tally'!A:A, "<=2025-11-30", 'For Tally'!L:L, $B$5:$F$5)) -> 0 | J10: =SUMPRODUCT(SUMIFS('For Tally'!C:C, 'For Tally'!H:H, $A10, 'For Tally'!A:A, ">=2025-12-01", 'For Tally'!A:A, "<=2025-12-31", 'For Tally'!L:L, $B$5:$F$5)) -> 0 | K10: =SUMPRODUCT(SUMIFS('For Tally'!C:C, 'For Tally'!H:H, $A10, 'For Tally'!A:A, ">=2026-01-01", 'For Tally'!A:A, "<=2026-01-31", 'For Tally'!L:L, $B$5:$F$5)) -> 295 | L10: =SUMPRODUCT(SUMIFS('For Tally'!C:C, 'For Tally'!H:H, $A10, 'For Tally'!A:A, ">=2026-02-01", 'For Tally'!A:A, "<=2026-02-28", 'For Tally'!L:L, $B$5:$F$5)) -> 295 | M10: =SUMPRODUCT(SUMIFS('For Tally'!C:C, 'For Tally'!H:H, $A10, 'For Tally'!A:A, ">=2026-03-01", 'For Tally'!A:A, "<=2026-03-31", 'For Tally'!L:L, $B$5:$F$5)) -> 885 | N10: =SUMPRODUCT(SUMIFS('For Tally'!C:C, 'For Tally'!H:H, $A10, 'For Tally'!A:A, ">=2026-04-01", 'For Tally'!A:A, "<=2026-04-30", 'For Tally'!L:L, $B$5:$F$5)) -> 0 | O10: =SUM(B10:N10) -> 2370.96
A11: Cash | B11: =SUMPRODUCT(SUMIFS('For Tally'!C:C, 'For Tally'!H:H, $A11, 'For Tally'!A:A, ">=2025-04-01", 'For Tally'!A:A, "<=2025-04-30", 'For Tally'!L:L, $B$5:$F$5)) -> 500 | C11: =SUMPRODUCT(SUMIFS('For Tally'!C:C, 'For Tally'!H:H, $A11, 'For Tally'!A:A, ">=2025-05-01", 'For Tally'!A:A, "<=2025-05-31", 'For Tally'!L:L, $B$5:$F$5)) -> 0 | D11: =SUMPRODUCT(SUMIFS('For Tally'!C:C, 'For Tally'!H:H, $A11, 'For Tally'!A:A, ">=2025-06-01", 'For Tally'!A:A, "<=2025-06-30", 'For Tally'!L:L, $B$5:$F$5)) -> 0 | E11: =SUMPRODUCT(SUMIFS('For Tally'!C:C, 'For Tally'!H:H, $A11, 'For Tally'!A:A, ">=2025-07-01", 'For Tally'!A:A, "<=2025-07-31", 'For Tally'!L:L, $B$5:$F$5)) -> 0 | F11: =SUMPRODUCT(SUMIFS('For Tally'!C:C, 'For Tally'!H:H, $A11, 'For Tally'!A:A, ">=2025-08-01", 'For Tally'!A:A, "<=2025-08-31", 'For Tally'!L:L, $B$5:$F$5)) -> 0 | G11: =SUMPRODUCT(SUMIFS('For Tally'!C:C, 'For Tally'!H:H, $A11, 'For Tally'!A:A, ">=2025-09-01", 'For Tally'!A:A, "<=2025-09-30", 'For Tally'!L:L, $B$5:$F$5)) -> 0 | H11: =SUMPRODUCT(SUMIFS('For Tally'!C:C, 'For Tally'!H:H, $A11, 'For Tally'!A:A, ">=2025-10-01", 'For Tally'!A:A, "<=2025-10-31", 'For Tally'!L:L, $B$5:$F$5)) -> 0 | I11: =SUMPRODUCT(SUMIFS('For Tally'!C:C, 'For Tally'!H:H, $A11, 'For Tally'!A:A, ">=2025-11-01", 'For Tally'!A:A, "<=2025-11-30", 'For Tally'!L:L, $B$5:$F$5)) -> 0 | J11: =SUMPRODUCT(SUMIFS('For Tally'!C:C, 'For Tally'!H:H, $A11, 'For Tally'!A:A, ">=2025-12-01", 'For Tally'!A:A, "<=2025-12-31", 'For Tally'!L:L, $B$5:$F$5)) -> 0 | K11: =SUMPRODUCT(SUMIFS('For Tally'!C:C, 'For Tally'!H:H, $A11, 'For Tally'!A:A, ">=2026-01-01", 'For Tally'!A:A, "<=2026-01-31", 'For Tally'!L:L, $B$5:$F$5)) -> 0 | L11: =SUMPRODUCT(SUMIFS('For Tally'!C:C, 'For Tally'!H:H, $A11, 'For Tally'!A:A, ">=2026-02-01", 'For Tally'!A:A, "<=2026-02-28", 'For Tally'!L:L, $B$5:$F$5)) -> 0 | M11: =SUMPRODUCT(SUMIFS('For Tally'!C:C, 'For Tally'!H:H, $A11, 'For Tally'!A:A, ">=2026-03-01", 'For Tally'!A:A, "<=2026-03-31", 'For Tally'!L:L, $B$5:$F$5)) -> 0 | N11: =SUMPRODUCT(SUMIFS('For Tally'!C:C, 'For Tally'!H:H, $A11, 'For Tally'!A:A, ">=2026-04-01", 'For Tally'!A:A, "<=2026-04-30", 'For Tally'!L:L, $B$5:$F$5)) -> 0 | O11: =SUM(B11:N11) -> 500
A12: Credit Card | B12: =SUMPRODUCT(SUMIFS('For Tally'!C:C, 'For Tally'!H:H, $A12, 'For Tally'!A:A, ">=2025-04-01", 'For Tally'!A:A, "<=2025-04-30", 'For Tally'!L:L, $B$5:$F$5)) -> 21872.93 | C12: =SUMPRODUCT(SUMIFS('For Tally'!C:C, 'For Tally'!H:H, $A12, 'For Tally'!A:A, ">=2025-05-01", 'For Tally'!A:A, "<=2025-05-31", 'For Tally'!L:L, $B$5:$F$5)) -> 3240.66 | D12: =SUMPRODUCT(SUMIFS('For Tally'!C:C, 'For Tally'!H:H, $A12, 'For Tally'!A:A, ">=2025-06-01", 'For Tally'!A:A, "<=2025-06-30", 'For Tally'!L:L, $B$5:$F$5)) -> 25902.75 | E12: =SUMPRODUCT(SUMIFS('For Tally'!C:C, 'For Tally'!H:H, $A12, 'For Tally'!A:A, ">=2025-07-01", 'For Tally'!A:A, "<=2025-07-31", 'For Tally'!L:L, $B$5:$F$5)) -> 15134.43 | F12: =SUMPRODUCT(SUMIFS('For Tally'!C:C, 'For Tally'!H:H, $A12, 'For Tally'!A:A, ">=2025-08-01", 'For Tally'!A:A, "<=2025-08-31", 'For Tally'!L:L, $B$5:$F$5)) -> 9876.87 | G12: =SUMPRODUCT(SUMIFS('For Tally'!C:C, 'For Tally'!H:H, $A12, 'For Tally'!A:A, ">=2025-09-01", 'For Tally'!A:A, "<=2025-09-30", 'For Tally'!L:L, $B$5:$F$5)) -> 29186.82 | H12: =SUMPRODUCT(SUMIFS('For Tally'!C:C, 'For Tally'!H:H, $A12, 'For Tally'!A:A, ">=2025-10-01", 'For Tally'!A:A, "<=2025-10-31", 'For Tally'!L:L, $B$5:$F$5)) -> 46603.95 | I12: =SUMPRODUCT(SUMIFS('For Tally'!C:C, 'For Tally'!H:H, $A12, 'For Tally'!A:A, ">=2025-11-01", 'For Tally'!A:A, "<=2025-11-30", 'For Tally'!L:L, $B$5:$F$5)) -> 26440.5 | J12: =SUMPRODUCT(SUMIFS('For Tally'!C:C, 'For Tally'!H:H, $A12, 'For Tally'!A:A, ">=2025-12-01", 'For Tally'!A:A, "<=2025-12-31", 'For Tally'!L:L, $B$5:$F$5)) -> 20167.93 | K12: =SUMPRODUCT(SUMIFS('For Tally'!C:C, 'For Tally'!H:H, $A12, 'For Tally'!A:A, ">=2026-01-01", 'For Tally'!A:A, "<=2026-01-31", 'For Tally'!L:L, $B$5:$F$5)) -> 48809.24 | L12: =SUMPRODUCT(SUMIFS('For Tally'!C:C, 'For Tally'!H:H, $A12, 'For Tally'!A:A, ">=2026-02-01", 'For Tally'!A:A, "<=2026-02-28", 'For Tally'!L:L, $B$5:$F$5)) -> 22106.85 | M12: =SUMPRODUCT(SUMIFS('For Tally'!C:C, 'For Tally'!H:H, $A12, 'For Tally'!A:A, ">=2026-03-01", 'For Tally'!A:A, "<=2026-03-31", 'For Tally'!L:L, $B$5:$F$5)) -> 12183.37 | N12: =SUMPRODUCT(SUMIFS('For Tally'!C:C, 'For Tally'!H:H, $A12, 'For Tally'!A:A, ">=2026-04-01", 'For Tally'!A:A, "<=2026-04-30", 'For Tally'!L:L, $B$5:$F$5)) -> 0 | O12: =SUM(B12:N12) -> 281526.3
A13: Depository Charges | B13: =SUMPRODUCT(SUMIFS('For Tally'!C:C, 'For Tally'!H:H, $A13, 'For Tally'!A:A, ">=2025-04-01", 'For Tally'!A:A, "<=2025-04-30", 'For Tally'!L:L, $B$5:$F$5)) -> 531 | C13: =SUMPRODUCT(SUMIFS('For Tally'!C:C, 'For Tally'!H:H, $A13, 'For Tally'!A:A, ">=2025-05-01", 'For Tally'!A:A, "<=2025-05-31", 'For Tally'!L:L, $B$5:$F$5)) -> 1062 | D13: =SUMPRODUCT(SUMIFS('For Tally'!C:C, 'For Tally'!H:H, $A13, 'For Tally'!A:A, ">=2025-06-01", 'For Tally'!A:A, "<=2025-06-30", 'For Tally'!L:L, $B$5:$F$5)) -> 719.8 | E13: =SUMPRODUCT(SUMIFS('For Tally'!C:C, 'For Tally'!H:H, $A13, 'For Tally'!A:A, ">=2025-07-01", 'For Tally'!A:A, "<=2025-07-31", 'For Tally'!L:L, $B$5:$F$5)) -> 330.4 | F13: =SUMPRODUCT(SUMIFS('For Tally'!C:C, 'For Tally'!H:H, $A13, 'For Tally'!A:A, ">=2025-08-01", 'For Tally'!A:A, "<=2025-08-31", 'For Tally'!L:L, $B$5:$F$5)) -> 460.2 | G13: =SUMPRODUCT(SUMIFS('For Tally'!C:C, 'For Tally'!H:H, $A13, 'For Tally'!A:A, ">=2025-09-01", 'For Tally'!A:A, "<=2025-09-30", 'For Tally'!L:L, $B$5:$F$5)) -> 330.4 | H13: =SUMPRODUCT(SUMIFS('For Tally'!C:C, 'For Tally'!H:H, $A13, 'For Tally'!A:A, ">=2025-10-01", 'For Tally'!A:A, "<=2025-10-31", 'For Tally'!L:L, $B$5:$F$5)) -> 637.2 | I13: =SUMPRODUCT(SUMIFS('For Tally'!C:C, 'For Tally'!H:H, $A13, 'For Tally'!A:A, ">=2025-11-01", 'For Tally'!A:A, "<=2025-11-30", 'For Tally'!L:L, $B$5:$F$5)) -> 1109.2 | J13: =SUMPRODUCT(SUMIFS('For Tally'!C:C, 'For Tally'!H:H, $A13, 'For Tally'!A:A, ">=2025-12-01", 'For Tally'!A:A, "<=2025-12-31", 'For Tally'!L:L, $B$5:$F$5)) -> 365.8 | K13: =SUMPRODUCT(SUMIFS('For Tally'!C:C, 'For Tally'!H:H, $A13, 'For Tally'!A:A, ">=2026-01-01", 'For Tally'!A:A, "<=2026-01-31", 'For Tally'!L:L, $B$5:$F$5)) -> 82.6 | L13: =SUMPRODUCT(SUMIFS('For Tally'!C:C, 'For Tally'!H:H, $A13, 'For Tally'!A:A, ">=2026-02-01", 'For Tally'!A:A, "<=2026-02-28", 'For Tally'!L:L, $B$5:$F$5)) -> 94.4 | M13: =SUMPRODUCT(SUMIFS('For Tally'!C:C, 'For Tally'!H:H, $A13, 'For Tally'!A:A, ">=2026-03-01", 'For Tally'!A:A, "<=2026-03-31", 'For Tally'!L:L, $B$5:$F$5)) -> 82.6 | N13: =SUMPRODUCT(SUMIFS('For Tally'!C:C, 'For Tally'!H:H, $A13, 'For Tally'!A:A, ">=2026-04-01", 'For Tally'!A:A, "<=2026-04-30", 'For Tally'!L:L, $B$5:$F$5)) -> 0 | O13: =SUM(B13:N13) -> 5805.6
A14: Entertainment | B14: =SUMPRODUCT(SUMIFS('For Tally'!C:C, 'For Tally'!H:H, $A14, 'For Tally'!A:A, ">=2025-04-01", 'For Tally'!A:A, "<=2025-04-30", 'For Tally'!L:L, $B$5:$F$5)) -> 0 | C14: =SUMPRODUCT(SUMIFS('For Tally'!C:C, 'For Tally'!H:H, $A14, 'For Tally'!A:A, ">=2025-05-01", 'For Tally'!A:A, "<=2025-05-31", 'For Tally'!L:L, $B$5:$F$5)) -> 0 | D14: =SUMPRODUCT(SUMIFS('For Tally'!C:C, 'For Tally'!H:H, $A14, 'For Tally'!A:A, ">=2025-06-01", 'For Tally'!A:A, "<=2025-06-30", 'For Tally'!L:L, $B$5:$F$5)) -> 0 | E14: =SUMPRODUCT(SUMIFS('For Tally'!C:C, 'For Tally'!H:H, $A14, 'For Tally'!A:A, ">=2025-07-01", 'For Tally'!A:A, "<=2025-07-31", 'For Tally'!L:L, $B$5:$F$5)) -> 0 | F14: =SUMPRODUCT(SUMIFS('For Tally'!C:C, 'For Tally'!H:H, $A14, 'For Tally'!A:A, ">=2025-08-01", 'For Tally'!A:A, "<=2025-08-31", 'For Tally'!L:L, $B$5:$F$5)) -> 0 | G14: =SUMPRODUCT(SUMIFS('For Tally'!C:C, 'For Tally'!H:H, $A14, 'For Tally'!A:A, ">=2025-09-01", 'For Tally'!A:A, "<=2025-09-30", 'For Tally'!L:L, $B$5:$F$5)) -> 2100 | H14: =SUMPRODUCT(SUMIFS('For Tally'!C:C, 'For Tally'!H:H, $A14, 'For Tally'!A:A, ">=2025-10-01", 'For Tally'!A:A, "<=2025-10-31", 'For Tally'!L:L, $B$5:$F$5)) -> 0 | I14: =SUMPRODUCT(SUMIFS('For Tally'!C:C, 'For Tally'!H:H, $A14, 'For Tally'!A:A, ">=2025-11-01", 'For Tally'!A:A, "<=2025-11-30", 'For Tally'!L:L, $B$5:$F$5)) -> 0 | J14: =SUMPRODUCT(SUMIFS('For Tally'!C:C, 'For Tally'!H:H, $A14, 'For Tally'!A:A, ">=2025-12-01", 'For Tally'!A:A, "<=2025-12-31", 'For Tally'!L:L, $B$5:$F$5)) -> 0 | K14: =SUMPRODUCT(SUMIFS('For Tally'!C:C, 'For Tally'!H:H, $A14, 'For Tally'!A:A, ">=2026-01-01", 'For Tally'!A:A, "<=2026-01-31", 'For Tally'!L:L, $B$5:$F$5)) -> 0 | L14: =SUMPRODUCT(SUMIFS('For Tally'!C:C, 'For Tally'!H:H, $A14, 'For Tally'!A:A, ">=2026-02-01", 'For Tally'!A:A, "<=2026-02-28", 'For Tally'!L:L, $B$5:$F$5)) -> 0 | M14: =SUMPRODUCT(SUMIFS('For Tally'!C:C, 'For Tally'!H:H, $A14, 'For Tally'!A:A, ">=2026-03-01", 'For Tally'!A:A, "<=2026-03-31", 'For Tally'!L:L, $B$5:$F$5)) -> 0 | N14: =SUMPRODUCT(SUMIFS('For Tally'!C:C, 'For Tally'!H:H, $A14, 'For Tally'!A:A, ">=2026-04-01", 'For Tally'!A:A, "<=2026-04-30", 'For Tally'!L:L, $B$5:$F$5)) -> 0 | O14: =SUM(B14:N14) -> 2100
A15: Equities | B15: =SUMPRODUCT(SUMIFS('For Tally'!C:C, 'For Tally'!H:H, $A15, 'For Tally'!A:A, ">=2025-04-01", 'For Tally'!A:A, "<=2025-04-30", 'For Tally'!L:L, $B$5:$F$5)) -> 0 | C15: =SUMPRODUCT(SUMIFS('For Tally'!C:C, 'For Tally'!H:H, $A15, 'For Tally'!A:A, ">=2025-05-01", 'For Tally'!A:A, "<=2025-05-31", 'For Tally'!L:L, $B$5:$F$5)) -> 0 | D15: =SUMPRODUCT(SUMIFS('For Tally'!C:C, 'For Tally'!H:H, $A15, 'For Tally'!A:A, ">=2025-06-01", 'For Tally'!A:A, "<=2025-06-30", 'For Tally'!L:L, $B$5:$F$5)) -> 0 | E15: =SUMPRODUCT(SUMIFS('For Tally'!C:C, 'For Tally'!H:H, $A15, 'For Tally'!A:A, ">=2025-07-01", 'For Tally'!A:A, "<=2025-07-31", 'For Tally'!L:L, $B$5:$F$5)) -> 0 | F15: =SUMPRODUCT(SUMIFS('For Tally'!C:C, 'For Tally'!H:H, $A15, 'For Tally'!A:A, ">=2025-08-01", 'For Tally'!A:A, "<=2025-08-31", 'For Tally'!L:L, $B$5:$F$5)) -> 14994 | G15: =SUMPRODUCT(SUMIFS('For Tally'!C:C, 'For Tally'!H:H, $A15, 'For Tally'!A:A, ">=2025-09-01", 'For Tally'!A:A, "<=2025-09-30", 'For Tally'!L:L, $B$5:$F$5)) -> 0 | H15: =SUMPRODUCT(SUMIFS('For Tally'!C:C, 'For Tally'!H:H, $A15, 'For Tally'!A:A, ">=2025-10-01", 'For Tally'!A:A, "<=2025-10-31", 'For Tally'!L:L, $B$5:$F$5)) -> 0 | I15: =SUMPRODUCT(SUMIFS('For Tally'!C:C, 'For Tally'!H:H, $A15, 'For Tally'!A:A, ">=2025-11-01", 'For Tally'!A:A, "<=2025-11-30", 'For Tally'!L:L, $B$5:$F$5)) -> 0 | J15: =SUMPRODUCT(SUMIFS('For Tally'!C:C, 'For Tally'!H:H, $A15, 'For Tally'!A:A, ">=2025-12-01", 'For Tally'!A:A, "<=2025-12-31", 'For Tally'!L:L, $B$5:$F$5)) -> 0 | K15: =SUMPRODUCT(SUMIFS('For Tally'!C:C, 'For Tally'!H:H, $A15, 'For Tally'!A:A, ">=2026-01-01", 'For Tally'!A:A, "<=2026-01-31", 'For Tally'!L:L, $B$5:$F$5)) -> 0 | L15: =SUMPRODUCT(SUMIFS('For Tally'!C:C, 'For Tally'!H:H, $A15, 'For Tally'!A:A, ">=2026-02-01", 'For Tally'!A:A, "<=2026-02-28", 'For Tally'!L:L, $B$5:$F$5)) -> 0 | M15: =SUMPRODUCT(SUMIFS('For Tally'!C:C, 'For Tally'!H:H, $A15, 'For Tally'!A:A, ">=2026-03-01", 'For Tally'!A:A, "<=2026-03-31", 'For Tally'!L:L, $B$5:$F$5)) -> 0 | N15: =SUMPRODUCT(SUMIFS('For Tally'!C:C, 'For Tally'!H:H, $A15, 'For Tally'!A:A, ">=2026-04-01", 'For Tally'!A:A, "<=2026-04-30", 'For Tally'!L:L, $B$5:$F$5)) -> 0 | O15: =SUM(B15:N15) -> 14994
A16: Food & Dining | B16: =SUMPRODUCT(SUMIFS('For Tally'!C:C, 'For Tally'!H:H, $A16, 'For Tally'!A:A, ">=2025-04-01", 'For Tally'!A:A, "<=2025-04-30", 'For Tally'!L:L, $B$5:$F$5)) -> 0 | C16: =SUMPRODUCT(SUMIFS('For Tally'!C:C, 'For Tally'!H:H, $A16, 'For Tally'!A:A, ">=2025-05-01", 'For Tally'!A:A, "<=2025-05-31", 'For Tally'!L:L, $B$5:$F$5)) -> 0 | D16: =SUMPRODUCT(SUMIFS('For Tally'!C:C, 'For Tally'!H:H, $A16, 'For Tally'!A:A, ">=2025-06-01", 'For Tally'!A:A, "<=2025-06-30", 'For Tally'!L:L, $B$5:$F$5)) -> 0 | E16: =SUMPRODUCT(SUMIFS('For Tally'!C:C, 'For Tally'!H:H, $A16, 'For Tally'!A:A, ">=2025-07-01", 'For Tally'!A:A, "<=2025-07-31", 'For Tally'!L:L, $B$5:$F$5)) -> 0 | F16: =SUMPRODUCT(SUMIFS('For Tally'!C:C, 'For Tally'!H:H, $A16, 'For Tally'!A:A, ">=2025-08-01", 'For Tally'!A:A, "<=2025-08-31", 'For Tally'!L:L, $B$5:$F$5)) -> 283 | G16: =SUMPRODUCT(SUMIFS('For Tally'!C:C, 'For Tally'!H:H, $A16, 'For Tally'!A:A, ">=2025-09-01", 'For Tally'!A:A, "<=2025-09-30", 'For Tally'!L:L, $B$5:$F$5)) -> 2382 | H16: =SUMPRODUCT(SUMIFS('For Tally'!C:C, 'For Tally'!H:H, $A16, 'For Tally'!A:A, ">=2025-10-01", 'For Tally'!A:A, "<=2025-10-31", 'For Tally'!L:L, $B$5:$F$5)) -> 0 | I16: =SUMPRODUCT(SUMIFS('For Tally'!C:C, 'For Tally'!H:H, $A16, 'For Tally'!A:A, ">=2025-11-01", 'For Tally'!A:A, "<=2025-11-30", 'For Tally'!L:L, $B$5:$F$5)) -> 0 | J16: =SUMPRODUCT(SUMIFS('For Tally'!C:C, 'For Tally'!H:H, $A16, 'For Tally'!A:A, ">=2025-12-01", 'For Tally'!A:A, "<=2025-12-31", 'For Tally'!L:L, $B$5:$F$5)) -> 0 | K16: =SUMPRODUCT(SUMIFS('For Tally'!C:C, 'For Tally'!H:H, $A16, 'For Tally'!A:A, ">=2026-01-01", 'For Tally'!A:A, "<=2026-01-31", 'For Tally'!L:L, $B$5:$F$5)) -> 2258.89 | L16: =SUMPRODUCT(SUMIFS('For Tally'!C:C, 'For Tally'!H:H, $A16, 'For Tally'!A:A, ">=2026-02-01", 'For Tally'!A:A, "<=2026-02-28", 'For Tally'!L:L, $B$5:$F$5)) -> 0 | M16: =SUMPRODUCT(SUMIFS('For Tally'!C:C, 'For Tally'!H:H, $A16, 'For Tally'!A:A, ">=2026-03-01", 'For Tally'!A:A, "<=2026-03-31", 'For Tally'!L:L, $B$5:$F$5)) -> 0 | N16: =SUMPRODUCT(SUMIFS('For Tally'!C:C, 'For Tally'!H:H, $A16, 'For Tally'!A:A, ">=2026-04-01", 'For Tally'!A:A, "<=2026-04-30", 'For Tally'!L:L, $B$5:$F$5)) -> 0 | O16: =SUM(B16:N16) -> 4923.89
A17: Fuel & Petrol | B17: =SUMPRODUCT(SUMIFS('For Tally'!C:C, 'For Tally'!H:H, $A17, 'For Tally'!A:A, ">=2025-04-01", 'For Tally'!A:A, "<=2025-04-30", 'For Tally'!L:L, $B$5:$F$5)) -> 0 | C17: =SUMPRODUCT(SUMIFS('For Tally'!C:C, 'For Tally'!H:H, $A17, 'For Tally'!A:A, ">=2025-05-01", 'For Tally'!A:A, "<=2025-05-31", 'For Tally'!L:L, $B$5:$F$5)) -> 0 | D17: =SUMPRODUCT(SUMIFS('For Tally'!C:C, 'For Tally'!H:H, $A17, 'For Tally'!A:A, ">=2025-06-01", 'For Tally'!A:A, "<=2025-06-30", 'For Tally'!L:L, $B$5:$F$5)) -> 260 | E17: =SUMPRODUCT(SUMIFS('For Tally'!C:C, 'For Tally'!H:H, $A17, 'For Tally'!A:A, ">=2025-07-01", 'For Tally'!A:A, "<=2025-07-31", 'For Tally'!L:L, $B$5:$F$5)) -> 360 | F17: =SUMPRODUCT(SUMIFS('For Tally'!C:C, 'For Tally'!H:H, $A17, 'For Tally'!A:A, ">=2025-08-01", 'For Tally'!A:A, "<=2025-08-31", 'For Tally'!L:L, $B$5:$F$5)) -> 620 | G17: =SUMPRODUCT(SUMIFS('For Tally'!C:C, 'For Tally'!H:H, $A17, 'For Tally'!A:A, ">=2025-09-01", 'For Tally'!A:A, "<=2025-09-30", 'For Tally'!L:L, $B$5:$F$5)) -> 360 | H17: =SUMPRODUCT(SUMIFS('For Tally'!C:C, 'For Tally'!H:H, $A17, 'For Tally'!A:A, ">=2025-10-01", 'For Tally'!A:A, "<=2025-10-31", 'For Tally'!L:L, $B$5:$F$5)) -> 310 | I17: =SUMPRODUCT(SUMIFS('For Tally'!C:C, 'For Tally'!H:H, $A17, 'For Tally'!A:A, ">=2025-11-01", 'For Tally'!A:A, "<=2025-11-30", 'For Tally'!L:L, $B$5:$F$5)) -> 260 | J17: =SUMPRODUCT(SUMIFS('For Tally'!C:C, 'For Tally'!H:H, $A17, 'For Tally'!A:A, ">=2025-12-01", 'For Tally'!A:A, "<=2025-12-31", 'For Tally'!L:L, $B$5:$F$5)) -> 210 | K17: =SUMPRODUCT(SUMIFS('For Tally'!C:C, 'For Tally'!H:H, $A17, 'For Tally'!A:A, ">=2026-01-01", 'For Tally'!A:A, "<=2026-01-31", 'For Tally'!L:L, $B$5:$F$5)) -> 0 | L17: =SUMPRODUCT(SUMIFS('For Tally'!C:C, 'For Tally'!H:H, $A17, 'For Tally'!A:A, ">=2026-02-01", 'For Tally'!A:A, "<=2026-02-28", 'For Tally'!L:L, $B$5:$F$5)) -> 0 | M17: =SUMPRODUCT(SUMIFS('For Tally'!C:C, 'For Tally'!H:H, $A17, 'For Tally'!A:A, ">=2026-03-01", 'For Tally'!A:A, "<=2026-03-31", 'For Tally'!L:L, $B$5:$F$5)) -> 0 | N17: =SUMPRODUCT(SUMIFS('For Tally'!C:C, 'For Tally'!H:H, $A17, 'For Tally'!A:A, ">=2026-04-01", 'For Tally'!A:A, "<=2026-04-30", 'For Tally'!L:L, $B$5:$F$5)) -> 0 | O17: =SUM(B17:N17) -> 2380
A18: Groceries | B18: =SUMPRODUCT(SUMIFS('For Tally'!C:C, 'For Tally'!H:H, $A18, 'For Tally'!A:A, ">=2025-04-01", 'For Tally'!A:A, "<=2025-04-30", 'For Tally'!L:L, $B$5:$F$5)) -> 60 | C18: =SUMPRODUCT(SUMIFS('For Tally'!C:C, 'For Tally'!H:H, $A18, 'For Tally'!A:A, ">=2025-05-01", 'For Tally'!A:A, "<=2025-05-31", 'For Tally'!L:L, $B$5:$F$5)) -> 584 | D18: =SUMPRODUCT(SUMIFS('For Tally'!C:C, 'For Tally'!H:H, $A18, 'For Tally'!A:A, ">=2025-06-01", 'For Tally'!A:A, "<=2025-06-30", 'For Tally'!L:L, $B$5:$F$5)) -> 430 | E18: =SUMPRODUCT(SUMIFS('For Tally'!C:C, 'For Tally'!H:H, $A18, 'For Tally'!A:A, ">=2025-07-01", 'For Tally'!A:A, "<=2025-07-31", 'For Tally'!L:L, $B$5:$F$5)) -> 3397 | F18: =SUMPRODUCT(SUMIFS('For Tally'!C:C, 'For Tally'!H:H, $A18, 'For Tally'!A:A, ">=2025-08-01", 'For Tally'!A:A, "<=2025-08-31", 'For Tally'!L:L, $B$5:$F$5)) -> 0 | G18: =SUMPRODUCT(SUMIFS('For Tally'!C:C, 'For Tally'!H:H, $A18, 'For Tally'!A:A, ">=2025-09-01", 'For Tally'!A:A, "<=2025-09-30", 'For Tally'!L:L, $B$5:$F$5)) -> 430 | H18: =SUMPRODUCT(SUMIFS('For Tally'!C:C, 'For Tally'!H:H, $A18, 'For Tally'!A:A, ">=2025-10-01", 'For Tally'!A:A, "<=2025-10-31", 'For Tally'!L:L, $B$5:$F$5)) -> 70 | I18: =SUMPRODUCT(SUMIFS('For Tally'!C:C, 'For Tally'!H:H, $A18, 'For Tally'!A:A, ">=2025-11-01", 'For Tally'!A:A, "<=2025-11-30", 'For Tally'!L:L, $B$5:$F$5)) -> 318 | J18: =SUMPRODUCT(SUMIFS('For Tally'!C:C, 'For Tally'!H:H, $A18, 'For Tally'!A:A, ">=2025-12-01", 'For Tally'!A:A, "<=2025-12-31", 'For Tally'!L:L, $B$5:$F$5)) -> 524 | K18: =SUMPRODUCT(SUMIFS('For Tally'!C:C, 'For Tally'!H:H, $A18, 'For Tally'!A:A, ">=2026-01-01", 'For Tally'!A:A, "<=2026-01-31", 'For Tally'!L:L, $B$5:$F$5)) -> 4192.3 | L18: =SUMPRODUCT(SUMIFS('For Tally'!C:C, 'For Tally'!H:H, $A18, 'For Tally'!A:A, ">=2026-02-01", 'For Tally'!A:A, "<=2026-02-28", 'For Tally'!L:L, $B$5:$F$5)) -> 158 | M18: =SUMPRODUCT(SUMIFS('For Tally'!C:C, 'For Tally'!H:H, $A18, 'For Tally'!A:A, ">=2026-03-01", 'For Tally'!A:A, "<=2026-03-31", 'For Tally'!L:L, $B$5:$F$5)) -> 0 | N18: =SUMPRODUCT(SUMIFS('For Tally'!C:C, 'For Tally'!H:H, $A18, 'For Tally'!A:A, ">=2026-04-01", 'For Tally'!A:A, "<=2026-04-30", 'For Tally'!L:L, $B$5:$F$5)) -> 0 | O18: =SUM(B18:N18) -> 10163.3
A19: HDFC Securities | B19: =SUMPRODUCT(SUMIFS('For Tally'!C:C, 'For Tally'!H:H, $A19, 'For Tally'!A:A, ">=2025-04-01", 'For Tally'!A:A, "<=2025-04-30", 'For Tally'!L:L, $B$5:$F$5)) -> 73370.42 | C19: =SUMPRODUCT(SUMIFS('For Tally'!C:C, 'For Tally'!H:H, $A19, 'For Tally'!A:A, ">=2025-05-01", 'For Tally'!A:A, "<=2025-05-31", 'For Tally'!L:L, $B$5:$F$5)) -> 107668.73 | D19: =SUMPRODUCT(SUMIFS('For Tally'!C:C, 'For Tally'!H:H, $A19, 'For Tally'!A:A, ">=2025-06-01", 'For Tally'!A:A, "<=2025-06-30", 'For Tally'!L:L, $B$5:$F$5)) -> 45869.9 | E19: =SUMPRODUCT(SUMIFS('For Tally'!C:C, 'For Tally'!H:H, $A19, 'For Tally'!A:A, ">=2025-07-01", 'For Tally'!A:A, "<=2025-07-31", 'For Tally'!L:L, $B$5:$F$5)) -> 94864.86 | F19: =SUMPRODUCT(SUMIFS('For Tally'!C:C, 'For Tally'!H:H, $A19, 'For Tally'!A:A, ">=2025-08-01", 'For Tally'!A:A, "<=2025-08-31", 'For Tally'!L:L, $B$5:$F$5)) -> 58188.21 | G19: =SUMPRODUCT(SUMIFS('For Tally'!C:C, 'For Tally'!H:H, $A19, 'For Tally'!A:A, ">=2025-09-01", 'For Tally'!A:A, "<=2025-09-30", 'For Tally'!L:L, $B$5:$F$5)) -> 146931.75 | H19: =SUMPRODUCT(SUMIFS('For Tally'!C:C, 'For Tally'!H:H, $A19, 'For Tally'!A:A, ">=2025-10-01", 'For Tally'!A:A, "<=2025-10-31", 'For Tally'!L:L, $B$5:$F$5)) -> 46065.23 | I19: =SUMPRODUCT(SUMIFS('For Tally'!C:C, 'For Tally'!H:H, $A19, 'For Tally'!A:A, ">=2025-11-01", 'For Tally'!A:A, "<=2025-11-30", 'For Tally'!L:L, $B$5:$F$5)) -> 18726.76 | J19: =SUMPRODUCT(SUMIFS('For Tally'!C:C, 'For Tally'!H:H, $A19, 'For Tally'!A:A, ">=2025-12-01", 'For Tally'!A:A, "<=2025-12-31", 'For Tally'!L:L, $B$5:$F$5)) -> 46303.46 | K19: =SUMPRODUCT(SUMIFS('For Tally'!C:C, 'For Tally'!H:H, $A19, 'For Tally'!A:A, ">=2026-01-01", 'For Tally'!A:A, "<=2026-01-31", 'For Tally'!L:L, $B$5:$F$5)) -> 24061.71 | L19: =SUMPRODUCT(SUMIFS('For Tally'!C:C, 'For Tally'!H:H, $A19, 'For Tally'!A:A, ">=2026-02-01", 'For Tally'!A:A, "<=2026-02-28", 'For Tally'!L:L, $B$5:$F$5)) -> 29593.2 | M19: =SUMPRODUCT(SUMIFS('For Tally'!C:C, 'For Tally'!H:H, $A19, 'For Tally'!A:A, ">=2026-03-01", 'For Tally'!A:A, "<=2026-03-31", 'For Tally'!L:L, $B$5:$F$5)) -> 35966.26 | N19: =SUMPRODUCT(SUMIFS('For Tally'!C:C, 'For Tally'!H:H, $A19, 'For Tally'!A:A, ">=2026-04-01", 'For Tally'!A:A, "<=2026-04-30", 'For Tally'!L:L, $B$5:$F$5)) -> 0 | O19: =SUM(B19:N19) -> 727610.49
... A40: Zerodha Broking Limited | B40: =SUMPRODUCT(SUMIFS('For Tally'!C:C, 'For Tally'!H:H, $A40, 'For Tally'!A:A, ">=2025-04-01", 'For Tally'!A:A, "<=2025-04-30", 'For Tally'!L:L, $B$5:$F$5)) -> 0 | C40: =SUMPRODUCT(SUMIFS('For Tally'!C:C, 'For Tally'!H:H, $A40, 'For Tally'!A:A, ">=2025-05-01", 'For Tally'!A:A, "<=2025-05-31", 'For Tally'!L:L, $B$5:$F$5)) -> 40000 | D40: =SUMPRODUCT(SUMIFS('For Tally'!C:C, 'For Tally'!H:H, $A40, 'For Tally'!A:A, ">=2025-06-01", 'For Tally'!A:A, "<=2025-06-30", 'For Tally'!L:L, $B$5:$F$5)) -> 0 | E40: =SUMPRODUCT(SUMIFS('For Tally'!C:C, 'For Tally'!H:H, $A40, 'For Tally'!A:A, ">=2025-07-01", 'For Tally'!A:A, "<=2025-07-31", 'For Tally'!L:L, $B$5:$F$5)) -> 50000 | F40: =SUMPRODUCT(SUMIFS('For Tally'!C:C, 'For Tally'!H:H, $A40, 'For Tally'!A:A, ">=2025-08-01", 'For Tally'!A:A, "<=2025-08-31", 'For Tally'!L:L, $B$5:$F$5)) -> 47000 | G40: =SUMPRODUCT(SUMIFS('For Tally'!C:C, 'For Tally'!H:H, $A40, 'For Tally'!A:A, ">=2025-09-01", 'For Tally'!A:A, "<=2025-09-30", 'For Tally'!L:L, $B$5:$F$5)) -> 15000 | H40: =SUMPRODUCT(SUMIFS('For Tally'!C:C, 'For Tally'!H:H, $A40, 'For Tally'!A:A, ">=2025-10-01", 'For Tally'!A:A, "<=2025-10-31", 'For Tally'!L:L, $B$5:$F$5)) -> 0 | I40: =SUMPRODUCT(SUMIFS('For Tally'!C:C, 'For Tally'!H:H, $A40, 'For Tally'!A:A, ">=2025-11-01", 'For Tally'!A:A, "<=2025-11-30", 'For Tally'!L:L, $B$5:$F$5)) -> 0 | J40: =SUMPRODUCT(SUMIFS('For Tally'!C:C, 'For Tally'!H:H, $A40, 'For Tally'!A:A, ">=2025-12-01", 'For Tally'!A:A, "<=2025-12-31", 'For Tally'!L:L, $B$5:$F$5)) -> 0 | K40: =SUMPRODUCT(SUMIFS('For Tally'!C:C, 'For Tally'!H:H, $A40, 'For Tally'!A:A, ">=2026-01-01", 'For Tally'!A:A, "<=2026-01-31", 'For Tally'!L:L, $B$5:$F$5)) -> 23000 | L40: =SUMPRODUCT(SUMIFS('For Tally'!C:C, 'For Tally'!H:H, $A40, 'For Tally'!A:A, ">=2026-02-01", 'For Tally'!A:A, "<=2026-02-28", 'For Tally'!L:L, $B$5:$F$5)) -> 0 | M40: =SUMPRODUCT(SUMIFS('For Tally'!C:C, 'For Tally'!H:H, $A40, 'For Tally'!A:A, ">=2026-03-01", 'For Tally'!A:A, "<=2026-03-31", 'For Tally'!L:L, $B$5:$F$5)) -> 33000 | N40: =SUMPRODUCT(SUMIFS('For Tally'!C:C, 'For Tally'!H:H, $A40, 'For Tally'!A:A, ">=2026-04-01", 'For Tally'!A:A, "<=2026-04-30", 'For Tally'!L:L, $B$5:$F$5)) -> 0 | O40: =SUM(B40:N40) -> 208000
A41: MONTHLY TOTAL | B41: =SUM(B8:B40) -> 267138.9 | C41: =SUM(C8:C40) -> 425709.94 | D41: =SUM(D8:D40) -> 210901.48 | E41: =SUM(E8:E40) -> 402673.44 | F41: =SUM(F8:F40) -> 308808.93 | G41: =SUM(G8:G40) -> 497611.73 | H41: =SUM(H8:H40) -> 775044.2 | I41: =SUM(I8:I40) -> 170473.52 | ... O41: =SUM(O8:O40) -> 4117216.7
A43: RECEIPTS / CREDITS | B43: Apr-2025 | C43: May-2025 | D43: Jun-2025 | E43: Jul-2025 | F43: Aug-2025 | G43: Sep-2025 | H43: Oct-2025 | I43: Nov-2025 | J43: Dec-2025 | K43: Jan-2026 | L43: Feb-2026 | M43: Mar-2026 | N43: Apr-2026 | O43: TOTAL
A44: AXIS | B44: =SUMPRODUCT(SUMIFS('For Tally'!D:D, 'For Tally'!H:H, $A44, 'For Tally'!A:A, ">=2025-04-01", 'For Tally'!A:A, "<=2025-04-30", 'For Tally'!L:L, $B$5:$F$5)) -> 65002 | C44: =SUMPRODUCT(SUMIFS('For Tally'!D:D, 'For Tally'!H:H, $A44, 'For Tally'!A:A, ">=2025-05-01", 'For Tally'!A:A, "<=2025-05-31", 'For Tally'!L:L, $B$5:$F$5)) -> 72002 | D44: =SUMPRODUCT(SUMIFS('For Tally'!D:D, 'For Tally'!H:H, $A44, 'For Tally'!A:A, ">=2025-06-01", 'For Tally'!A:A, "<=2025-06-30", 'For Tally'!L:L, $B$5:$F$5)) -> 60000 | E44: =SUMPRODUCT(SUMIFS('For Tally'!D:D, 'For Tally'!H:H, $A44, 'For Tally'!A:A, ">=2025-07-01", 'For Tally'!A:A, "<=2025-07-31", 'For Tally'!L:L, $B$5:$F$5)) -> 22000 | F44: =SUMPRODUCT(SUMIFS('For Tally'!D:D, 'For Tally'!H:H, $A44, 'For Tally'!A:A, ">=2025-08-01", 'For Tally'!A:A, "<=2025-08-31", 'For Tally'!L:L, $B$5:$F$5)) -> 54000 | G44: =SUMPRODUCT(SUMIFS('For Tally'!D:D, 'For Tally'!H:H, $A44, 'For Tally'!A:A, ">=2025-09-01", 'For Tally'!A:A, "<=2025-09-30", 'For Tally'!L:L, $B$5:$F$5)) -> 65000 | H44: =SUMPRODUCT(SUMIFS('For Tally'!D:D, 'For Tally'!H:H, $A44, 'For Tally'!A:A, ">=2025-10-01", 'For Tally'!A:A, "<=2025-10-31", 'For Tally'!L:L, $B$5:$F$5)) -> 0 | I44: =SUMPRODUCT(SUMIFS('For Tally'!D:D, 'For Tally'!H:H, $A44, 'For Tally'!A:A, ">=2025-11-01", 'For Tally'!A:A, "<=2025-11-30", 'For Tally'!L:L, $B$5:$F$5)) -> 20000 | J44: =SUMPRODUCT(SUMIFS('For Tally'!D:D, 'For Tally'!H:H, $A44, 'For Tally'!A:A, ">=2025-12-01", 'For Tally'!A:A, "<=2025-12-31", 'For Tally'!L:L, $B$5:$F$5)) -> 8000 | K44: =SUMPRODUCT(SUMIFS('For Tally'!D:D, 'For Tally'!H:H, $A44, 'For Tally'!A:A, ">=2026-01-01", 'For Tally'!A:A, "<=2026-01-31", 'For Tally'!L:L, $B$5:$F$5)) -> 52194 | L44: =SUMPRODUCT(SUMIFS('For Tally'!D:D, 'For Tally'!H:H, $A44, 'For Tally'!A:A, ">=2026-02-01", 'For Tally'!A:A, "<=2026-02-28", 'For Tally'!L:L, $B$5:$F$5)) -> 15638.97 | M44: =SUMPRODUCT(SUMIFS('For Tally'!D:D, 'For Tally'!H:H, $A44, 'For Tally'!A:A, ">=2026-03-01", 'For Tally'!A:A, "<=2026-03-31", 'For Tally'!L:L, $B$5:$F$5)) -> 15000 | N44: =SUMPRODUCT(SUMIFS('For Tally'!D:D, 'For Tally'!H:H, $A44, 'For Tally'!A:A, ">=2026-04-01", 'For Tally'!A:A, "<=2026-04-30", 'For Tally'!L:L, $B$5:$F$5)) -> 0 | O44: =SUM(B44:N44) -> 448836.97
A45: Ajay Gupta | B45: =SUMPRODUCT(SUMIFS('For Tally'!D:D, 'For Tally'!H:H, $A45, 'For Tally'!A:A, ">=2025-04-01", 'For Tally'!A:A, "<=2025-04-30", 'For Tally'!L:L, $B$5:$F$5)) -> 0 | C45: =SUMPRODUCT(SUMIFS('For Tally'!D:D, 'For Tally'!H:H, $A45, 'For Tally'!A:A, ">=2025-05-01", 'For Tally'!A:A, "<=2025-05-31", 'For Tally'!L:L, $B$5:$F$5)) -> 100000 | D45: =SUMPRODUCT(SUMIFS('For Tally'!D:D, 'For Tally'!H:H, $A45, 'For Tally'!A:A, ">=2025-06-01", 'For Tally'!A:A, "<=2025-06-30", 'For Tally'!L:L, $B$5:$F$5)) -> 0 | E45: =SUMPRODUCT(SUMIFS('For Tally'!D:D, 'For Tally'!H:H, $A45, 'For Tally'!A:A, ">=2025-07-01", 'For Tally'!A:A, "<=2025-07-31", 'For Tally'!L:L, $B$5:$F$5)) -> 0 | F45: =SUMPRODUCT(SUMIFS('For Tally'!D:D, 'For Tally'!H:H, $A45, 'For Tally'!A:A, ">=2025-08-01", 'For Tally'!A:A, "<=2025-08-31", 'For Tally'!L:L, $B$5:$F$5)) -> 0 | G45: =SUMPRODUCT(SUMIFS('For Tally'!D:D, 'For Tally'!H:H, $A45, 'For Tally'!A:A, ">=2025-09-01", 'For Tally'!A:A, "<=2025-09-30", 'For Tally'!L:L, $B$5:$F$5)) -> 68000 | H45: =SUMPRODUCT(SUMIFS('For Tally'!D:D, 'For Tally'!H:H, $A45, 'For Tally'!A:A, ">=2025-10-01", 'For Tally'!A:A, "<=2025-10-31", 'For Tally'!L:L, $B$5:$F$5)) -> 140000 | I45: =SUMPRODUCT(SUMIFS('For Tally'!D:D, 'For Tally'!H:H, $A45, 'For Tally'!A:A, ">=2025-11-01", 'For Tally'!A:A, "<=2025-11-30", 'For Tally'!L:L, $B$5:$F$5)) -> 0 | J45: =SUMPRODUCT(SUMIFS('For Tally'!D:D, 'For Tally'!H:H, $A45, 'For Tally'!A:A, ">=2025-12-01", 'For Tally'!A:A, "<=2025-12-31", 'For Tally'!L:L, $B$5:$F$5)) -> 0 | K45: =SUMPRODUCT(SUMIFS('For Tally'!D:D, 'For Tally'!H:H, $A45, 'For Tally'!A:A, ">=2026-01-01", 'For Tally'!A:A, "<=2026-01-31", 'For Tally'!L:L, $B$5:$F$5)) -> 0 | L45: =SUMPRODUCT(SUMIFS('For Tally'!D:D, 'For Tally'!H:H, $A45, 'For Tally'!A:A, ">=2026-02-01", 'For Tally'!A:A, "<=2026-02-28", 'For Tally'!L:L, $B$5:$F$5)) -> 0 | M45: =SUMPRODUCT(SUMIFS('For Tally'!D:D, 'For Tally'!H:H, $A45, 'For Tally'!A:A, ">=2026-03-01", 'For Tally'!A:A, "<=2026-03-31", 'For Tally'!L:L, $B$5:$F$5)) -> 85000 | N45: =SUMPRODUCT(SUMIFS('For Tally'!D:D, 'For Tally'!H:H, $A45, 'For Tally'!A:A, ">=2026-04-01", 'For Tally'!A:A, "<=2026-04-30", 'For Tally'!L:L, $B$5:$F$5)) -> 0 | O45: =SUM(B45:N45) -> 393000
A46: Annuity | B46: =SUMPRODUCT(SUMIFS('For Tally'!D:D, 'For Tally'!H:H, $A46, 'For Tally'!A:A, ">=2025-04-01", 'For Tally'!A:A, "<=2025-04-30", 'For Tally'!L:L, $B$5:$F$5)) -> 1880 | C46: =SUMPRODUCT(SUMIFS('For Tally'!D:D, 'For Tally'!H:H, $A46, 'For Tally'!A:A, ">=2025-05-01", 'For Tally'!A:A, "<=2025-05-31", 'For Tally'!L:L, $B$5:$F$5)) -> 1880 | D46: =SUMPRODUCT(SUMIFS('For Tally'!D:D, 'For Tally'!H:H, $A46, 'For Tally'!A:A, ">=2025-06-01", 'For Tally'!A:A, "<=2025-06-30", 'For Tally'!L:L, $B$5:$F$5)) -> 1880 | E46: =SUMPRODUCT(SUMIFS('For Tally'!D:D, 'For Tally'!H:H, $A46, 'For Tally'!A:A, ">=2025-07-01", 'For Tally'!A:A, "<=2025-07-31", 'For Tally'!L:L, $B$5:$F$5)) -> 1880 | F46: =SUMPRODUCT(SUMIFS('For Tally'!D:D, 'For Tally'!H:H, $A46, 'For Tally'!A:A, ">=2025-08-01", 'For Tally'!A:A, "<=2025-08-31", 'For Tally'!L:L, $B$5:$F$5)) -> 1880 | G46: =SUMPRODUCT(SUMIFS('For Tally'!D:D, 'For Tally'!H:H, $A46, 'For Tally'!A:A, ">=2025-09-01", 'For Tally'!A:A, "<=2025-09-30", 'For Tally'!L:L, $B$5:$F$5)) -> 1880 | H46: =SUMPRODUCT(SUMIFS('For Tally'!D:D, 'For Tally'!H:H, $A46, 'For Tally'!A:A, ">=2025-10-01", 'For Tally'!A:A, "<=2025-10-31", 'For Tally'!L:L, $B$5:$F$5)) -> 1880 | I46: =SUMPRODUCT(SUMIFS('For Tally'!D:D, 'For Tally'!H:H, $A46, 'For Tally'!A:A, ">=2025-11-01", 'For Tally'!A:A, "<=2025-11-30", 'For Tally'!L:L, $B$5:$F$5)) -> 1880 | J46: =SUMPRODUCT(SUMIFS('For Tally'!D:D, 'For Tally'!H:H, $A46, 'For Tally'!A:A, ">=2025-12-01", 'For Tally'!A:A, "<=2025-12-31", 'For Tally'!L:L, $B$5:$F$5)) -> 1880 | K46: =SUMPRODUCT(SUMIFS('For Tally'!D:D, 'For Tally'!H:H, $A46, 'For Tally'!A:A, ">=2026-01-01", 'For Tally'!A:A, "<=2026-01-31", 'For Tally'!L:L, $B$5:$F$5)) -> 1880 | L46: =SUMPRODUCT(SUMIFS('For Tally'!D:D, 'For Tally'!H:H, $A46, 'For Tally'!A:A, ">=2026-02-01", 'For Tally'!A:A, "<=2026-02-28", 'For Tally'!L:L, $B$5:$F$5)) -> 1880 | M46: =SUMPRODUCT(SUMIFS('For Tally'!D:D, 'For Tally'!H:H, $A46, 'For Tally'!A:A, ">=2026-03-01", 'For Tally'!A:A, "<=2026-03-31", 'For Tally'!L:L, $B$5:$F$5)) -> 1880 | N46: =SUMPRODUCT(SUMIFS('For Tally'!D:D, 'For Tally'!H:H, $A46, 'For Tally'!A:A, ">=2026-04-01", 'For Tally'!A:A, "<=2026-04-30", 'For Tally'!L:L, $B$5:$F$5)) -> 0 | O46: =SUM(B46:N46) -> 22560
A47: Archit Gupta | B47: =SUMPRODUCT(SUMIFS('For Tally'!D:D, 'For Tally'!H:H, $A47, 'For Tally'!A:A, ">=2025-04-01", 'For Tally'!A:A, "<=2025-04-30", 'For Tally'!L:L, $B$5:$F$5)) -> 0 | C47: =SUMPRODUCT(SUMIFS('For Tally'!D:D, 'For Tally'!H:H, $A47, 'For Tally'!A:A, ">=2025-05-01", 'For Tally'!A:A, "<=2025-05-31", 'For Tally'!L:L, $B$5:$F$5)) -> 0 | D47: =SUMPRODUCT(SUMIFS('For Tally'!D:D, 'For Tally'!H:H, $A47, 'For Tally'!A:A, ">=2025-06-01", 'For Tally'!A:A, "<=2025-06-30", 'For Tally'!L:L, $B$5:$F$5)) -> 10000 | E47: =SUMPRODUCT(SUMIFS('For Tally'!D:D, 'For Tally'!H:H, $A47, 'For Tally'!A:A, ">=2025-07-01", 'For Tally'!A:A, "<=2025-07-31", 'For Tally'!L:L, $B$5:$F$5)) -> 0 | F47: =SUMPRODUCT(SUMIFS('For Tally'!D:D, 'For Tally'!H:H, $A47, 'For Tally'!A:A, ">=2025-08-01", 'For Tally'!A:A, "<=2025-08-31", 'For Tally'!L:L, $B$5:$F$5)) -> 0 | G47: =SUMPRODUCT(SUMIFS('For Tally'!D:D, 'For Tally'!H:H, $A47, 'For Tally'!A:A, ">=2025-09-01", 'For Tally'!A:A, "<=2025-09-30", 'For Tally'!L:L, $B$5:$F$5)) -> 10 | H47: =SUMPRODUCT(SUMIFS('For Tally'!D:D, 'For Tally'!H:H, $A47, 'For Tally'!A:A, ">=2025-10-01", 'For Tally'!A:A, "<=2025-10-31", 'For Tally'!L:L, $B$5:$F$5)) -> 0 | I47: =SUMPRODUCT(SUMIFS('For Tally'!D:D, 'For Tally'!H:H, $A47, 'For Tally'!A:A, ">=2025-11-01", 'For Tally'!A:A, "<=2025-11-30", 'For Tally'!L:L, $B$5:$F$5)) -> 0 | J47: =SUMPRODUCT(SUMIFS('For Tally'!D:D, 'For Tally'!H:H, $A47, 'For Tally'!A:A, ">=2025-12-01", 'For Tally'!A:A, "<=2025-12-31", 'For Tally'!L:L, $B$5:$F$5)) -> 10000 | K47: =SUMPRODUCT(SUMIFS('For Tally'!D:D, 'For Tally'!H:H, $A47, 'For Tally'!A:A, ">=2026-01-01", 'For Tally'!A:A, "<=2026-01-31", 'For Tally'!L:L, $B$5:$F$5)) -> 0 | L47: =SUMPRODUCT(SUMIFS('For Tally'!D:D, 'For Tally'!H:H, $A47, 'For Tally'!A:A, ">=2026-02-01", 'For Tally'!A:A, "<=2026-02-28", 'For Tally'!L:L, $B$5:$F$5)) -> 101 | M47: =SUMPRODUCT(SUMIFS('For Tally'!D:D, 'For Tally'!H:H, $A47, 'For Tally'!A:A, ">=2026-03-01", 'For Tally'!A:A, "<=2026-03-31", 'For Tally'!L:L, $B$5:$F$5)) -> 0 | N47: =SUMPRODUCT(SUMIFS('For Tally'!D:D, 'For Tally'!H:H, $A47, 'For Tally'!A:A, ">=2026-04-01", 'For Tally'!A:A, "<=2026-04-30", 'For Tally'!L:L, $B$5:$F$5)) -> 0 | O47: =SUM(B47:N47) -> 20111
A48: Bank Interest | B48: =SUMPRODUCT(SUMIFS('For Tally'!D:D, 'For Tally'!H:H, $A48, 'For Tally'!A:A, ">=2025-04-01", 'For Tally'!A:A, "<=2025-04-30", 'For Tally'!L:L, $B$5:$F$5)) -> 0 | C48: =SUMPRODUCT(SUMIFS('For Tally'!D:D, 'For Tally'!H:H, $A48, 'For Tally'!A:A, ">=2025-05-01", 'For Tally'!A:A, "<=2025-05-31", 'For Tally'!L:L, $B$5:$F$5)) -> 1 | D48: =SUMPRODUCT(SUMIFS('For Tally'!D:D, 'For Tally'!H:H, $A48, 'For Tally'!A:A, ">=2025-06-01", 'For Tally'!A:A, "<=2025-06-30", 'For Tally'!L:L, $B$5:$F$5)) -> 82 | E48: =SUMPRODUCT(SUMIFS('For Tally'!D:D, 'For Tally'!H:H, $A48, 'For Tally'!A:A, ">=2025-07-01", 'For Tally'!A:A, "<=2025-07-31", 'For Tally'!L:L, $B$5:$F$5)) -> 1014 | F48: =SUMPRODUCT(SUMIFS('For Tally'!D:D, 'For Tally'!H:H, $A48, 'For Tally'!A:A, ">=2025-08-01", 'For Tally'!A:A, "<=2025-08-31", 'For Tally'!L:L, $B$5:$F$5)) -> 1 | G48: =SUMPRODUCT(SUMIFS('For Tally'!D:D, 'For Tally'!H:H, $A48, 'For Tally'!A:A, ">=2025-09-01", 'For Tally'!A:A, "<=2025-09-30", 'For Tally'!L:L, $B$5:$F$5)) -> 135 | H48: =SUMPRODUCT(SUMIFS('For Tally'!D:D, 'For Tally'!H:H, $A48, 'For Tally'!A:A, ">=2025-10-01", 'For Tally'!A:A, "<=2025-10-31", 'For Tally'!L:L, $B$5:$F$5)) -> 802 | I48: =SUMPRODUCT(SUMIFS('For Tally'!D:D, 'For Tally'!H:H, $A48, 'For Tally'!A:A, ">=2025-11-01", 'For Tally'!A:A, "<=2025-11-30", 'For Tally'!L:L, $B$5:$F$5)) -> 0 | J48: =SUMPRODUCT(SUMIFS('For Tally'!D:D, 'For Tally'!H:H, $A48, 'For Tally'!A:A, ">=2025-12-01", 'For Tally'!A:A, "<=2025-12-31", 'For Tally'!L:L, $B$5:$F$5)) -> 60 | K48: =SUMPRODUCT(SUMIFS('For Tally'!D:D, 'For Tally'!H:H, $A48, 'For Tally'!A:A, ">=2026-01-01", 'For Tally'!A:A, "<=2026-01-31", 'For Tally'!L:L, $B$5:$F$5)) -> 729 | L48: =SUMPRODUCT(SUMIFS('For Tally'!D:D, 'For Tally'!H:H, $A48, 'For Tally'!A:A, ">=2026-02-01", 'For Tally'!A:A, "<=2026-02-28", 'For Tally'!L:L, $B$5:$F$5)) -> 0 | M48: =SUMPRODUCT(SUMIFS('For Tally'!D:D, 'For Tally'!H:H, $A48, 'For Tally'!A:A, ">=2026-03-01", 'For Tally'!A:A, "<=2026-03-31", 'For Tally'!L:L, $B$5:$F$5)) -> 339 | N48: =SUMPRODUCT(SUMIFS('For Tally'!D:D, 'For Tally'!H:H, $A48, 'For Tally'!A:A, ">=2026-04-01", 'For Tally'!A:A, "<=2026-04-30", 'For Tally'!L:L, $B$5:$F$5)) -> 227 | O48: =SUM(B48:N48) -> 3390
A49: CDSL | B49: =SUMPRODUCT(SUMIFS('For Tally'!D:D, 'For Tally'!H:H, $A49, 'For Tally'!A:A, ">=2025-04-01", 'For Tally'!A:A, "<=2025-04-30", 'For Tally'!L:L, $B$5:$F$5)) -> 0 | C49: =SUMPRODUCT(SUMIFS('For Tally'!D:D, 'For Tally'!H:H, $A49, 'For Tally'!A:A, ">=2025-05-01", 'For Tally'!A:A, "<=2025-05-31", 'For Tally'!L:L, $B$5:$F$5)) -> 0 | D49: =SUMPRODUCT(SUMIFS('For Tally'!D:D, 'For Tally'!H:H, $A49, 'For Tally'!A:A, ">=2025-06-01", 'For Tally'!A:A, "<=2025-06-30", 'For Tally'!L:L, $B$5:$F$5)) -> 122.22 | E49: =SUMPRODUCT(SUMIFS('For Tally'!D:D, 'For Tally'!H:H, $A49, 'For Tally'!A:A, ">=2025-07-01", 'For Tally'!A:A, "<=2025-07-31", 'For Tally'!L:L, $B$5:$F$5)) -> 0 | F49: =SUMPRODUCT(SUMIFS('For Tally'!D:D, 'For Tally'!H:H, $A49, 'For Tally'!A:A, ">=2025-08-01", 'For Tally'!A:A, "<=2025-08-31", 'For Tally'!L:L, $B$5:$F$5)) -> 0 | G49: =SUMPRODUCT(SUMIFS('For Tally'!D:D, 'For Tally'!H:H, $A49, 'For Tally'!A:A, ">=2025-09-01", 'For Tally'!A:A, "<=2025-09-30", 'For Tally'!L:L, $B$5:$F$5)) -> 0 | H49: =SUMPRODUCT(SUMIFS('For Tally'!D:D, 'For Tally'!H:H, $A49, 'For Tally'!A:A, ">=2025-10-01", 'For Tally'!A:A, "<=2025-10-31", 'For Tally'!L:L, $B$5:$F$5)) -> 0 | I49: =SUMPRODUCT(SUMIFS('For Tally'!D:D, 'For Tally'!H:H, $A49, 'For Tally'!A:A, ">=2025-11-01", 'For Tally'!A:A, "<=2025-11-30", 'For Tally'!L:L, $B$5:$F$5)) -> 0 | J49: =SUMPRODUCT(SUMIFS('For Tally'!D:D, 'For Tally'!H:H, $A49, 'For Tally'!A:A, ">=2025-12-01", 'For Tally'!A:A, "<=2025-12-31", 'For Tally'!L:L, $B$5:$F$5)) -> 122.22 | K49: =SUMPRODUCT(SUMIFS('For Tally'!D:D, 'For Tally'!H:H, $A49, 'For Tally'!A:A, ">=2026-01-01", 'For Tally'!A:A, "<=2026-01-31", 'For Tally'!L:L, $B$5:$F$5)) -> 0 | L49: =SUMPRODUCT(SUMIFS('For Tally'!D:D, 'For Tally'!H:H, $A49, 'For Tally'!A:A, ">=2026-02-01", 'For Tally'!A:A, "<=2026-02-28", 'For Tally'!L:L, $B$5:$F$5)) -> 0 | M49: =SUMPRODUCT(SUMIFS('For Tally'!D:D, 'For Tally'!H:H, $A49, 'For Tally'!A:A, ">=2026-03-01", 'For Tally'!A:A, "<=2026-03-31", 'For Tally'!L:L, $B$5:$F$5)) -> 0 | N49: =SUMPRODUCT(SUMIFS('For Tally'!D:D, 'For Tally'!H:H, $A49, 'For Tally'!A:A, ">=2026-04-01", 'For Tally'!A:A, "<=2026-04-30", 'For Tally'!L:L, $B$5:$F$5)) -> 0 | O49: =SUM(B49:N49) -> 244.44
A50: Dividend Income | B50: =SUMPRODUCT(SUMIFS('For Tally'!D:D, 'For Tally'!H:H, $A50, 'For Tally'!A:A, ">=2025-04-01", 'For Tally'!A:A, "<=2025-04-30", 'For Tally'!L:L, $B$5:$F$5)) -> 0 | C50: =SUMPRODUCT(SUMIFS('For Tally'!D:D, 'For Tally'!H:H, $A50, 'For Tally'!A:A, ">=2025-05-01", 'For Tally'!A:A, "<=2025-05-31", 'For Tally'!L:L, $B$5:$F$5)) -> 2965.5 | D50: =SUMPRODUCT(SUMIFS('For Tally'!D:D, 'For Tally'!H:H, $A50, 'For Tally'!A:A, ">=2025-06-01", 'For Tally'!A:A, "<=2025-06-30", 'For Tally'!L:L, $B$5:$F$5)) -> 1665 | E50: =SUMPRODUCT(SUMIFS('For Tally'!D:D, 'For Tally'!H:H, $A50, 'For Tally'!A:A, ">=2025-07-01", 'For Tally'!A:A, "<=2025-07-31", 'For Tally'!L:L, $B$5:$F$5)) -> 3588 | F50: =SUMPRODUCT(SUMIFS('For Tally'!D:D, 'For Tally'!H:H, $A50, 'For Tally'!A:A, ">=2025-08-01", 'For Tally'!A:A, "<=2025-08-31", 'For Tally'!L:L, $B$5:$F$5)) -> 11816 | G50: =SUMPRODUCT(SUMIFS('For Tally'!D:D, 'For Tally'!H:H, $A50, 'For Tally'!A:A, ">=2025-09-01", 'For Tally'!A:A, "<=2025-09-30", 'For Tally'!L:L, $B$5:$F$5)) -> 1724 | H50: =SUMPRODUCT(SUMIFS('For Tally'!D:D, 'For Tally'!H:H, $A50, 'For Tally'!A:A, ">=2025-10-01", 'For Tally'!A:A, "<=2025-10-31", 'For Tally'!L:L, $B$5:$F$5)) -> 775.5 | I50: =SUMPRODUCT(SUMIFS('For Tally'!D:D, 'For Tally'!H:H, $A50, 'For Tally'!A:A, ">=2025-11-01", 'For Tally'!A:A, "<=2025-11-30", 'For Tally'!L:L, $B$5:$F$5)) -> 2139 | J50: =SUMPRODUCT(SUMIFS('For Tally'!D:D, 'For Tally'!H:H, $A50, 'For Tally'!A:A, ">=2025-12-01", 'For Tally'!A:A, "<=2025-12-31", 'For Tally'!L:L, $B$5:$F$5)) -> 700 | K50: =SUMPRODUCT(SUMIFS('For Tally'!D:D, 'For Tally'!H:H, $A50, 'For Tally'!A:A, ">=2026-01-01", 'For Tally'!A:A, "<=2026-01-31", 'For Tally'!L:L, $B$5:$F$5)) -> 0 | L50: =SUMPRODUCT(SUMIFS('For Tally'!D:D, 'For Tally'!H:H, $A50, 'For Tally'!A:A, ">=2026-02-01", 'For Tally'!A:A, "<=2026-02-28", 'For Tally'!L:L, $B$5:$F$5)) -> 3855.75 | M50: =SUMPRODUCT(SUMIFS('For Tally'!D:D, 'For Tally'!H:H, $A50, 'For Tally'!A:A, ">=2026-03-01", 'For Tally'!A:A, "<=2026-03-31", 'For Tally'!L:L, $B$5:$F$5)) -> 0 | N50: =SUMPRODUCT(SUMIFS('For Tally'!D:D, 'For Tally'!H:H, $A50, 'For Tally'!A:A, ">=2026-04-01", 'For Tally'!A:A, "<=2026-04-30", 'For Tally'!L:L, $B$5:$F$5)) -> 0 | O50: =SUM(B50:N50) -> 29228.75
A51: HDFC 5413 | B51: =SUMPRODUCT(SUMIFS('For Tally'!D:D, 'For Tally'!H:H, $A51, 'For Tally'!A:A, ">=2025-04-01", 'For Tally'!A:A, "<=2025-04-30", 'For Tally'!L:L, $B$5:$F$5)) -> 0 | C51: =SUMPRODUCT(SUMIFS('For Tally'!D:D, 'For Tally'!H:H, $A51, 'For Tally'!A:A, ">=2025-05-01", 'For Tally'!A:A, "<=2025-05-31", 'For Tally'!L:L, $B$5:$F$5)) -> 0 | D51: =SUMPRODUCT(SUMIFS('For Tally'!D:D, 'For Tally'!H:H, $A51, 'For Tally'!A:A, ">=2025-06-01", 'For Tally'!A:A, "<=2025-06-30", 'For Tally'!L:L, $B$5:$F$5)) -> 0 | E51: =SUMPRODUCT(SUMIFS('For Tally'!D:D, 'For Tally'!H:H, $A51, 'For Tally'!A:A, ">=2025-07-01", 'For Tally'!A:A, "<=2025-07-31", 'For Tally'!L:L, $B$5:$F$5)) -> 0 | F51: =SUMPRODUCT(SUMIFS('For Tally'!D:D, 'For Tally'!H:H, $A51, 'For Tally'!A:A, ">=2025-08-01", 'For Tally'!A:A, "<=2025-08-31", 'For Tally'!L:L, $B$5:$F$5)) -> 0 | G51: =SUMPRODUCT(SUMIFS('For Tally'!D:D, 'For Tally'!H:H, $A51, 'For Tally'!A:A, ">=2025-09-01", 'For Tally'!A:A, "<=2025-09-30", 'For Tally'!L:L, $B$5:$F$5)) -> 0 | H51: =SUMPRODUCT(SUMIFS('For Tally'!D:D, 'For Tally'!H:H, $A51, 'For Tally'!A:A, ">=2025-10-01", 'For Tally'!A:A, "<=2025-10-31", 'For Tally'!L:L, $B$5:$F$5)) -> 0 | I51: =SUMPRODUCT(SUMIFS('For Tally'!D:D, 'For Tally'!H:H, $A51, 'For Tally'!A:A, ">=2025-11-01", 'For Tally'!A:A, "<=2025-11-30", 'For Tally'!L:L, $B$5:$F$5)) -> 0 | J51: =SUMPRODUCT(SUMIFS('For Tally'!D:D, 'For Tally'!H:H, $A51, 'For Tally'!A:A, ">=2025-12-01", 'For Tally'!A:A, "<=2025-12-31", 'For Tally'!L:L, $B$5:$F$5)) -> 0 | K51: =SUMPRODUCT(SUMIFS('For Tally'!D:D, 'For Tally'!H:H, $A51, 'For Tally'!A:A, ">=2026-01-01", 'For Tally'!A:A, "<=2026-01-31", 'For Tally'!L:L, $B$5:$F$5)) -> 50000 | L51: =SUMPRODUCT(SUMIFS('For Tally'!D:D, 'For Tally'!H:H, $A51, 'For Tally'!A:A, ">=2026-02-01", 'For Tally'!A:A, "<=2026-02-28", 'For Tally'!L:L, $B$5:$F$5)) -> 0 | M51: =SUMPRODUCT(SUMIFS('For Tally'!D:D, 'For Tally'!H:H, $A51, 'For Tally'!A:A, ">=2026-03-01", 'For Tally'!A:A, "<=2026-03-31", 'For Tally'!L:L, $B$5:$F$5)) -> 0 | N51: =SUMPRODUCT(SUMIFS('For Tally'!D:D, 'For Tally'!H:H, $A51, 'For Tally'!A:A, ">=2026-04-01", 'For Tally'!A:A, "<=2026-04-30", 'For Tally'!L:L, $B$5:$F$5)) -> 0 | O51: =SUM(B51:N51) -> 50000
A52: HDFC Securities | B52: =SUMPRODUCT(SUMIFS('For Tally'!D:D, 'For Tally'!H:H, $A52, 'For Tally'!A:A, ">=2025-04-01", 'For Tally'!A:A, "<=2025-04-30", 'For Tally'!L:L, $B$5:$F$5)) -> 87932.74 | C52: =SUMPRODUCT(SUMIFS('For Tally'!D:D, 'For Tally'!H:H, $A52, 'For Tally'!A:A, ">=2025-05-01", 'For Tally'!A:A, "<=2025-05-31", 'For Tally'!L:L, $B$5:$F$5)) -> 82757.23 | D52: =SUMPRODUCT(SUMIFS('For Tally'!D:D, 'For Tally'!H:H, $A52, 'For Tally'!A:A, ">=2025-06-01", 'For Tally'!A:A, "<=2025-06-30", 'For Tally'!L:L, $B$5:$F$5)) -> 37520.35 | E52: =SUMPRODUCT(SUMIFS('For Tally'!D:D, 'For Tally'!H:H, $A52, 'For Tally'!A:A, ">=2025-07-01", 'For Tally'!A:A, "<=2025-07-31", 'For Tally'!L:L, $B$5:$F$5)) -> 159477.27 | F52: =SUMPRODUCT(SUMIFS('For Tally'!D:D, 'For Tally'!H:H, $A52, 'For Tally'!A:A, ">=2025-08-01", 'For Tally'!A:A, "<=2025-08-31", 'For Tally'!L:L, $B$5:$F$5)) -> 85938.31 | G52: =SUMPRODUCT(SUMIFS('For Tally'!D:D, 'For Tally'!H:H, $A52, 'For Tally'!A:A, ">=2025-09-01", 'For Tally'!A:A, "<=2025-09-30", 'For Tally'!L:L, $B$5:$F$5)) -> 192874.52 | H52: =SUMPRODUCT(SUMIFS('For Tally'!D:D, 'For Tally'!H:H, $A52, 'For Tally'!A:A, ">=2025-10-01", 'For Tally'!A:A, "<=2025-10-31", 'For Tally'!L:L, $B$5:$F$5)) -> 362397.17 | I52: =SUMPRODUCT(SUMIFS('For Tally'!D:D, 'For Tally'!H:H, $A52, 'For Tally'!A:A, ">=2025-11-01", 'For Tally'!A:A, "<=2025-11-30", 'For Tally'!L:L, $B$5:$F$5)) -> 74885.07 | J52: =SUMPRODUCT(SUMIFS('For Tally'!D:D, 'For Tally'!H:H, $A52, 'For Tally'!A:A, ">=2025-12-01", 'For Tally'!A:A, "<=2025-12-31", 'For Tally'!L:L, $B$5:$F$5)) -> 19456.5 | K52: =SUMPRODUCT(SUMIFS('For Tally'!D:D, 'For Tally'!H:H, $A52, 'For Tally'!A:A, ">=2026-01-01", 'For Tally'!A:A, "<=2026-01-31", 'For Tally'!L:L, $B$5:$F$5)) -> 45617.56 | L52: =SUMPRODUCT(SUMIFS('For Tally'!D:D, 'For Tally'!H:H, $A52, 'For Tally'!A:A, ">=2026-02-01", 'For Tally'!A:A, "<=2026-02-28", 'For Tally'!L:L, $B$5:$F$5)) -> 20104.85 | M52: =SUMPRODUCT(SUMIFS('For Tally'!D:D, 'For Tally'!H:H, $A52, 'For Tally'!A:A, ">=2026-03-01", 'For Tally'!A:A, "<=2026-03-31", 'For Tally'!L:L, $B$5:$F$5)) -> 35539.61 | N52: =SUMPRODUCT(SUMIFS('For Tally'!D:D, 'For Tally'!H:H, $A52, 'For Tally'!A:A, ">=2026-04-01", 'For Tally'!A:A, "<=2026-04-30", 'For Tally'!L:L, $B$5:$F$5)) -> 0 | O52: =SUM(B52:N52) -> 1204501.2
A53: Income Tax | B53: =SUMPRODUCT(SUMIFS('For Tally'!D:D, 'For Tally'!H:H, $A53, 'For Tally'!A:A, ">=2025-04-01", 'For Tally'!A:A, "<=2025-04-30", 'For Tally'!L:L, $B$5:$F$5)) -> 0 | C53: =SUMPRODUCT(SUMIFS('For Tally'!D:D, 'For Tally'!H:H, $A53, 'For Tally'!A:A, ">=2025-05-01", 'For Tally'!A:A, "<=2025-05-31", 'For Tally'!L:L, $B$5:$F$5)) -> 0 | D53: =SUMPRODUCT(SUMIFS('For Tally'!D:D, 'For Tally'!H:H, $A53, 'For Tally'!A:A, ">=2025-06-01", 'For Tally'!A:A, "<=2025-06-30", 'For Tally'!L:L, $B$5:$F$5)) -> 0 | E53: =SUMPRODUCT(SUMIFS('For Tally'!D:D, 'For Tally'!H:H, $A53, 'For Tally'!A:A, ">=2025-07-01", 'For Tally'!A:A, "<=2025-07-31", 'For Tally'!L:L, $B$5:$F$5)) -> 0 | F53: =SUMPRODUCT(SUMIFS('For Tally'!D:D, 'For Tally'!H:H, $A53, 'For Tally'!A:A, ">=2025-08-01", 'For Tally'!A:A, "<=2025-08-31", 'For Tally'!L:L, $B$5:$F$5)) -> 0 | G53: =SUMPRODUCT(SUMIFS('For Tally'!D:D, 'For Tally'!H:H, $A53, 'For Tally'!A:A, ">=2025-09-01", 'For Tally'!A:A, "<=2025-09-30", 'For Tally'!L:L, $B$5:$F$5)) -> 7220 | H53: =SUMPRODUCT(SUMIFS('For Tally'!D:D, 'For Tally'!H:H, $A53, 'For Tally'!A:A, ">=2025-10-01", 'For Tally'!A:A, "<=2025-10-31", 'For Tally'!L:L, $B$5:$F$5)) -> 0 | I53: =SUMPRODUCT(SUMIFS('For Tally'!D:D, 'For Tally'!H:H, $A53, 'For Tally'!A:A, ">=2025-11-01", 'For Tally'!A:A, "<=2025-11-30", 'For Tally'!L:L, $B$5:$F$5)) -> 0 | J53: =SUMPRODUCT(SUMIFS('For Tally'!D:D, 'For Tally'!H:H, $A53, 'For Tally'!A:A, ">=2025-12-01", 'For Tally'!A:A, "<=2025-12-31", 'For Tally'!L:L, $B$5:$F$5)) -> 0 | K53: =SUMPRODUCT(SUMIFS('For Tally'!D:D, 'For Tally'!H:H, $A53, 'For Tally'!A:A, ">=2026-01-01", 'For Tally'!A:A, "<=2026-01-31", 'For Tally'!L:L, $B$5:$F$5)) -> 0 | L53: =SUMPRODUCT(SUMIFS('For Tally'!D:D, 'For Tally'!H:H, $A53, 'For Tally'!A:A, ">=2026-02-01", 'For Tally'!A:A, "<=2026-02-28", 'For Tally'!L:L, $B$5:$F$5)) -> 0 | M53: =SUMPRODUCT(SUMIFS('For Tally'!D:D, 'For Tally'!H:H, $A53, 'For Tally'!A:A, ">=2026-03-01", 'For Tally'!A:A, "<=2026-03-31", 'For Tally'!L:L, $B$5:$F$5)) -> 0 | N53: =SUMPRODUCT(SUMIFS('For Tally'!D:D, 'For Tally'!H:H, $A53, 'For Tally'!A:A, ">=2026-04-01", 'For Tally'!A:A, "<=2026-04-30", 'For Tally'!L:L, $B$5:$F$5)) -> 0 | O53: =SUM(B53:N53) -> 7220
A54: KOTAK 0333 | B54: =SUMPRODUCT(SUMIFS('For Tally'!D:D, 'For Tally'!H:H, $A54, 'For Tally'!A:A, ">=2025-04-01", 'For Tally'!A:A, "<=2025-04-30", 'For Tally'!L:L, $B$5:$F$5)) -> 5000 | C54: =SUMPRODUCT(SUMIFS('For Tally'!D:D, 'For Tally'!H:H, $A54, 'For Tally'!A:A, ">=2025-05-01", 'For Tally'!A:A, "<=2025-05-31", 'For Tally'!L:L, $B$5:$F$5)) -> 0 | D54: =SUMPRODUCT(SUMIFS('For Tally'!D:D, 'For Tally'!H:H, $A54, 'For Tally'!A:A, ">=2025-06-01", 'For Tally'!A:A, "<=2025-06-30", 'For Tally'!L:L, $B$5:$F$5)) -> 0 | E54: =SUMPRODUCT(SUMIFS('For Tally'!D:D, 'For Tally'!H:H, $A54, 'For Tally'!A:A, ">=2025-07-01", 'For Tally'!A:A, "<=2025-07-31", 'For Tally'!L:L, $B$5:$F$5)) -> 0 | F54: =SUMPRODUCT(SUMIFS('For Tally'!D:D, 'For Tally'!H:H, $A54, 'For Tally'!A:A, ">=2025-08-01", 'For Tally'!A:A, "<=2025-08-31", 'For Tally'!L:L, $B$5:$F$5)) -> 0 | G54: =SUMPRODUCT(SUMIFS('For Tally'!D:D, 'For Tally'!H:H, $A54, 'For Tally'!A:A, ">=2025-09-01", 'For Tally'!A:A, "<=2025-09-30", 'For Tally'!L:L, $B$5:$F$5)) -> 0 | H54: =SUMPRODUCT(SUMIFS('For Tally'!D:D, 'For Tally'!H:H, $A54, 'For Tally'!A:A, ">=2025-10-01", 'For Tally'!A:A, "<=2025-10-31", 'For Tally'!L:L, $B$5:$F$5)) -> 0 | I54: =SUMPRODUCT(SUMIFS('For Tally'!D:D, 'For Tally'!H:H, $A54, 'For Tally'!A:A, ">=2025-11-01", 'For Tally'!A:A, "<=2025-11-30", 'For Tally'!L:L, $B$5:$F$5)) -> 0 | J54: =SUMPRODUCT(SUMIFS('For Tally'!D:D, 'For Tally'!H:H, $A54, 'For Tally'!A:A, ">=2025-12-01", 'For Tally'!A:A, "<=2025-12-31", 'For Tally'!L:L, $B$5:$F$5)) -> 0 | K54: =SUMPRODUCT(SUMIFS('For Tally'!D:D, 'For Tally'!H:H, $A54, 'For Tally'!A:A, ">=2026-01-01", 'For Tally'!A:A, "<=2026-01-31", 'For Tally'!L:L, $B$5:$F$5)) -> 12217.71 | L54: =SUMPRODUCT(SUMIFS('For Tally'!D:D, 'For Tally'!H:H, $A54, 'For Tally'!A:A, ">=2026-02-01", 'For Tally'!A:A, "<=2026-02-28", 'For Tally'!L:L, $B$5:$F$5)) -> 0 | M54: =SUMPRODUCT(SUMIFS('For Tally'!D:D, 'For Tally'!H:H, $A54, 'For Tally'!A:A, ">=2026-03-01", 'For Tally'!A:A, "<=2026-03-31", 'For Tally'!L:L, $B$5:$F$5)) -> 0 | N54: =SUMPRODUCT(SUMIFS('For Tally'!D:D, 'For Tally'!H:H, $A54, 'For Tally'!A:A, ">=2026-04-01", 'For Tally'!A:A, "<=2026-04-30", 'For Tally'!L:L, $B$5:$F$5)) -> 0 | O54: =SUM(B54:N54) -> 17217.71
A55: Megha Gupta | B55: =SUMPRODUCT(SUMIFS('For Tally'!D:D, 'For Tally'!H:H, $A55, 'For Tally'!A:A, ">=2025-04-01", 'For Tally'!A:A, "<=2025-04-30", 'For Tally'!L:L, $B$5:$F$5)) -> 10 | C55: =SUMPRODUCT(SUMIFS('For Tally'!D:D, 'For Tally'!H:H, $A55, 'For Tally'!A:A, ">=2025-05-01", 'For Tally'!A:A, "<=2025-05-31", 'For Tally'!L:L, $B$5:$F$5)) -> 2012 | D55: =SUMPRODUCT(SUMIFS('For Tally'!D:D, 'For Tally'!H:H, $A55, 'For Tally'!A:A, ">=2025-06-01", 'For Tally'!A:A, "<=2025-06-30", 'For Tally'!L:L, $B$5:$F$5)) -> 0 | E55: =SUMPRODUCT(SUMIFS('For Tally'!D:D, 'For Tally'!H:H, $A55, 'For Tally'!A:A, ">=2025-07-01", 'For Tally'!A:A, "<=2025-07-31", 'For Tally'!L:L, $B$5:$F$5)) -> 70000 | F55: =SUMPRODUCT(SUMIFS('For Tally'!D:D, 'For Tally'!H:H, $A55, 'For Tally'!A:A, ">=2025-08-01", 'For Tally'!A:A, "<=2025-08-31", 'For Tally'!L:L, $B$5:$F$5)) -> 0 | G55: =SUMPRODUCT(SUMIFS('For Tally'!D:D, 'For Tally'!H:H, $A55, 'For Tally'!A:A, ">=2025-09-01", 'For Tally'!A:A, "<=2025-09-30", 'For Tally'!L:L, $B$5:$F$5)) -> 0 | H55: =SUMPRODUCT(SUMIFS('For Tally'!D:D, 'For Tally'!H:H, $A55, 'For Tally'!A:A, ">=2025-10-01", 'For Tally'!A:A, "<=2025-10-31", 'For Tally'!L:L, $B$5:$F$5)) -> 2501 | I55: =SUMPRODUCT(SUMIFS('For Tally'!D:D, 'For Tally'!H:H, $A55, 'For Tally'!A:A, ">=2025-11-01", 'For Tally'!A:A, "<=2025-11-30", 'For Tally'!L:L, $B$5:$F$5)) -> 700 | J55: =SUMPRODUCT(SUMIFS('For Tally'!D:D, 'For Tally'!H:H, $A55, 'For Tally'!A:A, ">=2025-12-01", 'For Tally'!A:A, "<=2025-12-31", 'For Tally'!L:L, $B$5:$F$5)) -> 5350 | K55: =SUMPRODUCT(SUMIFS('For Tally'!D:D, 'For Tally'!H:H, $A55, 'For Tally'!A:A, ">=2026-01-01", 'For Tally'!A:A, "<=2026-01-31", 'For Tally'!L:L, $B$5:$F$5)) -> 12000 | L55: =SUMPRODUCT(SUMIFS('For Tally'!D:D, 'For Tally'!H:H, $A55, 'For Tally'!A:A, ">=2026-02-01", 'For Tally'!A:A, "<=2026-02-28", 'For Tally'!L:L, $B$5:$F$5)) -> 0 | M55: =SUMPRODUCT(SUMIFS('For Tally'!D:D, 'For Tally'!H:H, $A55, 'For Tally'!A:A, ">=2026-03-01", 'For Tally'!A:A, "<=2026-03-31", 'For Tally'!L:L, $B$5:$F$5)) -> 1000 | N55: =SUMPRODUCT(SUMIFS('For Tally'!D:D, 'For Tally'!H:H, $A55, 'For Tally'!A:A, ">=2026-04-01", 'For Tally'!A:A, "<=2026-04-30", 'For Tally'!L:L, $B$5:$F$5)) -> 0 | O55: =SUM(B55:N55) -> 93573
... A67: Zerodha Broking Limited | B67: =SUMPRODUCT(SUMIFS('For Tally'!D:D, 'For Tally'!H:H, $A67, 'For Tally'!A:A, ">=2025-04-01", 'For Tally'!A:A, "<=2025-04-30", 'For Tally'!L:L, $B$5:$F$5)) -> 4213.71 | C67: =SUMPRODUCT(SUMIFS('For Tally'!D:D, 'For Tally'!H:H, $A67, 'For Tally'!A:A, ">=2025-05-01", 'For Tally'!A:A, "<=2025-05-31", 'For Tally'!L:L, $B$5:$F$5)) -> 0 | D67: =SUMPRODUCT(SUMIFS('For Tally'!D:D, 'For Tally'!H:H, $A67, 'For Tally'!A:A, ">=2025-06-01", 'For Tally'!A:A, "<=2025-06-30", 'For Tally'!L:L, $B$5:$F$5)) -> 0 | E67: =SUMPRODUCT(SUMIFS('For Tally'!D:D, 'For Tally'!H:H, $A67, 'For Tally'!A:A, ">=2025-07-01", 'For Tally'!A:A, "<=2025-07-31", 'For Tally'!L:L, $B$5:$F$5)) -> 0 | F67: =SUMPRODUCT(SUMIFS('For Tally'!D:D, 'For Tally'!H:H, $A67, 'For Tally'!A:A, ">=2025-08-01", 'For Tally'!A:A, "<=2025-08-31", 'For Tally'!L:L, $B$5:$F$5)) -> 0 | G67: =SUMPRODUCT(SUMIFS('For Tally'!D:D, 'For Tally'!H:H, $A67, 'For Tally'!A:A, ">=2025-09-01", 'For Tally'!A:A, "<=2025-09-30", 'For Tally'!L:L, $B$5:$F$5)) -> 0 | H67: =SUMPRODUCT(SUMIFS('For Tally'!D:D, 'For Tally'!H:H, $A67, 'For Tally'!A:A, ">=2025-10-01", 'For Tally'!A:A, "<=2025-10-31", 'For Tally'!L:L, $B$5:$F$5)) -> 5974.19 | I67: =SUMPRODUCT(SUMIFS('For Tally'!D:D, 'For Tally'!H:H, $A67, 'For Tally'!A:A, ">=2025-11-01", 'For Tally'!A:A, "<=2025-11-30", 'For Tally'!L:L, $B$5:$F$5)) -> 0 | J67: =SUMPRODUCT(SUMIFS('For Tally'!D:D, 'For Tally'!H:H, $A67, 'For Tally'!A:A, ">=2025-12-01", 'For Tally'!A:A, "<=2025-12-31", 'For Tally'!L:L, $B$5:$F$5)) -> 0 | K67: =SUMPRODUCT(SUMIFS('For Tally'!D:D, 'For Tally'!H:H, $A67, 'For Tally'!A:A, ">=2026-01-01", 'For Tally'!A:A, "<=2026-01-31", 'For Tally'!L:L, $B$5:$F$5)) -> 25783.1 | L67: =SUMPRODUCT(SUMIFS('For Tally'!D:D, 'For Tally'!H:H, $A67, 'For Tally'!A:A, ">=2026-02-01", 'For Tally'!A:A, "<=2026-02-28", 'For Tally'!L:L, $B$5:$F$5)) -> 0 | M67: =SUMPRODUCT(SUMIFS('For Tally'!D:D, 'For Tally'!H:H, $A67, 'For Tally'!A:A, ">=2026-03-01", 'For Tally'!A:A, "<=2026-03-31", 'For Tally'!L:L, $B$5:$F$5)) -> 0 | N67: =SUMPRODUCT(SUMIFS('For Tally'!D:D, 'For Tally'!H:H, $A67, 'For Tally'!A:A, ">=2026-04-01", 'For Tally'!A:A, "<=2026-04-30", 'For Tally'!L:L, $B$5:$F$5)) -> 0 | O67: =SUM(B67:N67) -> 35971
A68: MONTHLY TOTAL | B68: =SUM(B44:B67) -> 332500.7 | C68: =SUM(C44:C67) -> 433492.01 | D68: =SUM(D44:D67) -> 240876.65 | E68: =SUM(E44:E67) -> 357540.69 | F68: =SUM(F44:F67) -> 287140.1 | G68: =SUM(G44:G67) -> 496211.51 | H68: =SUM(H44:H67) -> 738881.92 | I68: =SUM(I44:I67) -> 198811.07 | ... O68: =SUM(O44:O67) -> 4086977.1
A70: CC SPENDS (by transaction date) | B70: Apr-2025 | C70: May-2025 | D70: Jun-2025 | E70: Jul-2025 | F70: Aug-2025 | G70: Sep-2025 | H70: Oct-2025 | I70: Nov-2025 | J70: Dec-2025 | K70: Jan-2026 | L70: Feb-2026 | M70: Mar-2026 | N70: Apr-2026 | O70: TOTAL
A71: CC - Automotive | B71: =SUMIFS('CC Transactions'!E:E, 'CC Transactions'!D:D, $A71, 'CC Transactions'!A:A, ">=2025-04-01", 'CC Transactions'!A:A, "<=2025-04-30") -> 1500 | C71: =SUMIFS('CC Transactions'!E:E, 'CC Transactions'!D:D, $A71, 'CC Transactions'!A:A, ">=2025-05-01", 'CC Transactions'!A:A, "<=2025-05-31") -> 0 | D71: =SUMIFS('CC Transactions'!E:E, 'CC Transactions'!D:D, $A71, 'CC Transactions'!A:A, ">=2025-06-01", 'CC Transactions'!A:A, "<=2025-06-30") -> 2848 | E71: =SUMIFS('CC Transactions'!E:E, 'CC Transactions'!D:D, $A71, 'CC Transactions'!A:A, ">=2025-07-01", 'CC Transactions'!A:A, "<=2025-07-31") -> 0 | F71: =SUMIFS('CC Transactions'!E:E, 'CC Transactions'!D:D, $A71, 'CC Transactions'!A:A, ">=2025-08-01", 'CC Transactions'!A:A, "<=2025-08-31") -> 0 | G71: =SUMIFS('CC Transactions'!E:E, 'CC Transactions'!D:D, $A71, 'CC Transactions'!A:A, ">=2025-09-01", 'CC Transactions'!A:A, "<=2025-09-30") -> 6644 | H71: =SUMIFS('CC Transactions'!E:E, 'CC Transactions'!D:D, $A71, 'CC Transactions'!A:A, ">=2025-10-01", 'CC Transactions'!A:A, "<=2025-10-31") -> 0 | I71: =SUMIFS('CC Transactions'!E:E, 'CC Transactions'!D:D, $A71, 'CC Transactions'!A:A, ">=2025-11-01", 'CC Transactions'!A:A, "<=2025-11-30") -> 0 | J71: =SUMIFS('CC Transactions'!E:E, 'CC Transactions'!D:D, $A71, 'CC Transactions'!A:A, ">=2025-12-01", 'CC Transactions'!A:A, "<=2025-12-31") -> 0 | K71: =SUMIFS('CC Transactions'!E:E, 'CC Transactions'!D:D, $A71, 'CC Transactions'!A:A, ">=2026-01-01", 'CC Transactions'!A:A, "<=2026-01-31") -> 0 | L71: =SUMIFS('CC Transactions'!E:E, 'CC Transactions'!D:D, $A71, 'CC Transactions'!A:A, ">=2026-02-01", 'CC Transactions'!A:A, "<=2026-02-28") -> 700 | M71: =SUMIFS('CC Transactions'!E:E, 'CC Transactions'!D:D, $A71, 'CC Transactions'!A:A, ">=2026-03-01", 'CC Transactions'!A:A, "<=2026-03-31") -> 0 | N71: =SUMIFS('CC Transactions'!E:E, 'CC Transactions'!D:D, $A71, 'CC Transactions'!A:A, ">=2026-04-01", 'CC Transactions'!A:A, "<=2026-04-30") -> 0 | O71: =SUM(B71:N71) -> 11692
A72: CC - Entertainment | B72: =SUMIFS('CC Transactions'!E:E, 'CC Transactions'!D:D, $A72, 'CC Transactions'!A:A, ">=2025-04-01", 'CC Transactions'!A:A, "<=2025-04-30") -> 0 | C72: =SUMIFS('CC Transactions'!E:E, 'CC Transactions'!D:D, $A72, 'CC Transactions'!A:A, ">=2025-05-01", 'CC Transactions'!A:A, "<=2025-05-31") -> 0 | D72: =SUMIFS('CC Transactions'!E:E, 'CC Transactions'!D:D, $A72, 'CC Transactions'!A:A, ">=2025-06-01", 'CC Transactions'!A:A, "<=2025-06-30") -> 244.84 | E72: =SUMIFS('CC Transactions'!E:E, 'CC Transactions'!D:D, $A72, 'CC Transactions'!A:A, ">=2025-07-01", 'CC Transactions'!A:A, "<=2025-07-31") -> 561 | F72: =SUMIFS('CC Transactions'!E:E, 'CC Transactions'!D:D, $A72, 'CC Transactions'!A:A, ">=2025-08-01", 'CC Transactions'!A:A, "<=2025-08-31") -> 0 | G72: =SUMIFS('CC Transactions'!E:E, 'CC Transactions'!D:D, $A72, 'CC Transactions'!A:A, ">=2025-09-01", 'CC Transactions'!A:A, "<=2025-09-30") -> 1247 | H72: =SUMIFS('CC Transactions'!E:E, 'CC Transactions'!D:D, $A72, 'CC Transactions'!A:A, ">=2025-10-01", 'CC Transactions'!A:A, "<=2025-10-31") -> 0 | I72: =SUMIFS('CC Transactions'!E:E, 'CC Transactions'!D:D, $A72, 'CC Transactions'!A:A, ">=2025-11-01", 'CC Transactions'!A:A, "<=2025-11-30") -> 0 | J72: =SUMIFS('CC Transactions'!E:E, 'CC Transactions'!D:D, $A72, 'CC Transactions'!A:A, ">=2025-12-01", 'CC Transactions'!A:A, "<=2025-12-31") -> 0 | K72: =SUMIFS('CC Transactions'!E:E, 'CC Transactions'!D:D, $A72, 'CC Transactions'!A:A, ">=2026-01-01", 'CC Transactions'!A:A, "<=2026-01-31") -> 0 | L72: =SUMIFS('CC Transactions'!E:E, 'CC Transactions'!D:D, $A72, 'CC Transactions'!A:A, ">=2026-02-01", 'CC Transactions'!A:A, "<=2026-02-28") -> 0 | M72: =SUMIFS('CC Transactions'!E:E, 'CC Transactions'!D:D, $A72, 'CC Transactions'!A:A, ">=2026-03-01", 'CC Transactions'!A:A, "<=2026-03-31") -> 0 | N72: =SUMIFS('CC Transactions'!E:E, 'CC Transactions'!D:D, $A72, 'CC Transactions'!A:A, ">=2026-04-01", 'CC Transactions'!A:A, "<=2026-04-30") -> 0 | O72: =SUM(B72:N72) -> 2052.84
A73: CC - Fuel | B73: =SUMIFS('CC Transactions'!E:E, 'CC Transactions'!D:D, $A73, 'CC Transactions'!A:A, ">=2025-04-01", 'CC Transactions'!A:A, "<=2025-04-30") -> 0 | C73: =SUMIFS('CC Transactions'!E:E, 'CC Transactions'!D:D, $A73, 'CC Transactions'!A:A, ">=2025-05-01", 'CC Transactions'!A:A, "<=2025-05-31") -> 310 | D73: =SUMIFS('CC Transactions'!E:E, 'CC Transactions'!D:D, $A73, 'CC Transactions'!A:A, ">=2025-06-01", 'CC Transactions'!A:A, "<=2025-06-30") -> 0 | E73: =SUMIFS('CC Transactions'!E:E, 'CC Transactions'!D:D, $A73, 'CC Transactions'!A:A, ">=2025-07-01", 'CC Transactions'!A:A, "<=2025-07-31") -> 65 | F73: =SUMIFS('CC Transactions'!E:E, 'CC Transactions'!D:D, $A73, 'CC Transactions'!A:A, ">=2025-08-01", 'CC Transactions'!A:A, "<=2025-08-31") -> 0 | G73: =SUMIFS('CC Transactions'!E:E, 'CC Transactions'!D:D, $A73, 'CC Transactions'!A:A, ">=2025-09-01", 'CC Transactions'!A:A, "<=2025-09-30") -> 0 | H73: =SUMIFS('CC Transactions'!E:E, 'CC Transactions'!D:D, $A73, 'CC Transactions'!A:A, ">=2025-10-01", 'CC Transactions'!A:A, "<=2025-10-31") -> 0 | I73: =SUMIFS('CC Transactions'!E:E, 'CC Transactions'!D:D, $A73, 'CC Transactions'!A:A, ">=2025-11-01", 'CC Transactions'!A:A, "<=2025-11-30") -> 0 | J73: =SUMIFS('CC Transactions'!E:E, 'CC Transactions'!D:D, $A73, 'CC Transactions'!A:A, ">=2025-12-01", 'CC Transactions'!A:A, "<=2025-12-31") -> 260 | K73: =SUMIFS('CC Transactions'!E:E, 'CC Transactions'!D:D, $A73, 'CC Transactions'!A:A, ">=2026-01-01", 'CC Transactions'!A:A, "<=2026-01-31") -> 0 | L73: =SUMIFS('CC Transactions'!E:E, 'CC Transactions'!D:D, $A73, 'CC Transactions'!A:A, ">=2026-02-01", 'CC Transactions'!A:A, "<=2026-02-28") -> 0 | M73: =SUMIFS('CC Transactions'!E:E, 'CC Transactions'!D:D, $A73, 'CC Transactions'!A:A, ">=2026-03-01", 'CC Transactions'!A:A, "<=2026-03-31") -> 0 | N73: =SUMIFS('CC Transactions'!E:E, 'CC Transactions'!D:D, $A73, 'CC Transactions'!A:A, ">=2026-04-01", 'CC Transactions'!A:A, "<=2026-04-30") -> 0 | O73: =SUM(B73:N73) -> 635
A74: CC - Groceries | B74: =SUMIFS('CC Transactions'!E:E, 'CC Transactions'!D:D, $A74, 'CC Transactions'!A:A, ">=2025-04-01", 'CC Transactions'!A:A, "<=2025-04-30") -> 771 | C74: =SUMIFS('CC Transactions'!E:E, 'CC Transactions'!D:D, $A74, 'CC Transactions'!A:A, ">=2025-05-01", 'CC Transactions'!A:A, "<=2025-05-31") -> 6984.15 | D74: =SUMIFS('CC Transactions'!E:E, 'CC Transactions'!D:D, $A74, 'CC Transactions'!A:A, ">=2025-06-01", 'CC Transactions'!A:A, "<=2025-06-30") -> 1301 | E74: =SUMIFS('CC Transactions'!E:E, 'CC Transactions'!D:D, $A74, 'CC Transactions'!A:A, ">=2025-07-01", 'CC Transactions'!A:A, "<=2025-07-31") -> 8451.72 | F74: =SUMIFS('CC Transactions'!E:E, 'CC Transactions'!D:D, $A74, 'CC Transactions'!A:A, ">=2025-08-01", 'CC Transactions'!A:A, "<=2025-08-31") -> 2007.5 | G74: =SUMIFS('CC Transactions'!E:E, 'CC Transactions'!D:D, $A74, 'CC Transactions'!A:A, ">=2025-09-01", 'CC Transactions'!A:A, "<=2025-09-30") -> 7533.11 | H74: =SUMIFS('CC Transactions'!E:E, 'CC Transactions'!D:D, $A74, 'CC Transactions'!A:A, ">=2025-10-01", 'CC Transactions'!A:A, "<=2025-10-31") -> 5436 | I74: =SUMIFS('CC Transactions'!E:E, 'CC Transactions'!D:D, $A74, 'CC Transactions'!A:A, ">=2025-11-01", 'CC Transactions'!A:A, "<=2025-11-30") -> 1362 | J74: =SUMIFS('CC Transactions'!E:E, 'CC Transactions'!D:D, $A74, 'CC Transactions'!A:A, ">=2025-12-01", 'CC Transactions'!A:A, "<=2025-12-31") -> 6096.16 | K74: =SUMIFS('CC Transactions'!E:E, 'CC Transactions'!D:D, $A74, 'CC Transactions'!A:A, ">=2026-01-01", 'CC Transactions'!A:A, "<=2026-01-31") -> 895 | L74: =SUMIFS('CC Transactions'!E:E, 'CC Transactions'!D:D, $A74, 'CC Transactions'!A:A, ">=2026-02-01", 'CC Transactions'!A:A, "<=2026-02-28") -> 5141.81 | M74: =SUMIFS('CC Transactions'!E:E, 'CC Transactions'!D:D, $A74, 'CC Transactions'!A:A, ">=2026-03-01", 'CC Transactions'!A:A, "<=2026-03-31") -> 1879.38 | N74: =SUMIFS('CC Transactions'!E:E, 'CC Transactions'!D:D, $A74, 'CC Transactions'!A:A, ">=2026-04-01", 'CC Transactions'!A:A, "<=2026-04-30") -> 0 | O74: =SUM(B74:N74) -> 47858.83
A75: CC - Healthcare | B75: =SUMIFS('CC Transactions'!E:E, 'CC Transactions'!D:D, $A75, 'CC Transactions'!A:A, ">=2025-04-01", 'CC Transactions'!A:A, "<=2025-04-30") -> 0 | C75: =SUMIFS('CC Transactions'!E:E, 'CC Transactions'!D:D, $A75, 'CC Transactions'!A:A, ">=2025-05-01", 'CC Transactions'!A:A, "<=2025-05-31") -> 205 | D75: =SUMIFS('CC Transactions'!E:E, 'CC Transactions'!D:D, $A75, 'CC Transactions'!A:A, ">=2025-06-01", 'CC Transactions'!A:A, "<=2025-06-30") -> 0 | E75: =SUMIFS('CC Transactions'!E:E, 'CC Transactions'!D:D, $A75, 'CC Transactions'!A:A, ">=2025-07-01", 'CC Transactions'!A:A, "<=2025-07-31") -> 0 | F75: =SUMIFS('CC Transactions'!E:E, 'CC Transactions'!D:D, $A75, 'CC Transactions'!A:A, ">=2025-08-01", 'CC Transactions'!A:A, "<=2025-08-31") -> 0 | G75: =SUMIFS('CC Transactions'!E:E, 'CC Transactions'!D:D, $A75, 'CC Transactions'!A:A, ">=2025-09-01", 'CC Transactions'!A:A, "<=2025-09-30") -> 0 | H75: =SUMIFS('CC Transactions'!E:E, 'CC Transactions'!D:D, $A75, 'CC Transactions'!A:A, ">=2025-10-01", 'CC Transactions'!A:A, "<=2025-10-31") -> 0 | I75: =SUMIFS('CC Transactions'!E:E, 'CC Transactions'!D:D, $A75, 'CC Transactions'!A:A, ">=2025-11-01", 'CC Transactions'!A:A, "<=2025-11-30") -> 208 | J75: =SUMIFS('CC Transactions'!E:E, 'CC Transactions'!D:D, $A75, 'CC Transactions'!A:A, ">=2025-12-01", 'CC Transactions'!A:A, "<=2025-12-31") -> 64 | K75: =SUMIFS('CC Transactions'!E:E, 'CC Transactions'!D:D, $A75, 'CC Transactions'!A:A, ">=2026-01-01", 'CC Transactions'!A:A, "<=2026-01-31") -> 0 | L75: =SUMIFS('CC Transactions'!E:E, 'CC Transactions'!D:D, $A75, 'CC Transactions'!A:A, ">=2026-02-01", 'CC Transactions'!A:A, "<=2026-02-28") -> 0 | M75: =SUMIFS('CC Transactions'!E:E, 'CC Transactions'!D:D, $A75, 'CC Transactions'!A:A, ">=2026-03-01", 'CC Transactions'!A:A, "<=2026-03-31") -> 0 | N75: =SUMIFS('CC Transactions'!E:E, 'CC Transactions'!D:D, $A75, 'CC Transactions'!A:A, ">=2026-04-01", 'CC Transactions'!A:A, "<=2026-04-30") -> 0 | O75: =SUM(B75:N75) -> 477
A76: CC - Other | B76: =SUMIFS('CC Transactions'!E:E, 'CC Transactions'!D:D, $A76, 'CC Transactions'!A:A, ">=2025-04-01", 'CC Transactions'!A:A, "<=2025-04-30") -> 65 | C76: =SUMIFS('CC Transactions'!E:E, 'CC Transactions'!D:D, $A76, 'CC Transactions'!A:A, ">=2025-05-01", 'CC Transactions'!A:A, "<=2025-05-31") -> 185 | D76: =SUMIFS('CC Transactions'!E:E, 'CC Transactions'!D:D, $A76, 'CC Transactions'!A:A, ">=2025-06-01", 'CC Transactions'!A:A, "<=2025-06-30") -> 494.66 | E76: =SUMIFS('CC Transactions'!E:E, 'CC Transactions'!D:D, $A76, 'CC Transactions'!A:A, ">=2025-07-01", 'CC Transactions'!A:A, "<=2025-07-31") -> 1000 | F76: =SUMIFS('CC Transactions'!E:E, 'CC Transactions'!D:D, $A76, 'CC Transactions'!A:A, ">=2025-08-01", 'CC Transactions'!A:A, "<=2025-08-31") -> 1253 | G76: =SUMIFS('CC Transactions'!E:E, 'CC Transactions'!D:D, $A76, 'CC Transactions'!A:A, ">=2025-09-01", 'CC Transactions'!A:A, "<=2025-09-30") -> 1214 | H76: =SUMIFS('CC Transactions'!E:E, 'CC Transactions'!D:D, $A76, 'CC Transactions'!A:A, ">=2025-10-01", 'CC Transactions'!A:A, "<=2025-10-31") -> 1406 | I76: =SUMIFS('CC Transactions'!E:E, 'CC Transactions'!D:D, $A76, 'CC Transactions'!A:A, ">=2025-11-01", 'CC Transactions'!A:A, "<=2025-11-30") -> 40 | J76: =SUMIFS('CC Transactions'!E:E, 'CC Transactions'!D:D, $A76, 'CC Transactions'!A:A, ">=2025-12-01", 'CC Transactions'!A:A, "<=2025-12-31") -> 333 | K76: =SUMIFS('CC Transactions'!E:E, 'CC Transactions'!D:D, $A76, 'CC Transactions'!A:A, ">=2026-01-01", 'CC Transactions'!A:A, "<=2026-01-31") -> 84 | L76: =SUMIFS('CC Transactions'!E:E, 'CC Transactions'!D:D, $A76, 'CC Transactions'!A:A, ">=2026-02-01", 'CC Transactions'!A:A, "<=2026-02-28") -> 1088.96 | M76: =SUMIFS('CC Transactions'!E:E, 'CC Transactions'!D:D, $A76, 'CC Transactions'!A:A, ">=2026-03-01", 'CC Transactions'!A:A, "<=2026-03-31") -> 1011.22 | N76: =SUMIFS('CC Transactions'!E:E, 'CC Transactions'!D:D, $A76, 'CC Transactions'!A:A, ">=2026-04-01", 'CC Transactions'!A:A, "<=2026-04-30") -> 0 | O76: =SUM(B76:N76) -> 8174.84
A77: CC - Recreation | B77: =SUMIFS('CC Transactions'!E:E, 'CC Transactions'!D:D, $A77, 'CC Transactions'!A:A, ">=2025-04-01", 'CC Transactions'!A:A, "<=2025-04-30") -> 1149 | C77: =SUMIFS('CC Transactions'!E:E, 'CC Transactions'!D:D, $A77, 'CC Transactions'!A:A, ">=2025-05-01", 'CC Transactions'!A:A, "<=2025-05-31") -> 0 | D77: =SUMIFS('CC Transactions'!E:E, 'CC Transactions'!D:D, $A77, 'CC Transactions'!A:A, ">=2025-06-01", 'CC Transactions'!A:A, "<=2025-06-30") -> 0 | E77: =SUMIFS('CC Transactions'!E:E, 'CC Transactions'!D:D, $A77, 'CC Transactions'!A:A, ">=2025-07-01", 'CC Transactions'!A:A, "<=2025-07-31") -> 0 | F77: =SUMIFS('CC Transactions'!E:E, 'CC Transactions'!D:D, $A77, 'CC Transactions'!A:A, ">=2025-08-01", 'CC Transactions'!A:A, "<=2025-08-31") -> 0 | G77: =SUMIFS('CC Transactions'!E:E, 'CC Transactions'!D:D, $A77, 'CC Transactions'!A:A, ">=2025-09-01", 'CC Transactions'!A:A, "<=2025-09-30") -> 3000 | H77: =SUMIFS('CC Transactions'!E:E, 'CC Transactions'!D:D, $A77, 'CC Transactions'!A:A, ">=2025-10-01", 'CC Transactions'!A:A, "<=2025-10-31") -> 0 | I77: =SUMIFS('CC Transactions'!E:E, 'CC Transactions'!D:D, $A77, 'CC Transactions'!A:A, ">=2025-11-01", 'CC Transactions'!A:A, "<=2025-11-30") -> 0 | J77: =SUMIFS('CC Transactions'!E:E, 'CC Transactions'!D:D, $A77, 'CC Transactions'!A:A, ">=2025-12-01", 'CC Transactions'!A:A, "<=2025-12-31") -> 0 | K77: =SUMIFS('CC Transactions'!E:E, 'CC Transactions'!D:D, $A77, 'CC Transactions'!A:A, ">=2026-01-01", 'CC Transactions'!A:A, "<=2026-01-31") -> 30 | L77: =SUMIFS('CC Transactions'!E:E, 'CC Transactions'!D:D, $A77, 'CC Transactions'!A:A, ">=2026-02-01", 'CC Transactions'!A:A, "<=2026-02-28") -> 0 | M77: =SUMIFS('CC Transactions'!E:E, 'CC Transactions'!D:D, $A77, 'CC Transactions'!A:A, ">=2026-03-01", 'CC Transactions'!A:A, "<=2026-03-31") -> 0 | N77: =SUMIFS('CC Transactions'!E:E, 'CC Transactions'!D:D, $A77, 'CC Transactions'!A:A, ">=2026-04-01", 'CC Transactions'!A:A, "<=2026-04-30") -> 0 | O77: =SUM(B77:N77) -> 4179
A78: CC - Restaurants | B78: =SUMIFS('CC Transactions'!E:E, 'CC Transactions'!D:D, $A78, 'CC Transactions'!A:A, ">=2025-04-01", 'CC Transactions'!A:A, "<=2025-04-30") -> 1321.6 | C78: =SUMIFS('CC Transactions'!E:E, 'CC Transactions'!D:D, $A78, 'CC Transactions'!A:A, ">=2025-05-01", 'CC Transactions'!A:A, "<=2025-05-31") -> 1940.28 | D78: =SUMIFS('CC Transactions'!E:E, 'CC Transactions'!D:D, $A78, 'CC Transactions'!A:A, ">=2025-06-01", 'CC Transactions'!A:A, "<=2025-06-30") -> 1757.39 | E78: =SUMIFS('CC Transactions'!E:E, 'CC Transactions'!D:D, $A78, 'CC Transactions'!A:A, ">=2025-07-01", 'CC Transactions'!A:A, "<=2025-07-31") -> 2844.52 | F78: =SUMIFS('CC Transactions'!E:E, 'CC Transactions'!D:D, $A78, 'CC Transactions'!A:A, ">=2025-08-01", 'CC Transactions'!A:A, "<=2025-08-31") -> 3350.2 | G78: =SUMIFS('CC Transactions'!E:E, 'CC Transactions'!D:D, $A78, 'CC Transactions'!A:A, ">=2025-09-01", 'CC Transactions'!A:A, "<=2025-09-30") -> 7646.89 | H78: =SUMIFS('CC Transactions'!E:E, 'CC Transactions'!D:D, $A78, 'CC Transactions'!A:A, ">=2025-10-01", 'CC Transactions'!A:A, "<=2025-10-31") -> 2038.45 | I78: =SUMIFS('CC Transactions'!E:E, 'CC Transactions'!D:D, $A78, 'CC Transactions'!A:A, ">=2025-11-01", 'CC Transactions'!A:A, "<=2025-11-30") -> 2613 | J78: =SUMIFS('CC Transactions'!E:E, 'CC Transactions'!D:D, $A78, 'CC Transactions'!A:A, ">=2025-12-01", 'CC Transactions'!A:A, "<=2025-12-31") -> 2308.7 | K78: =SUMIFS('CC Transactions'!E:E, 'CC Transactions'!D:D, $A78, 'CC Transactions'!A:A, ">=2026-01-01", 'CC Transactions'!A:A, "<=2026-01-31") -> 1067 | L78: =SUMIFS('CC Transactions'!E:E, 'CC Transactions'!D:D, $A78, 'CC Transactions'!A:A, ">=2026-02-01", 'CC Transactions'!A:A, "<=2026-02-28") -> 1792.95 | M78: =SUMIFS('CC Transactions'!E:E, 'CC Transactions'!D:D, $A78, 'CC Transactions'!A:A, ">=2026-03-01", 'CC Transactions'!A:A, "<=2026-03-31") -> 2164.2 | N78: =SUMIFS('CC Transactions'!E:E, 'CC Transactions'!D:D, $A78, 'CC Transactions'!A:A, ">=2026-04-01", 'CC Transactions'!A:A, "<=2026-04-30") -> 0 | O78: =SUM(B78:N78) -> 30845.18
A79: CC - Services | B79: =SUMIFS('CC Transactions'!E:E, 'CC Transactions'!D:D, $A79, 'CC Transactions'!A:A, ">=2025-04-01", 'CC Transactions'!A:A, "<=2025-04-30") -> 100 | C79: =SUMIFS('CC Transactions'!E:E, 'CC Transactions'!D:D, $A79, 'CC Transactions'!A:A, ">=2025-05-01", 'CC Transactions'!A:A, "<=2025-05-31") -> 0 | D79: =SUMIFS('CC Transactions'!E:E, 'CC Transactions'!D:D, $A79, 'CC Transactions'!A:A, ">=2025-06-01", 'CC Transactions'!A:A, "<=2025-06-30") -> 70 | E79: =SUMIFS('CC Transactions'!E:E, 'CC Transactions'!D:D, $A79, 'CC Transactions'!A:A, ">=2025-07-01", 'CC Transactions'!A:A, "<=2025-07-31") -> 300 | F79: =SUMIFS('CC Transactions'!E:E, 'CC Transactions'!D:D, $A79, 'CC Transactions'!A:A, ">=2025-08-01", 'CC Transactions'!A:A, "<=2025-08-31") -> 185 | G79: =SUMIFS('CC Transactions'!E:E, 'CC Transactions'!D:D, $A79, 'CC Transactions'!A:A, ">=2025-09-01", 'CC Transactions'!A:A, "<=2025-09-30") -> 567 | H79: =SUMIFS('CC Transactions'!E:E, 'CC Transactions'!D:D, $A79, 'CC Transactions'!A:A, ">=2025-10-01", 'CC Transactions'!A:A, "<=2025-10-31") -> 100 | I79: =SUMIFS('CC Transactions'!E:E, 'CC Transactions'!D:D, $A79, 'CC Transactions'!A:A, ">=2025-11-01", 'CC Transactions'!A:A, "<=2025-11-30") -> 0 | J79: =SUMIFS('CC Transactions'!E:E, 'CC Transactions'!D:D, $A79, 'CC Transactions'!A:A, ">=2025-12-01", 'CC Transactions'!A:A, "<=2025-12-31") -> 0 | K79: =SUMIFS('CC Transactions'!E:E, 'CC Transactions'!D:D, $A79, 'CC Transactions'!A:A, ">=2026-01-01", 'CC Transactions'!A:A, "<=2026-01-31") -> 149 | L79: =SUMIFS('CC Transactions'!E:E, 'CC Transactions'!D:D, $A79, 'CC Transactions'!A:A, ">=2026-02-01", 'CC Transactions'!A:A, "<=2026-02-28") -> 100 | M79: =SUMIFS('CC Transactions'!E:E, 'CC Transactions'!D:D, $A79, 'CC Transactions'!A:A, ">=2026-03-01", 'CC Transactions'!A:A, "<=2026-03-31") -> 0 | N79: =SUMIFS('CC Transactions'!E:E, 'CC Transactions'!D:D, $A79, 'CC Transactions'!A:A, ">=2026-04-01", 'CC Transactions'!A:A, "<=2026-04-30") -> 0 | O79: =SUM(B79:N79) -> 1571
A80: CC - Shopping | B80: =SUMIFS('CC Transactions'!E:E, 'CC Transactions'!D:D, $A80, 'CC Transactions'!A:A, ">=2025-04-01", 'CC Transactions'!A:A, "<=2025-04-30") -> 501 | C80: =SUMIFS('CC Transactions'!E:E, 'CC Transactions'!D:D, $A80, 'CC Transactions'!A:A, ">=2025-05-01", 'CC Transactions'!A:A, "<=2025-05-31") -> 500 | D80: =SUMIFS('CC Transactions'!E:E, 'CC Transactions'!D:D, $A80, 'CC Transactions'!A:A, ">=2025-06-01", 'CC Transactions'!A:A, "<=2025-06-30") -> 794 | E80: =SUMIFS('CC Transactions'!E:E, 'CC Transactions'!D:D, $A80, 'CC Transactions'!A:A, ">=2025-07-01", 'CC Transactions'!A:A, "<=2025-07-31") -> 3315 | F80: =SUMIFS('CC Transactions'!E:E, 'CC Transactions'!D:D, $A80, 'CC Transactions'!A:A, ">=2025-08-01", 'CC Transactions'!A:A, "<=2025-08-31") -> 1194.89 | G80: =SUMIFS('CC Transactions'!E:E, 'CC Transactions'!D:D, $A80, 'CC Transactions'!A:A, ">=2025-09-01", 'CC Transactions'!A:A, "<=2025-09-30") -> 449.56 | H80: =SUMIFS('CC Transactions'!E:E, 'CC Transactions'!D:D, $A80, 'CC Transactions'!A:A, ">=2025-10-01", 'CC Transactions'!A:A, "<=2025-10-31") -> 42141 | I80: =SUMIFS('CC Transactions'!E:E, 'CC Transactions'!D:D, $A80, 'CC Transactions'!A:A, ">=2025-11-01", 'CC Transactions'!A:A, "<=2025-11-30") -> 1265 | J80: =SUMIFS('CC Transactions'!E:E, 'CC Transactions'!D:D, $A80, 'CC Transactions'!A:A, ">=2025-12-01", 'CC Transactions'!A:A, "<=2025-12-31") -> 120 | K80: =SUMIFS('CC Transactions'!E:E, 'CC Transactions'!D:D, $A80, 'CC Transactions'!A:A, ">=2026-01-01", 'CC Transactions'!A:A, "<=2026-01-31") -> 1300 | L80: =SUMIFS('CC Transactions'!E:E, 'CC Transactions'!D:D, $A80, 'CC Transactions'!A:A, ">=2026-02-01", 'CC Transactions'!A:A, "<=2026-02-28") -> 800 | M80: =SUMIFS('CC Transactions'!E:E, 'CC Transactions'!D:D, $A80, 'CC Transactions'!A:A, ">=2026-03-01", 'CC Transactions'!A:A, "<=2026-03-31") -> 427.3 | N80: =SUMIFS('CC Transactions'!E:E, 'CC Transactions'!D:D, $A80, 'CC Transactions'!A:A, ">=2026-04-01", 'CC Transactions'!A:A, "<=2026-04-30") -> 0 | O80: =SUM(B80:N80) -> 52807.75
A81: CC - Telecom | B81: =SUMIFS('CC Transactions'!E:E, 'CC Transactions'!D:D, $A81, 'CC Transactions'!A:A, ">=2025-04-01", 'CC Transactions'!A:A, "<=2025-04-30") -> 101 | C81: =SUMIFS('CC Transactions'!E:E, 'CC Transactions'!D:D, $A81, 'CC Transactions'!A:A, ">=2025-05-01", 'CC Transactions'!A:A, "<=2025-05-31") -> 0 | D81: =SUMIFS('CC Transactions'!E:E, 'CC Transactions'!D:D, $A81, 'CC Transactions'!A:A, ">=2025-06-01", 'CC Transactions'!A:A, "<=2025-06-30") -> 315 | E81: =SUMIFS('CC Transactions'!E:E, 'CC Transactions'!D:D, $A81, 'CC Transactions'!A:A, ">=2025-07-01", 'CC Transactions'!A:A, "<=2025-07-31") -> 145 | F81: =SUMIFS('CC Transactions'!E:E, 'CC Transactions'!D:D, $A81, 'CC Transactions'!A:A, ">=2025-08-01", 'CC Transactions'!A:A, "<=2025-08-31") -> 0 | G81: =SUMIFS('CC Transactions'!E:E, 'CC Transactions'!D:D, $A81, 'CC Transactions'!A:A, ">=2025-09-01", 'CC Transactions'!A:A, "<=2025-09-30") -> 558 | H81: =SUMIFS('CC Transactions'!E:E, 'CC Transactions'!D:D, $A81, 'CC Transactions'!A:A, ">=2025-10-01", 'CC Transactions'!A:A, "<=2025-10-31") -> 121 | I81: =SUMIFS('CC Transactions'!E:E, 'CC Transactions'!D:D, $A81, 'CC Transactions'!A:A, ">=2025-11-01", 'CC Transactions'!A:A, "<=2025-11-30") -> 3948 | J81: =SUMIFS('CC Transactions'!E:E, 'CC Transactions'!D:D, $A81, 'CC Transactions'!A:A, ">=2025-12-01", 'CC Transactions'!A:A, "<=2025-12-31") -> 0 | K81: =SUMIFS('CC Transactions'!E:E, 'CC Transactions'!D:D, $A81, 'CC Transactions'!A:A, ">=2026-01-01", 'CC Transactions'!A:A, "<=2026-01-31") -> 0 | L81: =SUMIFS('CC Transactions'!E:E, 'CC Transactions'!D:D, $A81, 'CC Transactions'!A:A, ">=2026-02-01", 'CC Transactions'!A:A, "<=2026-02-28") -> 0 | M81: =SUMIFS('CC Transactions'!E:E, 'CC Transactions'!D:D, $A81, 'CC Transactions'!A:A, ">=2026-03-01", 'CC Transactions'!A:A, "<=2026-03-31") -> 0 | N81: =SUMIFS('CC Transactions'!E:E, 'CC Transactions'!D:D, $A81, 'CC Transactions'!A:A, ">=2026-04-01", 'CC Transactions'!A:A, "<=2026-04-30") -> 0 | O81: =SUM(B81:N81) -> 5188
A82: CC - Travel | B82: =SUMIFS('CC Transactions'!E:E, 'CC Transactions'!D:D, $A82, 'CC Transactions'!A:A, ">=2025-04-01", 'CC Transactions'!A:A, "<=2025-04-30") -> 0 | C82: =SUMIFS('CC Transactions'!E:E, 'CC Transactions'!D:D, $A82, 'CC Transactions'!A:A, ">=2025-05-01", 'CC Transactions'!A:A, "<=2025-05-31") -> 24508 | D82: =SUMIFS('CC Transactions'!E:E, 'CC Transactions'!D:D, $A82, 'CC Transactions'!A:A, ">=2025-06-01", 'CC Transactions'!A:A, "<=2025-06-30") -> 0 | E82: =SUMIFS('CC Transactions'!E:E, 'CC Transactions'!D:D, $A82, 'CC Transactions'!A:A, ">=2025-07-01", 'CC Transactions'!A:A, "<=2025-07-31") -> 0 | F82: =SUMIFS('CC Transactions'!E:E, 'CC Transactions'!D:D, $A82, 'CC Transactions'!A:A, ">=2025-08-01", 'CC Transactions'!A:A, "<=2025-08-31") -> 140 | G82: =SUMIFS('CC Transactions'!E:E, 'CC Transactions'!D:D, $A82, 'CC Transactions'!A:A, ">=2025-09-01", 'CC Transactions'!A:A, "<=2025-09-30") -> 5061.35 | H82: =SUMIFS('CC Transactions'!E:E, 'CC Transactions'!D:D, $A82, 'CC Transactions'!A:A, ">=2025-10-01", 'CC Transactions'!A:A, "<=2025-10-31") -> 0 | I82: =SUMIFS('CC Transactions'!E:E, 'CC Transactions'!D:D, $A82, 'CC Transactions'!A:A, ">=2025-11-01", 'CC Transactions'!A:A, "<=2025-11-30") -> 8277.31 | J82: =SUMIFS('CC Transactions'!E:E, 'CC Transactions'!D:D, $A82, 'CC Transactions'!A:A, ">=2025-12-01", 'CC Transactions'!A:A, "<=2025-12-31") -> 37039.4 | K82: =SUMIFS('CC Transactions'!E:E, 'CC Transactions'!D:D, $A82, 'CC Transactions'!A:A, ">=2026-01-01", 'CC Transactions'!A:A, "<=2026-01-31") -> 0 | L82: =SUMIFS('CC Transactions'!E:E, 'CC Transactions'!D:D, $A82, 'CC Transactions'!A:A, ">=2026-02-01", 'CC Transactions'!A:A, "<=2026-02-28") -> 418.52 | M82: =SUMIFS('CC Transactions'!E:E, 'CC Transactions'!D:D, $A82, 'CC Transactions'!A:A, ">=2026-03-01", 'CC Transactions'!A:A, "<=2026-03-31") -> 0 | N82: =SUMIFS('CC Transactions'!E:E, 'CC Transactions'!D:D, $A82, 'CC Transactions'!A:A, ">=2026-04-01", 'CC Transactions'!A:A, "<=2026-04-30") -> 0 | O82: =SUM(B82:N82) -> 75444.58
... A84: CC - Wifi | B84: =SUMIFS('CC Transactions'!E:E, 'CC Transactions'!D:D, $A84, 'CC Transactions'!A:A, ">=2025-04-01", 'CC Transactions'!A:A, "<=2025-04-30") -> 0 | C84: =SUMIFS('CC Transactions'!E:E, 'CC Transactions'!D:D, $A84, 'CC Transactions'!A:A, ">=2025-05-01", 'CC Transactions'!A:A, "<=2025-05-31") -> 0 | D84: =SUMIFS('CC Transactions'!E:E, 'CC Transactions'!D:D, $A84, 'CC Transactions'!A:A, ">=2025-06-01", 'CC Transactions'!A:A, "<=2025-06-30") -> 0 | E84: =SUMIFS('CC Transactions'!E:E, 'CC Transactions'!D:D, $A84, 'CC Transactions'!A:A, ">=2025-07-01", 'CC Transactions'!A:A, "<=2025-07-31") -> 588.82 | F84: =SUMIFS('CC Transactions'!E:E, 'CC Transactions'!D:D, $A84, 'CC Transactions'!A:A, ">=2025-08-01", 'CC Transactions'!A:A, "<=2025-08-31") -> 588.82 | G84: =SUMIFS('CC Transactions'!E:E, 'CC Transactions'!D:D, $A84, 'CC Transactions'!A:A, ">=2025-09-01", 'CC Transactions'!A:A, "<=2025-09-30") -> 0 | H84: =SUMIFS('CC Transactions'!E:E, 'CC Transactions'!D:D, $A84, 'CC Transactions'!A:A, ">=2025-10-01", 'CC Transactions'!A:A, "<=2025-10-31") -> 0 | I84: =SUMIFS('CC Transactions'!E:E, 'CC Transactions'!D:D, $A84, 'CC Transactions'!A:A, ">=2025-11-01", 'CC Transactions'!A:A, "<=2025-11-30") -> 406.71 | J84: =SUMIFS('CC Transactions'!E:E, 'CC Transactions'!D:D, $A84, 'CC Transactions'!A:A, ">=2025-12-01", 'CC Transactions'!A:A, "<=2025-12-31") -> 0 | K84: =SUMIFS('CC Transactions'!E:E, 'CC Transactions'!D:D, $A84, 'CC Transactions'!A:A, ">=2026-01-01", 'CC Transactions'!A:A, "<=2026-01-31") -> 0 | L84: =SUMIFS('CC Transactions'!E:E, 'CC Transactions'!D:D, $A84, 'CC Transactions'!A:A, ">=2026-02-01", 'CC Transactions'!A:A, "<=2026-02-28") -> 588.82 | M84: =SUMIFS('CC Transactions'!E:E, 'CC Transactions'!D:D, $A84, 'CC Transactions'!A:A, ">=2026-03-01", 'CC Transactions'!A:A, "<=2026-03-31") -> 513.21 | N84: =SUMIFS('CC Transactions'!E:E, 'CC Transactions'!D:D, $A84, 'CC Transactions'!A:A, ">=2026-04-01", 'CC Transactions'!A:A, "<=2026-04-30") -> 0 | O84: =SUM(B84:N84) -> 2686.38
A85: CC MONTHLY TOTAL | B85: =SUM(B71:B84) -> 5508.6 | C85: =SUM(C71:C84) -> 34632.43 | D85: =SUM(D71:D84) -> 7824.89 | E85: =SUM(E71:E84) -> 17271.06 | F85: =SUM(F71:F84) -> 8719.41 | G85: =SUM(G71:G84) -> 33920.91 | H85: =SUM(H71:H84) -> 51242.45 | I85: =SUM(I71:I84) -> 18120.02 | ... O85: =SUM(O71:O84) -> 243627.4

Sheet CC Transactions
A1: Date | B1: Merchant | C1: CC Category | D1: Auto Narration | E1: DR (Rs.) | F1: CR (Rs.) | G1: Statement Period
A2: ── Apr-2025 ──
A3: 45748 | B3: Yesvegetable | C3: DepartmentalStore | D3: CC - Shopping | E3: 140 | G3: Mar-2025 to Apr-2025
A4: 45749 | B4: Shivaramaks | C4: Restaurants | D4: CC - Restaurants | E4: 50 | G4: Mar-2025 to Apr-2025
A5: 45749 | B5: Mrsmanjulab | C5: Grocery | D5: CC - Groceries | E5: 25 | G5: Mar-2025 to Apr-2025
A6: 45749 | B6: Familyfruits | C6: Grocery | D6: CC - Groceries | E6: 45 | G6: Mar-2025 to Apr-2025
A7: 45751 | B7: Bykemaniasol | C7: Recreation | D7: CC - Recreation | E7: 1149 | G7: Mar-2025 to Apr-2025
A8: 45751 | B8: Bykemaniasol | C8: Automotive | D8: CC - Automotive | E8: 1500 | G8: Mar-2025 to Apr-2025
A9: 45751 | B9: Themysoreca | C9: Restaurants | D9: CC - Restaurants | E9: 221 | G9: Mar-2025 to Apr-2025
A10: 45751 | B10: Shivaramu | C10: Restaurants | D10: CC - Restaurants | E10: 110 | G10: Mar-2025 to Apr-2025
A11: 45751 | B11: Ashokkumar | C11: OtherMerchants | D11: CC - Other | E11: 40 | G11: Mar-2025 to Apr-2025
A12: 45752 | B12: Oamindustrie | C12: Restaurants | D12: CC - Restaurants | E12: 15 | G12: Mar-2025 to Apr-2025
A13: 45752 | B13: Oamindustrie | C13: Restaurants | D13: CC - Restaurants | E13: 309.5 | G13: Mar-2025 to Apr-2025
A14: 45753 | B14: Tsashoka | C14: Grocery | D14: CC - Groceries | E14: 15 | G14: Mar-2025 to Apr-2025
... A40: 45776 | B40: Sajidnabiyar | C40: Hardware | D40: CC - Shopping | E40: 74 | G40: Apr-2025 to May-2025
A42: ── May-2025 ──
A43: 45778 | B43: Sheetalfood | C43: Grocery | D43: CC - Groceries | E43: 7 | G43: Apr-2025 to May-2025
A44: 45778 | B44: Celebrationc | C44: OtherMerchants | D44: CC - Other | E44: 40 | G44: Apr-2025 to May-2025
A45: 45781 | B45: Gitesanjays | C45: Grocery | D45: CC - Groceries | E45: 150 | G45: Apr-2025 to May-2025
A46: 45784 | B46: Gitesanjays | C46: Grocery | D46: CC - Groceries | E46: 150 | G46: Apr-2025 to May-2025
A47: 45785 | B47: Manishhemant | C47: Grocery | D47: CC - Groceries | E47: 63 | G47: Apr-2025 to May-2025
A48: 45786 | B48: Manishhemant | C48: Grocery | D48: CC - Groceries | E48: 55 | G48: Apr-2025 to May-2025
A49: 45786 | B49: Vishwanathni | C49: Grocery | D49: CC - Groceries | E49: 180 | G49: Apr-2025 to May-2025
A50: 45786 | B50: Gitesanjays | C50: Grocery | D50: CC - Groceries | E50: 83 | G50: Apr-2025 to May-2025
A51: 45787 | B51: Medplusashok | C51: Medical | D51: CC - Healthcare | E51: 205 | G51: Apr-2025 to May-2025
A52: 45787 | B52: Hldhatraka | C52: Fuel | D52: CC - Fuel | E52: 310 | G52: Apr-2025 to May-2025
A53: 45789 | B53: Omsuparshop | C53: Grocery | D53: CC - Groceries | E53: 30 | G53: Apr-2025 to May-2025
A54: 45792 | B54: Sagarsweets | C54: OtherMerchants | D54: CC - Other | E54: 50 | G54: Apr-2025 to May-2025
... A86: 45808 | B86: Chandrag | C86: Restaurants | D86: CC - Restaurants | E86: 255 | G86: May-2025 to Jun-2025
A88: ── Jun-2025 ──
A89: 45809 | B89: Meharali | C89: Automotive | D89: CC - Automotive | E89: 107 | G89: May-2025 to Jun-2025
A90: 45810 | B90: Rkfarmfresh | C90: Grocery | D90: CC - Groceries | E90: 45 | G90: May-2025 to Jun-2025
A91: 45811 | B91: Mcdonalds | C91: Restaurants | D91: CC - Restaurants | E91: 130 | G91: May-2025 to Jun-2025
A92: 45811 | B92: Bykemaniasol | C92: Automotive | D92: CC - Automotive | E92: 1500 | G92: May-2025 to Jun-2025
A93: 45811 | B93: Bhavanahome | C93: Hardware | D93: CC - Shopping | E93: 330 | G93: May-2025 to Jun-2025
A94: 45811 | B94: District | C94: Entertainment | D94: CC - Entertainment | E94: 242.84 | G94: May-2025 to Jun-2025
A95: 45811 | B95: Airtel | C95: Telecom | D95: CC - Telecom | E95: 195 | G95: May-2025 to Jun-2025
A96: 45811 | B96: Bykemaniasol | C96: Automotive | D96: CC - Automotive | E96: 1191 | G96: May-2025 to Jun-2025
A97: 45812 | B97: Itplpsqbike | C97: Automotive | D97: CC - Automotive | E97: 50 | G97: May-2025 to Jun-2025
A98: 45813 | B98: C108Kabeng | C98: Restaurants | D98: CC - Restaurants | E98: 180 | G98: May-2025 to Jun-2025
A99: 45813 | B99: Kvgayathri | C99: Grocery | D99: CC - Groceries | E99: 35 | G99: May-2025 to Jun-2025
A100: 45816 | B100: Nmahadeva | C100: Grocery | D100: CC - Groceries | E100: 390 | G100: May-2025 to Jun-2025
... A133: 45838 | B133: TRAVELCLUBLOUNGE 356 | C133: Entertainment | D133: CC - Entertainment | E133: 2 | G133: Jun-2025 to Jul-2025
A135: ── Jul-2025 ──
A136: 45839 | B136: Rkfarmfresh | C136: Grocery | D136: CC - Groceries | E136: 35 | G136: Jun-2025 to Jul-2025
A137: 45839 | B137: Vodafoneidea | C137: Telecom | D137: CC - Telecom | E137: 145 | G137: Jun-2025 to Jul-2025
A138: 45839 | B138: Sudarshan | C138: Grocery | D138: CC - Groceries | E138: 40 | G138: Jun-2025 to Jul-2025
A139: 45841 | B139: Sudarshan | C139: Grocery | D139: CC - Groceries | E139: 100 | G139: Jun-2025 to Jul-2025
A140: 45841 | B140: Rkfarmfresh | C140: Grocery | D140: CC - Groceries | E140: 90 | G140: Jun-2025 to Jul-2025
A141: 45842 | B141: Oamindustrie | C141: Restaurants | D141: CC - Restaurants | E141: 65 | G141: Jun-2025 to Jul-2025
A142: 45842 | B142: Oamindustrie | C142: Restaurants | D142: CC - Restaurants | E142: 84 | G142: Jun-2025 to Jul-2025
A143: 45843 | B143: Vinaykumars | C143: Services | D143: CC - Services | E143: 50 | G143: Jun-2025 to Jul-2025
A144: 45843 | B144: Matsfuelpar | C144: Fuel | D144: CC - Fuel | E144: 65 | G144: Jun-2025 to Jul-2025
A145: 45844 | B145: Rkfarmfresh | C145: Grocery | D145: CC - Groceries | E145: 35 | G145: Jun-2025 to Jul-2025
A146: 45844 | B146: Avenuesuperm | C146: Grocery | D146: CC - Groceries | E146: 5333.32 | G146: Jun-2025 to Jul-2025
A147: 45844 | B147: Kapoorscafe | C147: Restaurants | D147: CC - Restaurants | E147: 704 | G147: Jun-2025 to Jul-2025
... A193: 45869 | B193: Nandini | C193: Grocery | D193: CC - Groceries | E193: 24 | G193: Jul-2025 to Aug-2025
A195: ── Aug-2025 ──
A196: 45871 | B196: Yesvegetable | C196: DepartmentalStore | D196: CC - Shopping | E196: 16 | G196: Jul-2025 to Aug-2025
